Workbook

Sheet Total
A1: Месяц+Год | B1: Тип клиента | C1: Площадка | D1: Формат | E1: Гео | F1: Модель закупки | G1: Единица закупки | H1: Кол-во единиц закупки | I1: Стоимость единицы закупки, руб. с НДС | J1: АК% | K1: АК, руб. (абс.) | L1: НДС, руб. (абс.) | M1: Тотал бюджет, руб. без НДС и АК | N1: Тотал бюджет, руб. без НДС и с учетом АК | O1: Тотал бюджет руб. с учетом НДС и АК | P1: Кол-во показов | Q1: CTR, % | R1: Кол-во кликов | S1: СРС, руб. с НДС | T1: Кол-во оформленных заказов | U1: Стоимость оформл. заказа, руб. с НДС | V1: CR (конверсия из клика в заказ), % | W1: Оформленный доход, руб. с НДС | X1: ДРР от оформл. дохода, % | Y1: ROAS офомл. (Доход/Бюджет) | Z1: Средний чек по оформл. доходу, с НДС | AA1: Кол-во отгруженных заказов | AB1: Стоимость отгр. заказа, руб. с НДС | AC1: CR 2 (конверсия из оформленного в отгруженный заказ), % | AD1: Выручка (отгруженный доход), руб. с НДС | AE1: ДРР от выручки, % | AF1: ROAS отгр. (Выручка/Бюджет) | AG1: Средний чек по выручке, с НДС | AH1: Кол-во клиентов | AI1: Частота заказа | AJ1: Кол-во абсолютно новых клиентов (ранее не заказывали) | AK1: Кол-во вернувшихся клиентов (не заказывали более 12 мес) | AL1: Кол-во новых клиентов (абсолютно новые + вернувшиеся) | AM1: Доля новых клиентов, % | AN1: САС, руб. | AO1: СРА: кол-во активных веб мастеров | AP1: СРА: % аппрува | AR1: СR из клика в клиента, %
A2: 2026-2027 | B2: В2В | H2: =IFERROR(Periods!H2+Periods!H118+Periods!H234+Periods!H350+Periods!H466+Periods!H582+Periods!H698+Periods!H814+Periods!H930+Periods!H1046+Periods!H1162+Periods!H1278, "-") -> 0 | I2: =(M2*1.22)/R2 -> #DIV/0! | J2: =IFERROR(N2/M2-1,"-") -> - | K2: =I2*J2*H2 -> #DIV/0! | L2: =IFERROR(Periods!L2+Periods!L118+Periods!L234+Periods!L350+Periods!L466+Periods!L582+Periods!L698+Periods!L814+Periods!L930+Periods!L1046+Periods!L1162+Periods!L1278, "-") -> 0 | M2: =IFERROR(Periods!M2+Periods!M118+Periods!M234+Periods!M350+Periods!M466+Periods!M582+Periods!M698+Periods!M814+Periods!M930+Periods!M1046+Periods!M1162+Periods!M1278, "-") -> 0 | N2: =IFERROR(Periods!N2+Periods!N118+Periods!N234+Periods!N350+Periods!N466+Periods!N582+Periods!N698+Periods!N814+Periods!N930+Periods!N1046+Periods!N1162+Periods!N1278, "-") -> 0 | O2: =IFERROR(Periods!O2+Periods!O118+Periods!O234+Periods!O350+Periods!O466+Periods!O582+Periods!O698+Periods!O814+Periods!O930+Periods!O1046+Periods!O1162+Periods!O1278, "-") -> 0 | P2: =IFERROR(Periods!P2+Periods!P118+Periods!P234+Periods!P350+Periods!P466+Periods!P582+Periods!P698+Periods!P814+Periods!P930+Periods!P1046+Periods!P1162+Periods!P1278, "-") -> 0 | Q2: =IFERROR(R2/P2, "-") -> - | R2: =IFERROR(Periods!R2+Periods!R118+Periods!R234+Periods!R350+Periods!R466+Periods!R582+Periods!R698+Periods!R814+Periods!R930+Periods!R1046+Periods!R1162+Periods!R1278, "-") -> 0 | S2: =(ROUNDDOWN(O2/R2,0)) -> #DIV/0! | T2: =IFERROR(Periods!T2+Periods!T118+Periods!T234+Periods!T350+Periods!T466+Periods!T582+Periods!T698+Periods!T814+Periods!T930+Periods!T1046+Periods!T1162+Periods!T1278, "-") -> 0 | U2: =IFERROR(O2/T2, "-") -> - | V2: =IFERROR(R2/T2, "-") -> - | W2: =IFERROR(Periods!W2+Periods!W118+Periods!W234+Periods!W350+Periods!W466+Periods!W582+Periods!W698+Periods!W814+Periods!W930+Periods!W1046+Periods!W1162+Periods!W1278, "-") -> 0 | X2: =O2/W2 -> #DIV/0! | Y2: =W2/O2 -> #DIV/0! | Z2: =W2/T2 -> #DIV/0! | AA2: =IFERROR(Periods!AA2+Periods!AA118+Periods!AA234+Periods!AA350+Periods!AA466+Periods!AA582+Periods!AA698+Periods!AA814+Periods!AA930+Periods!AA1046+Periods!AA1162+Periods!AA1278, "-") -> 0 | AB2: =O2/AA2 -> #DIV/0! | AC2: =IFERROR(AA2/T2, "-") -> - | AD2: =IFERROR(Periods!AD2+Periods!AD118+Periods!AD234+Periods!AD350+Periods!AD466+Periods!AD582+Periods!AD698+Periods!AD814+Periods!AD930+Periods!AD1046+Periods!AD1162+Periods!AD1278, "-") -> 0 | AE2: =O2/AD2 -> #DIV/0! | AF2: =AD2/O2 -> #DIV/0! | AG2: =AD2/AA2 -> #DIV/0! | AH2: =IFERROR(Periods!AH2+Periods!AH118+Periods!AH234+Periods!AH350+Periods!AH466+Periods!AH582+Periods!AH698+Periods!AH814+Periods!AH930+Periods!AH1046+Periods!AH1162+Periods!AH1278, "-") -> 0 | AI2: =IFERROR(AVERAGE(Periods!AI2,Periods!AI118,Periods!AI234,Periods!AI350,Periods!AI466,Periods!AI582,Periods!AI698,Periods!AI814,Periods!AI930,Periods!AI1046,Periods!AI1162,Periods!AI1278), "-") -> - | AJ2: =IFERROR(Periods!AJ2+Periods!AJ118+Periods!AJ234+Periods!AJ350+Periods!AJ466+Periods!AJ582+Periods!AJ698+Periods!AJ814+Periods!AJ930+Periods!AJ1046+Periods!AJ1162+Periods!AJ1278, "-") -> 0 | AK2: =IFERROR(Periods!AK2+Periods!AK118+Periods!AK234+Periods!AK350+Periods!AK466+Periods!AK582+Periods!AK698+Periods!AK814+Periods!AK930+Periods!AK1046+Periods!AK1162+Periods!AK1278, "-") -> 0 | AL2: =AJ2+AK2 -> 0 | AM2: =AL2/AH2 -> #DIV/0! | AN2: =O2/AL2 -> #DIV/0! | AO2: =IFERROR(Periods!AO2+Periods!AO118+Periods!AO234+Periods!AO350+Periods!AO466+Periods!AO582+Periods!AO698+Periods!AO814+Periods!AO930+Periods!AO1046+Periods!AO1162+Periods!AO1278, "-") -> 0 | AP2: =IFERROR(AVERAGE(Periods!AP2,Periods!AP118,Periods!AP234,Periods!AP350,Periods!AP466,Periods!AP582,Periods!AP698,Periods!AP814,Periods!AP930,Periods!AP1046,Periods!AP1162,Periods!AP1278), "-") -> - | AR2: =IFERROR(AH2/R2, "-") -> -
A3: 2026-2027 | B3: В2В | H3: =IFERROR(Periods!H3+Periods!H119+Periods!H235+Periods!H351+Periods!H467+Periods!H583+Periods!H699+Periods!H815+Periods!H931+Periods!H1047+Periods!H1163+Periods!H1279, "-") -> 0 | I3: =(M3*1.22)/R3 -> #DIV/0! | J3: =IFERROR(N3/M3-1,"-") -> - | K3: =I3*J3*H3 -> #DIV/0! | L3: =IFERROR(Periods!L3+Periods!L119+Periods!L235+Periods!L351+Periods!L467+Periods!L583+Periods!L699+Periods!L815+Periods!L931+Periods!L1047+Periods!L1163+Periods!L1279, "-") -> 0 | M3: =IFERROR(Periods!M3+Periods!M119+Periods!M235+Periods!M351+Periods!M467+Periods!M583+Periods!M699+Periods!M815+Periods!M931+Periods!M1047+Periods!M1163+Periods!M1279, "-") -> 0 | N3: =IFERROR(Periods!N3+Periods!N119+Periods!N235+Periods!N351+Periods!N467+Periods!N583+Periods!N699+Periods!N815+Periods!N931+Periods!N1047+Periods!N1163+Periods!N1279, "-") -> 0 | O3: =IFERROR(Periods!O3+Periods!O119+Periods!O235+Periods!O351+Periods!O467+Periods!O583+Periods!O699+Periods!O815+Periods!O931+Periods!O1047+Periods!O1163+Periods!O1279, "-") -> 0 | P3: =IFERROR(Periods!P3+Periods!P119+Periods!P235+Periods!P351+Periods!P467+Periods!P583+Periods!P699+Periods!P815+Periods!P931+Periods!P1047+Periods!P1163+Periods!P1279, "-") -> 0 | Q3: =IFERROR(R3/P3, "-") -> - | R3: =IFERROR(Periods!R3+Periods!R119+Periods!R235+Periods!R351+Periods!R467+Periods!R583+Periods!R699+Periods!R815+Periods!R931+Periods!R1047+Periods!R1163+Periods!R1279, "-") -> 0 | S3: =(ROUNDDOWN(O3/R3,0)) -> #DIV/0! | T3: =IFERROR(Periods!T3+Periods!T119+Periods!T235+Periods!T351+Periods!T467+Periods!T583+Periods!T699+Periods!T815+Periods!T931+Periods!T1047+Periods!T1163+Periods!T1279, "-") -> 0 | U3: =IFERROR(O3/T3, "-") -> - | V3: =IFERROR(R3/T3, "-") -> - | W3: =IFERROR(Periods!W3+Periods!W119+Periods!W235+Periods!W351+Periods!W467+Periods!W583+Periods!W699+Periods!W815+Periods!W931+Periods!W1047+Periods!W1163+Periods!W1279, "-") -> 0 | X3: =O3/W3 -> #DIV/0! | Y3: =W3/O3 -> #DIV/0! | Z3: =W3/T3 -> #DIV/0! | AA3: =IFERROR(Periods!AA3+Periods!AA119+Periods!AA235+Periods!AA351+Periods!AA467+Periods!AA583+Periods!AA699+Periods!AA815+Periods!AA931+Periods!AA1047+Periods!AA1163+Periods!AA1279, "-") -> 0 | AB3: =O3/AA3 -> #DIV/0! | AC3: =IFERROR(AA3/T3, "-") -> - | AD3: =IFERROR(Periods!AD3+Periods!AD119+Periods!AD235+Periods!AD351+Periods!AD467+Periods!AD583+Periods!AD699+Periods!AD815+Periods!AD931+Periods!AD1047+Periods!AD1163+Periods!AD1279, "-") -> 0 | AE3: =O3/AD3 -> #DIV/0! | AF3: =AD3/O3 -> #DIV/0! | AG3: =AD3/AA3 -> #DIV/0! | AH3: =IFERROR(Periods!AH3+Periods!AH119+Periods!AH235+Periods!AH351+Periods!AH467+Periods!AH583+Periods!AH699+Periods!AH815+Periods!AH931+Periods!AH1047+Periods!AH1163+Periods!AH1279, "-") -> 0 | AI3: =IFERROR(AVERAGE(Periods!AI3,Periods!AI119,Periods!AI235,Periods!AI351,Periods!AI467,Periods!AI583,Periods!AI699,Periods!AI815,Periods!AI931,Periods!AI1047,Periods!AI1163,Periods!AI1279), "-") -> - | AJ3: =IFERROR(Periods!AJ3+Periods!AJ119+Periods!AJ235+Periods!AJ351+Periods!AJ467+Periods!AJ583+Periods!AJ699+Periods!AJ815+Periods!AJ931+Periods!AJ1047+Periods!AJ1163+Periods!AJ1279, "-") -> 0 | AK3: =IFERROR(Periods!AK3+Periods!AK119+Periods!AK235+Periods!AK351+Periods!AK467+Periods!AK583+Periods!AK699+Periods!AK815+Periods!AK931+Periods!AK1047+Periods!AK1163+Periods!AK1279, "-") -> 0 | AL3: =AJ3+AK3 -> 0 | AM3: =AL3/AH3 -> #DIV/0! | AN3: =O3/AL3 -> #DIV/0! | AO3: =IFERROR(Periods!AO3+Periods!AO119+Periods!AO235+Periods!AO351+Periods!AO467+Periods!AO583+Periods!AO699+Periods!AO815+Periods!AO931+Periods!AO1047+Periods!AO1163+Periods!AO1279, "-") -> 0 | AP3: =IFERROR(AVERAGE(Periods!AP3,Periods!AP119,Periods!AP235,Periods!AP351,Periods!AP467,Periods!AP583,Periods!AP699,Periods!AP815,Periods!AP931,Periods!AP1047,Periods!AP1163,Periods!AP1279), "-") -> - | AR3: =IFERROR(AH3/R3, "-") -> -
A4: 2026-2027 | B4: В2В | H4: =IFERROR(Periods!H4+Periods!H120+Periods!H236+Periods!H352+Periods!H468+Periods!H584+Periods!H700+Periods!H816+Periods!H932+Periods!H1048+Periods!H1164+Periods!H1280, "-") -> 0 | I4: =(M4*1.22)/R4 -> #DIV/0! | J4: =IFERROR(N4/M4-1,"-") -> - | K4: =I4*J4*H4 -> #DIV/0! | L4: =IFERROR(Periods!L4+Periods!L120+Periods!L236+Periods!L352+Periods!L468+Periods!L584+Periods!L700+Periods!L816+Periods!L932+Periods!L1048+Periods!L1164+Periods!L1280, "-") -> 0 | M4: =IFERROR(Periods!M4+Periods!M120+Periods!M236+Periods!M352+Periods!M468+Periods!M584+Periods!M700+Periods!M816+Periods!M932+Periods!M1048+Periods!M1164+Periods!M1280, "-") -> 0 | N4: =IFERROR(Periods!N4+Periods!N120+Periods!N236+Periods!N352+Periods!N468+Periods!N584+Periods!N700+Periods!N816+Periods!N932+Periods!N1048+Periods!N1164+Periods!N1280, "-") -> 0 | O4: =IFERROR(Periods!O4+Periods!O120+Periods!O236+Periods!O352+Periods!O468+Periods!O584+Periods!O700+Periods!O816+Periods!O932+Periods!O1048+Periods!O1164+Periods!O1280, "-") -> 0 | P4: =IFERROR(Periods!P4+Periods!P120+Periods!P236+Periods!P352+Periods!P468+Periods!P584+Periods!P700+Periods!P816+Periods!P932+Periods!P1048+Periods!P1164+Periods!P1280, "-") -> 0 | Q4: =IFERROR(R4/P4, "-") -> - | R4: =IFERROR(Periods!R4+Periods!R120+Periods!R236+Periods!R352+Periods!R468+Periods!R584+Periods!R700+Periods!R816+Periods!R932+Periods!R1048+Periods!R1164+Periods!R1280, "-") -> 0 | S4: =(ROUNDDOWN(O4/R4,0)) -> #DIV/0! | T4: =IFERROR(Periods!T4+Periods!T120+Periods!T236+Periods!T352+Periods!T468+Periods!T584+Periods!T700+Periods!T816+Periods!T932+Periods!T1048+Periods!T1164+Periods!T1280, "-") -> 0 | U4: =IFERROR(O4/T4, "-") -> - | V4: =IFERROR(R4/T4, "-") -> - | W4: =IFERROR(Periods!W4+Periods!W120+Periods!W236+Periods!W352+Periods!W468+Periods!W584+Periods!W700+Periods!W816+Periods!W932+Periods!W1048+Periods!W1164+Periods!W1280, "-") -> 0 | X4: =O4/W4 -> #DIV/0! | Y4: =W4/O4 -> #DIV/0! | Z4: =W4/T4 -> #DIV/0! | AA4: =IFERROR(Periods!AA4+Periods!AA120+Periods!AA236+Periods!AA352+Periods!AA468+Periods!AA584+Periods!AA700+Periods!AA816+Periods!AA932+Periods!AA1048+Periods!AA1164+Periods!AA1280, "-") -> 0 | AB4: =O4/AA4 -> #DIV/0! | AC4: =IFERROR(AA4/T4, "-") -> - | AD4: =IFERROR(Periods!AD4+Periods!AD120+Periods!AD236+Periods!AD352+Periods!AD468+Periods!AD584+Periods!AD700+Periods!AD816+Periods!AD932+Periods!AD1048+Periods!AD1164+Periods!AD1280, "-") -> 0 | AE4: =O4/AD4 -> #DIV/0! | AF4: =AD4/O4 -> #DIV/0! | AG4: =AD4/AA4 -> #DIV/0! | AH4: =IFERROR(Periods!AH4+Periods!AH120+Periods!AH236+Periods!AH352+Periods!AH468+Periods!AH584+Periods!AH700+Periods!AH816+Periods!AH932+Periods!AH1048+Periods!AH1164+Periods!AH1280, "-") -> 0 | AI4: =IFERROR(AVERAGE(Periods!AI4,Periods!AI120,Periods!AI236,Periods!AI352,Periods!AI468,Periods!AI584,Periods!AI700,Periods!AI816,Periods!AI932,Periods!AI1048,Periods!AI1164,Periods!AI1280), "-") -> - | AJ4: =IFERROR(Periods!AJ4+Periods!AJ120+Periods!AJ236+Periods!AJ352+Periods!AJ468+Periods!AJ584+Periods!AJ700+Periods!AJ816+Periods!AJ932+Periods!AJ1048+Periods!AJ1164+Periods!AJ1280, "-") -> 0 | AK4: =IFERROR(Periods!AK4+Periods!AK120+Periods!AK236+Periods!AK352+Periods!AK468+Periods!AK584+Periods!AK700+Periods!AK816+Periods!AK932+Periods!AK1048+Periods!AK1164+Periods!AK1280, "-") -> 0 | AL4: =AJ4+AK4 -> 0 | AM4: =AL4/AH4 -> #DIV/0! | AN4: =O4/AL4 -> #DIV/0! | AO4: =IFERROR(Periods!AO4+Periods!AO120+Periods!AO236+Periods!AO352+Periods!AO468+Periods!AO584+Periods!AO700+Periods!AO816+Periods!AO932+Periods!AO1048+Periods!AO1164+Periods!AO1280, "-") -> 0 | AP4: =IFERROR(AVERAGE(Periods!AP4,Periods!AP120,Periods!AP236,Periods!AP352,Periods!AP468,Periods!AP584,Periods!AP700,Periods!AP816,Periods!AP932,Periods!AP1048,Periods!AP1164,Periods!AP1280), "-") -> - | AR4: =IFERROR(AH4/R4, "-") -> -
A5: 2026-2027 | B5: В2В | H5: =IFERROR(Periods!H5+Periods!H121+Periods!H237+Periods!H353+Periods!H469+Periods!H585+Periods!H701+Periods!H817+Periods!H933+Periods!H1049+Periods!H1165+Periods!H1281, "-") -> 0 | I5: =(M5*1.22)/R5 -> #DIV/0! | J5: =IFERROR(N5/M5-1,"-") -> - | K5: =I5*J5*H5 -> #DIV/0! | L5: =IFERROR(Periods!L5+Periods!L121+Periods!L237+Periods!L353+Periods!L469+Periods!L585+Periods!L701+Periods!L817+Periods!L933+Periods!L1049+Periods!L1165+Periods!L1281, "-") -> 0 | M5: =IFERROR(Periods!M5+Periods!M121+Periods!M237+Periods!M353+Periods!M469+Periods!M585+Periods!M701+Periods!M817+Periods!M933+Periods!M1049+Periods!M1165+Periods!M1281, "-") -> 0 | N5: =IFERROR(Periods!N5+Periods!N121+Periods!N237+Periods!N353+Periods!N469+Periods!N585+Periods!N701+Periods!N817+Periods!N933+Periods!N1049+Periods!N1165+Periods!N1281, "-") -> 0 | O5: =IFERROR(Periods!O5+Periods!O121+Periods!O237+Periods!O353+Periods!O469+Periods!O585+Periods!O701+Periods!O817+Periods!O933+Periods!O1049+Periods!O1165+Periods!O1281, "-") -> 0 | P5: =IFERROR(Periods!P5+Periods!P121+Periods!P237+Periods!P353+Periods!P469+Periods!P585+Periods!P701+Periods!P817+Periods!P933+Periods!P1049+Periods!P1165+Periods!P1281, "-") -> 0 | Q5: =IFERROR(R5/P5, "-") -> - | R5: =IFERROR(Periods!R5+Periods!R121+Periods!R237+Periods!R353+Periods!R469+Periods!R585+Periods!R701+Periods!R817+Periods!R933+Periods!R1049+Periods!R1165+Periods!R1281, "-") -> 0 | S5: =(ROUNDDOWN(O5/R5,0)) -> #DIV/0! | T5: =IFERROR(Periods!T5+Periods!T121+Periods!T237+Periods!T353+Periods!T469+Periods!T585+Periods!T701+Periods!T817+Periods!T933+Periods!T1049+Periods!T1165+Periods!T1281, "-") -> 0 | U5: =IFERROR(O5/T5, "-") -> - | V5: =IFERROR(R5/T5, "-") -> - | W5: =IFERROR(Periods!W5+Periods!W121+Periods!W237+Periods!W353+Periods!W469+Periods!W585+Periods!W701+Periods!W817+Periods!W933+Periods!W1049+Periods!W1165+Periods!W1281, "-") -> 0 | X5: =O5/W5 -> #DIV/0! | Y5: =W5/O5 -> #DIV/0! | Z5: =W5/T5 -> #DIV/0! | AA5: =IFERROR(Periods!AA5+Periods!AA121+Periods!AA237+Periods!AA353+Periods!AA469+Periods!AA585+Periods!AA701+Periods!AA817+Periods!AA933+Periods!AA1049+Periods!AA1165+Periods!AA1281, "-") -> 0 | AB5: =O5/AA5 -> #DIV/0! | AC5: =IFERROR(AA5/T5, "-") -> - | AD5: =IFERROR(Periods!AD5+Periods!AD121+Periods!AD237+Periods!AD353+Periods!AD469+Periods!AD585+Periods!AD701+Periods!AD817+Periods!AD933+Periods!AD1049+Periods!AD1165+Periods!AD1281, "-") -> 0 | AE5: =O5/AD5 -> #DIV/0! | AF5: =AD5/O5 -> #DIV/0! | AG5: =AD5/AA5 -> #DIV/0! | AH5: =IFERROR(Periods!AH5+Periods!AH121+Periods!AH237+Periods!AH353+Periods!AH469+Periods!AH585+Periods!AH701+Periods!AH817+Periods!AH933+Periods!AH1049+Periods!AH1165+Periods!AH1281, "-") -> 0 | AI5: =IFERROR(AVERAGE(Periods!AI5,Periods!AI121,Periods!AI237,Periods!AI353,Periods!AI469,Periods!AI585,Periods!AI701,Periods!AI817,Periods!AI933,Periods!AI1049,Periods!AI1165,Periods!AI1281), "-") -> - | AJ5: =IFERROR(Periods!AJ5+Periods!AJ121+Periods!AJ237+Periods!AJ353+Periods!AJ469+Periods!AJ585+Periods!AJ701+Periods!AJ817+Periods!AJ933+Periods!AJ1049+Periods!AJ1165+Periods!AJ1281, "-") -> 0 | AK5: =IFERROR(Periods!AK5+Periods!AK121+Periods!AK237+Periods!AK353+Periods!AK469+Periods!AK585+Periods!AK701+Periods!AK817+Periods!AK933+Periods!AK1049+Periods!AK1165+Periods!AK1281, "-") -> 0 | AL5: =AJ5+AK5 -> 0 | AM5: =AL5/AH5 -> #DIV/0! | AN5: =O5/AL5 -> #DIV/0! | AO5: =IFERROR(Periods!AO5+Periods!AO121+Periods!AO237+Periods!AO353+Periods!AO469+Periods!AO585+Periods!AO701+Periods!AO817+Periods!AO933+Periods!AO1049+Periods!AO1165+Periods!AO1281, "-") -> 0 | AP5: =IFERROR(AVERAGE(Periods!AP5,Periods!AP121,Periods!AP237,Periods!AP353,Periods!AP469,Periods!AP585,Periods!AP701,Periods!AP817,Periods!AP933,Periods!AP1049,Periods!AP1165,Periods!AP1281), "-") -> - | AR5: =IFERROR(AH5/R5, "-") -> -
A6: 2026-2027 | B6: В2В | H6: =IFERROR(Periods!H6+Periods!H122+Periods!H238+Periods!H354+Periods!H470+Periods!H586+Periods!H702+Periods!H818+Periods!H934+Periods!H1050+Periods!H1166+Periods!H1282, "-") -> 0 | I6: =(M6*1.22)/R6 -> #DIV/0! | J6: =IFERROR(N6/M6-1,"-") -> - | K6: =I6*J6*H6 -> #DIV/0! | L6: =IFERROR(Periods!L6+Periods!L122+Periods!L238+Periods!L354+Periods!L470+Periods!L586+Periods!L702+Periods!L818+Periods!L934+Periods!L1050+Periods!L1166+Periods!L1282, "-") -> 0 | M6: =IFERROR(Periods!M6+Periods!M122+Periods!M238+Periods!M354+Periods!M470+Periods!M586+Periods!M702+Periods!M818+Periods!M934+Periods!M1050+Periods!M1166+Periods!M1282, "-") -> 0 | N6: =IFERROR(Periods!N6+Periods!N122+Periods!N238+Periods!N354+Periods!N470+Periods!N586+Periods!N702+Periods!N818+Periods!N934+Periods!N1050+Periods!N1166+Periods!N1282, "-") -> 0 | O6: =IFERROR(Periods!O6+Periods!O122+Periods!O238+Periods!O354+Periods!O470+Periods!O586+Periods!O702+Periods!O818+Periods!O934+Periods!O1050+Periods!O1166+Periods!O1282, "-") -> 0 | P6: =IFERROR(Periods!P6+Periods!P122+Periods!P238+Periods!P354+Periods!P470+Periods!P586+Periods!P702+Periods!P818+Periods!P934+Periods!P1050+Periods!P1166+Periods!P1282, "-") -> 0 | Q6: =IFERROR(R6/P6, "-") -> - | R6: =IFERROR(Periods!R6+Periods!R122+Periods!R238+Periods!R354+Periods!R470+Periods!R586+Periods!R702+Periods!R818+Periods!R934+Periods!R1050+Periods!R1166+Periods!R1282, "-") -> 0 | S6: =(ROUNDDOWN(O6/R6,0)) -> #DIV/0! | T6: =IFERROR(Periods!T6+Periods!T122+Periods!T238+Periods!T354+Periods!T470+Periods!T586+Periods!T702+Periods!T818+Periods!T934+Periods!T1050+Periods!T1166+Periods!T1282, "-") -> 0 | U6: =IFERROR(O6/T6, "-") -> - | V6: =IFERROR(R6/T6, "-") -> - | W6: =IFERROR(Periods!W6+Periods!W122+Periods!W238+Periods!W354+Periods!W470+Periods!W586+Periods!W702+Periods!W818+Periods!W934+Periods!W1050+Periods!W1166+Periods!W1282, "-") -> 0 | X6: =O6/W6 -> #DIV/0! | Y6: =W6/O6 -> #DIV/0! | Z6: =W6/T6 -> #DIV/0! | AA6: =IFERROR(Periods!AA6+Periods!AA122+Periods!AA238+Periods!AA354+Periods!AA470+Periods!AA586+Periods!AA702+Periods!AA818+Periods!AA934+Periods!AA1050+Periods!AA1166+Periods!AA1282, "-") -> 0 | AB6: =O6/AA6 -> #DIV/0! | AC6: =IFERROR(AA6/T6, "-") -> - | AD6: =IFERROR(Periods!AD6+Periods!AD122+Periods!AD238+Periods!AD354+Periods!AD470+Periods!AD586+Periods!AD702+Periods!AD818+Periods!AD934+Periods!AD1050+Periods!AD1166+Periods!AD1282, "-") -> 0 | AE6: =O6/AD6 -> #DIV/0! | AF6: =AD6/O6 -> #DIV/0! | AG6: =AD6/AA6 -> #DIV/0! | AH6: =IFERROR(Periods!AH6+Periods!AH122+Periods!AH238+Periods!AH354+Periods!AH470+Periods!AH586+Periods!AH702+Periods!AH818+Periods!AH934+Periods!AH1050+Periods!AH1166+Periods!AH1282, "-") -> 0 | AI6: =IFERROR(AVERAGE(Periods!AI6,Periods!AI122,Periods!AI238,Periods!AI354,Periods!AI470,Periods!AI586,Periods!AI702,Periods!AI818,Periods!AI934,Periods!AI1050,Periods!AI1166,Periods!AI1282), "-") -> - | AJ6: =IFERROR(Periods!AJ6+Periods!AJ122+Periods!AJ238+Periods!AJ354+Periods!AJ470+Periods!AJ586+Periods!AJ702+Periods!AJ818+Periods!AJ934+Periods!AJ1050+Periods!AJ1166+Periods!AJ1282, "-") -> 0 | AK6: =IFERROR(Periods!AK6+Periods!AK122+Periods!AK238+Periods!AK354+Periods!AK470+Periods!AK586+Periods!AK702+Periods!AK818+Periods!AK934+Periods!AK1050+Periods!AK1166+Periods!AK1282, "-") -> 0 | AL6: =AJ6+AK6 -> 0 | AM6: =AL6/AH6 -> #DIV/0! | AN6: =O6/AL6 -> #DIV/0! | AO6: =IFERROR(Periods!AO6+Periods!AO122+Periods!AO238+Periods!AO354+Periods!AO470+Periods!AO586+Periods!AO702+Periods!AO818+Periods!AO934+Periods!AO1050+Periods!AO1166+Periods!AO1282, "-") -> 0 | AP6: =IFERROR(AVERAGE(Periods!AP6,Periods!AP122,Periods!AP238,Periods!AP354,Periods!AP470,Periods!AP586,Periods!AP702,Periods!AP818,Periods!AP934,Periods!AP1050,Periods!AP1166,Periods!AP1282), "-") -> - | AR6: =IFERROR(AH6/R6, "-") -> -
A7: 2026-2027 | B7: В2В | H7: =IFERROR(Periods!H7+Periods!H123+Periods!H239+Periods!H355+Periods!H471+Periods!H587+Periods!H703+Periods!H819+Periods!H935+Periods!H1051+Periods!H1167+Periods!H1283, "-") -> 0 | I7: =(M7*1.22)/R7 -> #DIV/0! | J7: =IFERROR(N7/M7-1,"-") -> - | K7: =I7*J7*H7 -> #DIV/0! | L7: =IFERROR(Periods!L7+Periods!L123+Periods!L239+Periods!L355+Periods!L471+Periods!L587+Periods!L703+Periods!L819+Periods!L935+Periods!L1051+Periods!L1167+Periods!L1283, "-") -> 0 | M7: =IFERROR(Periods!M7+Periods!M123+Periods!M239+Periods!M355+Periods!M471+Periods!M587+Periods!M703+Periods!M819+Periods!M935+Periods!M1051+Periods!M1167+Periods!M1283, "-") -> 0 | N7: =IFERROR(Periods!N7+Periods!N123+Periods!N239+Periods!N355+Periods!N471+Periods!N587+Periods!N703+Periods!N819+Periods!N935+Periods!N1051+Periods!N1167+Periods!N1283, "-") -> 0 | O7: =IFERROR(Periods!O7+Periods!O123+Periods!O239+Periods!O355+Periods!O471+Periods!O587+Periods!O703+Periods!O819+Periods!O935+Periods!O1051+Periods!O1167+Periods!O1283, "-") -> 0 | P7: =IFERROR(Periods!P7+Periods!P123+Periods!P239+Periods!P355+Periods!P471+Periods!P587+Periods!P703+Periods!P819+Periods!P935+Periods!P1051+Periods!P1167+Periods!P1283, "-") -> 0 | Q7: =IFERROR(R7/P7, "-") -> - | R7: =IFERROR(Periods!R7+Periods!R123+Periods!R239+Periods!R355+Periods!R471+Periods!R587+Periods!R703+Periods!R819+Periods!R935+Periods!R1051+Periods!R1167+Periods!R1283, "-") -> 0 | S7: =(ROUNDDOWN(O7/R7,0)) -> #DIV/0! | T7: =IFERROR(Periods!T7+Periods!T123+Periods!T239+Periods!T355+Periods!T471+Periods!T587+Periods!T703+Periods!T819+Periods!T935+Periods!T1051+Periods!T1167+Periods!T1283, "-") -> 0 | U7: =IFERROR(O7/T7, "-") -> - | V7: =IFERROR(R7/T7, "-") -> - | W7: =IFERROR(Periods!W7+Periods!W123+Periods!W239+Periods!W355+Periods!W471+Periods!W587+Periods!W703+Periods!W819+Periods!W935+Periods!W1051+Periods!W1167+Periods!W1283, "-") -> 0 | X7: =O7/W7 -> #DIV/0! | Y7: =W7/O7 -> #DIV/0! | Z7: =W7/T7 -> #DIV/0! | AA7: =IFERROR(Periods!AA7+Periods!AA123+Periods!AA239+Periods!AA355+Periods!AA471+Periods!AA587+Periods!AA703+Periods!AA819+Periods!AA935+Periods!AA1051+Periods!AA1167+Periods!AA1283, "-") -> 0 | AB7: =O7/AA7 -> #DIV/0! | AC7: =IFERROR(AA7/T7, "-") -> - | AD7: =IFERROR(Periods!AD7+Periods!AD123+Periods!AD239+Periods!AD355+Periods!AD471+Periods!AD587+Periods!AD703+Periods!AD819+Periods!AD935+Periods!AD1051+Periods!AD1167+Periods!AD1283, "-") -> 0 | AE7: =O7/AD7 -> #DIV/0! | AF7: =AD7/O7 -> #DIV/0! | AG7: =AD7/AA7 -> #DIV/0! | AH7: =IFERROR(Periods!AH7+Periods!AH123+Periods!AH239+Periods!AH355+Periods!AH471+Periods!AH587+Periods!AH703+Periods!AH819+Periods!AH935+Periods!AH1051+Periods!AH1167+Periods!AH1283, "-") -> 0 | AI7: =IFERROR(AVERAGE(Periods!AI7,Periods!AI123,Periods!AI239,Periods!AI355,Periods!AI471,Periods!AI587,Periods!AI703,Periods!AI819,Periods!AI935,Periods!AI1051,Periods!AI1167,Periods!AI1283), "-") -> - | AJ7: =IFERROR(Periods!AJ7+Periods!AJ123+Periods!AJ239+Periods!AJ355+Periods!AJ471+Periods!AJ587+Periods!AJ703+Periods!AJ819+Periods!AJ935+Periods!AJ1051+Periods!AJ1167+Periods!AJ1283, "-") -> 0 | AK7: =IFERROR(Periods!AK7+Periods!AK123+Periods!AK239+Periods!AK355+Periods!AK471+Periods!AK587+Periods!AK703+Periods!AK819+Periods!AK935+Periods!AK1051+Periods!AK1167+Periods!AK1283, "-") -> 0 | AL7: =AJ7+AK7 -> 0 | AM7: =AL7/AH7 -> #DIV/0! | AN7: =O7/AL7 -> #DIV/0! | AO7: =IFERROR(Periods!AO7+Periods!AO123+Periods!AO239+Periods!AO355+Periods!AO471+Periods!AO587+Periods!AO703+Periods!AO819+Periods!AO935+Periods!AO1051+Periods!AO1167+Periods!AO1283, "-") -> 0 | AP7: =IFERROR(AVERAGE(Periods!AP7,Periods!AP123,Periods!AP239,Periods!AP355,Periods!AP471,Periods!AP587,Periods!AP703,Periods!AP819,Periods!AP935,Periods!AP1051,Periods!AP1167,Periods!AP1283), "-") -> - | AR7: =IFERROR(AH7/R7, "-") -> -
A8: 2026-2027 | B8: В2В | H8: =IFERROR(Periods!H8+Periods!H124+Periods!H240+Periods!H356+Periods!H472+Periods!H588+Periods!H704+Periods!H820+Periods!H936+Periods!H1052+Periods!H1168+Periods!H1284, "-") -> 0 | I8: =(M8*1.22)/R8 -> #DIV/0! | J8: =IFERROR(N8/M8-1,"-") -> - | K8: =I8*J8*H8 -> #DIV/0! | L8: =IFERROR(Periods!L8+Periods!L124+Periods!L240+Periods!L356+Periods!L472+Periods!L588+Periods!L704+Periods!L820+Periods!L936+Periods!L1052+Periods!L1168+Periods!L1284, "-") -> 0 | M8: =IFERROR(Periods!M8+Periods!M124+Periods!M240+Periods!M356+Periods!M472+Periods!M588+Periods!M704+Periods!M820+Periods!M936+Periods!M1052+Periods!M1168+Periods!M1284, "-") -> 0 | N8: =IFERROR(Periods!N8+Periods!N124+Periods!N240+Periods!N356+Periods!N472+Periods!N588+Periods!N704+Periods!N820+Periods!N936+Periods!N1052+Periods!N1168+Periods!N1284, "-") -> 0 | O8: =IFERROR(Periods!O8+Periods!O124+Periods!O240+Periods!O356+Periods!O472+Periods!O588+Periods!O704+Periods!O820+Periods!O936+Periods!O1052+Periods!O1168+Periods!O1284, "-") -> 0 | P8: =IFERROR(Periods!P8+Periods!P124+Periods!P240+Periods!P356+Periods!P472+Periods!P588+Periods!P704+Periods!P820+Periods!P936+Periods!P1052+Periods!P1168+Periods!P1284, "-") -> 0 | Q8: =IFERROR(R8/P8, "-") -> - | R8: =IFERROR(Periods!R8+Periods!R124+Periods!R240+Periods!R356+Periods!R472+Periods!R588+Periods!R704+Periods!R820+Periods!R936+Periods!R1052+Periods!R1168+Periods!R1284, "-") -> 0 | S8: =(ROUNDDOWN(O8/R8,0)) -> #DIV/0! | T8: =IFERROR(Periods!T8+Periods!T124+Periods!T240+Periods!T356+Periods!T472+Periods!T588+Periods!T704+Periods!T820+Periods!T936+Periods!T1052+Periods!T1168+Periods!T1284, "-") -> 0 | U8: =IFERROR(O8/T8, "-") -> - | V8: =IFERROR(R8/T8, "-") -> - | W8: =IFERROR(Periods!W8+Periods!W124+Periods!W240+Periods!W356+Periods!W472+Periods!W588+Periods!W704+Periods!W820+Periods!W936+Periods!W1052+Periods!W1168+Periods!W1284, "-") -> 0 | X8: =O8/W8 -> #DIV/0! | Y8: =W8/O8 -> #DIV/0! | Z8: =W8/T8 -> #DIV/0! | AA8: =IFERROR(Periods!AA8+Periods!AA124+Periods!AA240+Periods!AA356+Periods!AA472+Periods!AA588+Periods!AA704+Periods!AA820+Periods!AA936+Periods!AA1052+Periods!AA1168+Periods!AA1284, "-") -> 0 | AB8: =O8/AA8 -> #DIV/0! | AC8: =IFERROR(AA8/T8, "-") -> - | AD8: =IFERROR(Periods!AD8+Periods!AD124+Periods!AD240+Periods!AD356+Periods!AD472+Periods!AD588+Periods!AD704+Periods!AD820+Periods!AD936+Periods!AD1052+Periods!AD1168+Periods!AD1284, "-") -> 0 | AE8: =O8/AD8 -> #DIV/0! | AF8: =AD8/O8 -> #DIV/0! | AG8: =AD8/AA8 -> #DIV/0! | AH8: =IFERROR(Periods!AH8+Periods!AH124+Periods!AH240+Periods!AH356+Periods!AH472+Periods!AH588+Periods!AH704+Periods!AH820+Periods!AH936+Periods!AH1052+Periods!AH1168+Periods!AH1284, "-") -> 0 | AI8: =IFERROR(AVERAGE(Periods!AI8,Periods!AI124,Periods!AI240,Periods!AI356,Periods!AI472,Periods!AI588,Periods!AI704,Periods!AI820,Periods!AI936,Periods!AI1052,Periods!AI1168,Periods!AI1284), "-") -> - | AJ8: =IFERROR(Periods!AJ8+Periods!AJ124+Periods!AJ240+Periods!AJ356+Periods!AJ472+Periods!AJ588+Periods!AJ704+Periods!AJ820+Periods!AJ936+Periods!AJ1052+Periods!AJ1168+Periods!AJ1284, "-") -> 0 | AK8: =IFERROR(Periods!AK8+Periods!AK124+Periods!AK240+Periods!AK356+Periods!AK472+Periods!AK588+Periods!AK704+Periods!AK820+Periods!AK936+Periods!AK1052+Periods!AK1168+Periods!AK1284, "-") -> 0 | AL8: =AJ8+AK8 -> 0 | AM8: =AL8/AH8 -> #DIV/0! | AN8: =O8/AL8 -> #DIV/0! | AO8: =IFERROR(Periods!AO8+Periods!AO124+Periods!AO240+Periods!AO356+Periods!AO472+Periods!AO588+Periods!AO704+Periods!AO820+Periods!AO936+Periods!AO1052+Periods!AO1168+Periods!AO1284, "-") -> 0 | AP8: =IFERROR(AVERAGE(Periods!AP8,Periods!AP124,Periods!AP240,Periods!AP356,Periods!AP472,Periods!AP588,Periods!AP704,Periods!AP820,Periods!AP936,Periods!AP1052,Periods!AP1168,Periods!AP1284), "-") -> - | AR8: =IFERROR(AH8/R8, "-") -> -
A9: 2026-2027 | B9: В2В | H9: =IFERROR(Periods!H9+Periods!H125+Periods!H241+Periods!H357+Periods!H473+Periods!H589+Periods!H705+Periods!H821+Periods!H937+Periods!H1053+Periods!H1169+Periods!H1285, "-") -> 0 | I9: =(M9*1.22)/R9 -> #DIV/0! | J9: =IFERROR(N9/M9-1,"-") -> - | K9: =I9*J9*H9 -> #DIV/0! | L9: =IFERROR(Periods!L9+Periods!L125+Periods!L241+Periods!L357+Periods!L473+Periods!L589+Periods!L705+Periods!L821+Periods!L937+Periods!L1053+Periods!L1169+Periods!L1285, "-") -> 0 | M9: =IFERROR(Periods!M9+Periods!M125+Periods!M241+Periods!M357+Periods!M473+Periods!M589+Periods!M705+Periods!M821+Periods!M937+Periods!M1053+Periods!M1169+Periods!M1285, "-") -> 0 | N9: =IFERROR(Periods!N9+Periods!N125+Periods!N241+Periods!N357+Periods!N473+Periods!N589+Periods!N705+Periods!N821+Periods!N937+Periods!N1053+Periods!N1169+Periods!N1285, "-") -> 0 | O9: =IFERROR(Periods!O9+Periods!O125+Periods!O241+Periods!O357+Periods!O473+Periods!O589+Periods!O705+Periods!O821+Periods!O937+Periods!O1053+Periods!O1169+Periods!O1285, "-") -> 0 | P9: =IFERROR(Periods!P9+Periods!P125+Periods!P241+Periods!P357+Periods!P473+Periods!P589+Periods!P705+Periods!P821+Periods!P937+Periods!P1053+Periods!P1169+Periods!P1285, "-") -> 0 | Q9: =IFERROR(R9/P9, "-") -> - | R9: =IFERROR(Periods!R9+Periods!R125+Periods!R241+Periods!R357+Periods!R473+Periods!R589+Periods!R705+Periods!R821+Periods!R937+Periods!R1053+Periods!R1169+Periods!R1285, "-") -> 0 | S9: =(ROUNDDOWN(O9/R9,0)) -> #DIV/0! | T9: =IFERROR(Periods!T9+Periods!T125+Periods!T241+Periods!T357+Periods!T473+Periods!T589+Periods!T705+Periods!T821+Periods!T937+Periods!T1053+Periods!T1169+Periods!T1285, "-") -> 0 | U9: =IFERROR(O9/T9, "-") -> - | V9: =IFERROR(R9/T9, "-") -> - | W9: =IFERROR(Periods!W9+Periods!W125+Periods!W241+Periods!W357+Periods!W473+Periods!W589+Periods!W705+Periods!W821+Periods!W937+Periods!W1053+Periods!W1169+Periods!W1285, "-") -> 0 | X9: =O9/W9 -> #DIV/0! | Y9: =W9/O9 -> #DIV/0! | Z9: =W9/T9 -> #DIV/0! | AA9: =IFERROR(Periods!AA9+Periods!AA125+Periods!AA241+Periods!AA357+Periods!AA473+Periods!AA589+Periods!AA705+Periods!AA821+Periods!AA937+Periods!AA1053+Periods!AA1169+Periods!AA1285, "-") -> 0 | AB9: =O9/AA9 -> #DIV/0! | AC9: =IFERROR(AA9/T9, "-") -> - | AD9: =IFERROR(Periods!AD9+Periods!AD125+Periods!AD241+Periods!AD357+Periods!AD473+Periods!AD589+Periods!AD705+Periods!AD821+Periods!AD937+Periods!AD1053+Periods!AD1169+Periods!AD1285, "-") -> 0 | AE9: =O9/AD9 -> #DIV/0! | AF9: =AD9/O9 -> #DIV/0! | AG9: =AD9/AA9 -> #DIV/0! | AH9: =IFERROR(Periods!AH9+Periods!AH125+Periods!AH241+Periods!AH357+Periods!AH473+Periods!AH589+Periods!AH705+Periods!AH821+Periods!AH937+Periods!AH1053+Periods!AH1169+Periods!AH1285, "-") -> 0 | AI9: =IFERROR(AVERAGE(Periods!AI9,Periods!AI125,Periods!AI241,Periods!AI357,Periods!AI473,Periods!AI589,Periods!AI705,Periods!AI821,Periods!AI937,Periods!AI1053,Periods!AI1169,Periods!AI1285), "-") -> - | AJ9: =IFERROR(Periods!AJ9+Periods!AJ125+Periods!AJ241+Periods!AJ357+Periods!AJ473+Periods!AJ589+Periods!AJ705+Periods!AJ821+Periods!AJ937+Periods!AJ1053+Periods!AJ1169+Periods!AJ1285, "-") -> 0 | AK9: =IFERROR(Periods!AK9+Periods!AK125+Periods!AK241+Periods!AK357+Periods!AK473+Periods!AK589+Periods!AK705+Periods!AK821+Periods!AK937+Periods!AK1053+Periods!AK1169+Periods!AK1285, "-") -> 0 | AL9: =AJ9+AK9 -> 0 | AM9: =AL9/AH9 -> #DIV/0! | AN9: =O9/AL9 -> #DIV/0! | AO9: =IFERROR(Periods!AO9+Periods!AO125+Periods!AO241+Periods!AO357+Periods!AO473+Periods!AO589+Periods!AO705+Periods!AO821+Periods!AO937+Periods!AO1053+Periods!AO1169+Periods!AO1285, "-") -> 0 | AP9: =IFERROR(AVERAGE(Periods!AP9,Periods!AP125,Periods!AP241,Periods!AP357,Periods!AP473,Periods!AP589,Periods!AP705,Periods!AP821,Periods!AP937,Periods!AP1053,Periods!AP1169,Periods!AP1285), "-") -> - | AR9: =IFERROR(AH9/R9, "-") -> -
A10: 2026-2027 | B10: В2В | H10: =IFERROR(Periods!H10+Periods!H126+Periods!H242+Periods!H358+Periods!H474+Periods!H590+Periods!H706+Periods!H822+Periods!H938+Periods!H1054+Periods!H1170+Periods!H1286, "-") -> 0 | I10: =(M10*1.22)/R10 -> #DIV/0! | J10: =IFERROR(N10/M10-1,"-") -> - | K10: =I10*J10*H10 -> #DIV/0! | L10: =IFERROR(Periods!L10+Periods!L126+Periods!L242+Periods!L358+Periods!L474+Periods!L590+Periods!L706+Periods!L822+Periods!L938+Periods!L1054+Periods!L1170+Periods!L1286, "-") -> 0 | M10: =IFERROR(Periods!M10+Periods!M126+Periods!M242+Periods!M358+Periods!M474+Periods!M590+Periods!M706+Periods!M822+Periods!M938+Periods!M1054+Periods!M1170+Periods!M1286, "-") -> 0 | N10: =IFERROR(Periods!N10+Periods!N126+Periods!N242+Periods!N358+Periods!N474+Periods!N590+Periods!N706+Periods!N822+Periods!N938+Periods!N1054+Periods!N1170+Periods!N1286, "-") -> 0 | O10: =IFERROR(Periods!O10+Periods!O126+Periods!O242+Periods!O358+Periods!O474+Periods!O590+Periods!O706+Periods!O822+Periods!O938+Periods!O1054+Periods!O1170+Periods!O1286, "-") -> 0 | P10: =IFERROR(Periods!P10+Periods!P126+Periods!P242+Periods!P358+Periods!P474+Periods!P590+Periods!P706+Periods!P822+Periods!P938+Periods!P1054+Periods!P1170+Periods!P1286, "-") -> 0 | Q10: =IFERROR(R10/P10, "-") -> - | R10: =IFERROR(Periods!R10+Periods!R126+Periods!R242+Periods!R358+Periods!R474+Periods!R590+Periods!R706+Periods!R822+Periods!R938+Periods!R1054+Periods!R1170+Periods!R1286, "-") -> 0 | S10: =(ROUNDDOWN(O10/R10,0)) -> #DIV/0! | T10: =IFERROR(Periods!T10+Periods!T126+Periods!T242+Periods!T358+Periods!T474+Periods!T590+Periods!T706+Periods!T822+Periods!T938+Periods!T1054+Periods!T1170+Periods!T1286, "-") -> 0 | U10: =IFERROR(O10/T10, "-") -> - | V10: =IFERROR(R10/T10, "-") -> - | W10: =IFERROR(Periods!W10+Periods!W126+Periods!W242+Periods!W358+Periods!W474+Periods!W590+Periods!W706+Periods!W822+Periods!W938+Periods!W1054+Periods!W1170+Periods!W1286, "-") -> 0 | X10: =O10/W10 -> #DIV/0! | Y10: =W10/O10 -> #DIV/0! | Z10: =W10/T10 -> #DIV/0! | AA10: =IFERROR(Periods!AA10+Periods!AA126+Periods!AA242+Periods!AA358+Periods!AA474+Periods!AA590+Periods!AA706+Periods!AA822+Periods!AA938+Periods!AA1054+Periods!AA1170+Periods!AA1286, "-") -> 0 | AB10: =O10/AA10 -> #DIV/0! | AC10: =IFERROR(AA10/T10, "-") -> - | AD10: =IFERROR(Periods!AD10+Periods!AD126+Periods!AD242+Periods!AD358+Periods!AD474+Periods!AD590+Periods!AD706+Periods!AD822+Periods!AD938+Periods!AD1054+Periods!AD1170+Periods!AD1286, "-") -> 0 | AE10: =O10/AD10 -> #DIV/0! | AF10: =AD10/O10 -> #DIV/0! | AG10: =AD10/AA10 -> #DIV/0! | AH10: =IFERROR(Periods!AH10+Periods!AH126+Periods!AH242+Periods!AH358+Periods!AH474+Periods!AH590+Periods!AH706+Periods!AH822+Periods!AH938+Periods!AH1054+Periods!AH1170+Periods!AH1286, "-") -> 0 | AI10: =IFERROR(AVERAGE(Periods!AI10,Periods!AI126,Periods!AI242,Periods!AI358,Periods!AI474,Periods!AI590,Periods!AI706,Periods!AI822,Periods!AI938,Periods!AI1054,Periods!AI1170,Periods!AI1286), "-") -> - | AJ10: =IFERROR(Periods!AJ10+Periods!AJ126+Periods!AJ242+Periods!AJ358+Periods!AJ474+Periods!AJ590+Periods!AJ706+Periods!AJ822+Periods!AJ938+Periods!AJ1054+Periods!AJ1170+Periods!AJ1286, "-") -> 0 | AK10: =IFERROR(Periods!AK10+Periods!AK126+Periods!AK242+Periods!AK358+Periods!AK474+Periods!AK590+Periods!AK706+Periods!AK822+Periods!AK938+Periods!AK1054+Periods!AK1170+Periods!AK1286, "-") -> 0 | AL10: =AJ10+AK10 -> 0 | AM10: =AL10/AH10 -> #DIV/0! | AN10: =O10/AL10 -> #DIV/0! | AO10: =IFERROR(Periods!AO10+Periods!AO126+Periods!AO242+Periods!AO358+Periods!AO474+Periods!AO590+Periods!AO706+Periods!AO822+Periods!AO938+Periods!AO1054+Periods!AO1170+Periods!AO1286, "-") -> 0 | AP10: =IFERROR(AVERAGE(Periods!AP10,Periods!AP126,Periods!AP242,Periods!AP358,Periods!AP474,Periods!AP590,Periods!AP706,Periods!AP822,Periods!AP938,Periods!AP1054,Periods!AP1170,Periods!AP1286), "-") -> - | AR10: =IFERROR(AH10/R10, "-") -> -
A11: 2026-2027 | B11: В2В | H11: =IFERROR(Periods!H11+Periods!H127+Periods!H243+Periods!H359+Periods!H475+Periods!H591+Periods!H707+Periods!H823+Periods!H939+Periods!H1055+Periods!H1171+Periods!H1287, "-") -> 0 | I11: =(M11*1.22)/R11 -> #DIV/0! | J11: =IFERROR(N11/M11-1,"-") -> - | K11: =I11*J11*H11 -> #DIV/0! | L11: =IFERROR(Periods!L11+Periods!L127+Periods!L243+Periods!L359+Periods!L475+Periods!L591+Periods!L707+Periods!L823+Periods!L939+Periods!L1055+Periods!L1171+Periods!L1287, "-") -> 0 | M11: =IFERROR(Periods!M11+Periods!M127+Periods!M243+Periods!M359+Periods!M475+Periods!M591+Periods!M707+Periods!M823+Periods!M939+Periods!M1055+Periods!M1171+Periods!M1287, "-") -> 0 | N11: =IFERROR(Periods!N11+Periods!N127+Periods!N243+Periods!N359+Periods!N475+Periods!N591+Periods!N707+Periods!N823+Periods!N939+Periods!N1055+Periods!N1171+Periods!N1287, "-") -> 0 | O11: =IFERROR(Periods!O11+Periods!O127+Periods!O243+Periods!O359+Periods!O475+Periods!O591+Periods!O707+Periods!O823+Periods!O939+Periods!O1055+Periods!O1171+Periods!O1287, "-") -> 0 | P11: =IFERROR(Periods!P11+Periods!P127+Periods!P243+Periods!P359+Periods!P475+Periods!P591+Periods!P707+Periods!P823+Periods!P939+Periods!P1055+Periods!P1171+Periods!P1287, "-") -> 0 | Q11: =IFERROR(R11/P11, "-") -> - | R11: =IFERROR(Periods!R11+Periods!R127+Periods!R243+Periods!R359+Periods!R475+Periods!R591+Periods!R707+Periods!R823+Periods!R939+Periods!R1055+Periods!R1171+Periods!R1287, "-") -> 0 | S11: =(ROUNDDOWN(O11/R11,0)) -> #DIV/0! | T11: =IFERROR(Periods!T11+Periods!T127+Periods!T243+Periods!T359+Periods!T475+Periods!T591+Periods!T707+Periods!T823+Periods!T939+Periods!T1055+Periods!T1171+Periods!T1287, "-") -> 0 | U11: =IFERROR(O11/T11, "-") -> - | V11: =IFERROR(R11/T11, "-") -> - | W11: =IFERROR(Periods!W11+Periods!W127+Periods!W243+Periods!W359+Periods!W475+Periods!W591+Periods!W707+Periods!W823+Periods!W939+Periods!W1055+Periods!W1171+Periods!W1287, "-") -> 0 | X11: =O11/W11 -> #DIV/0! | Y11: =W11/O11 -> #DIV/0! | Z11: =W11/T11 -> #DIV/0! | AA11: =IFERROR(Periods!AA11+Periods!AA127+Periods!AA243+Periods!AA359+Periods!AA475+Periods!AA591+Periods!AA707+Periods!AA823+Periods!AA939+Periods!AA1055+Periods!AA1171+Periods!AA1287, "-") -> 0 | AB11: =O11/AA11 -> #DIV/0! | AC11: =IFERROR(AA11/T11, "-") -> - | AD11: =IFERROR(Periods!AD11+Periods!AD127+Periods!AD243+Periods!AD359+Periods!AD475+Periods!AD591+Periods!AD707+Periods!AD823+Periods!AD939+Periods!AD1055+Periods!AD1171+Periods!AD1287, "-") -> 0 | AE11: =O11/AD11 -> #DIV/0! | AF11: =AD11/O11 -> #DIV/0! | AG11: =AD11/AA11 -> #DIV/0! | AH11: =IFERROR(Periods!AH11+Periods!AH127+Periods!AH243+Periods!AH359+Periods!AH475+Periods!AH591+Periods!AH707+Periods!AH823+Periods!AH939+Periods!AH1055+Periods!AH1171+Periods!AH1287, "-") -> 0 | AI11: =IFERROR(AVERAGE(Periods!AI11,Periods!AI127,Periods!AI243,Periods!AI359,Periods!AI475,Periods!AI591,Periods!AI707,Periods!AI823,Periods!AI939,Periods!AI1055,Periods!AI1171,Periods!AI1287), "-") -> - | AJ11: =IFERROR(Periods!AJ11+Periods!AJ127+Periods!AJ243+Periods!AJ359+Periods!AJ475+Periods!AJ591+Periods!AJ707+Periods!AJ823+Periods!AJ939+Periods!AJ1055+Periods!AJ1171+Periods!AJ1287, "-") -> 0 | AK11: =IFERROR(Periods!AK11+Periods!AK127+Periods!AK243+Periods!AK359+Periods!AK475+Periods!AK591+Periods!AK707+Periods!AK823+Periods!AK939+Periods!AK1055+Periods!AK1171+Periods!AK1287, "-") -> 0 | AL11: =AJ11+AK11 -> 0 | AM11: =AL11/AH11 -> #DIV/0! | AN11: =O11/AL11 -> #DIV/0! | AO11: =IFERROR(Periods!AO11+Periods!AO127+Periods!AO243+Periods!AO359+Periods!AO475+Periods!AO591+Periods!AO707+Periods!AO823+Periods!AO939+Periods!AO1055+Periods!AO1171+Periods!AO1287, "-") -> 0 | AP11: =IFERROR(AVERAGE(Periods!AP11,Periods!AP127,Periods!AP243,Periods!AP359,Periods!AP475,Periods!AP591,Periods!AP707,Periods!AP823,Periods!AP939,Periods!AP1055,Periods!AP1171,Periods!AP1287), "-") -> - | AR11: =IFERROR(AH11/R11, "-") -> -
A12: 2026-2027 | B12: В2В | H12: =IFERROR(Periods!H12+Periods!H128+Periods!H244+Periods!H360+Periods!H476+Periods!H592+Periods!H708+Periods!H824+Periods!H940+Periods!H1056+Periods!H1172+Periods!H1288, "-") -> 0 | I12: =(M12*1.22)/R12 -> #DIV/0! | J12: =IFERROR(N12/M12-1,"-") -> - | K12: =I12*J12*H12 -> #DIV/0! | L12: =IFERROR(Periods!L12+Periods!L128+Periods!L244+Periods!L360+Periods!L476+Periods!L592+Periods!L708+Periods!L824+Periods!L940+Periods!L1056+Periods!L1172+Periods!L1288, "-") -> 0 | M12: =IFERROR(Periods!M12+Periods!M128+Periods!M244+Periods!M360+Periods!M476+Periods!M592+Periods!M708+Periods!M824+Periods!M940+Periods!M1056+Periods!M1172+Periods!M1288, "-") -> 0 | N12: =IFERROR(Periods!N12+Periods!N128+Periods!N244+Periods!N360+Periods!N476+Periods!N592+Periods!N708+Periods!N824+Periods!N940+Periods!N1056+Periods!N1172+Periods!N1288, "-") -> 0 | O12: =IFERROR(Periods!O12+Periods!O128+Periods!O244+Periods!O360+Periods!O476+Periods!O592+Periods!O708+Periods!O824+Periods!O940+Periods!O1056+Periods!O1172+Periods!O1288, "-") -> 0 | P12: =IFERROR(Periods!P12+Periods!P128+Periods!P244+Periods!P360+Periods!P476+Periods!P592+Periods!P708+Periods!P824+Periods!P940+Periods!P1056+Periods!P1172+Periods!P1288, "-") -> 0 | Q12: =IFERROR(R12/P12, "-") -> - | R12: =IFERROR(Periods!R12+Periods!R128+Periods!R244+Periods!R360+Periods!R476+Periods!R592+Periods!R708+Periods!R824+Periods!R940+Periods!R1056+Periods!R1172+Periods!R1288, "-") -> 0 | S12: =(ROUNDDOWN(O12/R12,0)) -> #DIV/0! | T12: =IFERROR(Periods!T12+Periods!T128+Periods!T244+Periods!T360+Periods!T476+Periods!T592+Periods!T708+Periods!T824+Periods!T940+Periods!T1056+Periods!T1172+Periods!T1288, "-") -> 0 | U12: =IFERROR(O12/T12, "-") -> - | V12: =IFERROR(R12/T12, "-") -> - | W12: =IFERROR(Periods!W12+Periods!W128+Periods!W244+Periods!W360+Periods!W476+Periods!W592+Periods!W708+Periods!W824+Periods!W940+Periods!W1056+Periods!W1172+Periods!W1288, "-") -> 0 | X12: =O12/W12 -> #DIV/0! | Y12: =W12/O12 -> #DIV/0! | Z12: =W12/T12 -> #DIV/0! | AA12: =IFERROR(Periods!AA12+Periods!AA128+Periods!AA244+Periods!AA360+Periods!AA476+Periods!AA592+Periods!AA708+Periods!AA824+Periods!AA940+Periods!AA1056+Periods!AA1172+Periods!AA1288, "-") -> 0 | AB12: =O12/AA12 -> #DIV/0! | AC12: =IFERROR(AA12/T12, "-") -> - | AD12: =IFERROR(Periods!AD12+Periods!AD128+Periods!AD244+Periods!AD360+Periods!AD476+Periods!AD592+Periods!AD708+Periods!AD824+Periods!AD940+Periods!AD1056+Periods!AD1172+Periods!AD1288, "-") -> 0 | AE12: =O12/AD12 -> #DIV/0! | AF12: =AD12/O12 -> #DIV/0! | AG12: =AD12/AA12 -> #DIV/0! | AH12: =IFERROR(Periods!AH12+Periods!AH128+Periods!AH244+Periods!AH360+Periods!AH476+Periods!AH592+Periods!AH708+Periods!AH824+Periods!AH940+Periods!AH1056+Periods!AH1172+Periods!AH1288, "-") -> 0 | AI12: =IFERROR(AVERAGE(Periods!AI12,Periods!AI128,Periods!AI244,Periods!AI360,Periods!AI476,Periods!AI592,Periods!AI708,Periods!AI824,Periods!AI940,Periods!AI1056,Periods!AI1172,Periods!AI1288), "-") -> - | AJ12: =IFERROR(Periods!AJ12+Periods!AJ128+Periods!AJ244+Periods!AJ360+Periods!AJ476+Periods!AJ592+Periods!AJ708+Periods!AJ824+Periods!AJ940+Periods!AJ1056+Periods!AJ1172+Periods!AJ1288, "-") -> 0 | AK12: =IFERROR(Periods!AK12+Periods!AK128+Periods!AK244+Periods!AK360+Periods!AK476+Periods!AK592+Periods!AK708+Periods!AK824+Periods!AK940+Periods!AK1056+Periods!AK1172+Periods!AK1288, "-") -> 0 | AL12: =AJ12+AK12 -> 0 | AM12: =AL12/AH12 -> #DIV/0! | AN12: =O12/AL12 -> #DIV/0! | AO12: =IFERROR(Periods!AO12+Periods!AO128+Periods!AO244+Periods!AO360+Periods!AO476+Periods!AO592+Periods!AO708+Periods!AO824+Periods!AO940+Periods!AO1056+Periods!AO1172+Periods!AO1288, "-") -> 0 | AP12: =IFERROR(AVERAGE(Periods!AP12,Periods!AP128,Periods!AP244,Periods!AP360,Periods!AP476,Periods!AP592,Periods!AP708,Periods!AP824,Periods!AP940,Periods!AP1056,Periods!AP1172,Periods!AP1288), "-") -> - | AR12: =IFERROR(AH12/R12, "-") -> -
A13: 2026-2027 | B13: В2В | H13: =IFERROR(Periods!H13+Periods!H129+Periods!H245+Periods!H361+Periods!H477+Periods!H593+Periods!H709+Periods!H825+Periods!H941+Periods!H1057+Periods!H1173+Periods!H1289, "-") -> 0 | I13: =(M13*1.22)/R13 -> #DIV/0! | J13: =IFERROR(N13/M13-1,"-") -> - | K13: =I13*J13*H13 -> #DIV/0! | L13: =IFERROR(Periods!L13+Periods!L129+Periods!L245+Periods!L361+Periods!L477+Periods!L593+Periods!L709+Periods!L825+Periods!L941+Periods!L1057+Periods!L1173+Periods!L1289, "-") -> 0 | M13: =IFERROR(Periods!M13+Periods!M129+Periods!M245+Periods!M361+Periods!M477+Periods!M593+Periods!M709+Periods!M825+Periods!M941+Periods!M1057+Periods!M1173+Periods!M1289, "-") -> 0 | N13: =IFERROR(Periods!N13+Periods!N129+Periods!N245+Periods!N361+Periods!N477+Periods!N593+Periods!N709+Periods!N825+Periods!N941+Periods!N1057+Periods!N1173+Periods!N1289, "-") -> 0 | O13: =IFERROR(Periods!O13+Periods!O129+Periods!O245+Periods!O361+Periods!O477+Periods!O593+Periods!O709+Periods!O825+Periods!O941+Periods!O1057+Periods!O1173+Periods!O1289, "-") -> 0 | P13: =IFERROR(Periods!P13+Periods!P129+Periods!P245+Periods!P361+Periods!P477+Periods!P593+Periods!P709+Periods!P825+Periods!P941+Periods!P1057+Periods!P1173+Periods!P1289, "-") -> 0 | Q13: =IFERROR(R13/P13, "-") -> - | R13: =IFERROR(Periods!R13+Periods!R129+Periods!R245+Periods!R361+Periods!R477+Periods!R593+Periods!R709+Periods!R825+Periods!R941+Periods!R1057+Periods!R1173+Periods!R1289, "-") -> 0 | S13: =(ROUNDDOWN(O13/R13,0)) -> #DIV/0! | T13: =IFERROR(Periods!T13+Periods!T129+Periods!T245+Periods!T361+Periods!T477+Periods!T593+Periods!T709+Periods!T825+Periods!T941+Periods!T1057+Periods!T1173+Periods!T1289, "-") -> 0 | U13: =IFERROR(O13/T13, "-") -> - | V13: =IFERROR(R13/T13, "-") -> - | W13: =IFERROR(Periods!W13+Periods!W129+Periods!W245+Periods!W361+Periods!W477+Periods!W593+Periods!W709+Periods!W825+Periods!W941+Periods!W1057+Periods!W1173+Periods!W1289, "-") -> 0 | X13: =O13/W13 -> #DIV/0! | Y13: =W13/O13 -> #DIV/0! | Z13: =W13/T13 -> #DIV/0! | AA13: =IFERROR(Periods!AA13+Periods!AA129+Periods!AA245+Periods!AA361+Periods!AA477+Periods!AA593+Periods!AA709+Periods!AA825+Periods!AA941+Periods!AA1057+Periods!AA1173+Periods!AA1289, "-") -> 0 | AB13: =O13/AA13 -> #DIV/0! | AC13: =IFERROR(AA13/T13, "-") -> - | AD13: =IFERROR(Periods!AD13+Periods!AD129+Periods!AD245+Periods!AD361+Periods!AD477+Periods!AD593+Periods!AD709+Periods!AD825+Periods!AD941+Periods!AD1057+Periods!AD1173+Periods!AD1289, "-") -> 0 | AE13: =O13/AD13 -> #DIV/0! | AF13: =AD13/O13 -> #DIV/0! | AG13: =AD13/AA13 -> #DIV/0! | AH13: =IFERROR(Periods!AH13+Periods!AH129+Periods!AH245+Periods!AH361+Periods!AH477+Periods!AH593+Periods!AH709+Periods!AH825+Periods!AH941+Periods!AH1057+Periods!AH1173+Periods!AH1289, "-") -> 0 | AI13: =IFERROR(AVERAGE(Periods!AI13,Periods!AI129,Periods!AI245,Periods!AI361,Periods!AI477,Periods!AI593,Periods!AI709,Periods!AI825,Periods!AI941,Periods!AI1057,Periods!AI1173,Periods!AI1289), "-") -> - | AJ13: =IFERROR(Periods!AJ13+Periods!AJ129+Periods!AJ245+Periods!AJ361+Periods!AJ477+Periods!AJ593+Periods!AJ709+Periods!AJ825+Periods!AJ941+Periods!AJ1057+Periods!AJ1173+Periods!AJ1289, "-") -> 0 | AK13: =IFERROR(Periods!AK13+Periods!AK129+Periods!AK245+Periods!AK361+Periods!AK477+Periods!AK593+Periods!AK709+Periods!AK825+Periods!AK941+Periods!AK1057+Periods!AK1173+Periods!AK1289, "-") -> 0 | AL13: =AJ13+AK13 -> 0 | AM13: =AL13/AH13 -> #DIV/0! | AN13: =O13/AL13 -> #DIV/0! | AO13: =IFERROR(Periods!AO13+Periods!AO129+Periods!AO245+Periods!AO361+Periods!AO477+Periods!AO593+Periods!AO709+Periods!AO825+Periods!AO941+Periods!AO1057+Periods!AO1173+Periods!AO1289, "-") -> 0 | AP13: =IFERROR(AVERAGE(Periods!AP13,Periods!AP129,Periods!AP245,Periods!AP361,Periods!AP477,Periods!AP593,Periods!AP709,Periods!AP825,Periods!AP941,Periods!AP1057,Periods!AP1173,Periods!AP1289), "-") -> - | AR13: =IFERROR(AH13/R13, "-") -> -
... A56: 2026-2027 | B56: В2В | H56: =IFERROR(Periods!H56+Periods!H172+Periods!H288+Periods!H404+Periods!H520+Periods!H636+Periods!H752+Periods!H868+Periods!H984+Periods!H1100+Periods!H1216+Periods!H1332, "-") -> 0 | I56: =(M56*1.22)/R56 -> #DIV/0! | J56: =IFERROR(N56/M56-1,"-") -> - | K56: =I56*J56*H56 -> #DIV/0! | L56: =IFERROR(Periods!L56+Periods!L172+Periods!L288+Periods!L404+Periods!L520+Periods!L636+Periods!L752+Periods!L868+Periods!L984+Periods!L1100+Periods!L1216+Periods!L1332, "-") -> 0 | M56: =IFERROR(Periods!M56+Periods!M172+Periods!M288+Periods!M404+Periods!M520+Periods!M636+Periods!M752+Periods!M868+Periods!M984+Periods!M1100+Periods!M1216+Periods!M1332, "-") -> 0 | N56: =IFERROR(Periods!N56+Periods!N172+Periods!N288+Periods!N404+Periods!N520+Periods!N636+Periods!N752+Periods!N868+Periods!N984+Periods!N1100+Periods!N1216+Periods!N1332, "-") -> 0 | O56: =IFERROR(Periods!O56+Periods!O172+Periods!O288+Periods!O404+Periods!O520+Periods!O636+Periods!O752+Periods!O868+Periods!O984+Periods!O1100+Periods!O1216+Periods!O1332, "-") -> 0 | P56: =IFERROR(Periods!P56+Periods!P172+Periods!P288+Periods!P404+Periods!P520+Periods!P636+Periods!P752+Periods!P868+Periods!P984+Periods!P1100+Periods!P1216+Periods!P1332, "-") -> 0 | Q56: =IFERROR(R56/P56, "-") -> - | R56: =IFERROR(Periods!R56+Periods!R172+Periods!R288+Periods!R404+Periods!R520+Periods!R636+Periods!R752+Periods!R868+Periods!R984+Periods!R1100+Periods!R1216+Periods!R1332, "-") -> 0 | S56: =(ROUNDDOWN(O56/R56,0)) -> #DIV/0! | T56: =IFERROR(Periods!T56+Periods!T172+Periods!T288+Periods!T404+Periods!T520+Periods!T636+Periods!T752+Periods!T868+Periods!T984+Periods!T1100+Periods!T1216+Periods!T1332, "-") -> 0 | U56: =IFERROR(O56/T56, "-") -> - | V56: =IFERROR(R56/T56, "-") -> - | W56: =IFERROR(Periods!W56+Periods!W172+Periods!W288+Periods!W404+Periods!W520+Periods!W636+Periods!W752+Periods!W868+Periods!W984+Periods!W1100+Periods!W1216+Periods!W1332, "-") -> 0 | X56: =O56/W56 -> #DIV/0! | Y56: =W56/O56 -> #DIV/0! | Z56: =W56/T56 -> #DIV/0! | AA56: =IFERROR(Periods!AA56+Periods!AA172+Periods!AA288+Periods!AA404+Periods!AA520+Periods!AA636+Periods!AA752+Periods!AA868+Periods!AA984+Periods!AA1100+Periods!AA1216+Periods!AA1332, "-") -> 0 | AB56: =O56/AA56 -> #DIV/0! | AC56: =IFERROR(AA56/T56, "-") -> - | AD56: =IFERROR(Periods!AD56+Periods!AD172+Periods!AD288+Periods!AD404+Periods!AD520+Periods!AD636+Periods!AD752+Periods!AD868+Periods!AD984+Periods!AD1100+Periods!AD1216+Periods!AD1332, "-") -> 0 | AE56: =O56/AD56 -> #DIV/0! | AF56: =AD56/O56 -> #DIV/0! | AG56: =AD56/AA56 -> #DIV/0! | AH56: =IFERROR(Periods!AH56+Periods!AH172+Periods!AH288+Periods!AH404+Periods!AH520+Periods!AH636+Periods!AH752+Periods!AH868+Periods!AH984+Periods!AH1100+Periods!AH1216+Periods!AH1332, "-") -> 0 | AI56: =IFERROR(AVERAGE(Periods!AI56,Periods!AI172,Periods!AI288,Periods!AI404,Periods!AI520,Periods!AI636,Periods!AI752,Periods!AI868,Periods!AI984,Periods!AI1100,Periods!AI1216,Periods!AI1332), "-") -> - | AJ56: =IFERROR(Periods!AJ56+Periods!AJ172+Periods!AJ288+Periods!AJ404+Periods!AJ520+Periods!AJ636+Periods!AJ752+Periods!AJ868+Periods!AJ984+Periods!AJ1100+Periods!AJ1216+Periods!AJ1332, "-") -> 0 | AK56: =IFERROR(Periods!AK56+Periods!AK172+Periods!AK288+Periods!AK404+Periods!AK520+Periods!AK636+Periods!AK752+Periods!AK868+Periods!AK984+Periods!AK1100+Periods!AK1216+Periods!AK1332, "-") -> 0 | AL56: =AJ56+AK56 -> 0 | AM56: =AL56/AH56 -> #DIV/0! | AN56: =O56/AL56 -> #DIV/0! | AO56: =IFERROR(Periods!AO56+Periods!AO172+Periods!AO288+Periods!AO404+Periods!AO520+Periods!AO636+Periods!AO752+Periods!AO868+Periods!AO984+Periods!AO1100+Periods!AO1216+Periods!AO1332, "-") -> 0 | AP56: =IFERROR(AVERAGE(Periods!AP56,Periods!AP172,Periods!AP288,Periods!AP404,Periods!AP520,Periods!AP636,Periods!AP752,Periods!AP868,Periods!AP984,Periods!AP1100,Periods!AP1216,Periods!AP1332), "-") -> - | AR56: =IFERROR(AH56/R56, "-") -> -
A57: ИТОГО | B57: B2B | H57: =IFERROR(SUM(H2:H56),"-") -> 0 | I57: =IFERROR(SUM(I2:I56),"-") -> - | J57: =IFERROR(N57/M57-1,"-") -> - | K57: =IFERROR(N57-M57,"-") -> 0 | L57: =IFERROR(SUM(L2:L56),"-") -> 0 | M57: =IFERROR(SUM(M2:M56),"-") -> 0 | N57: =IFERROR(SUM(N2:N56),"-") -> 0 | O57: =IFERROR(SUM(O2:O56),"-") -> 0 | P57: =IFERROR(SUM(P2:P56),"-") -> 0 | Q57: =IFERROR(R57/P57, "-") -> - | R57: =IFERROR(SUM(R2:R56),"-") -> 0 | S57: =IFERROR(O57/R57, "-") -> - | T57: =IFERROR(SUM(T2:T56),"-") -> 0 | U57: =IFERROR(O57/T57, "-") -> - | V57: =IFERROR(R57/T57, "-") -> - | W57: =IFERROR(SUM(W2:W56),"-") -> 0 | X57: =IFERROR(O57/W57, "-") -> - | Y57: =IFERROR(W57/O57, "-") -> - | Z57: =IFERROR(W57/T57, "-") -> - | AA57: =IFERROR(SUM(AA2:AA56),"-") -> 0 | AB57: =IFERROR(O57/AA57, "-") -> - | AC57: =IFERROR(AA57/T57, "-") -> - | AD57: =IFERROR(SUM(AD2:AD56),"-") -> 0 | AE57: =IFERROR(O57/AD57, "-") -> - | AF57: =IFERROR(AD57/O57, "-") -> - | AG57: =IFERROR(AD57/AA57, "-") -> - | AH57: =IFERROR(SUM(AH2:AH56),"-") -> 0 | AI57: =IFERROR(ROUND(AVERAGE(AI2:AI56),0),"-") -> - | AJ57: =IFERROR(SUM(AJ2:AJ56),"-") -> 0 | AK57: =IFERROR(SUM(AK2:AK56),"-") -> 0 | AL57: =IFERROR(AK57+AJ57,"-") -> 0 | AM57: =IFERROR(AL57/AH57, "-") -> - | AN57: =IFERROR(O57/AL57, "-") -> - | AO57: =IFERROR(SUM(AO2:AO56),"-") -> 0 | AP57: =IFERROR(AVERAGE(AP2:AP56),"-") -> - | AR57: =IFERROR(AH57/R57, "-") -> -
A58: 2026-2027 | B58: B2C | H58: =IFERROR(Periods!H58+Periods!H174+Periods!H290+Periods!H406+Periods!H522+Periods!H638+Periods!H754+Periods!H870+Periods!H986+Periods!H1102+Periods!H1218+Periods!H1334, "-") -> 0 | I58: =(M58*1.22)/R58 -> #DIV/0! | J58: =IFERROR(N58/M58-1,"-") -> - | K58: =I58*J58*H58 -> #DIV/0! | L58: =IFERROR(Periods!L58+Periods!L174+Periods!L290+Periods!L406+Periods!L522+Periods!L638+Periods!L754+Periods!L870+Periods!L986+Periods!L1102+Periods!L1218+Periods!L1334, "-") -> 0 | M58: =IFERROR(Periods!M58+Periods!M174+Periods!M290+Periods!M406+Periods!M522+Periods!M638+Periods!M754+Periods!M870+Periods!M986+Periods!M1102+Periods!M1218+Periods!M1334, "-") -> 0 | N58: =IFERROR(Periods!N58+Periods!N174+Periods!N290+Periods!N406+Periods!N522+Periods!N638+Periods!N754+Periods!N870+Periods!N986+Periods!N1102+Periods!N1218+Periods!N1334, "-") -> 0 | O58: =IFERROR(Periods!O58+Periods!O174+Periods!O290+Periods!O406+Periods!O522+Periods!O638+Periods!O754+Periods!O870+Periods!O986+Periods!O1102+Periods!O1218+Periods!O1334, "-") -> 0 | P58: =IFERROR(Periods!P58+Periods!P174+Periods!P290+Periods!P406+Periods!P522+Periods!P638+Periods!P754+Periods!P870+Periods!P986+Periods!P1102+Periods!P1218+Periods!P1334, "-") -> 0 | Q58: =IFERROR(R58/P58, "-") -> - | R58: =IFERROR(Periods!R58+Periods!R174+Periods!R290+Periods!R406+Periods!R522+Periods!R638+Periods!R754+Periods!R870+Periods!R986+Periods!R1102+Periods!R1218+Periods!R1334, "-") -> 0 | S58: =(ROUNDDOWN(O58/R58,0)) -> #DIV/0! | T58: =IFERROR(Periods!T58+Periods!T174+Periods!T290+Periods!T406+Periods!T522+Periods!T638+Periods!T754+Periods!T870+Periods!T986+Periods!T1102+Periods!T1218+Periods!T1334, "-") -> 0 | U58: =IFERROR(O58/T58, "-") -> - | V58: =IFERROR(R58/T58, "-") -> - | W58: =IFERROR(Periods!W58+Periods!W174+Periods!W290+Periods!W406+Periods!W522+Periods!W638+Periods!W754+Periods!W870+Periods!W986+Periods!W1102+Periods!W1218+Periods!W1334, "-") -> 0 | X58: =O58/W58 -> #DIV/0! | Y58: =W58/O58 -> #DIV/0! | Z58: =W58/T58 -> #DIV/0! | AA58: =IFERROR(Periods!AA58+Periods!AA174+Periods!AA290+Periods!AA406+Periods!AA522+Periods!AA638+Periods!AA754+Periods!AA870+Periods!AA986+Periods!AA1102+Periods!AA1218+Periods!AA1334, "-") -> 0 | AB58: =O58/AA58 -> #DIV/0! | AC58: =IFERROR(AA58/T58, "-") -> - | AD58: =IFERROR(Periods!AD58+Periods!AD174+Periods!AD290+Periods!AD406+Periods!AD522+Periods!AD638+Periods!AD754+Periods!AD870+Periods!AD986+Periods!AD1102+Periods!AD1218+Periods!AD1334, "-") -> 0 | AE58: =O58/AD58 -> #DIV/0! | AF58: =AD58/O58 -> #DIV/0! | AG58: =AD58/AA58 -> #DIV/0! | AH58: =IFERROR(Periods!AH58+Periods!AH174+Periods!AH290+Periods!AH406+Periods!AH522+Periods!AH638+Periods!AH754+Periods!AH870+Periods!AH986+Periods!AH1102+Periods!AH1218+Periods!AH1334, "-") -> 0 | AI58: =IFERROR(AVERAGE(Periods!AI58,Periods!AI174,Periods!AI290,Periods!AI406,Periods!AI522,Periods!AI638,Periods!AI754,Periods!AI870,Periods!AI986,Periods!AI1102,Periods!AI1218,Periods!AI1334), "-") -> - | AJ58: =IFERROR(Periods!AJ58+Periods!AJ174+Periods!AJ290+Periods!AJ406+Periods!AJ522+Periods!AJ638+Periods!AJ754+Periods!AJ870+Periods!AJ986+Periods!AJ1102+Periods!AJ1218+Periods!AJ1334, "-") -> 0 | AK58: =IFERROR(Periods!AK58+Periods!AK174+Periods!AK290+Periods!AK406+Periods!AK522+Periods!AK638+Periods!AK754+Periods!AK870+Periods!AK986+Periods!AK1102+Periods!AK1218+Periods!AK1334, "-") -> 0 | AL58: =AJ58+AK58 -> 0 | AM58: =AL58/AH58 -> #DIV/0! | AN58: =O58/AL58 -> #DIV/0! | AO58: =IFERROR(Periods!AO58+Periods!AO174+Periods!AO290+Periods!AO406+Periods!AO522+Periods!AO638+Periods!AO754+Periods!AO870+Periods!AO986+Periods!AO1102+Periods!AO1218+Periods!AO1334, "-") -> 0 | AP58: =IFERROR(AVERAGE(Periods!AP58,Periods!AP174,Periods!AP290,Periods!AP406,Periods!AP522,Periods!AP638,Periods!AP754,Periods!AP870,Periods!AP986,Periods!AP1102,Periods!AP1218,Periods!AP1334), "-") -> - | AR58: =IFERROR(AH58/R58, "-") -> -
A59: 2026-2027 | B59: B2C | H59: =IFERROR(Periods!H59+Periods!H175+Periods!H291+Periods!H407+Periods!H523+Periods!H639+Periods!H755+Periods!H871+Periods!H987+Periods!H1103+Periods!H1219+Periods!H1335, "-") -> 0 | I59: =(M59*1.22)/R59 -> #DIV/0! | J59: =IFERROR(N59/M59-1,"-") -> - | K59: =I59*J59*H59 -> #DIV/0! | L59: =IFERROR(Periods!L59+Periods!L175+Periods!L291+Periods!L407+Periods!L523+Periods!L639+Periods!L755+Periods!L871+Periods!L987+Periods!L1103+Periods!L1219+Periods!L1335, "-") -> 0 | M59: =IFERROR(Periods!M59+Periods!M175+Periods!M291+Periods!M407+Periods!M523+Periods!M639+Periods!M755+Periods!M871+Periods!M987+Periods!M1103+Periods!M1219+Periods!M1335, "-") -> 0 | N59: =IFERROR(Periods!N59+Periods!N175+Periods!N291+Periods!N407+Periods!N523+Periods!N639+Periods!N755+Periods!N871+Periods!N987+Periods!N1103+Periods!N1219+Periods!N1335, "-") -> 0 | O59: =IFERROR(Periods!O59+Periods!O175+Periods!O291+Periods!O407+Periods!O523+Periods!O639+Periods!O755+Periods!O871+Periods!O987+Periods!O1103+Periods!O1219+Periods!O1335, "-") -> 0 | P59: =IFERROR(Periods!P59+Periods!P175+Periods!P291+Periods!P407+Periods!P523+Periods!P639+Periods!P755+Periods!P871+Periods!P987+Periods!P1103+Periods!P1219+Periods!P1335, "-") -> 0 | Q59: =IFERROR(R59/P59, "-") -> - | R59: =IFERROR(Periods!R59+Periods!R175+Periods!R291+Periods!R407+Periods!R523+Periods!R639+Periods!R755+Periods!R871+Periods!R987+Periods!R1103+Periods!R1219+Periods!R1335, "-") -> 0 | S59: =(ROUNDDOWN(O59/R59,0)) -> #DIV/0! | T59: =IFERROR(Periods!T59+Periods!T175+Periods!T291+Periods!T407+Periods!T523+Periods!T639+Periods!T755+Periods!T871+Periods!T987+Periods!T1103+Periods!T1219+Periods!T1335, "-") -> 0 | U59: =IFERROR(O59/T59, "-") -> - | V59: =IFERROR(R59/T59, "-") -> - | W59: =IFERROR(Periods!W59+Periods!W175+Periods!W291+Periods!W407+Periods!W523+Periods!W639+Periods!W755+Periods!W871+Periods!W987+Periods!W1103+Periods!W1219+Periods!W1335, "-") -> 0 | X59: =O59/W59 -> #DIV/0! | Y59: =W59/O59 -> #DIV/0! | Z59: =W59/T59 -> #DIV/0! | AA59: =IFERROR(Periods!AA59+Periods!AA175+Periods!AA291+Periods!AA407+Periods!AA523+Periods!AA639+Periods!AA755+Periods!AA871+Periods!AA987+Periods!AA1103+Periods!AA1219+Periods!AA1335, "-") -> 0 | AB59: =O59/AA59 -> #DIV/0! | AC59: =IFERROR(AA59/T59, "-") -> - | AD59: =IFERROR(Periods!AD59+Periods!AD175+Periods!AD291+Periods!AD407+Periods!AD523+Periods!AD639+Periods!AD755+Periods!AD871+Periods!AD987+Periods!AD1103+Periods!AD1219+Periods!AD1335, "-") -> 0 | AE59: =O59/AD59 -> #DIV/0! | AF59: =AD59/O59 -> #DIV/0! | AG59: =AD59/AA59 -> #DIV/0! | AH59: =IFERROR(Periods!AH59+Periods!AH175+Periods!AH291+Periods!AH407+Periods!AH523+Periods!AH639+Periods!AH755+Periods!AH871+Periods!AH987+Periods!AH1103+Periods!AH1219+Periods!AH1335, "-") -> 0 | AI59: =IFERROR(AVERAGE(Periods!AI59,Periods!AI175,Periods!AI291,Periods!AI407,Periods!AI523,Periods!AI639,Periods!AI755,Periods!AI871,Periods!AI987,Periods!AI1103,Periods!AI1219,Periods!AI1335), "-") -> - | AJ59: =IFERROR(Periods!AJ59+Periods!AJ175+Periods!AJ291+Periods!AJ407+Periods!AJ523+Periods!AJ639+Periods!AJ755+Periods!AJ871+Periods!AJ987+Periods!AJ1103+Periods!AJ1219+Periods!AJ1335, "-") -> 0 | AK59: =IFERROR(Periods!AK59+Periods!AK175+Periods!AK291+Periods!AK407+Periods!AK523+Periods!AK639+Periods!AK755+Periods!AK871+Periods!AK987+Periods!AK1103+Periods!AK1219+Periods!AK1335, "-") -> 0 | AL59: =AJ59+AK59 -> 0 | AM59: =AL59/AH59 -> #DIV/0! | AN59: =O59/AL59 -> #DIV/0! | AO59: =IFERROR(Periods!AO59+Periods!AO175+Periods!AO291+Periods!AO407+Periods!AO523+Periods!AO639+Periods!AO755+Periods!AO871+Periods!AO987+Periods!AO1103+Periods!AO1219+Periods!AO1335, "-") -> 0 | AP59: =IFERROR(AVERAGE(Periods!AP59,Periods!AP175,Periods!AP291,Periods!AP407,Periods!AP523,Periods!AP639,Periods!AP755,Periods!AP871,Periods!AP987,Periods!AP1103,Periods!AP1219,Periods!AP1335), "-") -> - | AR59: =IFERROR(AH59/R59, "-") -> -
A60: 2026-2027 | B60: B2C | H60: =IFERROR(Periods!H60+Periods!H176+Periods!H292+Periods!H408+Periods!H524+Periods!H640+Periods!H756+Periods!H872+Periods!H988+Periods!H1104+Periods!H1220+Periods!H1336, "-") -> 0 | I60: =(M60*1.22)/R60 -> #DIV/0! | J60: =IFERROR(N60/M60-1,"-") -> - | K60: =I60*J60*H60 -> #DIV/0! | L60: =IFERROR(Periods!L60+Periods!L176+Periods!L292+Periods!L408+Periods!L524+Periods!L640+Periods!L756+Periods!L872+Periods!L988+Periods!L1104+Periods!L1220+Periods!L1336, "-") -> 0 | M60: =IFERROR(Periods!M60+Periods!M176+Periods!M292+Periods!M408+Periods!M524+Periods!M640+Periods!M756+Periods!M872+Periods!M988+Periods!M1104+Periods!M1220+Periods!M1336, "-") -> 0 | N60: =IFERROR(Periods!N60+Periods!N176+Periods!N292+Periods!N408+Periods!N524+Periods!N640+Periods!N756+Periods!N872+Periods!N988+Periods!N1104+Periods!N1220+Periods!N1336, "-") -> 0 | O60: =IFERROR(Periods!O60+Periods!O176+Periods!O292+Periods!O408+Periods!O524+Periods!O640+Periods!O756+Periods!O872+Periods!O988+Periods!O1104+Periods!O1220+Periods!O1336, "-") -> 0 | P60: =IFERROR(Periods!P60+Periods!P176+Periods!P292+Periods!P408+Periods!P524+Periods!P640+Periods!P756+Periods!P872+Periods!P988+Periods!P1104+Periods!P1220+Periods!P1336, "-") -> 0 | Q60: =IFERROR(R60/P60, "-") -> - | R60: =IFERROR(Periods!R60+Periods!R176+Periods!R292+Periods!R408+Periods!R524+Periods!R640+Periods!R756+Periods!R872+Periods!R988+Periods!R1104+Periods!R1220+Periods!R1336, "-") -> 0 | S60: =(ROUNDDOWN(O60/R60,0)) -> #DIV/0! | T60: =IFERROR(Periods!T60+Periods!T176+Periods!T292+Periods!T408+Periods!T524+Periods!T640+Periods!T756+Periods!T872+Periods!T988+Periods!T1104+Periods!T1220+Periods!T1336, "-") -> 0 | U60: =IFERROR(O60/T60, "-") -> - | V60: =IFERROR(R60/T60, "-") -> - | W60: =IFERROR(Periods!W60+Periods!W176+Periods!W292+Periods!W408+Periods!W524+Periods!W640+Periods!W756+Periods!W872+Periods!W988+Periods!W1104+Periods!W1220+Periods!W1336, "-") -> 0 | X60: =O60/W60 -> #DIV/0! | Y60: =W60/O60 -> #DIV/0! | Z60: =W60/T60 -> #DIV/0! | AA60: =IFERROR(Periods!AA60+Periods!AA176+Periods!AA292+Periods!AA408+Periods!AA524+Periods!AA640+Periods!AA756+Periods!AA872+Periods!AA988+Periods!AA1104+Periods!AA1220+Periods!AA1336, "-") -> 0 | AB60: =O60/AA60 -> #DIV/0! | AC60: =IFERROR(AA60/T60, "-") -> - | AD60: =IFERROR(Periods!AD60+Periods!AD176+Periods!AD292+Periods!AD408+Periods!AD524+Periods!AD640+Periods!AD756+Periods!AD872+Periods!AD988+Periods!AD1104+Periods!AD1220+Periods!AD1336, "-") -> 0 | AE60: =O60/AD60 -> #DIV/0! | AF60: =AD60/O60 -> #DIV/0! | AG60: =AD60/AA60 -> #DIV/0! | AH60: =IFERROR(Periods!AH60+Periods!AH176+Periods!AH292+Periods!AH408+Periods!AH524+Periods!AH640+Periods!AH756+Periods!AH872+Periods!AH988+Periods!AH1104+Periods!AH1220+Periods!AH1336, "-") -> 0 | AI60: =IFERROR(AVERAGE(Periods!AI60,Periods!AI176,Periods!AI292,Periods!AI408,Periods!AI524,Periods!AI640,Periods!AI756,Periods!AI872,Periods!AI988,Periods!AI1104,Periods!AI1220,Periods!AI1336), "-") -> - | AJ60: =IFERROR(Periods!AJ60+Periods!AJ176+Periods!AJ292+Periods!AJ408+Periods!AJ524+Periods!AJ640+Periods!AJ756+Periods!AJ872+Periods!AJ988+Periods!AJ1104+Periods!AJ1220+Periods!AJ1336, "-") -> 0 | AK60: =IFERROR(Periods!AK60+Periods!AK176+Periods!AK292+Periods!AK408+Periods!AK524+Periods!AK640+Periods!AK756+Periods!AK872+Periods!AK988+Periods!AK1104+Periods!AK1220+Periods!AK1336, "-") -> 0 | AL60: =AJ60+AK60 -> 0 | AM60: =AL60/AH60 -> #DIV/0! | AN60: =O60/AL60 -> #DIV/0! | AO60: =IFERROR(Periods!AO60+Periods!AO176+Periods!AO292+Periods!AO408+Periods!AO524+Periods!AO640+Periods!AO756+Periods!AO872+Periods!AO988+Periods!AO1104+Periods!AO1220+Periods!AO1336, "-") -> 0 | AP60: =IFERROR(AVERAGE(Periods!AP60,Periods!AP176,Periods!AP292,Periods!AP408,Periods!AP524,Periods!AP640,Periods!AP756,Periods!AP872,Periods!AP988,Periods!AP1104,Periods!AP1220,Periods!AP1336), "-") -> - | AR60: =IFERROR(AH60/R60, "-") -> -
A61: 2026-2027 | B61: B2C | H61: =IFERROR(Periods!H61+Periods!H177+Periods!H293+Periods!H409+Periods!H525+Periods!H641+Periods!H757+Periods!H873+Periods!H989+Periods!H1105+Periods!H1221+Periods!H1337, "-") -> 0 | I61: =(M61*1.22)/R61 -> #DIV/0! | J61: =IFERROR(N61/M61-1,"-") -> - | K61: =I61*J61*H61 -> #DIV/0! | L61: =IFERROR(Periods!L61+Periods!L177+Periods!L293+Periods!L409+Periods!L525+Periods!L641+Periods!L757+Periods!L873+Periods!L989+Periods!L1105+Periods!L1221+Periods!L1337, "-") -> 0 | M61: =IFERROR(Periods!M61+Periods!M177+Periods!M293+Periods!M409+Periods!M525+Periods!M641+Periods!M757+Periods!M873+Periods!M989+Periods!M1105+Periods!M1221+Periods!M1337, "-") -> 0 | N61: =IFERROR(Periods!N61+Periods!N177+Periods!N293+Periods!N409+Periods!N525+Periods!N641+Periods!N757+Periods!N873+Periods!N989+Periods!N1105+Periods!N1221+Periods!N1337, "-") -> 0 | O61: =IFERROR(Periods!O61+Periods!O177+Periods!O293+Periods!O409+Periods!O525+Periods!O641+Periods!O757+Periods!O873+Periods!O989+Periods!O1105+Periods!O1221+Periods!O1337, "-") -> 0 | P61: =IFERROR(Periods!P61+Periods!P177+Periods!P293+Periods!P409+Periods!P525+Periods!P641+Periods!P757+Periods!P873+Periods!P989+Periods!P1105+Periods!P1221+Periods!P1337, "-") -> 0 | Q61: =IFERROR(R61/P61, "-") -> - | R61: =IFERROR(Periods!R61+Periods!R177+Periods!R293+Periods!R409+Periods!R525+Periods!R641+Periods!R757+Periods!R873+Periods!R989+Periods!R1105+Periods!R1221+Periods!R1337, "-") -> 0 | S61: =(ROUNDDOWN(O61/R61,0)) -> #DIV/0! | T61: =IFERROR(Periods!T61+Periods!T177+Periods!T293+Periods!T409+Periods!T525+Periods!T641+Periods!T757+Periods!T873+Periods!T989+Periods!T1105+Periods!T1221+Periods!T1337, "-") -> 0 | U61: =IFERROR(O61/T61, "-") -> - | V61: =IFERROR(R61/T61, "-") -> - | W61: =IFERROR(Periods!W61+Periods!W177+Periods!W293+Periods!W409+Periods!W525+Periods!W641+Periods!W757+Periods!W873+Periods!W989+Periods!W1105+Periods!W1221+Periods!W1337, "-") -> 0 | X61: =O61/W61 -> #DIV/0! | Y61: =W61/O61 -> #DIV/0! | Z61: =W61/T61 -> #DIV/0! | AA61: =IFERROR(Periods!AA61+Periods!AA177+Periods!AA293+Periods!AA409+Periods!AA525+Periods!AA641+Periods!AA757+Periods!AA873+Periods!AA989+Periods!AA1105+Periods!AA1221+Periods!AA1337, "-") -> 0 | AB61: =O61/AA61 -> #DIV/0! | AC61: =IFERROR(AA61/T61, "-") -> - | AD61: =IFERROR(Periods!AD61+Periods!AD177+Periods!AD293+Periods!AD409+Periods!AD525+Periods!AD641+Periods!AD757+Periods!AD873+Periods!AD989+Periods!AD1105+Periods!AD1221+Periods!AD1337, "-") -> 0 | AE61: =O61/AD61 -> #DIV/0! | AF61: =AD61/O61 -> #DIV/0! | AG61: =AD61/AA61 -> #DIV/0! | AH61: =IFERROR(Periods!AH61+Periods!AH177+Periods!AH293+Periods!AH409+Periods!AH525+Periods!AH641+Periods!AH757+Periods!AH873+Periods!AH989+Periods!AH1105+Periods!AH1221+Periods!AH1337, "-") -> 0 | AI61: =IFERROR(AVERAGE(Periods!AI61,Periods!AI177,Periods!AI293,Periods!AI409,Periods!AI525,Periods!AI641,Periods!AI757,Periods!AI873,Periods!AI989,Periods!AI1105,Periods!AI1221,Periods!AI1337), "-") -> - | AJ61: =IFERROR(Periods!AJ61+Periods!AJ177+Periods!AJ293+Periods!AJ409+Periods!AJ525+Periods!AJ641+Periods!AJ757+Periods!AJ873+Periods!AJ989+Periods!AJ1105+Periods!AJ1221+Periods!AJ1337, "-") -> 0 | AK61: =IFERROR(Periods!AK61+Periods!AK177+Periods!AK293+Periods!AK409+Periods!AK525+Periods!AK641+Periods!AK757+Periods!AK873+Periods!AK989+Periods!AK1105+Periods!AK1221+Periods!AK1337, "-") -> 0 | AL61: =AJ61+AK61 -> 0 | AM61: =AL61/AH61 -> #DIV/0! | AN61: =O61/AL61 -> #DIV/0! | AO61: =IFERROR(Periods!AO61+Periods!AO177+Periods!AO293+Periods!AO409+Periods!AO525+Periods!AO641+Periods!AO757+Periods!AO873+Periods!AO989+Periods!AO1105+Periods!AO1221+Periods!AO1337, "-") -> 0 | AP61: =IFERROR(AVERAGE(Periods!AP61,Periods!AP177,Periods!AP293,Periods!AP409,Periods!AP525,Periods!AP641,Periods!AP757,Periods!AP873,Periods!AP989,Periods!AP1105,Periods!AP1221,Periods!AP1337), "-") -> - | AR61: =IFERROR(AH61/R61, "-") -> -
A62: 2026-2027 | B62: B2C | H62: =IFERROR(Periods!H62+Periods!H178+Periods!H294+Periods!H410+Periods!H526+Periods!H642+Periods!H758+Periods!H874+Periods!H990+Periods!H1106+Periods!H1222+Periods!H1338, "-") -> 0 | I62: =(M62*1.22)/R62 -> #DIV/0! | J62: =IFERROR(N62/M62-1,"-") -> - | K62: =I62*J62*H62 -> #DIV/0! | L62: =IFERROR(Periods!L62+Periods!L178+Periods!L294+Periods!L410+Periods!L526+Periods!L642+Periods!L758+Periods!L874+Periods!L990+Periods!L1106+Periods!L1222+Periods!L1338, "-") -> 0 | M62: =IFERROR(Periods!M62+Periods!M178+Periods!M294+Periods!M410+Periods!M526+Periods!M642+Periods!M758+Periods!M874+Periods!M990+Periods!M1106+Periods!M1222+Periods!M1338, "-") -> 0 | N62: =IFERROR(Periods!N62+Periods!N178+Periods!N294+Periods!N410+Periods!N526+Periods!N642+Periods!N758+Periods!N874+Periods!N990+Periods!N1106+Periods!N1222+Periods!N1338, "-") -> 0 | O62: =IFERROR(Periods!O62+Periods!O178+Periods!O294+Periods!O410+Periods!O526+Periods!O642+Periods!O758+Periods!O874+Periods!O990+Periods!O1106+Periods!O1222+Periods!O1338, "-") -> 0 | P62: =IFERROR(Periods!P62+Periods!P178+Periods!P294+Periods!P410+Periods!P526+Periods!P642+Periods!P758+Periods!P874+Periods!P990+Periods!P1106+Periods!P1222+Periods!P1338, "-") -> 0 | Q62: =IFERROR(R62/P62, "-") -> - | R62: =IFERROR(Periods!R62+Periods!R178+Periods!R294+Periods!R410+Periods!R526+Periods!R642+Periods!R758+Periods!R874+Periods!R990+Periods!R1106+Periods!R1222+Periods!R1338, "-") -> 0 | S62: =(ROUNDDOWN(O62/R62,0)) -> #DIV/0! | T62: =IFERROR(Periods!T62+Periods!T178+Periods!T294+Periods!T410+Periods!T526+Periods!T642+Periods!T758+Periods!T874+Periods!T990+Periods!T1106+Periods!T1222+Periods!T1338, "-") -> 0 | U62: =IFERROR(O62/T62, "-") -> - | V62: =IFERROR(R62/T62, "-") -> - | W62: =IFERROR(Periods!W62+Periods!W178+Periods!W294+Periods!W410+Periods!W526+Periods!W642+Periods!W758+Periods!W874+Periods!W990+Periods!W1106+Periods!W1222+Periods!W1338, "-") -> 0 | X62: =O62/W62 -> #DIV/0! | Y62: =W62/O62 -> #DIV/0! | Z62: =W62/T62 -> #DIV/0! | AA62: =IFERROR(Periods!AA62+Periods!AA178+Periods!AA294+Periods!AA410+Periods!AA526+Periods!AA642+Periods!AA758+Periods!AA874+Periods!AA990+Periods!AA1106+Periods!AA1222+Periods!AA1338, "-") -> 0 | AB62: =O62/AA62 -> #DIV/0! | AC62: =IFERROR(AA62/T62, "-") -> - | AD62: =IFERROR(Periods!AD62+Periods!AD178+Periods!AD294+Periods!AD410+Periods!AD526+Periods!AD642+Periods!AD758+Periods!AD874+Periods!AD990+Periods!AD1106+Periods!AD1222+Periods!AD1338, "-") -> 0 | AE62: =O62/AD62 -> #DIV/0! | AF62: =AD62/O62 -> #DIV/0! | AG62: =AD62/AA62 -> #DIV/0! | AH62: =IFERROR(Periods!AH62+Periods!AH178+Periods!AH294+Periods!AH410+Periods!AH526+Periods!AH642+Periods!AH758+Periods!AH874+Periods!AH990+Periods!AH1106+Periods!AH1222+Periods!AH1338, "-") -> 0 | AI62: =IFERROR(AVERAGE(Periods!AI62,Periods!AI178,Periods!AI294,Periods!AI410,Periods!AI526,Periods!AI642,Periods!AI758,Periods!AI874,Periods!AI990,Periods!AI1106,Periods!AI1222,Periods!AI1338), "-") -> - | AJ62: =IFERROR(Periods!AJ62+Periods!AJ178+Periods!AJ294+Periods!AJ410+Periods!AJ526+Periods!AJ642+Periods!AJ758+Periods!AJ874+Periods!AJ990+Periods!AJ1106+Periods!AJ1222+Periods!AJ1338, "-") -> 0 | AK62: =IFERROR(Periods!AK62+Periods!AK178+Periods!AK294+Periods!AK410+Periods!AK526+Periods!AK642+Periods!AK758+Periods!AK874+Periods!AK990+Periods!AK1106+Periods!AK1222+Periods!AK1338, "-") -> 0 | AL62: =AJ62+AK62 -> 0 | AM62: =AL62/AH62 -> #DIV/0! | AN62: =O62/AL62 -> #DIV/0! | AO62: =IFERROR(Periods!AO62+Periods!AO178+Periods!AO294+Periods!AO410+Periods!AO526+Periods!AO642+Periods!AO758+Periods!AO874+Periods!AO990+Periods!AO1106+Periods!AO1222+Periods!AO1338, "-") -> 0 | AP62: =IFERROR(AVERAGE(Periods!AP62,Periods!AP178,Periods!AP294,Periods!AP410,Periods!AP526,Periods!AP642,Periods!AP758,Periods!AP874,Periods!AP990,Periods!AP1106,Periods!AP1222,Periods!AP1338), "-") -> - | AR62: =IFERROR(AH62/R62, "-") -> -
A63: 2026-2027 | B63: B2C | H63: =IFERROR(Periods!H63+Periods!H179+Periods!H295+Periods!H411+Periods!H527+Periods!H643+Periods!H759+Periods!H875+Periods!H991+Periods!H1107+Periods!H1223+Periods!H1339, "-") -> 0 | I63: =(M63*1.22)/R63 -> #DIV/0! | J63: =IFERROR(N63/M63-1,"-") -> - | K63: =I63*J63*H63 -> #DIV/0! | L63: =IFERROR(Periods!L63+Periods!L179+Periods!L295+Periods!L411+Periods!L527+Periods!L643+Periods!L759+Periods!L875+Periods!L991+Periods!L1107+Periods!L1223+Periods!L1339, "-") -> 0 | M63: =IFERROR(Periods!M63+Periods!M179+Periods!M295+Periods!M411+Periods!M527+Periods!M643+Periods!M759+Periods!M875+Periods!M991+Periods!M1107+Periods!M1223+Periods!M1339, "-") -> 0 | N63: =IFERROR(Periods!N63+Periods!N179+Periods!N295+Periods!N411+Periods!N527+Periods!N643+Periods!N759+Periods!N875+Periods!N991+Periods!N1107+Periods!N1223+Periods!N1339, "-") -> 0 | O63: =IFERROR(Periods!O63+Periods!O179+Periods!O295+Periods!O411+Periods!O527+Periods!O643+Periods!O759+Periods!O875+Periods!O991+Periods!O1107+Periods!O1223+Periods!O1339, "-") -> 0 | P63: =IFERROR(Periods!P63+Periods!P179+Periods!P295+Periods!P411+Periods!P527+Periods!P643+Periods!P759+Periods!P875+Periods!P991+Periods!P1107+Periods!P1223+Periods!P1339, "-") -> 0 | Q63: =IFERROR(R63/P63, "-") -> - | R63: =IFERROR(Periods!R63+Periods!R179+Periods!R295+Periods!R411+Periods!R527+Periods!R643+Periods!R759+Periods!R875+Periods!R991+Periods!R1107+Periods!R1223+Periods!R1339, "-") -> 0 | S63: =(ROUNDDOWN(O63/R63,0)) -> #DIV/0! | T63: =IFERROR(Periods!T63+Periods!T179+Periods!T295+Periods!T411+Periods!T527+Periods!T643+Periods!T759+Periods!T875+Periods!T991+Periods!T1107+Periods!T1223+Periods!T1339, "-") -> 0 | U63: =IFERROR(O63/T63, "-") -> - | V63: =IFERROR(R63/T63, "-") -> - | W63: =IFERROR(Periods!W63+Periods!W179+Periods!W295+Periods!W411+Periods!W527+Periods!W643+Periods!W759+Periods!W875+Periods!W991+Periods!W1107+Periods!W1223+Periods!W1339, "-") -> 0 | X63: =O63/W63 -> #DIV/0! | Y63: =W63/O63 -> #DIV/0! | Z63: =W63/T63 -> #DIV/0! | AA63: =IFERROR(Periods!AA63+Periods!AA179+Periods!AA295+Periods!AA411+Periods!AA527+Periods!AA643+Periods!AA759+Periods!AA875+Periods!AA991+Periods!AA1107+Periods!AA1223+Periods!AA1339, "-") -> 0 | AB63: =O63/AA63 -> #DIV/0! | AC63: =IFERROR(AA63/T63, "-") -> - | AD63: =IFERROR(Periods!AD63+Periods!AD179+Periods!AD295+Periods!AD411+Periods!AD527+Periods!AD643+Periods!AD759+Periods!AD875+Periods!AD991+Periods!AD1107+Periods!AD1223+Periods!AD1339, "-") -> 0 | AE63: =O63/AD63 -> #DIV/0! | AF63: =AD63/O63 -> #DIV/0! | AG63: =AD63/AA63 -> #DIV/0! | AH63: =IFERROR(Periods!AH63+Periods!AH179+Periods!AH295+Periods!AH411+Periods!AH527+Periods!AH643+Periods!AH759+Periods!AH875+Periods!AH991+Periods!AH1107+Periods!AH1223+Periods!AH1339, "-") -> 0 | AI63: =IFERROR(AVERAGE(Periods!AI63,Periods!AI179,Periods!AI295,Periods!AI411,Periods!AI527,Periods!AI643,Periods!AI759,Periods!AI875,Periods!AI991,Periods!AI1107,Periods!AI1223,Periods!AI1339), "-") -> - | AJ63: =IFERROR(Periods!AJ63+Periods!AJ179+Periods!AJ295+Periods!AJ411+Periods!AJ527+Periods!AJ643+Periods!AJ759+Periods!AJ875+Periods!AJ991+Periods!AJ1107+Periods!AJ1223+Periods!AJ1339, "-") -> 0 | AK63: =IFERROR(Periods!AK63+Periods!AK179+Periods!AK295+Periods!AK411+Periods!AK527+Periods!AK643+Periods!AK759+Periods!AK875+Periods!AK991+Periods!AK1107+Periods!AK1223+Periods!AK1339, "-") -> 0 | AL63: =AJ63+AK63 -> 0 | AM63: =AL63/AH63 -> #DIV/0! | AN63: =O63/AL63 -> #DIV/0! | AO63: =IFERROR(Periods!AO63+Periods!AO179+Periods!AO295+Periods!AO411+Periods!AO527+Periods!AO643+Periods!AO759+Periods!AO875+Periods!AO991+Periods!AO1107+Periods!AO1223+Periods!AO1339, "-") -> 0 | AP63: =IFERROR(AVERAGE(Periods!AP63,Periods!AP179,Periods!AP295,Periods!AP411,Periods!AP527,Periods!AP643,Periods!AP759,Periods!AP875,Periods!AP991,Periods!AP1107,Periods!AP1223,Periods!AP1339), "-") -> - | AR63: =IFERROR(AH63/R63, "-") -> -
A64: 2026-2027 | B64: B2C | H64: =IFERROR(Periods!H64+Periods!H180+Periods!H296+Periods!H412+Periods!H528+Periods!H644+Periods!H760+Periods!H876+Periods!H992+Periods!H1108+Periods!H1224+Periods!H1340, "-") -> 0 | I64: =(M64*1.22)/R64 -> #DIV/0! | J64: =IFERROR(N64/M64-1,"-") -> - | K64: =I64*J64*H64 -> #DIV/0! | L64: =IFERROR(Periods!L64+Periods!L180+Periods!L296+Periods!L412+Periods!L528+Periods!L644+Periods!L760+Periods!L876+Periods!L992+Periods!L1108+Periods!L1224+Periods!L1340, "-") -> 0 | M64: =IFERROR(Periods!M64+Periods!M180+Periods!M296+Periods!M412+Periods!M528+Periods!M644+Periods!M760+Periods!M876+Periods!M992+Periods!M1108+Periods!M1224+Periods!M1340, "-") -> 0 | N64: =IFERROR(Periods!N64+Periods!N180+Periods!N296+Periods!N412+Periods!N528+Periods!N644+Periods!N760+Periods!N876+Periods!N992+Periods!N1108+Periods!N1224+Periods!N1340, "-") -> 0 | O64: =IFERROR(Periods!O64+Periods!O180+Periods!O296+Periods!O412+Periods!O528+Periods!O644+Periods!O760+Periods!O876+Periods!O992+Periods!O1108+Periods!O1224+Periods!O1340, "-") -> 0 | P64: =IFERROR(Periods!P64+Periods!P180+Periods!P296+Periods!P412+Periods!P528+Periods!P644+Periods!P760+Periods!P876+Periods!P992+Periods!P1108+Periods!P1224+Periods!P1340, "-") -> 0 | Q64: =IFERROR(R64/P64, "-") -> - | R64: =IFERROR(Periods!R64+Periods!R180+Periods!R296+Periods!R412+Periods!R528+Periods!R644+Periods!R760+Periods!R876+Periods!R992+Periods!R1108+Periods!R1224+Periods!R1340, "-") -> 0 | S64: =(ROUNDDOWN(O64/R64,0)) -> #DIV/0! | T64: =IFERROR(Periods!T64+Periods!T180+Periods!T296+Periods!T412+Periods!T528+Periods!T644+Periods!T760+Periods!T876+Periods!T992+Periods!T1108+Periods!T1224+Periods!T1340, "-") -> 0 | U64: =IFERROR(O64/T64, "-") -> - | V64: =IFERROR(R64/T64, "-") -> - | W64: =IFERROR(Periods!W64+Periods!W180+Periods!W296+Periods!W412+Periods!W528+Periods!W644+Periods!W760+Periods!W876+Periods!W992+Periods!W1108+Periods!W1224+Periods!W1340, "-") -> 0 | X64: =O64/W64 -> #DIV/0! | Y64: =W64/O64 -> #DIV/0! | Z64: =W64/T64 -> #DIV/0! | AA64: =IFERROR(Periods!AA64+Periods!AA180+Periods!AA296+Periods!AA412+Periods!AA528+Periods!AA644+Periods!AA760+Periods!AA876+Periods!AA992+Periods!AA1108+Periods!AA1224+Periods!AA1340, "-") -> 0 | AB64: =O64/AA64 -> #DIV/0! | AC64: =IFERROR(AA64/T64, "-") -> - | AD64: =IFERROR(Periods!AD64+Periods!AD180+Periods!AD296+Periods!AD412+Periods!AD528+Periods!AD644+Periods!AD760+Periods!AD876+Periods!AD992+Periods!AD1108+Periods!AD1224+Periods!AD1340, "-") -> 0 | AE64: =O64/AD64 -> #DIV/0! | AF64: =AD64/O64 -> #DIV/0! | AG64: =AD64/AA64 -> #DIV/0! | AH64: =IFERROR(Periods!AH64+Periods!AH180+Periods!AH296+Periods!AH412+Periods!AH528+Periods!AH644+Periods!AH760+Periods!AH876+Periods!AH992+Periods!AH1108+Periods!AH1224+Periods!AH1340, "-") -> 0 | AI64: =IFERROR(AVERAGE(Periods!AI64,Periods!AI180,Periods!AI296,Periods!AI412,Periods!AI528,Periods!AI644,Periods!AI760,Periods!AI876,Periods!AI992,Periods!AI1108,Periods!AI1224,Periods!AI1340), "-") -> - | AJ64: =IFERROR(Periods!AJ64+Periods!AJ180+Periods!AJ296+Periods!AJ412+Periods!AJ528+Periods!AJ644+Periods!AJ760+Periods!AJ876+Periods!AJ992+Periods!AJ1108+Periods!AJ1224+Periods!AJ1340, "-") -> 0 | AK64: =IFERROR(Periods!AK64+Periods!AK180+Periods!AK296+Periods!AK412+Periods!AK528+Periods!AK644+Periods!AK760+Periods!AK876+Periods!AK992+Periods!AK1108+Periods!AK1224+Periods!AK1340, "-") -> 0 | AL64: =AJ64+AK64 -> 0 | AM64: =AL64/AH64 -> #DIV/0! | AN64: =O64/AL64 -> #DIV/0! | AO64: =IFERROR(Periods!AO64+Periods!AO180+Periods!AO296+Periods!AO412+Periods!AO528+Periods!AO644+Periods!AO760+Periods!AO876+Periods!AO992+Periods!AO1108+Periods!AO1224+Periods!AO1340, "-") -> 0 | AP64: =IFERROR(AVERAGE(Periods!AP64,Periods!AP180,Periods!AP296,Periods!AP412,Periods!AP528,Periods!AP644,Periods!AP760,Periods!AP876,Periods!AP992,Periods!AP1108,Periods!AP1224,Periods!AP1340), "-") -> - | AR64: =IFERROR(AH64/R64, "-") -> -
A65: 2026-2027 | B65: B2C | H65: =IFERROR(Periods!H65+Periods!H181+Periods!H297+Periods!H413+Periods!H529+Periods!H645+Periods!H761+Periods!H877+Periods!H993+Periods!H1109+Periods!H1225+Periods!H1341, "-") -> 0 | I65: =(M65*1.22)/R65 -> #DIV/0! | J65: =IFERROR(N65/M65-1,"-") -> - | K65: =I65*J65*H65 -> #DIV/0! | L65: =IFERROR(Periods!L65+Periods!L181+Periods!L297+Periods!L413+Periods!L529+Periods!L645+Periods!L761+Periods!L877+Periods!L993+Periods!L1109+Periods!L1225+Periods!L1341, "-") -> 0 | M65: =IFERROR(Periods!M65+Periods!M181+Periods!M297+Periods!M413+Periods!M529+Periods!M645+Periods!M761+Periods!M877+Periods!M993+Periods!M1109+Periods!M1225+Periods!M1341, "-") -> 0 | N65: =IFERROR(Periods!N65+Periods!N181+Periods!N297+Periods!N413+Periods!N529+Periods!N645+Periods!N761+Periods!N877+Periods!N993+Periods!N1109+Periods!N1225+Periods!N1341, "-") -> 0 | O65: =IFERROR(Periods!O65+Periods!O181+Periods!O297+Periods!O413+Periods!O529+Periods!O645+Periods!O761+Periods!O877+Periods!O993+Periods!O1109+Periods!O1225+Periods!O1341, "-") -> 0 | P65: =IFERROR(Periods!P65+Periods!P181+Periods!P297+Periods!P413+Periods!P529+Periods!P645+Periods!P761+Periods!P877+Periods!P993+Periods!P1109+Periods!P1225+Periods!P1341, "-") -> 0 | Q65: =IFERROR(R65/P65, "-") -> - | R65: =IFERROR(Periods!R65+Periods!R181+Periods!R297+Periods!R413+Periods!R529+Periods!R645+Periods!R761+Periods!R877+Periods!R993+Periods!R1109+Periods!R1225+Periods!R1341, "-") -> 0 | S65: =(ROUNDDOWN(O65/R65,0)) -> #DIV/0! | T65: =IFERROR(Periods!T65+Periods!T181+Periods!T297+Periods!T413+Periods!T529+Periods!T645+Periods!T761+Periods!T877+Periods!T993+Periods!T1109+Periods!T1225+Periods!T1341, "-") -> 0 | U65: =IFERROR(O65/T65, "-") -> - | V65: =IFERROR(R65/T65, "-") -> - | W65: =IFERROR(Periods!W65+Periods!W181+Periods!W297+Periods!W413+Periods!W529+Periods!W645+Periods!W761+Periods!W877+Periods!W993+Periods!W1109+Periods!W1225+Periods!W1341, "-") -> 0 | X65: =O65/W65 -> #DIV/0! | Y65: =W65/O65 -> #DIV/0! | Z65: =W65/T65 -> #DIV/0! | AA65: =IFERROR(Periods!AA65+Periods!AA181+Periods!AA297+Periods!AA413+Periods!AA529+Periods!AA645+Periods!AA761+Periods!AA877+Periods!AA993+Periods!AA1109+Periods!AA1225+Periods!AA1341, "-") -> 0 | AB65: =O65/AA65 -> #DIV/0! | AC65: =IFERROR(AA65/T65, "-") -> - | AD65: =IFERROR(Periods!AD65+Periods!AD181+Periods!AD297+Periods!AD413+Periods!AD529+Periods!AD645+Periods!AD761+Periods!AD877+Periods!AD993+Periods!AD1109+Periods!AD1225+Periods!AD1341, "-") -> 0 | AE65: =O65/AD65 -> #DIV/0! | AF65: =AD65/O65 -> #DIV/0! | AG65: =AD65/AA65 -> #DIV/0! | AH65: =IFERROR(Periods!AH65+Periods!AH181+Periods!AH297+Periods!AH413+Periods!AH529+Periods!AH645+Periods!AH761+Periods!AH877+Periods!AH993+Periods!AH1109+Periods!AH1225+Periods!AH1341, "-") -> 0 | AI65: =IFERROR(AVERAGE(Periods!AI65,Periods!AI181,Periods!AI297,Periods!AI413,Periods!AI529,Periods!AI645,Periods!AI761,Periods!AI877,Periods!AI993,Periods!AI1109,Periods!AI1225,Periods!AI1341), "-") -> - | AJ65: =IFERROR(Periods!AJ65+Periods!AJ181+Periods!AJ297+Periods!AJ413+Periods!AJ529+Periods!AJ645+Periods!AJ761+Periods!AJ877+Periods!AJ993+Periods!AJ1109+Periods!AJ1225+Periods!AJ1341, "-") -> 0 | AK65: =IFERROR(Periods!AK65+Periods!AK181+Periods!AK297+Periods!AK413+Periods!AK529+Periods!AK645+Periods!AK761+Periods!AK877+Periods!AK993+Periods!AK1109+Periods!AK1225+Periods!AK1341, "-") -> 0 | AL65: =AJ65+AK65 -> 0 | AM65: =AL65/AH65 -> #DIV/0! | AN65: =O65/AL65 -> #DIV/0! | AO65: =IFERROR(Periods!AO65+Periods!AO181+Periods!AO297+Periods!AO413+Periods!AO529+Periods!AO645+Periods!AO761+Periods!AO877+Periods!AO993+Periods!AO1109+Periods!AO1225+Periods!AO1341, "-") -> 0 | AP65: =IFERROR(AVERAGE(Periods!AP65,Periods!AP181,Periods!AP297,Periods!AP413,Periods!AP529,Periods!AP645,Periods!AP761,Periods!AP877,Periods!AP993,Periods!AP1109,Periods!AP1225,Periods!AP1341), "-") -> - | AR65: =IFERROR(AH65/R65, "-") -> -
A66: 2026-2027 | B66: B2C | H66: =IFERROR(Periods!H66+Periods!H182+Periods!H298+Periods!H414+Periods!H530+Periods!H646+Periods!H762+Periods!H878+Periods!H994+Periods!H1110+Periods!H1226+Periods!H1342, "-") -> 0 | I66: =(M66*1.22)/R66 -> #DIV/0! | J66: =IFERROR(N66/M66-1,"-") -> - | K66: =I66*J66*H66 -> #DIV/0! | L66: =IFERROR(Periods!L66+Periods!L182+Periods!L298+Periods!L414+Periods!L530+Periods!L646+Periods!L762+Periods!L878+Periods!L994+Periods!L1110+Periods!L1226+Periods!L1342, "-") -> 0 | M66: =IFERROR(Periods!M66+Periods!M182+Periods!M298+Periods!M414+Periods!M530+Periods!M646+Periods!M762+Periods!M878+Periods!M994+Periods!M1110+Periods!M1226+Periods!M1342, "-") -> 0 | N66: =IFERROR(Periods!N66+Periods!N182+Periods!N298+Periods!N414+Periods!N530+Periods!N646+Periods!N762+Periods!N878+Periods!N994+Periods!N1110+Periods!N1226+Periods!N1342, "-") -> 0 | O66: =IFERROR(Periods!O66+Periods!O182+Periods!O298+Periods!O414+Periods!O530+Periods!O646+Periods!O762+Periods!O878+Periods!O994+Periods!O1110+Periods!O1226+Periods!O1342, "-") -> 0 | P66: =IFERROR(Periods!P66+Periods!P182+Periods!P298+Periods!P414+Periods!P530+Periods!P646+Periods!P762+Periods!P878+Periods!P994+Periods!P1110+Periods!P1226+Periods!P1342, "-") -> 0 | Q66: =IFERROR(R66/P66, "-") -> - | R66: =IFERROR(Periods!R66+Periods!R182+Periods!R298+Periods!R414+Periods!R530+Periods!R646+Periods!R762+Periods!R878+Periods!R994+Periods!R1110+Periods!R1226+Periods!R1342, "-") -> 0 | S66: =(ROUNDDOWN(O66/R66,0)) -> #DIV/0! | T66: =IFERROR(Periods!T66+Periods!T182+Periods!T298+Periods!T414+Periods!T530+Periods!T646+Periods!T762+Periods!T878+Periods!T994+Periods!T1110+Periods!T1226+Periods!T1342, "-") -> 0 | U66: =IFERROR(O66/T66, "-") -> - | V66: =IFERROR(R66/T66, "-") -> - | W66: =IFERROR(Periods!W66+Periods!W182+Periods!W298+Periods!W414+Periods!W530+Periods!W646+Periods!W762+Periods!W878+Periods!W994+Periods!W1110+Periods!W1226+Periods!W1342, "-") -> 0 | X66: =O66/W66 -> #DIV/0! | Y66: =W66/O66 -> #DIV/0! | Z66: =W66/T66 -> #DIV/0! | AA66: =IFERROR(Periods!AA66+Periods!AA182+Periods!AA298+Periods!AA414+Periods!AA530+Periods!AA646+Periods!AA762+Periods!AA878+Periods!AA994+Periods!AA1110+Periods!AA1226+Periods!AA1342, "-") -> 0 | AB66: =O66/AA66 -> #DIV/0! | AC66: =IFERROR(AA66/T66, "-") -> - | AD66: =IFERROR(Periods!AD66+Periods!AD182+Periods!AD298+Periods!AD414+Periods!AD530+Periods!AD646+Periods!AD762+Periods!AD878+Periods!AD994+Periods!AD1110+Periods!AD1226+Periods!AD1342, "-") -> 0 | AE66: =O66/AD66 -> #DIV/0! | AF66: =AD66/O66 -> #DIV/0! | AG66: =AD66/AA66 -> #DIV/0! | AH66: =IFERROR(Periods!AH66+Periods!AH182+Periods!AH298+Periods!AH414+Periods!AH530+Periods!AH646+Periods!AH762+Periods!AH878+Periods!AH994+Periods!AH1110+Periods!AH1226+Periods!AH1342, "-") -> 0 | AI66: =IFERROR(AVERAGE(Periods!AI66,Periods!AI182,Periods!AI298,Periods!AI414,Periods!AI530,Periods!AI646,Periods!AI762,Periods!AI878,Periods!AI994,Periods!AI1110,Periods!AI1226,Periods!AI1342), "-") -> - | AJ66: =IFERROR(Periods!AJ66+Periods!AJ182+Periods!AJ298+Periods!AJ414+Periods!AJ530+Periods!AJ646+Periods!AJ762+Periods!AJ878+Periods!AJ994+Periods!AJ1110+Periods!AJ1226+Periods!AJ1342, "-") -> 0 | AK66: =IFERROR(Periods!AK66+Periods!AK182+Periods!AK298+Periods!AK414+Periods!AK530+Periods!AK646+Periods!AK762+Periods!AK878+Periods!AK994+Periods!AK1110+Periods!AK1226+Periods!AK1342, "-") -> 0 | AL66: =AJ66+AK66 -> 0 | AM66: =AL66/AH66 -> #DIV/0! | AN66: =O66/AL66 -> #DIV/0! | AO66: =IFERROR(Periods!AO66+Periods!AO182+Periods!AO298+Periods!AO414+Periods!AO530+Periods!AO646+Periods!AO762+Periods!AO878+Periods!AO994+Periods!AO1110+Periods!AO1226+Periods!AO1342, "-") -> 0 | AP66: =IFERROR(AVERAGE(Periods!AP66,Periods!AP182,Periods!AP298,Periods!AP414,Periods!AP530,Periods!AP646,Periods!AP762,Periods!AP878,Periods!AP994,Periods!AP1110,Periods!AP1226,Periods!AP1342), "-") -> - | AR66: =IFERROR(AH66/R66, "-") -> -
A67: 2026-2027 | B67: B2C | H67: =IFERROR(Periods!H67+Periods!H183+Periods!H299+Periods!H415+Periods!H531+Periods!H647+Periods!H763+Periods!H879+Periods!H995+Periods!H1111+Periods!H1227+Periods!H1343, "-") -> 0 | I67: =(M67*1.22)/R67 -> #DIV/0! | J67: =IFERROR(N67/M67-1,"-") -> - | K67: =I67*J67*H67 -> #DIV/0! | L67: =IFERROR(Periods!L67+Periods!L183+Periods!L299+Periods!L415+Periods!L531+Periods!L647+Periods!L763+Periods!L879+Periods!L995+Periods!L1111+Periods!L1227+Periods!L1343, "-") -> 0 | M67: =IFERROR(Periods!M67+Periods!M183+Periods!M299+Periods!M415+Periods!M531+Periods!M647+Periods!M763+Periods!M879+Periods!M995+Periods!M1111+Periods!M1227+Periods!M1343, "-") -> 0 | N67: =IFERROR(Periods!N67+Periods!N183+Periods!N299+Periods!N415+Periods!N531+Periods!N647+Periods!N763+Periods!N879+Periods!N995+Periods!N1111+Periods!N1227+Periods!N1343, "-") -> 0 | O67: =IFERROR(Periods!O67+Periods!O183+Periods!O299+Periods!O415+Periods!O531+Periods!O647+Periods!O763+Periods!O879+Periods!O995+Periods!O1111+Periods!O1227+Periods!O1343, "-") -> 0 | P67: =IFERROR(Periods!P67+Periods!P183+Periods!P299+Periods!P415+Periods!P531+Periods!P647+Periods!P763+Periods!P879+Periods!P995+Periods!P1111+Periods!P1227+Periods!P1343, "-") -> 0 | Q67: =IFERROR(R67/P67, "-") -> - | R67: =IFERROR(Periods!R67+Periods!R183+Periods!R299+Periods!R415+Periods!R531+Periods!R647+Periods!R763+Periods!R879+Periods!R995+Periods!R1111+Periods!R1227+Periods!R1343, "-") -> 0 | S67: =(ROUNDDOWN(O67/R67,0)) -> #DIV/0! | T67: =IFERROR(Periods!T67+Periods!T183+Periods!T299+Periods!T415+Periods!T531+Periods!T647+Periods!T763+Periods!T879+Periods!T995+Periods!T1111+Periods!T1227+Periods!T1343, "-") -> 0 | U67: =IFERROR(O67/T67, "-") -> - | V67: =IFERROR(R67/T67, "-") -> - | W67: =IFERROR(Periods!W67+Periods!W183+Periods!W299+Periods!W415+Periods!W531+Periods!W647+Periods!W763+Periods!W879+Periods!W995+Periods!W1111+Periods!W1227+Periods!W1343, "-") -> 0 | X67: =O67/W67 -> #DIV/0! | Y67: =W67/O67 -> #DIV/0! | Z67: =W67/T67 -> #DIV/0! | AA67: =IFERROR(Periods!AA67+Periods!AA183+Periods!AA299+Periods!AA415+Periods!AA531+Periods!AA647+Periods!AA763+Periods!AA879+Periods!AA995+Periods!AA1111+Periods!AA1227+Periods!AA1343, "-") -> 0 | AB67: =O67/AA67 -> #DIV/0! | AC67: =IFERROR(AA67/T67, "-") -> - | AD67: =IFERROR(Periods!AD67+Periods!AD183+Periods!AD299+Periods!AD415+Periods!AD531+Periods!AD647+Periods!AD763+Periods!AD879+Periods!AD995+Periods!AD1111+Periods!AD1227+Periods!AD1343, "-") -> 0 | AE67: =O67/AD67 -> #DIV/0! | AF67: =AD67/O67 -> #DIV/0! | AG67: =AD67/AA67 -> #DIV/0! | AH67: =IFERROR(Periods!AH67+Periods!AH183+Periods!AH299+Periods!AH415+Periods!AH531+Periods!AH647+Periods!AH763+Periods!AH879+Periods!AH995+Periods!AH1111+Periods!AH1227+Periods!AH1343, "-") -> 0 | AI67: =IFERROR(AVERAGE(Periods!AI67,Periods!AI183,Periods!AI299,Periods!AI415,Periods!AI531,Periods!AI647,Periods!AI763,Periods!AI879,Periods!AI995,Periods!AI1111,Periods!AI1227,Periods!AI1343), "-") -> - | AJ67: =IFERROR(Periods!AJ67+Periods!AJ183+Periods!AJ299+Periods!AJ415+Periods!AJ531+Periods!AJ647+Periods!AJ763+Periods!AJ879+Periods!AJ995+Periods!AJ1111+Periods!AJ1227+Periods!AJ1343, "-") -> 0 | AK67: =IFERROR(Periods!AK67+Periods!AK183+Periods!AK299+Periods!AK415+Periods!AK531+Periods!AK647+Periods!AK763+Periods!AK879+Periods!AK995+Periods!AK1111+Periods!AK1227+Periods!AK1343, "-") -> 0 | AL67: =AJ67+AK67 -> 0 | AM67: =AL67/AH67 -> #DIV/0! | AN67: =O67/AL67 -> #DIV/0! | AO67: =IFERROR(Periods!AO67+Periods!AO183+Periods!AO299+Periods!AO415+Periods!AO531+Periods!AO647+Periods!AO763+Periods!AO879+Periods!AO995+Periods!AO1111+Periods!AO1227+Periods!AO1343, "-") -> 0 | AP67: =IFERROR(AVERAGE(Periods!AP67,Periods!AP183,Periods!AP299,Periods!AP415,Periods!AP531,Periods!AP647,Periods!AP763,Periods!AP879,Periods!AP995,Periods!AP1111,Periods!AP1227,Periods!AP1343), "-") -> - | AR67: =IFERROR(AH67/R67, "-") -> -
A68: 2026-2027 | B68: B2C | H68: =IFERROR(Periods!H68+Periods!H184+Periods!H300+Periods!H416+Periods!H532+Periods!H648+Periods!H764+Periods!H880+Periods!H996+Periods!H1112+Periods!H1228+Periods!H1344, "-") -> 0 | I68: =(M68*1.22)/R68 -> #DIV/0! | J68: =IFERROR(N68/M68-1,"-") -> - | K68: =I68*J68*H68 -> #DIV/0! | L68: =IFERROR(Periods!L68+Periods!L184+Periods!L300+Periods!L416+Periods!L532+Periods!L648+Periods!L764+Periods!L880+Periods!L996+Periods!L1112+Periods!L1228+Periods!L1344, "-") -> 0 | M68: =IFERROR(Periods!M68+Periods!M184+Periods!M300+Periods!M416+Periods!M532+Periods!M648+Periods!M764+Periods!M880+Periods!M996+Periods!M1112+Periods!M1228+Periods!M1344, "-") -> 0 | N68: =IFERROR(Periods!N68+Periods!N184+Periods!N300+Periods!N416+Periods!N532+Periods!N648+Periods!N764+Periods!N880+Periods!N996+Periods!N1112+Periods!N1228+Periods!N1344, "-") -> 0 | O68: =IFERROR(Periods!O68+Periods!O184+Periods!O300+Periods!O416+Periods!O532+Periods!O648+Periods!O764+Periods!O880+Periods!O996+Periods!O1112+Periods!O1228+Periods!O1344, "-") -> 0 | P68: =IFERROR(Periods!P68+Periods!P184+Periods!P300+Periods!P416+Periods!P532+Periods!P648+Periods!P764+Periods!P880+Periods!P996+Periods!P1112+Periods!P1228+Periods!P1344, "-") -> 0 | Q68: =IFERROR(R68/P68, "-") -> - | R68: =IFERROR(Periods!R68+Periods!R184+Periods!R300+Periods!R416+Periods!R532+Periods!R648+Periods!R764+Periods!R880+Periods!R996+Periods!R1112+Periods!R1228+Periods!R1344, "-") -> 0 | S68: =(ROUNDDOWN(O68/R68,0)) -> #DIV/0! | T68: =IFERROR(Periods!T68+Periods!T184+Periods!T300+Periods!T416+Periods!T532+Periods!T648+Periods!T764+Periods!T880+Periods!T996+Periods!T1112+Periods!T1228+Periods!T1344, "-") -> 0 | U68: =IFERROR(O68/T68, "-") -> - | V68: =IFERROR(R68/T68, "-") -> - | W68: =IFERROR(Periods!W68+Periods!W184+Periods!W300+Periods!W416+Periods!W532+Periods!W648+Periods!W764+Periods!W880+Periods!W996+Periods!W1112+Periods!W1228+Periods!W1344, "-") -> 0 | X68: =O68/W68 -> #DIV/0! | Y68: =W68/O68 -> #DIV/0! | Z68: =W68/T68 -> #DIV/0! | AA68: =IFERROR(Periods!AA68+Periods!AA184+Periods!AA300+Periods!AA416+Periods!AA532+Periods!AA648+Periods!AA764+Periods!AA880+Periods!AA996+Periods!AA1112+Periods!AA1228+Periods!AA1344, "-") -> 0 | AB68: =O68/AA68 -> #DIV/0! | AC68: =IFERROR(AA68/T68, "-") -> - | AD68: =IFERROR(Periods!AD68+Periods!AD184+Periods!AD300+Periods!AD416+Periods!AD532+Periods!AD648+Periods!AD764+Periods!AD880+Periods!AD996+Periods!AD1112+Periods!AD1228+Periods!AD1344, "-") -> 0 | AE68: =O68/AD68 -> #DIV/0! | AF68: =AD68/O68 -> #DIV/0! | AG68: =AD68/AA68 -> #DIV/0! | AH68: =IFERROR(Periods!AH68+Periods!AH184+Periods!AH300+Periods!AH416+Periods!AH532+Periods!AH648+Periods!AH764+Periods!AH880+Periods!AH996+Periods!AH1112+Periods!AH1228+Periods!AH1344, "-") -> 0 | AI68: =IFERROR(AVERAGE(Periods!AI68,Periods!AI184,Periods!AI300,Periods!AI416,Periods!AI532,Periods!AI648,Periods!AI764,Periods!AI880,Periods!AI996,Periods!AI1112,Periods!AI1228,Periods!AI1344), "-") -> - | AJ68: =IFERROR(Periods!AJ68+Periods!AJ184+Periods!AJ300+Periods!AJ416+Periods!AJ532+Periods!AJ648+Periods!AJ764+Periods!AJ880+Periods!AJ996+Periods!AJ1112+Periods!AJ1228+Periods!AJ1344, "-") -> 0 | AK68: =IFERROR(Periods!AK68+Periods!AK184+Periods!AK300+Periods!AK416+Periods!AK532+Periods!AK648+Periods!AK764+Periods!AK880+Periods!AK996+Periods!AK1112+Periods!AK1228+Periods!AK1344, "-") -> 0 | AL68: =AJ68+AK68 -> 0 | AM68: =AL68/AH68 -> #DIV/0! | AN68: =O68/AL68 -> #DIV/0! | AO68: =IFERROR(Periods!AO68+Periods!AO184+Periods!AO300+Periods!AO416+Periods!AO532+Periods!AO648+Periods!AO764+Periods!AO880+Periods!AO996+Periods!AO1112+Periods!AO1228+Periods!AO1344, "-") -> 0 | AP68: =IFERROR(AVERAGE(Periods!AP68,Periods!AP184,Periods!AP300,Periods!AP416,Periods!AP532,Periods!AP648,Periods!AP764,Periods!AP880,Periods!AP996,Periods!AP1112,Periods!AP1228,Periods!AP1344), "-") -> - | AR68: =IFERROR(AH68/R68, "-") -> -
A69: 2026-2027 | B69: B2C | H69: =IFERROR(Periods!H69+Periods!H185+Periods!H301+Periods!H417+Periods!H533+Periods!H649+Periods!H765+Periods!H881+Periods!H997+Periods!H1113+Periods!H1229+Periods!H1345, "-") -> 0 | I69: =(M69*1.22)/R69 -> #DIV/0! | J69: =IFERROR(N69/M69-1,"-") -> - | K69: =I69*J69*H69 -> #DIV/0! | L69: =IFERROR(Periods!L69+Periods!L185+Periods!L301+Periods!L417+Periods!L533+Periods!L649+Periods!L765+Periods!L881+Periods!L997+Periods!L1113+Periods!L1229+Periods!L1345, "-") -> 0 | M69: =IFERROR(Periods!M69+Periods!M185+Periods!M301+Periods!M417+Periods!M533+Periods!M649+Periods!M765+Periods!M881+Periods!M997+Periods!M1113+Periods!M1229+Periods!M1345, "-") -> 0 | N69: =IFERROR(Periods!N69+Periods!N185+Periods!N301+Periods!N417+Periods!N533+Periods!N649+Periods!N765+Periods!N881+Periods!N997+Periods!N1113+Periods!N1229+Periods!N1345, "-") -> 0 | O69: =IFERROR(Periods!O69+Periods!O185+Periods!O301+Periods!O417+Periods!O533+Periods!O649+Periods!O765+Periods!O881+Periods!O997+Periods!O1113+Periods!O1229+Periods!O1345, "-") -> 0 | P69: =IFERROR(Periods!P69+Periods!P185+Periods!P301+Periods!P417+Periods!P533+Periods!P649+Periods!P765+Periods!P881+Periods!P997+Periods!P1113+Periods!P1229+Periods!P1345, "-") -> 0 | Q69: =IFERROR(R69/P69, "-") -> - | R69: =IFERROR(Periods!R69+Periods!R185+Periods!R301+Periods!R417+Periods!R533+Periods!R649+Periods!R765+Periods!R881+Periods!R997+Periods!R1113+Periods!R1229+Periods!R1345, "-") -> 0 | S69: =(ROUNDDOWN(O69/R69,0)) -> #DIV/0! | T69: =IFERROR(Periods!T69+Periods!T185+Periods!T301+Periods!T417+Periods!T533+Periods!T649+Periods!T765+Periods!T881+Periods!T997+Periods!T1113+Periods!T1229+Periods!T1345, "-") -> 0 | U69: =IFERROR(O69/T69, "-") -> - | V69: =IFERROR(R69/T69, "-") -> - | W69: =IFERROR(Periods!W69+Periods!W185+Periods!W301+Periods!W417+Periods!W533+Periods!W649+Periods!W765+Periods!W881+Periods!W997+Periods!W1113+Periods!W1229+Periods!W1345, "-") -> 0 | X69: =O69/W69 -> #DIV/0! | Y69: =W69/O69 -> #DIV/0! | Z69: =W69/T69 -> #DIV/0! | AA69: =IFERROR(Periods!AA69+Periods!AA185+Periods!AA301+Periods!AA417+Periods!AA533+Periods!AA649+Periods!AA765+Periods!AA881+Periods!AA997+Periods!AA1113+Periods!AA1229+Periods!AA1345, "-") -> 0 | AB69: =O69/AA69 -> #DIV/0! | AC69: =IFERROR(AA69/T69, "-") -> - | AD69: =IFERROR(Periods!AD69+Periods!AD185+Periods!AD301+Periods!AD417+Periods!AD533+Periods!AD649+Periods!AD765+Periods!AD881+Periods!AD997+Periods!AD1113+Periods!AD1229+Periods!AD1345, "-") -> 0 | AE69: =O69/AD69 -> #DIV/0! | AF69: =AD69/O69 -> #DIV/0! | AG69: =AD69/AA69 -> #DIV/0! | AH69: =IFERROR(Periods!AH69+Periods!AH185+Periods!AH301+Periods!AH417+Periods!AH533+Periods!AH649+Periods!AH765+Periods!AH881+Periods!AH997+Periods!AH1113+Periods!AH1229+Periods!AH1345, "-") -> 0 | AI69: =IFERROR(AVERAGE(Periods!AI69,Periods!AI185,Periods!AI301,Periods!AI417,Periods!AI533,Periods!AI649,Periods!AI765,Periods!AI881,Periods!AI997,Periods!AI1113,Periods!AI1229,Periods!AI1345), "-") -> - | AJ69: =IFERROR(Periods!AJ69+Periods!AJ185+Periods!AJ301+Periods!AJ417+Periods!AJ533+Periods!AJ649+Periods!AJ765+Periods!AJ881+Periods!AJ997+Periods!AJ1113+Periods!AJ1229+Periods!AJ1345, "-") -> 0 | AK69: =IFERROR(Periods!AK69+Periods!AK185+Periods!AK301+Periods!AK417+Periods!AK533+Periods!AK649+Periods!AK765+Periods!AK881+Periods!AK997+Periods!AK1113+Periods!AK1229+Periods!AK1345, "-") -> 0 | AL69: =AJ69+AK69 -> 0 | AM69: =AL69/AH69 -> #DIV/0! | AN69: =O69/AL69 -> #DIV/0! | AO69: =IFERROR(Periods!AO69+Periods!AO185+Periods!AO301+Periods!AO417+Periods!AO533+Periods!AO649+Periods!AO765+Periods!AO881+Periods!AO997+Periods!AO1113+Periods!AO1229+Periods!AO1345, "-") -> 0 | AP69: =IFERROR(AVERAGE(Periods!AP69,Periods!AP185,Periods!AP301,Periods!AP417,Periods!AP533,Periods!AP649,Periods!AP765,Periods!AP881,Periods!AP997,Periods!AP1113,Periods!AP1229,Periods!AP1345), "-") -> - | AR69: =IFERROR(AH69/R69, "-") -> -
... A112: 2026-2027 | B112: B2C | H112: =IFERROR(Periods!H112+Periods!H228+Periods!H344+Periods!H460+Periods!H576+Periods!H692+Periods!H808+Periods!H924+Periods!H1040+Periods!H1156+Periods!H1272+Periods!H1388, "-") -> 0 | I112: =(M112*1.22)/R112 -> #DIV/0! | J112: =IFERROR(N112/M112-1,"-") -> - | K112: =I112*J112*H112 -> #DIV/0! | L112: =IFERROR(Periods!L112+Periods!L228+Periods!L344+Periods!L460+Periods!L576+Periods!L692+Periods!L808+Periods!L924+Periods!L1040+Periods!L1156+Periods!L1272+Periods!L1388, "-") -> 0 | M112: =IFERROR(Periods!M112+Periods!M228+Periods!M344+Periods!M460+Periods!M576+Periods!M692+Periods!M808+Periods!M924+Periods!M1040+Periods!M1156+Periods!M1272+Periods!M1388, "-") -> 0 | N112: =IFERROR(Periods!N112+Periods!N228+Periods!N344+Periods!N460+Periods!N576+Periods!N692+Periods!N808+Periods!N924+Periods!N1040+Periods!N1156+Periods!N1272+Periods!N1388, "-") -> 0 | O112: =IFERROR(Periods!O112+Periods!O228+Periods!O344+Periods!O460+Periods!O576+Periods!O692+Periods!O808+Periods!O924+Periods!O1040+Periods!O1156+Periods!O1272+Periods!O1388, "-") -> 0 | P112: =IFERROR(Periods!P112+Periods!P228+Periods!P344+Periods!P460+Periods!P576+Periods!P692+Periods!P808+Periods!P924+Periods!P1040+Periods!P1156+Periods!P1272+Periods!P1388, "-") -> 0 | Q112: =IFERROR(R112/P112, "-") -> - | R112: =IFERROR(Periods!R112+Periods!R228+Periods!R344+Periods!R460+Periods!R576+Periods!R692+Periods!R808+Periods!R924+Periods!R1040+Periods!R1156+Periods!R1272+Periods!R1388, "-") -> 0 | S112: =(ROUNDDOWN(O112/R112,0)) -> #DIV/0! | T112: =IFERROR(Periods!T112+Periods!T228+Periods!T344+Periods!T460+Periods!T576+Periods!T692+Periods!T808+Periods!T924+Periods!T1040+Periods!T1156+Periods!T1272+Periods!T1388, "-") -> 0 | U112: =IFERROR(O112/T112, "-") -> - | V112: =IFERROR(R112/T112, "-") -> - | W112: =IFERROR(Periods!W112+Periods!W228+Periods!W344+Periods!W460+Periods!W576+Periods!W692+Periods!W808+Periods!W924+Periods!W1040+Periods!W1156+Periods!W1272+Periods!W1388, "-") -> 0 | X112: =O112/W112 -> #DIV/0! | Y112: =W112/O112 -> #DIV/0! | Z112: =W112/T112 -> #DIV/0! | AA112: =IFERROR(Periods!AA112+Periods!AA228+Periods!AA344+Periods!AA460+Periods!AA576+Periods!AA692+Periods!AA808+Periods!AA924+Periods!AA1040+Periods!AA1156+Periods!AA1272+Periods!AA1388, "-") -> 0 | AB112: =O112/AA112 -> #DIV/0! | AC112: =IFERROR(AA112/T112, "-") -> - | AD112: =IFERROR(Periods!AD112+Periods!AD228+Periods!AD344+Periods!AD460+Periods!AD576+Periods!AD692+Periods!AD808+Periods!AD924+Periods!AD1040+Periods!AD1156+Periods!AD1272+Periods!AD1388, "-") -> 0 | AE112: =O112/AD112 -> #DIV/0! | AF112: =AD112/O112 -> #DIV/0! | AG112: =AD112/AA112 -> #DIV/0! | AH112: =IFERROR(Periods!AH112+Periods!AH228+Periods!AH344+Periods!AH460+Periods!AH576+Periods!AH692+Periods!AH808+Periods!AH924+Periods!AH1040+Periods!AH1156+Periods!AH1272+Periods!AH1388, "-") -> 0 | AI112: =IFERROR(AVERAGE(Periods!AI112,Periods!AI228,Periods!AI344,Periods!AI460,Periods!AI576,Periods!AI692,Periods!AI808,Periods!AI924,Periods!AI1040,Periods!AI1156,Periods!AI1272,Periods!AI1388), "-") -> - | AJ112: =IFERROR(Periods!AJ112+Periods!AJ228+Periods!AJ344+Periods!AJ460+Periods!AJ576+Periods!AJ692+Periods!AJ808+Periods!AJ924+Periods!AJ1040+Periods!AJ1156+Periods!AJ1272+Periods!AJ1388, "-") -> 0 | AK112: =IFERROR(Periods!AK112+Periods!AK228+Periods!AK344+Periods!AK460+Periods!AK576+Periods!AK692+Periods!AK808+Periods!AK924+Periods!AK1040+Periods!AK1156+Periods!AK1272+Periods!AK1388, "-") -> 0 | AL112: =AJ112+AK112 -> 0 | AM112: =AL112/AH112 -> #DIV/0! | AN112: =O112/AL112 -> #DIV/0! | AO112: =IFERROR(Periods!AO112+Periods!AO228+Periods!AO344+Periods!AO460+Periods!AO576+Periods!AO692+Periods!AO808+Periods!AO924+Periods!AO1040+Periods!AO1156+Periods!AO1272+Periods!AO1388, "-") -> 0 | AP112: =IFERROR(AVERAGE(Periods!AP112,Periods!AP228,Periods!AP344,Periods!AP460,Periods!AP576,Periods!AP692,Periods!AP808,Periods!AP924,Periods!AP1040,Periods!AP1156,Periods!AP1272,Periods!AP1388), "-") -> - | AR112: =IFERROR(AH112/R112, "-") -> -
A113: ИТОГО | B113: B2C | H113: =IFERROR(SUM(H58:H112),"-") -> 0 | I113: =IFERROR(SUM(I58:I112),"-") -> - | J113: =IFERROR(N113/M113-1,"-") -> - | K113: =IFERROR(N113-M113,"-") -> 0 | L113: =IFERROR(SUM(L58:L112),"-") -> 0 | M113: =IFERROR(SUM(M58:M112),"-") -> 0 | N113: =IFERROR(SUM(N58:N112),"-") -> 0 | O113: =IFERROR(SUM(O58:O112),"-") -> 0 | P113: =IFERROR(SUM(P58:P112),"-") -> 0 | Q113: =IFERROR(R113/P113, "-") -> - | R113: =IFERROR(SUM(R58:R112),"-") -> 0 | S113: =IFERROR(O113/R113, "-") -> - | T113: =IFERROR(SUM(T58:T112),"-") -> 0 | U113: =IFERROR(O113/T113, "-") -> - | V113: =IFERROR(R113/T113, "-") -> - | W113: =IFERROR(SUM(W58:W112),"-") -> 0 | X113: =IFERROR(O113/W113, "-") -> - | Y113: =IFERROR(W113/O113, "-") -> - | Z113: =IFERROR(W113/T113, "-") -> - | AA113: =SUM(AA58:AA112) -> 0 | AB113: =IFERROR(O113/AA113, "-") -> - | AC113: =IFERROR(AA113/T113, "-") -> - | AD113: =IFERROR(SUM(AD58:AD112),"-") -> 0 | AE113: =IFERROR(O113/AD113, "-") -> - | AF113: =IFERROR(AD113/O113, "-") -> - | AG113: =IFERROR(AD113/AA113, "-") -> - | AH113: =IFERROR(SUM(AH58:AH112),"-") -> 0 | AI113: =IFERROR(ROUND(AVERAGE(AI58:AI112),0),"-") -> - | AJ113: =IFERROR(SUM(AJ58:AJ112),"-") -> 0 | AK113: =IFERROR(SUM(AK58:AK112),"-") -> 0 | AL113: =IFERROR(AK113+AJ113,"-") -> 0 | AM113: =IFERROR(AL113/AH113, "-") -> - | AN113: =IFERROR(O113/AL113, "-") -> - | AO113: =IFERROR(SUM(AO58:AO112),"-") -> 0 | AP113: =IFERROR(AVERAGE(AP58:AP112),"-") -> - | AR113: =IFERROR(AH113/R113, "-") -> -
A114: ИТОГО | B114: 2026-2027 | H114: =IFERROR(H57+H113,"-") -> 0 | I114: =IFERROR(I57+I113,"-") -> - | J114: =IFERROR(N114/M114-1,"-") -> - | K114: =IFERROR(K57+K113,"-") -> 0 | L114: =IFERROR(L57+L113,"-") -> 0 | M114: =IFERROR(M57+M113,"-") -> 0 | N114: =IFERROR(N57+N113,"-") -> 0 | O114: =IFERROR(O57+O113,"-") -> 0 | P114: =IFERROR(P57+P113,"-") -> 0 | Q114: =IFERROR(R114/P114, "-") -> - | R114: =IFERROR(R57+R113,"-") -> 0 | S114: =IFERROR(O114/R114, "-") -> - | T114: =IFERROR(T57+T113,"-") -> 0 | U114: =IFERROR(O114/T114, "-") -> - | V114: =IFERROR(R114/T114, "-") -> - | W114: =IFERROR(W57+W113,"-") -> 0 | X114: =IFERROR(O114/W114, "-") -> - | Y114: =IFERROR(W114/O114, "-") -> - | Z114: =IFERROR(W114/T114, "-") -> - | AA114: =IFERROR(AA57+AA113,"-") -> 0 | AB114: =IFERROR(O114/AA114,"-") -> - | AC114: =IFERROR(AA114/T114, "-") -> - | AD114: =IFERROR(AD57+AD113,"-") -> 0 | AE114: =IFERROR(O114/AD114, "-") -> - | AF114: =IFERROR(AD114/O114, "-") -> - | AG114: =IFERROR(AD114/AA114, "-") -> - | AH114: =IFERROR(AH57+AH113,"-") -> 0 | AI114: =IFERROR(ROUND(AVERAGE(AI57,AI113),0),"-") -> - | AJ114: =IFERROR(AJ57+AJ113,"-") -> 0 | AK114: =IFERROR(AK57+AK113,"-") -> 0 | AL114: =IFERROR(AK114+AJ114,"-") -> 0 | AM114: =IFERROR(AL114/AH114, "-") -> - | AN114: =IFERROR(O114/AL114, "-") -> - | AO114: =IFERROR(AO57+AO113,"-") -> 0 | AP114: =IFERROR(AVERAGE(AP57,AP113),"-") -> - | AR114: =IFERROR(AH114/R114, "-") -> -

Sheet Periods
A1: Месяц+Год | B1: Тип клиента | C1: Площадка | D1: Формат | E1: Гео | F1: Модель закупки | G1: Единица закупки | H1: Кол-во единиц закупки | I1: Стоимость единицы закупки, руб. с НДС | J1: АК% | K1: АК, руб. (абс.) | L1: НДС, руб. (абс.) | M1: Тотал бюджет, руб. без НДС и АК | N1: Тотал бюджет, руб. без НДС и с учетом АК | O1: Тотал бюджет руб. с учетом НДС и АК | P1: Кол-во показов | Q1: CTR, % | R1: Кол-во кликов | S1: СРС, руб. с НДС | T1: Кол-во оформленных заказов | U1: Стоимость оформл. заказа, руб. с НДС | V1: CR (конверсия из клика в заказ), % | W1: Оформленный доход, руб. с НДС | X1: ДРР от оформл. дохода, % | Y1: ROAS офомл. (Доход/Бюджет) | Z1: Средний чек по оформл. доходу, с НДС | AA1: Кол-во отгруженных заказов | AB1: Стоимость отгр. заказа, руб. с НДС | AC1: CR 2 (конверсия из оформленного в отгруженный заказ), % | AD1: Выручка (отгруженный доход), руб. с НДС | AE1: ДРР от выручки, % | AF1: ROAS отгр. (Выручка/Бюджет) | AG1: Средний чек по выручке, с НДС | AH1: Кол-во клиентов | AI1: Частота заказа | AJ1: Кол-во абсолютно новых клиентов (ранее не заказывали) | AK1: Кол-во вернувшихся клиентов (не заказывали более 12 мес) | AL1: Кол-во новых клиентов (абсолютно новые + вернувшиеся) | AM1: Доля новых клиентов, % | AN1: САС, руб. | AO1: СРА: кол-во активных веб мастеров | AP1: СРА: % аппрува | AR1: СR из клика в клиента, %
A2: Май 2026 | B2: В2В | H2: =INT(P2*Q2) -> 0 | K2: =I2*J2*H2 -> 0 | L2: =0.22*M2 -> 0 | M2: =(H2*I2)/1.22 -> 0 | N2: =K2+M2 -> 0 | O2: =(H2*I2)+K2 -> 0 | R2: =(ROUNDDOWN(P2*Q2,0)) -> 0 | S2: =(ROUNDDOWN(O2/R2,0)) -> #DIV/0! | T2: =INT(R2*V2) -> 0 | U2: =O2/T2 -> #DIV/0! | W2: =T2*Z2 -> 0 | X2: =O2/W2 -> #DIV/0! | Y2: =W2/O2 -> #DIV/0! | AA2: =ROUNDDOWN(T2*AC2,0) -> 0 | AB2: =O2/AA2 -> #DIV/0! | AD2: =AA2*AG2 -> 0 | AE2: =O2/AD2 -> #DIV/0! | AF2: =AD2/O2 -> #DIV/0! | AH2: =ROUNDDOWN(AR2*R2,0) -> 0 | AL2: =AJ2+AK2 -> 0 | AM2: =AL2/AH2 -> #DIV/0! | AN2: =O2/AL2 -> #DIV/0!
A3: Май 2026 | B3: В2В | H3: =INT(P3*Q3) -> 0 | K3: =I3*J3*H3 -> 0 | L3: =0.22*M3 -> 0 | M3: =(H3*I3)/1.22 -> 0 | N3: =K3+M3 -> 0 | O3: =(H3*I3)+K3 -> 0 | R3: =(ROUNDDOWN(P3*Q3,0)) -> 0 | S3: =(ROUNDDOWN(O3/R3,0)) -> #DIV/0! | T3: =INT(R3*V3) -> 0 | U3: =O3/T3 -> #DIV/0! | W3: =T3*Z3 -> 0 | X3: =O3/W3 -> #DIV/0! | Y3: =W3/O3 -> #DIV/0! | AA3: =ROUNDDOWN(T3*AC3,0) -> 0 | AB3: =O3/AA3 -> #DIV/0! | AD3: =AA3*AG3 -> 0 | AE3: =O3/AD3 -> #DIV/0! | AF3: =AD3/O3 -> #DIV/0! | AH3: =ROUNDDOWN(AR3*R3,0) -> 0 | AL3: =AJ3+AK3 -> 0 | AM3: =AL3/AH3 -> #DIV/0! | AN3: =O3/AL3 -> #DIV/0!
A4: Май 2026 | B4: В2В | H4: =INT(P4*Q4) -> 0 | K4: =I4*J4*H4 -> 0 | L4: =0.22*M4 -> 0 | M4: =(H4*I4)/1.22 -> 0 | N4: =K4+M4 -> 0 | O4: =(H4*I4)+K4 -> 0 | R4: =(ROUNDDOWN(P4*Q4,0)) -> 0 | S4: =(ROUNDDOWN(O4/R4,0)) -> #DIV/0! | T4: =INT(R4*V4) -> 0 | U4: =O4/T4 -> #DIV/0! | W4: =T4*Z4 -> 0 | X4: =O4/W4 -> #DIV/0! | Y4: =W4/O4 -> #DIV/0! | AA4: =ROUNDDOWN(T4*AC4,0) -> 0 | AB4: =O4/AA4 -> #DIV/0! | AD4: =AA4*AG4 -> 0 | AE4: =O4/AD4 -> #DIV/0! | AF4: =AD4/O4 -> #DIV/0! | AH4: =ROUNDDOWN(AR4*R4,0) -> 0 | AL4: =AJ4+AK4 -> 0 | AM4: =AL4/AH4 -> #DIV/0! | AN4: =O4/AL4 -> #DIV/0!
A5: Май 2026 | B5: В2В | H5: =INT(P5*Q5) -> 0 | K5: =I5*J5*H5 -> 0 | L5: =0.22*M5 -> 0 | M5: =(H5*I5)/1.22 -> 0 | N5: =K5+M5 -> 0 | O5: =(H5*I5)+K5 -> 0 | R5: =(ROUNDDOWN(P5*Q5,0)) -> 0 | S5: =(ROUNDDOWN(O5/R5,0)) -> #DIV/0! | T5: =INT(R5*V5) -> 0 | U5: =O5/T5 -> #DIV/0! | W5: =T5*Z5 -> 0 | X5: =O5/W5 -> #DIV/0! | Y5: =W5/O5 -> #DIV/0! | AA5: =ROUNDDOWN(T5*AC5,0) -> 0 | AB5: =O5/AA5 -> #DIV/0! | AD5: =AA5*AG5 -> 0 | AE5: =O5/AD5 -> #DIV/0! | AF5: =AD5/O5 -> #DIV/0! | AH5: =ROUNDDOWN(AR5*R5,0) -> 0 | AL5: =AJ5+AK5 -> 0 | AM5: =AL5/AH5 -> #DIV/0! | AN5: =O5/AL5 -> #DIV/0!
A6: Май 2026 | B6: В2В | H6: =INT(P6*Q6) -> 0 | K6: =I6*J6*H6 -> 0 | L6: =0.22*M6 -> 0 | M6: =(H6*I6)/1.22 -> 0 | N6: =K6+M6 -> 0 | O6: =(H6*I6)+K6 -> 0 | R6: =(ROUNDDOWN(P6*Q6,0)) -> 0 | S6: =(ROUNDDOWN(O6/R6,0)) -> #DIV/0! | T6: =INT(R6*V6) -> 0 | U6: =O6/T6 -> #DIV/0! | W6: =T6*Z6 -> 0 | X6: =O6/W6 -> #DIV/0! | Y6: =W6/O6 -> #DIV/0! | AA6: =ROUNDDOWN(T6*AC6,0) -> 0 | AB6: =O6/AA6 -> #DIV/0! | AD6: =AA6*AG6 -> 0 | AE6: =O6/AD6 -> #DIV/0! | AF6: =AD6/O6 -> #DIV/0! | AH6: =ROUNDDOWN(AR6*R6,0) -> 0 | AL6: =AJ6+AK6 -> 0 | AM6: =AL6/AH6 -> #DIV/0! | AN6: =O6/AL6 -> #DIV/0!
A7: Май 2026 | B7: В2В | H7: =INT(P7*Q7) -> 0 | K7: =I7*J7*H7 -> 0 | L7: =0.22*M7 -> 0 | M7: =(H7*I7)/1.22 -> 0 | N7: =K7+M7 -> 0 | O7: =(H7*I7)+K7 -> 0 | R7: =(ROUNDDOWN(P7*Q7,0)) -> 0 | S7: =(ROUNDDOWN(O7/R7,0)) -> #DIV/0! | T7: =INT(R7*V7) -> 0 | U7: =O7/T7 -> #DIV/0! | W7: =T7*Z7 -> 0 | X7: =O7/W7 -> #DIV/0! | Y7: =W7/O7 -> #DIV/0! | AA7: =ROUNDDOWN(T7*AC7,0) -> 0 | AB7: =O7/AA7 -> #DIV/0! | AD7: =AA7*AG7 -> 0 | AE7: =O7/AD7 -> #DIV/0! | AF7: =AD7/O7 -> #DIV/0! | AH7: =ROUNDDOWN(AR7*R7,0) -> 0 | AL7: =AJ7+AK7 -> 0 | AM7: =AL7/AH7 -> #DIV/0! | AN7: =O7/AL7 -> #DIV/0!
A8: Май 2026 | B8: В2В | H8: =INT(P8*Q8) -> 0 | K8: =I8*J8*H8 -> 0 | L8: =0.22*M8 -> 0 | M8: =(H8*I8)/1.22 -> 0 | N8: =K8+M8 -> 0 | O8: =(H8*I8)+K8 -> 0 | R8: =(ROUNDDOWN(P8*Q8,0)) -> 0 | S8: =(ROUNDDOWN(O8/R8,0)) -> #DIV/0! | T8: =INT(R8*V8) -> 0 | U8: =O8/T8 -> #DIV/0! | W8: =T8*Z8 -> 0 | X8: =O8/W8 -> #DIV/0! | Y8: =W8/O8 -> #DIV/0! | AA8: =ROUNDDOWN(T8*AC8,0) -> 0 | AB8: =O8/AA8 -> #DIV/0! | AD8: =AA8*AG8 -> 0 | AE8: =O8/AD8 -> #DIV/0! | AF8: =AD8/O8 -> #DIV/0! | AH8: =ROUNDDOWN(AR8*R8,0) -> 0 | AL8: =AJ8+AK8 -> 0 | AM8: =AL8/AH8 -> #DIV/0! | AN8: =O8/AL8 -> #DIV/0!
A9: Май 2026 | B9: В2В | H9: =INT(P9*Q9) -> 0 | K9: =I9*J9*H9 -> 0 | L9: =0.22*M9 -> 0 | M9: =(H9*I9)/1.22 -> 0 | N9: =K9+M9 -> 0 | O9: =(H9*I9)+K9 -> 0 | R9: =(ROUNDDOWN(P9*Q9,0)) -> 0 | S9: =(ROUNDDOWN(O9/R9,0)) -> #DIV/0! | T9: =INT(R9*V9) -> 0 | U9: =O9/T9 -> #DIV/0! | W9: =T9*Z9 -> 0 | X9: =O9/W9 -> #DIV/0! | Y9: =W9/O9 -> #DIV/0! | AA9: =ROUNDDOWN(T9*AC9,0) -> 0 | AB9: =O9/AA9 -> #DIV/0! | AD9: =AA9*AG9 -> 0 | AE9: =O9/AD9 -> #DIV/0! | AF9: =AD9/O9 -> #DIV/0! | AH9: =ROUNDDOWN(AR9*R9,0) -> 0 | AL9: =AJ9+AK9 -> 0 | AM9: =AL9/AH9 -> #DIV/0! | AN9: =O9/AL9 -> #DIV/0!
A10: Май 2026 | B10: В2В | H10: =INT(P10*Q10) -> 0 | K10: =I10*J10*H10 -> 0 | L10: =0.22*M10 -> 0 | M10: =(H10*I10)/1.22 -> 0 | N10: =K10+M10 -> 0 | O10: =(H10*I10)+K10 -> 0 | R10: =(ROUNDDOWN(P10*Q10,0)) -> 0 | S10: =(ROUNDDOWN(O10/R10,0)) -> #DIV/0! | T10: =INT(R10*V10) -> 0 | U10: =O10/T10 -> #DIV/0! | W10: =T10*Z10 -> 0 | X10: =O10/W10 -> #DIV/0! | Y10: =W10/O10 -> #DIV/0! | AA10: =ROUNDDOWN(T10*AC10,0) -> 0 | AB10: =O10/AA10 -> #DIV/0! | AD10: =AA10*AG10 -> 0 | AE10: =O10/AD10 -> #DIV/0! | AF10: =AD10/O10 -> #DIV/0! | AH10: =ROUNDDOWN(AR10*R10,0) -> 0 | AL10: =AJ10+AK10 -> 0 | AM10: =AL10/AH10 -> #DIV/0! | AN10: =O10/AL10 -> #DIV/0!
A11: Май 2026 | B11: В2В | H11: =INT(P11*Q11) -> 0 | K11: =I11*J11*H11 -> 0 | L11: =0.22*M11 -> 0 | M11: =(H11*I11)/1.22 -> 0 | N11: =K11+M11 -> 0 | O11: =(H11*I11)+K11 -> 0 | R11: =(ROUNDDOWN(P11*Q11,0)) -> 0 | S11: =(ROUNDDOWN(O11/R11,0)) -> #DIV/0! | T11: =INT(R11*V11) -> 0 | U11: =O11/T11 -> #DIV/0! | W11: =T11*Z11 -> 0 | X11: =O11/W11 -> #DIV/0! | Y11: =W11/O11 -> #DIV/0! | AA11: =ROUNDDOWN(T11*AC11,0) -> 0 | AB11: =O11/AA11 -> #DIV/0! | AD11: =AA11*AG11 -> 0 | AE11: =O11/AD11 -> #DIV/0! | AF11: =AD11/O11 -> #DIV/0! | AH11: =ROUNDDOWN(AR11*R11,0) -> 0 | AL11: =AJ11+AK11 -> 0 | AM11: =AL11/AH11 -> #DIV/0! | AN11: =O11/AL11 -> #DIV/0!
A12: Май 2026 | B12: В2В | H12: =INT(P12*Q12) -> 0 | K12: =I12*J12*H12 -> 0 | L12: =0.22*M12 -> 0 | M12: =(H12*I12)/1.22 -> 0 | N12: =K12+M12 -> 0 | O12: =(H12*I12)+K12 -> 0 | R12: =(ROUNDDOWN(P12*Q12,0)) -> 0 | S12: =(ROUNDDOWN(O12/R12,0)) -> #DIV/0! | T12: =INT(R12*V12) -> 0 | U12: =O12/T12 -> #DIV/0! | W12: =T12*Z12 -> 0 | X12: =O12/W12 -> #DIV/0! | Y12: =W12/O12 -> #DIV/0! | AA12: =ROUNDDOWN(T12*AC12,0) -> 0 | AB12: =O12/AA12 -> #DIV/0! | AD12: =AA12*AG12 -> 0 | AE12: =O12/AD12 -> #DIV/0! | AF12: =AD12/O12 -> #DIV/0! | AH12: =ROUNDDOWN(AR12*R12,0) -> 0 | AL12: =AJ12+AK12 -> 0 | AM12: =AL12/AH12 -> #DIV/0! | AN12: =O12/AL12 -> #DIV/0!
A13: Май 2026 | B13: В2В | H13: =INT(P13*Q13) -> 0 | K13: =I13*J13*H13 -> 0 | L13: =0.22*M13 -> 0 | M13: =(H13*I13)/1.22 -> 0 | N13: =K13+M13 -> 0 | O13: =(H13*I13)+K13 -> 0 | R13: =(ROUNDDOWN(P13*Q13,0)) -> 0 | S13: =(ROUNDDOWN(O13/R13,0)) -> #DIV/0! | T13: =INT(R13*V13) -> 0 | U13: =O13/T13 -> #DIV/0! | W13: =T13*Z13 -> 0 | X13: =O13/W13 -> #DIV/0! | Y13: =W13/O13 -> #DIV/0! | AA13: =ROUNDDOWN(T13*AC13,0) -> 0 | AB13: =O13/AA13 -> #DIV/0! | AD13: =AA13*AG13 -> 0 | AE13: =O13/AD13 -> #DIV/0! | AF13: =AD13/O13 -> #DIV/0! | AH13: =ROUNDDOWN(AR13*R13,0) -> 0 | AL13: =AJ13+AK13 -> 0 | AM13: =AL13/AH13 -> #DIV/0! | AN13: =O13/AL13 -> #DIV/0!
... A56: Май 2026 | B56: В2В | H56: =INT(P56*Q56) -> 0 | K56: =I56*J56*H56 -> 0 | L56: =0.22*M56 -> 0 | M56: =(H56*I56)/1.22 -> 0 | N56: =K56+M56 -> 0 | O56: =(H56*I56)+K56 -> 0 | R56: =(ROUNDDOWN(P56*Q56,0)) -> 0 | S56: =(ROUNDDOWN(O56/R56,0)) -> #DIV/0! | T56: =INT(R56*V56) -> 0 | U56: =O56/T56 -> #DIV/0! | W56: =T56*Z56 -> 0 | X56: =O56/W56 -> #DIV/0! | Y56: =W56/O56 -> #DIV/0! | AA56: =ROUNDDOWN(T56*AC56,0) -> 0 | AB56: =O56/AA56 -> #DIV/0! | AD56: =AA56*AG56 -> 0 | AE56: =O56/AD56 -> #DIV/0! | AF56: =AD56/O56 -> #DIV/0! | AH56: =ROUNDDOWN(AR56*R56,0) -> 0 | AL56: =AJ56+AK56 -> 0 | AM56: =AL56/AH56 -> #DIV/0! | AN56: =O56/AL56 -> #DIV/0!
A57: ИТОГО | B57: B2B | H57: =IFERROR(SUM(H2:H56),"-") -> 0 | I57: =IFERROR(SUM(I2:I56),"-") -> 0 | J57: =IFERROR(N57/M57-1,"-") -> - | K57: =IFERROR(N57-M57,"-") -> 0 | L57: =IFERROR(SUM(L2:L56),"-") -> 0 | M57: =IFERROR(SUM(M2:M56),"-") -> 0 | N57: =IFERROR(SUM(N2:N56),"-") -> 0 | O57: =IFERROR(SUM(O2:O56),"-") -> 0 | P57: =IFERROR(SUM(P2:P56),"-") -> 0 | Q57: =IFERROR(R57/P57, "-") -> - | R57: =IFERROR(SUM(R2:R56),"-") -> 0 | S57: =IFERROR(O57/R57, "-") -> - | T57: =IFERROR(SUM(T2:T56),"-") -> 0 | U57: =IFERROR(O57/T57, "-") -> - | V57: =IFERROR(R57/T57, "-") -> - | W57: =IFERROR(SUM(W2:W56),"-") -> 0 | X57: =IFERROR(O57/W57, "-") -> - | Y57: =IFERROR(W57/O57, "-") -> - | Z57: =IFERROR(W57/T57, "-") -> - | AA57: =IFERROR(SUM(AA2:AA56),"-") -> 0 | AB57: =IFERROR(O57/AA57, "-") -> - | AC57: =IFERROR(AA57/T57, "-") -> - | AD57: =IFERROR(SUM(AD2:AD56),"-") -> 0 | AE57: =IFERROR(O57/AD57, "-") -> - | AF57: =IFERROR(AD57/O57, "-") -> - | AG57: =IFERROR(AD57/AA57, "-") -> - | AH57: =IFERROR(SUM(AH2:AH56),"-") -> 0 | AI57: =IFERROR(ROUND(AVERAGE(AI2:AI56),0),"-") -> - | AJ57: =IFERROR(SUM(AJ2:AJ56),"-") -> 0 | AK57: =IFERROR(SUM(AK2:AK56),"-") -> 0 | AL57: =IFERROR(AK57+AJ57,"-") -> 0 | AM57: =IFERROR(AL57/AH57, "-") -> - | AN57: =IFERROR(O57/AL57, "-") -> - | AO57: =IFERROR(SUM(AO2:AO56),"-") -> 0 | AP57: =IFERROR(AVERAGE(AP2:AP56),"-") -> - | AR57: =IFERROR(AH57/R57, "-") -> -
A58: Май 2026 | B58: B2C | H58: =INT(P58*Q58) -> 0 | K58: =I58*J58*H58 -> 0 | L58: =0.22*M58 -> 0 | M58: =(H58*I58)/1.22 -> 0 | N58: =K58+M58 -> 0 | O58: =(H58*I58)+K58 -> 0 | R58: =(ROUNDDOWN(P58*Q58,0)) -> 0 | S58: =(ROUNDDOWN(O58/R58,0)) -> #DIV/0! | T58: =INT(R58*V58) -> 0 | U58: =O58/T58 -> #DIV/0! | W58: =T58*Z58 -> 0 | X58: =O58/W58 -> #DIV/0! | Y58: =W58/O58 -> #DIV/0! | AA58: =ROUNDDOWN(T58*AC58,0) -> 0 | AB58: =O58/AA58 -> #DIV/0! | AD58: =AA58*AG58 -> 0 | AE58: =O58/AD58 -> #DIV/0! | AF58: =AD58/O58 -> #DIV/0! | AH58: =ROUNDDOWN(AR58*R58,0) -> 0 | AL58: =AJ58+AK58 -> 0 | AM58: =AL58/AH58 -> #DIV/0! | AN58: =O58/AL58 -> #DIV/0!
A59: Май 2026 | B59: B2C | H59: =INT(P59*Q59) -> 0 | K59: =I59*J59*H59 -> 0 | L59: =0.22*M59 -> 0 | M59: =(H59*I59)/1.22 -> 0 | N59: =K59+M59 -> 0 | O59: =(H59*I59)+K59 -> 0 | R59: =(ROUNDDOWN(P59*Q59,0)) -> 0 | S59: =(ROUNDDOWN(O59/R59,0)) -> #DIV/0! | T59: =INT(R59*V59) -> 0 | U59: =O59/T59 -> #DIV/0! | W59: =T59*Z59 -> 0 | X59: =O59/W59 -> #DIV/0! | Y59: =W59/O59 -> #DIV/0! | AA59: =ROUNDDOWN(T59*AC59,0) -> 0 | AB59: =O59/AA59 -> #DIV/0! | AD59: =AA59*AG59 -> 0 | AE59: =O59/AD59 -> #DIV/0! | AF59: =AD59/O59 -> #DIV/0! | AH59: =ROUNDDOWN(AR59*R59,0) -> 0 | AL59: =AJ59+AK59 -> 0 | AM59: =AL59/AH59 -> #DIV/0! | AN59: =O59/AL59 -> #DIV/0!
A60: Май 2026 | B60: B2C | H60: =INT(P60*Q60) -> 0 | K60: =I60*J60*H60 -> 0 | L60: =0.22*M60 -> 0 | M60: =(H60*I60)/1.22 -> 0 | N60: =K60+M60 -> 0 | O60: =(H60*I60)+K60 -> 0 | R60: =(ROUNDDOWN(P60*Q60,0)) -> 0 | S60: =(ROUNDDOWN(O60/R60,0)) -> #DIV/0! | T60: =INT(R60*V60) -> 0 | U60: =O60/T60 -> #DIV/0! | W60: =T60*Z60 -> 0 | X60: =O60/W60 -> #DIV/0! | Y60: =W60/O60 -> #DIV/0! | AA60: =ROUNDDOWN(T60*AC60,0) -> 0 | AB60: =O60/AA60 -> #DIV/0! | AD60: =AA60*AG60 -> 0 | AE60: =O60/AD60 -> #DIV/0! | AF60: =AD60/O60 -> #DIV/0! | AH60: =ROUNDDOWN(AR60*R60,0) -> 0 | AL60: =AJ60+AK60 -> 0 | AM60: =AL60/AH60 -> #DIV/0! | AN60: =O60/AL60 -> #DIV/0!
A61: Май 2026 | B61: B2C | H61: =INT(P61*Q61) -> 0 | K61: =I61*J61*H61 -> 0 | L61: =0.22*M61 -> 0 | M61: =(H61*I61)/1.22 -> 0 | N61: =K61+M61 -> 0 | O61: =(H61*I61)+K61 -> 0 | R61: =(ROUNDDOWN(P61*Q61,0)) -> 0 | S61: =(ROUNDDOWN(O61/R61,0)) -> #DIV/0! | T61: =INT(R61*V61) -> 0 | U61: =O61/T61 -> #DIV/0! | W61: =T61*Z61 -> 0 | X61: =O61/W61 -> #DIV/0! | Y61: =W61/O61 -> #DIV/0! | AA61: =ROUNDDOWN(T61*AC61,0) -> 0 | AB61: =O61/AA61 -> #DIV/0! | AD61: =AA61*AG61 -> 0 | AE61: =O61/AD61 -> #DIV/0! | AF61: =AD61/O61 -> #DIV/0! | AH61: =ROUNDDOWN(AR61*R61,0) -> 0 | AL61: =AJ61+AK61 -> 0 | AM61: =AL61/AH61 -> #DIV/0! | AN61: =O61/AL61 -> #DIV/0!
A62: Май 2026 | B62: B2C | H62: =INT(P62*Q62) -> 0 | K62: =I62*J62*H62 -> 0 | L62: =0.22*M62 -> 0 | M62: =(H62*I62)/1.22 -> 0 | N62: =K62+M62 -> 0 | O62: =(H62*I62)+K62 -> 0 | R62: =(ROUNDDOWN(P62*Q62,0)) -> 0 | S62: =(ROUNDDOWN(O62/R62,0)) -> #DIV/0! | T62: =INT(R62*V62) -> 0 | U62: =O62/T62 -> #DIV/0! | W62: =T62*Z62 -> 0 | X62: =O62/W62 -> #DIV/0! | Y62: =W62/O62 -> #DIV/0! | AA62: =ROUNDDOWN(T62*AC62,0) -> 0 | AB62: =O62/AA62 -> #DIV/0! | AD62: =AA62*AG62 -> 0 | AE62: =O62/AD62 -> #DIV/0! | AF62: =AD62/O62 -> #DIV/0! | AH62: =ROUNDDOWN(AR62*R62,0) -> 0 | AL62: =AJ62+AK62 -> 0 | AM62: =AL62/AH62 -> #DIV/0! | AN62: =O62/AL62 -> #DIV/0!
A63: Май 2026 | B63: B2C | H63: =INT(P63*Q63) -> 0 | K63: =I63*J63*H63 -> 0 | L63: =0.22*M63 -> 0 | M63: =(H63*I63)/1.22 -> 0 | N63: =K63+M63 -> 0 | O63: =(H63*I63)+K63 -> 0 | R63: =(ROUNDDOWN(P63*Q63,0)) -> 0 | S63: =(ROUNDDOWN(O63/R63,0)) -> #DIV/0! | T63: =INT(R63*V63) -> 0 | U63: =O63/T63 -> #DIV/0! | W63: =T63*Z63 -> 0 | X63: =O63/W63 -> #DIV/0! | Y63: =W63/O63 -> #DIV/0! | AA63: =ROUNDDOWN(T63*AC63,0) -> 0 | AB63: =O63/AA63 -> #DIV/0! | AD63: =AA63*AG63 -> 0 | AE63: =O63/AD63 -> #DIV/0! | AF63: =AD63/O63 -> #DIV/0! | AH63: =ROUNDDOWN(AR63*R63,0) -> 0 | AL63: =AJ63+AK63 -> 0 | AM63: =AL63/AH63 -> #DIV/0! | AN63: =O63/AL63 -> #DIV/0!
A64: Май 2026 | B64: B2C | H64: =INT(P64*Q64) -> 0 | K64: =I64*J64*H64 -> 0 | L64: =0.22*M64 -> 0 | M64: =(H64*I64)/1.22 -> 0 | N64: =K64+M64 -> 0 | O64: =(H64*I64)+K64 -> 0 | R64: =(ROUNDDOWN(P64*Q64,0)) -> 0 | S64: =(ROUNDDOWN(O64/R64,0)) -> #DIV/0! | T64: =INT(R64*V64) -> 0 | U64: =O64/T64 -> #DIV/0! | W64: =T64*Z64 -> 0 | X64: =O64/W64 -> #DIV/0! | Y64: =W64/O64 -> #DIV/0! | AA64: =ROUNDDOWN(T64*AC64,0) -> 0 | AB64: =O64/AA64 -> #DIV/0! | AD64: =AA64*AG64 -> 0 | AE64: =O64/AD64 -> #DIV/0! | AF64: =AD64/O64 -> #DIV/0! | AH64: =ROUNDDOWN(AR64*R64,0) -> 0 | AL64: =AJ64+AK64 -> 0 | AM64: =AL64/AH64 -> #DIV/0! | AN64: =O64/AL64 -> #DIV/0!
A65: Май 2026 | B65: B2C | H65: =INT(P65*Q65) -> 0 | K65: =I65*J65*H65 -> 0 | L65: =0.22*M65 -> 0 | M65: =(H65*I65)/1.22 -> 0 | N65: =K65+M65 -> 0 | O65: =(H65*I65)+K65 -> 0 | R65: =(ROUNDDOWN(P65*Q65,0)) -> 0 | S65: =(ROUNDDOWN(O65/R65,0)) -> #DIV/0! | T65: =INT(R65*V65) -> 0 | U65: =O65/T65 -> #DIV/0! | W65: =T65*Z65 -> 0 | X65: =O65/W65 -> #DIV/0! | Y65: =W65/O65 -> #DIV/0! | AA65: =ROUNDDOWN(T65*AC65,0) -> 0 | AB65: =O65/AA65 -> #DIV/0! | AD65: =AA65*AG65 -> 0 | AE65: =O65/AD65 -> #DIV/0! | AF65: =AD65/O65 -> #DIV/0! | AH65: =ROUNDDOWN(AR65*R65,0) -> 0 | AL65: =AJ65+AK65 -> 0 | AM65: =AL65/AH65 -> #DIV/0! | AN65: =O65/AL65 -> #DIV/0!
A66: Май 2026 | B66: B2C | H66: =INT(P66*Q66) -> 0 | K66: =I66*J66*H66 -> 0 | L66: =0.22*M66 -> 0 | M66: =(H66*I66)/1.22 -> 0 | N66: =K66+M66 -> 0 | O66: =(H66*I66)+K66 -> 0 | R66: =(ROUNDDOWN(P66*Q66,0)) -> 0 | S66: =(ROUNDDOWN(O66/R66,0)) -> #DIV/0! | T66: =INT(R66*V66) -> 0 | U66: =O66/T66 -> #DIV/0! | W66: =T66*Z66 -> 0 | X66: =O66/W66 -> #DIV/0! | Y66: =W66/O66 -> #DIV/0! | AA66: =ROUNDDOWN(T66*AC66,0) -> 0 | AB66: =O66/AA66 -> #DIV/0! | AD66: =AA66*AG66 -> 0 | AE66: =O66/AD66 -> #DIV/0! | AF66: =AD66/O66 -> #DIV/0! | AH66: =ROUNDDOWN(AR66*R66,0) -> 0 | AL66: =AJ66+AK66 -> 0 | AM66: =AL66/AH66 -> #DIV/0! | AN66: =O66/AL66 -> #DIV/0!
A67: Май 2026 | B67: B2C | H67: =INT(P67*Q67) -> 0 | K67: =I67*J67*H67 -> 0 | L67: =0.22*M67 -> 0 | M67: =(H67*I67)/1.22 -> 0 | N67: =K67+M67 -> 0 | O67: =(H67*I67)+K67 -> 0 | R67: =(ROUNDDOWN(P67*Q67,0)) -> 0 | S67: =(ROUNDDOWN(O67/R67,0)) -> #DIV/0! | T67: =INT(R67*V67) -> 0 | U67: =O67/T67 -> #DIV/0! | W67: =T67*Z67 -> 0 | X67: =O67/W67 -> #DIV/0! | Y67: =W67/O67 -> #DIV/0! | AA67: =ROUNDDOWN(T67*AC67,0) -> 0 | AB67: =O67/AA67 -> #DIV/0! | AD67: =AA67*AG67 -> 0 | AE67: =O67/AD67 -> #DIV/0! | AF67: =AD67/O67 -> #DIV/0! | AH67: =ROUNDDOWN(AR67*R67,0) -> 0 | AL67: =AJ67+AK67 -> 0 | AM67: =AL67/AH67 -> #DIV/0! | AN67: =O67/AL67 -> #DIV/0!
A68: Май 2026 | B68: B2C | H68: =INT(P68*Q68) -> 0 | K68: =I68*J68*H68 -> 0 | L68: =0.22*M68 -> 0 | M68: =(H68*I68)/1.22 -> 0 | N68: =K68+M68 -> 0 | O68: =(H68*I68)+K68 -> 0 | R68: =(ROUNDDOWN(P68*Q68,0)) -> 0 | S68: =(ROUNDDOWN(O68/R68,0)) -> #DIV/0! | T68: =INT(R68*V68) -> 0 | U68: =O68/T68 -> #DIV/0! | W68: =T68*Z68 -> 0 | X68: =O68/W68 -> #DIV/0! | Y68: =W68/O68 -> #DIV/0! | AA68: =ROUNDDOWN(T68*AC68,0) -> 0 | AB68: =O68/AA68 -> #DIV/0! | AD68: =AA68*AG68 -> 0 | AE68: =O68/AD68 -> #DIV/0! | AF68: =AD68/O68 -> #DIV/0! | AH68: =ROUNDDOWN(AR68*R68,0) -> 0 | AL68: =AJ68+AK68 -> 0 | AM68: =AL68/AH68 -> #DIV/0! | AN68: =O68/AL68 -> #DIV/0!
A69: Май 2026 | B69: B2C | H69: =INT(P69*Q69) -> 0 | K69: =I69*J69*H69 -> 0 | L69: =0.22*M69 -> 0 | M69: =(H69*I69)/1.22 -> 0 | N69: =K69+M69 -> 0 | O69: =(H69*I69)+K69 -> 0 | R69: =(ROUNDDOWN(P69*Q69,0)) -> 0 | S69: =(ROUNDDOWN(O69/R69,0)) -> #DIV/0! | T69: =INT(R69*V69) -> 0 | U69: =O69/T69 -> #DIV/0! | W69: =T69*Z69 -> 0 | X69: =O69/W69 -> #DIV/0! | Y69: =W69/O69 -> #DIV/0! | AA69: =ROUNDDOWN(T69*AC69,0) -> 0 | AB69: =O69/AA69 -> #DIV/0! | AD69: =AA69*AG69 -> 0 | AE69: =O69/AD69 -> #DIV/0! | AF69: =AD69/O69 -> #DIV/0! | AH69: =ROUNDDOWN(AR69*R69,0) -> 0 | AL69: =AJ69+AK69 -> 0 | AM69: =AL69/AH69 -> #DIV/0! | AN69: =O69/AL69 -> #DIV/0!
... A112: Май 2026 | B112: B2C | H112: =INT(P112*Q112) -> 0 | K112: =I112*J112*H112 -> 0 | L112: =0.22*M112 -> 0 | M112: =(H112*I112)/1.22 -> 0 | N112: =K112+M112 -> 0 | O112: =(H112*I112)+K112 -> 0 | R112: =(ROUNDDOWN(P112*Q112,0)) -> 0 | S112: =(ROUNDDOWN(O112/R112,0)) -> #DIV/0! | T112: =INT(R112*V112) -> 0 | U112: =O112/T112 -> #DIV/0! | W112: =T112*Z112 -> 0 | X112: =O112/W112 -> #DIV/0! | Y112: =W112/O112 -> #DIV/0! | AA112: =ROUNDDOWN(T112*AC112,0) -> 0 | AB112: =O112/AA112 -> #DIV/0! | AD112: =AA112*AG112 -> 0 | AE112: =O112/AD112 -> #DIV/0! | AF112: =AD112/O112 -> #DIV/0! | AH112: =ROUNDDOWN(AR112*R112,0) -> 0 | AL112: =AJ112+AK112 -> 0 | AM112: =AL112/AH112 -> #DIV/0! | AN112: =O112/AL112 -> #DIV/0!
A113: ИТОГО | B113: B2C | H113: =IFERROR(SUM(H58:H112),"-") -> 0 | I113: =IFERROR(SUM(I58:I112),"-") -> 0 | J113: =IFERROR(N113/M113-1,"-") -> - | K113: =IFERROR(N113-M113,"-") -> 0 | L113: =IFERROR(SUM(L58:L112),"-") -> 0 | M113: =IFERROR(SUM(M58:M112),"-") -> 0 | N113: =IFERROR(SUM(N58:N112),"-") -> 0 | O113: =IFERROR(SUM(O58:O112),"-") -> 0 | P113: =IFERROR(SUM(P58:P112),"-") -> 0 | Q113: =IFERROR(R113/P113, "-") -> - | R113: =IFERROR(SUM(R58:R112),"-") -> 0 | S113: =IFERROR(O113/R113, "-") -> - | T113: =IFERROR(SUM(T58:T112),"-") -> 0 | U113: =IFERROR(O113/T113, "-") -> - | V113: =IFERROR(R113/T113, "-") -> - | W113: =IFERROR(SUM(W58:W112),"-") -> 0 | X113: =IFERROR(O113/W113, "-") -> - | Y113: =IFERROR(W113/O113, "-") -> - | Z113: =IFERROR(W113/T113, "-") -> - | AA113: =SUM(AA58:AA112) -> 0 | AB113: =IFERROR(O113/AA113, "-") -> - | AC113: =IFERROR(AA113/T113, "-") -> - | AD113: =IFERROR(SUM(AD58:AD112),"-") -> 0 | AE113: =IFERROR(O113/AD113, "-") -> - | AF113: =IFERROR(AD113/O113, "-") -> - | AG113: =IFERROR(AD113/AA113, "-") -> - | AH113: =IFERROR(SUM(AH58:AH112),"-") -> 0 | AI113: =IFERROR(ROUND(AVERAGE(AI58:AI112),0),"-") -> - | AJ113: =IFERROR(SUM(AJ58:AJ112),"-") -> 0 | AK113: =IFERROR(SUM(AK58:AK112),"-") -> 0 | AL113: =IFERROR(AK113+AJ113,"-") -> 0 | AM113: =IFERROR(AL113/AH113, "-") -> - | AN113: =IFERROR(O113/AL113, "-") -> - | AO113: =IFERROR(SUM(AO58:AO112),"-") -> 0 | AP113: =IFERROR(AVERAGE(AP58:AP112),"-") -> - | AR113: =IFERROR(AH113/R113, "-") -> -
A114: ИТОГО | B114: Май | H114: =IFERROR(H57+H113,"-") -> 0 | I114: =IFERROR(I57+I113,"-") -> 0 | J114: =IFERROR(N114/M114-1,"-") -> - | K114: =IFERROR(K57+K113,"-") -> 0 | L114: =IFERROR(L57+L113,"-") -> 0 | M114: =IFERROR(M57+M113,"-") -> 0 | N114: =IFERROR(N57+N113,"-") -> 0 | O114: =IFERROR(O57+O113,"-") -> 0 | P114: =IFERROR(P57+P113,"-") -> 0 | Q114: =IFERROR(R114/P114, "-") -> - | R114: =IFERROR(R57+R113,"-") -> 0 | S114: =IFERROR(O114/R114, "-") -> - | T114: =IFERROR(T57+T113,"-") -> 0 | U114: =IFERROR(O114/T114, "-") -> - | V114: =IFERROR(R114/T114, "-") -> - | W114: =IFERROR(W57+W113,"-") -> 0 | X114: =IFERROR(O114/W114, "-") -> - | Y114: =IFERROR(W114/O114, "-") -> - | Z114: =IFERROR(W114/T114, "-") -> - | AA114: =IFERROR(AA57+AA113,"-") -> 0 | AB114: =IFERROR(AB57+AB113,"-") -> - | AC114: =IFERROR(AA114/T114, "-") -> - | AD114: =IFERROR(AD57+AD113,"-") -> 0 | AE114: =IFERROR(O114/AD114, "-") -> - | AF114: =IFERROR(AD114/O114, "-") -> - | AG114: =IFERROR(AD114/AA114, "-") -> - | AH114: =IFERROR(AH57+AH113,"-") -> 0 | AI114: =IFERROR(ROUND(AVERAGE(AI57,AI113),0),"-") -> - | AJ114: =IFERROR(AJ57+AJ113,"-") -> 0 | AK114: =IFERROR(AK57+AK113,"-") -> 0 | AL114: =IFERROR(AK114+AJ114,"-") -> 0 | AM114: =IFERROR(AL114/AH114, "-") -> - | AN114: =IFERROR(O114/AL114, "-") -> - | AO114: =IFERROR(AO57+AO113,"-") -> 0 | AP114: =IFERROR(AVERAGE(AP57,AP113),"-") -> - | AR114: =IFERROR(AH114/R114, "-") -> -
A117: Месяц+Год | B117: Тип клиента | C117: Площадка | D117: Формат | E117: Гео | F117: Модель закупки | G117: Единица закупки | H117: Кол-во единиц закупки | I117: Стоимость единицы закупки, руб. с НДС | J117: АК% | K117: АК, руб. (абс.) | L117: НДС, руб. (абс.) | M117: Тотал бюджет, руб. без НДС и АК | N117: Тотал бюджет, руб. без НДС и с учетом АК | O117: Тотал бюджет руб. с учетом НДС и АК | P117: Кол-во показов | Q117: CTR, % | R117: Кол-во кликов | S117: СРС, руб. с НДС | T117: Кол-во оформленных заказов | U117: Стоимость оформл. заказа, руб. с НДС | V117: CR (конверсия из клика в заказ), % | W117: Оформленный доход, руб. с НДС | X117: ДРР от оформл. дохода, % | Y117: ROAS офомл. (Доход/Бюджет) | Z117: Средний чек по оформл. доходу, с НДС | AA117: Кол-во отгруженных заказов | AB117: Стоимость отгр. заказа, руб. с НДС | AC117: CR 2 (конверсия из оформленного в отгруженный заказ), % | AD117: Выручка (отгруженный доход), руб. с НДС | AE117: ДРР от выручки, % | AF117: ROAS отгр. (Выручка/Бюджет) | AG117: Средний чек по выручке, с НДС | AH117: Кол-во клиентов | AI117: Частота заказа | AJ117: Кол-во абсолютно новых клиентов (ранее не заказывали) | AK117: Кол-во вернувшихся клиентов (не заказывали более 12 мес) | AL117: Кол-во новых клиентов (абсолютно новые + вернувшиеся) | AM117: Доля новых клиентов, % | AN117: САС, руб. | AO117: СРА: кол-во активных веб мастеров | AP117: СРА: % аппрува
A118: Июнь 2026 | B118: В2В | H118: =INT(P118*Q118) -> 0 | K118: =I118*J118*H118 -> 0 | L118: =0.22*M118 -> 0 | M118: =(H118*I118)/1.22 -> 0 | N118: =K118+M118 -> 0 | O118: =(H118*I118)+K118 -> 0 | R118: =(ROUNDDOWN(P118*Q118,0)) -> 0 | S118: =(ROUNDDOWN(O118/R118,0)) -> #DIV/0! | T118: =(ROUNDDOWN(V118*R118,0)) -> 0 | U118: =O118/T118 -> #DIV/0! | W118: =T118*Z118 -> 0 | X118: =O118/W118 -> #DIV/0! | Y118: =W118/O118 -> #DIV/0! | AA118: =ROUNDDOWN(T118*AC118,0) -> 0 | AB118: =O118/AA118 -> #DIV/0! | AD118: =AA118*AG118 -> 0 | AE118: =O118/AD118 -> #DIV/0! | AF118: =AD118/O118 -> #DIV/0! | AH118: =ROUNDDOWN(AR118*R118,0) -> 0 | AL118: =AJ118+AK118 -> 0 | AM118: =AL118/AH118 -> #DIV/0! | AN118: =O118/AL118 -> #DIV/0!
A119: Июнь 2026 | B119: В2В | H119: =INT(P119*Q119) -> 0 | K119: =I119*J119*H119 -> 0 | L119: =0.22*M119 -> 0 | M119: =(H119*I119)/1.22 -> 0 | N119: =K119+M119 -> 0 | O119: =(H119*I119)+K119 -> 0 | R119: =(ROUNDDOWN(P119*Q119,0)) -> 0 | S119: =(ROUNDDOWN(O119/R119,0)) -> #DIV/0! | T119: =(ROUNDDOWN(V119*R119,0)) -> 0 | U119: =O119/T119 -> #DIV/0! | W119: =T119*Z119 -> 0 | X119: =O119/W119 -> #DIV/0! | Y119: =W119/O119 -> #DIV/0! | AA119: =ROUNDDOWN(T119*AC119,0) -> 0 | AB119: =O119/AA119 -> #DIV/0! | AD119: =AA119*AG119 -> 0 | AE119: =O119/AD119 -> #DIV/0! | AF119: =AD119/O119 -> #DIV/0! | AH119: =ROUNDDOWN(AR119*R119,0) -> 0 | AL119: =AJ119+AK119 -> 0 | AM119: =AL119/AH119 -> #DIV/0! | AN119: =O119/AL119 -> #DIV/0!
A120: Июнь 2026 | B120: В2В | H120: =INT(P120*Q120) -> 0 | K120: =I120*J120*H120 -> 0 | L120: =0.22*M120 -> 0 | M120: =(H120*I120)/1.22 -> 0 | N120: =K120+M120 -> 0 | O120: =(H120*I120)+K120 -> 0 | R120: =(ROUNDDOWN(P120*Q120,0)) -> 0 | S120: =(ROUNDDOWN(O120/R120,0)) -> #DIV/0! | T120: =(ROUNDDOWN(V120*R120,0)) -> 0 | U120: =O120/T120 -> #DIV/0! | W120: =T120*Z120 -> 0 | X120: =O120/W120 -> #DIV/0! | Y120: =W120/O120 -> #DIV/0! | AA120: =ROUNDDOWN(T120*AC120,0) -> 0 | AB120: =O120/AA120 -> #DIV/0! | AD120: =AA120*AG120 -> 0 | AE120: =O120/AD120 -> #DIV/0! | AF120: =AD120/O120 -> #DIV/0! | AH120: =ROUNDDOWN(AR120*R120,0) -> 0 | AL120: =AJ120+AK120 -> 0 | AM120: =AL120/AH120 -> #DIV/0! | AN120: =O120/AL120 -> #DIV/0!
A121: Июнь 2026 | B121: В2В | H121: =INT(P121*Q121) -> 0 | K121: =I121*J121*H121 -> 0 | L121: =0.22*M121 -> 0 | M121: =(H121*I121)/1.22 -> 0 | N121: =K121+M121 -> 0 | O121: =(H121*I121)+K121 -> 0 | R121: =(ROUNDDOWN(P121*Q121,0)) -> 0 | S121: =(ROUNDDOWN(O121/R121,0)) -> #DIV/0! | T121: =(ROUNDDOWN(V121*R121,0)) -> 0 | U121: =O121/T121 -> #DIV/0! | W121: =T121*Z121 -> 0 | X121: =O121/W121 -> #DIV/0! | Y121: =W121/O121 -> #DIV/0! | AA121: =ROUNDDOWN(T121*AC121,0) -> 0 | AB121: =O121/AA121 -> #DIV/0! | AD121: =AA121*AG121 -> 0 | AE121: =O121/AD121 -> #DIV/0! | AF121: =AD121/O121 -> #DIV/0! | AH121: =ROUNDDOWN(AR121*R121,0) -> 0 | AL121: =AJ121+AK121 -> 0 | AM121: =AL121/AH121 -> #DIV/0! | AN121: =O121/AL121 -> #DIV/0!
A122: Июнь 2026 | B122: В2В | H122: =INT(P122*Q122) -> 0 | K122: =I122*J122*H122 -> 0 | L122: =0.22*M122 -> 0 | M122: =(H122*I122)/1.22 -> 0 | N122: =K122+M122 -> 0 | O122: =(H122*I122)+K122 -> 0 | R122: =(ROUNDDOWN(P122*Q122,0)) -> 0 | S122: =(ROUNDDOWN(O122/R122,0)) -> #DIV/0! | T122: =(ROUNDDOWN(V122*R122,0)) -> 0 | U122: =O122/T122 -> #DIV/0! | W122: =T122*Z122 -> 0 | X122: =O122/W122 -> #DIV/0! | Y122: =W122/O122 -> #DIV/0! | AA122: =ROUNDDOWN(T122*AC122,0) -> 0 | AB122: =O122/AA122 -> #DIV/0! | AD122: =AA122*AG122 -> 0 | AE122: =O122/AD122 -> #DIV/0! | AF122: =AD122/O122 -> #DIV/0! | AH122: =ROUNDDOWN(AR122*R122,0) -> 0 | AL122: =AJ122+AK122 -> 0 | AM122: =AL122/AH122 -> #DIV/0! | AN122: =O122/AL122 -> #DIV/0!
A123: Июнь 2026 | B123: В2В | H123: =INT(P123*Q123) -> 0 | K123: =I123*J123*H123 -> 0 | L123: =0.22*M123 -> 0 | M123: =(H123*I123)/1.22 -> 0 | N123: =K123+M123 -> 0 | O123: =(H123*I123)+K123 -> 0 | R123: =(ROUNDDOWN(P123*Q123,0)) -> 0 | S123: =(ROUNDDOWN(O123/R123,0)) -> #DIV/0! | T123: =(ROUNDDOWN(V123*R123,0)) -> 0 | U123: =O123/T123 -> #DIV/0! | W123: =T123*Z123 -> 0 | X123: =O123/W123 -> #DIV/0! | Y123: =W123/O123 -> #DIV/0! | AA123: =ROUNDDOWN(T123*AC123,0) -> 0 | AB123: =O123/AA123 -> #DIV/0! | AD123: =AA123*AG123 -> 0 | AE123: =O123/AD123 -> #DIV/0! | AF123: =AD123/O123 -> #DIV/0! | AH123: =ROUNDDOWN(AR123*R123,0) -> 0 | AL123: =AJ123+AK123 -> 0 | AM123: =AL123/AH123 -> #DIV/0! | AN123: =O123/AL123 -> #DIV/0!
A124: Июнь 2026 | B124: В2В | H124: =INT(P124*Q124) -> 0 | K124: =I124*J124*H124 -> 0 | L124: =0.22*M124 -> 0 | M124: =(H124*I124)/1.22 -> 0 | N124: =K124+M124 -> 0 | O124: =(H124*I124)+K124 -> 0 | R124: =(ROUNDDOWN(P124*Q124,0)) -> 0 | S124: =(ROUNDDOWN(O124/R124,0)) -> #DIV/0! | T124: =(ROUNDDOWN(V124*R124,0)) -> 0 | U124: =O124/T124 -> #DIV/0! | W124: =T124*Z124 -> 0 | X124: =O124/W124 -> #DIV/0! | Y124: =W124/O124 -> #DIV/0! | AA124: =ROUNDDOWN(T124*AC124,0) -> 0 | AB124: =O124/AA124 -> #DIV/0! | AD124: =AA124*AG124 -> 0 | AE124: =O124/AD124 -> #DIV/0! | AF124: =AD124/O124 -> #DIV/0! | AH124: =ROUNDDOWN(AR124*R124,0) -> 0 | AL124: =AJ124+AK124 -> 0 | AM124: =AL124/AH124 -> #DIV/0! | AN124: =O124/AL124 -> #DIV/0!
A125: Июнь 2026 | B125: В2В | H125: =INT(P125*Q125) -> 0 | K125: =I125*J125*H125 -> 0 | L125: =0.22*M125 -> 0 | M125: =(H125*I125)/1.22 -> 0 | N125: =K125+M125 -> 0 | O125: =(H125*I125)+K125 -> 0 | R125: =(ROUNDDOWN(P125*Q125,0)) -> 0 | S125: =(ROUNDDOWN(O125/R125,0)) -> #DIV/0! | T125: =(ROUNDDOWN(V125*R125,0)) -> 0 | U125: =O125/T125 -> #DIV/0! | W125: =T125*Z125 -> 0 | X125: =O125/W125 -> #DIV/0! | Y125: =W125/O125 -> #DIV/0! | AA125: =ROUNDDOWN(T125*AC125,0) -> 0 | AB125: =O125/AA125 -> #DIV/0! | AD125: =AA125*AG125 -> 0 | AE125: =O125/AD125 -> #DIV/0! | AF125: =AD125/O125 -> #DIV/0! | AH125: =ROUNDDOWN(AR125*R125,0) -> 0 | AL125: =AJ125+AK125 -> 0 | AM125: =AL125/AH125 -> #DIV/0! | AN125: =O125/AL125 -> #DIV/0!
A126: Июнь 2026 | B126: В2В | H126: =INT(P126*Q126) -> 0 | K126: =I126*J126*H126 -> 0 | L126: =0.22*M126 -> 0 | M126: =(H126*I126)/1.22 -> 0 | N126: =K126+M126 -> 0 | O126: =(H126*I126)+K126 -> 0 | R126: =(ROUNDDOWN(P126*Q126,0)) -> 0 | S126: =(ROUNDDOWN(O126/R126,0)) -> #DIV/0! | T126: =(ROUNDDOWN(V126*R126,0)) -> 0 | U126: =O126/T126 -> #DIV/0! | W126: =T126*Z126 -> 0 | X126: =O126/W126 -> #DIV/0! | Y126: =W126/O126 -> #DIV/0! | AA126: =ROUNDDOWN(T126*AC126,0) -> 0 | AB126: =O126/AA126 -> #DIV/0! | AD126: =AA126*AG126 -> 0 | AE126: =O126/AD126 -> #DIV/0! | AF126: =AD126/O126 -> #DIV/0! | AH126: =ROUNDDOWN(AR126*R126,0) -> 0 | AL126: =AJ126+AK126 -> 0 | AM126: =AL126/AH126 -> #DIV/0! | AN126: =O126/AL126 -> #DIV/0!
A127: Июнь 2026 | B127: В2В | H127: =INT(P127*Q127) -> 0 | K127: =I127*J127*H127 -> 0 | L127: =0.22*M127 -> 0 | M127: =(H127*I127)/1.22 -> 0 | N127: =K127+M127 -> 0 | O127: =(H127*I127)+K127 -> 0 | R127: =(ROUNDDOWN(P127*Q127,0)) -> 0 | S127: =(ROUNDDOWN(O127/R127,0)) -> #DIV/0! | T127: =(ROUNDDOWN(V127*R127,0)) -> 0 | U127: =O127/T127 -> #DIV/0! | W127: =T127*Z127 -> 0 | X127: =O127/W127 -> #DIV/0! | Y127: =W127/O127 -> #DIV/0! | AA127: =ROUNDDOWN(T127*AC127,0) -> 0 | AB127: =O127/AA127 -> #DIV/0! | AD127: =AA127*AG127 -> 0 | AE127: =O127/AD127 -> #DIV/0! | AF127: =AD127/O127 -> #DIV/0! | AH127: =ROUNDDOWN(AR127*R127,0) -> 0 | AL127: =AJ127+AK127 -> 0 | AM127: =AL127/AH127 -> #DIV/0! | AN127: =O127/AL127 -> #DIV/0!
A128: Июнь 2026 | B128: В2В | H128: =INT(P128*Q128) -> 0 | K128: =I128*J128*H128 -> 0 | L128: =0.22*M128 -> 0 | M128: =(H128*I128)/1.22 -> 0 | N128: =K128+M128 -> 0 | O128: =(H128*I128)+K128 -> 0 | R128: =(ROUNDDOWN(P128*Q128,0)) -> 0 | S128: =(ROUNDDOWN(O128/R128,0)) -> #DIV/0! | T128: =(ROUNDDOWN(V128*R128,0)) -> 0 | U128: =O128/T128 -> #DIV/0! | W128: =T128*Z128 -> 0 | X128: =O128/W128 -> #DIV/0! | Y128: =W128/O128 -> #DIV/0! | AA128: =ROUNDDOWN(T128*AC128,0) -> 0 | AB128: =O128/AA128 -> #DIV/0! | AD128: =AA128*AG128 -> 0 | AE128: =O128/AD128 -> #DIV/0! | AF128: =AD128/O128 -> #DIV/0! | AH128: =ROUNDDOWN(AR128*R128,0) -> 0 | AL128: =AJ128+AK128 -> 0 | AM128: =AL128/AH128 -> #DIV/0! | AN128: =O128/AL128 -> #DIV/0!
A129: Июнь 2026 | B129: В2В | H129: =INT(P129*Q129) -> 0 | K129: =I129*J129*H129 -> 0 | L129: =0.22*M129 -> 0 | M129: =(H129*I129)/1.22 -> 0 | N129: =K129+M129 -> 0 | O129: =(H129*I129)+K129 -> 0 | R129: =(ROUNDDOWN(P129*Q129,0)) -> 0 | S129: =(ROUNDDOWN(O129/R129,0)) -> #DIV/0! | T129: =(ROUNDDOWN(V129*R129,0)) -> 0 | U129: =O129/T129 -> #DIV/0! | W129: =T129*Z129 -> 0 | X129: =O129/W129 -> #DIV/0! | Y129: =W129/O129 -> #DIV/0! | AA129: =ROUNDDOWN(T129*AC129,0) -> 0 | AB129: =O129/AA129 -> #DIV/0! | AD129: =AA129*AG129 -> 0 | AE129: =O129/AD129 -> #DIV/0! | AF129: =AD129/O129 -> #DIV/0! | AH129: =ROUNDDOWN(AR129*R129,0) -> 0 | AL129: =AJ129+AK129 -> 0 | AM129: =AL129/AH129 -> #DIV/0! | AN129: =O129/AL129 -> #DIV/0!
... A172: Июнь 2026 | B172: В2В | H172: =INT(P172*Q172) -> 0 | K172: =I172*J172*H172 -> 0 | L172: =0.22*M172 -> 0 | M172: =(H172*I172)/1.22 -> 0 | N172: =K172+M172 -> 0 | O172: =(H172*I172)+K172 -> 0 | R172: =(ROUNDDOWN(P172*Q172,0)) -> 0 | S172: =(ROUNDDOWN(O172/R172,0)) -> #DIV/0! | T172: =(ROUNDDOWN(V172*R172,0)) -> 0 | U172: =O172/T172 -> #DIV/0! | W172: =T172*Z172 -> 0 | X172: =O172/W172 -> #DIV/0! | Y172: =W172/O172 -> #DIV/0! | AA172: =ROUNDDOWN(T172*AC172,0) -> 0 | AB172: =O172/AA172 -> #DIV/0! | AD172: =AA172*AG172 -> 0 | AE172: =O172/AD172 -> #DIV/0! | AF172: =AD172/O172 -> #DIV/0! | AH172: =ROUNDDOWN(AR172*R172,0) -> 0 | AL172: =AJ172+AK172 -> 0 | AM172: =AL172/AH172 -> #DIV/0! | AN172: =O172/AL172 -> #DIV/0!
A173: ИТОГО | B173: B2B | H173: =IFERROR(SUM(H118:H172),"-") -> 0 | I173: =IFERROR(SUM(I118:I172),"-") -> 0 | J173: =IFERROR(N173/M173-1,"-") -> - | K173: =IFERROR(N173-M173,"-") -> 0 | L173: =IFERROR(SUM(L118:L172),"-") -> 0 | M173: =IFERROR(SUM(M118:M172),"-") -> 0 | N173: =IFERROR(SUM(N118:N172),"-") -> 0 | O173: =IFERROR(SUM(O118:O172),"-") -> 0 | P173: =IFERROR(SUM(P118:P172),"-") -> 0 | Q173: =IFERROR(R173/P173, "-") -> - | R173: =IFERROR(SUM(R118:R172),"-") -> 0 | S173: =IFERROR(O173/R173, "-") -> - | T173: =IFERROR(SUM(T118:T172),"-") -> 0 | U173: =IFERROR(O173/T173, "-") -> - | V173: =IFERROR(R173/T173, "-") -> - | W173: =IFERROR(SUM(W118:W172),"-") -> 0 | X173: =IFERROR(O173/W173, "-") -> - | Y173: =IFERROR(W173/O173, "-") -> - | Z173: =IFERROR(W173/T173, "-") -> - | AA173: =IFERROR(SUM(AA118:AA172),"-") -> 0 | AB173: =IFERROR(O173/AA173, "-") -> - | AC173: =IFERROR(AA173/T173, "-") -> - | AD173: =IFERROR(SUM(AD118:AD172),"-") -> 0 | AE173: =IFERROR(O173/AD173, "-") -> - | AF173: =IFERROR(AD173/O173, "-") -> - | AG173: =IFERROR(AD173/AA173, "-") -> - | AH173: =IFERROR(SUM(AH118:AH172),"-") -> 0 | AI173: =IFERROR(ROUND(AVERAGE(AI118:AI172),0),"-") -> - | AJ173: =IFERROR(SUM(AJ118:AJ172),"-") -> 0 | AK173: =IFERROR(SUM(AK118:AK172),"-") -> 0 | AL173: =IFERROR(AK173+AJ173,"-") -> 0 | AM173: =IFERROR(AL173/AH173, "-") -> - | AN173: =IFERROR(O173/AL173, "-") -> - | AO173: =IFERROR(SUM(AO118:AO172),"-") -> 0 | AP173: =IFERROR(AVERAGE(AP118:AP172),"-") -> - | AR173: =IFERROR(AH173/R173, "-") -> -
A174: Июнь 2026 | B174: B2C | H174: =INT(P174*Q174) -> 0 | K174: =I174*J174*H174 -> 0 | L174: =0.22*M174 -> 0 | M174: =(H174*I174)/1.22 -> 0 | N174: =K174+M174 -> 0 | O174: =(H174*I174)+K174 -> 0 | R174: =(ROUNDDOWN(P174*Q174,0)) -> 0 | S174: =(ROUNDDOWN(O174/R174,0)) -> #DIV/0! | T174: =(ROUNDDOWN(V174*R174,0)) -> 0 | U174: =O174/T174 -> #DIV/0! | W174: =T174*Z174 -> 0 | X174: =O174/W174 -> #DIV/0! | Y174: =W174/O174 -> #DIV/0! | AA174: =ROUNDDOWN(T174*AC174,0) -> 0 | AB174: =O174/AA174 -> #DIV/0! | AD174: =AA174*AG174 -> 0 | AE174: =O174/AD174 -> #DIV/0! | AF174: =AD174/O174 -> #DIV/0! | AH174: =ROUNDDOWN(AR174*R174,0) -> 0 | AL174: =AJ174+AK174 -> 0 | AM174: =AL174/AH174 -> #DIV/0! | AN174: =O174/AL174 -> #DIV/0!
A175: Июнь 2026 | B175: B2C | H175: =INT(P175*Q175) -> 0 | K175: =I175*J175*H175 -> 0 | L175: =0.22*M175 -> 0 | M175: =(H175*I175)/1.22 -> 0 | N175: =K175+M175 -> 0 | O175: =(H175*I175)+K175 -> 0 | R175: =(ROUNDDOWN(P175*Q175,0)) -> 0 | S175: =(ROUNDDOWN(O175/R175,0)) -> #DIV/0! | T175: =(ROUNDDOWN(V175*R175,0)) -> 0 | U175: =O175/T175 -> #DIV/0! | W175: =T175*Z175 -> 0 | X175: =O175/W175 -> #DIV/0! | Y175: =W175/O175 -> #DIV/0! | AA175: =ROUNDDOWN(T175*AC175,0) -> 0 | AB175: =O175/AA175 -> #DIV/0! | AD175: =AA175*AG175 -> 0 | AE175: =O175/AD175 -> #DIV/0! | AF175: =AD175/O175 -> #DIV/0! | AH175: =ROUNDDOWN(AR175*R175,0) -> 0 | AL175: =AJ175+AK175 -> 0 | AM175: =AL175/AH175 -> #DIV/0! | AN175: =O175/AL175 -> #DIV/0!
A176: Июнь 2026 | B176: B2C | H176: =INT(P176*Q176) -> 0 | K176: =I176*J176*H176 -> 0 | L176: =0.22*M176 -> 0 | M176: =(H176*I176)/1.22 -> 0 | N176: =K176+M176 -> 0 | O176: =(H176*I176)+K176 -> 0 | R176: =(ROUNDDOWN(P176*Q176,0)) -> 0 | S176: =(ROUNDDOWN(O176/R176,0)) -> #DIV/0! | T176: =(ROUNDDOWN(V176*R176,0)) -> 0 | U176: =O176/T176 -> #DIV/0! | W176: =T176*Z176 -> 0 | X176: =O176/W176 -> #DIV/0! | Y176: =W176/O176 -> #DIV/0! | AA176: =ROUNDDOWN(T176*AC176,0) -> 0 | AB176: =O176/AA176 -> #DIV/0! | AD176: =AA176*AG176 -> 0 | AE176: =O176/AD176 -> #DIV/0! | AF176: =AD176/O176 -> #DIV/0! | AH176: =ROUNDDOWN(AR176*R176,0) -> 0 | AL176: =AJ176+AK176 -> 0 | AM176: =AL176/AH176 -> #DIV/0! | AN176: =O176/AL176 -> #DIV/0!
A177: Июнь 2026 | B177: B2C | H177: =INT(P177*Q177) -> 0 | K177: =I177*J177*H177 -> 0 | L177: =0.22*M177 -> 0 | M177: =(H177*I177)/1.22 -> 0 | N177: =K177+M177 -> 0 | O177: =(H177*I177)+K177 -> 0 | R177: =(ROUNDDOWN(P177*Q177,0)) -> 0 | S177: =(ROUNDDOWN(O177/R177,0)) -> #DIV/0! | T177: =(ROUNDDOWN(V177*R177,0)) -> 0 | U177: =O177/T177 -> #DIV/0! | W177: =T177*Z177 -> 0 | X177: =O177/W177 -> #DIV/0! | Y177: =W177/O177 -> #DIV/0! | AA177: =ROUNDDOWN(T177*AC177,0) -> 0 | AB177: =O177/AA177 -> #DIV/0! | AD177: =AA177*AG177 -> 0 | AE177: =O177/AD177 -> #DIV/0! | AF177: =AD177/O177 -> #DIV/0! | AH177: =ROUNDDOWN(AR177*R177,0) -> 0 | AL177: =AJ177+AK177 -> 0 | AM177: =AL177/AH177 -> #DIV/0! | AN177: =O177/AL177 -> #DIV/0!
A178: Июнь 2026 | B178: B2C | H178: =INT(P178*Q178) -> 0 | K178: =I178*J178*H178 -> 0 | L178: =0.22*M178 -> 0 | M178: =(H178*I178)/1.22 -> 0 | N178: =K178+M178 -> 0 | O178: =(H178*I178)+K178 -> 0 | R178: =(ROUNDDOWN(P178*Q178,0)) -> 0 | S178: =(ROUNDDOWN(O178/R178,0)) -> #DIV/0! | T178: =(ROUNDDOWN(V178*R178,0)) -> 0 | U178: =O178/T178 -> #DIV/0! | W178: =T178*Z178 -> 0 | X178: =O178/W178 -> #DIV/0! | Y178: =W178/O178 -> #DIV/0! | AA178: =ROUNDDOWN(T178*AC178,0) -> 0 | AB178: =O178/AA178 -> #DIV/0! | AD178: =AA178*AG178 -> 0 | AE178: =O178/AD178 -> #DIV/0! | AF178: =AD178/O178 -> #DIV/0! | AH178: =ROUNDDOWN(AR178*R178,0) -> 0 | AL178: =AJ178+AK178 -> 0 | AM178: =AL178/AH178 -> #DIV/0! | AN178: =O178/AL178 -> #DIV/0!
A179: Июнь 2026 | B179: B2C | H179: =INT(P179*Q179) -> 0 | K179: =I179*J179*H179 -> 0 | L179: =0.22*M179 -> 0 | M179: =(H179*I179)/1.22 -> 0 | N179: =K179+M179 -> 0 | O179: =(H179*I179)+K179 -> 0 | R179: =(ROUNDDOWN(P179*Q179,0)) -> 0 | S179: =(ROUNDDOWN(O179/R179,0)) -> #DIV/0! | T179: =(ROUNDDOWN(V179*R179,0)) -> 0 | U179: =O179/T179 -> #DIV/0! | W179: =T179*Z179 -> 0 | X179: =O179/W179 -> #DIV/0! | Y179: =W179/O179 -> #DIV/0! | AA179: =ROUNDDOWN(T179*AC179,0) -> 0 | AB179: =O179/AA179 -> #DIV/0! | AD179: =AA179*AG179 -> 0 | AE179: =O179/AD179 -> #DIV/0! | AF179: =AD179/O179 -> #DIV/0! | AH179: =ROUNDDOWN(AR179*R179,0) -> 0 | AL179: =AJ179+AK179 -> 0 | AM179: =AL179/AH179 -> #DIV/0! | AN179: =O179/AL179 -> #DIV/0!
A180: Июнь 2026 | B180: B2C | H180: =INT(P180*Q180) -> 0 | K180: =I180*J180*H180 -> 0 | L180: =0.22*M180 -> 0 | M180: =(H180*I180)/1.22 -> 0 | N180: =K180+M180 -> 0 | O180: =(H180*I180)+K180 -> 0 | R180: =(ROUNDDOWN(P180*Q180,0)) -> 0 | S180: =(ROUNDDOWN(O180/R180,0)) -> #DIV/0! | T180: =(ROUNDDOWN(V180*R180,0)) -> 0 | U180: =O180/T180 -> #DIV/0! | W180: =T180*Z180 -> 0 | X180: =O180/W180 -> #DIV/0! | Y180: =W180/O180 -> #DIV/0! | AA180: =ROUNDDOWN(T180*AC180,0) -> 0 | AB180: =O180/AA180 -> #DIV/0! | AD180: =AA180*AG180 -> 0 | AE180: =O180/AD180 -> #DIV/0! | AF180: =AD180/O180 -> #DIV/0! | AH180: =ROUNDDOWN(AR180*R180,0) -> 0 | AL180: =AJ180+AK180 -> 0 | AM180: =AL180/AH180 -> #DIV/0! | AN180: =O180/AL180 -> #DIV/0!
A181: Июнь 2026 | B181: B2C | H181: =INT(P181*Q181) -> 0 | K181: =I181*J181*H181 -> 0 | L181: =0.22*M181 -> 0 | M181: =(H181*I181)/1.22 -> 0 | N181: =K181+M181 -> 0 | O181: =(H181*I181)+K181 -> 0 | R181: =(ROUNDDOWN(P181*Q181,0)) -> 0 | S181: =(ROUNDDOWN(O181/R181,0)) -> #DIV/0! | T181: =(ROUNDDOWN(V181*R181,0)) -> 0 | U181: =O181/T181 -> #DIV/0! | W181: =T181*Z181 -> 0 | X181: =O181/W181 -> #DIV/0! | Y181: =W181/O181 -> #DIV/0! | AA181: =ROUNDDOWN(T181*AC181,0) -> 0 | AB181: =O181/AA181 -> #DIV/0! | AD181: =AA181*AG181 -> 0 | AE181: =O181/AD181 -> #DIV/0! | AF181: =AD181/O181 -> #DIV/0! | AH181: =ROUNDDOWN(AR181*R181,0) -> 0 | AL181: =AJ181+AK181 -> 0 | AM181: =AL181/AH181 -> #DIV/0! | AN181: =O181/AL181 -> #DIV/0!
A182: Июнь 2026 | B182: B2C | H182: =INT(P182*Q182) -> 0 | K182: =I182*J182*H182 -> 0 | L182: =0.22*M182 -> 0 | M182: =(H182*I182)/1.22 -> 0 | N182: =K182+M182 -> 0 | O182: =(H182*I182)+K182 -> 0 | R182: =(ROUNDDOWN(P182*Q182,0)) -> 0 | S182: =(ROUNDDOWN(O182/R182,0)) -> #DIV/0! | T182: =(ROUNDDOWN(V182*R182,0)) -> 0 | U182: =O182/T182 -> #DIV/0! | W182: =T182*Z182 -> 0 | X182: =O182/W182 -> #DIV/0! | Y182: =W182/O182 -> #DIV/0! | AA182: =ROUNDDOWN(T182*AC182,0) -> 0 | AB182: =O182/AA182 -> #DIV/0! | AD182: =AA182*AG182 -> 0 | AE182: =O182/AD182 -> #DIV/0! | AF182: =AD182/O182 -> #DIV/0! | AH182: =ROUNDDOWN(AR182*R182,0) -> 0 | AL182: =AJ182+AK182 -> 0 | AM182: =AL182/AH182 -> #DIV/0! | AN182: =O182/AL182 -> #DIV/0!
A183: Июнь 2026 | B183: B2C | H183: =INT(P183*Q183) -> 0 | K183: =I183*J183*H183 -> 0 | L183: =0.22*M183 -> 0 | M183: =(H183*I183)/1.22 -> 0 | N183: =K183+M183 -> 0 | O183: =(H183*I183)+K183 -> 0 | R183: =(ROUNDDOWN(P183*Q183,0)) -> 0 | S183: =(ROUNDDOWN(O183/R183,0)) -> #DIV/0! | T183: =(ROUNDDOWN(V183*R183,0)) -> 0 | U183: =O183/T183 -> #DIV/0! | W183: =T183*Z183 -> 0 | X183: =O183/W183 -> #DIV/0! | Y183: =W183/O183 -> #DIV/0! | AA183: =ROUNDDOWN(T183*AC183,0) -> 0 | AB183: =O183/AA183 -> #DIV/0! | AD183: =AA183*AG183 -> 0 | AE183: =O183/AD183 -> #DIV/0! | AF183: =AD183/O183 -> #DIV/0! | AH183: =ROUNDDOWN(AR183*R183,0) -> 0 | AL183: =AJ183+AK183 -> 0 | AM183: =AL183/AH183 -> #DIV/0! | AN183: =O183/AL183 -> #DIV/0!
A184: Июнь 2026 | B184: B2C | H184: =INT(P184*Q184) -> 0 | K184: =I184*J184*H184 -> 0 | L184: =0.22*M184 -> 0 | M184: =(H184*I184)/1.22 -> 0 | N184: =K184+M184 -> 0 | O184: =(H184*I184)+K184 -> 0 | R184: =(ROUNDDOWN(P184*Q184,0)) -> 0 | S184: =(ROUNDDOWN(O184/R184,0)) -> #DIV/0! | T184: =(ROUNDDOWN(V184*R184,0)) -> 0 | U184: =O184/T184 -> #DIV/0! | W184: =T184*Z184 -> 0 | X184: =O184/W184 -> #DIV/0! | Y184: =W184/O184 -> #DIV/0! | AA184: =ROUNDDOWN(T184*AC184,0) -> 0 | AB184: =O184/AA184 -> #DIV/0! | AD184: =AA184*AG184 -> 0 | AE184: =O184/AD184 -> #DIV/0! | AF184: =AD184/O184 -> #DIV/0! | AH184: =ROUNDDOWN(AR184*R184,0) -> 0 | AL184: =AJ184+AK184 -> 0 | AM184: =AL184/AH184 -> #DIV/0! | AN184: =O184/AL184 -> #DIV/0!
A185: Июнь 2026 | B185: B2C | H185: =INT(P185*Q185) -> 0 | K185: =I185*J185*H185 -> 0 | L185: =0.22*M185 -> 0 | M185: =(H185*I185)/1.22 -> 0 | N185: =K185+M185 -> 0 | O185: =(H185*I185)+K185 -> 0 | R185: =(ROUNDDOWN(P185*Q185,0)) -> 0 | S185: =(ROUNDDOWN(O185/R185,0)) -> #DIV/0! | T185: =(ROUNDDOWN(V185*R185,0)) -> 0 | U185: =O185/T185 -> #DIV/0! | W185: =T185*Z185 -> 0 | X185: =O185/W185 -> #DIV/0! | Y185: =W185/O185 -> #DIV/0! | AA185: =ROUNDDOWN(T185*AC185,0) -> 0 | AB185: =O185/AA185 -> #DIV/0! | AD185: =AA185*AG185 -> 0 | AE185: =O185/AD185 -> #DIV/0! | AF185: =AD185/O185 -> #DIV/0! | AH185: =ROUNDDOWN(AR185*R185,0) -> 0 | AL185: =AJ185+AK185 -> 0 | AM185: =AL185/AH185 -> #DIV/0! | AN185: =O185/AL185 -> #DIV/0!
... A228: Июнь 2026 | B228: B2C | H228: =INT(P228*Q228) -> 0 | K228: =I228*J228*H228 -> 0 | L228: =0.22*M228 -> 0 | M228: =(H228*I228)/1.22 -> 0 | N228: =K228+M228 -> 0 | O228: =(H228*I228)+K228 -> 0 | R228: =(ROUNDDOWN(P228*Q228,0)) -> 0 | S228: =(ROUNDDOWN(O228/R228,0)) -> #DIV/0! | T228: =(ROUNDDOWN(V228*R228,0)) -> 0 | U228: =O228/T228 -> #DIV/0! | W228: =T228*Z228 -> 0 | X228: =O228/W228 -> #DIV/0! | Y228: =W228/O228 -> #DIV/0! | AA228: =ROUNDDOWN(T228*AC228,0) -> 0 | AB228: =O228/AA228 -> #DIV/0! | AD228: =AA228*AG228 -> 0 | AE228: =O228/AD228 -> #DIV/0! | AF228: =AD228/O228 -> #DIV/0! | AH228: =ROUNDDOWN(AR228*R228,0) -> 0 | AL228: =AJ228+AK228 -> 0 | AM228: =AL228/AH228 -> #DIV/0! | AN228: =O228/AL228 -> #DIV/0!
A229: ИТОГО | B229: B2C | H229: =IFERROR(SUM(H174:H228),"-") -> 0 | I229: =IFERROR(SUM(I174:I228),"-") -> 0 | J229: =IFERROR(N229/M229-1,"-") -> - | K229: =IFERROR(N229-M229,"-") -> 0 | L229: =IFERROR(SUM(L174:L228),"-") -> 0 | M229: =IFERROR(SUM(M174:M228),"-") -> 0 | N229: =IFERROR(SUM(N174:N228),"-") -> 0 | O229: =IFERROR(SUM(O174:O228),"-") -> 0 | P229: =IFERROR(SUM(P174:P228),"-") -> 0 | Q229: =IFERROR(R229/P229, "-") -> - | R229: =IFERROR(SUM(R174:R228),"-") -> 0 | S229: =IFERROR(O229/R229, "-") -> - | T229: =IFERROR(SUM(T174:T228),"-") -> 0 | U229: =IFERROR(O229/T229, "-") -> - | V229: =IFERROR(R229/T229, "-") -> - | W229: =IFERROR(SUM(W174:W228),"-") -> 0 | X229: =IFERROR(O229/W229, "-") -> - | Y229: =IFERROR(W229/O229, "-") -> - | Z229: =IFERROR(W229/T229, "-") -> - | AA229: =SUM(AA174:AA228) -> 0 | AB229: =IFERROR(O229/AA229, "-") -> - | AC229: =IFERROR(AA229/T229, "-") -> - | AD229: =IFERROR(SUM(AD174:AD228),"-") -> 0 | AE229: =IFERROR(O229/AD229, "-") -> - | AF229: =IFERROR(AD229/O229, "-") -> - | AG229: =IFERROR(AD229/AA229, "-") -> - | AH229: =IFERROR(SUM(AH174:AH228),"-") -> 0 | AI229: =IFERROR(ROUND(AVERAGE(AI174:AI228),0),"-") -> - | AJ229: =IFERROR(SUM(AJ174:AJ228),"-") -> 0 | AK229: =IFERROR(SUM(AK174:AK228),"-") -> 0 | AL229: =IFERROR(AK229+AJ229,"-") -> 0 | AM229: =IFERROR(AL229/AH229, "-") -> - | AN229: =IFERROR(O229/AL229, "-") -> - | AO229: =IFERROR(SUM(AO174:AO228),"-") -> 0 | AP229: =IFERROR(AVERAGE(AP174:AP228),"-") -> - | AR229: =IFERROR(AH229/R229, "-") -> -
A230: ИТОГО | B230: Июнь | H230: =IFERROR(H173+H229,"-") -> 0 | I230: =IFERROR(I173+I229,"-") -> 0 | J230: =IFERROR(N230/M230-1,"-") -> - | K230: =IFERROR(K173+K229,"-") -> 0 | L230: =IFERROR(L173+L229,"-") -> 0 | M230: =IFERROR(M173+M229,"-") -> 0 | N230: =IFERROR(N173+N229,"-") -> 0 | O230: =IFERROR(O173+O229,"-") -> 0 | P230: =IFERROR(P173+P229,"-") -> 0 | Q230: =IFERROR(R230/P230, "-") -> - | R230: =IFERROR(R173+R229,"-") -> 0 | S230: =IFERROR(O230/R230, "-") -> - | T230: =IFERROR(T173+T229,"-") -> 0 | U230: =IFERROR(O230/T230, "-") -> - | V230: =IFERROR(R230/T230, "-") -> - | W230: =IFERROR(W173+W229,"-") -> 0 | X230: =IFERROR(O230/W230, "-") -> - | Y230: =IFERROR(W230/O230, "-") -> - | Z230: =IFERROR(W230/T230, "-") -> - | AA230: =IFERROR(AA173+AA229,"-") -> 0 | AB230: =IFERROR(AB173+AB229,"-") -> - | AC230: =IFERROR(AA230/T230, "-") -> - | AD230: =IFERROR(AD173+AD229,"-") -> 0 | AE230: =IFERROR(O230/AD230, "-") -> - | AF230: =IFERROR(AD230/O230, "-") -> - | AG230: =IFERROR(AD230/AA230, "-") -> - | AH230: =IFERROR(AH173+AH229,"-") -> 0 | AI230: =IFERROR(ROUND(AVERAGE(AI173,AI229),0),"-") -> - | AJ230: =IFERROR(AJ173+AJ229,"-") -> 0 | AK230: =IFERROR(AK173+AK229,"-") -> 0 | AL230: =IFERROR(AK230+AJ230,"-") -> 0 | AM230: =IFERROR(AL230/AH230, "-") -> - | AN230: =IFERROR(O230/AL230, "-") -> - | AO230: =IFERROR(AO173+AO229,"-") -> 0 | AP230: =IFERROR(AVERAGE(AP173,AP229),"-") -> - | AR230: =IFERROR(AH230/R230, "-") -> -
A233: Месяц+Год | B233: Тип клиента | C233: Площадка | D233: Формат | E233: Гео | F233: Модель закупки | G233: Единица закупки | H233: Кол-во единиц закупки | I233: Стоимость единицы закупки, руб. с НДС | J233: АК% | K233: АК, руб. (абс.) | L233: НДС, руб. (абс.) | M233: Тотал бюджет, руб. без НДС и АК | N233: Тотал бюджет, руб. без НДС и с учетом АК | O233: Тотал бюджет руб. с учетом НДС и АК | P233: Кол-во показов | Q233: CTR, % | R233: Кол-во кликов | S233: СРС, руб. с НДС | T233: Кол-во оформленных заказов | U233: Стоимость оформл. заказа, руб. с НДС | V233: CR (конверсия из клика в заказ), % | W233: Оформленный доход, руб. с НДС | X233: ДРР от оформл. дохода, % | Y233: ROAS офомл. (Доход/Бюджет) | Z233: Средний чек по оформл. доходу, с НДС | AA233: Кол-во отгруженных заказов | AB233: Стоимость отгр. заказа, руб. с НДС | AC233: CR 2 (конверсия из оформленного в отгруженный заказ), % | AD233: Выручка (отгруженный доход), руб. с НДС | AE233: ДРР от выручки, % | AF233: ROAS отгр. (Выручка/Бюджет) | AG233: Средний чек по выручке, с НДС | AH233: Кол-во клиентов | AI233: Частота заказа | AJ233: Кол-во абсолютно новых клиентов (ранее не заказывали) | AK233: Кол-во вернувшихся клиентов (не заказывали более 12 мес) | AL233: Кол-во новых клиентов (абсолютно новые + вернувшиеся) | AM233: Доля новых клиентов, % | AN233: САС, руб. | AO233: СРА: кол-во активных веб мастеров | AP233: СРА: % аппрува
A234: Июль 2026 | B234: В2В | H234: =INT(P234*Q234) -> 0 | K234: =I234*J234*H234 -> 0 | L234: =0.22*M234 -> 0 | M234: =(H234*I234)/1.22 -> 0 | N234: =K234+M234 -> 0 | O234: =(H234*I234)+K234 -> 0 | R234: =(ROUNDDOWN(P234*Q234,0)) -> 0 | S234: =(ROUNDDOWN(O234/R234,0)) -> #DIV/0! | T234: =(ROUNDDOWN(V234*R234,0)) -> 0 | U234: =O234/T234 -> #DIV/0! | W234: =T234*Z234 -> 0 | X234: =O234/W234 -> #DIV/0! | Y234: =W234/O234 -> #DIV/0! | AA234: =ROUNDDOWN(T234*AC234,0) -> 0 | AB234: =O234/AA234 -> #DIV/0! | AD234: =AA234*AG234 -> 0 | AE234: =O234/AD234 -> #DIV/0! | AF234: =AD234/O234 -> #DIV/0! | AH234: =ROUNDDOWN(AR234*R234,0) -> 0 | AL234: =AJ234+AK234 -> 0 | AM234: =AL234/AH234 -> #DIV/0! | AN234: =O234/AL234 -> #DIV/0!
A235: Июль 2026 | B235: В2В | H235: =INT(P235*Q235) -> 0 | K235: =I235*J235*H235 -> 0 | L235: =0.22*M235 -> 0 | M235: =(H235*I235)/1.22 -> 0 | N235: =K235+M235 -> 0 | O235: =(H235*I235)+K235 -> 0 | R235: =(ROUNDDOWN(P235*Q235,0)) -> 0 | S235: =(ROUNDDOWN(O235/R235,0)) -> #DIV/0! | T235: =(ROUNDDOWN(V235*R235,0)) -> 0 | U235: =O235/T235 -> #DIV/0! | W235: =T235*Z235 -> 0 | X235: =O235/W235 -> #DIV/0! | Y235: =W235/O235 -> #DIV/0! | AA235: =ROUNDDOWN(T235*AC235,0) -> 0 | AB235: =O235/AA235 -> #DIV/0! | AD235: =AA235*AG235 -> 0 | AE235: =O235/AD235 -> #DIV/0! | AF235: =AD235/O235 -> #DIV/0! | AH235: =ROUNDDOWN(AR235*R235,0) -> 0 | AL235: =AJ235+AK235 -> 0 | AM235: =AL235/AH235 -> #DIV/0! | AN235: =O235/AL235 -> #DIV/0!
A236: Июль 2026 | B236: В2В | H236: =INT(P236*Q236) -> 0 | K236: =I236*J236*H236 -> 0 | L236: =0.22*M236 -> 0 | M236: =(H236*I236)/1.22 -> 0 | N236: =K236+M236 -> 0 | O236: =(H236*I236)+K236 -> 0 | R236: =(ROUNDDOWN(P236*Q236,0)) -> 0 | S236: =(ROUNDDOWN(O236/R236,0)) -> #DIV/0! | T236: =(ROUNDDOWN(V236*R236,0)) -> 0 | U236: =O236/T236 -> #DIV/0! | W236: =T236*Z236 -> 0 | X236: =O236/W236 -> #DIV/0! | Y236: =W236/O236 -> #DIV/0! | AA236: =ROUNDDOWN(T236*AC236,0) -> 0 | AB236: =O236/AA236 -> #DIV/0! | AD236: =AA236*AG236 -> 0 | AE236: =O236/AD236 -> #DIV/0! | AF236: =AD236/O236 -> #DIV/0! | AH236: =ROUNDDOWN(AR236*R236,0) -> 0 | AL236: =AJ236+AK236 -> 0 | AM236: =AL236/AH236 -> #DIV/0! | AN236: =O236/AL236 -> #DIV/0!
A237: Июль 2026 | B237: В2В | H237: =INT(P237*Q237) -> 0 | K237: =I237*J237*H237 -> 0 | L237: =0.22*M237 -> 0 | M237: =(H237*I237)/1.22 -> 0 | N237: =K237+M237 -> 0 | O237: =(H237*I237)+K237 -> 0 | R237: =(ROUNDDOWN(P237*Q237,0)) -> 0 | S237: =(ROUNDDOWN(O237/R237,0)) -> #DIV/0! | T237: =(ROUNDDOWN(V237*R237,0)) -> 0 | U237: =O237/T237 -> #DIV/0! | W237: =T237*Z237 -> 0 | X237: =O237/W237 -> #DIV/0! | Y237: =W237/O237 -> #DIV/0! | AA237: =ROUNDDOWN(T237*AC237,0) -> 0 | AB237: =O237/AA237 -> #DIV/0! | AD237: =AA237*AG237 -> 0 | AE237: =O237/AD237 -> #DIV/0! | AF237: =AD237/O237 -> #DIV/0! | AH237: =ROUNDDOWN(AR237*R237,0) -> 0 | AL237: =AJ237+AK237 -> 0 | AM237: =AL237/AH237 -> #DIV/0! | AN237: =O237/AL237 -> #DIV/0!
A238: Июль 2026 | B238: В2В | H238: =INT(P238*Q238) -> 0 | K238: =I238*J238*H238 -> 0 | L238: =0.22*M238 -> 0 | M238: =(H238*I238)/1.22 -> 0 | N238: =K238+M238 -> 0 | O238: =(H238*I238)+K238 -> 0 | R238: =(ROUNDDOWN(P238*Q238,0)) -> 0 | S238: =(ROUNDDOWN(O238/R238,0)) -> #DIV/0! | T238: =(ROUNDDOWN(V238*R238,0)) -> 0 | U238: =O238/T238 -> #DIV/0! | W238: =T238*Z238 -> 0 | X238: =O238/W238 -> #DIV/0! | Y238: =W238/O238 -> #DIV/0! | AA238: =ROUNDDOWN(T238*AC238,0) -> 0 | AB238: =O238/AA238 -> #DIV/0! | AD238: =AA238*AG238 -> 0 | AE238: =O238/AD238 -> #DIV/0! | AF238: =AD238/O238 -> #DIV/0! | AH238: =ROUNDDOWN(AR238*R238,0) -> 0 | AL238: =AJ238+AK238 -> 0 | AM238: =AL238/AH238 -> #DIV/0! | AN238: =O238/AL238 -> #DIV/0!
A239: Июль 2026 | B239: В2В | H239: =INT(P239*Q239) -> 0 | K239: =I239*J239*H239 -> 0 | L239: =0.22*M239 -> 0 | M239: =(H239*I239)/1.22 -> 0 | N239: =K239+M239 -> 0 | O239: =(H239*I239)+K239 -> 0 | R239: =(ROUNDDOWN(P239*Q239,0)) -> 0 | S239: =(ROUNDDOWN(O239/R239,0)) -> #DIV/0! | T239: =(ROUNDDOWN(V239*R239,0)) -> 0 | U239: =O239/T239 -> #DIV/0! | W239: =T239*Z239 -> 0 | X239: =O239/W239 -> #DIV/0! | Y239: =W239/O239 -> #DIV/0! | AA239: =ROUNDDOWN(T239*AC239,0) -> 0 | AB239: =O239/AA239 -> #DIV/0! | AD239: =AA239*AG239 -> 0 | AE239: =O239/AD239 -> #DIV/0! | AF239: =AD239/O239 -> #DIV/0! | AH239: =ROUNDDOWN(AR239*R239,0) -> 0 | AL239: =AJ239+AK239 -> 0 | AM239: =AL239/AH239 -> #DIV/0! | AN239: =O239/AL239 -> #DIV/0!
A240: Июль 2026 | B240: В2В | H240: =INT(P240*Q240) -> 0 | K240: =I240*J240*H240 -> 0 | L240: =0.22*M240 -> 0 | M240: =(H240*I240)/1.22 -> 0 | N240: =K240+M240 -> 0 | O240: =(H240*I240)+K240 -> 0 | R240: =(ROUNDDOWN(P240*Q240,0)) -> 0 | S240: =(ROUNDDOWN(O240/R240,0)) -> #DIV/0! | T240: =(ROUNDDOWN(V240*R240,0)) -> 0 | U240: =O240/T240 -> #DIV/0! | W240: =T240*Z240 -> 0 | X240: =O240/W240 -> #DIV/0! | Y240: =W240/O240 -> #DIV/0! | AA240: =ROUNDDOWN(T240*AC240,0) -> 0 | AB240: =O240/AA240 -> #DIV/0! | AD240: =AA240*AG240 -> 0 | AE240: =O240/AD240 -> #DIV/0! | AF240: =AD240/O240 -> #DIV/0! | AH240: =ROUNDDOWN(AR240*R240,0) -> 0 | AL240: =AJ240+AK240 -> 0 | AM240: =AL240/AH240 -> #DIV/0! | AN240: =O240/AL240 -> #DIV/0!
A241: Июль 2026 | B241: В2В | H241: =INT(P241*Q241) -> 0 | K241: =I241*J241*H241 -> 0 | L241: =0.22*M241 -> 0 | M241: =(H241*I241)/1.22 -> 0 | N241: =K241+M241 -> 0 | O241: =(H241*I241)+K241 -> 0 | R241: =(ROUNDDOWN(P241*Q241,0)) -> 0 | S241: =(ROUNDDOWN(O241/R241,0)) -> #DIV/0! | T241: =(ROUNDDOWN(V241*R241,0)) -> 0 | U241: =O241/T241 -> #DIV/0! | W241: =T241*Z241 -> 0 | X241: =O241/W241 -> #DIV/0! | Y241: =W241/O241 -> #DIV/0! | AA241: =ROUNDDOWN(T241*AC241,0) -> 0 | AB241: =O241/AA241 -> #DIV/0! | AD241: =AA241*AG241 -> 0 | AE241: =O241/AD241 -> #DIV/0! | AF241: =AD241/O241 -> #DIV/0! | AH241: =ROUNDDOWN(AR241*R241,0) -> 0 | AL241: =AJ241+AK241 -> 0 | AM241: =AL241/AH241 -> #DIV/0! | AN241: =O241/AL241 -> #DIV/0!
A242: Июль 2026 | B242: В2В | H242: =INT(P242*Q242) -> 0 | K242: =I242*J242*H242 -> 0 | L242: =0.22*M242 -> 0 | M242: =(H242*I242)/1.22 -> 0 | N242: =K242+M242 -> 0 | O242: =(H242*I242)+K242 -> 0 | R242: =(ROUNDDOWN(P242*Q242,0)) -> 0 | S242: =(ROUNDDOWN(O242/R242,0)) -> #DIV/0! | T242: =(ROUNDDOWN(V242*R242,0)) -> 0 | U242: =O242/T242 -> #DIV/0! | W242: =T242*Z242 -> 0 | X242: =O242/W242 -> #DIV/0! | Y242: =W242/O242 -> #DIV/0! | AA242: =ROUNDDOWN(T242*AC242,0) -> 0 | AB242: =O242/AA242 -> #DIV/0! | AD242: =AA242*AG242 -> 0 | AE242: =O242/AD242 -> #DIV/0! | AF242: =AD242/O242 -> #DIV/0! | AH242: =ROUNDDOWN(AR242*R242,0) -> 0 | AL242: =AJ242+AK242 -> 0 | AM242: =AL242/AH242 -> #DIV/0! | AN242: =O242/AL242 -> #DIV/0!
A243: Июль 2026 | B243: В2В | H243: =INT(P243*Q243) -> 0 | K243: =I243*J243*H243 -> 0 | L243: =0.22*M243 -> 0 | M243: =(H243*I243)/1.22 -> 0 | N243: =K243+M243 -> 0 | O243: =(H243*I243)+K243 -> 0 | R243: =(ROUNDDOWN(P243*Q243,0)) -> 0 | S243: =(ROUNDDOWN(O243/R243,0)) -> #DIV/0! | T243: =(ROUNDDOWN(V243*R243,0)) -> 0 | U243: =O243/T243 -> #DIV/0! | W243: =T243*Z243 -> 0 | X243: =O243/W243 -> #DIV/0! | Y243: =W243/O243 -> #DIV/0! | AA243: =ROUNDDOWN(T243*AC243,0) -> 0 | AB243: =O243/AA243 -> #DIV/0! | AD243: =AA243*AG243 -> 0 | AE243: =O243/AD243 -> #DIV/0! | AF243: =AD243/O243 -> #DIV/0! | AH243: =ROUNDDOWN(AR243*R243,0) -> 0 | AL243: =AJ243+AK243 -> 0 | AM243: =AL243/AH243 -> #DIV/0! | AN243: =O243/AL243 -> #DIV/0!
A244: Июль 2026 | B244: В2В | H244: =INT(P244*Q244) -> 0 | K244: =I244*J244*H244 -> 0 | L244: =0.22*M244 -> 0 | M244: =(H244*I244)/1.22 -> 0 | N244: =K244+M244 -> 0 | O244: =(H244*I244)+K244 -> 0 | R244: =(ROUNDDOWN(P244*Q244,0)) -> 0 | S244: =(ROUNDDOWN(O244/R244,0)) -> #DIV/0! | T244: =(ROUNDDOWN(V244*R244,0)) -> 0 | U244: =O244/T244 -> #DIV/0! | W244: =T244*Z244 -> 0 | X244: =O244/W244 -> #DIV/0! | Y244: =W244/O244 -> #DIV/0! | AA244: =ROUNDDOWN(T244*AC244,0) -> 0 | AB244: =O244/AA244 -> #DIV/0! | AD244: =AA244*AG244 -> 0 | AE244: =O244/AD244 -> #DIV/0! | AF244: =AD244/O244 -> #DIV/0! | AH244: =ROUNDDOWN(AR244*R244,0) -> 0 | AL244: =AJ244+AK244 -> 0 | AM244: =AL244/AH244 -> #DIV/0! | AN244: =O244/AL244 -> #DIV/0!
A245: Июль 2026 | B245: В2В | H245: =INT(P245*Q245) -> 0 | K245: =I245*J245*H245 -> 0 | L245: =0.22*M245 -> 0 | M245: =(H245*I245)/1.22 -> 0 | N245: =K245+M245 -> 0 | O245: =(H245*I245)+K245 -> 0 | R245: =(ROUNDDOWN(P245*Q245,0)) -> 0 | S245: =(ROUNDDOWN(O245/R245,0)) -> #DIV/0! | T245: =(ROUNDDOWN(V245*R245,0)) -> 0 | U245: =O245/T245 -> #DIV/0! | W245: =T245*Z245 -> 0 | X245: =O245/W245 -> #DIV/0! | Y245: =W245/O245 -> #DIV/0! | AA245: =ROUNDDOWN(T245*AC245,0) -> 0 | AB245: =O245/AA245 -> #DIV/0! | AD245: =AA245*AG245 -> 0 | AE245: =O245/AD245 -> #DIV/0! | AF245: =AD245/O245 -> #DIV/0! | AH245: =ROUNDDOWN(AR245*R245,0) -> 0 | AL245: =AJ245+AK245 -> 0 | AM245: =AL245/AH245 -> #DIV/0! | AN245: =O245/AL245 -> #DIV/0!
... A288: Июль 2026 | B288: В2В | H288: =INT(P288*Q288) -> 0 | K288: =I288*J288*H288 -> 0 | L288: =0.22*M288 -> 0 | M288: =(H288*I288)/1.22 -> 0 | N288: =K288+M288 -> 0 | O288: =(H288*I288)+K288 -> 0 | R288: =(ROUNDDOWN(P288*Q288,0)) -> 0 | S288: =(ROUNDDOWN(O288/R288,0)) -> #DIV/0! | T288: =(ROUNDDOWN(V288*R288,0)) -> 0 | U288: =O288/T288 -> #DIV/0! | W288: =T288*Z288 -> 0 | X288: =O288/W288 -> #DIV/0! | Y288: =W288/O288 -> #DIV/0! | AA288: =ROUNDDOWN(T288*AC288,0) -> 0 | AB288: =O288/AA288 -> #DIV/0! | AD288: =AA288*AG288 -> 0 | AE288: =O288/AD288 -> #DIV/0! | AF288: =AD288/O288 -> #DIV/0! | AH288: =ROUNDDOWN(AR288*R288,0) -> 0 | AL288: =AJ288+AK288 -> 0 | AM288: =AL288/AH288 -> #DIV/0! | AN288: =O288/AL288 -> #DIV/0!
A289: ИТОГО | B289: B2B | H289: =IFERROR(SUM(H234:H288),"-") -> 0 | I289: =IFERROR(SUM(I234:I288),"-") -> 0 | J289: =IFERROR(N289/M289-1,"-") -> - | K289: =IFERROR(N289-M289,"-") -> 0 | L289: =IFERROR(SUM(L234:L288),"-") -> 0 | M289: =IFERROR(SUM(M234:M288),"-") -> 0 | N289: =IFERROR(SUM(N234:N288),"-") -> 0 | O289: =IFERROR(SUM(O234:O288),"-") -> 0 | P289: =IFERROR(SUM(P234:P288),"-") -> 0 | Q289: =IFERROR(R289/P289, "-") -> - | R289: =IFERROR(SUM(R234:R288),"-") -> 0 | S289: =IFERROR(O289/R289, "-") -> - | T289: =IFERROR(SUM(T234:T288),"-") -> 0 | U289: =IFERROR(O289/T289, "-") -> - | V289: =IFERROR(R289/T289, "-") -> - | W289: =IFERROR(SUM(W234:W288),"-") -> 0 | X289: =IFERROR(O289/W289, "-") -> - | Y289: =IFERROR(W289/O289, "-") -> - | Z289: =IFERROR(W289/T289, "-") -> - | AA289: =IFERROR(SUM(AA234:AA288),"-") -> 0 | AB289: =IFERROR(O289/AA289, "-") -> - | AC289: =IFERROR(AA289/T289, "-") -> - | AD289: =IFERROR(SUM(AD234:AD288),"-") -> 0 | AE289: =IFERROR(O289/AD289, "-") -> - | AF289: =IFERROR(AD289/O289, "-") -> - | AG289: =IFERROR(AD289/AA289, "-") -> - | AH289: =IFERROR(SUM(AH234:AH288),"-") -> 0 | AI289: =IFERROR(ROUND(AVERAGE(AI234:AI288),0),"-") -> - | AJ289: =IFERROR(SUM(AJ234:AJ288),"-") -> 0 | AK289: =IFERROR(SUM(AK234:AK288),"-") -> 0 | AL289: =IFERROR(AK289+AJ289,"-") -> 0 | AM289: =IFERROR(AL289/AH289, "-") -> - | AN289: =IFERROR(O289/AL289, "-") -> - | AO289: =IFERROR(SUM(AO234:AO288),"-") -> 0 | AP289: =IFERROR(AVERAGE(AP234:AP288),"-") -> - | AR289: =IFERROR(AH289/R289, "-") -> -
A290: Июль 2026 | B290: B2C | H290: =INT(P290*Q290) -> 0 | K290: =I290*J290*H290 -> 0 | L290: =0.22*M290 -> 0 | M290: =(H290*I290)/1.22 -> 0 | N290: =K290+M290 -> 0 | O290: =(H290*I290)+K290 -> 0 | R290: =(ROUNDDOWN(P290*Q290,0)) -> 0 | S290: =(ROUNDDOWN(O290/R290,0)) -> #DIV/0! | T290: =(ROUNDDOWN(V290*R290,0)) -> 0 | U290: =O290/T290 -> #DIV/0! | W290: =T290*Z290 -> 0 | X290: =O290/W290 -> #DIV/0! | Y290: =W290/O290 -> #DIV/0! | AA290: =ROUNDDOWN(T290*AC290,0) -> 0 | AB290: =O290/AA290 -> #DIV/0! | AD290: =AA290*AG290 -> 0 | AE290: =O290/AD290 -> #DIV/0! | AF290: =AD290/O290 -> #DIV/0! | AH290: =ROUNDDOWN(AR290*R290,0) -> 0 | AL290: =AJ290+AK290 -> 0 | AM290: =AL290/AH290 -> #DIV/0! | AN290: =O290/AL290 -> #DIV/0!
A291: Июль 2026 | B291: B2C | H291: =INT(P291*Q291) -> 0 | K291: =I291*J291*H291 -> 0 | L291: =0.22*M291 -> 0 | M291: =(H291*I291)/1.22 -> 0 | N291: =K291+M291 -> 0 | O291: =(H291*I291)+K291 -> 0 | R291: =(ROUNDDOWN(P291*Q291,0)) -> 0 | S291: =(ROUNDDOWN(O291/R291,0)) -> #DIV/0! | T291: =(ROUNDDOWN(V291*R291,0)) -> 0 | U291: =O291/T291 -> #DIV/0! | W291: =T291*Z291 -> 0 | X291: =O291/W291 -> #DIV/0! | Y291: =W291/O291 -> #DIV/0! | AA291: =ROUNDDOWN(T291*AC291,0) -> 0 | AB291: =O291/AA291 -> #DIV/0! | AD291: =AA291*AG291 -> 0 | AE291: =O291/AD291 -> #DIV/0! | AF291: =AD291/O291 -> #DIV/0! | AH291: =ROUNDDOWN(AR291*R291,0) -> 0 | AL291: =AJ291+AK291 -> 0 | AM291: =AL291/AH291 -> #DIV/0! | AN291: =O291/AL291 -> #DIV/0!
A292: Июль 2026 | B292: B2C | H292: =INT(P292*Q292) -> 0 | K292: =I292*J292*H292 -> 0 | L292: =0.22*M292 -> 0 | M292: =(H292*I292)/1.22 -> 0 | N292: =K292+M292 -> 0 | O292: =(H292*I292)+K292 -> 0 | R292: =(ROUNDDOWN(P292*Q292,0)) -> 0 | S292: =(ROUNDDOWN(O292/R292,0)) -> #DIV/0! | T292: =(ROUNDDOWN(V292*R292,0)) -> 0 | U292: =O292/T292 -> #DIV/0! | W292: =T292*Z292 -> 0 | X292: =O292/W292 -> #DIV/0! | Y292: =W292/O292 -> #DIV/0! | AA292: =ROUNDDOWN(T292*AC292,0) -> 0 | AB292: =O292/AA292 -> #DIV/0! | AD292: =AA292*AG292 -> 0 | AE292: =O292/AD292 -> #DIV/0! | AF292: =AD292/O292 -> #DIV/0! | AH292: =ROUNDDOWN(AR292*R292,0) -> 0 | AL292: =AJ292+AK292 -> 0 | AM292: =AL292/AH292 -> #DIV/0! | AN292: =O292/AL292 -> #DIV/0!
A293: Июль 2026 | B293: B2C | H293: =INT(P293*Q293) -> 0 | K293: =I293*J293*H293 -> 0 | L293: =0.22*M293 -> 0 | M293: =(H293*I293)/1.22 -> 0 | N293: =K293+M293 -> 0 | O293: =(H293*I293)+K293 -> 0 | R293: =(ROUNDDOWN(P293*Q293,0)) -> 0 | S293: =(ROUNDDOWN(O293/R293,0)) -> #DIV/0! | T293: =(ROUNDDOWN(V293*R293,0)) -> 0 | U293: =O293/T293 -> #DIV/0! | W293: =T293*Z293 -> 0 | X293: =O293/W293 -> #DIV/0! | Y293: =W293/O293 -> #DIV/0! | AA293: =ROUNDDOWN(T293*AC293,0) -> 0 | AB293: =O293/AA293 -> #DIV/0! | AD293: =AA293*AG293 -> 0 | AE293: =O293/AD293 -> #DIV/0! | AF293: =AD293/O293 -> #DIV/0! | AH293: =ROUNDDOWN(AR293*R293,0) -> 0 | AL293: =AJ293+AK293 -> 0 | AM293: =AL293/AH293 -> #DIV/0! | AN293: =O293/AL293 -> #DIV/0!
A294: Июль 2026 | B294: B2C | H294: =INT(P294*Q294) -> 0 | K294: =I294*J294*H294 -> 0 | L294: =0.22*M294 -> 0 | M294: =(H294*I294)/1.22 -> 0 | N294: =K294+M294 -> 0 | O294: =(H294*I294)+K294 -> 0 | R294: =(ROUNDDOWN(P294*Q294,0)) -> 0 | S294: =(ROUNDDOWN(O294/R294,0)) -> #DIV/0! | T294: =(ROUNDDOWN(V294*R294,0)) -> 0 | U294: =O294/T294 -> #DIV/0! | W294: =T294*Z294 -> 0 | X294: =O294/W294 -> #DIV/0! | Y294: =W294/O294 -> #DIV/0! | AA294: =ROUNDDOWN(T294*AC294,0) -> 0 | AB294: =O294/AA294 -> #DIV/0! | AD294: =AA294*AG294 -> 0 | AE294: =O294/AD294 -> #DIV/0! | AF294: =AD294/O294 -> #DIV/0! | AH294: =ROUNDDOWN(AR294*R294,0) -> 0 | AL294: =AJ294+AK294 -> 0 | AM294: =AL294/AH294 -> #DIV/0! | AN294: =O294/AL294 -> #DIV/0!
A295: Июль 2026 | B295: B2C | H295: =INT(P295*Q295) -> 0 | K295: =I295*J295*H295 -> 0 | L295: =0.22*M295 -> 0 | M295: =(H295*I295)/1.22 -> 0 | N295: =K295+M295 -> 0 | O295: =(H295*I295)+K295 -> 0 | R295: =(ROUNDDOWN(P295*Q295,0)) -> 0 | S295: =(ROUNDDOWN(O295/R295,0)) -> #DIV/0! | T295: =(ROUNDDOWN(V295*R295,0)) -> 0 | U295: =O295/T295 -> #DIV/0! | W295: =T295*Z295 -> 0 | X295: =O295/W295 -> #DIV/0! | Y295: =W295/O295 -> #DIV/0! | AA295: =ROUNDDOWN(T295*AC295,0) -> 0 | AB295: =O295/AA295 -> #DIV/0! | AD295: =AA295*AG295 -> 0 | AE295: =O295/AD295 -> #DIV/0! | AF295: =AD295/O295 -> #DIV/0! | AH295: =ROUNDDOWN(AR295*R295,0) -> 0 | AL295: =AJ295+AK295 -> 0 | AM295: =AL295/AH295 -> #DIV/0! | AN295: =O295/AL295 -> #DIV/0!
A296: Июль 2026 | B296: B2C | H296: =INT(P296*Q296) -> 0 | K296: =I296*J296*H296 -> 0 | L296: =0.22*M296 -> 0 | M296: =(H296*I296)/1.22 -> 0 | N296: =K296+M296 -> 0 | O296: =(H296*I296)+K296 -> 0 | R296: =(ROUNDDOWN(P296*Q296,0)) -> 0 | S296: =(ROUNDDOWN(O296/R296,0)) -> #DIV/0! | T296: =(ROUNDDOWN(V296*R296,0)) -> 0 | U296: =O296/T296 -> #DIV/0! | W296: =T296*Z296 -> 0 | X296: =O296/W296 -> #DIV/0! | Y296: =W296/O296 -> #DIV/0! | AA296: =ROUNDDOWN(T296*AC296,0) -> 0 | AB296: =O296/AA296 -> #DIV/0! | AD296: =AA296*AG296 -> 0 | AE296: =O296/AD296 -> #DIV/0! | AF296: =AD296/O296 -> #DIV/0! | AH296: =ROUNDDOWN(AR296*R296,0) -> 0 | AL296: =AJ296+AK296 -> 0 | AM296: =AL296/AH296 -> #DIV/0! | AN296: =O296/AL296 -> #DIV/0!
A297: Июль 2026 | B297: B2C | H297: =INT(P297*Q297) -> 0 | K297: =I297*J297*H297 -> 0 | L297: =0.22*M297 -> 0 | M297: =(H297*I297)/1.22 -> 0 | N297: =K297+M297 -> 0 | O297: =(H297*I297)+K297 -> 0 | R297: =(ROUNDDOWN(P297*Q297,0)) -> 0 | S297: =(ROUNDDOWN(O297/R297,0)) -> #DIV/0! | T297: =(ROUNDDOWN(V297*R297,0)) -> 0 | U297: =O297/T297 -> #DIV/0! | W297: =T297*Z297 -> 0 | X297: =O297/W297 -> #DIV/0! | Y297: =W297/O297 -> #DIV/0! | AA297: =ROUNDDOWN(T297*AC297,0) -> 0 | AB297: =O297/AA297 -> #DIV/0! | AD297: =AA297*AG297 -> 0 | AE297: =O297/AD297 -> #DIV/0! | AF297: =AD297/O297 -> #DIV/0! | AH297: =ROUNDDOWN(AR297*R297,0) -> 0 | AL297: =AJ297+AK297 -> 0 | AM297: =AL297/AH297 -> #DIV/0! | AN297: =O297/AL297 -> #DIV/0!
A298: Июль 2026 | B298: B2C | H298: =INT(P298*Q298) -> 0 | K298: =I298*J298*H298 -> 0 | L298: =0.22*M298 -> 0 | M298: =(H298*I298)/1.22 -> 0 | N298: =K298+M298 -> 0 | O298: =(H298*I298)+K298 -> 0 | R298: =(ROUNDDOWN(P298*Q298,0)) -> 0 | S298: =(ROUNDDOWN(O298/R298,0)) -> #DIV/0! | T298: =(ROUNDDOWN(V298*R298,0)) -> 0 | U298: =O298/T298 -> #DIV/0! | W298: =T298*Z298 -> 0 | X298: =O298/W298 -> #DIV/0! | Y298: =W298/O298 -> #DIV/0! | AA298: =ROUNDDOWN(T298*AC298,0) -> 0 | AB298: =O298/AA298 -> #DIV/0! | AD298: =AA298*AG298 -> 0 | AE298: =O298/AD298 -> #DIV/0! | AF298: =AD298/O298 -> #DIV/0! | AH298: =ROUNDDOWN(AR298*R298,0) -> 0 | AL298: =AJ298+AK298 -> 0 | AM298: =AL298/AH298 -> #DIV/0! | AN298: =O298/AL298 -> #DIV/0!
A299: Июль 2026 | B299: B2C | H299: =INT(P299*Q299) -> 0 | K299: =I299*J299*H299 -> 0 | L299: =0.22*M299 -> 0 | M299: =(H299*I299)/1.22 -> 0 | N299: =K299+M299 -> 0 | O299: =(H299*I299)+K299 -> 0 | R299: =(ROUNDDOWN(P299*Q299,0)) -> 0 | S299: =(ROUNDDOWN(O299/R299,0)) -> #DIV/0! | T299: =(ROUNDDOWN(V299*R299,0)) -> 0 | U299: =O299/T299 -> #DIV/0! | W299: =T299*Z299 -> 0 | X299: =O299/W299 -> #DIV/0! | Y299: =W299/O299 -> #DIV/0! | AA299: =ROUNDDOWN(T299*AC299,0) -> 0 | AB299: =O299/AA299 -> #DIV/0! | AD299: =AA299*AG299 -> 0 | AE299: =O299/AD299 -> #DIV/0! | AF299: =AD299/O299 -> #DIV/0! | AH299: =ROUNDDOWN(AR299*R299,0) -> 0 | AL299: =AJ299+AK299 -> 0 | AM299: =AL299/AH299 -> #DIV/0! | AN299: =O299/AL299 -> #DIV/0!
A300: Июль 2026 | B300: B2C | H300: =INT(P300*Q300) -> 0 | K300: =I300*J300*H300 -> 0 | L300: =0.22*M300 -> 0 | M300: =(H300*I300)/1.22 -> 0 | N300: =K300+M300 -> 0 | O300: =(H300*I300)+K300 -> 0 | R300: =(ROUNDDOWN(P300*Q300,0)) -> 0 | S300: =(ROUNDDOWN(O300/R300,0)) -> #DIV/0! | T300: =(ROUNDDOWN(V300*R300,0)) -> 0 | U300: =O300/T300 -> #DIV/0! | W300: =T300*Z300 -> 0 | X300: =O300/W300 -> #DIV/0! | Y300: =W300/O300 -> #DIV/0! | AA300: =ROUNDDOWN(T300*AC300,0) -> 0 | AB300: =O300/AA300 -> #DIV/0! | AD300: =AA300*AG300 -> 0 | AE300: =O300/AD300 -> #DIV/0! | AF300: =AD300/O300 -> #DIV/0! | AH300: =ROUNDDOWN(AR300*R300,0) -> 0 | AL300: =AJ300+AK300 -> 0 | AM300: =AL300/AH300 -> #DIV/0! | AN300: =O300/AL300 -> #DIV/0!
A301: Июль 2026 | B301: B2C | H301: =INT(P301*Q301) -> 0 | K301: =I301*J301*H301 -> 0 | L301: =0.22*M301 -> 0 | M301: =(H301*I301)/1.22 -> 0 | N301: =K301+M301 -> 0 | O301: =(H301*I301)+K301 -> 0 | R301: =(ROUNDDOWN(P301*Q301,0)) -> 0 | S301: =(ROUNDDOWN(O301/R301,0)) -> #DIV/0! | T301: =(ROUNDDOWN(V301*R301,0)) -> 0 | U301: =O301/T301 -> #DIV/0! | W301: =T301*Z301 -> 0 | X301: =O301/W301 -> #DIV/0! | Y301: =W301/O301 -> #DIV/0! | AA301: =ROUNDDOWN(T301*AC301,0) -> 0 | AB301: =O301/AA301 -> #DIV/0! | AD301: =AA301*AG301 -> 0 | AE301: =O301/AD301 -> #DIV/0! | AF301: =AD301/O301 -> #DIV/0! | AH301: =ROUNDDOWN(AR301*R301,0) -> 0 | AL301: =AJ301+AK301 -> 0 | AM301: =AL301/AH301 -> #DIV/0! | AN301: =O301/AL301 -> #DIV/0!
... A344: Июль 2026 | B344: B2C | H344: =INT(P344*Q344) -> 0 | K344: =I344*J344*H344 -> 0 | L344: =0.22*M344 -> 0 | M344: =(H344*I344)/1.22 -> 0 | N344: =K344+M344 -> 0 | O344: =(H344*I344)+K344 -> 0 | R344: =(ROUNDDOWN(P344*Q344,0)) -> 0 | S344: =(ROUNDDOWN(O344/R344,0)) -> #DIV/0! | T344: =(ROUNDDOWN(V344*R344,0)) -> 0 | U344: =O344/T344 -> #DIV/0! | W344: =T344*Z344 -> 0 | X344: =O344/W344 -> #DIV/0! | Y344: =W344/O344 -> #DIV/0! | AA344: =ROUNDDOWN(T344*AC344,0) -> 0 | AB344: =O344/AA344 -> #DIV/0! | AD344: =AA344*AG344 -> 0 | AE344: =O344/AD344 -> #DIV/0! | AF344: =AD344/O344 -> #DIV/0! | AH344: =ROUNDDOWN(AR344*R344,0) -> 0 | AL344: =AJ344+AK344 -> 0 | AM344: =AL344/AH344 -> #DIV/0! | AN344: =O344/AL344 -> #DIV/0!
A345: ИТОГО | B345: B2B | H345: =IFERROR(SUM(H290:H344),"-") -> 0 | I345: =IFERROR(SUM(I290:I344),"-") -> 0 | J345: =IFERROR(N345/M345-1,"-") -> - | K345: =IFERROR(N345-M345,"-") -> 0 | L345: =IFERROR(SUM(L290:L344),"-") -> 0 | M345: =IFERROR(SUM(M290:M344),"-") -> 0 | N345: =IFERROR(SUM(N290:N344),"-") -> 0 | O345: =IFERROR(SUM(O290:O344),"-") -> 0 | P345: =IFERROR(SUM(P290:P344),"-") -> 0 | Q345: =IFERROR(R345/P345, "-") -> - | R345: =IFERROR(SUM(R290:R344),"-") -> 0 | S345: =IFERROR(O345/R345, "-") -> - | T345: =IFERROR(SUM(T290:T344),"-") -> 0 | U345: =IFERROR(O345/T345, "-") -> - | V345: =IFERROR(R345/T345, "-") -> - | W345: =IFERROR(SUM(W290:W344),"-") -> 0 | X345: =IFERROR(O345/W345, "-") -> - | Y345: =IFERROR(W345/O345, "-") -> - | Z345: =IFERROR(W345/T345, "-") -> - | AA345: =SUM(AA290:AA344) -> 0 | AB345: =IFERROR(O345/AA345, "-") -> - | AC345: =IFERROR(AA345/T345, "-") -> - | AD345: =IFERROR(SUM(AD290:AD344),"-") -> 0 | AE345: =IFERROR(O345/AD345, "-") -> - | AF345: =IFERROR(AD345/O345, "-") -> - | AG345: =IFERROR(AD345/AA345, "-") -> - | AH345: =IFERROR(SUM(AH290:AH344),"-") -> 0 | AI345: =IFERROR(ROUND(AVERAGE(AI290:AI344),0),"-") -> - | AJ345: =IFERROR(SUM(AJ290:AJ344),"-") -> 0 | AK345: =IFERROR(SUM(AK290:AK344),"-") -> 0 | AL345: =IFERROR(AK345+AJ345,"-") -> 0 | AM345: =IFERROR(AL345/AH345, "-") -> - | AN345: =IFERROR(O345/AL345, "-") -> - | AO345: =IFERROR(SUM(AO290:AO344),"-") -> 0 | AP345: =IFERROR(AVERAGE(AP290:AP344),"-") -> - | AR345: =IFERROR(AH345/R345, "-") -> -
A346: ИТОГО | B346: Июль | H346: =IFERROR(H289+H345,"-") -> 0 | I346: =IFERROR(I289+I345,"-") -> 0 | J346: =IFERROR(N346/M346-1,"-") -> - | K346: =IFERROR(K289+K345,"-") -> 0 | L346: =IFERROR(L289+L345,"-") -> 0 | M346: =IFERROR(M289+M345,"-") -> 0 | N346: =IFERROR(N289+N345,"-") -> 0 | O346: =IFERROR(O289+O345,"-") -> 0 | P346: =IFERROR(P289+P345,"-") -> 0 | Q346: =IFERROR(R346/P346, "-") -> - | R346: =IFERROR(R289+R345,"-") -> 0 | S346: =IFERROR(O346/R346, "-") -> - | T346: =IFERROR(T289+T345,"-") -> 0 | U346: =IFERROR(O346/T346, "-") -> - | V346: =IFERROR(R346/T346, "-") -> - | W346: =IFERROR(W289+W345,"-") -> 0 | X346: =IFERROR(O346/W346, "-") -> - | Y346: =IFERROR(W346/O346, "-") -> - | Z346: =IFERROR(W346/T346, "-") -> - | AA346: =IFERROR(AA289+AA345,"-") -> 0 | AB346: =IFERROR(AB289+AB345,"-") -> - | AC346: =IFERROR(AA346/T346, "-") -> - | AD346: =IFERROR(AD289+AD345,"-") -> 0 | AE346: =IFERROR(O346/AD346, "-") -> - | AF346: =IFERROR(AD346/O346, "-") -> - | AG346: =IFERROR(AD346/AA346, "-") -> - | AH346: =IFERROR(AH289+AH345,"-") -> 0 | AI346: =IFERROR(ROUND(AVERAGE(AI289,AI345),0),"-") -> - | AJ346: =IFERROR(AJ289+AJ345,"-") -> 0 | AK346: =IFERROR(AK289+AK345,"-") -> 0 | AL346: =IFERROR(AK346+AJ346,"-") -> 0 | AM346: =IFERROR(AL346/AH346, "-") -> - | AN346: =IFERROR(O346/AL346, "-") -> - | AO346: =IFERROR(AO289+AO345,"-") -> 0 | AP346: =IFERROR(AVERAGE(AP289,AP345),"-") -> - | AR346: =IFERROR(AH346/R346, "-") -> -
A349: Месяц+Год | B349: Тип клиента | C349: Площадка | D349: Формат | E349: Гео | F349: Модель закупки | G349: Единица закупки | H349: Кол-во единиц закупки | I349: Стоимость единицы закупки, руб. с НДС | J349: АК% | K349: АК, руб. (абс.) | L349: НДС, руб. (абс.) | M349: Тотал бюджет, руб. без НДС и АК | N349: Тотал бюджет, руб. без НДС и с учетом АК | O349: Тотал бюджет руб. с учетом НДС и АК | P349: Кол-во показов | Q349: CTR, % | R349: Кол-во кликов | S349: СРС, руб. с НДС | T349: Кол-во оформленных заказов | U349: Стоимость оформл. заказа, руб. с НДС | V349: CR (конверсия из клика в заказ), % | W349: Оформленный доход, руб. с НДС | X349: ДРР от оформл. дохода, % | Y349: ROAS офомл. (Доход/Бюджет) | Z349: Средний чек по оформл. доходу, с НДС | AA349: Кол-во отгруженных заказов | AB349: Стоимость отгр. заказа, руб. с НДС | AC349: CR 2 (конверсия из оформленного в отгруженный заказ), % | AD349: Выручка (отгруженный доход), руб. с НДС | AE349: ДРР от выручки, % | AF349: ROAS отгр. (Выручка/Бюджет) | AG349: Средний чек по выручке, с НДС | AH349: Кол-во клиентов | AI349: Частота заказа | AJ349: Кол-во абсолютно новых клиентов (ранее не заказывали) | AK349: Кол-во вернувшихся клиентов (не заказывали более 12 мес) | AL349: Кол-во новых клиентов (абсолютно новые + вернувшиеся) | AM349: Доля новых клиентов, % | AN349: САС, руб. | AO349: СРА: кол-во активных веб мастеров | AP349: СРА: % аппрува
A350: Август 2026 | B350: В2В | H350: =INT(P350*Q350) -> 0 | K350: =I350*J350*H350 -> 0 | L350: =0.22*M350 -> 0 | M350: =(H350*I350)/1.22 -> 0 | N350: =K350+M350 -> 0 | O350: =(H350*I350)+K350 -> 0 | R350: =(ROUNDDOWN(P350*Q350,0)) -> 0 | S350: =(ROUNDDOWN(O350/R350,0)) -> #DIV/0! | T350: =(ROUNDDOWN(V350*R350,0)) -> 0 | U350: =O350/T350 -> #DIV/0! | W350: =T350*Z350 -> 0 | X350: =O350/W350 -> #DIV/0! | Y350: =W350/O350 -> #DIV/0! | AA350: =ROUNDDOWN(T350*AC350,0) -> 0 | AB350: =O350/AA350 -> #DIV/0! | AD350: =AA350*AG350 -> 0 | AE350: =O350/AD350 -> #DIV/0! | AF350: =AD350/O350 -> #DIV/0! | AH350: =ROUNDDOWN(AR350*R350,0) -> 0 | AL350: =AJ350+AK350 -> 0 | AM350: =AL350/AH350 -> #DIV/0! | AN350: =O350/AL350 -> #DIV/0!
A351: Август 2026 | B351: В2В | H351: =INT(P351*Q351) -> 0 | K351: =I351*J351*H351 -> 0 | L351: =0.22*M351 -> 0 | M351: =(H351*I351)/1.22 -> 0 | N351: =K351+M351 -> 0 | O351: =(H351*I351)+K351 -> 0 | R351: =(ROUNDDOWN(P351*Q351,0)) -> 0 | S351: =(ROUNDDOWN(O351/R351,0)) -> #DIV/0! | T351: =(ROUNDDOWN(V351*R351,0)) -> 0 | U351: =O351/T351 -> #DIV/0! | W351: =T351*Z351 -> 0 | X351: =O351/W351 -> #DIV/0! | Y351: =W351/O351 -> #DIV/0! | AA351: =ROUNDDOWN(T351*AC351,0) -> 0 | AB351: =O351/AA351 -> #DIV/0! | AD351: =AA351*AG351 -> 0 | AE351: =O351/AD351 -> #DIV/0! | AF351: =AD351/O351 -> #DIV/0! | AH351: =ROUNDDOWN(AR351*R351,0) -> 0 | AL351: =AJ351+AK351 -> 0 | AM351: =AL351/AH351 -> #DIV/0! | AN351: =O351/AL351 -> #DIV/0!
A352: Август 2026 | B352: В2В | H352: =INT(P352*Q352) -> 0 | K352: =I352*J352*H352 -> 0 | L352: =0.22*M352 -> 0 | M352: =(H352*I352)/1.22 -> 0 | N352: =K352+M352 -> 0 | O352: =(H352*I352)+K352 -> 0 | R352: =(ROUNDDOWN(P352*Q352,0)) -> 0 | S352: =(ROUNDDOWN(O352/R352,0)) -> #DIV/0! | T352: =(ROUNDDOWN(V352*R352,0)) -> 0 | U352: =O352/T352 -> #DIV/0! | W352: =T352*Z352 -> 0 | X352: =O352/W352 -> #DIV/0! | Y352: =W352/O352 -> #DIV/0! | AA352: =ROUNDDOWN(T352*AC352,0) -> 0 | AB352: =O352/AA352 -> #DIV/0! | AD352: =AA352*AG352 -> 0 | AE352: =O352/AD352 -> #DIV/0! | AF352: =AD352/O352 -> #DIV/0! | AH352: =ROUNDDOWN(AR352*R352,0) -> 0 | AL352: =AJ352+AK352 -> 0 | AM352: =AL352/AH352 -> #DIV/0! | AN352: =O352/AL352 -> #DIV/0!
A353: Август 2026 | B353: В2В | H353: =INT(P353*Q353) -> 0 | K353: =I353*J353*H353 -> 0 | L353: =0.22*M353 -> 0 | M353: =(H353*I353)/1.22 -> 0 | N353: =K353+M353 -> 0 | O353: =(H353*I353)+K353 -> 0 | R353: =(ROUNDDOWN(P353*Q353,0)) -> 0 | S353: =(ROUNDDOWN(O353/R353,0)) -> #DIV/0! | T353: =(ROUNDDOWN(V353*R353,0)) -> 0 | U353: =O353/T353 -> #DIV/0! | W353: =T353*Z353 -> 0 | X353: =O353/W353 -> #DIV/0! | Y353: =W353/O353 -> #DIV/0! | AA353: =ROUNDDOWN(T353*AC353,0) -> 0 | AB353: =O353/AA353 -> #DIV/0! | AD353: =AA353*AG353 -> 0 | AE353: =O353/AD353 -> #DIV/0! | AF353: =AD353/O353 -> #DIV/0! | AH353: =ROUNDDOWN(AR353*R353,0) -> 0 | AL353: =AJ353+AK353 -> 0 | AM353: =AL353/AH353 -> #DIV/0! | AN353: =O353/AL353 -> #DIV/0!
A354: Август 2026 | B354: В2В | H354: =INT(P354*Q354) -> 0 | K354: =I354*J354*H354 -> 0 | L354: =0.22*M354 -> 0 | M354: =(H354*I354)/1.22 -> 0 | N354: =K354+M354 -> 0 | O354: =(H354*I354)+K354 -> 0 | R354: =(ROUNDDOWN(P354*Q354,0)) -> 0 | S354: =(ROUNDDOWN(O354/R354,0)) -> #DIV/0! | T354: =(ROUNDDOWN(V354*R354,0)) -> 0 | U354: =O354/T354 -> #DIV/0! | W354: =T354*Z354 -> 0 | X354: =O354/W354 -> #DIV/0! | Y354: =W354/O354 -> #DIV/0! | AA354: =ROUNDDOWN(T354*AC354,0) -> 0 | AB354: =O354/AA354 -> #DIV/0! | AD354: =AA354*AG354 -> 0 | AE354: =O354/AD354 -> #DIV/0! | AF354: =AD354/O354 -> #DIV/0! | AH354: =ROUNDDOWN(AR354*R354,0) -> 0 | AL354: =AJ354+AK354 -> 0 | AM354: =AL354/AH354 -> #DIV/0! | AN354: =O354/AL354 -> #DIV/0!
A355: Август 2026 | B355: В2В | H355: =INT(P355*Q355) -> 0 | K355: =I355*J355*H355 -> 0 | L355: =0.22*M355 -> 0 | M355: =(H355*I355)/1.22 -> 0 | N355: =K355+M355 -> 0 | O355: =(H355*I355)+K355 -> 0 | R355: =(ROUNDDOWN(P355*Q355,0)) -> 0 | S355: =(ROUNDDOWN(O355/R355,0)) -> #DIV/0! | T355: =(ROUNDDOWN(V355*R355,0)) -> 0 | U355: =O355/T355 -> #DIV/0! | W355: =T355*Z355 -> 0 | X355: =O355/W355 -> #DIV/0! | Y355: =W355/O355 -> #DIV/0! | AA355: =ROUNDDOWN(T355*AC355,0) -> 0 | AB355: =O355/AA355 -> #DIV/0! | AD355: =AA355*AG355 -> 0 | AE355: =O355/AD355 -> #DIV/0! | AF355: =AD355/O355 -> #DIV/0! | AH355: =ROUNDDOWN(AR355*R355,0) -> 0 | AL355: =AJ355+AK355 -> 0 | AM355: =AL355/AH355 -> #DIV/0! | AN355: =O355/AL355 -> #DIV/0!
A356: Август 2026 | B356: В2В | H356: =INT(P356*Q356) -> 0 | K356: =I356*J356*H356 -> 0 | L356: =0.22*M356 -> 0 | M356: =(H356*I356)/1.22 -> 0 | N356: =K356+M356 -> 0 | O356: =(H356*I356)+K356 -> 0 | R356: =(ROUNDDOWN(P356*Q356,0)) -> 0 | S356: =(ROUNDDOWN(O356/R356,0)) -> #DIV/0! | T356: =(ROUNDDOWN(V356*R356,0)) -> 0 | U356: =O356/T356 -> #DIV/0! | W356: =T356*Z356 -> 0 | X356: =O356/W356 -> #DIV/0! | Y356: =W356/O356 -> #DIV/0! | AA356: =ROUNDDOWN(T356*AC356,0) -> 0 | AB356: =O356/AA356 -> #DIV/0! | AD356: =AA356*AG356 -> 0 | AE356: =O356/AD356 -> #DIV/0! | AF356: =AD356/O356 -> #DIV/0! | AH356: =ROUNDDOWN(AR356*R356,0) -> 0 | AL356: =AJ356+AK356 -> 0 | AM356: =AL356/AH356 -> #DIV/0! | AN356: =O356/AL356 -> #DIV/0!
A357: Август 2026 | B357: В2В | H357: =INT(P357*Q357) -> 0 | K357: =I357*J357*H357 -> 0 | L357: =0.22*M357 -> 0 | M357: =(H357*I357)/1.22 -> 0 | N357: =K357+M357 -> 0 | O357: =(H357*I357)+K357 -> 0 | R357: =(ROUNDDOWN(P357*Q357,0)) -> 0 | S357: =(ROUNDDOWN(O357/R357,0)) -> #DIV/0! | T357: =(ROUNDDOWN(V357*R357,0)) -> 0 | U357: =O357/T357 -> #DIV/0! | W357: =T357*Z357 -> 0 | X357: =O357/W357 -> #DIV/0! | Y357: =W357/O357 -> #DIV/0! | AA357: =ROUNDDOWN(T357*AC357,0) -> 0 | AB357: =O357/AA357 -> #DIV/0! | AD357: =AA357*AG357 -> 0 | AE357: =O357/AD357 -> #DIV/0! | AF357: =AD357/O357 -> #DIV/0! | AH357: =ROUNDDOWN(AR357*R357,0) -> 0 | AL357: =AJ357+AK357 -> 0 | AM357: =AL357/AH357 -> #DIV/0! | AN357: =O357/AL357 -> #DIV/0!
A358: Август 2026 | B358: В2В | H358: =INT(P358*Q358) -> 0 | K358: =I358*J358*H358 -> 0 | L358: =0.22*M358 -> 0 | M358: =(H358*I358)/1.22 -> 0 | N358: =K358+M358 -> 0 | O358: =(H358*I358)+K358 -> 0 | R358: =(ROUNDDOWN(P358*Q358,0)) -> 0 | S358: =(ROUNDDOWN(O358/R358,0)) -> #DIV/0! | T358: =(ROUNDDOWN(V358*R358,0)) -> 0 | U358: =O358/T358 -> #DIV/0! | W358: =T358*Z358 -> 0 | X358: =O358/W358 -> #DIV/0! | Y358: =W358/O358 -> #DIV/0! | AA358: =ROUNDDOWN(T358*AC358,0) -> 0 | AB358: =O358/AA358 -> #DIV/0! | AD358: =AA358*AG358 -> 0 | AE358: =O358/AD358 -> #DIV/0! | AF358: =AD358/O358 -> #DIV/0! | AH358: =ROUNDDOWN(AR358*R358,0) -> 0 | AL358: =AJ358+AK358 -> 0 | AM358: =AL358/AH358 -> #DIV/0! | AN358: =O358/AL358 -> #DIV/0!
...

Sheet Periods_RF
A1: Месяц+Год | B1: Тип клиента | C1: Площадка | D1: Формат | E1: Гео | F1: Модель закупки | G1: Единица закупки | H1: Кол-во единиц закупки | I1: Стоимость единицы закупки, руб. с НДС | J1: АК% | K1: АК, руб. (абс.) | L1: НДС, руб. (абс.) | M1: Тотал бюджет, руб. без НДС и АК | N1: Тотал бюджет, руб. без НДС и с учетом АК | O1: Тотал бюджет руб. с учетом НДС и АК | P1: Кол-во показов | Q1: CTR, % | R1: Кол-во кликов | S1: СРС, руб. с НДС | T1: Кол-во оформленных заказов | U1: Стоимость оформл. заказа, руб. с НДС | V1: CR (конверсия из клика в заказ), % | W1: Оформленный доход, руб. с НДС | X1: ДРР от оформл. дохода, % | Y1: ROAS офомл. (Доход/Бюджет) | Z1: Средний чек по оформл. доходу, с НДС | AA1: Кол-во отгруженных заказов | AB1: Стоимость отгр. заказа, руб. с НДС | AC1: CR 2 (конверсия из оформленного в отгруженный заказ), % | AD1: Выручка (отгруженный доход), руб. с НДС | AE1: ДРР от выручки, % | AF1: ROAS отгр. (Выручка/Бюджет) | AG1: Средний чек по выручке, с НДС | AH1: Кол-во клиентов | AI1: Частота заказа | AJ1: Кол-во абсолютно новых клиентов (ранее не заказывали) | AK1: Кол-во вернувшихся клиентов (не заказывали более 12 мес) | AL1: Кол-во новых клиентов (абсолютно новые + вернувшиеся) | AM1: Доля новых клиентов, % | AN1: САС, руб. | AO1: СРА: кол-во активных веб мастеров | AP1: СРА: % аппрува | AR1: СR из клика в клиента, %
A2: Май 2026 | B2: В2В | H2: =INT(P2*Q2) -> 0 | K2: =I2*J2*H2 -> 0 | L2: =0.22*M2 -> 0 | M2: =(H2*I2)/1.22 -> 0 | N2: =K2+M2 -> 0 | O2: =(H2*I2)+K2 -> 0 | R2: =(ROUNDDOWN(P2*Q2,0)) -> 0 | S2: =(ROUNDDOWN(O2/R2,0)) -> #DIV/0! | T2: =INT(R2*V2) -> 0 | U2: =O2/T2 -> #DIV/0! | W2: =T2*Z2 -> 0 | X2: =O2/W2 -> #DIV/0! | Y2: =W2/O2 -> #DIV/0! | AA2: =ROUNDDOWN(T2*AC2,0) -> 0 | AB2: =O2/AA2 -> #DIV/0! | AD2: =AA2*AG2 -> 0 | AE2: =O2/AD2 -> #DIV/0! | AF2: =AD2/O2 -> #DIV/0! | AH2: =ROUNDDOWN(AR2*R2,0) -> 0 | AL2: =AJ2+AK2 -> 0 | AM2: =AL2/AH2 -> #DIV/0! | AN2: =O2/AL2 -> #DIV/0!
A3: Май 2026 | B3: В2В | H3: =INT(P3*Q3) -> 0 | K3: =I3*J3*H3 -> 0 | L3: =0.22*M3 -> 0 | M3: =(H3*I3)/1.22 -> 0 | N3: =K3+M3 -> 0 | O3: =(H3*I3)+K3 -> 0 | R3: =(ROUNDDOWN(P3*Q3,0)) -> 0 | S3: =(ROUNDDOWN(O3/R3,0)) -> #DIV/0! | T3: =INT(R3*V3) -> 0 | U3: =O3/T3 -> #DIV/0! | W3: =T3*Z3 -> 0 | X3: =O3/W3 -> #DIV/0! | Y3: =W3/O3 -> #DIV/0! | AA3: =ROUNDDOWN(T3*AC3,0) -> 0 | AB3: =O3/AA3 -> #DIV/0! | AD3: =AA3*AG3 -> 0 | AE3: =O3/AD3 -> #DIV/0! | AF3: =AD3/O3 -> #DIV/0! | AH3: =ROUNDDOWN(AR3*R3,0) -> 0 | AL3: =AJ3+AK3 -> 0 | AM3: =AL3/AH3 -> #DIV/0! | AN3: =O3/AL3 -> #DIV/0!
A4: Май 2026 | B4: В2В | H4: =INT(P4*Q4) -> 0 | K4: =I4*J4*H4 -> 0 | L4: =0.22*M4 -> 0 | M4: =(H4*I4)/1.22 -> 0 | N4: =K4+M4 -> 0 | O4: =(H4*I4)+K4 -> 0 | R4: =(ROUNDDOWN(P4*Q4,0)) -> 0 | S4: =(ROUNDDOWN(O4/R4,0)) -> #DIV/0! | T4: =INT(R4*V4) -> 0 | U4: =O4/T4 -> #DIV/0! | W4: =T4*Z4 -> 0 | X4: =O4/W4 -> #DIV/0! | Y4: =W4/O4 -> #DIV/0! | AA4: =ROUNDDOWN(T4*AC4,0) -> 0 | AB4: =O4/AA4 -> #DIV/0! | AD4: =AA4*AG4 -> 0 | AE4: =O4/AD4 -> #DIV/0! | AF4: =AD4/O4 -> #DIV/0! | AH4: =ROUNDDOWN(AR4*R4,0) -> 0 | AL4: =AJ4+AK4 -> 0 | AM4: =AL4/AH4 -> #DIV/0! | AN4: =O4/AL4 -> #DIV/0!
A5: Май 2026 | B5: В2В | H5: =INT(P5*Q5) -> 0 | K5: =I5*J5*H5 -> 0 | L5: =0.22*M5 -> 0 | M5: =(H5*I5)/1.22 -> 0 | N5: =K5+M5 -> 0 | O5: =(H5*I5)+K5 -> 0 | R5: =(ROUNDDOWN(P5*Q5,0)) -> 0 | S5: =(ROUNDDOWN(O5/R5,0)) -> #DIV/0! | T5: =INT(R5*V5) -> 0 | U5: =O5/T5 -> #DIV/0! | W5: =T5*Z5 -> 0 | X5: =O5/W5 -> #DIV/0! | Y5: =W5/O5 -> #DIV/0! | AA5: =ROUNDDOWN(T5*AC5,0) -> 0 | AB5: =O5/AA5 -> #DIV/0! | AD5: =AA5*AG5 -> 0 | AE5: =O5/AD5 -> #DIV/0! | AF5: =AD5/O5 -> #DIV/0! | AH5: =ROUNDDOWN(AR5*R5,0) -> 0 | AL5: =AJ5+AK5 -> 0 | AM5: =AL5/AH5 -> #DIV/0! | AN5: =O5/AL5 -> #DIV/0!
A6: Май 2026 | B6: В2В | H6: =INT(P6*Q6) -> 0 | K6: =I6*J6*H6 -> 0 | L6: =0.22*M6 -> 0 | M6: =(H6*I6)/1.22 -> 0 | N6: =K6+M6 -> 0 | O6: =(H6*I6)+K6 -> 0 | R6: =(ROUNDDOWN(P6*Q6,0)) -> 0 | S6: =(ROUNDDOWN(O6/R6,0)) -> #DIV/0! | T6: =INT(R6*V6) -> 0 | U6: =O6/T6 -> #DIV/0! | W6: =T6*Z6 -> 0 | X6: =O6/W6 -> #DIV/0! | Y6: =W6/O6 -> #DIV/0! | AA6: =ROUNDDOWN(T6*AC6,0) -> 0 | AB6: =O6/AA6 -> #DIV/0! | AD6: =AA6*AG6 -> 0 | AE6: =O6/AD6 -> #DIV/0! | AF6: =AD6/O6 -> #DIV/0! | AH6: =ROUNDDOWN(AR6*R6,0) -> 0 | AL6: =AJ6+AK6 -> 0 | AM6: =AL6/AH6 -> #DIV/0! | AN6: =O6/AL6 -> #DIV/0!
A7: Май 2026 | B7: В2В | H7: =INT(P7*Q7) -> 0 | K7: =I7*J7*H7 -> 0 | L7: =0.22*M7 -> 0 | M7: =(H7*I7)/1.22 -> 0 | N7: =K7+M7 -> 0 | O7: =(H7*I7)+K7 -> 0 | R7: =(ROUNDDOWN(P7*Q7,0)) -> 0 | S7: =(ROUNDDOWN(O7/R7,0)) -> #DIV/0! | T7: =INT(R7*V7) -> 0 | U7: =O7/T7 -> #DIV/0! | W7: =T7*Z7 -> 0 | X7: =O7/W7 -> #DIV/0! | Y7: =W7/O7 -> #DIV/0! | AA7: =ROUNDDOWN(T7*AC7,0) -> 0 | AB7: =O7/AA7 -> #DIV/0! | AD7: =AA7*AG7 -> 0 | AE7: =O7/AD7 -> #DIV/0! | AF7: =AD7/O7 -> #DIV/0! | AH7: =ROUNDDOWN(AR7*R7,0) -> 0 | AL7: =AJ7+AK7 -> 0 | AM7: =AL7/AH7 -> #DIV/0! | AN7: =O7/AL7 -> #DIV/0!
A8: Май 2026 | B8: В2В | H8: =INT(P8*Q8) -> 0 | K8: =I8*J8*H8 -> 0 | L8: =0.22*M8 -> 0 | M8: =(H8*I8)/1.22 -> 0 | N8: =K8+M8 -> 0 | O8: =(H8*I8)+K8 -> 0 | R8: =(ROUNDDOWN(P8*Q8,0)) -> 0 | S8: =(ROUNDDOWN(O8/R8,0)) -> #DIV/0! | T8: =INT(R8*V8) -> 0 | U8: =O8/T8 -> #DIV/0! | W8: =T8*Z8 -> 0 | X8: =O8/W8 -> #DIV/0! | Y8: =W8/O8 -> #DIV/0! | AA8: =ROUNDDOWN(T8*AC8,0) -> 0 | AB8: =O8/AA8 -> #DIV/0! | AD8: =AA8*AG8 -> 0 | AE8: =O8/AD8 -> #DIV/0! | AF8: =AD8/O8 -> #DIV/0! | AH8: =ROUNDDOWN(AR8*R8,0) -> 0 | AL8: =AJ8+AK8 -> 0 | AM8: =AL8/AH8 -> #DIV/0! | AN8: =O8/AL8 -> #DIV/0!
A9: Май 2026 | B9: В2В | H9: =INT(P9*Q9) -> 0 | K9: =I9*J9*H9 -> 0 | L9: =0.22*M9 -> 0 | M9: =(H9*I9)/1.22 -> 0 | N9: =K9+M9 -> 0 | O9: =(H9*I9)+K9 -> 0 | R9: =(ROUNDDOWN(P9*Q9,0)) -> 0 | S9: =(ROUNDDOWN(O9/R9,0)) -> #DIV/0! | T9: =INT(R9*V9) -> 0 | U9: =O9/T9 -> #DIV/0! | W9: =T9*Z9 -> 0 | X9: =O9/W9 -> #DIV/0! | Y9: =W9/O9 -> #DIV/0! | AA9: =ROUNDDOWN(T9*AC9,0) -> 0 | AB9: =O9/AA9 -> #DIV/0! | AD9: =AA9*AG9 -> 0 | AE9: =O9/AD9 -> #DIV/0! | AF9: =AD9/O9 -> #DIV/0! | AH9: =ROUNDDOWN(AR9*R9,0) -> 0 | AL9: =AJ9+AK9 -> 0 | AM9: =AL9/AH9 -> #DIV/0! | AN9: =O9/AL9 -> #DIV/0!
A10: Май 2026 | B10: В2В | H10: =INT(P10*Q10) -> 0 | K10: =I10*J10*H10 -> 0 | L10: =0.22*M10 -> 0 | M10: =(H10*I10)/1.22 -> 0 | N10: =K10+M10 -> 0 | O10: =(H10*I10)+K10 -> 0 | R10: =(ROUNDDOWN(P10*Q10,0)) -> 0 | S10: =(ROUNDDOWN(O10/R10,0)) -> #DIV/0! | T10: =INT(R10*V10) -> 0 | U10: =O10/T10 -> #DIV/0! | W10: =T10*Z10 -> 0 | X10: =O10/W10 -> #DIV/0! | Y10: =W10/O10 -> #DIV/0! | AA10: =ROUNDDOWN(T10*AC10,0) -> 0 | AB10: =O10/AA10 -> #DIV/0! | AD10: =AA10*AG10 -> 0 | AE10: =O10/AD10 -> #DIV/0! | AF10: =AD10/O10 -> #DIV/0! | AH10: =ROUNDDOWN(AR10*R10,0) -> 0 | AL10: =AJ10+AK10 -> 0 | AM10: =AL10/AH10 -> #DIV/0! | AN10: =O10/AL10 -> #DIV/0!
A11: Май 2026 | B11: В2В | H11: =INT(P11*Q11) -> 0 | K11: =I11*J11*H11 -> 0 | L11: =0.22*M11 -> 0 | M11: =(H11*I11)/1.22 -> 0 | N11: =K11+M11 -> 0 | O11: =(H11*I11)+K11 -> 0 | R11: =(ROUNDDOWN(P11*Q11,0)) -> 0 | S11: =(ROUNDDOWN(O11/R11,0)) -> #DIV/0! | T11: =INT(R11*V11) -> 0 | U11: =O11/T11 -> #DIV/0! | W11: =T11*Z11 -> 0 | X11: =O11/W11 -> #DIV/0! | Y11: =W11/O11 -> #DIV/0! | AA11: =ROUNDDOWN(T11*AC11,0) -> 0 | AB11: =O11/AA11 -> #DIV/0! | AD11: =AA11*AG11 -> 0 | AE11: =O11/AD11 -> #DIV/0! | AF11: =AD11/O11 -> #DIV/0! | AH11: =ROUNDDOWN(AR11*R11,0) -> 0 | AL11: =AJ11+AK11 -> 0 | AM11: =AL11/AH11 -> #DIV/0! | AN11: =O11/AL11 -> #DIV/0!
A12: Май 2026 | B12: В2В | H12: =INT(P12*Q12) -> 0 | K12: =I12*J12*H12 -> 0 | L12: =0.22*M12 -> 0 | M12: =(H12*I12)/1.22 -> 0 | N12: =K12+M12 -> 0 | O12: =(H12*I12)+K12 -> 0 | R12: =(ROUNDDOWN(P12*Q12,0)) -> 0 | S12: =(ROUNDDOWN(O12/R12,0)) -> #DIV/0! | T12: =INT(R12*V12) -> 0 | U12: =O12/T12 -> #DIV/0! | W12: =T12*Z12 -> 0 | X12: =O12/W12 -> #DIV/0! | Y12: =W12/O12 -> #DIV/0! | AA12: =ROUNDDOWN(T12*AC12,0) -> 0 | AB12: =O12/AA12 -> #DIV/0! | AD12: =AA12*AG12 -> 0 | AE12: =O12/AD12 -> #DIV/0! | AF12: =AD12/O12 -> #DIV/0! | AH12: =ROUNDDOWN(AR12*R12,0) -> 0 | AL12: =AJ12+AK12 -> 0 | AM12: =AL12/AH12 -> #DIV/0! | AN12: =O12/AL12 -> #DIV/0!
A13: Май 2026 | B13: В2В | H13: =INT(P13*Q13) -> 0 | K13: =I13*J13*H13 -> 0 | L13: =0.22*M13 -> 0 | M13: =(H13*I13)/1.22 -> 0 | N13: =K13+M13 -> 0 | O13: =(H13*I13)+K13 -> 0 | R13: =(ROUNDDOWN(P13*Q13,0)) -> 0 | S13: =(ROUNDDOWN(O13/R13,0)) -> #DIV/0! | T13: =INT(R13*V13) -> 0 | U13: =O13/T13 -> #DIV/0! | W13: =T13*Z13 -> 0 | X13: =O13/W13 -> #DIV/0! | Y13: =W13/O13 -> #DIV/0! | AA13: =ROUNDDOWN(T13*AC13,0) -> 0 | AB13: =O13/AA13 -> #DIV/0! | AD13: =AA13*AG13 -> 0 | AE13: =O13/AD13 -> #DIV/0! | AF13: =AD13/O13 -> #DIV/0! | AH13: =ROUNDDOWN(AR13*R13,0) -> 0 | AL13: =AJ13+AK13 -> 0 | AM13: =AL13/AH13 -> #DIV/0! | AN13: =O13/AL13 -> #DIV/0!
... A56: Май 2026 | B56: В2В | H56: =INT(P56*Q56) -> 0 | K56: =I56*J56*H56 -> 0 | L56: =0.22*M56 -> 0 | M56: =(H56*I56)/1.22 -> 0 | N56: =K56+M56 -> 0 | O56: =(H56*I56)+K56 -> 0 | R56: =(ROUNDDOWN(P56*Q56,0)) -> 0 | S56: =(ROUNDDOWN(O56/R56,0)) -> #DIV/0! | T56: =INT(R56*V56) -> 0 | U56: =O56/T56 -> #DIV/0! | W56: =T56*Z56 -> 0 | X56: =O56/W56 -> #DIV/0! | Y56: =W56/O56 -> #DIV/0! | AA56: =ROUNDDOWN(T56*AC56,0) -> 0 | AB56: =O56/AA56 -> #DIV/0! | AD56: =AA56*AG56 -> 0 | AE56: =O56/AD56 -> #DIV/0! | AF56: =AD56/O56 -> #DIV/0! | AH56: =ROUNDDOWN(AR56*R56,0) -> 0 | AL56: =AJ56+AK56 -> 0 | AM56: =AL56/AH56 -> #DIV/0! | AN56: =O56/AL56 -> #DIV/0!
A57: ИТОГО | B57: B2B | H57: =IFERROR(SUM(H2:H56),"-") -> 0 | I57: =IFERROR(SUM(I2:I56),"-") -> 0 | J57: =IFERROR(N57/M57-1,"-") -> - | K57: =IFERROR(N57-M57,"-") -> 0 | L57: =IFERROR(SUM(L2:L56),"-") -> 0 | M57: =IFERROR(SUM(M2:M56),"-") -> 0 | N57: =IFERROR(SUM(N2:N56),"-") -> 0 | O57: =IFERROR(SUM(O2:O56),"-") -> 0 | P57: =IFERROR(SUM(P2:P56),"-") -> 0 | Q57: =IFERROR(R57/P57, "-") -> - | R57: =IFERROR(SUM(R2:R56),"-") -> 0 | S57: =IFERROR(O57/R57, "-") -> - | T57: =IFERROR(SUM(T2:T56),"-") -> 0 | U57: =IFERROR(O57/T57, "-") -> - | V57: =IFERROR(R57/T57, "-") -> - | W57: =IFERROR(SUM(W2:W56),"-") -> 0 | X57: =IFERROR(O57/W57, "-") -> - | Y57: =IFERROR(W57/O57, "-") -> - | Z57: =IFERROR(W57/T57, "-") -> - | AA57: =IFERROR(SUM(AA2:AA56),"-") -> 0 | AB57: =IFERROR(O57/AA57, "-") -> - | AC57: =IFERROR(AA57/T57, "-") -> - | AD57: =IFERROR(SUM(AD2:AD56),"-") -> 0 | AE57: =IFERROR(O57/AD57, "-") -> - | AF57: =IFERROR(AD57/O57, "-") -> - | AG57: =IFERROR(AD57/AA57, "-") -> - | AH57: =IFERROR(SUM(AH2:AH56),"-") -> 0 | AI57: =IFERROR(ROUND(AVERAGE(AI2:AI56),0),"-") -> - | AJ57: =IFERROR(SUM(AJ2:AJ56),"-") -> 0 | AK57: =IFERROR(SUM(AK2:AK56),"-") -> 0 | AL57: =IFERROR(AK57+AJ57,"-") -> 0 | AM57: =IFERROR(AL57/AH57, "-") -> - | AN57: =IFERROR(O57/AL57, "-") -> - | AO57: =IFERROR(SUM(AO2:AO56),"-") -> 0 | AP57: =IFERROR(AVERAGE(AP2:AP56),"-") -> - | AR57: =IFERROR(AH57/R57, "-") -> -
A58: Май 2026 | B58: B2C | H58: =INT(P58*Q58) -> 0 | K58: =I58*J58*H58 -> 0 | L58: =0.22*M58 -> 0 | M58: =(H58*I58)/1.22 -> 0 | N58: =K58+M58 -> 0 | O58: =(H58*I58)+K58 -> 0 | R58: =(ROUNDDOWN(P58*Q58,0)) -> 0 | S58: =(ROUNDDOWN(O58/R58,0)) -> #DIV/0! | T58: =INT(R58*V58) -> 0 | U58: =O58/T58 -> #DIV/0! | W58: =T58*Z58 -> 0 | X58: =O58/W58 -> #DIV/0! | Y58: =W58/O58 -> #DIV/0! | AA58: =ROUNDDOWN(T58*AC58,0) -> 0 | AB58: =O58/AA58 -> #DIV/0! | AD58: =AA58*AG58 -> 0 | AE58: =O58/AD58 -> #DIV/0! | AF58: =AD58/O58 -> #DIV/0! | AH58: =ROUNDDOWN(AR58*R58,0) -> 0 | AL58: =AJ58+AK58 -> 0 | AM58: =AL58/AH58 -> #DIV/0! | AN58: =O58/AL58 -> #DIV/0!
A59: Май 2026 | B59: B2C | H59: =INT(P59*Q59) -> 0 | K59: =I59*J59*H59 -> 0 | L59: =0.22*M59 -> 0 | M59: =(H59*I59)/1.22 -> 0 | N59: =K59+M59 -> 0 | O59: =(H59*I59)+K59 -> 0 | R59: =(ROUNDDOWN(P59*Q59,0)) -> 0 | S59: =(ROUNDDOWN(O59/R59,0)) -> #DIV/0! | T59: =INT(R59*V59) -> 0 | U59: =O59/T59 -> #DIV/0! | W59: =T59*Z59 -> 0 | X59: =O59/W59 -> #DIV/0! | Y59: =W59/O59 -> #DIV/0! | AA59: =ROUNDDOWN(T59*AC59,0) -> 0 | AB59: =O59/AA59 -> #DIV/0! | AD59: =AA59*AG59 -> 0 | AE59: =O59/AD59 -> #DIV/0! | AF59: =AD59/O59 -> #DIV/0! | AH59: =ROUNDDOWN(AR59*R59,0) -> 0 | AL59: =AJ59+AK59 -> 0 | AM59: =AL59/AH59 -> #DIV/0! | AN59: =O59/AL59 -> #DIV/0!
A60: Май 2026 | B60: B2C | H60: =INT(P60*Q60) -> 0 | K60: =I60*J60*H60 -> 0 | L60: =0.22*M60 -> 0 | M60: =(H60*I60)/1.22 -> 0 | N60: =K60+M60 -> 0 | O60: =(H60*I60)+K60 -> 0 | R60: =(ROUNDDOWN(P60*Q60,0)) -> 0 | S60: =(ROUNDDOWN(O60/R60,0)) -> #DIV/0! | T60: =INT(R60*V60) -> 0 | U60: =O60/T60 -> #DIV/0! | W60: =T60*Z60 -> 0 | X60: =O60/W60 -> #DIV/0! | Y60: =W60/O60 -> #DIV/0! | AA60: =ROUNDDOWN(T60*AC60,0) -> 0 | AB60: =O60/AA60 -> #DIV/0! | AD60: =AA60*AG60 -> 0 | AE60: =O60/AD60 -> #DIV/0! | AF60: =AD60/O60 -> #DIV/0! | AH60: =ROUNDDOWN(AR60*R60,0) -> 0 | AL60: =AJ60+AK60 -> 0 | AM60: =AL60/AH60 -> #DIV/0! | AN60: =O60/AL60 -> #DIV/0!
A61: Май 2026 | B61: B2C | H61: =INT(P61*Q61) -> 0 | K61: =I61*J61*H61 -> 0 | L61: =0.22*M61 -> 0 | M61: =(H61*I61)/1.22 -> 0 | N61: =K61+M61 -> 0 | O61: =(H61*I61)+K61 -> 0 | R61: =(ROUNDDOWN(P61*Q61,0)) -> 0 | S61: =(ROUNDDOWN(O61/R61,0)) -> #DIV/0! | T61: =INT(R61*V61) -> 0 | U61: =O61/T61 -> #DIV/0! | W61: =T61*Z61 -> 0 | X61: =O61/W61 -> #DIV/0! | Y61: =W61/O61 -> #DIV/0! | AA61: =ROUNDDOWN(T61*AC61,0) -> 0 | AB61: =O61/AA61 -> #DIV/0! | AD61: =AA61*AG61 -> 0 | AE61: =O61/AD61 -> #DIV/0! | AF61: =AD61/O61 -> #DIV/0! | AH61: =ROUNDDOWN(AR61*R61,0) -> 0 | AL61: =AJ61+AK61 -> 0 | AM61: =AL61/AH61 -> #DIV/0! | AN61: =O61/AL61 -> #DIV/0!
A62: Май 2026 | B62: B2C | H62: =INT(P62*Q62) -> 0 | K62: =I62*J62*H62 -> 0 | L62: =0.22*M62 -> 0 | M62: =(H62*I62)/1.22 -> 0 | N62: =K62+M62 -> 0 | O62: =(H62*I62)+K62 -> 0 | R62: =(ROUNDDOWN(P62*Q62,0)) -> 0 | S62: =(ROUNDDOWN(O62/R62,0)) -> #DIV/0! | T62: =INT(R62*V62) -> 0 | U62: =O62/T62 -> #DIV/0! | W62: =T62*Z62 -> 0 | X62: =O62/W62 -> #DIV/0! | Y62: =W62/O62 -> #DIV/0! | AA62: =ROUNDDOWN(T62*AC62,0) -> 0 | AB62: =O62/AA62 -> #DIV/0! | AD62: =AA62*AG62 -> 0 | AE62: =O62/AD62 -> #DIV/0! | AF62: =AD62/O62 -> #DIV/0! | AH62: =ROUNDDOWN(AR62*R62,0) -> 0 | AL62: =AJ62+AK62 -> 0 | AM62: =AL62/AH62 -> #DIV/0! | AN62: =O62/AL62 -> #DIV/0!
