Workbook

Sheet МП_Total
B2: Рекламная система | C2: Рекламный формат, размер, вид размещения | D2: Таргетинги | F2: Январь | G2: Февраль | H2: Март | I2: Апрель | J2: Май | K2: Июнь | L2: Июль | M2: Август | N2: Сентябрь | O2: Октябрь | P2: Ноябрь | Q2: Декабрь | S2: Период | T2: Модель закупки | U2: Стоимость единицы закупки (без НДС) | V2: Кол-во единиц закупки | X2: Стоимость (без НДС) | Y2: СК, % | Z2: Стоимость с учетом СК (без НДС) | AA2: АК, % | AB2: Итоговая стоимость (без НДС) | AC2: Итоговая стоимость (с НДС) | AD2: Доля рекламного бюджета, % | AF2: Показы | AG2: Частота (весь срок) | AH2: Охват | AI2: CPM (с НДС) | AJ2: CPT (с НДС) | AK2: Доступная емкость аудитории | AL2: SOV, % | AN2: CTR, % | AO2: Клики | AP2: CPC (с НДС) | AR2: CR, % | AS2: Конверсии | AT2: CPA (с НДС) | AV2: ДРР, % | AW2: Средний чек | AX2: Доход | AZ2: RTR, % | BA2: Дочитывания | BB2: CPR (с НДС) | BC2: % открытий статьи | BD2: Открытия статьи | BF2: ER, % | BG2: Вовлечения | BH2: CPE (с НДС)
T3: CPC | U3: =IFERROR(X3/V3,"-") -> - | V3: =IFERROR(МП_Periods!I3+МП_Periods!I16+МП_Periods!I29+МП_Periods!I42+МП_Periods!I55+МП_Periods!I68+МП_Periods!I81+МП_Periods!I94+МП_Periods!I107+МП_Periods!I120+МП_Periods!I133+МП_Periods!I146,"-") -> 0 | X3: =SUM(МП_Periods!K3,МП_Periods!K16,МП_Periods!K29,МП_Periods!K42,МП_Periods!K55,МП_Periods!K68,МП_Periods!K81,МП_Periods!K94,МП_Periods!K107,МП_Periods!K120,МП_Periods!K133,МП_Periods!K146) -> 0 | Y3: =IFERROR(1-(Z3/X3),"-") -> - | Z3: =SUM(МП_Periods!M3,МП_Periods!M16,МП_Periods!M29,МП_Periods!M42,МП_Periods!M55,МП_Periods!M68,МП_Periods!M81,МП_Periods!M94,МП_Periods!M107,МП_Periods!M120,МП_Periods!M133,МП_Periods!M146) -> 0 | AA3: =IFERROR((AB3/Z3)-1,"-") -> - | AB3: =SUM(МП_Periods!O3,МП_Periods!O16,МП_Periods!O29,МП_Periods!O42,МП_Periods!O55,МП_Periods!O68,МП_Periods!O81,МП_Periods!O94,МП_Periods!O107,МП_Periods!O120,МП_Periods!O133,МП_Periods!O146) -> 0 | AC3: =SUM(МП_Periods!P3,МП_Periods!P16,МП_Periods!P29,МП_Periods!P42,МП_Periods!P55,МП_Periods!P68,МП_Periods!P81,МП_Periods!P94,МП_Periods!P107,МП_Periods!P120,МП_Periods!P133,МП_Periods!P146) -> 0 | AD3: =IFERROR(AC3/$AC$13,"-") -> - | AF3: =SUM(МП_Periods!S3,МП_Periods!S16,МП_Periods!S29,МП_Periods!S42,МП_Periods!S55,МП_Periods!S68,МП_Periods!S81,МП_Periods!S94,МП_Periods!S107,МП_Periods!S120,МП_Periods!S133,МП_Periods!S146) -> 0 | AG3: =IFERROR(AF3/AH3,"-") -> - | AH3: =IFERROR(МП_Periods!U3+МП_Periods!U16+МП_Periods!U29+МП_Periods!U42+МП_Periods!U55+МП_Periods!U68+МП_Periods!U81+МП_Periods!U94+МП_Periods!U107+МП_Periods!U120+МП_Periods!U133+МП_Periods!U146,"-") -> - | AI3: =IFERROR(AC3/AF3*1000,"-") -> - | AJ3: =IFERROR(AC3/AH3*1000,"-") -> - | AK3: =SUM(МП_Periods!X3,МП_Periods!X16,МП_Periods!X29,МП_Periods!X42,МП_Periods!X55,МП_Periods!X68,МП_Periods!X81,МП_Periods!X94,МП_Periods!X107,МП_Periods!X120,МП_Periods!X133,МП_Periods!X146) -> 0 | AL3: =IFERROR(#REF!/AK3,"-") -> - | AN3: =IFERROR(AO3/AF3,"-") -> - | AO3: =SUM(МП_Periods!AB3,МП_Periods!AB16,МП_Periods!AB29,МП_Periods!AB42,МП_Periods!AB55,МП_Periods!AB68,МП_Periods!AB81,МП_Periods!AB94,МП_Periods!AB107,МП_Periods!AB120,МП_Periods!AB133,МП_Periods!AB146) -> 0 | AP3: =IFERROR(AC3/AO3,"-") -> - | AR3: =IFERROR(AS3/AO3,"-") -> - | AS3: =SUM(МП_Periods!AF3,МП_Periods!AF16,МП_Periods!AF29,МП_Periods!AF42,МП_Periods!AF55,МП_Periods!AF68,МП_Periods!AF81,МП_Periods!AF94,МП_Periods!AF107,МП_Periods!AF120,МП_Periods!AF133,МП_Periods!AF146) -> 0 | AT3: =IFERROR(AC3/AS3,"-") -> - | AV3: =IFERROR(AC3/AX3,"-") -> - | AW3: =IFERROR(AX3/AS3,"-") -> - | AX3: =SUM(МП_Periods!AO3,МП_Periods!AO16,МП_Periods!AO29,МП_Periods!AO42,МП_Periods!AO55,МП_Periods!AO68,МП_Periods!AO81,МП_Periods!AO94,МП_Periods!AO107,МП_Periods!AO120,МП_Periods!AO133,МП_Periods!AO146) -> 0 | AZ3: =IFERROR(BA3/AF3,"-") -> - | BA3: =IFERROR(#REF!+#REF!+#REF!+#REF!+#REF!+#REF!+#REF!+#REF!+#REF!+#REF!+#REF!+#REF!,"-") -> - | BB3: =IFERROR(AC3/BA3,"-") -> - | BC3: =IFERROR(BD3/AF3,"-") -> - | BD3: =IFERROR(#REF!+#REF!+#REF!+#REF!+#REF!+#REF!+#REF!+#REF!+#REF!+#REF!+#REF!+#REF!,"-") -> - | BF3: =IFERROR(BG3/AF3,"-") -> - | BG3: =IFERROR(#REF!+#REF!+#REF!+#REF!+#REF!+#REF!+#REF!+#REF!+#REF!+#REF!+#REF!+#REF!,"-") -> - | BH3: =IFERROR(AC3/BG3,"-") -> -
T4: CPC | U4: =IFERROR(X4/V4,"-") -> - | V4: =IFERROR(МП_Periods!I4+МП_Periods!I17+МП_Periods!I30+МП_Periods!I48+МП_Periods!I56+МП_Periods!I69+МП_Periods!I82+МП_Periods!I95+МП_Periods!I108+МП_Periods!I121+МП_Periods!I134+МП_Periods!I147,"-") -> 0 | X4: =SUM(МП_Periods!K4,МП_Periods!K17,МП_Periods!K30,МП_Periods!K43,МП_Periods!K56,МП_Periods!K69,МП_Periods!K82,МП_Periods!K95,МП_Periods!K108,МП_Periods!K121,МП_Periods!K134,МП_Periods!K147) -> 0 | Y4: =IFERROR(1-(Z4/X4),"-") -> - | Z4: =SUM(МП_Periods!M4,МП_Periods!M17,МП_Periods!M30,МП_Periods!M43,МП_Periods!M56,МП_Periods!M69,МП_Periods!M82,МП_Periods!M95,МП_Periods!M108,МП_Periods!M121,МП_Periods!M134,МП_Periods!M147) -> 0 | AA4: =IFERROR((AB4/Z4)-1,"-") -> - | AB4: =SUM(МП_Periods!O4,МП_Periods!O17,МП_Periods!O30,МП_Periods!O43,МП_Periods!O56,МП_Periods!O69,МП_Periods!O82,МП_Periods!O95,МП_Periods!O108,МП_Periods!O121,МП_Periods!O134,МП_Periods!O147) -> 0 | AC4: =SUM(МП_Periods!P4,МП_Periods!P17,МП_Periods!P30,МП_Periods!P43,МП_Periods!P56,МП_Periods!P69,МП_Periods!P82,МП_Periods!P95,МП_Periods!P108,МП_Periods!P121,МП_Periods!P134,МП_Periods!P147) -> 0 | AD4: =IFERROR(AC4/$AC$13,"-") -> - | AF4: =SUM(МП_Periods!S4,МП_Periods!S17,МП_Periods!S30,МП_Periods!S43,МП_Periods!S56,МП_Periods!S69,МП_Periods!S82,МП_Periods!S95,МП_Periods!S108,МП_Periods!S121,МП_Periods!S134,МП_Periods!S147) -> 0 | AG4: =IFERROR(AF4/AH4,"-") -> - | AH4: =IFERROR(МП_Periods!U4+МП_Periods!U17+МП_Periods!U30+МП_Periods!U48+МП_Periods!U56+МП_Periods!U69+МП_Periods!U82+МП_Periods!U95+МП_Periods!U108+МП_Periods!U121+МП_Periods!U134+МП_Periods!U147,"-") -> - | AI4: =IFERROR(AC4/AF4*1000,"-") -> - | AJ4: =IFERROR(AC4/AH4*1000,"-") -> - | AK4: =IFERROR(MAX(МП_Periods!X4,МП_Periods!X17,МП_Periods!X30,МП_Periods!X48,МП_Periods!X56,МП_Periods!X69,МП_Periods!X82,МП_Periods!X95,МП_Periods!X108,МП_Periods!X121,МП_Periods!X134,МП_Periods!X147),"-") -> 0 | AL4: =IFERROR(#REF!/AK4,"-") -> - | AN4: =IFERROR(AO4/AF4,"-") -> - | AO4: =SUM(МП_Periods!AB4,МП_Periods!AB17,МП_Periods!AB30,МП_Periods!AB43,МП_Periods!AB56,МП_Periods!AB69,МП_Periods!AB82,МП_Periods!AB95,МП_Periods!AB108,МП_Periods!AB121,МП_Periods!AB134,МП_Periods!AB147) -> 0 | AP4: =IFERROR(AC4/AO4,"-") -> - | AR4: =IFERROR(AS4/AO4,"-") -> - | AS4: =SUM(МП_Periods!AF4,МП_Periods!AF17,МП_Periods!AF30,МП_Periods!AF43,МП_Periods!AF56,МП_Periods!AF69,МП_Periods!AF82,МП_Periods!AF95,МП_Periods!AF108,МП_Periods!AF121,МП_Periods!AF134,МП_Periods!AF147) -> 0 | AT4: =IFERROR(AC4/AS4,"-") -> - | AV4: =IFERROR(AC4/AX4,"-") -> - | AW4: =IFERROR(AX4/AS4,"-") -> - | AX4: =SUM(МП_Periods!AO4,МП_Periods!AO17,МП_Periods!AO30,МП_Periods!AO43,МП_Periods!AO56,МП_Periods!AO69,МП_Periods!AO82,МП_Periods!AO95,МП_Periods!AO108,МП_Periods!AO121,МП_Periods!AO134,МП_Periods!AO147) -> 0 | AZ4: =IFERROR(BA4/AF4,"-") -> - | BA4: =IFERROR(#REF!+#REF!+#REF!+#REF!+#REF!+#REF!+#REF!+#REF!+#REF!+#REF!+#REF!+#REF!,"-") -> - | BB4: =IFERROR(AC4/BA4,"-") -> - | BC4: =IFERROR(BD4/AF4,"-") -> - | BD4: =IFERROR(#REF!+#REF!+#REF!+#REF!+#REF!+#REF!+#REF!+#REF!+#REF!+#REF!+#REF!+#REF!,"-") -> - | BF4: =IFERROR(BG4/AF4,"-") -> - | BG4: =IFERROR(#REF!+#REF!+#REF!+#REF!+#REF!+#REF!+#REF!+#REF!+#REF!+#REF!+#REF!+#REF!,"-") -> - | BH4: =IFERROR(AC4/BG4,"-") -> -
T5: CPC | U5: =IFERROR(X5/V5,"-") -> - | V5: =IFERROR(МП_Periods!I5+МП_Periods!I18+МП_Periods!I31+МП_Periods!I44+МП_Periods!I57+МП_Periods!I70+МП_Periods!I83+МП_Periods!I96+МП_Periods!I109+МП_Periods!I122+МП_Periods!I135+МП_Periods!I148,"-") -> 0 | X5: =SUM(МП_Periods!K5,МП_Periods!K18,МП_Periods!K31,МП_Periods!K44,МП_Periods!K57,МП_Periods!K70,МП_Periods!K83,МП_Periods!K96,МП_Periods!K109,МП_Periods!K122,МП_Periods!K135,МП_Periods!K148) -> 0 | Y5: =IFERROR(1-(Z5/X5),"-") -> - | Z5: =SUM(МП_Periods!M5,МП_Periods!M18,МП_Periods!M31,МП_Periods!M44,МП_Periods!M57,МП_Periods!M70,МП_Periods!M83,МП_Periods!M96,МП_Periods!M109,МП_Periods!M122,МП_Periods!M135,МП_Periods!M148) -> 0 | AA5: =IFERROR((AB5/Z5)-1,"-") -> - | AB5: =SUM(МП_Periods!O5,МП_Periods!O18,МП_Periods!O31,МП_Periods!O44,МП_Periods!O57,МП_Periods!O70,МП_Periods!O83,МП_Periods!O96,МП_Periods!O109,МП_Periods!O122,МП_Periods!O135,МП_Periods!O148) -> 0 | AC5: =SUM(МП_Periods!P5,МП_Periods!P18,МП_Periods!P31,МП_Periods!P44,МП_Periods!P57,МП_Periods!P70,МП_Periods!P83,МП_Periods!P96,МП_Periods!P109,МП_Periods!P122,МП_Periods!P135,МП_Periods!P148) -> 0 | AD5: =IFERROR(AC5/$AC$13,"-") -> - | AF5: =SUM(МП_Periods!S5,МП_Periods!S18,МП_Periods!S31,МП_Periods!S44,МП_Periods!S57,МП_Periods!S70,МП_Periods!S83,МП_Periods!S96,МП_Periods!S109,МП_Periods!S122,МП_Periods!S135,МП_Periods!S148) -> 0 | AG5: =IFERROR(AF5/AH5,"-") -> - | AH5: =IFERROR(МП_Periods!U5+МП_Periods!U18+МП_Periods!U31+МП_Periods!U44+МП_Periods!U57+МП_Periods!U70+МП_Periods!U83+МП_Periods!U96+МП_Periods!U109+МП_Periods!U122+МП_Periods!U135+МП_Periods!U148,"-") -> - | AI5: =IFERROR(AC5/AF5*1000,"-") -> - | AJ5: =IFERROR(AC5/AH5*1000,"-") -> - | AK5: =IFERROR(MAX(МП_Periods!X5,МП_Periods!X18,МП_Periods!X31,МП_Periods!X44,МП_Periods!X57,МП_Periods!X70,МП_Periods!X83,МП_Periods!X96,МП_Periods!X109,МП_Periods!X122,МП_Periods!X135,МП_Periods!X148),"-") -> 0 | AL5: =IFERROR(#REF!/AK5,"-") -> - | AN5: =IFERROR(AO5/AF5,"-") -> - | AO5: =SUM(МП_Periods!AB5,МП_Periods!AB18,МП_Periods!AB31,МП_Periods!AB44,МП_Periods!AB57,МП_Periods!AB70,МП_Periods!AB83,МП_Periods!AB96,МП_Periods!AB109,МП_Periods!AB122,МП_Periods!AB135,МП_Periods!AB148) -> 0 | AP5: =IFERROR(AC5/AO5,"-") -> - | AR5: =IFERROR(AS5/AO5,"-") -> - | AS5: =SUM(МП_Periods!AF5,МП_Periods!AF18,МП_Periods!AF31,МП_Periods!AF44,МП_Periods!AF57,МП_Periods!AF70,МП_Periods!AF83,МП_Periods!AF96,МП_Periods!AF109,МП_Periods!AF122,МП_Periods!AF135,МП_Periods!AF148) -> 0 | AT5: =IFERROR(AC5/AS5,"-") -> - | AV5: =IFERROR(AC5/AX5,"-") -> - | AW5: =IFERROR(AX5/AS5,"-") -> - | AX5: =SUM(МП_Periods!AO5,МП_Periods!AO18,МП_Periods!AO31,МП_Periods!AO44,МП_Periods!AO57,МП_Periods!AO70,МП_Periods!AO83,МП_Periods!AO96,МП_Periods!AO109,МП_Periods!AO122,МП_Periods!AO135,МП_Periods!AO148) -> 0 | AZ5: =IFERROR(BA5/AF5,"-") -> - | BA5: =IFERROR(#REF!+#REF!+#REF!+#REF!+#REF!+#REF!+#REF!+#REF!+#REF!+#REF!+#REF!+#REF!,"-") -> - | BB5: =IFERROR(AC5/BA5,"-") -> - | BC5: =IFERROR(BD5/AF5,"-") -> - | BD5: =IFERROR(#REF!+#REF!+#REF!+#REF!+#REF!+#REF!+#REF!+#REF!+#REF!+#REF!+#REF!+#REF!,"-") -> - | BF5: =IFERROR(BG5/AF5,"-") -> - | BG5: =IFERROR(#REF!+#REF!+#REF!+#REF!+#REF!+#REF!+#REF!+#REF!+#REF!+#REF!+#REF!+#REF!,"-") -> - | BH5: =IFERROR(AC5/BG5,"-") -> -
T6: CPC | U6: =IFERROR(X6/V6,"-") -> - | V6: =IFERROR(МП_Periods!I6+МП_Periods!I19+МП_Periods!I32+МП_Periods!I45+МП_Periods!I58+МП_Periods!I71+МП_Periods!I84+МП_Periods!I97+МП_Periods!I110+МП_Periods!I123+МП_Periods!I136+МП_Periods!I149,"-") -> 0 | X6: =SUM(МП_Periods!K6,МП_Periods!K19,МП_Periods!K32,МП_Periods!K45,МП_Periods!K58,МП_Periods!K71,МП_Periods!K84,МП_Periods!K97,МП_Periods!K110,МП_Periods!K123,МП_Periods!K136,МП_Periods!K149) -> 0 | Y6: =IFERROR(1-(Z6/X6),"-") -> - | Z6: =SUM(МП_Periods!M6,МП_Periods!M19,МП_Periods!M32,МП_Periods!M45,МП_Periods!M58,МП_Periods!M71,МП_Periods!M84,МП_Periods!M97,МП_Periods!M110,МП_Periods!M123,МП_Periods!M136,МП_Periods!M149) -> 0 | AA6: =IFERROR((AB6/Z6)-1,"-") -> - | AB6: =SUM(МП_Periods!O6,МП_Periods!O19,МП_Periods!O32,МП_Periods!O45,МП_Periods!O58,МП_Periods!O71,МП_Periods!O84,МП_Periods!O97,МП_Periods!O110,МП_Periods!O123,МП_Periods!O136,МП_Periods!O149) -> 0 | AC6: =SUM(МП_Periods!P6,МП_Periods!P19,МП_Periods!P32,МП_Periods!P45,МП_Periods!P58,МП_Periods!P71,МП_Periods!P84,МП_Periods!P97,МП_Periods!P110,МП_Periods!P123,МП_Periods!P136,МП_Periods!P149) -> 0 | AD6: =IFERROR(AC6/$AC$13,"-") -> - | AF6: =SUM(МП_Periods!S6,МП_Periods!S19,МП_Periods!S32,МП_Periods!S45,МП_Periods!S58,МП_Periods!S71,МП_Periods!S84,МП_Periods!S97,МП_Periods!S110,МП_Periods!S123,МП_Periods!S136,МП_Periods!S149) -> 0 | AG6: =IFERROR(AF6/AH6,"-") -> - | AH6: =IFERROR(МП_Periods!U6+МП_Periods!U19+МП_Periods!U32+МП_Periods!U45+МП_Periods!U58+МП_Periods!U71+МП_Periods!U84+МП_Periods!U97+МП_Periods!U110+МП_Periods!U123+МП_Periods!U136+МП_Periods!U149,"-") -> - | AI6: =IFERROR(AC6/AF6*1000,"-") -> - | AJ6: =IFERROR(AC6/AH6*1000,"-") -> - | AK6: =IFERROR(MAX(МП_Periods!X6,МП_Periods!X19,МП_Periods!X32,МП_Periods!X45,МП_Periods!X58,МП_Periods!X71,МП_Periods!X84,МП_Periods!X97,МП_Periods!X110,МП_Periods!X123,МП_Periods!X136,МП_Periods!X149),"-") -> 0 | AL6: =IFERROR(#REF!/AK6,"-") -> - | AN6: =IFERROR(AO6/AF6,"-") -> - | AO6: =SUM(МП_Periods!AB6,МП_Periods!AB19,МП_Periods!AB32,МП_Periods!AB45,МП_Periods!AB58,МП_Periods!AB71,МП_Periods!AB84,МП_Periods!AB97,МП_Periods!AB110,МП_Periods!AB123,МП_Periods!AB136,МП_Periods!AB149) -> 0 | AP6: =IFERROR(AC6/AO6,"-") -> - | AR6: =IFERROR(AS6/AO6,"-") -> - | AS6: =SUM(МП_Periods!AF6,МП_Periods!AF19,МП_Periods!AF32,МП_Periods!AF45,МП_Periods!AF58,МП_Periods!AF71,МП_Periods!AF84,МП_Periods!AF97,МП_Periods!AF110,МП_Periods!AF123,МП_Periods!AF136,МП_Periods!AF149) -> 0 | AT6: =IFERROR(AC6/AS6,"-") -> - | AV6: =IFERROR(AC6/AX6,"-") -> - | AW6: =IFERROR(AX6/AS6,"-") -> - | AX6: =SUM(МП_Periods!AO6,МП_Periods!AO19,МП_Periods!AO32,МП_Periods!AO45,МП_Periods!AO58,МП_Periods!AO71,МП_Periods!AO84,МП_Periods!AO97,МП_Periods!AO110,МП_Periods!AO123,МП_Periods!AO136,МП_Periods!AO149) -> 0 | AZ6: =IFERROR(BA6/AF6,"-") -> - | BA6: =IFERROR(#REF!+#REF!+#REF!+#REF!+#REF!+#REF!+#REF!+#REF!+#REF!+#REF!+#REF!+#REF!,"-") -> - | BB6: =IFERROR(AC6/BA6,"-") -> - | BC6: =IFERROR(BD6/AF6,"-") -> - | BD6: =IFERROR(#REF!+#REF!+#REF!+#REF!+#REF!+#REF!+#REF!+#REF!+#REF!+#REF!+#REF!+#REF!,"-") -> - | BF6: =IFERROR(BG6/AF6,"-") -> - | BG6: =IFERROR(#REF!+#REF!+#REF!+#REF!+#REF!+#REF!+#REF!+#REF!+#REF!+#REF!+#REF!+#REF!,"-") -> - | BH6: =IFERROR(AC6/BG6,"-") -> -
T7: CPC | U7: =IFERROR(X7/V7,"-") -> - | V7: =IFERROR(МП_Periods!I7+МП_Periods!I20+МП_Periods!I33+МП_Periods!I46+МП_Periods!I59+МП_Periods!I72+МП_Periods!I85+МП_Periods!I98+МП_Periods!I111+МП_Periods!I124+МП_Periods!I137+МП_Periods!I150,"-") -> 0 | X7: =SUM(МП_Periods!K7,МП_Periods!K20,МП_Periods!K33,МП_Periods!K46,МП_Periods!K59,МП_Periods!K72,МП_Periods!K85,МП_Periods!K98,МП_Periods!K111,МП_Periods!K124,МП_Periods!K137,МП_Periods!K150) -> 0 | Y7: =IFERROR(1-(Z7/X7),"-") -> - | Z7: =SUM(МП_Periods!M7,МП_Periods!M20,МП_Periods!M33,МП_Periods!M46,МП_Periods!M59,МП_Periods!M72,МП_Periods!M85,МП_Periods!M98,МП_Periods!M111,МП_Periods!M124,МП_Periods!M137,МП_Periods!M150) -> 0 | AA7: =IFERROR((AB7/Z7)-1,"-") -> - | AB7: =SUM(МП_Periods!O7,МП_Periods!O20,МП_Periods!O33,МП_Periods!O46,МП_Periods!O59,МП_Periods!O72,МП_Periods!O85,МП_Periods!O98,МП_Periods!O111,МП_Periods!O124,МП_Periods!O137,МП_Periods!O150) -> 0 | AC7: =SUM(МП_Periods!P7,МП_Periods!P20,МП_Periods!P33,МП_Periods!P46,МП_Periods!P59,МП_Periods!P72,МП_Periods!P85,МП_Periods!P98,МП_Periods!P111,МП_Periods!P124,МП_Periods!P137,МП_Periods!P150) -> 0 | AD7: =IFERROR(AC7/$AC$13,"-") -> - | AF7: =SUM(МП_Periods!S7,МП_Periods!S20,МП_Periods!S33,МП_Periods!S46,МП_Periods!S59,МП_Periods!S72,МП_Periods!S85,МП_Periods!S98,МП_Periods!S111,МП_Periods!S124,МП_Periods!S137,МП_Periods!S150) -> 0 | AG7: =IFERROR(AF7/AH7,"-") -> - | AH7: =IFERROR(МП_Periods!U7+МП_Periods!U20+МП_Periods!U33+МП_Periods!U46+МП_Periods!U59+МП_Periods!U72+МП_Periods!U85+МП_Periods!U98+МП_Periods!U111+МП_Periods!U124+МП_Periods!U137+МП_Periods!U150,"-") -> - | AI7: =IFERROR(AC7/AF7*1000,"-") -> - | AJ7: =IFERROR(AC7/AH7*1000,"-") -> - | AK7: =IFERROR(MAX(МП_Periods!X7,МП_Periods!X20,МП_Periods!X33,МП_Periods!X46,МП_Periods!X59,МП_Periods!X72,МП_Periods!X85,МП_Periods!X98,МП_Periods!X111,МП_Periods!X124,МП_Periods!X137,МП_Periods!X150),"-") -> 0 | AL7: =IFERROR(#REF!/AK7,"-") -> - | AN7: =IFERROR(AO7/AF7,"-") -> - | AO7: =SUM(МП_Periods!AB7,МП_Periods!AB20,МП_Periods!AB33,МП_Periods!AB46,МП_Periods!AB59,МП_Periods!AB72,МП_Periods!AB85,МП_Periods!AB98,МП_Periods!AB111,МП_Periods!AB124,МП_Periods!AB137,МП_Periods!AB150) -> 0 | AP7: =IFERROR(AC7/AO7,"-") -> - | AR7: =IFERROR(AS7/AO7,"-") -> - | AS7: =SUM(МП_Periods!AF7,МП_Periods!AF20,МП_Periods!AF33,МП_Periods!AF46,МП_Periods!AF59,МП_Periods!AF72,МП_Periods!AF85,МП_Periods!AF98,МП_Periods!AF111,МП_Periods!AF124,МП_Periods!AF137,МП_Periods!AF150) -> 0 | AT7: =IFERROR(AC7/AS7,"-") -> - | AV7: =IFERROR(AC7/AX7,"-") -> - | AW7: =IFERROR(AX7/AS7,"-") -> - | AX7: =SUM(МП_Periods!AO7,МП_Periods!AO20,МП_Periods!AO33,МП_Periods!AO46,МП_Periods!AO59,МП_Periods!AO72,МП_Periods!AO85,МП_Periods!AO98,МП_Periods!AO111,МП_Periods!AO124,МП_Periods!AO137,МП_Periods!AO150) -> 0 | AZ7: =IFERROR(BA7/AF7,"-") -> - | BA7: =IFERROR(#REF!+#REF!+#REF!+#REF!+#REF!+#REF!+#REF!+#REF!+#REF!+#REF!+#REF!+#REF!,"-") -> - | BB7: =IFERROR(AC7/BA7,"-") -> - | BC7: =IFERROR(BD7/AF7,"-") -> - | BD7: =IFERROR(#REF!+#REF!+#REF!+#REF!+#REF!+#REF!+#REF!+#REF!+#REF!+#REF!+#REF!+#REF!,"-") -> - | BF7: =IFERROR(BG7/AF7,"-") -> - | BG7: =IFERROR(#REF!+#REF!+#REF!+#REF!+#REF!+#REF!+#REF!+#REF!+#REF!+#REF!+#REF!+#REF!,"-") -> - | BH7: =IFERROR(AC7/BG7,"-") -> -
T8: CPC | U8: =IFERROR(X8/V8,"-") -> - | V8: =IFERROR(МП_Periods!I8+МП_Periods!I21+МП_Periods!I34+МП_Periods!I47+МП_Periods!I60+МП_Periods!I73+МП_Periods!I86+МП_Periods!I99+МП_Periods!I112+МП_Periods!I125+МП_Periods!I138+МП_Periods!I151,"-") -> 0 | X8: =SUM(МП_Periods!K8,МП_Periods!K21,МП_Periods!K34,МП_Periods!K47,МП_Periods!K60,МП_Periods!K73,МП_Periods!K86,МП_Periods!K99,МП_Periods!K112,МП_Periods!K125,МП_Periods!K138,МП_Periods!K151) -> 0 | Y8: =IFERROR(1-(Z8/X8),"-") -> - | Z8: =SUM(МП_Periods!M8,МП_Periods!M21,МП_Periods!M34,МП_Periods!M47,МП_Periods!M60,МП_Periods!M73,МП_Periods!M86,МП_Periods!M99,МП_Periods!M112,МП_Periods!M125,МП_Periods!M138,МП_Periods!M151) -> 0 | AA8: =IFERROR((AB8/Z8)-1,"-") -> - | AB8: =SUM(МП_Periods!O8,МП_Periods!O21,МП_Periods!O34,МП_Periods!O47,МП_Periods!O60,МП_Periods!O73,МП_Periods!O86,МП_Periods!O99,МП_Periods!O112,МП_Periods!O125,МП_Periods!O138,МП_Periods!O151) -> 0 | AC8: =SUM(МП_Periods!P8,МП_Periods!P21,МП_Periods!P34,МП_Periods!P47,МП_Periods!P60,МП_Periods!P73,МП_Periods!P86,МП_Periods!P99,МП_Periods!P112,МП_Periods!P125,МП_Periods!P138,МП_Periods!P151) -> 0 | AD8: =IFERROR(AC8/$AC$13,"-") -> - | AF8: =SUM(МП_Periods!S8,МП_Periods!S21,МП_Periods!S34,МП_Periods!S47,МП_Periods!S60,МП_Periods!S73,МП_Periods!S86,МП_Periods!S99,МП_Periods!S112,МП_Periods!S125,МП_Periods!S138,МП_Periods!S151) -> 0 | AG8: =IFERROR(AF8/AH8,"-") -> - | AH8: =IFERROR(МП_Periods!U8+МП_Periods!U21+МП_Periods!U34+МП_Periods!U47+МП_Periods!U60+МП_Periods!U73+МП_Periods!U86+МП_Periods!U99+МП_Periods!U112+МП_Periods!U125+МП_Periods!U138+МП_Periods!U151,"-") -> - | AI8: =IFERROR(AC8/AF8*1000,"-") -> - | AJ8: =IFERROR(AC8/AH8*1000,"-") -> - | AK8: =IFERROR(MAX(МП_Periods!X8,МП_Periods!X21,МП_Periods!X34,МП_Periods!X47,МП_Periods!X60,МП_Periods!X73,МП_Periods!X86,МП_Periods!X99,МП_Periods!X112,МП_Periods!X125,МП_Periods!X138,МП_Periods!X151),"-") -> 0 | AL8: =IFERROR(#REF!/AK8,"-") -> - | AN8: =IFERROR(AO8/AF8,"-") -> - | AO8: =SUM(МП_Periods!AB8,МП_Periods!AB21,МП_Periods!AB34,МП_Periods!AB47,МП_Periods!AB60,МП_Periods!AB73,МП_Periods!AB86,МП_Periods!AB99,МП_Periods!AB112,МП_Periods!AB125,МП_Periods!AB138,МП_Periods!AB151) -> 0 | AP8: =IFERROR(AC8/AO8,"-") -> - | AR8: =IFERROR(AS8/AO8,"-") -> - | AS8: =SUM(МП_Periods!AF8,МП_Periods!AF21,МП_Periods!AF34,МП_Periods!AF47,МП_Periods!AF60,МП_Periods!AF73,МП_Periods!AF86,МП_Periods!AF99,МП_Periods!AF112,МП_Periods!AF125,МП_Periods!AF138,МП_Periods!AF151) -> 0 | AT8: =IFERROR(AC8/AS8,"-") -> - | AV8: =IFERROR(AC8/AX8,"-") -> - | AW8: =IFERROR(AX8/AS8,"-") -> - | AX8: =SUM(МП_Periods!AO8,МП_Periods!AO21,МП_Periods!AO34,МП_Periods!AO47,МП_Periods!AO60,МП_Periods!AO73,МП_Periods!AO86,МП_Periods!AO99,МП_Periods!AO112,МП_Periods!AO125,МП_Periods!AO138,МП_Periods!AO151) -> 0 | AZ8: =IFERROR(BA8/AF8,"-") -> - | BA8: =IFERROR(#REF!+#REF!+#REF!+#REF!+#REF!+#REF!+#REF!+#REF!+#REF!+#REF!+#REF!+#REF!,"-") -> - | BB8: =IFERROR(AC8/BA8,"-") -> - | BC8: =IFERROR(BD8/AF8,"-") -> - | BD8: =IFERROR(#REF!+#REF!+#REF!+#REF!+#REF!+#REF!+#REF!+#REF!+#REF!+#REF!+#REF!+#REF!,"-") -> - | BF8: =IFERROR(BG8/AF8,"-") -> - | BG8: =IFERROR(#REF!+#REF!+#REF!+#REF!+#REF!+#REF!+#REF!+#REF!+#REF!+#REF!+#REF!+#REF!,"-") -> - | BH8: =IFERROR(AC8/BG8,"-") -> -
T9: CPC | U9: =IFERROR(X9/V9,"-") -> - | V9: =IFERROR(МП_Periods!I9+МП_Periods!I22+МП_Periods!I35+МП_Periods!I48+МП_Periods!I61+МП_Periods!I74+МП_Periods!I87+МП_Periods!I100+МП_Periods!I113+МП_Periods!I126+МП_Periods!I139+МП_Periods!I152,"-") -> 0 | X9: =SUM(МП_Periods!K9,МП_Periods!K22,МП_Periods!K35,МП_Periods!K48,МП_Periods!K61,МП_Periods!K74,МП_Periods!K87,МП_Periods!K100,МП_Periods!K113,МП_Periods!K126,МП_Periods!K139,МП_Periods!K152) -> 0 | Y9: =IFERROR(1-(Z9/X9),"-") -> - | Z9: =SUM(МП_Periods!M9,МП_Periods!M22,МП_Periods!M35,МП_Periods!M48,МП_Periods!M61,МП_Periods!M74,МП_Periods!M87,МП_Periods!M100,МП_Periods!M113,МП_Periods!M126,МП_Periods!M139,МП_Periods!M152) -> 0 | AA9: =IFERROR((AB9/Z9)-1,"-") -> - | AB9: =SUM(МП_Periods!O9,МП_Periods!O22,МП_Periods!O35,МП_Periods!O48,МП_Periods!O61,МП_Periods!O74,МП_Periods!O87,МП_Periods!O100,МП_Periods!O113,МП_Periods!O126,МП_Periods!O139,МП_Periods!O152) -> 0 | AC9: =SUM(МП_Periods!P9,МП_Periods!P22,МП_Periods!P35,МП_Periods!P48,МП_Periods!P61,МП_Periods!P74,МП_Periods!P87,МП_Periods!P100,МП_Periods!P113,МП_Periods!P126,МП_Periods!P139,МП_Periods!P152) -> 0 | AD9: =IFERROR(AC9/$AC$13,"-") -> - | AF9: =SUM(МП_Periods!S9,МП_Periods!S22,МП_Periods!S35,МП_Periods!S48,МП_Periods!S61,МП_Periods!S74,МП_Periods!S87,МП_Periods!S100,МП_Periods!S113,МП_Periods!S126,МП_Periods!S139,МП_Periods!S152) -> 0 | AG9: =IFERROR(AF9/AH9,"-") -> - | AH9: =IFERROR(МП_Periods!U9+МП_Periods!U22+МП_Periods!U35+МП_Periods!U48+МП_Periods!U61+МП_Periods!U74+МП_Periods!U87+МП_Periods!U100+МП_Periods!U113+МП_Periods!U126+МП_Periods!U139+МП_Periods!U152,"-") -> - | AI9: =IFERROR(AC9/AF9*1000,"-") -> - | AJ9: =IFERROR(AC9/AH9*1000,"-") -> - | AK9: =IFERROR(MAX(МП_Periods!X9,МП_Periods!X22,МП_Periods!X35,МП_Periods!X48,МП_Periods!X61,МП_Periods!X74,МП_Periods!X87,МП_Periods!X100,МП_Periods!X113,МП_Periods!X126,МП_Periods!X139,МП_Periods!X152),"-") -> 0 | AL9: =IFERROR(#REF!/AK9,"-") -> - | AN9: =IFERROR(AO9/AF9,"-") -> - | AO9: =SUM(МП_Periods!AB9,МП_Periods!AB22,МП_Periods!AB35,МП_Periods!AB48,МП_Periods!AB61,МП_Periods!AB74,МП_Periods!AB87,МП_Periods!AB100,МП_Periods!AB113,МП_Periods!AB126,МП_Periods!AB139,МП_Periods!AB152) -> 0 | AP9: =IFERROR(AC9/AO9,"-") -> - | AR9: =IFERROR(AS9/AO9,"-") -> - | AS9: =SUM(МП_Periods!AF9,МП_Periods!AF22,МП_Periods!AF35,МП_Periods!AF48,МП_Periods!AF61,МП_Periods!AF74,МП_Periods!AF87,МП_Periods!AF100,МП_Periods!AF113,МП_Periods!AF126,МП_Periods!AF139,МП_Periods!AF152) -> 0 | AT9: =IFERROR(AC9/AS9,"-") -> - | AV9: =IFERROR(AC9/AX9,"-") -> - | AW9: =IFERROR(AX9/AS9,"-") -> - | AX9: =SUM(МП_Periods!AO9,МП_Periods!AO22,МП_Periods!AO35,МП_Periods!AO48,МП_Periods!AO61,МП_Periods!AO74,МП_Periods!AO87,МП_Periods!AO100,МП_Periods!AO113,МП_Periods!AO126,МП_Periods!AO139,МП_Periods!AO152) -> 0 | AZ9: =IFERROR(BA9/AF9,"-") -> - | BA9: =IFERROR(#REF!+#REF!+#REF!+#REF!+#REF!+#REF!+#REF!+#REF!+#REF!+#REF!+#REF!+#REF!,"-") -> - | BB9: =IFERROR(AC9/BA9,"-") -> - | BC9: =IFERROR(BD9/AF9,"-") -> - | BD9: =IFERROR(#REF!+#REF!+#REF!+#REF!+#REF!+#REF!+#REF!+#REF!+#REF!+#REF!+#REF!+#REF!,"-") -> - | BF9: =IFERROR(BG9/AF9,"-") -> - | BG9: =IFERROR(#REF!+#REF!+#REF!+#REF!+#REF!+#REF!+#REF!+#REF!+#REF!+#REF!+#REF!+#REF!,"-") -> - | BH9: =IFERROR(AC9/BG9,"-") -> -
T10: CPC | U10: =IFERROR(X10/V10,"-") -> - | V10: =IFERROR(МП_Periods!I10+МП_Periods!I23+МП_Periods!I36+МП_Periods!I49+МП_Periods!I62+МП_Periods!I75+МП_Periods!I88+МП_Periods!I101+МП_Periods!I114+МП_Periods!I127+МП_Periods!I140+МП_Periods!I153,"-") -> 0 | X10: =SUM(МП_Periods!K10,МП_Periods!K23,МП_Periods!K36,МП_Periods!K49,МП_Periods!K62,МП_Periods!K75,МП_Periods!K88,МП_Periods!K101,МП_Periods!K114,МП_Periods!K127,МП_Periods!K140,МП_Periods!K153) -> 0 | Y10: =IFERROR(1-(Z10/X10),"-") -> - | Z10: =SUM(МП_Periods!M10,МП_Periods!M23,МП_Periods!M36,МП_Periods!M49,МП_Periods!M62,МП_Periods!M75,МП_Periods!M88,МП_Periods!M101,МП_Periods!M114,МП_Periods!M127,МП_Periods!M140,МП_Periods!M153) -> 0 | AA10: =IFERROR((AB10/Z10)-1,"-") -> - | AB10: =SUM(МП_Periods!O10,МП_Periods!O23,МП_Periods!O36,МП_Periods!O49,МП_Periods!O62,МП_Periods!O75,МП_Periods!O88,МП_Periods!O101,МП_Periods!O114,МП_Periods!O127,МП_Periods!O140,МП_Periods!O153) -> 0 | AC10: =SUM(МП_Periods!P10,МП_Periods!P23,МП_Periods!P36,МП_Periods!P49,МП_Periods!P62,МП_Periods!P75,МП_Periods!P88,МП_Periods!P101,МП_Periods!P114,МП_Periods!P127,МП_Periods!P140,МП_Periods!P153) -> 0 | AD10: =IFERROR(AC10/$AC$13,"-") -> - | AF10: =SUM(МП_Periods!S10,МП_Periods!S23,МП_Periods!S36,МП_Periods!S49,МП_Periods!S62,МП_Periods!S75,МП_Periods!S88,МП_Periods!S101,МП_Periods!S114,МП_Periods!S127,МП_Periods!S140,МП_Periods!S153) -> 0 | AG10: =IFERROR(AF10/AH10,"-") -> - | AH10: =IFERROR(МП_Periods!U10+МП_Periods!U23+МП_Periods!U36+МП_Periods!U49+МП_Periods!U62+МП_Periods!U75+МП_Periods!U88+МП_Periods!U101+МП_Periods!U114+МП_Periods!U127+МП_Periods!U140+МП_Periods!U153,"-") -> - | AI10: =IFERROR(AC10/AF10*1000,"-") -> - | AJ10: =IFERROR(AC10/AH10*1000,"-") -> - | AK10: =IFERROR(MAX(МП_Periods!X10,МП_Periods!X23,МП_Periods!X36,МП_Periods!X49,МП_Periods!X62,МП_Periods!X75,МП_Periods!X88,МП_Periods!X101,МП_Periods!X114,МП_Periods!X127,МП_Periods!X140,МП_Periods!X153),"-") -> 0 | AL10: =IFERROR(#REF!/AK10,"-") -> - | AN10: =IFERROR(AO10/AF10,"-") -> - | AO10: =SUM(МП_Periods!AB10,МП_Periods!AB23,МП_Periods!AB36,МП_Periods!AB49,МП_Periods!AB62,МП_Periods!AB75,МП_Periods!AB88,МП_Periods!AB101,МП_Periods!AB114,МП_Periods!AB127,МП_Periods!AB140,МП_Periods!AB153) -> 0 | AP10: =IFERROR(AC10/AO10,"-") -> - | AR10: =IFERROR(AS10/AO10,"-") -> - | AS10: =SUM(МП_Periods!AF10,МП_Periods!AF23,МП_Periods!AF36,МП_Periods!AF49,МП_Periods!AF62,МП_Periods!AF75,МП_Periods!AF88,МП_Periods!AF101,МП_Periods!AF114,МП_Periods!AF127,МП_Periods!AF140,МП_Periods!AF153) -> 0 | AT10: =IFERROR(AC10/AS10,"-") -> - | AV10: =IFERROR(AC10/AX10,"-") -> - | AW10: =IFERROR(AX10/AS10,"-") -> - | AX10: =SUM(МП_Periods!AO10,МП_Periods!AO23,МП_Periods!AO36,МП_Periods!AO49,МП_Periods!AO62,МП_Periods!AO75,МП_Periods!AO88,МП_Periods!AO101,МП_Periods!AO114,МП_Periods!AO127,МП_Periods!AO140,МП_Periods!AO153) -> 0 | AZ10: =IFERROR(BA10/AF10,"-") -> - | BA10: =IFERROR(#REF!+#REF!+#REF!+#REF!+#REF!+#REF!+#REF!+#REF!+#REF!+#REF!+#REF!+#REF!,"-") -> - | BB10: =IFERROR(AC10/BA10,"-") -> - | BC10: =IFERROR(BD10/AF10,"-") -> - | BD10: =IFERROR(#REF!+#REF!+#REF!+#REF!+#REF!+#REF!+#REF!+#REF!+#REF!+#REF!+#REF!+#REF!,"-") -> - | BF10: =IFERROR(BG10/AF10,"-") -> - | BG10: =IFERROR(#REF!+#REF!+#REF!+#REF!+#REF!+#REF!+#REF!+#REF!+#REF!+#REF!+#REF!+#REF!,"-") -> - | BH10: =IFERROR(AC10/BG10,"-") -> -
T11: CPC | U11: =IFERROR(X11/V11,"-") -> - | V11: =IFERROR(МП_Periods!I11+МП_Periods!I24+МП_Periods!I37+МП_Periods!I50+МП_Periods!I63+МП_Periods!I76+МП_Periods!I89+МП_Periods!I102+МП_Periods!I115+МП_Periods!I128+МП_Periods!I141+МП_Periods!I154,"-") -> 0 | X11: =SUM(МП_Periods!K11,МП_Periods!K24,МП_Periods!K37,МП_Periods!K50,МП_Periods!K63,МП_Periods!K76,МП_Periods!K89,МП_Periods!K102,МП_Periods!K115,МП_Periods!K128,МП_Periods!K141,МП_Periods!K154) -> 0 | Y11: =IFERROR(1-(Z11/X11),"-") -> - | Z11: =SUM(МП_Periods!M11,МП_Periods!M24,МП_Periods!M37,МП_Periods!M50,МП_Periods!M63,МП_Periods!M76,МП_Periods!M89,МП_Periods!M102,МП_Periods!M115,МП_Periods!M128,МП_Periods!M141,МП_Periods!M154) -> 0 | AA11: =IFERROR((AB11/Z11)-1,"-") -> - | AB11: =SUM(МП_Periods!O11,МП_Periods!O24,МП_Periods!O37,МП_Periods!O50,МП_Periods!O63,МП_Periods!O76,МП_Periods!O89,МП_Periods!O102,МП_Periods!O115,МП_Periods!O128,МП_Periods!O141,МП_Periods!O154) -> 0 | AC11: =SUM(МП_Periods!P11,МП_Periods!P24,МП_Periods!P37,МП_Periods!P50,МП_Periods!P63,МП_Periods!P76,МП_Periods!P89,МП_Periods!P102,МП_Periods!P115,МП_Periods!P128,МП_Periods!P141,МП_Periods!P154) -> 0 | AD11: =IFERROR(AC11/$AC$13,"-") -> - | AF11: =SUM(МП_Periods!S11,МП_Periods!S24,МП_Periods!S37,МП_Periods!S50,МП_Periods!S63,МП_Periods!S76,МП_Periods!S89,МП_Periods!S102,МП_Periods!S115,МП_Periods!S128,МП_Periods!S141,МП_Periods!S154) -> 0 | AG11: =IFERROR(AF11/AH11,"-") -> - | AH11: =IFERROR(МП_Periods!U11+МП_Periods!U24+МП_Periods!U37+МП_Periods!U50+МП_Periods!U63+МП_Periods!U76+МП_Periods!U89+МП_Periods!U102+МП_Periods!U115+МП_Periods!U128+МП_Periods!U141+МП_Periods!U154,"-") -> - | AI11: =IFERROR(AC11/AF11*1000,"-") -> - | AJ11: =IFERROR(AC11/AH11*1000,"-") -> - | AK11: =IFERROR(MAX(МП_Periods!X11,МП_Periods!X24,МП_Periods!X37,МП_Periods!X50,МП_Periods!X63,МП_Periods!X76,МП_Periods!X89,МП_Periods!X102,МП_Periods!X115,МП_Periods!X128,МП_Periods!X141,МП_Periods!X154),"-") -> 0 | AL11: =IFERROR(#REF!/AK11,"-") -> - | AN11: =IFERROR(AO11/AF11,"-") -> - | AO11: =SUM(МП_Periods!AB11,МП_Periods!AB24,МП_Periods!AB37,МП_Periods!AB50,МП_Periods!AB63,МП_Periods!AB76,МП_Periods!AB89,МП_Periods!AB102,МП_Periods!AB115,МП_Periods!AB128,МП_Periods!AB141,МП_Periods!AB154) -> 0 | AP11: =IFERROR(AC11/AO11,"-") -> - | AR11: =IFERROR(AS11/AO11,"-") -> - | AS11: =SUM(МП_Periods!AF11,МП_Periods!AF24,МП_Periods!AF37,МП_Periods!AF50,МП_Periods!AF63,МП_Periods!AF76,МП_Periods!AF89,МП_Periods!AF102,МП_Periods!AF115,МП_Periods!AF128,МП_Periods!AF141,МП_Periods!AF154) -> 0 | AT11: =IFERROR(AC11/AS11,"-") -> - | AV11: =IFERROR(AC11/AX11,"-") -> - | AW11: =IFERROR(AX11/AS11,"-") -> - | AX11: =SUM(МП_Periods!AO11,МП_Periods!AO24,МП_Periods!AO37,МП_Periods!AO50,МП_Periods!AO63,МП_Periods!AO76,МП_Periods!AO89,МП_Periods!AO102,МП_Periods!AO115,МП_Periods!AO128,МП_Periods!AO141,МП_Periods!AO154) -> 0 | AZ11: =IFERROR(BA11/AF11,"-") -> - | BA11: =IFERROR(#REF!+#REF!+#REF!+#REF!+#REF!+#REF!+#REF!+#REF!+#REF!+#REF!+#REF!+#REF!,"-") -> - | BB11: =IFERROR(AC11/BA11,"-") -> - | BC11: =IFERROR(BD11/AF11,"-") -> - | BD11: =IFERROR(#REF!+#REF!+#REF!+#REF!+#REF!+#REF!+#REF!+#REF!+#REF!+#REF!+#REF!+#REF!,"-") -> - | BF11: =IFERROR(BG11/AF11,"-") -> - | BG11: =IFERROR(#REF!+#REF!+#REF!+#REF!+#REF!+#REF!+#REF!+#REF!+#REF!+#REF!+#REF!+#REF!,"-") -> - | BH11: =IFERROR(AC11/BG11,"-") -> -
T12: CPC | U12: =IFERROR(X12/V12,"-") -> - | V12: =IFERROR(МП_Periods!I12+МП_Periods!I25+МП_Periods!I38+МП_Periods!I51+МП_Periods!I64+МП_Periods!I77+МП_Periods!I90+МП_Periods!I103+МП_Periods!I116+МП_Periods!I129+МП_Periods!I142+МП_Periods!I155,"-") -> 0 | X12: =SUM(МП_Periods!K12,МП_Periods!K25,МП_Periods!K38,МП_Periods!K51,МП_Periods!K64,МП_Periods!K77,МП_Periods!K90,МП_Periods!K103,МП_Periods!K116,МП_Periods!K129,МП_Periods!K142,МП_Periods!K155) -> 0 | Y12: =IFERROR(1-(Z12/X12),"-") -> - | Z12: =SUM(МП_Periods!M12,МП_Periods!M25,МП_Periods!M38,МП_Periods!M51,МП_Periods!M64,МП_Periods!M77,МП_Periods!M90,МП_Periods!M103,МП_Periods!M116,МП_Periods!M129,МП_Periods!M142,МП_Periods!M155) -> 0 | AA12: =IFERROR((AB12/Z12)-1,"-") -> - | AB12: =SUM(МП_Periods!O12,МП_Periods!O25,МП_Periods!O38,МП_Periods!O51,МП_Periods!O64,МП_Periods!O77,МП_Periods!O90,МП_Periods!O103,МП_Periods!O116,МП_Periods!O129,МП_Periods!O142,МП_Periods!O155) -> 0 | AC12: =SUM(МП_Periods!P12,МП_Periods!P25,МП_Periods!P38,МП_Periods!P51,МП_Periods!P64,МП_Periods!P77,МП_Periods!P90,МП_Periods!P103,МП_Periods!P116,МП_Periods!P129,МП_Periods!P142,МП_Periods!P155) -> 0 | AD12: =IFERROR(AC12/$AC$13,"-") -> - | AF12: =SUM(МП_Periods!S12,МП_Periods!S25,МП_Periods!S38,МП_Periods!S51,МП_Periods!S64,МП_Periods!S77,МП_Periods!S90,МП_Periods!S103,МП_Periods!S116,МП_Periods!S129,МП_Periods!S142,МП_Periods!S155) -> 0 | AG12: =IFERROR(AF12/AH12,"-") -> - | AH12: =IFERROR(МП_Periods!U12+МП_Periods!U25+МП_Periods!U38+МП_Periods!U51+МП_Periods!U64+МП_Periods!U77+МП_Periods!U90+МП_Periods!U103+МП_Periods!U116+МП_Periods!U129+МП_Periods!U142+МП_Periods!U155,"-") -> - | AI12: =IFERROR(AC12/AF12*1000,"-") -> - | AJ12: =IFERROR(AC12/AH12*1000,"-") -> - | AK12: =IFERROR(MAX(МП_Periods!X12,МП_Periods!X25,МП_Periods!X38,МП_Periods!X51,МП_Periods!X64,МП_Periods!X77,МП_Periods!X90,МП_Periods!X103,МП_Periods!X116,МП_Periods!X129,МП_Periods!X142,МП_Periods!X155),"-") -> 0 | AL12: =IFERROR(#REF!/AK12,"-") -> - | AN12: =IFERROR(AO12/AF12,"-") -> - | AO12: =SUM(МП_Periods!AB12,МП_Periods!AB25,МП_Periods!AB38,МП_Periods!AB51,МП_Periods!AB64,МП_Periods!AB77,МП_Periods!AB90,МП_Periods!AB103,МП_Periods!AB116,МП_Periods!AB129,МП_Periods!AB142,МП_Periods!AB155) -> 0 | AP12: =IFERROR(AC12/AO12,"-") -> - | AR12: =IFERROR(AS12/AO12,"-") -> - | AS12: =SUM(МП_Periods!AF12,МП_Periods!AF25,МП_Periods!AF38,МП_Periods!AF51,МП_Periods!AF64,МП_Periods!AF77,МП_Periods!AF90,МП_Periods!AF103,МП_Periods!AF116,МП_Periods!AF129,МП_Periods!AF142,МП_Periods!AF155) -> 0 | AT12: =IFERROR(AC12/AS12,"-") -> - | AV12: =IFERROR(AC12/AX12,"-") -> - | AW12: =IFERROR(AX12/AS12,"-") -> - | AX12: =SUM(МП_Periods!AO12,МП_Periods!AO25,МП_Periods!AO38,МП_Periods!AO51,МП_Periods!AO64,МП_Periods!AO77,МП_Periods!AO90,МП_Periods!AO103,МП_Periods!AO116,МП_Periods!AO129,МП_Periods!AO142,МП_Periods!AO155) -> 0 | AZ12: =IFERROR(BA12/AF12,"-") -> - | BA12: =IFERROR(#REF!+#REF!+#REF!+#REF!+#REF!+#REF!+#REF!+#REF!+#REF!+#REF!+#REF!+#REF!,"-") -> - | BB12: =IFERROR(AC12/BA12,"-") -> - | BC12: =IFERROR(BD12/AF12,"-") -> - | BD12: =IFERROR(#REF!+#REF!+#REF!+#REF!+#REF!+#REF!+#REF!+#REF!+#REF!+#REF!+#REF!+#REF!,"-") -> - | BF12: =IFERROR(BG12/AF12,"-") -> - | BG12: =IFERROR(#REF!+#REF!+#REF!+#REF!+#REF!+#REF!+#REF!+#REF!+#REF!+#REF!+#REF!+#REF!,"-") -> - | BH12: =IFERROR(AC12/BG12,"-") -> -
B13: Итого | C13: - | D13: - | F13: - | G13: - | H13: - | I13: - | J13: - | K13: - | L13: - | M13: - | N13: - | O13: - | P13: - | Q13: - | S13: - | T13: - | U13: =IFERROR(X13/V13,"-") -> - | V13: =SUM(V3:V12) -> 0 | X13: =IFERROR(SUM(X3:X12),"-") -> 0 | Y13: - | Z13: =IFERROR(SUM(Z3:Z12),"-") -> 0 | AA13: - | AB13: =IFERROR(SUM(AB3:AB12),"-") -> 0 | AC13: =IFERROR(SUM(AC3:AC12),"-") -> 0 | AD13: 1 | AF13: =IFERROR(SUM(AF3:AF12),"-") -> 0 | AG13: - | AH13: - | AI13: =IFERROR(AC13/AF13*1000,"-") -> - | AJ13: =IFERROR(AC13/AH13*1000,"-") -> - | AK13: - | AL13: - | AN13: =IFERROR(AO13/AF13,"-") -> - | AO13: =IFERROR(SUM(AO3:AO12),"-") -> 0 | AP13: =IFERROR(AC13/AO13,"-") -> - | AR13: =IFERROR(AS13/AO13,"-") -> - | AS13: =IFERROR(SUM(AS3:AS12),"-") -> 0 | AT13: =IFERROR(AC13/AS13,"-") -> - | AV13: =IFERROR(AC13/AX13,"-") -> - | AW13: =IFERROR(AX13/#REF!,"-") -> - | AX13: =IFERROR(SUM(AX3:AX12),"-") -> 0 | AZ13: =IFERROR(BA13/AF13,"-") -> - | BA13: =IFERROR(SUM(BA3:BA12),"-") -> 0 | BB13: =IFERROR(AC13/BA13,"-") -> - | BC13: =IFERROR(BD13/AF13,"-") -> - | BD13: =IFERROR(SUM(BD3:BD12),"-") -> 0 | BF13: =IFERROR(BG13/AF13,"-") -> - | BG13: =IFERROR(SUM(BG3:BG12),"-") -> 0 | BH13: =IFERROR(AC13/BG13,"-") -> -
B15: Медиабюджет до НДС | C15: =IFERROR(Z13,"-") -> 0
B16: Агентская комиссия до НДС | C16: =IFERROR((AB13-Z13),"-") -> 0
B17: Медиабюджет с АК до НДС | C17: =IFERROR(SUM(C15:C16),"-") -> 0
B18: НДС | C18: =IFERROR((AC13-AB13),"-") -> 0
B19: Медиабюджет с АК и НДС | C19: =IFERROR(SUM(C17:C18),"-") -> 0
B20: Разработка креативов | C20: 0
B21: Настройка аналитики | C21: 0
B22: Итого с АК и НДС | C22: =IFERROR(SUM(C19:C21),"-") -> 0

Sheet МП_Periods
AH1: \
B2: Рекламная система | C2: Рекламный формат, размер, вид размещения | D2: Таргетинги | F2: Период | G2: Модель закупки | H2: Стоимость единицы закупки (без НДС) | I2: Кол-во единиц закупки | K2: Стоимость (без НДС) | L2: СК, % | M2: Стоимость с учетом СК (без НДС) | N2: АК, % | O2: Итоговая стоимость (без НДС) | P2: Итоговая стоимость (с НДС) | Q2: Доля рекламного бюджета, % | S2: Показы | T2: Частота (весь срок) | U2: Охват | V2: CPM (с НДС) | W2: CPT (с НДС) | X2: Доступная емкость аудитории | Y2: SOV, % | AA2: CTR, % | AB2: Клики | AC2: CPC (с НДС) | AE2: CR, % | AF2: Конверсии | AG2: CPA (с НДС) | AI2: CR(I), % | AJ2: Установки | AK2: CPI (с НДС) | AM2: ДРР, % | AN2: Средний чек | AO2: Доход
F3: 01.01.2026 - 31.01.2026 | G3: CPC | I3: =IFERROR(S3*AA3,"-") -> 0 | K3: =IFERROR((H3*I3),"-") -> 0 | M3: =IFERROR(K3*(1-L3),"-") -> 0 | O3: =IFERROR(M3*(1+N3),"-") -> 0 | P3: =IFERROR(O3*1.22,"-") -> 0 | Q3: =IFERROR(P3/$P$13,"-") -> - | U3: - | V3: =IFERROR(P3/S3*1000,"-") -> - | W3: =IFERROR(P3/U3*1000,"-") -> - | Y3: =IFERROR(U3/X3,"-") -> - | AB3: =IFERROR(ROUNDDOWN(S3*AA3,0),"-") -> 0 | AC3: =IFERROR(P3/AB3,"-") -> - | AF3: =IF(G3="CPI",AJ3*AE3,IFERROR(ROUNDDOWN(AB3*AE3,0),"-")) -> 0 | AG3: =IFERROR(P3/AF3,"-") -> - | AJ3: =IF(G3="CPI",I3,0) -> 0 | AK3: =IFERROR(P3/AJ3,"-") -> - | AM3: =IFERROR(P3/AO3,"-") -> - | AO3: =AN3*AF3 -> 0
F4: 01.01.2026 - 31.01.2026 | G4: CPC | I4: =IFERROR(S4*AA4,"-") -> 0 | K4: =IFERROR((H4*I4),"-") -> 0 | M4: =IFERROR(K4*(1-L4),"-") -> 0 | O4: =IFERROR(M4*(1+N4),"-") -> 0 | P4: =IFERROR(O4*1.22,"-") -> 0 | Q4: =IFERROR(P4/$P$13,"-") -> - | U4: - | V4: =IFERROR(P4/S4*1000,"-") -> - | W4: =IFERROR(P4/U4*1000,"-") -> - | Y4: =IFERROR(U4/X4,"-") -> - | AB4: =IFERROR(ROUNDDOWN(S4*AA4,0),"-") -> 0 | AC4: =IFERROR(P4/AB4,"-") -> - | AF4: =IF(G4="CPI",AJ4*AE4,IFERROR(ROUNDDOWN(AB4*AE4,0),"-")) -> 0 | AG4: =IFERROR(P4/AF4,"-") -> - | AJ4: =IF(G4="CPI",I4,0) -> 0 | AK4: =IFERROR(P4/AJ4,"-") -> - | AM4: =IFERROR(P4/AO4,"-") -> - | AO4: =AN4*AF4 -> 0
F5: 01.01.2026 - 31.01.2026 | G5: CPC | I5: =IFERROR(S5*AA5,"-") -> 0 | K5: =IFERROR((H5*I5),"-") -> 0 | M5: =IFERROR(K5*(1-L5),"-") -> 0 | O5: =IFERROR(M5*(1+N5),"-") -> 0 | P5: =IFERROR(O5*1.22,"-") -> 0 | Q5: =IFERROR(P5/$P$13,"-") -> - | U5: - | V5: =IFERROR(P5/S5*1000,"-") -> - | W5: =IFERROR(P5/U5*1000,"-") -> - | Y5: =IFERROR(U5/X5,"-") -> - | AB5: =IFERROR(ROUNDDOWN(S5*AA5,0),"-") -> 0 | AC5: =IFERROR(P5/AB5,"-") -> - | AF5: =IF(G5="CPI",AJ5*AE5,IFERROR(ROUNDDOWN(AB5*AE5,0),"-")) -> 0 | AG5: =IFERROR(P5/AF5,"-") -> - | AJ5: =IF(G5="CPI",I5,0) -> 0 | AK5: =IFERROR(P5/AJ5,"-") -> - | AM5: =IFERROR(P5/AO5,"-") -> - | AO5: =AN5*AF5 -> 0
F6: 01.01.2026 - 31.01.2026 | G6: CPC | I6: =IFERROR(S6*AA6,"-") -> 0 | K6: =IFERROR((H6*I6),"-") -> 0 | M6: =IFERROR(K6*(1-L6),"-") -> 0 | O6: =IFERROR(M6*(1+N6),"-") -> 0 | P6: =IFERROR(O6*1.22,"-") -> 0 | Q6: =IFERROR(P6/$P$13,"-") -> - | U6: - | V6: =IFERROR(P6/S6*1000,"-") -> - | W6: =IFERROR(P6/U6*1000,"-") -> - | Y6: =IFERROR(U6/X6,"-") -> - | AB6: =IFERROR(ROUNDDOWN(S6*AA6,0),"-") -> 0 | AC6: =IFERROR(P6/AB6,"-") -> - | AF6: =IF(G6="CPI",AJ6*AE6,IFERROR(ROUNDDOWN(AB6*AE6,0),"-")) -> 0 | AG6: =IFERROR(P6/AF6,"-") -> - | AJ6: =IF(G6="CPI",I6,0) -> 0 | AK6: =IFERROR(P6/AJ6,"-") -> - | AM6: =IFERROR(P6/AO6,"-") -> - | AO6: =AN6*AF6 -> 0
F7: 01.01.2026 - 31.01.2026 | G7: CPC | I7: =IFERROR(S7*AA7,"-") -> 0 | K7: =IFERROR((H7*I7),"-") -> 0 | M7: =IFERROR(K7*(1-L7),"-") -> 0 | O7: =IFERROR(M7*(1+N7),"-") -> 0 | P7: =IFERROR(O7*1.22,"-") -> 0 | Q7: =IFERROR(P7/$P$13,"-") -> - | U7: - | V7: =IFERROR(P7/S7*1000,"-") -> - | W7: =IFERROR(P7/U7*1000,"-") -> - | Y7: =IFERROR(U7/X7,"-") -> - | AB7: =IFERROR(ROUNDDOWN(S7*AA7,0),"-") -> 0 | AC7: =IFERROR(P7/AB7,"-") -> - | AF7: =IF(G7="CPI",AJ7*AE7,IFERROR(ROUNDDOWN(AB7*AE7,0),"-")) -> 0 | AG7: =IFERROR(P7/AF7,"-") -> - | AJ7: =IF(G7="CPI",I7,0) -> 0 | AK7: =IFERROR(P7/AJ7,"-") -> - | AM7: =IFERROR(P7/AO7,"-") -> - | AO7: =AN7*AF7 -> 0
F8: 01.01.2026 - 31.01.2026 | G8: CPC | I8: =IFERROR(S8*AA8,"-") -> 0 | K8: =IFERROR((H8*I8),"-") -> 0 | M8: =IFERROR(K8*(1-L8),"-") -> 0 | O8: =IFERROR(M8*(1+N8),"-") -> 0 | P8: =IFERROR(O8*1.22,"-") -> 0 | Q8: =IFERROR(P8/$P$13,"-") -> - | U8: - | V8: =IFERROR(P8/S8*1000,"-") -> - | W8: =IFERROR(P8/U8*1000,"-") -> - | Y8: =IFERROR(U8/X8,"-") -> - | AB8: =IFERROR(ROUNDDOWN(S8*AA8,0),"-") -> 0 | AC8: =IFERROR(P8/AB8,"-") -> - | AF8: =IF(G8="CPI",AJ8*AE8,IFERROR(ROUNDDOWN(AB8*AE8,0),"-")) -> 0 | AG8: =IFERROR(P8/AF8,"-") -> - | AJ8: =IF(G8="CPI",I8,0) -> 0 | AK8: =IFERROR(P8/AJ8,"-") -> - | AM8: =IFERROR(P8/AO8,"-") -> - | AO8: =AN8*AF8 -> 0
F9: 01.01.2026 - 31.01.2026 | G9: CPC | I9: =IFERROR(S9*AA9,"-") -> 0 | K9: =IFERROR((H9*I9),"-") -> 0 | M9: =IFERROR(K9*(1-L9),"-") -> 0 | O9: =IFERROR(M9*(1+N9),"-") -> 0 | P9: =IFERROR(O9*1.22,"-") -> 0 | Q9: =IFERROR(P9/$P$13,"-") -> - | U9: - | V9: =IFERROR(P9/S9*1000,"-") -> - | W9: =IFERROR(P9/U9*1000,"-") -> - | Y9: =IFERROR(U9/X9,"-") -> - | AB9: =IFERROR(ROUNDDOWN(S9*AA9,0),"-") -> 0 | AC9: =IFERROR(P9/AB9,"-") -> - | AF9: =IF(G9="CPI",AJ9*AE9,IFERROR(ROUNDDOWN(AB9*AE9,0),"-")) -> 0 | AG9: =IFERROR(P9/AF9,"-") -> - | AJ9: =IF(G9="CPI",I9,0) -> 0 | AK9: =IFERROR(P9/AJ9,"-") -> - | AM9: =IFERROR(P9/AO9,"-") -> - | AO9: =AN9*AF9 -> 0
F10: 01.01.2026 - 31.01.2026 | G10: CPC | I10: =IFERROR(S10*AA10,"-") -> 0 | K10: =IFERROR((H10*I10),"-") -> 0 | M10: =IFERROR(K10*(1-L10),"-") -> 0 | O10: =IFERROR(M10*(1+N10),"-") -> 0 | P10: =IFERROR(O10*1.22,"-") -> 0 | Q10: =IFERROR(P10/$P$13,"-") -> - | U10: - | V10: =IFERROR(P10/S10*1000,"-") -> - | W10: =IFERROR(P10/U10*1000,"-") -> - | Y10: =IFERROR(U10/X10,"-") -> - | AB10: =IFERROR(ROUNDDOWN(S10*AA10,0),"-") -> 0 | AC10: =IFERROR(P10/AB10,"-") -> - | AF10: =IF(G10="CPI",AJ10*AE10,IFERROR(ROUNDDOWN(AB10*AE10,0),"-")) -> 0 | AG10: =IFERROR(P10/AF10,"-") -> - | AJ10: =IF(G10="CPI",I10,0) -> 0 | AK10: =IFERROR(P10/AJ10,"-") -> - | AM10: =IFERROR(P10/AO10,"-") -> - | AO10: =AN10*AF10 -> 0
F11: 01.01.2026 - 31.01.2026 | G11: CPC | I11: =IFERROR(S11*AA11,"-") -> 0 | K11: =IFERROR((H11*I11),"-") -> 0 | M11: =IFERROR(K11*(1-L11),"-") -> 0 | O11: =IFERROR(M11*(1+N11),"-") -> 0 | P11: =IFERROR(O11*1.22,"-") -> 0 | Q11: =IFERROR(P11/$P$13,"-") -> - | U11: - | V11: =IFERROR(P11/S11*1000,"-") -> - | W11: =IFERROR(P11/U11*1000,"-") -> - | Y11: =IFERROR(U11/X11,"-") -> - | AB11: =IFERROR(ROUNDDOWN(S11*AA11,0),"-") -> 0 | AC11: =IFERROR(P11/AB11,"-") -> - | AF11: =IF(G11="CPI",AJ11*AE11,IFERROR(ROUNDDOWN(AB11*AE11,0),"-")) -> 0 | AG11: =IFERROR(P11/AF11,"-") -> - | AJ11: =IF(G11="CPI",I11,0) -> 0 | AK11: =IFERROR(P11/AJ11,"-") -> - | AM11: =IFERROR(P11/AO11,"-") -> - | AO11: =AN11*AF11 -> 0
F12: 01.01.2026 - 31.01.2026 | G12: CPC | I12: =IFERROR(S12*AA12,"-") -> 0 | K12: =IFERROR((H12*I12),"-") -> 0 | M12: =IFERROR(K12*(1-L12),"-") -> 0 | O12: =IFERROR(M12*(1+N12),"-") -> 0 | P12: =IFERROR(O12*1.22,"-") -> 0 | Q12: =IFERROR(P12/$P$13,"-") -> - | U12: - | V12: =IFERROR(P12/S12*1000,"-") -> - | W12: =IFERROR(P12/U12*1000,"-") -> - | Y12: =IFERROR(U12/X12,"-") -> - | AB12: =IFERROR(ROUNDDOWN(S12*AA12,0),"-") -> 0 | AC12: =IFERROR(P12/AB12,"-") -> - | AF12: =IF(G12="CPI",AJ12*AE12,IFERROR(ROUNDDOWN(AB12*AE12,0),"-")) -> 0 | AG12: =IFERROR(P12/AF12,"-") -> - | AJ12: =IF(G12="CPI",I12,0) -> 0 | AK12: =IFERROR(P12/AJ12,"-") -> - | AM12: =IFERROR(P12/AO12,"-") -> - | AO12: =AN12*AF12 -> 0
B13: Итого | C13: - | D13: - | F13: - | G13: - | H13: =IFERROR(K13/I13,"-") -> - | I13: =IFERROR(SUM(I3:I12),"-") -> 0 | K13: =IFERROR(SUM(K3:K12),"-") -> 0 | L13: - | M13: =IFERROR(SUM(M3:M12),"-") -> 0 | N13: - | O13: =IFERROR(SUM(O3:O12),"-") -> 0 | P13: =IFERROR(O13*1.22,"-") -> 0 | Q13: 0 | S13: =IFERROR(SUM(S3:S12),"-") -> 0 | T13: - | U13: - | V13: =IFERROR(P13/S13*1000,"-") -> - | W13: =IFERROR(P13/U13*1000,"-") -> - | X13: - | Y13: - | AA13: =IFERROR(AB13/S13,"-") -> - | AB13: =IFERROR(SUM(AB3:AB12),"-") -> 0 | AC13: =IFERROR(P13/AB13,"-") -> - | AE13: =IFERROR(AF13/AB13,"-") -> - | AF13: =IFERROR(SUM(AF3:AF12),"-") -> 0 | AG13: =IFERROR(P13/AF13,"-") -> - | AI13: =IFERROR(AJ13/AB13,"-") -> - | AJ13: 0 | AK13: =IFERROR(L13/AJ13,"-") -> - | AM13: =IFERROR(P13/AO13,"-") -> - | AN13: =IFERROR(AO13/AF13,"-") -> - | AO13: =IFERROR(SUM(AO3:AO12),"-") -> 0
B15: Рекламная система | C15: Рекламный формат, размер, вид размещения | D15: Таргетинги | F15: Период | G15: Единица измерения стоимости | H15: Цена за единицу (без НДС) | I15: Кол-во единиц | K15: Стоимость (без НДС) | L15: СК, % | M15: Стоимость с учетом СК (без НДС) | N15: АК, % | O15: Итоговая стоимость (без НДС) | P15: Итоговая стоимость (с НДС) | Q15: Доля рекламного бюджета, % | S15: Показы | T15: Частота (весь срок) | U15: Охват | V15: CPM (с НДС) | W15: CPT (с НДС) | X15: Доступная емкость аудитории | Y15: SOV, % | AA15: CTR, % | AB15: Клики | AC15: CPC (с НДС) | AE15: CR, % | AF15: Конверсии | AG15: CPA (с НДС) | AI15: CR(I), % | AJ15: Установки | AK15: CPI | AM15: ДРР, % | AN15: Средний чек | AO15: Доход
F16: 01.02.2026 - 28.02.2026 | G16: CPC | I16: =IFERROR(S16*AA16,"-") -> 0 | K16: =IFERROR((H16*I16),"-") -> 0 | M16: =IFERROR(K16*(1-L16),"-") -> 0 | O16: =IFERROR(M16*(1+N16),"-") -> 0 | P16: =IFERROR(O16*1.22,"-") -> 0 | Q16: =IFERROR(P16/$P$13,"-") -> - | U16: - | V16: =IFERROR(P16/S16*1000,"-") -> - | W16: =IFERROR(P16/U16*1000,"-") -> - | Y16: =IFERROR(U16/X16,"-") -> - | AB16: =IFERROR(ROUNDDOWN(S16*AA16,0),"-") -> 0 | AC16: =IFERROR(P16/AB16,"-") -> - | AF16: =IF(G16="CPI",AJ16*AE16,IFERROR(ROUNDDOWN(AB16*AE16,0),"-")) -> 0 | AG16: =IFERROR(P16/AF16,"-") -> - | AJ16: =IF(G16="CPI",I16,0) -> 0 | AK16: =IFERROR(P16/AJ16,"-") -> - | AM16: =IFERROR(P16/AO16,"-") -> - | AO16: =AN16*AF16 -> 0
F17: 01.02.2026 - 28.02.2026 | G17: CPC | I17: =IFERROR(S17*AA17,"-") -> 0 | K17: =IFERROR((H17*I17),"-") -> 0 | M17: =IFERROR(K17*(1-L17),"-") -> 0 | O17: =IFERROR(M17*(1+N17),"-") -> 0 | P17: =IFERROR(O17*1.22,"-") -> 0 | Q17: =IFERROR(P17/$P$13,"-") -> - | U17: 0 | V17: =IFERROR(P17/S17*1000,"-") -> - | W17: =IFERROR(P17/U17*1000,"-") -> - | Y17: =IFERROR(U17/X17,"-") -> - | AB17: =IFERROR(ROUNDDOWN(S17*AA17,0),"-") -> 0 | AC17: =IFERROR(P17/AB17,"-") -> - | AF17: =IF(G17="CPI",AJ17*AE17,IFERROR(ROUNDDOWN(AB17*AE17,0),"-")) -> 0 | AG17: =IFERROR(P17/AF17,"-") -> - | AJ17: =IF(G17="CPI",I17,0) -> 0 | AK17: =IFERROR(P17/AJ17,"-") -> - | AM17: =IFERROR(P17/AO17,"-") -> - | AO17: =AN17*AF17 -> 0
F18: 01.02.2026 - 28.02.2026 | G18: CPC | I18: =IFERROR(S18*AA18,"-") -> 0 | K18: =IFERROR((H18*I18),"-") -> 0 | M18: =IFERROR(K18*(1-L18),"-") -> 0 | O18: =IFERROR(M18*(1+N18),"-") -> 0 | P18: =IFERROR(O18*1.22,"-") -> 0 | Q18: =IFERROR(P18/$P$13,"-") -> - | U18: 0 | V18: =IFERROR(P18/S18*1000,"-") -> - | W18: =IFERROR(P18/U18*1000,"-") -> - | Y18: =IFERROR(U18/X18,"-") -> - | AB18: =IFERROR(ROUNDDOWN(S18*AA18,0),"-") -> 0 | AC18: =IFERROR(P18/AB18,"-") -> - | AF18: =IF(G18="CPI",AJ18*AE18,IFERROR(ROUNDDOWN(AB18*AE18,0),"-")) -> 0 | AG18: =IFERROR(P18/AF18,"-") -> - | AJ18: =IF(G18="CPI",I18,0) -> 0 | AK18: =IFERROR(P18/AJ18,"-") -> - | AM18: =IFERROR(P18/AO18,"-") -> - | AO18: =AN18*AF18 -> 0
F19: 01.02.2026 - 28.02.2026 | G19: CPC | I19: =IFERROR(S19*AA19,"-") -> 0 | K19: =IFERROR((H19*I19),"-") -> 0 | M19: =IFERROR(K19*(1-L19),"-") -> 0 | O19: =IFERROR(M19*(1+N19),"-") -> 0 | P19: =IFERROR(O19*1.22,"-") -> 0 | Q19: =IFERROR(P19/$P$13,"-") -> - | U19: 0 | V19: =IFERROR(P19/S19*1000,"-") -> - | W19: =IFERROR(P19/U19*1000,"-") -> - | Y19: =IFERROR(U19/X19,"-") -> - | AB19: =IFERROR(ROUNDDOWN(S19*AA19,0),"-") -> 0 | AC19: =IFERROR(P19/AB19,"-") -> - | AF19: =IF(G19="CPI",AJ19*AE19,IFERROR(ROUNDDOWN(AB19*AE19,0),"-")) -> 0 | AG19: =IFERROR(P19/AF19,"-") -> - | AJ19: =IF(G19="CPI",I19,0) -> 0 | AK19: =IFERROR(P19/AJ19,"-") -> - | AM19: =IFERROR(P19/AO19,"-") -> - | AO19: =AN19*AF19 -> 0
F20: 01.02.2026 - 28.02.2026 | G20: CPC | I20: =IFERROR(S20*AA20,"-") -> 0 | K20: =IFERROR((H20*I20),"-") -> 0 | M20: =IFERROR(K20*(1-L20),"-") -> 0 | O20: =IFERROR(M20*(1+N20),"-") -> 0 | P20: =IFERROR(O20*1.22,"-") -> 0 | Q20: =IFERROR(P20/$P$13,"-") -> - | U20: 0 | V20: =IFERROR(P20/S20*1000,"-") -> - | W20: =IFERROR(P20/U20*1000,"-") -> - | Y20: =IFERROR(U20/X20,"-") -> - | AB20: =IFERROR(ROUNDDOWN(S20*AA20,0),"-") -> 0 | AC20: =IFERROR(P20/AB20,"-") -> - | AF20: =IF(G20="CPI",AJ20*AE20,IFERROR(ROUNDDOWN(AB20*AE20,0),"-")) -> 0 | AG20: =IFERROR(P20/AF20,"-") -> - | AJ20: =IF(G20="CPI",I20,0) -> 0 | AK20: =IFERROR(P20/AJ20,"-") -> - | AM20: =IFERROR(P20/AO20,"-") -> - | AO20: =AN20*AF20 -> 0
F21: 01.02.2026 - 28.02.2026 | G21: CPC | I21: =IFERROR(S21*AA21,"-") -> 0 | K21: =IFERROR((H21*I21),"-") -> 0 | M21: =IFERROR(K21*(1-L21),"-") -> 0 | O21: =IFERROR(M21*(1+N21),"-") -> 0 | P21: =IFERROR(O21*1.22,"-") -> 0 | Q21: =IFERROR(P21/$P$13,"-") -> - | U21: 0 | V21: =IFERROR(P21/S21*1000,"-") -> - | W21: =IFERROR(P21/U21*1000,"-") -> - | Y21: =IFERROR(U21/X21,"-") -> - | AB21: =IFERROR(ROUNDDOWN(S21*AA21,0),"-") -> 0 | AC21: =IFERROR(P21/AB21,"-") -> - | AF21: =IF(G21="CPI",AJ21*AE21,IFERROR(ROUNDDOWN(AB21*AE21,0),"-")) -> 0 | AG21: =IFERROR(P21/AF21,"-") -> - | AJ21: =IF(G21="CPI",I21,0) -> 0 | AK21: =IFERROR(P21/AJ21,"-") -> - | AM21: =IFERROR(P21/AO21,"-") -> - | AO21: =AN21*AF21 -> 0
F22: 01.02.2026 - 28.02.2026 | G22: CPC | I22: =IFERROR(S22*AA22,"-") -> 0 | K22: =IFERROR((H22*I22),"-") -> 0 | M22: =IFERROR(K22*(1-L22),"-") -> 0 | O22: =IFERROR(M22*(1+N22),"-") -> 0 | P22: =IFERROR(O22*1.22,"-") -> 0 | Q22: =IFERROR(P22/$P$13,"-") -> - | U22: 0 | V22: =IFERROR(P22/S22*1000,"-") -> - | W22: =IFERROR(P22/U22*1000,"-") -> - | Y22: =IFERROR(U22/X22,"-") -> - | AB22: =IFERROR(ROUNDDOWN(S22*AA22,0),"-") -> 0 | AC22: =IFERROR(P22/AB22,"-") -> - | AF22: =IF(G22="CPI",AJ22*AE22,IFERROR(ROUNDDOWN(AB22*AE22,0),"-")) -> 0 | AG22: =IFERROR(P22/AF22,"-") -> - | AJ22: =IF(G22="CPI",I22,0) -> 0 | AK22: =IFERROR(P22/AJ22,"-") -> - | AM22: =IFERROR(P22/AO22,"-") -> - | AO22: =AN22*AF22 -> 0
F23: 01.02.2026 - 28.02.2026 | G23: CPC | I23: =IFERROR(S23*AA23,"-") -> 0 | K23: =IFERROR((H23*I23),"-") -> 0 | M23: =IFERROR(K23*(1-L23),"-") -> 0 | O23: =IFERROR(M23*(1+N23),"-") -> 0 | P23: =IFERROR(O23*1.22,"-") -> 0 | Q23: =IFERROR(P23/$P$13,"-") -> - | U23: - | V23: =IFERROR(P23/S23*1000,"-") -> - | W23: =IFERROR(P23/U23*1000,"-") -> - | Y23: =IFERROR(U23/X23,"-") -> - | AB23: =IFERROR(ROUNDDOWN(S23*AA23,0),"-") -> 0 | AC23: =IFERROR(P23/AB23,"-") -> - | AF23: =IF(G23="CPI",AJ23*AE23,IFERROR(ROUNDDOWN(AB23*AE23,0),"-")) -> 0 | AG23: =IFERROR(P23/AF23,"-") -> - | AJ23: =IF(G23="CPI",I23,0) -> 0 | AK23: =IFERROR(P23/AJ23,"-") -> - | AM23: =IFERROR(P23/AO23,"-") -> - | AO23: =AN23*AF23 -> 0
F24: 01.02.2026 - 28.02.2026 | G24: CPC | I24: =IFERROR(S24*AA24,"-") -> 0 | K24: =IFERROR((H24*I24),"-") -> 0 | M24: =IFERROR(K24*(1-L24),"-") -> 0 | O24: =IFERROR(M24*(1+N24),"-") -> 0 | P24: =IFERROR(O24*1.22,"-") -> 0 | Q24: =IFERROR(P24/$P$13,"-") -> - | U24: - | V24: =IFERROR(P24/S24*1000,"-") -> - | W24: =IFERROR(P24/U24*1000,"-") -> - | Y24: =IFERROR(U24/X24,"-") -> - | AB24: =IFERROR(ROUNDDOWN(S24*AA24,0),"-") -> 0 | AC24: =IFERROR(P24/AB24,"-") -> - | AF24: =IF(G24="CPI",AJ24*AE24,IFERROR(ROUNDDOWN(AB24*AE24,0),"-")) -> 0 | AG24: =IFERROR(P24/AF24,"-") -> - | AJ24: =IF(G24="CPI",I24,0) -> 0 | AK24: =IFERROR(P24/AJ24,"-") -> - | AM24: =IFERROR(P24/AO24,"-") -> - | AO24: =AN24*AF24 -> 0
F25: 01.02.2026 - 28.02.2026 | G25: CPC | I25: =IFERROR(S25*AA25,"-") -> 0 | K25: =IFERROR((H25*I25),"-") -> 0 | M25: =IFERROR(K25*(1-L25),"-") -> 0 | O25: =IFERROR(M25*(1+N25),"-") -> 0 | P25: =IFERROR(O25*1.22,"-") -> 0 | Q25: =IFERROR(P25/$P$13,"-") -> - | U25: - | V25: =IFERROR(P25/S25*1000,"-") -> - | W25: =IFERROR(P25/U25*1000,"-") -> - | Y25: =IFERROR(U25/X25,"-") -> - | AB25: =IFERROR(ROUNDDOWN(S25*AA25,0),"-") -> 0 | AC25: =IFERROR(P25/AB25,"-") -> - | AF25: =IF(G25="CPI",AJ25*AE25,IFERROR(ROUNDDOWN(AB25*AE25,0),"-")) -> 0 | AG25: =IFERROR(P25/AF25,"-") -> - | AJ25: =IF(G25="CPI",I25,0) -> 0 | AK25: =IFERROR(P25/AJ25,"-") -> - | AM25: =IFERROR(P25/AO25,"-") -> - | AO25: =AN25*AF25 -> 0
B26: Итого | C26: - | D26: - | F26: - | G26: - | H26: =IFERROR(K26/I26,"-") -> - | I26: =IFERROR(SUM(I16:I25),"-") -> 0 | K26: =IFERROR(SUM(K16:K25),"-") -> 0 | L26: - | M26: =IFERROR(SUM(M16:M25),"-") -> 0 | N26: - | O26: =IFERROR(SUM(O16:O25),"-") -> 0 | P26: =IFERROR(O26*1.22,"-") -> 0 | Q26: 0 | S26: =IFERROR(SUM(S16:S25),"-") -> 0 | T26: - | U26: - | V26: =IFERROR(P26/S26*1000,"-") -> - | W26: =IFERROR(P26/U26*1000,"-") -> - | X26: - | Y26: - | AA26: =IFERROR(AB26/S26,"-") -> - | AB26: =IFERROR(SUM(AB16:AB25),"-") -> 0 | AC26: =IFERROR(P26/AB26,"-") -> - | AE26: =IFERROR(AF26/AB26,"-") -> - | AF26: =IFERROR(SUM(AF16:AF25),"-") -> 0 | AG26: =IFERROR(P26/AF26,"-") -> - | AI26: =IFERROR(AJ26/AB26,"-") -> - | AJ26: 0 | AK26: =IFERROR(L26/AJ26,"-") -> - | AM26: =IFERROR(P26/AO26,"-") -> - | AN26: =IFERROR(AO26/AF26,"-") -> - | AO26: =IFERROR(SUM(AO16:AO25),"-") -> 0
B28: Рекламная система | C28: Рекламный формат, размер, вид размещения | D28: Таргетинги | F28: Период | G28: Единица измерения стоимости | H28: Цена за единицу (без НДС) | I28: Кол-во единиц | K28: Стоимость (без НДС) | L28: СК, % | M28: Стоимость с учетом СК (без НДС) | N28: АК, % | O28: Итоговая стоимость (без НДС) | P28: Итоговая стоимость (с НДС) | Q28: Доля рекламного бюджета, % | S28: Показы | T28: Частота (весь срок) | U28: Охват | V28: CPM (с НДС) | W28: CPT (с НДС) | X28: Доступная емкость аудитории | Y28: SOV, % | AA28: CTR, % | AB28: Клики | AC28: CPC (с НДС) | AE28: CR, % | AF28: Конверсии | AG28: CPA (с НДС) | AI28: CR(I), % | AJ28: Установки | AK28: CPI | AM28: ДРР, % | AN28: Средний чек | AO28: Доход
F29: 01.03.2026 - 31.03.2026 | G29: CPC | I29: =IFERROR(S29*AA29,"-") -> 0 | K29: =IFERROR((H29*I29),"-") -> 0 | M29: =IFERROR(K29*(1-L29),"-") -> 0 | O29: =IFERROR(M29*(1+N29),"-") -> 0 | P29: =IFERROR(O29*1.22,"-") -> 0 | Q29: =IFERROR(P29/$P$13,"-") -> - | U29: - | V29: =IFERROR(P29/S29*1000,"-") -> - | W29: =IFERROR(P29/U29*1000,"-") -> - | Y29: =IFERROR(U29/X29,"-") -> - | AB29: =IFERROR(ROUNDDOWN(S29*AA29,0),"-") -> 0 | AC29: =IFERROR(P29/AB29,"-") -> - | AF29: =IF(G29="CPI",AJ29*AE29,IFERROR(ROUNDDOWN(AB29*AE29,0),"-")) -> 0 | AG29: =IFERROR(P29/AF29,"-") -> - | AJ29: =IF(G29="CPI",I29,0) -> 0 | AK29: =IFERROR(P29/AJ29,"-") -> - | AM29: =IFERROR(P29/AO29,"-") -> - | AO29: =AN29*AF29 -> 0
F30: 01.03.2026 - 31.03.2026 | G30: CPC | I30: =IFERROR(S30*AA30,"-") -> 0 | K30: =IFERROR((H30*I30),"-") -> 0 | M30: =IFERROR(K30*(1-L30),"-") -> 0 | O30: =IFERROR(M30*(1+N30),"-") -> 0 | P30: =IFERROR(O30*1.22,"-") -> 0 | Q30: =IFERROR(P30/$P$13,"-") -> - | U30: - | V30: =IFERROR(P30/S30*1000,"-") -> - | W30: =IFERROR(P30/U30*1000,"-") -> - | Y30: =IFERROR(U30/X30,"-") -> - | AB30: =IFERROR(ROUNDDOWN(S30*AA30,0),"-") -> 0 | AC30: =IFERROR(P30/AB30,"-") -> - | AF30: =IF(G30="CPI",AJ30*AE30,IFERROR(ROUNDDOWN(AB30*AE30,0),"-")) -> 0 | AG30: =IFERROR(P30/AF30,"-") -> - | AJ30: =IF(G30="CPI",I30,0) -> 0 | AK30: =IFERROR(P30/AJ30,"-") -> - | AM30: =IFERROR(P30/AO30,"-") -> - | AO30: =AN30*AF30 -> 0
F31: 01.03.2026 - 31.03.2026 | G31: CPC | I31: =IFERROR(S31*AA31,"-") -> 0 | K31: =IFERROR((H31*I31),"-") -> 0 | M31: =IFERROR(K31*(1-L31),"-") -> 0 | O31: =IFERROR(M31*(1+N31),"-") -> 0 | P31: =IFERROR(O31*1.22,"-") -> 0 | Q31: =IFERROR(P31/$P$13,"-") -> - | U31: - | V31: =IFERROR(P31/S31*1000,"-") -> - | W31: =IFERROR(P31/U31*1000,"-") -> - | Y31: =IFERROR(U31/X31,"-") -> - | AB31: =IFERROR(ROUNDDOWN(S31*AA31,0),"-") -> 0 | AC31: =IFERROR(P31/AB31,"-") -> - | AF31: =IF(G31="CPI",AJ31*AE31,IFERROR(ROUNDDOWN(AB31*AE31,0),"-")) -> 0 | AG31: =IFERROR(P31/AF31,"-") -> - | AJ31: =IF(G31="CPI",I31,0) -> 0 | AK31: =IFERROR(P31/AJ31,"-") -> - | AM31: =IFERROR(P31/AO31,"-") -> - | AO31: =AN31*AF31 -> 0
F32: 01.03.2026 - 31.03.2026 | G32: CPC | I32: =IFERROR(S32*AA32,"-") -> 0 | K32: =IFERROR((H32*I32),"-") -> 0 | M32: =IFERROR(K32*(1-L32),"-") -> 0 | O32: =IFERROR(M32*(1+N32),"-") -> 0 | P32: =IFERROR(O32*1.22,"-") -> 0 | Q32: =IFERROR(P32/$P$13,"-") -> - | U32: - | V32: =IFERROR(P32/S32*1000,"-") -> - | W32: =IFERROR(P32/U32*1000,"-") -> - | Y32: =IFERROR(U32/X32,"-") -> - | AB32: =IFERROR(ROUNDDOWN(S32*AA32,0),"-") -> 0 | AC32: =IFERROR(P32/AB32,"-") -> - | AF32: =IF(G32="CPI",AJ32*AE32,IFERROR(ROUNDDOWN(AB32*AE32,0),"-")) -> 0 | AG32: =IFERROR(P32/AF32,"-") -> - | AJ32: =IF(G32="CPI",I32,0) -> 0 | AK32: =IFERROR(P32/AJ32,"-") -> - | AM32: =IFERROR(P32/AO32,"-") -> - | AO32: =AN32*AF32 -> 0
F33: 01.03.2026 - 31.03.2026 | G33: CPC | I33: =IFERROR(S33*AA33,"-") -> 0 | K33: =IFERROR((H33*I33),"-") -> 0 | M33: =IFERROR(K33*(1-L33),"-") -> 0 | O33: =IFERROR(M33*(1+N33),"-") -> 0 | P33: =IFERROR(O33*1.22,"-") -> 0 | Q33: =IFERROR(P33/$P$13,"-") -> - | U33: - | V33: =IFERROR(P33/S33*1000,"-") -> - | W33: =IFERROR(P33/U33*1000,"-") -> - | Y33: =IFERROR(U33/X33,"-") -> - | AB33: =IFERROR(ROUNDDOWN(S33*AA33,0),"-") -> 0 | AC33: =IFERROR(P33/AB33,"-") -> - | AF33: =IF(G33="CPI",AJ33*AE33,IFERROR(ROUNDDOWN(AB33*AE33,0),"-")) -> 0 | AG33: =IFERROR(P33/AF33,"-") -> - | AJ33: =IF(G33="CPI",I33,0) -> 0 | AK33: =IFERROR(P33/AJ33,"-") -> - | AM33: =IFERROR(P33/AO33,"-") -> - | AO33: =AN33*AF33 -> 0
F34: 01.03.2026 - 31.03.2026 | G34: CPC | I34: =IFERROR(S34*AA34,"-") -> 0 | K34: =IFERROR((H34*I34),"-") -> 0 | M34: =IFERROR(K34*(1-L34),"-") -> 0 | O34: =IFERROR(M34*(1+N34),"-") -> 0 | P34: =IFERROR(O34*1.22,"-") -> 0 | Q34: =IFERROR(P34/$P$13,"-") -> - | U34: - | V34: =IFERROR(P34/S34*1000,"-") -> - | W34: =IFERROR(P34/U34*1000,"-") -> - | Y34: =IFERROR(U34/X34,"-") -> - | AB34: =IFERROR(ROUNDDOWN(S34*AA34,0),"-") -> 0 | AC34: =IFERROR(P34/AB34,"-") -> - | AF34: =IF(G34="CPI",AJ34*AE34,IFERROR(ROUNDDOWN(AB34*AE34,0),"-")) -> 0 | AG34: =IFERROR(P34/AF34,"-") -> - | AJ34: =IF(G34="CPI",I34,0) -> 0 | AK34: =IFERROR(P34/AJ34,"-") -> - | AM34: =IFERROR(P34/AO34,"-") -> - | AO34: =AN34*AF34 -> 0
F35: 01.03.2026 - 31.03.2026 | G35: CPC | I35: =IFERROR(S35*AA35,"-") -> 0 | K35: =IFERROR((H35*I35),"-") -> 0 | M35: =IFERROR(K35*(1-L35),"-") -> 0 | O35: =IFERROR(M35*(1+N35),"-") -> 0 | P35: =IFERROR(O35*1.22,"-") -> 0 | Q35: =IFERROR(P35/$P$13,"-") -> - | U35: - | V35: =IFERROR(P35/S35*1000,"-") -> - | W35: =IFERROR(P35/U35*1000,"-") -> - | Y35: =IFERROR(U35/X35,"-") -> - | AB35: =IFERROR(ROUNDDOWN(S35*AA35,0),"-") -> 0 | AC35: =IFERROR(P35/AB35,"-") -> - | AF35: =IF(G35="CPI",AJ35*AE35,IFERROR(ROUNDDOWN(AB35*AE35,0),"-")) -> 0 | AG35: =IFERROR(P35/AF35,"-") -> - | AJ35: =IF(G35="CPI",I35,0) -> 0 | AK35: =IFERROR(P35/AJ35,"-") -> - | AM35: =IFERROR(P35/AO35,"-") -> - | AO35: =AN35*AF35 -> 0
F36: 01.03.2026 - 31.03.2026 | G36: CPC | I36: =IFERROR(S36*AA36,"-") -> 0 | K36: =IFERROR((H36*I36),"-") -> 0 | M36: =IFERROR(K36*(1-L36),"-") -> 0 | O36: =IFERROR(M36*(1+N36),"-") -> 0 | P36: =IFERROR(O36*1.22,"-") -> 0 | Q36: =IFERROR(P36/$P$13,"-") -> - | U36: - | V36: =IFERROR(P36/S36*1000,"-") -> - | W36: =IFERROR(P36/U36*1000,"-") -> - | Y36: =IFERROR(U36/X36,"-") -> - | AB36: =IFERROR(ROUNDDOWN(S36*AA36,0),"-") -> 0 | AC36: =IFERROR(P36/AB36,"-") -> - | AF36: =IF(G36="CPI",AJ36*AE36,IFERROR(ROUNDDOWN(AB36*AE36,0),"-")) -> 0 | AG36: =IFERROR(P36/AF36,"-") -> - | AJ36: =IF(G36="CPI",I36,0) -> 0 | AK36: =IFERROR(P36/AJ36,"-") -> - | AM36: =IFERROR(P36/AO36,"-") -> - | AO36: =AN36*AF36 -> 0
F37: 01.03.2026 - 31.03.2026 | G37: CPC | I37: =IFERROR(S37*AA37,"-") -> 0 | K37: =IFERROR((H37*I37),"-") -> 0 | M37: =IFERROR(K37*(1-L37),"-") -> 0 | O37: =IFERROR(M37*(1+N37),"-") -> 0 | P37: =IFERROR(O37*1.22,"-") -> 0 | Q37: =IFERROR(P37/$P$13,"-") -> - | U37: - | V37: =IFERROR(P37/S37*1000,"-") -> - | W37: =IFERROR(P37/U37*1000,"-") -> - | Y37: =IFERROR(U37/X37,"-") -> - | AB37: =IFERROR(ROUNDDOWN(S37*AA37,0),"-") -> 0 | AC37: =IFERROR(P37/AB37,"-") -> - | AF37: =IF(G37="CPI",AJ37*AE37,IFERROR(ROUNDDOWN(AB37*AE37,0),"-")) -> 0 | AG37: =IFERROR(P37/AF37,"-") -> - | AJ37: =IF(G37="CPI",I37,0) -> 0 | AK37: =IFERROR(P37/AJ37,"-") -> - | AM37: =IFERROR(P37/AO37,"-") -> - | AO37: =AN37*AF37 -> 0
F38: 01.03.2026 - 31.03.2026 | G38: CPC | I38: =IFERROR(S38*AA38,"-") -> 0 | K38: =IFERROR((H38*I38),"-") -> 0 | M38: =IFERROR(K38*(1-L38),"-") -> 0 | O38: =IFERROR(M38*(1+N38),"-") -> 0 | P38: =IFERROR(O38*1.22,"-") -> 0 | Q38: =IFERROR(P38/$P$13,"-") -> - | U38: - | V38: =IFERROR(P38/S38*1000,"-") -> - | W38: =IFERROR(P38/U38*1000,"-") -> - | Y38: =IFERROR(U38/X38,"-") -> - | AB38: =IFERROR(ROUNDDOWN(S38*AA38,0),"-") -> 0 | AC38: =IFERROR(P38/AB38,"-") -> - | AF38: =IF(G38="CPI",AJ38*AE38,IFERROR(ROUNDDOWN(AB38*AE38,0),"-")) -> 0 | AG38: =IFERROR(P38/AF38,"-") -> - | AJ38: =IF(G38="CPI",I38,0) -> 0 | AK38: =IFERROR(P38/AJ38,"-") -> - | AM38: =IFERROR(P38/AO38,"-") -> - | AO38: =AN38*AF38 -> 0
B39: Итого | C39: - | D39: - | F39: - | G39: - | H39: =IFERROR(K39/I39,"-") -> - | I39: =IFERROR(SUM(I29:I38),"-") -> 0 | K39: =IFERROR(SUM(K29:K38),"-") -> 0 | L39: - | M39: =IFERROR(SUM(M29:M38),"-") -> 0 | N39: - | O39: =IFERROR(SUM(O29:O38),"-") -> 0 | P39: =IFERROR(O39*1.22,"-") -> 0 | Q39: 0 | S39: =IFERROR(SUM(S29:S38),"-") -> 0 | T39: - | U39: - | V39: =IFERROR(P39/S39*1000,"-") -> - | W39: =IFERROR(P39/U39*1000,"-") -> - | X39: - | Y39: - | AA39: =IFERROR(AB39/S39,"-") -> - | AB39: =IFERROR(SUM(AB29:AB38),"-") -> 0 | AC39: =IFERROR(P39/AB39,"-") -> - | AE39: =IFERROR(AF39/AB39,"-") -> - | AF39: =IFERROR(SUM(AF29:AF38),"-") -> 0 | AG39: =IFERROR(P39/AF39,"-") -> - | AI39: =IFERROR(AJ39/AB39,"-") -> - | AJ39: 0 | AK39: =IFERROR(L39/AJ39,"-") -> - | AM39: =IFERROR(P39/AO39,"-") -> - | AN39: =IFERROR(AO39/AF39,"-") -> - | AO39: =IFERROR(SUM(AO29:AO38),"-") -> 0
B41: Рекламная система | C41: Рекламный формат, размер, вид размещения | D41: Таргетинги | F41: Период | G41: Единица измерения стоимости | H41: Цена за единицу (без НДС) | I41: Кол-во единиц | K41: Стоимость (без НДС) | L41: СК, % | M41: Стоимость с учетом СК (без НДС) | N41: АК, % | O41: Итоговая стоимость (без НДС) | P41: Итоговая стоимость (с НДС) | Q41: Доля рекламного бюджета, % | S41: Показы | T41: Частота (весь срок) | U41: Охват | V41: CPM (с НДС) | W41: CPT (с НДС) | X41: Доступная емкость аудитории | Y41: SOV, % | AA41: CTR, % | AB41: Клики | AC41: CPC (с НДС) | AE41: CR, % | AF41: Конверсии | AG41: CPA (с НДС) | AI41: CR(I), % | AJ41: Установки | AK41: CPI | AM41: ДРР, % | AN41: Средний чек | AO41: Доход
F42: 01.04.2026 - 30.04.2026 | G42: CPC | I42: =IFERROR(S42*AA42,"-") -> 0 | K42: =IFERROR((H42*I42),"-") -> 0 | M42: =IFERROR(K42*(1-L42),"-") -> 0 | O42: =IFERROR(M42*(1+N42),"-") -> 0 | P42: =IFERROR(O42*1.22,"-") -> 0 | Q42: =IFERROR(P42/$P$13,"-") -> - | U42: - | V42: =IFERROR(P42/S42*1000,"-") -> - | W42: =IFERROR(P42/U42*1000,"-") -> - | Y42: =IFERROR(U42/X42,"-") -> - | AB42: =IFERROR(ROUNDDOWN(S42*AA42,0),"-") -> 0 | AC42: =IFERROR(P42/AB42,"-") -> - | AF42: =IF(G42="CPI",AJ42*AE42,IFERROR(ROUNDDOWN(AB42*AE42,0),"-")) -> 0 | AG42: =IFERROR(P42/AF42,"-") -> - | AJ42: =IF(G42="CPI",I42,0) -> 0 | AK42: =IFERROR(P42/AJ42,"-") -> - | AM42: =IFERROR(P42/AO42,"-") -> - | AO42: =AN42*AF42 -> 0
F43: 01.04.2026 - 30.04.2026 | G43: CPC | I43: =IFERROR(S43*AA43,"-") -> 0 | K43: =IFERROR((H43*I43),"-") -> 0 | M43: =IFERROR(K43*(1-L43),"-") -> 0 | O43: =IFERROR(M43*(1+N43),"-") -> 0 | P43: =IFERROR(O43*1.22,"-") -> 0 | Q43: =IFERROR(P43/$P$13,"-") -> - | U43: - | V43: =IFERROR(P43/S43*1000,"-") -> - | W43: =IFERROR(P43/U43*1000,"-") -> - | Y43: =IFERROR(U43/X43,"-") -> - | AB43: =IFERROR(ROUNDDOWN(S43*AA43,0),"-") -> 0 | AC43: =IFERROR(P43/AB43,"-") -> - | AF43: =IF(G43="CPI",AJ43*AE43,IFERROR(ROUNDDOWN(AB43*AE43,0),"-")) -> 0 | AG43: =IFERROR(P43/AF43,"-") -> - | AJ43: =IF(G43="CPI",I43,0) -> 0 | AK43: =IFERROR(P43/AJ43,"-") -> - | AM43: =IFERROR(P43/AO43,"-") -> - | AO43: =AN43*AF43 -> 0
F44: 01.04.2026 - 30.04.2026 | G44: CPC | I44: =IFERROR(S44*AA44,"-") -> 0 | K44: =IFERROR((H44*I44),"-") -> 0 | M44: =IFERROR(K44*(1-L44),"-") -> 0 | O44: =IFERROR(M44*(1+N44),"-") -> 0 | P44: =IFERROR(O44*1.22,"-") -> 0 | Q44: =IFERROR(P44/$P$13,"-") -> - | U44: - | V44: =IFERROR(P44/S44*1000,"-") -> - | W44: =IFERROR(P44/U44*1000,"-") -> - | Y44: =IFERROR(U44/X44,"-") -> - | AB44: =IFERROR(ROUNDDOWN(S44*AA44,0),"-") -> 0 | AC44: =IFERROR(P44/AB44,"-") -> - | AF44: =IF(G44="CPI",AJ44*AE44,IFERROR(ROUNDDOWN(AB44*AE44,0),"-")) -> 0 | AG44: =IFERROR(P44/AF44,"-") -> - | AJ44: =IF(G44="CPI",I44,0) -> 0 | AK44: =IFERROR(P44/AJ44,"-") -> - | AM44: =IFERROR(P44/AO44,"-") -> - | AO44: =AN44*AF44 -> 0
F45: 01.04.2026 - 30.04.2026 | G45: CPC | I45: =IFERROR(S45*AA45,"-") -> 0 | K45: =IFERROR((H45*I45),"-") -> 0 | M45: =IFERROR(K45*(1-L45),"-") -> 0 | O45: =IFERROR(M45*(1+N45),"-") -> 0 | P45: =IFERROR(O45*1.22,"-") -> 0 | Q45: =IFERROR(P45/$P$13,"-") -> - | U45: - | V45: =IFERROR(P45/S45*1000,"-") -> - | W45: =IFERROR(P45/U45*1000,"-") -> - | Y45: =IFERROR(U45/X45,"-") -> - | AB45: =IFERROR(ROUNDDOWN(S45*AA45,0),"-") -> 0 | AC45: =IFERROR(P45/AB45,"-") -> - | AF45: =IF(G45="CPI",AJ45*AE45,IFERROR(ROUNDDOWN(AB45*AE45,0),"-")) -> 0 | AG45: =IFERROR(P45/AF45,"-") -> - | AJ45: =IF(G45="CPI",I45,0) -> 0 | AK45: =IFERROR(P45/AJ45,"-") -> - | AM45: =IFERROR(P45/AO45,"-") -> - | AO45: =AN45*AF45 -> 0
F46: 01.04.2026 - 30.04.2026 | G46: CPC | I46: =IFERROR(S46*AA46,"-") -> 0 | K46: =IFERROR((H46*I46),"-") -> 0 | M46: =IFERROR(K46*(1-L46),"-") -> 0 | O46: =IFERROR(M46*(1+N46),"-") -> 0 | P46: =IFERROR(O46*1.22,"-") -> 0 | Q46: =IFERROR(P46/$P$13,"-") -> - | U46: - | V46: =IFERROR(P46/S46*1000,"-") -> - | W46: =IFERROR(P46/U46*1000,"-") -> - | Y46: =IFERROR(U46/X46,"-") -> - | AB46: =IFERROR(ROUNDDOWN(S46*AA46,0),"-") -> 0 | AC46: =IFERROR(P46/AB46,"-") -> - | AF46: =IF(G46="CPI",AJ46*AE46,IFERROR(ROUNDDOWN(AB46*AE46,0),"-")) -> 0 | AG46: =IFERROR(P46/AF46,"-") -> - | AJ46: =IF(G46="CPI",I46,0) -> 0 | AK46: =IFERROR(P46/AJ46,"-") -> - | AM46: =IFERROR(P46/AO46,"-") -> - | AO46: =AN46*AF46 -> 0
F47: 01.04.2026 - 30.04.2026 | G47: CPC | I47: =IFERROR(S47*AA47,"-") -> 0 | K47: =IFERROR((H47*I47),"-") -> 0 | M47: =IFERROR(K47*(1-L47),"-") -> 0 | O47: =IFERROR(M47*(1+N47),"-") -> 0 | P47: =IFERROR(O47*1.22,"-") -> 0 | Q47: =IFERROR(P47/$P$13,"-") -> - | U47: - | V47: =IFERROR(P47/S47*1000,"-") -> - | W47: =IFERROR(P47/U47*1000,"-") -> - | Y47: =IFERROR(U47/X47,"-") -> - | AB47: =IFERROR(ROUNDDOWN(S47*AA47,0),"-") -> 0 | AC47: =IFERROR(P47/AB47,"-") -> - | AF47: =IF(G47="CPI",AJ47*AE47,IFERROR(ROUNDDOWN(AB47*AE47,0),"-")) -> 0 | AG47: =IFERROR(P47/AF47,"-") -> - | AJ47: =IF(G47="CPI",I47,0) -> 0 | AK47: =IFERROR(P47/AJ47,"-") -> - | AM47: =IFERROR(P47/AO47,"-") -> - | AO47: =AN47*AF47 -> 0
F48: 01.04.2026 - 30.04.2026 | G48: CPC | I48: =IFERROR(S48*AA48,"-") -> 0 | K48: =IFERROR((H48*I48),"-") -> 0 | M48: =IFERROR(K48*(1-L48),"-") -> 0 | O48: =IFERROR(M48*(1+N48),"-") -> 0 | P48: =IFERROR(O48*1.22,"-") -> 0 | Q48: =IFERROR(P48/$P$13,"-") -> - | U48: - | V48: =IFERROR(P48/S48*1000,"-") -> - | W48: =IFERROR(P48/U48*1000,"-") -> - | Y48: =IFERROR(U48/X48,"-") -> - | AB48: =IFERROR(ROUNDDOWN(S48*AA48,0),"-") -> 0 | AC48: =IFERROR(P48/AB48,"-") -> - | AF48: =IF(G48="CPI",AJ48*AE48,IFERROR(ROUNDDOWN(AB48*AE48,0),"-")) -> 0 | AG48: =IFERROR(P48/AF48,"-") -> - | AJ48: =IF(G48="CPI",I48,0) -> 0 | AK48: =IFERROR(P48/AJ48,"-") -> - | AM48: =IFERROR(P48/AO48,"-") -> - | AO48: =AN48*AF48 -> 0
F49: 01.04.2026 - 30.04.2026 | G49: CPC | I49: =IFERROR(S49*AA49,"-") -> 0 | K49: =IFERROR((H49*I49),"-") -> 0 | M49: =IFERROR(K49*(1-L49),"-") -> 0 | O49: =IFERROR(M49*(1+N49),"-") -> 0 | P49: =IFERROR(O49*1.22,"-") -> 0 | Q49: =IFERROR(P49/$P$13,"-") -> - | U49: - | V49: =IFERROR(P49/S49*1000,"-") -> - | W49: =IFERROR(P49/U49*1000,"-") -> - | Y49: =IFERROR(U49/X49,"-") -> - | AB49: =IFERROR(ROUNDDOWN(S49*AA49,0),"-") -> 0 | AC49: =IFERROR(P49/AB49,"-") -> - | AF49: =IF(G49="CPI",AJ49*AE49,IFERROR(ROUNDDOWN(AB49*AE49,0),"-")) -> 0 | AG49: =IFERROR(P49/AF49,"-") -> - | AJ49: =IF(G49="CPI",I49,0) -> 0 | AK49: =IFERROR(P49/AJ49,"-") -> - | AM49: =IFERROR(P49/AO49,"-") -> - | AO49: =AN49*AF49 -> 0
F50: 01.04.2026 - 30.04.2026 | G50: CPC | I50: =IFERROR(S50*AA50,"-") -> 0 | K50: =IFERROR((H50*I50),"-") -> 0 | M50: =IFERROR(K50*(1-L50),"-") -> 0 | O50: =IFERROR(M50*(1+N50),"-") -> 0 | P50: =IFERROR(O50*1.22,"-") -> 0 | Q50: =IFERROR(P50/$P$13,"-") -> - | U50: - | V50: =IFERROR(P50/S50*1000,"-") -> - | W50: =IFERROR(P50/U50*1000,"-") -> - | Y50: =IFERROR(U50/X50,"-") -> - | AB50: =IFERROR(ROUNDDOWN(S50*AA50,0),"-") -> 0 | AC50: =IFERROR(P50/AB50,"-") -> - | AF50: =IF(G50="CPI",AJ50*AE50,IFERROR(ROUNDDOWN(AB50*AE50,0),"-")) -> 0 | AG50: =IFERROR(P50/AF50,"-") -> - | AJ50: =IF(G50="CPI",I50,0) -> 0 | AK50: =IFERROR(P50/AJ50,"-") -> - | AM50: =IFERROR(P50/AO50,"-") -> - | AO50: =AN50*AF50 -> 0
F51: 01.04.2026 - 30.04.2026 | G51: CPC | I51: =IFERROR(S51*AA51,"-") -> 0 | K51: =IFERROR((H51*I51),"-") -> 0 | M51: =IFERROR(K51*(1-L51),"-") -> 0 | O51: =IFERROR(M51*(1+N51),"-") -> 0 | P51: =IFERROR(O51*1.22,"-") -> 0 | Q51: =IFERROR(P51/$P$13,"-") -> - | U51: - | V51: =IFERROR(P51/S51*1000,"-") -> - | W51: =IFERROR(P51/U51*1000,"-") -> - | Y51: =IFERROR(U51/X51,"-") -> - | AB51: =IFERROR(ROUNDDOWN(S51*AA51,0),"-") -> 0 | AC51: =IFERROR(P51/AB51,"-") -> - | AF51: =IF(G51="CPI",AJ51*AE51,IFERROR(ROUNDDOWN(AB51*AE51,0),"-")) -> 0 | AG51: =IFERROR(P51/AF51,"-") -> - | AJ51: =IF(G51="CPI",I51,0) -> 0 | AK51: =IFERROR(P51/AJ51,"-") -> - | AM51: =IFERROR(P51/AO51,"-") -> - | AO51: =AN51*AF51 -> 0
B52: Итого | C52: - | D52: - | F52: - | G52: - | H52: =IFERROR(K52/I52,"-") -> - | I52: =IFERROR(SUM(I42:I51),"-") -> 0 | K52: =IFERROR(SUM(K42:K51),"-") -> 0 | L52: - | M52: =IFERROR(SUM(M42:M51),"-") -> 0 | N52: - | O52: =IFERROR(SUM(O42:O51),"-") -> 0 | P52: =IFERROR(O52*1.22,"-") -> 0 | Q52: 0 | S52: =IFERROR(SUM(S42:S51),"-") -> 0 | T52: - | U52: - | V52: =IFERROR(P52/S52*1000,"-") -> - | W52: =IFERROR(P52/U52*1000,"-") -> - | X52: - | Y52: - | AA52: =IFERROR(AB52/S52,"-") -> - | AB52: =IFERROR(SUM(AB42:AB51),"-") -> 0 | AC52: =IFERROR(P52/AB52,"-") -> - | AE52: =IFERROR(AF52/AB52,"-") -> - | AF52: =IFERROR(SUM(AF42:AF51),"-") -> 0 | AG52: =IFERROR(P52/AF52,"-") -> - | AI52: =IFERROR(AJ52/AB52,"-") -> - | AJ52: 0 | AK52: =IFERROR(L52/AJ52,"-") -> - | AM52: =IFERROR(P52/AO52,"-") -> - | AN52: =IFERROR(AO52/AF52,"-") -> - | AO52: =IFERROR(SUM(AO42:AO51),"-") -> 0
B54: Рекламная система | C54: Рекламный формат, размер, вид размещения | D54: Таргетинги | F54: Период | G54: Единица измерения стоимости | H54: Цена за единицу (без НДС) | I54: Кол-во единиц | K54: Стоимость (без НДС) | L54: СК, % | M54: Стоимость с учетом СК (без НДС) | N54: АК, % | O54: Итоговая стоимость (без НДС) | P54: Итоговая стоимость (с НДС) | Q54: Доля рекламного бюджета, % | S54: Показы | T54: Частота (весь срок) | U54: Охват | V54: CPM (с НДС) | W54: CPT (с НДС) | X54: Доступная емкость аудитории | Y54: SOV, % | AA54: CTR, % | AB54: Клики | AC54: CPC (с НДС) | AE54: CR, % | AF54: Конверсии | AG54: CPA (с НДС) | AI54: CR(I), % | AJ54: Установки | AK54: CPI | AM54: ДРР, % | AN54: Средний чек | AO54: Доход
F55: 01.05.2026 - 31.05.2026 | G55: CPC | I55: =IFERROR(S55*AA55,"-") -> 0 | K55: =IFERROR((H55*I55),"-") -> 0 | M55: =IFERROR(K55*(1-L55),"-") -> 0 | O55: =IFERROR(M55*(1+N55),"-") -> 0 | P55: =IFERROR(O55*1.22,"-") -> 0 | Q55: =IFERROR(P55/$P$13,"-") -> - | U55: - | V55: =IFERROR(P55/S55*1000,"-") -> - | W55: =IFERROR(P55/U55*1000,"-") -> - | Y55: =IFERROR(U55/X55,"-") -> - | AB55: =IFERROR(ROUNDDOWN(S55*AA55,0),"-") -> 0 | AC55: =IFERROR(P55/AB55,"-") -> - | AF55: =IF(G55="CPI",AJ55*AE55,IFERROR(ROUNDDOWN(AB55*AE55,0),"-")) -> 0 | AG55: =IFERROR(P55/AF55,"-") -> - | AJ55: =IF(G55="CPI",I55,0) -> 0 | AK55: =IFERROR(P55/AJ55,"-") -> - | AM55: =IFERROR(P55/AO55,"-") -> - | AO55: =AN55*AF55 -> 0
F56: 01.05.2026 - 31.05.2026 | G56: CPC | I56: =IFERROR(S56*AA56,"-") -> 0 | K56: =IFERROR((H56*I56),"-") -> 0 | M56: =IFERROR(K56*(1-L56),"-") -> 0 | O56: =IFERROR(M56*(1+N56),"-") -> 0 | P56: =IFERROR(O56*1.22,"-") -> 0 | Q56: =IFERROR(P56/$P$13,"-") -> - | U56: - | V56: =IFERROR(P56/S56*1000,"-") -> - | W56: =IFERROR(P56/U56*1000,"-") -> - | Y56: =IFERROR(U56/X56,"-") -> - | AB56: =IFERROR(ROUNDDOWN(S56*AA56,0),"-") -> 0 | AC56: =IFERROR(P56/AB56,"-") -> - | AF56: =IF(G56="CPI",AJ56*AE56,IFERROR(ROUNDDOWN(AB56*AE56,0),"-")) -> 0 | AG56: =IFERROR(P56/AF56,"-") -> - | AJ56: =IF(G56="CPI",I56,0) -> 0 | AK56: =IFERROR(P56/AJ56,"-") -> - | AM56: =IFERROR(P56/AO56,"-") -> - | AO56: =AN56*AF56 -> 0
F57: 01.05.2026 - 31.05.2026 | G57: CPC | I57: =IFERROR(S57*AA57,"-") -> 0 | K57: =IFERROR((H57*I57),"-") -> 0 | M57: =IFERROR(K57*(1-L57),"-") -> 0 | O57: =IFERROR(M57*(1+N57),"-") -> 0 | P57: =IFERROR(O57*1.22,"-") -> 0 | Q57: =IFERROR(P57/$P$13,"-") -> - | U57: - | V57: =IFERROR(P57/S57*1000,"-") -> - | W57: =IFERROR(P57/U57*1000,"-") -> - | Y57: =IFERROR(U57/X57,"-") -> - | AB57: =IFERROR(ROUNDDOWN(S57*AA57,0),"-") -> 0 | AC57: =IFERROR(P57/AB57,"-") -> - | AF57: =IF(G57="CPI",AJ57*AE57,IFERROR(ROUNDDOWN(AB57*AE57,0),"-")) -> 0 | AG57: =IFERROR(P57/AF57,"-") -> - | AJ57: =IF(G57="CPI",I57,0) -> 0 | AK57: =IFERROR(P57/AJ57,"-") -> - | AM57: =IFERROR(P57/AO57,"-") -> - | AO57: =AN57*AF57 -> 0
F58: 01.05.2026 - 31.05.2026 | G58: CPC | I58: =IFERROR(S58*AA58,"-") -> 0 | K58: =IFERROR((H58*I58),"-") -> 0 | M58: =IFERROR(K58*(1-L58),"-") -> 0 | O58: =IFERROR(M58*(1+N58),"-") -> 0 | P58: =IFERROR(O58*1.22,"-") -> 0 | Q58: =IFERROR(P58/$P$13,"-") -> - | U58: - | V58: =IFERROR(P58/S58*1000,"-") -> - | W58: =IFERROR(P58/U58*1000,"-") -> - | Y58: =IFERROR(U58/X58,"-") -> - | AB58: =IFERROR(ROUNDDOWN(S58*AA58,0),"-") -> 0 | AC58: =IFERROR(P58/AB58,"-") -> - | AF58: =IF(G58="CPI",AJ58*AE58,IFERROR(ROUNDDOWN(AB58*AE58,0),"-")) -> 0 | AG58: =IFERROR(P58/AF58,"-") -> - | AJ58: =IF(G58="CPI",I58,0) -> 0 | AK58: =IFERROR(P58/AJ58,"-") -> - | AM58: =IFERROR(P58/AO58,"-") -> - | AO58: =AN58*AF58 -> 0
F59: 01.05.2026 - 31.05.2026 | G59: CPC | I59: =IFERROR(S59*AA59,"-") -> 0 | K59: =IFERROR((H59*I59),"-") -> 0 | M59: =IFERROR(K59*(1-L59),"-") -> 0 | O59: =IFERROR(M59*(1+N59),"-") -> 0 | P59: =IFERROR(O59*1.22,"-") -> 0 | Q59: =IFERROR(P59/$P$13,"-") -> - | U59: - | V59: =IFERROR(P59/S59*1000,"-") -> - | W59: =IFERROR(P59/U59*1000,"-") -> - | Y59: =IFERROR(U59/X59,"-") -> - | AB59: =IFERROR(ROUNDDOWN(S59*AA59,0),"-") -> 0 | AC59: =IFERROR(P59/AB59,"-") -> - | AF59: =IF(G59="CPI",AJ59*AE59,IFERROR(ROUNDDOWN(AB59*AE59,0),"-")) -> 0 | AG59: =IFERROR(P59/AF59,"-") -> - | AJ59: =IF(G59="CPI",I59,0) -> 0 | AK59: =IFERROR(P59/AJ59,"-") -> - | AM59: =IFERROR(P59/AO59,"-") -> - | AO59: =AN59*AF59 -> 0
F60: 01.05.2026 - 31.05.2026 | G60: CPC | I60: =IFERROR(S60*AA60,"-") -> 0 | K60: =IFERROR((H60*I60),"-") -> 0 | M60: =IFERROR(K60*(1-L60),"-") -> 0 | O60: =IFERROR(M60*(1+N60),"-") -> 0 | P60: =IFERROR(O60*1.22,"-") -> 0 | Q60: =IFERROR(P60/$P$13,"-") -> - | U60: - | V60: =IFERROR(P60/S60*1000,"-") -> - | W60: =IFERROR(P60/U60*1000,"-") -> - | Y60: =IFERROR(U60/X60,"-") -> - | AB60: =IFERROR(ROUNDDOWN(S60*AA60,0),"-") -> 0 | AC60: =IFERROR(P60/AB60,"-") -> - | AF60: =IF(G60="CPI",AJ60*AE60,IFERROR(ROUNDDOWN(AB60*AE60,0),"-")) -> 0 | AG60: =IFERROR(P60/AF60,"-") -> - | AJ60: =IF(G60="CPI",I60,0) -> 0 | AK60: =IFERROR(P60/AJ60,"-") -> - | AM60: =IFERROR(P60/AO60,"-") -> - | AO60: =AN60*AF60 -> 0
F61: 01.05.2026 - 31.05.2026 | G61: CPC | I61: =IFERROR(S61*AA61,"-") -> 0 | K61: =IFERROR((H61*I61),"-") -> 0 | M61: =IFERROR(K61*(1-L61),"-") -> 0 | O61: =IFERROR(M61*(1+N61),"-") -> 0 | P61: =IFERROR(O61*1.22,"-") -> 0 | Q61: =IFERROR(P61/$P$13,"-") -> - | U61: - | V61: =IFERROR(P61/S61*1000,"-") -> - | W61: =IFERROR(P61/U61*1000,"-") -> - | Y61: =IFERROR(U61/X61,"-") -> - | AB61: =IFERROR(ROUNDDOWN(S61*AA61,0),"-") -> 0 | AC61: =IFERROR(P61/AB61,"-") -> - | AF61: =IF(G61="CPI",AJ61*AE61,IFERROR(ROUNDDOWN(AB61*AE61,0),"-")) -> 0 | AG61: =IFERROR(P61/AF61,"-") -> - | AJ61: =IF(G61="CPI",I61,0) -> 0 | AK61: =IFERROR(P61/AJ61,"-") -> - | AM61: =IFERROR(P61/AO61,"-") -> - | AO61: =AN61*AF61 -> 0
F62: 01.05.2026 - 31.05.2026 | G62: CPC | I62: =IFERROR(S62*AA62,"-") -> 0 | K62: =IFERROR((H62*I62),"-") -> 0 | M62: =IFERROR(K62*(1-L62),"-") -> 0 | O62: =IFERROR(M62*(1+N62),"-") -> 0 | P62: =IFERROR(O62*1.22,"-") -> 0 | Q62: =IFERROR(P62/$P$13,"-") -> - | U62: - | V62: =IFERROR(P62/S62*1000,"-") -> - | W62: =IFERROR(P62/U62*1000,"-") -> - | Y62: =IFERROR(U62/X62,"-") -> - | AB62: =IFERROR(ROUNDDOWN(S62*AA62,0),"-") -> 0 | AC62: =IFERROR(P62/AB62,"-") -> - | AF62: =IF(G62="CPI",AJ62*AE62,IFERROR(ROUNDDOWN(AB62*AE62,0),"-")) -> 0 | AG62: =IFERROR(P62/AF62,"-") -> - | AJ62: =IF(G62="CPI",I62,0) -> 0 | AK62: =IFERROR(P62/AJ62,"-") -> - | AM62: =IFERROR(P62/AO62,"-") -> - | AO62: =AN62*AF62 -> 0
F63: 01.05.2026 - 31.05.2026 | G63: CPC | I63: =IFERROR(S63*AA63,"-") -> 0 | K63: =IFERROR((H63*I63),"-") -> 0 | M63: =IFERROR(K63*(1-L63),"-") -> 0 | O63: =IFERROR(M63*(1+N63),"-") -> 0 | P63: =IFERROR(O63*1.22,"-") -> 0 | Q63: =IFERROR(P63/$P$13,"-") -> - | U63: - | V63: =IFERROR(P63/S63*1000,"-") -> - | W63: =IFERROR(P63/U63*1000,"-") -> - | Y63: =IFERROR(U63/X63,"-") -> - | AB63: =IFERROR(ROUNDDOWN(S63*AA63,0),"-") -> 0 | AC63: =IFERROR(P63/AB63,"-") -> - | AF63: =IF(G63="CPI",AJ63*AE63,IFERROR(ROUNDDOWN(AB63*AE63,0),"-")) -> 0 | AG63: =IFERROR(P63/AF63,"-") -> - | AJ63: =IF(G63="CPI",I63,0) -> 0 | AK63: =IFERROR(P63/AJ63,"-") -> - | AM63: =IFERROR(P63/AO63,"-") -> - | AO63: =AN63*AF63 -> 0
F64: 01.05.2026 - 31.05.2026 | G64: CPC | I64: =IFERROR(S64*AA64,"-") -> 0 | K64: =IFERROR((H64*I64),"-") -> 0 | M64: =IFERROR(K64*(1-L64),"-") -> 0 | O64: =IFERROR(M64*(1+N64),"-") -> 0 | P64: =IFERROR(O64*1.22,"-") -> 0 | Q64: =IFERROR(P64/$P$13,"-") -> - | U64: - | V64: =IFERROR(P64/S64*1000,"-") -> - | W64: =IFERROR(P64/U64*1000,"-") -> - | Y64: =IFERROR(U64/X64,"-") -> - | AB64: =IFERROR(ROUNDDOWN(S64*AA64,0),"-") -> 0 | AC64: =IFERROR(P64/AB64,"-") -> - | AF64: =IF(G64="CPI",AJ64*AE64,IFERROR(ROUNDDOWN(AB64*AE64,0),"-")) -> 0 | AG64: =IFERROR(P64/AF64,"-") -> - | AJ64: =IF(G64="CPI",I64,0) -> 0 | AK64: =IFERROR(P64/AJ64,"-") -> - | AM64: =IFERROR(P64/AO64,"-") -> - | AO64: =AN64*AF64 -> 0
B65: Итого | C65: - | D65: - | F65: - | G65: - | H65: =IFERROR(K65/I65,"-") -> - | I65: =IFERROR(SUM(I55:I64),"-") -> 0 | K65: =IFERROR(SUM(K55:K64),"-") -> 0 | L65: - | M65: =IFERROR(SUM(M55:M64),"-") -> 0 | N65: - | O65: =IFERROR(SUM(O55:O64),"-") -> 0 | P65: =IFERROR(O65*1.22,"-") -> 0 | Q65: 0 | S65: =IFERROR(SUM(S55:S64),"-") -> 0 | T65: - | U65: - | V65: =IFERROR(P65/S65*1000,"-") -> - | W65: =IFERROR(P65/U65*1000,"-") -> - | X65: - | Y65: - | AA65: =IFERROR(AB65/S65,"-") -> - | AB65: =IFERROR(SUM(AB55:AB64),"-") -> 0 | AC65: =IFERROR(P65/AB65,"-") -> - | AE65: =IFERROR(AF65/AB65,"-") -> - | AF65: =IFERROR(SUM(AF55:AF64),"-") -> 0 | AG65: =IFERROR(P65/AF65,"-") -> - | AI65: =IFERROR(AJ65/AB65,"-") -> - | AJ65: 0 | AK65: =IFERROR(L65/AJ65,"-") -> - | AM65: =IFERROR(P65/AO65,"-") -> - | AN65: =IFERROR(AO65/AF65,"-") -> - | AO65: =IFERROR(SUM(AO55:AO64),"-") -> 0
B67: Рекламная система | C67: Рекламный формат, размер, вид размещения | D67: Таргетинги | F67: Период | G67: Единица измерения стоимости | H67: Цена за единицу (без НДС) | I67: Кол-во единиц | K67: Стоимость (без НДС) | L67: СК, % | M67: Стоимость с учетом СК (без НДС) | N67: АК, % | O67: Итоговая стоимость (без НДС) | P67: Итоговая стоимость (с НДС) | Q67: Доля рекламного бюджета, % | S67: Показы | T67: Частота (весь срок) | U67: Охват | V67: CPM (с НДС) | W67: CPT (с НДС) | X67: Доступная емкость аудитории | Y67: SOV, % | AA67: CTR, % | AB67: Клики | AC67: CPC (с НДС) | AE67: CR, % | AF67: Конверсии | AG67: CPA (с НДС) | AI67: CR(I), % | AJ67: Установки | AK67: CPI | AM67: ДРР, % | AN67: Средний чек | AO67: Доход
F68: 01.06.2026 - 30.06.2026 | G68: CPC | I68: =IFERROR(S68*AA68,"-") -> 0 | K68: =IFERROR((H68*I68),"-") -> 0 | M68: =IFERROR(K68*(1-L68),"-") -> 0 | O68: =IFERROR(M68*(1+N68),"-") -> 0 | P68: =IFERROR(O68*1.22,"-") -> 0 | Q68: =IFERROR(P68/$P$13,"-") -> - | U68: - | V68: =IFERROR(P68/S68*1000,"-") -> - | W68: =IFERROR(P68/U68*1000,"-") -> - | Y68: =IFERROR(U68/X68,"-") -> - | AB68: =IFERROR(ROUNDDOWN(S68*AA68,0),"-") -> 0 | AC68: =IFERROR(P68/AB68,"-") -> - | AF68: =IF(G68="CPI",AJ68*AE68,IFERROR(ROUNDDOWN(AB68*AE68,0),"-")) -> 0 | AG68: =IFERROR(P68/AF68,"-") -> - | AJ68: =IF(G68="CPI",I68,0) -> 0 | AK68: =IFERROR(P68/AJ68,"-") -> - | AM68: =IFERROR(P68/AO68,"-") -> - | AO68: =AN68*AF68 -> 0
F69: 01.06.2026 - 30.06.2026 | G69: CPC | I69: =IFERROR(S69*AA69,"-") -> 0 | K69: =IFERROR((H69*I69),"-") -> 0 | M69: =IFERROR(K69*(1-L69),"-") -> 0 | O69: =IFERROR(M69*(1+N69),"-") -> 0 | P69: =IFERROR(O69*1.22,"-") -> 0 | Q69: =IFERROR(P69/$P$13,"-") -> - | U69: - | V69: =IFERROR(P69/S69*1000,"-") -> - | W69: =IFERROR(P69/U69*1000,"-") -> - | Y69: =IFERROR(U69/X69,"-") -> - | AB69: =IFERROR(ROUNDDOWN(S69*AA69,0),"-") -> 0 | AC69: =IFERROR(P69/AB69,"-") -> - | AF69: =IF(G69="CPI",AJ69*AE69,IFERROR(ROUNDDOWN(AB69*AE69,0),"-")) -> 0 | AG69: =IFERROR(P69/AF69,"-") -> - | AJ69: =IF(G69="CPI",I69,0) -> 0 | AK69: =IFERROR(P69/AJ69,"-") -> - | AM69: =IFERROR(P69/AO69,"-") -> - | AO69: =AN69*AF69 -> 0
F70: 01.06.2026 - 30.06.2026 | G70: CPC | I70: =IFERROR(S70*AA70,"-") -> 0 | K70: =IFERROR((H70*I70),"-") -> 0 | M70: =IFERROR(K70*(1-L70),"-") -> 0 | O70: =IFERROR(M70*(1+N70),"-") -> 0 | P70: =IFERROR(O70*1.22,"-") -> 0 | Q70: =IFERROR(P70/$P$13,"-") -> - | U70: - | V70: =IFERROR(P70/S70*1000,"-") -> - | W70: =IFERROR(P70/U70*1000,"-") -> - | Y70: =IFERROR(U70/X70,"-") -> - | AB70: =IFERROR(ROUNDDOWN(S70*AA70,0),"-") -> 0 | AC70: =IFERROR(P70/AB70,"-") -> - | AF70: =IF(G70="CPI",AJ70*AE70,IFERROR(ROUNDDOWN(AB70*AE70,0),"-")) -> 0 | AG70: =IFERROR(P70/AF70,"-") -> - | AJ70: =IF(G70="CPI",I70,0) -> 0 | AK70: =IFERROR(P70/AJ70,"-") -> - | AM70: =IFERROR(P70/AO70,"-") -> - | AO70: =AN70*AF70 -> 0
F71: 01.06.2026 - 30.06.2026 | G71: CPC | I71: =IFERROR(S71*AA71,"-") -> 0 | K71: =IFERROR((H71*I71),"-") -> 0 | M71: =IFERROR(K71*(1-L71),"-") -> 0 | O71: =IFERROR(M71*(1+N71),"-") -> 0 | P71: =IFERROR(O71*1.22,"-") -> 0 | Q71: =IFERROR(P71/$P$13,"-") -> - | U71: - | V71: =IFERROR(P71/S71*1000,"-") -> - | W71: =IFERROR(P71/U71*1000,"-") -> - | Y71: =IFERROR(U71/X71,"-") -> - | AB71: =IFERROR(ROUNDDOWN(S71*AA71,0),"-") -> 0 | AC71: =IFERROR(P71/AB71,"-") -> - | AF71: =IF(G71="CPI",AJ71*AE71,IFERROR(ROUNDDOWN(AB71*AE71,0),"-")) -> 0 | AG71: =IFERROR(P71/AF71,"-") -> - | AJ71: =IF(G71="CPI",I71,0) -> 0 | AK71: =IFERROR(P71/AJ71,"-") -> - | AM71: =IFERROR(P71/AO71,"-") -> - | AO71: =AN71*AF71 -> 0
F72: 01.06.2026 - 30.06.2026 | G72: CPC | I72: =IFERROR(S72*AA72,"-") -> 0 | K72: =IFERROR((H72*I72),"-") -> 0 | M72: =IFERROR(K72*(1-L72),"-") -> 0 | O72: =IFERROR(M72*(1+N72),"-") -> 0 | P72: =IFERROR(O72*1.22,"-") -> 0 | Q72: =IFERROR(P72/$P$13,"-") -> - | U72: - | V72: =IFERROR(P72/S72*1000,"-") -> - | W72: =IFERROR(P72/U72*1000,"-") -> - | Y72: =IFERROR(U72/X72,"-") -> - | AB72: =IFERROR(ROUNDDOWN(S72*AA72,0),"-") -> 0 | AC72: =IFERROR(P72/AB72,"-") -> - | AF72: =IF(G72="CPI",AJ72*AE72,IFERROR(ROUNDDOWN(AB72*AE72,0),"-")) -> 0 | AG72: =IFERROR(P72/AF72,"-") -> - | AJ72: =IF(G72="CPI",I72,0) -> 0 | AK72: =IFERROR(P72/AJ72,"-") -> - | AM72: =IFERROR(P72/AO72,"-") -> - | AO72: =AN72*AF72 -> 0
F73: 01.06.2026 - 30.06.2026 | G73: CPC | I73: =IFERROR(S73*AA73,"-") -> 0 | K73: =IFERROR((H73*I73),"-") -> 0 | M73: =IFERROR(K73*(1-L73),"-") -> 0 | O73: =IFERROR(M73*(1+N73),"-") -> 0 | P73: =IFERROR(O73*1.22,"-") -> 0 | Q73: =IFERROR(P73/$P$13,"-") -> - | U73: - | V73: =IFERROR(P73/S73*1000,"-") -> - | W73: =IFERROR(P73/U73*1000,"-") -> - | Y73: =IFERROR(U73/X73,"-") -> - | AB73: =IFERROR(ROUNDDOWN(S73*AA73,0),"-") -> 0 | AC73: =IFERROR(P73/AB73,"-") -> - | AF73: =IF(G73="CPI",AJ73*AE73,IFERROR(ROUNDDOWN(AB73*AE73,0),"-")) -> 0 | AG73: =IFERROR(P73/AF73,"-") -> - | AJ73: =IF(G73="CPI",I73,0) -> 0 | AK73: =IFERROR(P73/AJ73,"-") -> - | AM73: =IFERROR(P73/AO73,"-") -> - | AO73: =AN73*AF73 -> 0
F74: 01.06.2026 - 30.06.2026 | G74: CPC | I74: =IFERROR(S74*AA74,"-") -> 0 | K74: =IFERROR((H74*I74),"-") -> 0 | M74: =IFERROR(K74*(1-L74),"-") -> 0 | O74: =IFERROR(M74*(1+N74),"-") -> 0 | P74: =IFERROR(O74*1.22,"-") -> 0 | Q74: =IFERROR(P74/$P$13,"-") -> - | U74: - | V74: =IFERROR(P74/S74*1000,"-") -> - | W74: =IFERROR(P74/U74*1000,"-") -> - | Y74: =IFERROR(U74/X74,"-") -> - | AB74: =IFERROR(ROUNDDOWN(S74*AA74,0),"-") -> 0 | AC74: =IFERROR(P74/AB74,"-") -> - | AF74: =IF(G74="CPI",AJ74*AE74,IFERROR(ROUNDDOWN(AB74*AE74,0),"-")) -> 0 | AG74: =IFERROR(P74/AF74,"-") -> - | AJ74: =IF(G74="CPI",I74,0) -> 0 | AK74: =IFERROR(P74/AJ74,"-") -> - | AM74: =IFERROR(P74/AO74,"-") -> - | AO74: =AN74*AF74 -> 0
F75: 01.06.2026 - 30.06.2026 | G75: CPC | I75: =IFERROR(S75*AA75,"-") -> 0 | K75: =IFERROR((H75*I75),"-") -> 0 | M75: =IFERROR(K75*(1-L75),"-") -> 0 | O75: =IFERROR(M75*(1+N75),"-") -> 0 | P75: =IFERROR(O75*1.22,"-") -> 0 | Q75: =IFERROR(P75/$P$13,"-") -> - | U75: - | V75: =IFERROR(P75/S75*1000,"-") -> - | W75: =IFERROR(P75/U75*1000,"-") -> - | Y75: =IFERROR(U75/X75,"-") -> - | AB75: =IFERROR(ROUNDDOWN(S75*AA75,0),"-") -> 0 | AC75: =IFERROR(P75/AB75,"-") -> - | AF75: =IF(G75="CPI",AJ75*AE75,IFERROR(ROUNDDOWN(AB75*AE75,0),"-")) -> 0 | AG75: =IFERROR(P75/AF75,"-") -> - | AJ75: =IF(G75="CPI",I75,0) -> 0 | AK75: =IFERROR(P75/AJ75,"-") -> - | AM75: =IFERROR(P75/AO75,"-") -> - | AO75: =AN75*AF75 -> 0
F76: 01.06.2026 - 30.06.2026 | G76: CPC | I76: =IFERROR(S76*AA76,"-") -> 0 | K76: =IFERROR((H76*I76),"-") -> 0 | M76: =IFERROR(K76*(1-L76),"-") -> 0 | O76: =IFERROR(M76*(1+N76),"-") -> 0 | P76: =IFERROR(O76*1.22,"-") -> 0 | Q76: =IFERROR(P76/$P$13,"-") -> - | U76: - | V76: =IFERROR(P76/S76*1000,"-") -> - | W76: =IFERROR(P76/U76*1000,"-") -> - | Y76: =IFERROR(U76/X76,"-") -> - | AB76: =IFERROR(ROUNDDOWN(S76*AA76,0),"-") -> 0 | AC76: =IFERROR(P76/AB76,"-") -> - | AF76: =IF(G76="CPI",AJ76*AE76,IFERROR(ROUNDDOWN(AB76*AE76,0),"-")) -> 0 | AG76: =IFERROR(P76/AF76,"-") -> - | AJ76: =IF(G76="CPI",I76,0) -> 0 | AK76: =IFERROR(P76/AJ76,"-") -> - | AM76: =IFERROR(P76/AO76,"-") -> - | AO76: =AN76*AF76 -> 0
F77: 01.06.2026 - 30.06.2026 | G77: CPC | I77: =IFERROR(S77*AA77,"-") -> 0 | K77: =IFERROR((H77*I77),"-") -> 0 | M77: =IFERROR(K77*(1-L77),"-") -> 0 | O77: =IFERROR(M77*(1+N77),"-") -> 0 | P77: =IFERROR(O77*1.22,"-") -> 0 | Q77: =IFERROR(P77/$P$13,"-") -> - | U77: - | V77: =IFERROR(P77/S77*1000,"-") -> - | W77: =IFERROR(P77/U77*1000,"-") -> - | Y77: =IFERROR(U77/X77,"-") -> - | AB77: =IFERROR(ROUNDDOWN(S77*AA77,0),"-") -> 0 | AC77: =IFERROR(P77/AB77,"-") -> - | AF77: =IF(G77="CPI",AJ77*AE77,IFERROR(ROUNDDOWN(AB77*AE77,0),"-")) -> 0 | AG77: =IFERROR(P77/AF77,"-") -> - | AJ77: =IF(G77="CPI",I77,0) -> 0 | AK77: =IFERROR(P77/AJ77,"-") -> - | AM77: =IFERROR(P77/AO77,"-") -> - | AO77: =AN77*AF77 -> 0
B78: Итого | C78: - | D78: - | F78: - | G78: - | H78: =IFERROR(K78/I78,"-") -> - | I78: =IFERROR(SUM(I68:I77),"-") -> 0 | K78: =IFERROR(SUM(K68:K77),"-") -> 0 | L78: - | M78: =IFERROR(SUM(M68:M77),"-") -> 0 | N78: - | O78: =IFERROR(SUM(O68:O77),"-") -> 0 | P78: =IFERROR(O78*1.22,"-") -> 0 | Q78: 0 | S78: =IFERROR(SUM(S68:S77),"-") -> 0 | T78: - | U78: - | V78: =IFERROR(P78/S78*1000,"-") -> - | W78: =IFERROR(P78/U78*1000,"-") -> - | X78: - | Y78: - | AA78: =IFERROR(AB78/S78,"-") -> - | AB78: =IFERROR(SUM(AB68:AB77),"-") -> 0 | AC78: =IFERROR(P78/AB78,"-") -> - | AE78: =IFERROR(AF78/AB78,"-") -> - | AF78: =IFERROR(SUM(AF68:AF77),"-") -> 0 | AG78: =IFERROR(P78/AF78,"-") -> - | AI78: =IFERROR(AJ78/AB78,"-") -> - | AJ78: 0 | AK78: =IFERROR(L78/AJ78,"-") -> - | AM78: =IFERROR(P78/AO78,"-") -> - | AN78: =IFERROR(AO78/AF78,"-") -> - | AO78: =IFERROR(SUM(AO68:AO77),"-") -> 0
B80: Рекламная система | C80: Рекламный формат, размер, вид размещения | D80: Таргетинги | F80: Период | G80: Единица измерения стоимости | H80: Цена за единицу (без НДС) | I80: Кол-во единиц | K80: Стоимость (без НДС) | L80: СК, % | M80: Стоимость с учетом СК (без НДС) | N80: АК, % | O80: Итоговая стоимость (без НДС) | P80: Итоговая стоимость (с НДС) | Q80: Доля рекламного бюджета, % | S80: Показы | T80: Частота (весь срок) | U80: Охват | V80: CPM (с НДС) | W80: CPT (с НДС) | X80: Доступная емкость аудитории | Y80: SOV, % | AA80: CTR, % | AB80: Клики | AC80: CPC (с НДС) | AE80: CR, % | AF80: Конверсии | AG80: CPA (с НДС) | AI80: CR(I), % | AJ80: Установки | AK80: CPI | AM80: ДРР, % | AN80: Средний чек | AO80: Доход
F81: 01.07.2026 - 31.07.2026 | G81: CPC | I81: =IFERROR(S81*AA81,"-") -> 0 | K81: =IFERROR((H81*I81),"-") -> 0 | M81: =IFERROR(K81*(1-L81),"-") -> 0 | O81: =IFERROR(M81*(1+N81),"-") -> 0 | P81: =IFERROR(O81*1.22,"-") -> 0 | Q81: =IFERROR(P81/$P$13,"-") -> - | U81: - | V81: =IFERROR(P81/S81*1000,"-") -> - | W81: =IFERROR(P81/U81*1000,"-") -> - | Y81: =IFERROR(U81/X81,"-") -> - | AB81: =IFERROR(ROUNDDOWN(S81*AA81,0),"-") -> 0 | AC81: =IFERROR(P81/AB81,"-") -> - | AF81: =IF(G81="CPI",AJ81*AE81,IFERROR(ROUNDDOWN(AB81*AE81,0),"-")) -> 0 | AG81: =IFERROR(P81/AF81,"-") -> - | AJ81: =IF(G81="CPI",I81,0) -> 0 | AK81: =IFERROR(P81/AJ81,"-") -> - | AM81: =IFERROR(P81/AO81,"-") -> - | AO81: =AN81*AF81 -> 0
F82: 01.07.2026 - 31.07.2026 | G82: CPC | I82: =IFERROR(S82*AA82,"-") -> 0 | K82: =IFERROR((H82*I82),"-") -> 0 | M82: =IFERROR(K82*(1-L82),"-") -> 0 | O82: =IFERROR(M82*(1+N82),"-") -> 0 | P82: =IFERROR(O82*1.22,"-") -> 0 | Q82: =IFERROR(P82/$P$13,"-") -> - | U82: - | V82: =IFERROR(P82/S82*1000,"-") -> - | W82: =IFERROR(P82/U82*1000,"-") -> - | Y82: =IFERROR(U82/X82,"-") -> - | AB82: =IFERROR(ROUNDDOWN(S82*AA82,0),"-") -> 0 | AC82: =IFERROR(P82/AB82,"-") -> - | AF82: =IF(G82="CPI",AJ82*AE82,IFERROR(ROUNDDOWN(AB82*AE82,0),"-")) -> 0 | AG82: =IFERROR(P82/AF82,"-") -> - | AJ82: =IF(G82="CPI",I82,0) -> 0 | AK82: =IFERROR(P82/AJ82,"-") -> - | AM82: =IFERROR(P82/AO82,"-") -> - | AO82: =AN82*AF82 -> 0
F83: 01.07.2026 - 31.07.2026 | G83: CPC | I83: =IFERROR(S83*AA83,"-") -> 0 | K83: =IFERROR((H83*I83),"-") -> 0 | M83: =IFERROR(K83*(1-L83),"-") -> 0 | O83: =IFERROR(M83*(1+N83),"-") -> 0 | P83: =IFERROR(O83*1.22,"-") -> 0 | Q83: =IFERROR(P83/$P$13,"-") -> - | U83: - | V83: =IFERROR(P83/S83*1000,"-") -> - | W83: =IFERROR(P83/U83*1000,"-") -> - | Y83: =IFERROR(U83/X83,"-") -> - | AB83: =IFERROR(ROUNDDOWN(S83*AA83,0),"-") -> 0 | AC83: =IFERROR(P83/AB83,"-") -> - | AF83: =IF(G83="CPI",AJ83*AE83,IFERROR(ROUNDDOWN(AB83*AE83,0),"-")) -> 0 | AG83: =IFERROR(P83/AF83,"-") -> - | AJ83: =IF(G83="CPI",I83,0) -> 0 | AK83: =IFERROR(P83/AJ83,"-") -> - | AM83: =IFERROR(P83/AO83,"-") -> - | AO83: =AN83*AF83 -> 0
F84: 01.07.2026 - 31.07.2026 | G84: CPC | I84: =IFERROR(S84*AA84,"-") -> 0 | K84: =IFERROR((H84*I84),"-") -> 0 | M84: =IFERROR(K84*(1-L84),"-") -> 0 | O84: =IFERROR(M84*(1+N84),"-") -> 0 | P84: =IFERROR(O84*1.22,"-") -> 0 | Q84: =IFERROR(P84/$P$13,"-") -> - | U84: - | V84: =IFERROR(P84/S84*1000,"-") -> - | W84: =IFERROR(P84/U84*1000,"-") -> - | Y84: =IFERROR(U84/X84,"-") -> - | AB84: =IFERROR(ROUNDDOWN(S84*AA84,0),"-") -> 0 | AC84: =IFERROR(P84/AB84,"-") -> - | AF84: =IF(G84="CPI",AJ84*AE84,IFERROR(ROUNDDOWN(AB84*AE84,0),"-")) -> 0 | AG84: =IFERROR(P84/AF84,"-") -> - | AJ84: =IF(G84="CPI",I84,0) -> 0 | AK84: =IFERROR(P84/AJ84,"-") -> - | AM84: =IFERROR(P84/AO84,"-") -> - | AO84: =AN84*AF84 -> 0
F85: 01.07.2026 - 31.07.2026 | G85: CPC | I85: =IFERROR(S85*AA85,"-") -> 0 | K85: =IFERROR((H85*I85),"-") -> 0 | M85: =IFERROR(K85*(1-L85),"-") -> 0 | O85: =IFERROR(M85*(1+N85),"-") -> 0 | P85: =IFERROR(O85*1.22,"-") -> 0 | Q85: =IFERROR(P85/$P$13,"-") -> - | U85: - | V85: =IFERROR(P85/S85*1000,"-") -> - | W85: =IFERROR(P85/U85*1000,"-") -> - | Y85: =IFERROR(U85/X85,"-") -> - | AB85: =IFERROR(ROUNDDOWN(S85*AA85,0),"-") -> 0 | AC85: =IFERROR(P85/AB85,"-") -> - | AF85: =IF(G85="CPI",AJ85*AE85,IFERROR(ROUNDDOWN(AB85*AE85,0),"-")) -> 0 | AG85: =IFERROR(P85/AF85,"-") -> - | AJ85: =IF(G85="CPI",I85,0) -> 0 | AK85: =IFERROR(P85/AJ85,"-") -> - | AM85: =IFERROR(P85/AO85,"-") -> - | AO85: =AN85*AF85 -> 0
F86: 01.07.2026 - 31.07.2026 | G86: CPC | I86: =IFERROR(S86*AA86,"-") -> 0 | K86: =IFERROR((H86*I86),"-") -> 0 | M86: =IFERROR(K86*(1-L86),"-") -> 0 | O86: =IFERROR(M86*(1+N86),"-") -> 0 | P86: =IFERROR(O86*1.22,"-") -> 0 | Q86: =IFERROR(P86/$P$13,"-") -> - | U86: - | V86: =IFERROR(P86/S86*1000,"-") -> - | W86: =IFERROR(P86/U86*1000,"-") -> - | Y86: =IFERROR(U86/X86,"-") -> - | AB86: =IFERROR(ROUNDDOWN(S86*AA86,0),"-") -> 0 | AC86: =IFERROR(P86/AB86,"-") -> - | AF86: =IF(G86="CPI",AJ86*AE86,IFERROR(ROUNDDOWN(AB86*AE86,0),"-")) -> 0 | AG86: =IFERROR(P86/AF86,"-") -> - | AJ86: =IF(G86="CPI",I86,0) -> 0 | AK86: =IFERROR(P86/AJ86,"-") -> - | AM86: =IFERROR(P86/AO86,"-") -> - | AO86: =AN86*AF86 -> 0
F87: 01.07.2026 - 31.07.2026 | G87: CPC | I87: =IFERROR(S87*AA87,"-") -> 0 | K87: =IFERROR((H87*I87),"-") -> 0 | M87: =IFERROR(K87*(1-L87),"-") -> 0 | O87: =IFERROR(M87*(1+N87),"-") -> 0 | P87: =IFERROR(O87*1.22,"-") -> 0 | Q87: =IFERROR(P87/$P$13,"-") -> - | U87: - | V87: =IFERROR(P87/S87*1000,"-") -> - | W87: =IFERROR(P87/U87*1000,"-") -> - | Y87: =IFERROR(U87/X87,"-") -> - | AB87: =IFERROR(ROUNDDOWN(S87*AA87,0),"-") -> 0 | AC87: =IFERROR(P87/AB87,"-") -> - | AF87: =IF(G87="CPI",AJ87*AE87,IFERROR(ROUNDDOWN(AB87*AE87,0),"-")) -> 0 | AG87: =IFERROR(P87/AF87,"-") -> - | AJ87: =IF(G87="CPI",I87,0) -> 0 | AK87: =IFERROR(P87/AJ87,"-") -> - | AM87: =IFERROR(P87/AO87,"-") -> - | AO87: =AN87*AF87 -> 0
F88: 01.07.2026 - 31.07.2026 | G88: CPC | I88: =IFERROR(S88*AA88,"-") -> 0 | K88: =IFERROR((H88*I88),"-") -> 0 | M88: =IFERROR(K88*(1-L88),"-") -> 0 | O88: =IFERROR(M88*(1+N88),"-") -> 0 | P88: =IFERROR(O88*1.22,"-") -> 0 | Q88: =IFERROR(P88/$P$13,"-") -> - | U88: - | V88: =IFERROR(P88/S88*1000,"-") -> - | W88: =IFERROR(P88/U88*1000,"-") -> - | Y88: =IFERROR(U88/X88,"-") -> - | AB88: =IFERROR(ROUNDDOWN(S88*AA88,0),"-") -> 0 | AC88: =IFERROR(P88/AB88,"-") -> - | AF88: =IF(G88="CPI",AJ88*AE88,IFERROR(ROUNDDOWN(AB88*AE88,0),"-")) -> 0 | AG88: =IFERROR(P88/AF88,"-") -> - | AJ88: =IF(G88="CPI",I88,0) -> 0 | AK88: =IFERROR(P88/AJ88,"-") -> - | AM88: =IFERROR(P88/AO88,"-") -> - | AO88: =AN88*AF88 -> 0
F89: 01.07.2026 - 31.07.2026 | G89: CPC | I89: =IFERROR(S89*AA89,"-") -> 0 | K89: =IFERROR((H89*I89),"-") -> 0 | M89: =IFERROR(K89*(1-L89),"-") -> 0 | O89: =IFERROR(M89*(1+N89),"-") -> 0 | P89: =IFERROR(O89*1.22,"-") -> 0 | Q89: =IFERROR(P89/$P$13,"-") -> - | U89: - | V89: =IFERROR(P89/S89*1000,"-") -> - | W89: =IFERROR(P89/U89*1000,"-") -> - | Y89: =IFERROR(U89/X89,"-") -> - | AB89: =IFERROR(ROUNDDOWN(S89*AA89,0),"-") -> 0 | AC89: =IFERROR(P89/AB89,"-") -> - | AF89: =IF(G89="CPI",AJ89*AE89,IFERROR(ROUNDDOWN(AB89*AE89,0),"-")) -> 0 | AG89: =IFERROR(P89/AF89,"-") -> - | AJ89: =IF(G89="CPI",I89,0) -> 0 | AK89: =IFERROR(P89/AJ89,"-") -> - | AM89: =IFERROR(P89/AO89,"-") -> - | AO89: =AN89*AF89 -> 0
F90: 01.07.2026 - 31.07.2026 | G90: CPC | I90: =IFERROR(S90*AA90,"-") -> 0 | K90: =IFERROR((H90*I90),"-") -> 0 | M90: =IFERROR(K90*(1-L90),"-") -> 0 | O90: =IFERROR(M90*(1+N90),"-") -> 0 | P90: =IFERROR(O90*1.22,"-") -> 0 | Q90: =IFERROR(P90/$P$13,"-") -> - | U90: - | V90: =IFERROR(P90/S90*1000,"-") -> - | W90: =IFERROR(P90/U90*1000,"-") -> - | Y90: =IFERROR(U90/X90,"-") -> - | AB90: =IFERROR(ROUNDDOWN(S90*AA90,0),"-") -> 0 | AC90: =IFERROR(P90/AB90,"-") -> - | AF90: =IF(G90="CPI",AJ90*AE90,IFERROR(ROUNDDOWN(AB90*AE90,0),"-")) -> 0 | AG90: =IFERROR(P90/AF90,"-") -> - | AJ90: =IF(G90="CPI",I90,0) -> 0 | AK90: =IFERROR(P90/AJ90,"-") -> - | AM90: =IFERROR(P90/AO90,"-") -> - | AO90: =AN90*AF90 -> 0
B91: Итого | C91: - | D91: - | F91: - | G91: - | H91: =IFERROR(K91/I91,"-") -> - | I91: =IFERROR(SUM(I81:I90),"-") -> 0 | K91: =IFERROR(SUM(K81:K90),"-") -> 0 | L91: - | M91: =IFERROR(SUM(M81:M90),"-") -> 0 | N91: - | O91: =IFERROR(SUM(O81:O90),"-") -> 0 | P91: =IFERROR(O91*1.22,"-") -> 0 | Q91: 0 | S91: =IFERROR(SUM(S81:S90),"-") -> 0 | T91: - | U91: - | V91: =IFERROR(P91/S91*1000,"-") -> - | W91: =IFERROR(P91/U91*1000,"-") -> - | X91: - | Y91: - | AA91: =IFERROR(AB91/S91,"-") -> - | AB91: =IFERROR(SUM(AB81:AB90),"-") -> 0 | AC91: =IFERROR(P91/AB91,"-") -> - | AE91: =IFERROR(AF91/AB91,"-") -> - | AF91: =IFERROR(SUM(AF81:AF90),"-") -> 0 | AG91: =IFERROR(P91/AF91,"-") -> - | AI91: =IFERROR(AJ91/AB91,"-") -> - | AJ91: 0 | AK91: =IFERROR(L91/AJ91,"-") -> - | AM91: =IFERROR(P91/AO91,"-") -> - | AN91: =IFERROR(AO91/AF91,"-") -> - | AO91: =IFERROR(SUM(AO81:AO90),"-") -> 0
B93: Рекламная система | C93: Рекламный формат, размер, вид размещения | D93: Таргетинги | F93: Период | G93: Единица измерения стоимости | H93: Цена за единицу (без НДС) | I93: Кол-во единиц | K93: Стоимость (без НДС) | L93: СК, % | M93: Стоимость с учетом СК (без НДС) | N93: АК, % | O93: Итоговая стоимость (без НДС) | P93: Итоговая стоимость (с НДС) | Q93: Доля рекламного бюджета, % | S93: Показы | T93: Частота (весь срок) | U93: Охват | V93: CPM (с НДС) | W93: CPT (с НДС) | X93: Доступная емкость аудитории | Y93: SOV, % | AA93: CTR, % | AB93: Клики | AC93: CPC (с НДС) | AE93: CR, % | AF93: Конверсии | AG93: CPA (с НДС) | AI93: CR(I), % | AJ93: Установки | AK93: CPI | AM93: ДРР, % | AN93: Средний чек | AO93: Доход
F94: 01.08.2026 - 31.08.2026 | G94: CPC | I94: =IFERROR(S94*AA94,"-") -> 0 | K94: =IFERROR((H94*I94),"-") -> 0 | M94: =IFERROR(K94*(1-L94),"-") -> 0 | O94: =IFERROR(M94*(1+N94),"-") -> 0 | P94: =IFERROR(O94*1.22,"-") -> 0 | Q94: =IFERROR(P94/$P$13,"-") -> - | U94: - | V94: =IFERROR(P94/S94*1000,"-") -> - | W94: =IFERROR(P94/U94*1000,"-") -> - | Y94: =IFERROR(U94/X94,"-") -> - | AB94: =IFERROR(ROUNDDOWN(S94*AA94,0),"-") -> 0 | AC94: =IFERROR(P94/AB94,"-") -> - | AF94: =IF(G94="CPI",AJ94*AE94,IFERROR(ROUNDDOWN(AB94*AE94,0),"-")) -> 0 | AG94: =IFERROR(P94/AF94,"-") -> - | AJ94: =IF(G94="CPI",I94,0) -> 0 | AK94: =IFERROR(P94/AJ94,"-") -> - | AM94: =IFERROR(P94/AO94,"-") -> - | AO94: =AN94*AF94 -> 0
F95: 01.08.2026 - 31.08.2026 | G95: CPC | I95: =IFERROR(S95*AA95,"-") -> 0 | K95: =IFERROR((H95*I95),"-") -> 0 | M95: =IFERROR(K95*(1-L95),"-") -> 0 | O95: =IFERROR(M95*(1+N95),"-") -> 0 | P95: =IFERROR(O95*1.22,"-") -> 0 | Q95: =IFERROR(P95/$P$13,"-") -> - | U95: - | V95: =IFERROR(P95/S95*1000,"-") -> - | W95: =IFERROR(P95/U95*1000,"-") -> - | Y95: =IFERROR(U95/X95,"-") -> - | AB95: =IFERROR(ROUNDDOWN(S95*AA95,0),"-") -> 0 | AC95: =IFERROR(P95/AB95,"-") -> - | AF95: =IF(G95="CPI",AJ95*AE95,IFERROR(ROUNDDOWN(AB95*AE95,0),"-")) -> 0 | AG95: =IFERROR(P95/AF95,"-") -> - | AJ95: =IF(G95="CPI",I95,0) -> 0 | AK95: =IFERROR(P95/AJ95,"-") -> - | AM95: =IFERROR(P95/AO95,"-") -> - | AO95: =AN95*AF95 -> 0
F96: 01.08.2026 - 31.08.2026 | G96: CPC | I96: =IFERROR(S96*AA96,"-") -> 0 | K96: =IFERROR((H96*I96),"-") -> 0 | M96: =IFERROR(K96*(1-L96),"-") -> 0 | O96: =IFERROR(M96*(1+N96),"-") -> 0 | P96: =IFERROR(O96*1.22,"-") -> 0 | Q96: =IFERROR(P96/$P$13,"-") -> - | U96: - | V96: =IFERROR(P96/S96*1000,"-") -> - | W96: =IFERROR(P96/U96*1000,"-") -> - | Y96: =IFERROR(U96/X96,"-") -> - | AB96: =IFERROR(ROUNDDOWN(S96*AA96,0),"-") -> 0 | AC96: =IFERROR(P96/AB96,"-") -> - | AF96: =IF(G96="CPI",AJ96*AE96,IFERROR(ROUNDDOWN(AB96*AE96,0),"-")) -> 0 | AG96: =IFERROR(P96/AF96,"-") -> - | AJ96: =IF(G96="CPI",I96,0) -> 0 | AK96: =IFERROR(P96/AJ96,"-") -> - | AM96: =IFERROR(P96/AO96,"-") -> - | AO96: =AN96*AF96 -> 0
F97: 01.08.2026 - 31.08.2026 | G97: CPC | I97: =IFERROR(S97*AA97,"-") -> 0 | K97: =IFERROR((H97*I97),"-") -> 0 | M97: =IFERROR(K97*(1-L97),"-") -> 0 | O97: =IFERROR(M97*(1+N97),"-") -> 0 | P97: =IFERROR(O97*1.22,"-") -> 0 | Q97: =IFERROR(P97/$P$13,"-") -> - | U97: - | V97: =IFERROR(P97/S97*1000,"-") -> - | W97: =IFERROR(P97/U97*1000,"-") -> - | Y97: =IFERROR(U97/X97,"-") -> - | AB97: =IFERROR(ROUNDDOWN(S97*AA97,0),"-") -> 0 | AC97: =IFERROR(P97/AB97,"-") -> - | AF97: =IF(G97="CPI",AJ97*AE97,IFERROR(ROUNDDOWN(AB97*AE97,0),"-")) -> 0 | AG97: =IFERROR(P97/AF97,"-") -> - | AJ97: =IF(G97="CPI",I97,0) -> 0 | AK97: =IFERROR(P97/AJ97,"-") -> - | AM97: =IFERROR(P97/AO97,"-") -> - | AO97: =AN97*AF97 -> 0
F98: 01.08.2026 - 31.08.2026 | G98: CPC | I98: =IFERROR(S98*AA98,"-") -> 0 | K98: =IFERROR((H98*I98),"-") -> 0 | M98: =IFERROR(K98*(1-L98),"-") -> 0 | O98: =IFERROR(M98*(1+N98),"-") -> 0 | P98: =IFERROR(O98*1.22,"-") -> 0 | Q98: =IFERROR(P98/$P$13,"-") -> - | U98: - | V98: =IFERROR(P98/S98*1000,"-") -> - | W98: =IFERROR(P98/U98*1000,"-") -> - | Y98: =IFERROR(U98/X98,"-") -> - | AB98: =IFERROR(ROUNDDOWN(S98*AA98,0),"-") -> 0 | AC98: =IFERROR(P98/AB98,"-") -> - | AF98: =IF(G98="CPI",AJ98*AE98,IFERROR(ROUNDDOWN(AB98*AE98,0),"-")) -> 0 | AG98: =IFERROR(P98/AF98,"-") -> - | AJ98: =IF(G98="CPI",I98,0) -> 0 | AK98: =IFERROR(P98/AJ98,"-") -> - | AM98: =IFERROR(P98/AO98,"-") -> - | AO98: =AN98*AF98 -> 0
F99: 01.08.2026 - 31.08.2026 | G99: CPC | I99: =IFERROR(S99*AA99,"-") -> 0 | K99: =IFERROR((H99*I99),"-") -> 0 | M99: =IFERROR(K99*(1-L99),"-") -> 0 | O99: =IFERROR(M99*(1+N99),"-") -> 0 | P99: =IFERROR(O99*1.22,"-") -> 0 | Q99: =IFERROR(P99/$P$13,"-") -> - | U99: - | V99: =IFERROR(P99/S99*1000,"-") -> - | W99: =IFERROR(P99/U99*1000,"-") -> - | Y99: =IFERROR(U99/X99,"-") -> - | AB99: =IFERROR(ROUNDDOWN(S99*AA99,0),"-") -> 0 | AC99: =IFERROR(P99/AB99,"-") -> - | AF99: =IF(G99="CPI",AJ99*AE99,IFERROR(ROUNDDOWN(AB99*AE99,0),"-")) -> 0 | AG99: =IFERROR(P99/AF99,"-") -> - | AJ99: =IF(G99="CPI",I99,0) -> 0 | AK99: =IFERROR(P99/AJ99,"-") -> - | AM99: =IFERROR(P99/AO99,"-") -> - | AO99: =AN99*AF99 -> 0
F100: 01.08.2026 - 31.08.2026 | G100: CPC | I100: =IFERROR(S100*AA100,"-") -> 0 | K100: =IFERROR((H100*I100),"-") -> 0 | M100: =IFERROR(K100*(1-L100),"-") -> 0 | O100: =IFERROR(M100*(1+N100),"-") -> 0 | P100: =IFERROR(O100*1.22,"-") -> 0 | Q100: =IFERROR(P100/$P$13,"-") -> - | U100: - | V100: =IFERROR(P100/S100*1000,"-") -> - | W100: =IFERROR(P100/U100*1000,"-") -> - | Y100: =IFERROR(U100/X100,"-") -> - | AB100: =IFERROR(ROUNDDOWN(S100*AA100,0),"-") -> 0 | AC100: =IFERROR(P100/AB100,"-") -> - | AF100: =IF(G100="CPI",AJ100*AE100,IFERROR(ROUNDDOWN(AB100*AE100,0),"-")) -> 0 | AG100: =IFERROR(P100/AF100,"-") -> - | AJ100: =IF(G100="CPI",I100,0) -> 0 | AK100: =IFERROR(P100/AJ100,"-") -> - | AM100: =IFERROR(P100/AO100,"-") -> - | AO100: =AN100*AF100 -> 0
F101: 01.08.2026 - 31.08.2026 | G101: CPC | I101: =IFERROR(S101*AA101,"-") -> 0 | K101: =IFERROR((H101*I101),"-") -> 0 | M101: =IFERROR(K101*(1-L101),"-") -> 0 | O101: =IFERROR(M101*(1+N101),"-") -> 0 | P101: =IFERROR(O101*1.22,"-") -> 0 | Q101: =IFERROR(P101/$P$13,"-") -> - | U101: - | V101: =IFERROR(P101/S101*1000,"-") -> - | W101: =IFERROR(P101/U101*1000,"-") -> - | Y101: =IFERROR(U101/X101,"-") -> - | AB101: =IFERROR(ROUNDDOWN(S101*AA101,0),"-") -> 0 | AC101: =IFERROR(P101/AB101,"-") -> - | AF101: =IF(G101="CPI",AJ101*AE101,IFERROR(ROUNDDOWN(AB101*AE101,0),"-")) -> 0 | AG101: =IFERROR(P101/AF101,"-") -> - | AJ101: =IF(G101="CPI",I101,0) -> 0 | AK101: =IFERROR(P101/AJ101,"-") -> - | AM101: =IFERROR(P101/AO101,"-") -> - | AO101: =AN101*AF101 -> 0
F102: 01.08.2026 - 31.08.2026 | G102: CPC | I102: =IFERROR(S102*AA102,"-") -> 0 | K102: =IFERROR((H102*I102),"-") -> 0 | M102: =IFERROR(K102*(1-L102),"-") -> 0 | O102: =IFERROR(M102*(1+N102),"-") -> 0 | P102: =IFERROR(O102*1.22,"-") -> 0 | Q102: =IFERROR(P102/$P$13,"-") -> - | U102: - | V102: =IFERROR(P102/S102*1000,"-") -> - | W102: =IFERROR(P102/U102*1000,"-") -> - | Y102: =IFERROR(U102/X102,"-") -> - | AB102: =IFERROR(ROUNDDOWN(S102*AA102,0),"-") -> 0 | AC102: =IFERROR(P102/AB102,"-") -> - | AF102: =IF(G102="CPI",AJ102*AE102,IFERROR(ROUNDDOWN(AB102*AE102,0),"-")) -> 0 | AG102: =IFERROR(P102/AF102,"-") -> - | AJ102: =IF(G102="CPI",I102,0) -> 0 | AK102: =IFERROR(P102/AJ102,"-") -> - | AM102: =IFERROR(P102/AO102,"-") -> - | AO102: =AN102*AF102 -> 0
F103: 01.08.2026 - 31.08.2026 | G103: CPC | I103: =IFERROR(S103*AA103,"-") -> 0 | K103: =IFERROR((H103*I103),"-") -> 0 | M103: =IFERROR(K103*(1-L103),"-") -> 0 | O103: =IFERROR(M103*(1+N103),"-") -> 0 | P103: =IFERROR(O103*1.22,"-") -> 0 | Q103: =IFERROR(P103/$P$13,"-") -> - | U103: - | V103: =IFERROR(P103/S103*1000,"-") -> - | W103: =IFERROR(P103/U103*1000,"-") -> - | Y103: =IFERROR(U103/X103,"-") -> - | AB103: =IFERROR(ROUNDDOWN(S103*AA103,0),"-") -> 0 | AC103: =IFERROR(P103/AB103,"-") -> - | AF103: =IF(G103="CPI",AJ103*AE103,IFERROR(ROUNDDOWN(AB103*AE103,0),"-")) -> 0 | AG103: =IFERROR(P103/AF103,"-") -> - | AJ103: =IF(G103="CPI",I103,0) -> 0 | AK103: =IFERROR(P103/AJ103,"-") -> - | AM103: =IFERROR(P103/AO103,"-") -> - | AO103: =AN103*AF103 -> 0
B104: Итого | C104: - | D104: - | F104: - | G104: - | H104: =IFERROR(K104/I104,"-") -> - | I104: =IFERROR(SUM(I94:I103),"-") -> 0 | K104: =IFERROR(SUM(K94:K103),"-") -> 0 | L104: - | M104: =IFERROR(SUM(M94:M103),"-") -> 0 | N104: - | O104: =IFERROR(SUM(O94:O103),"-") -> 0 | P104: =IFERROR(O104*1.22,"-") -> 0 | Q104: 0 | S104: =IFERROR(SUM(S94:S103),"-") -> 0 | T104: - | U104: - | V104: =IFERROR(P104/S104*1000,"-") -> - | W104: =IFERROR(P104/U104*1000,"-") -> - | X104: - | Y104: - | AA104: =IFERROR(AB104/S104,"-") -> - | AB104: =IFERROR(SUM(AB94:AB103),"-") -> 0 | AC104: =IFERROR(P104/AB104,"-") -> - | AE104: =IFERROR(AF104/AB104,"-") -> - | AF104: =IFERROR(SUM(AF94:AF103),"-") -> 0 | AG104: =IFERROR(P104/AF104,"-") -> - | AI104: =IFERROR(AJ104/AB104,"-") -> - | AJ104: 0 | AK104: =IFERROR(L104/AJ104,"-") -> - | AM104: =IFERROR(P104/AO104,"-") -> - | AN104: =IFERROR(AO104/AF104,"-") -> - | AO104: =IFERROR(SUM(AO94:AO103),"-") -> 0
B106: Рекламная система | C106: Рекламный формат, размер, вид размещения | D106: Таргетинги | F106: Период | G106: Единица измерения стоимости | H106: Цена за единицу (без НДС) | I106: Кол-во единиц | K106: Стоимость (без НДС) | L106: СК, % | M106: Стоимость с учетом СК (без НДС) | N106: АК, % | O106: Итоговая стоимость (без НДС) | P106: Итоговая стоимость (с НДС) | Q106: Доля рекламного бюджета, % | S106: Показы | T106: Частота (весь срок) | U106: Охват | V106: CPM (с НДС) | W106: CPT (с НДС) | X106: Доступная емкость аудитории | Y106: SOV, % | AA106: CTR, % | AB106: Клики | AC106: CPC (с НДС) | AE106: CR, % | AF106: Конверсии | AG106: CPA (с НДС) | AI106: CR(I), % | AJ106: Установки | AK106: CPI | AM106: ДРР, % | AN106: Средний чек | AO106: Доход
F107: 01.09.2026 - 30.09.2026 | G107: CPC | I107: =IFERROR(S107*AA107,"-") -> 0 | K107: =IFERROR((H107*I107),"-") -> 0 | M107: =IFERROR(K107*(1-L107),"-") -> 0 | O107: =IFERROR(M107*(1+N107),"-") -> 0 | P107: =IFERROR(O107*1.22,"-") -> 0 | Q107: =IFERROR(P107/$P$13,"-") -> - | U107: - | V107: =IFERROR(P107/S107*1000,"-") -> - | W107: =IFERROR(P107/U107*1000,"-") -> - | Y107: =IFERROR(U107/X107,"-") -> - | AB107: =IFERROR(ROUNDDOWN(S107*AA107,0),"-") -> 0 | AC107: =IFERROR(P107/AB107,"-") -> - | AF107: =IF(G107="CPI",AJ107*AE107,IFERROR(ROUNDDOWN(AB107*AE107,0),"-")) -> 0 | AG107: =IFERROR(P107/AF107,"-") -> - | AJ107: =IF(G107="CPI",I107,0) -> 0 | AK107: =IFERROR(P107/AJ107,"-") -> - | AM107: =IFERROR(P107/AO107,"-") -> - | AO107: =AN107*AF107 -> 0
F108: 01.09.2026 - 30.09.2026 | G108: CPC | I108: =IFERROR(S108*AA108,"-") -> 0 | K108: =IFERROR((H108*I108),"-") -> 0 | M108: =IFERROR(K108*(1-L108),"-") -> 0 | O108: =IFERROR(M108*(1+N108),"-") -> 0 | P108: =IFERROR(O108*1.22,"-") -> 0 | Q108: =IFERROR(P108/$P$13,"-") -> - | U108: - | V108: =IFERROR(P108/S108*1000,"-") -> - | W108: =IFERROR(P108/U108*1000,"-") -> - | Y108: =IFERROR(U108/X108,"-") -> - | AB108: =IFERROR(ROUNDDOWN(S108*AA108,0),"-") -> 0 | AC108: =IFERROR(P108/AB108,"-") -> - | AF108: =IF(G108="CPI",AJ108*AE108,IFERROR(ROUNDDOWN(AB108*AE108,0),"-")) -> 0 | AG108: =IFERROR(P108/AF108,"-") -> - | AJ108: =IF(G108="CPI",I108,0) -> 0 | AK108: =IFERROR(P108/AJ108,"-") -> - | AM108: =IFERROR(P108/AO108,"-") -> - | AO108: =AN108*AF108 -> 0
...
