Workbook

Sheet МП_Total
B2: Рекламная система | C2: Рекламный формат, размер, вид размещения | D2: Таргетинги | E2: ГЕО | F2: Январь | G2: Февраль | H2: Март | I2: Апрель | J2: Май | K2: Июнь | L2: Июль | M2: Август | N2: Сентябрь | O2: Октябрь | P2: Ноябрь | Q2: Декабрь | S2: Модель закупки | T2: Цена за единицу (без НДС) | U2: Кол-во единиц закупки | W2: Стоимость (без НДС) | X2: СК, % | Y2: Тотал бюджет, руб. без НДС и АК | Z2: АК, % | AA2: АК, руб. (без НДС) | AB2: Тотал бюджет, руб. без НДС и с учетом АК | AC2: Тотал бюджет руб. с учетом НДС и АК | AD2: НДС руб. | AE2: Доля рекламного бюджета, % | AG2: Кол-во показов | AH2: Частота (весь срок) | AI2: Доля новых клиентов, % | AJ2: Кол-во клиентов | AK2: Кол-во абсолютно новых клиентов (ранее не заказывали) | AL2: Кол-во вернувшихся клиентов (не заказывали более 12 мес) | AM2: Кол-во новых клиентов (абсолютно новые + вернувшиеся) | AN2: Частота заказа | AO2: САС, руб. | AP2: Доступная емкость аудитории | AQ2: SOV, % | AS2: CTR, % | AT2: Клики | AU2: CPC (с НДС) | AW2: CR, % | AX2: Кол-во оформленных заказов | AY2: Стоимость оформл. заказа, руб. с НДС | AZ2: Доля заказов, % | BB2: ROAS офомл. (Доход/Бюджет) | BC2: ДРР от оформл. дохода, % | BD2: Средний чек по оформл. доходу, с НДС | BE2: Оформленный доход, руб. с НДС | BF2: Доля выручки, % | BH2: CR2, % | BI2: Кол-во отгруженных заказов | BJ2: Стоимость отгр. заказа, руб. с НДС | BK2: Доля заказов, % | BM2: ROAS отгр. (Выручка/Бюджет) | BN2: ДРР от выручки, % | BO2: Средний чек по выручке, с НДС | BP2: Выручка (отгруженный доход), руб. с НДС | BQ2: Доля выручки, %
S3: CPC | T3: =IFERROR(W3/U3,"-") -> - | U3: =SUM(МП_Periods!J3,МП_Periods!J118,МП_Periods!J233,МП_Periods!J348,МП_Periods!J464,МП_Periods!J579,МП_Periods!J694,МП_Periods!J809,МП_Periods!J924,МП_Periods!J1039,МП_Periods!J1154,МП_Periods!J1269) -> 0 | W3: =SUM(МП_Periods!L3,МП_Periods!L118,МП_Periods!L233,МП_Periods!L348,МП_Periods!L464,МП_Periods!L579,МП_Periods!L694,МП_Periods!L809,МП_Periods!L924,МП_Periods!L1039,МП_Periods!L1154,МП_Periods!L1269) -> 0 | Y3: =SUM(МП_Periods!N3,МП_Periods!N118,МП_Periods!N233,МП_Periods!N348,МП_Periods!N464,МП_Periods!N579,МП_Periods!N694,МП_Periods!N809,МП_Periods!N924,МП_Periods!N1039,МП_Periods!N1154,МП_Periods!N1269) -> 0 | AA3: =SUM(МП_Periods!P3,МП_Periods!P118,МП_Periods!P233,МП_Periods!P348,МП_Periods!P464,МП_Periods!P579,МП_Periods!P694,МП_Periods!P809,МП_Periods!P924,МП_Periods!P1039,МП_Periods!P1154,МП_Periods!P1269) -> 0 | AB3: =SUM(МП_Periods!Q3,МП_Periods!Q118,МП_Periods!Q233,МП_Periods!Q348,МП_Periods!Q464,МП_Periods!Q579,МП_Periods!Q694,МП_Periods!Q809,МП_Periods!Q924,МП_Periods!Q1039,МП_Periods!Q1154,МП_Periods!Q1269) -> 0 | AC3: =SUM(МП_Periods!R3,МП_Periods!R118,МП_Periods!R233,МП_Periods!R348,МП_Periods!R464,МП_Periods!R579,МП_Periods!R694,МП_Periods!R809,МП_Periods!R924,МП_Periods!R1039,МП_Periods!R1154,МП_Periods!R1269) -> 0 | AD3: =SUM(МП_Periods!S3,МП_Periods!S118,МП_Periods!S233,МП_Periods!S348,МП_Periods!S464,МП_Periods!S579,МП_Periods!S694,МП_Periods!S809,МП_Periods!S924,МП_Periods!S1039,МП_Periods!S1154,МП_Periods!S1269) -> 0 | AE3: =IFERROR(AC3/$AC$115,"-") -> - | AG3: =SUM(МП_Periods!V3,МП_Periods!V118,МП_Periods!V233,МП_Periods!V348,МП_Periods!V464,МП_Periods!V579,МП_Periods!V694,МП_Periods!V809,МП_Periods!V924,МП_Periods!V1039,МП_Periods!V1154,МП_Periods!V1269) -> 0 | AJ3: =SUM(МП_Periods!Y3,МП_Periods!Y118,МП_Periods!Y233,МП_Periods!Y348,МП_Periods!Y464,МП_Periods!Y579,МП_Periods!Y694,МП_Periods!Y809,МП_Periods!Y924,МП_Periods!Y1039,МП_Periods!Y1154,МП_Periods!Y1269) -> 0 | AK3: =SUM(МП_Periods!Z3,МП_Periods!Z118,МП_Periods!Z233,МП_Periods!Z348,МП_Periods!Z464,МП_Periods!Z579,МП_Periods!Z694,МП_Periods!Z809,МП_Periods!Z924,МП_Periods!Z1039,МП_Periods!Z1154,МП_Periods!Z1269) -> 0 | AL3: =SUM(МП_Periods!AA3,МП_Periods!AA118,МП_Periods!AA233,МП_Periods!AA348,МП_Periods!AA464,МП_Periods!AA579,МП_Periods!AA694,МП_Periods!AA809,МП_Periods!AA924,МП_Periods!AA1039,МП_Periods!AA1154,МП_Periods!AA1269) -> 0 | AM3: =SUM(МП_Periods!AB3,МП_Periods!AB118,МП_Periods!AB233,МП_Periods!AB348,МП_Periods!AB464,МП_Periods!AB579,МП_Periods!AB694,МП_Periods!AB809,МП_Periods!AB924,МП_Periods!AB1039,МП_Periods!AB1154,МП_Periods!AB1269) -> 0 | AO3: =IFERROR(AC3/AM3,"-") -> - | AP3: =SUM(МП_Periods!AE3,МП_Periods!AE118,МП_Periods!AE233,МП_Periods!AE348,МП_Periods!AE464,МП_Periods!AE579,МП_Periods!AE694,МП_Periods!AE809,МП_Periods!AE924,МП_Periods!AE1039,МП_Periods!AE1154,МП_Periods!AE1269) -> 0 | AQ3: =IFERROR(#REF!/AP3,"-") -> - | AS3: =IFERROR(U3/AG3,"-") -> - | AT3: =SUM(МП_Periods!AI3,МП_Periods!AI118,МП_Periods!AI233,МП_Periods!AI348,МП_Periods!AI464,МП_Periods!AI579,МП_Periods!AI694,МП_Periods!AI809,МП_Periods!AI924,МП_Periods!AI1039,МП_Periods!AI1154,МП_Periods!AI1269) -> 0 | AU3: =IFERROR(AC3/AT3,"-") -> - | AW3: =IFERROR(AX3/AT3,"-") -> - | AX3: =SUM(МП_Periods!AM3,МП_Periods!AM118,МП_Periods!AM233,МП_Periods!AM348,МП_Periods!AM464,МП_Periods!AM579,МП_Periods!AM694,МП_Periods!AM809,МП_Periods!AM924,МП_Periods!AM1039,МП_Periods!AM1154,МП_Periods!AM1269,) -> 0 | AY3: =IFERROR(AC3/AX3,"-") -> - | AZ3: =IFERROR(AX3/$AX$115,"-") -> - | BB3: =IFERROR(BE3/AC3,"-") -> - | BC3: =IFERROR(AC3/BE3,"-") -> - | BD3: =IFERROR(BE3/AX3,"-") -> - | BE3: =SUM(МП_Periods!AT3,МП_Periods!AT118,МП_Periods!AT233,МП_Periods!AT348,МП_Periods!AT464,МП_Periods!AT579,МП_Periods!AT694,МП_Periods!AT809,МП_Periods!AT924,МП_Periods!AT1039,МП_Periods!AT1154,МП_Periods!AT1269) -> 0 | BF3: =IFERROR(BE3/$BE$115,"-") -> - | BH3: =IFERROR(BI3/AX3,"-") -> - | BI3: =SUM(МП_Periods!AX3,МП_Periods!AX118,МП_Periods!AX233,МП_Periods!AX348,МП_Periods!AX464,МП_Periods!AX579,МП_Periods!AX694,МП_Periods!AX809,МП_Periods!AX924,МП_Periods!AX1039,МП_Periods!AX1154,МП_Periods!AX1269) -> 0 | BJ3: =IFERROR(AC3/BI3,"-") -> - | BK3: =IFERROR(BI3/$AX$115,"-") -> - | BM3: =IFERROR(BP3/AC3,"-") -> - | BN3: =IFERROR(AC3/BP3,"-") -> - | BO3: =IFERROR(BP3/BI3,"-") -> - | BP3: =SUM(МП_Periods!BE3,МП_Periods!BE118,МП_Periods!BE233,МП_Periods!BE348,МП_Periods!BE464,МП_Periods!BE579,МП_Periods!BE694,МП_Periods!BE809,МП_Periods!BE924,МП_Periods!BE1039,МП_Periods!BE1154,МП_Periods!BE1269) -> 0 | BQ3: =IFERROR(BP3/$BP$115,"-") -> -
S4: CPC | T4: =IFERROR(W4/U4,"-") -> - | U4: =SUM(МП_Periods!J4,МП_Periods!J119,МП_Periods!J234,МП_Periods!J349,МП_Periods!J465,МП_Periods!J580,МП_Periods!J695,МП_Periods!J810,МП_Periods!J925,МП_Periods!J1040,МП_Periods!J1155,МП_Periods!J1270) -> 0 | W4: =SUM(МП_Periods!L4,МП_Periods!L119,МП_Periods!L234,МП_Periods!L349,МП_Periods!L465,МП_Periods!L580,МП_Periods!L695,МП_Periods!L810,МП_Periods!L925,МП_Periods!L1040,МП_Periods!L1155,МП_Periods!L1270) -> 0 | Y4: =SUM(МП_Periods!N4,МП_Periods!N119,МП_Periods!N234,МП_Periods!N349,МП_Periods!N465,МП_Periods!N580,МП_Periods!N695,МП_Periods!N810,МП_Periods!N925,МП_Periods!N1040,МП_Periods!N1155,МП_Periods!N1270) -> 0 | AA4: =SUM(МП_Periods!P4,МП_Periods!P119,МП_Periods!P234,МП_Periods!P349,МП_Periods!P465,МП_Periods!P580,МП_Periods!P695,МП_Periods!P810,МП_Periods!P925,МП_Periods!P1040,МП_Periods!P1155,МП_Periods!P1270) -> 0 | AB4: =SUM(МП_Periods!Q4,МП_Periods!Q119,МП_Periods!Q234,МП_Periods!Q349,МП_Periods!Q465,МП_Periods!Q580,МП_Periods!Q695,МП_Periods!Q810,МП_Periods!Q925,МП_Periods!Q1040,МП_Periods!Q1155,МП_Periods!Q1270) -> 0 | AC4: =SUM(МП_Periods!R4,МП_Periods!R119,МП_Periods!R234,МП_Periods!R349,МП_Periods!R465,МП_Periods!R580,МП_Periods!R695,МП_Periods!R810,МП_Periods!R925,МП_Periods!R1040,МП_Periods!R1155,МП_Periods!R1270) -> 0 | AD4: =SUM(МП_Periods!S4,МП_Periods!S119,МП_Periods!S234,МП_Periods!S349,МП_Periods!S465,МП_Periods!S580,МП_Periods!S695,МП_Periods!S810,МП_Periods!S925,МП_Periods!S1040,МП_Periods!S1155,МП_Periods!S1270) -> 0 | AE4: =IFERROR(AC4/$AC$115,"-") -> - | AG4: =SUM(МП_Periods!V4,МП_Periods!V119,МП_Periods!V234,МП_Periods!V349,МП_Periods!V465,МП_Periods!V580,МП_Periods!V695,МП_Periods!V810,МП_Periods!V925,МП_Periods!V1040,МП_Periods!V1155,МП_Periods!V1270) -> 0 | AJ4: =SUM(МП_Periods!Y4,МП_Periods!Y119,МП_Periods!Y234,МП_Periods!Y349,МП_Periods!Y465,МП_Periods!Y580,МП_Periods!Y695,МП_Periods!Y810,МП_Periods!Y925,МП_Periods!Y1040,МП_Periods!Y1155,МП_Periods!Y1270) -> 0 | AK4: =SUM(МП_Periods!Z4,МП_Periods!Z119,МП_Periods!Z234,МП_Periods!Z349,МП_Periods!Z465,МП_Periods!Z580,МП_Periods!Z695,МП_Periods!Z810,МП_Periods!Z925,МП_Periods!Z1040,МП_Periods!Z1155,МП_Periods!Z1270) -> 0 | AL4: =SUM(МП_Periods!AA4,МП_Periods!AA119,МП_Periods!AA234,МП_Periods!AA349,МП_Periods!AA465,МП_Periods!AA580,МП_Periods!AA695,МП_Periods!AA810,МП_Periods!AA925,МП_Periods!AA1040,МП_Periods!AA1155,МП_Periods!AA1270) -> 0 | AM4: =SUM(МП_Periods!AB4,МП_Periods!AB119,МП_Periods!AB234,МП_Periods!AB349,МП_Periods!AB465,МП_Periods!AB580,МП_Periods!AB695,МП_Periods!AB810,МП_Periods!AB925,МП_Periods!AB1040,МП_Periods!AB1155,МП_Periods!AB1270) -> 0 | AO4: =IFERROR(AC4/AM4,"-") -> - | AP4: =SUM(МП_Periods!AE4,МП_Periods!AE119,МП_Periods!AE234,МП_Periods!AE349,МП_Periods!AE465,МП_Periods!AE580,МП_Periods!AE695,МП_Periods!AE810,МП_Periods!AE925,МП_Periods!AE1040,МП_Periods!AE1155,МП_Periods!AE1270) -> 0 | AQ4: =IFERROR(#REF!/AP4,"-") -> - | AS4: =IFERROR(U4/AG4,"-") -> - | AT4: =SUM(МП_Periods!AI4,МП_Periods!AI119,МП_Periods!AI234,МП_Periods!AI349,МП_Periods!AI465,МП_Periods!AI580,МП_Periods!AI695,МП_Periods!AI810,МП_Periods!AI925,МП_Periods!AI1040,МП_Periods!AI1155,МП_Periods!AI1270) -> 0 | AU4: =IFERROR(AC4/AT4,"-") -> - | AW4: =IFERROR(AX4/AT4,"-") -> - | AX4: =SUM(МП_Periods!AM4,МП_Periods!AM119,МП_Periods!AM234,МП_Periods!AM349,МП_Periods!AM465,МП_Periods!AM580,МП_Periods!AM695,МП_Periods!AM810,МП_Periods!AM925,МП_Periods!AM1040,МП_Periods!AM1155,МП_Periods!AM1270,) -> 0 | AY4: =IFERROR(AC4/AX4,"-") -> - | AZ4: =IFERROR(AX4/$AX$115,"-") -> - | BB4: =IFERROR(BE4/AC4,"-") -> - | BC4: =IFERROR(AC4/BE4,"-") -> - | BD4: =IFERROR(BE4/AX4,"-") -> - | BE4: =SUM(МП_Periods!AT4,МП_Periods!AT119,МП_Periods!AT234,МП_Periods!AT349,МП_Periods!AT465,МП_Periods!AT580,МП_Periods!AT695,МП_Periods!AT810,МП_Periods!AT925,МП_Periods!AT1040,МП_Periods!AT1155,МП_Periods!AT1270) -> 0 | BF4: =IFERROR(BE4/$BE$115,"-") -> - | BH4: =IFERROR(BI4/AX4,"-") -> - | BI4: =SUM(МП_Periods!AX4,МП_Periods!AX119,МП_Periods!AX234,МП_Periods!AX349,МП_Periods!AX465,МП_Periods!AX580,МП_Periods!AX695,МП_Periods!AX810,МП_Periods!AX925,МП_Periods!AX1040,МП_Periods!AX1155,МП_Periods!AX1270) -> 0 | BJ4: =IFERROR(AC4/BI4,"-") -> - | BK4: =IFERROR(BI4/$AX$115,"-") -> - | BM4: =IFERROR(BP4/AC4,"-") -> - | BN4: =IFERROR(AC4/BP4,"-") -> - | BO4: =IFERROR(BP4/BI4,"-") -> - | BP4: =SUM(МП_Periods!BE4,МП_Periods!BE119,МП_Periods!BE234,МП_Periods!BE349,МП_Periods!BE465,МП_Periods!BE580,МП_Periods!BE695,МП_Periods!BE810,МП_Periods!BE925,МП_Periods!BE1040,МП_Periods!BE1155,МП_Periods!BE1270) -> 0 | BQ4: =IFERROR(BP4/$BP$115,"-") -> -
S5: CPC | T5: =IFERROR(W5/U5,"-") -> - | U5: =SUM(МП_Periods!J5,МП_Periods!J120,МП_Periods!J235,МП_Periods!J350,МП_Periods!J466,МП_Periods!J581,МП_Periods!J696,МП_Periods!J811,МП_Periods!J926,МП_Periods!J1041,МП_Periods!J1156,МП_Periods!J1271) -> 0 | W5: =SUM(МП_Periods!L5,МП_Periods!L120,МП_Periods!L235,МП_Periods!L350,МП_Periods!L466,МП_Periods!L581,МП_Periods!L696,МП_Periods!L811,МП_Periods!L926,МП_Periods!L1041,МП_Periods!L1156,МП_Periods!L1271) -> 0 | Y5: =SUM(МП_Periods!N5,МП_Periods!N120,МП_Periods!N235,МП_Periods!N350,МП_Periods!N466,МП_Periods!N581,МП_Periods!N696,МП_Periods!N811,МП_Periods!N926,МП_Periods!N1041,МП_Periods!N1156,МП_Periods!N1271) -> 0 | AA5: =SUM(МП_Periods!P5,МП_Periods!P120,МП_Periods!P235,МП_Periods!P350,МП_Periods!P466,МП_Periods!P581,МП_Periods!P696,МП_Periods!P811,МП_Periods!P926,МП_Periods!P1041,МП_Periods!P1156,МП_Periods!P1271) -> 0 | AB5: =SUM(МП_Periods!Q5,МП_Periods!Q120,МП_Periods!Q235,МП_Periods!Q350,МП_Periods!Q466,МП_Periods!Q581,МП_Periods!Q696,МП_Periods!Q811,МП_Periods!Q926,МП_Periods!Q1041,МП_Periods!Q1156,МП_Periods!Q1271) -> 0 | AC5: =SUM(МП_Periods!R5,МП_Periods!R120,МП_Periods!R235,МП_Periods!R350,МП_Periods!R466,МП_Periods!R581,МП_Periods!R696,МП_Periods!R811,МП_Periods!R926,МП_Periods!R1041,МП_Periods!R1156,МП_Periods!R1271) -> 0 | AD5: =SUM(МП_Periods!S5,МП_Periods!S120,МП_Periods!S235,МП_Periods!S350,МП_Periods!S466,МП_Periods!S581,МП_Periods!S696,МП_Periods!S811,МП_Periods!S926,МП_Periods!S1041,МП_Periods!S1156,МП_Periods!S1271) -> 0 | AE5: =IFERROR(AC5/$AC$115,"-") -> - | AG5: =SUM(МП_Periods!V5,МП_Periods!V120,МП_Periods!V235,МП_Periods!V350,МП_Periods!V466,МП_Periods!V581,МП_Periods!V696,МП_Periods!V811,МП_Periods!V926,МП_Periods!V1041,МП_Periods!V1156,МП_Periods!V1271) -> 0 | AJ5: =SUM(МП_Periods!Y5,МП_Periods!Y120,МП_Periods!Y235,МП_Periods!Y350,МП_Periods!Y466,МП_Periods!Y581,МП_Periods!Y696,МП_Periods!Y811,МП_Periods!Y926,МП_Periods!Y1041,МП_Periods!Y1156,МП_Periods!Y1271) -> 0 | AK5: =SUM(МП_Periods!Z5,МП_Periods!Z120,МП_Periods!Z235,МП_Periods!Z350,МП_Periods!Z466,МП_Periods!Z581,МП_Periods!Z696,МП_Periods!Z811,МП_Periods!Z926,МП_Periods!Z1041,МП_Periods!Z1156,МП_Periods!Z1271) -> 0 | AL5: =SUM(МП_Periods!AA5,МП_Periods!AA120,МП_Periods!AA235,МП_Periods!AA350,МП_Periods!AA466,МП_Periods!AA581,МП_Periods!AA696,МП_Periods!AA811,МП_Periods!AA926,МП_Periods!AA1041,МП_Periods!AA1156,МП_Periods!AA1271) -> 0 | AM5: =SUM(МП_Periods!AB5,МП_Periods!AB120,МП_Periods!AB235,МП_Periods!AB350,МП_Periods!AB466,МП_Periods!AB581,МП_Periods!AB696,МП_Periods!AB811,МП_Periods!AB926,МП_Periods!AB1041,МП_Periods!AB1156,МП_Periods!AB1271) -> 0 | AO5: =IFERROR(AC5/AM5,"-") -> - | AP5: =SUM(МП_Periods!AE5,МП_Periods!AE120,МП_Periods!AE235,МП_Periods!AE350,МП_Periods!AE466,МП_Periods!AE581,МП_Periods!AE696,МП_Periods!AE811,МП_Periods!AE926,МП_Periods!AE1041,МП_Periods!AE1156,МП_Periods!AE1271) -> 0 | AQ5: =IFERROR(#REF!/AP5,"-") -> - | AS5: =IFERROR(U5/AG5,"-") -> - | AT5: =SUM(МП_Periods!AI5,МП_Periods!AI120,МП_Periods!AI235,МП_Periods!AI350,МП_Periods!AI466,МП_Periods!AI581,МП_Periods!AI696,МП_Periods!AI811,МП_Periods!AI926,МП_Periods!AI1041,МП_Periods!AI1156,МП_Periods!AI1271) -> 0 | AU5: =IFERROR(AC5/AT5,"-") -> - | AW5: =IFERROR(AX5/AT5,"-") -> - | AX5: =SUM(МП_Periods!AM5,МП_Periods!AM120,МП_Periods!AM235,МП_Periods!AM350,МП_Periods!AM466,МП_Periods!AM581,МП_Periods!AM696,МП_Periods!AM811,МП_Periods!AM926,МП_Periods!AM1041,МП_Periods!AM1156,МП_Periods!AM1271,) -> 0 | AY5: =IFERROR(AC5/AX5,"-") -> - | AZ5: =IFERROR(AX5/$AX$115,"-") -> - | BB5: =IFERROR(BE5/AC5,"-") -> - | BC5: =IFERROR(AC5/BE5,"-") -> - | BD5: =IFERROR(BE5/AX5,"-") -> - | BE5: =SUM(МП_Periods!AT5,МП_Periods!AT120,МП_Periods!AT235,МП_Periods!AT350,МП_Periods!AT466,МП_Periods!AT581,МП_Periods!AT696,МП_Periods!AT811,МП_Periods!AT926,МП_Periods!AT1041,МП_Periods!AT1156,МП_Periods!AT1271) -> 0 | BF5: =IFERROR(BE5/$BE$115,"-") -> - | BH5: =IFERROR(BI5/AX5,"-") -> - | BI5: =SUM(МП_Periods!AX5,МП_Periods!AX120,МП_Periods!AX235,МП_Periods!AX350,МП_Periods!AX466,МП_Periods!AX581,МП_Periods!AX696,МП_Periods!AX811,МП_Periods!AX926,МП_Periods!AX1041,МП_Periods!AX1156,МП_Periods!AX1271) -> 0 | BJ5: =IFERROR(AC5/BI5,"-") -> - | BK5: =IFERROR(BI5/$AX$115,"-") -> - | BM5: =IFERROR(BP5/AC5,"-") -> - | BN5: =IFERROR(AC5/BP5,"-") -> - | BO5: =IFERROR(BP5/BI5,"-") -> - | BP5: =SUM(МП_Periods!BE5,МП_Periods!BE120,МП_Periods!BE235,МП_Periods!BE350,МП_Periods!BE466,МП_Periods!BE581,МП_Periods!BE696,МП_Periods!BE811,МП_Periods!BE926,МП_Periods!BE1041,МП_Periods!BE1156,МП_Periods!BE1271) -> 0 | BQ5: =IFERROR(BP5/$BP$115,"-") -> -
S6: CPC | T6: =IFERROR(W6/U6,"-") -> - | U6: =SUM(МП_Periods!J6,МП_Periods!J121,МП_Periods!J236,МП_Periods!J351,МП_Periods!J467,МП_Periods!J582,МП_Periods!J697,МП_Periods!J812,МП_Periods!J927,МП_Periods!J1042,МП_Periods!J1157,МП_Periods!J1272) -> 0 | W6: =SUM(МП_Periods!L6,МП_Periods!L121,МП_Periods!L236,МП_Periods!L351,МП_Periods!L467,МП_Periods!L582,МП_Periods!L697,МП_Periods!L812,МП_Periods!L927,МП_Periods!L1042,МП_Periods!L1157,МП_Periods!L1272) -> 0 | Y6: =SUM(МП_Periods!N6,МП_Periods!N121,МП_Periods!N236,МП_Periods!N351,МП_Periods!N467,МП_Periods!N582,МП_Periods!N697,МП_Periods!N812,МП_Periods!N927,МП_Periods!N1042,МП_Periods!N1157,МП_Periods!N1272) -> 0 | AA6: =SUM(МП_Periods!P6,МП_Periods!P121,МП_Periods!P236,МП_Periods!P351,МП_Periods!P467,МП_Periods!P582,МП_Periods!P697,МП_Periods!P812,МП_Periods!P927,МП_Periods!P1042,МП_Periods!P1157,МП_Periods!P1272) -> 0 | AB6: =SUM(МП_Periods!Q6,МП_Periods!Q121,МП_Periods!Q236,МП_Periods!Q351,МП_Periods!Q467,МП_Periods!Q582,МП_Periods!Q697,МП_Periods!Q812,МП_Periods!Q927,МП_Periods!Q1042,МП_Periods!Q1157,МП_Periods!Q1272) -> 0 | AC6: =SUM(МП_Periods!R6,МП_Periods!R121,МП_Periods!R236,МП_Periods!R351,МП_Periods!R467,МП_Periods!R582,МП_Periods!R697,МП_Periods!R812,МП_Periods!R927,МП_Periods!R1042,МП_Periods!R1157,МП_Periods!R1272) -> 0 | AD6: =SUM(МП_Periods!S6,МП_Periods!S121,МП_Periods!S236,МП_Periods!S351,МП_Periods!S467,МП_Periods!S582,МП_Periods!S697,МП_Periods!S812,МП_Periods!S927,МП_Periods!S1042,МП_Periods!S1157,МП_Periods!S1272) -> 0 | AE6: =IFERROR(AC6/$AC$115,"-") -> - | AG6: =SUM(МП_Periods!V6,МП_Periods!V121,МП_Periods!V236,МП_Periods!V351,МП_Periods!V467,МП_Periods!V582,МП_Periods!V697,МП_Periods!V812,МП_Periods!V927,МП_Periods!V1042,МП_Periods!V1157,МП_Periods!V1272) -> 0 | AJ6: =SUM(МП_Periods!Y6,МП_Periods!Y121,МП_Periods!Y236,МП_Periods!Y351,МП_Periods!Y467,МП_Periods!Y582,МП_Periods!Y697,МП_Periods!Y812,МП_Periods!Y927,МП_Periods!Y1042,МП_Periods!Y1157,МП_Periods!Y1272) -> 0 | AK6: =SUM(МП_Periods!Z6,МП_Periods!Z121,МП_Periods!Z236,МП_Periods!Z351,МП_Periods!Z467,МП_Periods!Z582,МП_Periods!Z697,МП_Periods!Z812,МП_Periods!Z927,МП_Periods!Z1042,МП_Periods!Z1157,МП_Periods!Z1272) -> 0 | AL6: =SUM(МП_Periods!AA6,МП_Periods!AA121,МП_Periods!AA236,МП_Periods!AA351,МП_Periods!AA467,МП_Periods!AA582,МП_Periods!AA697,МП_Periods!AA812,МП_Periods!AA927,МП_Periods!AA1042,МП_Periods!AA1157,МП_Periods!AA1272) -> 0 | AM6: =SUM(МП_Periods!AB6,МП_Periods!AB121,МП_Periods!AB236,МП_Periods!AB351,МП_Periods!AB467,МП_Periods!AB582,МП_Periods!AB697,МП_Periods!AB812,МП_Periods!AB927,МП_Periods!AB1042,МП_Periods!AB1157,МП_Periods!AB1272) -> 0 | AO6: =IFERROR(AC6/AM6,"-") -> - | AP6: =SUM(МП_Periods!AE6,МП_Periods!AE121,МП_Periods!AE236,МП_Periods!AE351,МП_Periods!AE467,МП_Periods!AE582,МП_Periods!AE697,МП_Periods!AE812,МП_Periods!AE927,МП_Periods!AE1042,МП_Periods!AE1157,МП_Periods!AE1272) -> 0 | AQ6: =IFERROR(#REF!/AP6,"-") -> - | AS6: =IFERROR(U6/AG6,"-") -> - | AT6: =SUM(МП_Periods!AI6,МП_Periods!AI121,МП_Periods!AI236,МП_Periods!AI351,МП_Periods!AI467,МП_Periods!AI582,МП_Periods!AI697,МП_Periods!AI812,МП_Periods!AI927,МП_Periods!AI1042,МП_Periods!AI1157,МП_Periods!AI1272) -> 0 | AU6: =IFERROR(AC6/AT6,"-") -> - | AW6: =IFERROR(AX6/AT6,"-") -> - | AX6: =SUM(МП_Periods!AM6,МП_Periods!AM121,МП_Periods!AM236,МП_Periods!AM351,МП_Periods!AM467,МП_Periods!AM582,МП_Periods!AM697,МП_Periods!AM812,МП_Periods!AM927,МП_Periods!AM1042,МП_Periods!AM1157,МП_Periods!AM1272,) -> 0 | AY6: =IFERROR(AC6/AX6,"-") -> - | AZ6: =IFERROR(AX6/$AX$115,"-") -> - | BB6: =IFERROR(BE6/AC6,"-") -> - | BC6: =IFERROR(AC6/BE6,"-") -> - | BD6: =IFERROR(BE6/AX6,"-") -> - | BE6: =SUM(МП_Periods!AT6,МП_Periods!AT121,МП_Periods!AT236,МП_Periods!AT351,МП_Periods!AT467,МП_Periods!AT582,МП_Periods!AT697,МП_Periods!AT812,МП_Periods!AT927,МП_Periods!AT1042,МП_Periods!AT1157,МП_Periods!AT1272) -> 0 | BF6: =IFERROR(BE6/$BE$115,"-") -> - | BH6: =IFERROR(BI6/AX6,"-") -> - | BI6: =SUM(МП_Periods!AX6,МП_Periods!AX121,МП_Periods!AX236,МП_Periods!AX351,МП_Periods!AX467,МП_Periods!AX582,МП_Periods!AX697,МП_Periods!AX812,МП_Periods!AX927,МП_Periods!AX1042,МП_Periods!AX1157,МП_Periods!AX1272) -> 0 | BJ6: =IFERROR(AC6/BI6,"-") -> - | BK6: =IFERROR(BI6/$AX$115,"-") -> - | BM6: =IFERROR(BP6/AC6,"-") -> - | BN6: =IFERROR(AC6/BP6,"-") -> - | BO6: =IFERROR(BP6/BI6,"-") -> - | BP6: =SUM(МП_Periods!BE6,МП_Periods!BE121,МП_Periods!BE236,МП_Periods!BE351,МП_Periods!BE467,МП_Periods!BE582,МП_Periods!BE697,МП_Periods!BE812,МП_Periods!BE927,МП_Periods!BE1042,МП_Periods!BE1157,МП_Periods!BE1272) -> 0 | BQ6: =IFERROR(BP6/$BP$115,"-") -> -
S7: CPC | T7: =IFERROR(W7/U7,"-") -> - | U7: =SUM(МП_Periods!J7,МП_Periods!J122,МП_Periods!J237,МП_Periods!J352,МП_Periods!J468,МП_Periods!J583,МП_Periods!J698,МП_Periods!J813,МП_Periods!J928,МП_Periods!J1043,МП_Periods!J1158,МП_Periods!J1273) -> 0 | W7: =SUM(МП_Periods!L7,МП_Periods!L122,МП_Periods!L237,МП_Periods!L352,МП_Periods!L468,МП_Periods!L583,МП_Periods!L698,МП_Periods!L813,МП_Periods!L928,МП_Periods!L1043,МП_Periods!L1158,МП_Periods!L1273) -> 0 | Y7: =SUM(МП_Periods!N7,МП_Periods!N122,МП_Periods!N237,МП_Periods!N352,МП_Periods!N468,МП_Periods!N583,МП_Periods!N698,МП_Periods!N813,МП_Periods!N928,МП_Periods!N1043,МП_Periods!N1158,МП_Periods!N1273) -> 0 | AA7: =SUM(МП_Periods!P7,МП_Periods!P122,МП_Periods!P237,МП_Periods!P352,МП_Periods!P468,МП_Periods!P583,МП_Periods!P698,МП_Periods!P813,МП_Periods!P928,МП_Periods!P1043,МП_Periods!P1158,МП_Periods!P1273) -> 0 | AB7: =SUM(МП_Periods!Q7,МП_Periods!Q122,МП_Periods!Q237,МП_Periods!Q352,МП_Periods!Q468,МП_Periods!Q583,МП_Periods!Q698,МП_Periods!Q813,МП_Periods!Q928,МП_Periods!Q1043,МП_Periods!Q1158,МП_Periods!Q1273) -> 0 | AC7: =SUM(МП_Periods!R7,МП_Periods!R122,МП_Periods!R237,МП_Periods!R352,МП_Periods!R468,МП_Periods!R583,МП_Periods!R698,МП_Periods!R813,МП_Periods!R928,МП_Periods!R1043,МП_Periods!R1158,МП_Periods!R1273) -> 0 | AD7: =SUM(МП_Periods!S7,МП_Periods!S122,МП_Periods!S237,МП_Periods!S352,МП_Periods!S468,МП_Periods!S583,МП_Periods!S698,МП_Periods!S813,МП_Periods!S928,МП_Periods!S1043,МП_Periods!S1158,МП_Periods!S1273) -> 0 | AE7: =IFERROR(AC7/$AC$115,"-") -> - | AG7: =SUM(МП_Periods!V7,МП_Periods!V122,МП_Periods!V237,МП_Periods!V352,МП_Periods!V468,МП_Periods!V583,МП_Periods!V698,МП_Periods!V813,МП_Periods!V928,МП_Periods!V1043,МП_Periods!V1158,МП_Periods!V1273) -> 0 | AJ7: =SUM(МП_Periods!Y7,МП_Periods!Y122,МП_Periods!Y237,МП_Periods!Y352,МП_Periods!Y468,МП_Periods!Y583,МП_Periods!Y698,МП_Periods!Y813,МП_Periods!Y928,МП_Periods!Y1043,МП_Periods!Y1158,МП_Periods!Y1273) -> 0 | AK7: =SUM(МП_Periods!Z7,МП_Periods!Z122,МП_Periods!Z237,МП_Periods!Z352,МП_Periods!Z468,МП_Periods!Z583,МП_Periods!Z698,МП_Periods!Z813,МП_Periods!Z928,МП_Periods!Z1043,МП_Periods!Z1158,МП_Periods!Z1273) -> 0 | AL7: =SUM(МП_Periods!AA7,МП_Periods!AA122,МП_Periods!AA237,МП_Periods!AA352,МП_Periods!AA468,МП_Periods!AA583,МП_Periods!AA698,МП_Periods!AA813,МП_Periods!AA928,МП_Periods!AA1043,МП_Periods!AA1158,МП_Periods!AA1273) -> 0 | AM7: =SUM(МП_Periods!AB7,МП_Periods!AB122,МП_Periods!AB237,МП_Periods!AB352,МП_Periods!AB468,МП_Periods!AB583,МП_Periods!AB698,МП_Periods!AB813,МП_Periods!AB928,МП_Periods!AB1043,МП_Periods!AB1158,МП_Periods!AB1273) -> 0 | AO7: =IFERROR(AC7/AM7,"-") -> - | AP7: =SUM(МП_Periods!AE7,МП_Periods!AE122,МП_Periods!AE237,МП_Periods!AE352,МП_Periods!AE468,МП_Periods!AE583,МП_Periods!AE698,МП_Periods!AE813,МП_Periods!AE928,МП_Periods!AE1043,МП_Periods!AE1158,МП_Periods!AE1273) -> 0 | AQ7: =IFERROR(#REF!/AP7,"-") -> - | AS7: =IFERROR(U7/AG7,"-") -> - | AT7: =SUM(МП_Periods!AI7,МП_Periods!AI122,МП_Periods!AI237,МП_Periods!AI352,МП_Periods!AI468,МП_Periods!AI583,МП_Periods!AI698,МП_Periods!AI813,МП_Periods!AI928,МП_Periods!AI1043,МП_Periods!AI1158,МП_Periods!AI1273) -> 0 | AU7: =IFERROR(AC7/AT7,"-") -> - | AW7: =IFERROR(AX7/AT7,"-") -> - | AX7: =SUM(МП_Periods!AM7,МП_Periods!AM122,МП_Periods!AM237,МП_Periods!AM352,МП_Periods!AM468,МП_Periods!AM583,МП_Periods!AM698,МП_Periods!AM813,МП_Periods!AM928,МП_Periods!AM1043,МП_Periods!AM1158,МП_Periods!AM1273,) -> 0 | AY7: =IFERROR(AC7/AX7,"-") -> - | AZ7: =IFERROR(AX7/$AX$115,"-") -> - | BB7: =IFERROR(BE7/AC7,"-") -> - | BC7: =IFERROR(AC7/BE7,"-") -> - | BD7: =IFERROR(BE7/AX7,"-") -> - | BE7: =SUM(МП_Periods!AT7,МП_Periods!AT122,МП_Periods!AT237,МП_Periods!AT352,МП_Periods!AT468,МП_Periods!AT583,МП_Periods!AT698,МП_Periods!AT813,МП_Periods!AT928,МП_Periods!AT1043,МП_Periods!AT1158,МП_Periods!AT1273) -> 0 | BF7: =IFERROR(BE7/$BE$115,"-") -> - | BH7: =IFERROR(BI7/AX7,"-") -> - | BI7: =SUM(МП_Periods!AX7,МП_Periods!AX122,МП_Periods!AX237,МП_Periods!AX352,МП_Periods!AX468,МП_Periods!AX583,МП_Periods!AX698,МП_Periods!AX813,МП_Periods!AX928,МП_Periods!AX1043,МП_Periods!AX1158,МП_Periods!AX1273) -> 0 | BJ7: =IFERROR(AC7/BI7,"-") -> - | BK7: =IFERROR(BI7/$AX$115,"-") -> - | BM7: =IFERROR(BP7/AC7,"-") -> - | BN7: =IFERROR(AC7/BP7,"-") -> - | BO7: =IFERROR(BP7/BI7,"-") -> - | BP7: =SUM(МП_Periods!BE7,МП_Periods!BE122,МП_Periods!BE237,МП_Periods!BE352,МП_Periods!BE468,МП_Periods!BE583,МП_Periods!BE698,МП_Periods!BE813,МП_Periods!BE928,МП_Periods!BE1043,МП_Periods!BE1158,МП_Periods!BE1273) -> 0 | BQ7: =IFERROR(BP7/$BP$115,"-") -> -
S8: CPC | T8: =IFERROR(W8/U8,"-") -> - | U8: =SUM(МП_Periods!J8,МП_Periods!J123,МП_Periods!J238,МП_Periods!J353,МП_Periods!J469,МП_Periods!J584,МП_Periods!J699,МП_Periods!J814,МП_Periods!J929,МП_Periods!J1044,МП_Periods!J1159,МП_Periods!J1274) -> 0 | W8: =SUM(МП_Periods!L8,МП_Periods!L123,МП_Periods!L238,МП_Periods!L353,МП_Periods!L469,МП_Periods!L584,МП_Periods!L699,МП_Periods!L814,МП_Periods!L929,МП_Periods!L1044,МП_Periods!L1159,МП_Periods!L1274) -> 0 | Y8: =SUM(МП_Periods!N8,МП_Periods!N123,МП_Periods!N238,МП_Periods!N353,МП_Periods!N469,МП_Periods!N584,МП_Periods!N699,МП_Periods!N814,МП_Periods!N929,МП_Periods!N1044,МП_Periods!N1159,МП_Periods!N1274) -> 0 | AA8: =SUM(МП_Periods!P8,МП_Periods!P123,МП_Periods!P238,МП_Periods!P353,МП_Periods!P469,МП_Periods!P584,МП_Periods!P699,МП_Periods!P814,МП_Periods!P929,МП_Periods!P1044,МП_Periods!P1159,МП_Periods!P1274) -> 0 | AB8: =SUM(МП_Periods!Q8,МП_Periods!Q123,МП_Periods!Q238,МП_Periods!Q353,МП_Periods!Q469,МП_Periods!Q584,МП_Periods!Q699,МП_Periods!Q814,МП_Periods!Q929,МП_Periods!Q1044,МП_Periods!Q1159,МП_Periods!Q1274) -> 0 | AC8: =SUM(МП_Periods!R8,МП_Periods!R123,МП_Periods!R238,МП_Periods!R353,МП_Periods!R469,МП_Periods!R584,МП_Periods!R699,МП_Periods!R814,МП_Periods!R929,МП_Periods!R1044,МП_Periods!R1159,МП_Periods!R1274) -> 0 | AD8: =SUM(МП_Periods!S8,МП_Periods!S123,МП_Periods!S238,МП_Periods!S353,МП_Periods!S469,МП_Periods!S584,МП_Periods!S699,МП_Periods!S814,МП_Periods!S929,МП_Periods!S1044,МП_Periods!S1159,МП_Periods!S1274) -> 0 | AE8: =IFERROR(AC8/$AC$115,"-") -> - | AG8: =SUM(МП_Periods!V8,МП_Periods!V123,МП_Periods!V238,МП_Periods!V353,МП_Periods!V469,МП_Periods!V584,МП_Periods!V699,МП_Periods!V814,МП_Periods!V929,МП_Periods!V1044,МП_Periods!V1159,МП_Periods!V1274) -> 0 | AJ8: =SUM(МП_Periods!Y8,МП_Periods!Y123,МП_Periods!Y238,МП_Periods!Y353,МП_Periods!Y469,МП_Periods!Y584,МП_Periods!Y699,МП_Periods!Y814,МП_Periods!Y929,МП_Periods!Y1044,МП_Periods!Y1159,МП_Periods!Y1274) -> 0 | AK8: =SUM(МП_Periods!Z8,МП_Periods!Z123,МП_Periods!Z238,МП_Periods!Z353,МП_Periods!Z469,МП_Periods!Z584,МП_Periods!Z699,МП_Periods!Z814,МП_Periods!Z929,МП_Periods!Z1044,МП_Periods!Z1159,МП_Periods!Z1274) -> 0 | AL8: =SUM(МП_Periods!AA8,МП_Periods!AA123,МП_Periods!AA238,МП_Periods!AA353,МП_Periods!AA469,МП_Periods!AA584,МП_Periods!AA699,МП_Periods!AA814,МП_Periods!AA929,МП_Periods!AA1044,МП_Periods!AA1159,МП_Periods!AA1274) -> 0 | AM8: =SUM(МП_Periods!AB8,МП_Periods!AB123,МП_Periods!AB238,МП_Periods!AB353,МП_Periods!AB469,МП_Periods!AB584,МП_Periods!AB699,МП_Periods!AB814,МП_Periods!AB929,МП_Periods!AB1044,МП_Periods!AB1159,МП_Periods!AB1274) -> 0 | AO8: =IFERROR(AC8/AM8,"-") -> - | AP8: =SUM(МП_Periods!AE8,МП_Periods!AE123,МП_Periods!AE238,МП_Periods!AE353,МП_Periods!AE469,МП_Periods!AE584,МП_Periods!AE699,МП_Periods!AE814,МП_Periods!AE929,МП_Periods!AE1044,МП_Periods!AE1159,МП_Periods!AE1274) -> 0 | AQ8: =IFERROR(#REF!/AP8,"-") -> - | AS8: =IFERROR(U8/AG8,"-") -> - | AT8: =SUM(МП_Periods!AI8,МП_Periods!AI123,МП_Periods!AI238,МП_Periods!AI353,МП_Periods!AI469,МП_Periods!AI584,МП_Periods!AI699,МП_Periods!AI814,МП_Periods!AI929,МП_Periods!AI1044,МП_Periods!AI1159,МП_Periods!AI1274) -> 0 | AU8: =IFERROR(AC8/AT8,"-") -> - | AW8: =IFERROR(AX8/AT8,"-") -> - | AX8: =SUM(МП_Periods!AM8,МП_Periods!AM123,МП_Periods!AM238,МП_Periods!AM353,МП_Periods!AM469,МП_Periods!AM584,МП_Periods!AM699,МП_Periods!AM814,МП_Periods!AM929,МП_Periods!AM1044,МП_Periods!AM1159,МП_Periods!AM1274,) -> 0 | AY8: =IFERROR(AC8/AX8,"-") -> - | AZ8: =IFERROR(AX8/$AX$115,"-") -> - | BB8: =IFERROR(BE8/AC8,"-") -> - | BC8: =IFERROR(AC8/BE8,"-") -> - | BD8: =IFERROR(BE8/AX8,"-") -> - | BE8: =SUM(МП_Periods!AT8,МП_Periods!AT123,МП_Periods!AT238,МП_Periods!AT353,МП_Periods!AT469,МП_Periods!AT584,МП_Periods!AT699,МП_Periods!AT814,МП_Periods!AT929,МП_Periods!AT1044,МП_Periods!AT1159,МП_Periods!AT1274) -> 0 | BF8: =IFERROR(BE8/$BE$115,"-") -> - | BH8: =IFERROR(BI8/AX8,"-") -> - | BI8: =SUM(МП_Periods!AX8,МП_Periods!AX123,МП_Periods!AX238,МП_Periods!AX353,МП_Periods!AX469,МП_Periods!AX584,МП_Periods!AX699,МП_Periods!AX814,МП_Periods!AX929,МП_Periods!AX1044,МП_Periods!AX1159,МП_Periods!AX1274) -> 0 | BJ8: =IFERROR(AC8/BI8,"-") -> - | BK8: =IFERROR(BI8/$AX$115,"-") -> - | BM8: =IFERROR(BP8/AC8,"-") -> - | BN8: =IFERROR(AC8/BP8,"-") -> - | BO8: =IFERROR(BP8/BI8,"-") -> - | BP8: =SUM(МП_Periods!BE8,МП_Periods!BE123,МП_Periods!BE238,МП_Periods!BE353,МП_Periods!BE469,МП_Periods!BE584,МП_Periods!BE699,МП_Periods!BE814,МП_Periods!BE929,МП_Periods!BE1044,МП_Periods!BE1159,МП_Periods!BE1274) -> 0 | BQ8: =IFERROR(BP8/$BP$115,"-") -> -
S9: CPC | T9: =IFERROR(W9/U9,"-") -> - | U9: =SUM(МП_Periods!J9,МП_Periods!J124,МП_Periods!J239,МП_Periods!J354,МП_Periods!J470,МП_Periods!J585,МП_Periods!J700,МП_Periods!J815,МП_Periods!J930,МП_Periods!J1045,МП_Periods!J1160,МП_Periods!J1275) -> 0 | W9: =SUM(МП_Periods!L9,МП_Periods!L124,МП_Periods!L239,МП_Periods!L354,МП_Periods!L470,МП_Periods!L585,МП_Periods!L700,МП_Periods!L815,МП_Periods!L930,МП_Periods!L1045,МП_Periods!L1160,МП_Periods!L1275) -> 0 | Y9: =SUM(МП_Periods!N9,МП_Periods!N124,МП_Periods!N239,МП_Periods!N354,МП_Periods!N470,МП_Periods!N585,МП_Periods!N700,МП_Periods!N815,МП_Periods!N930,МП_Periods!N1045,МП_Periods!N1160,МП_Periods!N1275) -> 0 | AA9: =SUM(МП_Periods!P9,МП_Periods!P124,МП_Periods!P239,МП_Periods!P354,МП_Periods!P470,МП_Periods!P585,МП_Periods!P700,МП_Periods!P815,МП_Periods!P930,МП_Periods!P1045,МП_Periods!P1160,МП_Periods!P1275) -> 0 | AB9: =SUM(МП_Periods!Q9,МП_Periods!Q124,МП_Periods!Q239,МП_Periods!Q354,МП_Periods!Q470,МП_Periods!Q585,МП_Periods!Q700,МП_Periods!Q815,МП_Periods!Q930,МП_Periods!Q1045,МП_Periods!Q1160,МП_Periods!Q1275) -> 0 | AC9: =SUM(МП_Periods!R9,МП_Periods!R124,МП_Periods!R239,МП_Periods!R354,МП_Periods!R470,МП_Periods!R585,МП_Periods!R700,МП_Periods!R815,МП_Periods!R930,МП_Periods!R1045,МП_Periods!R1160,МП_Periods!R1275) -> 0 | AD9: =SUM(МП_Periods!S9,МП_Periods!S124,МП_Periods!S239,МП_Periods!S354,МП_Periods!S470,МП_Periods!S585,МП_Periods!S700,МП_Periods!S815,МП_Periods!S930,МП_Periods!S1045,МП_Periods!S1160,МП_Periods!S1275) -> 0 | AE9: =IFERROR(AC9/$AC$115,"-") -> - | AG9: =SUM(МП_Periods!V9,МП_Periods!V124,МП_Periods!V239,МП_Periods!V354,МП_Periods!V470,МП_Periods!V585,МП_Periods!V700,МП_Periods!V815,МП_Periods!V930,МП_Periods!V1045,МП_Periods!V1160,МП_Periods!V1275) -> 0 | AJ9: =SUM(МП_Periods!Y9,МП_Periods!Y124,МП_Periods!Y239,МП_Periods!Y354,МП_Periods!Y470,МП_Periods!Y585,МП_Periods!Y700,МП_Periods!Y815,МП_Periods!Y930,МП_Periods!Y1045,МП_Periods!Y1160,МП_Periods!Y1275) -> 0 | AK9: =SUM(МП_Periods!Z9,МП_Periods!Z124,МП_Periods!Z239,МП_Periods!Z354,МП_Periods!Z470,МП_Periods!Z585,МП_Periods!Z700,МП_Periods!Z815,МП_Periods!Z930,МП_Periods!Z1045,МП_Periods!Z1160,МП_Periods!Z1275) -> 0 | AL9: =SUM(МП_Periods!AA9,МП_Periods!AA124,МП_Periods!AA239,МП_Periods!AA354,МП_Periods!AA470,МП_Periods!AA585,МП_Periods!AA700,МП_Periods!AA815,МП_Periods!AA930,МП_Periods!AA1045,МП_Periods!AA1160,МП_Periods!AA1275) -> 0 | AM9: =SUM(МП_Periods!AB9,МП_Periods!AB124,МП_Periods!AB239,МП_Periods!AB354,МП_Periods!AB470,МП_Periods!AB585,МП_Periods!AB700,МП_Periods!AB815,МП_Periods!AB930,МП_Periods!AB1045,МП_Periods!AB1160,МП_Periods!AB1275) -> 0 | AO9: =IFERROR(AC9/AM9,"-") -> - | AP9: =SUM(МП_Periods!AE9,МП_Periods!AE124,МП_Periods!AE239,МП_Periods!AE354,МП_Periods!AE470,МП_Periods!AE585,МП_Periods!AE700,МП_Periods!AE815,МП_Periods!AE930,МП_Periods!AE1045,МП_Periods!AE1160,МП_Periods!AE1275) -> 0 | AQ9: =IFERROR(#REF!/AP9,"-") -> - | AS9: =IFERROR(U9/AG9,"-") -> - | AT9: =SUM(МП_Periods!AI9,МП_Periods!AI124,МП_Periods!AI239,МП_Periods!AI354,МП_Periods!AI470,МП_Periods!AI585,МП_Periods!AI700,МП_Periods!AI815,МП_Periods!AI930,МП_Periods!AI1045,МП_Periods!AI1160,МП_Periods!AI1275) -> 0 | AU9: =IFERROR(AC9/AT9,"-") -> - | AW9: =IFERROR(AX9/AT9,"-") -> - | AX9: =SUM(МП_Periods!AM9,МП_Periods!AM124,МП_Periods!AM239,МП_Periods!AM354,МП_Periods!AM470,МП_Periods!AM585,МП_Periods!AM700,МП_Periods!AM815,МП_Periods!AM930,МП_Periods!AM1045,МП_Periods!AM1160,МП_Periods!AM1275,) -> 0 | AY9: =IFERROR(AC9/AX9,"-") -> - | AZ9: =IFERROR(AX9/$AX$115,"-") -> - | BB9: =IFERROR(BE9/AC9,"-") -> - | BC9: =IFERROR(AC9/BE9,"-") -> - | BD9: =IFERROR(BE9/AX9,"-") -> - | BE9: =SUM(МП_Periods!AT9,МП_Periods!AT124,МП_Periods!AT239,МП_Periods!AT354,МП_Periods!AT470,МП_Periods!AT585,МП_Periods!AT700,МП_Periods!AT815,МП_Periods!AT930,МП_Periods!AT1045,МП_Periods!AT1160,МП_Periods!AT1275) -> 0 | BF9: =IFERROR(BE9/$BE$115,"-") -> - | BH9: =IFERROR(BI9/AX9,"-") -> - | BI9: =SUM(МП_Periods!AX9,МП_Periods!AX124,МП_Periods!AX239,МП_Periods!AX354,МП_Periods!AX470,МП_Periods!AX585,МП_Periods!AX700,МП_Periods!AX815,МП_Periods!AX930,МП_Periods!AX1045,МП_Periods!AX1160,МП_Periods!AX1275) -> 0 | BJ9: =IFERROR(AC9/BI9,"-") -> - | BK9: =IFERROR(BI9/$AX$115,"-") -> - | BM9: =IFERROR(BP9/AC9,"-") -> - | BN9: =IFERROR(AC9/BP9,"-") -> - | BO9: =IFERROR(BP9/BI9,"-") -> - | BP9: =SUM(МП_Periods!BE9,МП_Periods!BE124,МП_Periods!BE239,МП_Periods!BE354,МП_Periods!BE470,МП_Periods!BE585,МП_Periods!BE700,МП_Periods!BE815,МП_Periods!BE930,МП_Periods!BE1045,МП_Periods!BE1160,МП_Periods!BE1275) -> 0 | BQ9: =IFERROR(BP9/$BP$115,"-") -> -
S10: CPC | T10: =IFERROR(W10/U10,"-") -> - | U10: =SUM(МП_Periods!J10,МП_Periods!J125,МП_Periods!J240,МП_Periods!J355,МП_Periods!J471,МП_Periods!J586,МП_Periods!J701,МП_Periods!J816,МП_Periods!J931,МП_Periods!J1046,МП_Periods!J1161,МП_Periods!J1276) -> 0 | W10: =SUM(МП_Periods!L10,МП_Periods!L125,МП_Periods!L240,МП_Periods!L355,МП_Periods!L471,МП_Periods!L586,МП_Periods!L701,МП_Periods!L816,МП_Periods!L931,МП_Periods!L1046,МП_Periods!L1161,МП_Periods!L1276) -> 0 | Y10: =SUM(МП_Periods!N10,МП_Periods!N125,МП_Periods!N240,МП_Periods!N355,МП_Periods!N471,МП_Periods!N586,МП_Periods!N701,МП_Periods!N816,МП_Periods!N931,МП_Periods!N1046,МП_Periods!N1161,МП_Periods!N1276) -> 0 | AA10: =SUM(МП_Periods!P10,МП_Periods!P125,МП_Periods!P240,МП_Periods!P355,МП_Periods!P471,МП_Periods!P586,МП_Periods!P701,МП_Periods!P816,МП_Periods!P931,МП_Periods!P1046,МП_Periods!P1161,МП_Periods!P1276) -> 0 | AB10: =SUM(МП_Periods!Q10,МП_Periods!Q125,МП_Periods!Q240,МП_Periods!Q355,МП_Periods!Q471,МП_Periods!Q586,МП_Periods!Q701,МП_Periods!Q816,МП_Periods!Q931,МП_Periods!Q1046,МП_Periods!Q1161,МП_Periods!Q1276) -> 0 | AC10: =SUM(МП_Periods!R10,МП_Periods!R125,МП_Periods!R240,МП_Periods!R355,МП_Periods!R471,МП_Periods!R586,МП_Periods!R701,МП_Periods!R816,МП_Periods!R931,МП_Periods!R1046,МП_Periods!R1161,МП_Periods!R1276) -> 0 | AD10: =SUM(МП_Periods!S10,МП_Periods!S125,МП_Periods!S240,МП_Periods!S355,МП_Periods!S471,МП_Periods!S586,МП_Periods!S701,МП_Periods!S816,МП_Periods!S931,МП_Periods!S1046,МП_Periods!S1161,МП_Periods!S1276) -> 0 | AE10: =IFERROR(AC10/$AC$115,"-") -> - | AG10: =SUM(МП_Periods!V10,МП_Periods!V125,МП_Periods!V240,МП_Periods!V355,МП_Periods!V471,МП_Periods!V586,МП_Periods!V701,МП_Periods!V816,МП_Periods!V931,МП_Periods!V1046,МП_Periods!V1161,МП_Periods!V1276) -> 0 | AJ10: =SUM(МП_Periods!Y10,МП_Periods!Y125,МП_Periods!Y240,МП_Periods!Y355,МП_Periods!Y471,МП_Periods!Y586,МП_Periods!Y701,МП_Periods!Y816,МП_Periods!Y931,МП_Periods!Y1046,МП_Periods!Y1161,МП_Periods!Y1276) -> 0 | AK10: =SUM(МП_Periods!Z10,МП_Periods!Z125,МП_Periods!Z240,МП_Periods!Z355,МП_Periods!Z471,МП_Periods!Z586,МП_Periods!Z701,МП_Periods!Z816,МП_Periods!Z931,МП_Periods!Z1046,МП_Periods!Z1161,МП_Periods!Z1276) -> 0 | AL10: =SUM(МП_Periods!AA10,МП_Periods!AA125,МП_Periods!AA240,МП_Periods!AA355,МП_Periods!AA471,МП_Periods!AA586,МП_Periods!AA701,МП_Periods!AA816,МП_Periods!AA931,МП_Periods!AA1046,МП_Periods!AA1161,МП_Periods!AA1276) -> 0 | AM10: =SUM(МП_Periods!AB10,МП_Periods!AB125,МП_Periods!AB240,МП_Periods!AB355,МП_Periods!AB471,МП_Periods!AB586,МП_Periods!AB701,МП_Periods!AB816,МП_Periods!AB931,МП_Periods!AB1046,МП_Periods!AB1161,МП_Periods!AB1276) -> 0 | AO10: =IFERROR(AC10/AM10,"-") -> - | AP10: =SUM(МП_Periods!AE10,МП_Periods!AE125,МП_Periods!AE240,МП_Periods!AE355,МП_Periods!AE471,МП_Periods!AE586,МП_Periods!AE701,МП_Periods!AE816,МП_Periods!AE931,МП_Periods!AE1046,МП_Periods!AE1161,МП_Periods!AE1276) -> 0 | AQ10: =IFERROR(#REF!/AP10,"-") -> - | AS10: =IFERROR(U10/AG10,"-") -> - | AT10: =SUM(МП_Periods!AI10,МП_Periods!AI125,МП_Periods!AI240,МП_Periods!AI355,МП_Periods!AI471,МП_Periods!AI586,МП_Periods!AI701,МП_Periods!AI816,МП_Periods!AI931,МП_Periods!AI1046,МП_Periods!AI1161,МП_Periods!AI1276) -> 0 | AU10: =IFERROR(AC10/AT10,"-") -> - | AW10: =IFERROR(AX10/AT10,"-") -> - | AX10: =SUM(МП_Periods!AM10,МП_Periods!AM125,МП_Periods!AM240,МП_Periods!AM355,МП_Periods!AM471,МП_Periods!AM586,МП_Periods!AM701,МП_Periods!AM816,МП_Periods!AM931,МП_Periods!AM1046,МП_Periods!AM1161,МП_Periods!AM1276,) -> 0 | AY10: =IFERROR(AC10/AX10,"-") -> - | AZ10: =IFERROR(AX10/$AX$115,"-") -> - | BB10: =IFERROR(BE10/AC10,"-") -> - | BC10: =IFERROR(AC10/BE10,"-") -> - | BD10: =IFERROR(BE10/AX10,"-") -> - | BE10: =SUM(МП_Periods!AT10,МП_Periods!AT125,МП_Periods!AT240,МП_Periods!AT355,МП_Periods!AT471,МП_Periods!AT586,МП_Periods!AT701,МП_Periods!AT816,МП_Periods!AT931,МП_Periods!AT1046,МП_Periods!AT1161,МП_Periods!AT1276) -> 0 | BF10: =IFERROR(BE10/$BE$115,"-") -> - | BH10: =IFERROR(BI10/AX10,"-") -> - | BI10: =SUM(МП_Periods!AX10,МП_Periods!AX125,МП_Periods!AX240,МП_Periods!AX355,МП_Periods!AX471,МП_Periods!AX586,МП_Periods!AX701,МП_Periods!AX816,МП_Periods!AX931,МП_Periods!AX1046,МП_Periods!AX1161,МП_Periods!AX1276) -> 0 | BJ10: =IFERROR(AC10/BI10,"-") -> - | BK10: =IFERROR(BI10/$AX$115,"-") -> - | BM10: =IFERROR(BP10/AC10,"-") -> - | BN10: =IFERROR(AC10/BP10,"-") -> - | BO10: =IFERROR(BP10/BI10,"-") -> - | BP10: =SUM(МП_Periods!BE10,МП_Periods!BE125,МП_Periods!BE240,МП_Periods!BE355,МП_Periods!BE471,МП_Periods!BE586,МП_Periods!BE701,МП_Periods!BE816,МП_Periods!BE931,МП_Periods!BE1046,МП_Periods!BE1161,МП_Periods!BE1276) -> 0 | BQ10: =IFERROR(BP10/$BP$115,"-") -> -
S11: CPC | T11: =IFERROR(W11/U11,"-") -> - | U11: =SUM(МП_Periods!J11,МП_Periods!J126,МП_Periods!J241,МП_Periods!J356,МП_Periods!J472,МП_Periods!J587,МП_Periods!J702,МП_Periods!J817,МП_Periods!J932,МП_Periods!J1047,МП_Periods!J1162,МП_Periods!J1277) -> 0 | W11: =SUM(МП_Periods!L11,МП_Periods!L126,МП_Periods!L241,МП_Periods!L356,МП_Periods!L472,МП_Periods!L587,МП_Periods!L702,МП_Periods!L817,МП_Periods!L932,МП_Periods!L1047,МП_Periods!L1162,МП_Periods!L1277) -> 0 | Y11: =SUM(МП_Periods!N11,МП_Periods!N126,МП_Periods!N241,МП_Periods!N356,МП_Periods!N472,МП_Periods!N587,МП_Periods!N702,МП_Periods!N817,МП_Periods!N932,МП_Periods!N1047,МП_Periods!N1162,МП_Periods!N1277) -> 0 | AA11: =SUM(МП_Periods!P11,МП_Periods!P126,МП_Periods!P241,МП_Periods!P356,МП_Periods!P472,МП_Periods!P587,МП_Periods!P702,МП_Periods!P817,МП_Periods!P932,МП_Periods!P1047,МП_Periods!P1162,МП_Periods!P1277) -> 0 | AB11: =SUM(МП_Periods!Q11,МП_Periods!Q126,МП_Periods!Q241,МП_Periods!Q356,МП_Periods!Q472,МП_Periods!Q587,МП_Periods!Q702,МП_Periods!Q817,МП_Periods!Q932,МП_Periods!Q1047,МП_Periods!Q1162,МП_Periods!Q1277) -> 0 | AC11: =SUM(МП_Periods!R11,МП_Periods!R126,МП_Periods!R241,МП_Periods!R356,МП_Periods!R472,МП_Periods!R587,МП_Periods!R702,МП_Periods!R817,МП_Periods!R932,МП_Periods!R1047,МП_Periods!R1162,МП_Periods!R1277) -> 0 | AD11: =SUM(МП_Periods!S11,МП_Periods!S126,МП_Periods!S241,МП_Periods!S356,МП_Periods!S472,МП_Periods!S587,МП_Periods!S702,МП_Periods!S817,МП_Periods!S932,МП_Periods!S1047,МП_Periods!S1162,МП_Periods!S1277) -> 0 | AE11: =IFERROR(AC11/$AC$115,"-") -> - | AG11: =SUM(МП_Periods!V11,МП_Periods!V126,МП_Periods!V241,МП_Periods!V356,МП_Periods!V472,МП_Periods!V587,МП_Periods!V702,МП_Periods!V817,МП_Periods!V932,МП_Periods!V1047,МП_Periods!V1162,МП_Periods!V1277) -> 0 | AJ11: =SUM(МП_Periods!Y11,МП_Periods!Y126,МП_Periods!Y241,МП_Periods!Y356,МП_Periods!Y472,МП_Periods!Y587,МП_Periods!Y702,МП_Periods!Y817,МП_Periods!Y932,МП_Periods!Y1047,МП_Periods!Y1162,МП_Periods!Y1277) -> 0 | AK11: =SUM(МП_Periods!Z11,МП_Periods!Z126,МП_Periods!Z241,МП_Periods!Z356,МП_Periods!Z472,МП_Periods!Z587,МП_Periods!Z702,МП_Periods!Z817,МП_Periods!Z932,МП_Periods!Z1047,МП_Periods!Z1162,МП_Periods!Z1277) -> 0 | AL11: =SUM(МП_Periods!AA11,МП_Periods!AA126,МП_Periods!AA241,МП_Periods!AA356,МП_Periods!AA472,МП_Periods!AA587,МП_Periods!AA702,МП_Periods!AA817,МП_Periods!AA932,МП_Periods!AA1047,МП_Periods!AA1162,МП_Periods!AA1277) -> 0 | AM11: =SUM(МП_Periods!AB11,МП_Periods!AB126,МП_Periods!AB241,МП_Periods!AB356,МП_Periods!AB472,МП_Periods!AB587,МП_Periods!AB702,МП_Periods!AB817,МП_Periods!AB932,МП_Periods!AB1047,МП_Periods!AB1162,МП_Periods!AB1277) -> 0 | AO11: =IFERROR(AC11/AM11,"-") -> - | AP11: =SUM(МП_Periods!AE11,МП_Periods!AE126,МП_Periods!AE241,МП_Periods!AE356,МП_Periods!AE472,МП_Periods!AE587,МП_Periods!AE702,МП_Periods!AE817,МП_Periods!AE932,МП_Periods!AE1047,МП_Periods!AE1162,МП_Periods!AE1277) -> 0 | AQ11: =IFERROR(#REF!/AP11,"-") -> - | AS11: =IFERROR(U11/AG11,"-") -> - | AT11: =SUM(МП_Periods!AI11,МП_Periods!AI126,МП_Periods!AI241,МП_Periods!AI356,МП_Periods!AI472,МП_Periods!AI587,МП_Periods!AI702,МП_Periods!AI817,МП_Periods!AI932,МП_Periods!AI1047,МП_Periods!AI1162,МП_Periods!AI1277) -> 0 | AU11: =IFERROR(AC11/AT11,"-") -> - | AW11: =IFERROR(AX11/AT11,"-") -> - | AX11: =SUM(МП_Periods!AM11,МП_Periods!AM126,МП_Periods!AM241,МП_Periods!AM356,МП_Periods!AM472,МП_Periods!AM587,МП_Periods!AM702,МП_Periods!AM817,МП_Periods!AM932,МП_Periods!AM1047,МП_Periods!AM1162,МП_Periods!AM1277,) -> 0 | AY11: =IFERROR(AC11/AX11,"-") -> - | AZ11: =IFERROR(AX11/$AX$115,"-") -> - | BB11: =IFERROR(BE11/AC11,"-") -> - | BC11: =IFERROR(AC11/BE11,"-") -> - | BD11: =IFERROR(BE11/AX11,"-") -> - | BE11: =SUM(МП_Periods!AT11,МП_Periods!AT126,МП_Periods!AT241,МП_Periods!AT356,МП_Periods!AT472,МП_Periods!AT587,МП_Periods!AT702,МП_Periods!AT817,МП_Periods!AT932,МП_Periods!AT1047,МП_Periods!AT1162,МП_Periods!AT1277) -> 0 | BF11: =IFERROR(BE11/$BE$115,"-") -> - | BH11: =IFERROR(BI11/AX11,"-") -> - | BI11: =SUM(МП_Periods!AX11,МП_Periods!AX126,МП_Periods!AX241,МП_Periods!AX356,МП_Periods!AX472,МП_Periods!AX587,МП_Periods!AX702,МП_Periods!AX817,МП_Periods!AX932,МП_Periods!AX1047,МП_Periods!AX1162,МП_Periods!AX1277) -> 0 | BJ11: =IFERROR(AC11/BI11,"-") -> - | BK11: =IFERROR(BI11/$AX$115,"-") -> - | BM11: =IFERROR(BP11/AC11,"-") -> - | BN11: =IFERROR(AC11/BP11,"-") -> - | BO11: =IFERROR(BP11/BI11,"-") -> - | BP11: =SUM(МП_Periods!BE11,МП_Periods!BE126,МП_Periods!BE241,МП_Periods!BE356,МП_Periods!BE472,МП_Periods!BE587,МП_Periods!BE702,МП_Periods!BE817,МП_Periods!BE932,МП_Periods!BE1047,МП_Periods!BE1162,МП_Periods!BE1277) -> 0 | BQ11: =IFERROR(BP11/$BP$115,"-") -> -
S12: CPC | T12: =IFERROR(W12/U12,"-") -> - | U12: =SUM(МП_Periods!J12,МП_Periods!J127,МП_Periods!J242,МП_Periods!J357,МП_Periods!J473,МП_Periods!J588,МП_Periods!J703,МП_Periods!J818,МП_Periods!J933,МП_Periods!J1048,МП_Periods!J1163,МП_Periods!J1278) -> 0 | W12: =SUM(МП_Periods!L12,МП_Periods!L127,МП_Periods!L242,МП_Periods!L357,МП_Periods!L473,МП_Periods!L588,МП_Periods!L703,МП_Periods!L818,МП_Periods!L933,МП_Periods!L1048,МП_Periods!L1163,МП_Periods!L1278) -> 0 | Y12: =SUM(МП_Periods!N12,МП_Periods!N127,МП_Periods!N242,МП_Periods!N357,МП_Periods!N473,МП_Periods!N588,МП_Periods!N703,МП_Periods!N818,МП_Periods!N933,МП_Periods!N1048,МП_Periods!N1163,МП_Periods!N1278) -> 0 | AA12: =SUM(МП_Periods!P12,МП_Periods!P127,МП_Periods!P242,МП_Periods!P357,МП_Periods!P473,МП_Periods!P588,МП_Periods!P703,МП_Periods!P818,МП_Periods!P933,МП_Periods!P1048,МП_Periods!P1163,МП_Periods!P1278) -> 0 | AB12: =SUM(МП_Periods!Q12,МП_Periods!Q127,МП_Periods!Q242,МП_Periods!Q357,МП_Periods!Q473,МП_Periods!Q588,МП_Periods!Q703,МП_Periods!Q818,МП_Periods!Q933,МП_Periods!Q1048,МП_Periods!Q1163,МП_Periods!Q1278) -> 0 | AC12: =SUM(МП_Periods!R12,МП_Periods!R127,МП_Periods!R242,МП_Periods!R357,МП_Periods!R473,МП_Periods!R588,МП_Periods!R703,МП_Periods!R818,МП_Periods!R933,МП_Periods!R1048,МП_Periods!R1163,МП_Periods!R1278) -> 0 | AD12: =SUM(МП_Periods!S12,МП_Periods!S127,МП_Periods!S242,МП_Periods!S357,МП_Periods!S473,МП_Periods!S588,МП_Periods!S703,МП_Periods!S818,МП_Periods!S933,МП_Periods!S1048,МП_Periods!S1163,МП_Periods!S1278) -> 0 | AE12: =IFERROR(AC12/$AC$115,"-") -> - | AG12: =SUM(МП_Periods!V12,МП_Periods!V127,МП_Periods!V242,МП_Periods!V357,МП_Periods!V473,МП_Periods!V588,МП_Periods!V703,МП_Periods!V818,МП_Periods!V933,МП_Periods!V1048,МП_Periods!V1163,МП_Periods!V1278) -> 0 | AJ12: =SUM(МП_Periods!Y12,МП_Periods!Y127,МП_Periods!Y242,МП_Periods!Y357,МП_Periods!Y473,МП_Periods!Y588,МП_Periods!Y703,МП_Periods!Y818,МП_Periods!Y933,МП_Periods!Y1048,МП_Periods!Y1163,МП_Periods!Y1278) -> 0 | AK12: =SUM(МП_Periods!Z12,МП_Periods!Z127,МП_Periods!Z242,МП_Periods!Z357,МП_Periods!Z473,МП_Periods!Z588,МП_Periods!Z703,МП_Periods!Z818,МП_Periods!Z933,МП_Periods!Z1048,МП_Periods!Z1163,МП_Periods!Z1278) -> 0 | AL12: =SUM(МП_Periods!AA12,МП_Periods!AA127,МП_Periods!AA242,МП_Periods!AA357,МП_Periods!AA473,МП_Periods!AA588,МП_Periods!AA703,МП_Periods!AA818,МП_Periods!AA933,МП_Periods!AA1048,МП_Periods!AA1163,МП_Periods!AA1278) -> 0 | AM12: =SUM(МП_Periods!AB12,МП_Periods!AB127,МП_Periods!AB242,МП_Periods!AB357,МП_Periods!AB473,МП_Periods!AB588,МП_Periods!AB703,МП_Periods!AB818,МП_Periods!AB933,МП_Periods!AB1048,МП_Periods!AB1163,МП_Periods!AB1278) -> 0 | AO12: =IFERROR(AC12/AM12,"-") -> - | AP12: =SUM(МП_Periods!AE12,МП_Periods!AE127,МП_Periods!AE242,МП_Periods!AE357,МП_Periods!AE473,МП_Periods!AE588,МП_Periods!AE703,МП_Periods!AE818,МП_Periods!AE933,МП_Periods!AE1048,МП_Periods!AE1163,МП_Periods!AE1278) -> 0 | AQ12: =IFERROR(#REF!/AP12,"-") -> - | AS12: =IFERROR(U12/AG12,"-") -> - | AT12: =SUM(МП_Periods!AI12,МП_Periods!AI127,МП_Periods!AI242,МП_Periods!AI357,МП_Periods!AI473,МП_Periods!AI588,МП_Periods!AI703,МП_Periods!AI818,МП_Periods!AI933,МП_Periods!AI1048,МП_Periods!AI1163,МП_Periods!AI1278) -> 0 | AU12: =IFERROR(AC12/AT12,"-") -> - | AW12: =IFERROR(AX12/AT12,"-") -> - | AX12: =SUM(МП_Periods!AM12,МП_Periods!AM127,МП_Periods!AM242,МП_Periods!AM357,МП_Periods!AM473,МП_Periods!AM588,МП_Periods!AM703,МП_Periods!AM818,МП_Periods!AM933,МП_Periods!AM1048,МП_Periods!AM1163,МП_Periods!AM1278,) -> 0 | AY12: =IFERROR(AC12/AX12,"-") -> - | AZ12: =IFERROR(AX12/$AX$115,"-") -> - | BB12: =IFERROR(BE12/AC12,"-") -> - | BC12: =IFERROR(AC12/BE12,"-") -> - | BD12: =IFERROR(BE12/AX12,"-") -> - | BE12: =SUM(МП_Periods!AT12,МП_Periods!AT127,МП_Periods!AT242,МП_Periods!AT357,МП_Periods!AT473,МП_Periods!AT588,МП_Periods!AT703,МП_Periods!AT818,МП_Periods!AT933,МП_Periods!AT1048,МП_Periods!AT1163,МП_Periods!AT1278) -> 0 | BF12: =IFERROR(BE12/$BE$115,"-") -> - | BH12: =IFERROR(BI12/AX12,"-") -> - | BI12: =SUM(МП_Periods!AX12,МП_Periods!AX127,МП_Periods!AX242,МП_Periods!AX357,МП_Periods!AX473,МП_Periods!AX588,МП_Periods!AX703,МП_Periods!AX818,МП_Periods!AX933,МП_Periods!AX1048,МП_Periods!AX1163,МП_Periods!AX1278) -> 0 | BJ12: =IFERROR(AC12/BI12,"-") -> - | BK12: =IFERROR(BI12/$AX$115,"-") -> - | BM12: =IFERROR(BP12/AC12,"-") -> - | BN12: =IFERROR(AC12/BP12,"-") -> - | BO12: =IFERROR(BP12/BI12,"-") -> - | BP12: =SUM(МП_Periods!BE12,МП_Periods!BE127,МП_Periods!BE242,МП_Periods!BE357,МП_Periods!BE473,МП_Periods!BE588,МП_Periods!BE703,МП_Periods!BE818,МП_Periods!BE933,МП_Periods!BE1048,МП_Periods!BE1163,МП_Periods!BE1278) -> 0 | BQ12: =IFERROR(BP12/$BP$115,"-") -> -
S13: CPC | T13: =IFERROR(W13/U13,"-") -> - | U13: =SUM(МП_Periods!J13,МП_Periods!J128,МП_Periods!J243,МП_Periods!J358,МП_Periods!J474,МП_Periods!J589,МП_Periods!J704,МП_Periods!J819,МП_Periods!J934,МП_Periods!J1049,МП_Periods!J1164,МП_Periods!J1279) -> 0 | W13: =SUM(МП_Periods!L13,МП_Periods!L128,МП_Periods!L243,МП_Periods!L358,МП_Periods!L474,МП_Periods!L589,МП_Periods!L704,МП_Periods!L819,МП_Periods!L934,МП_Periods!L1049,МП_Periods!L1164,МП_Periods!L1279) -> 0 | Y13: =SUM(МП_Periods!N13,МП_Periods!N128,МП_Periods!N243,МП_Periods!N358,МП_Periods!N474,МП_Periods!N589,МП_Periods!N704,МП_Periods!N819,МП_Periods!N934,МП_Periods!N1049,МП_Periods!N1164,МП_Periods!N1279) -> 0 | AA13: =SUM(МП_Periods!P13,МП_Periods!P128,МП_Periods!P243,МП_Periods!P358,МП_Periods!P474,МП_Periods!P589,МП_Periods!P704,МП_Periods!P819,МП_Periods!P934,МП_Periods!P1049,МП_Periods!P1164,МП_Periods!P1279) -> 0 | AB13: =SUM(МП_Periods!Q13,МП_Periods!Q128,МП_Periods!Q243,МП_Periods!Q358,МП_Periods!Q474,МП_Periods!Q589,МП_Periods!Q704,МП_Periods!Q819,МП_Periods!Q934,МП_Periods!Q1049,МП_Periods!Q1164,МП_Periods!Q1279) -> 0 | AC13: =SUM(МП_Periods!R13,МП_Periods!R128,МП_Periods!R243,МП_Periods!R358,МП_Periods!R474,МП_Periods!R589,МП_Periods!R704,МП_Periods!R819,МП_Periods!R934,МП_Periods!R1049,МП_Periods!R1164,МП_Periods!R1279) -> 0 | AD13: =SUM(МП_Periods!S13,МП_Periods!S128,МП_Periods!S243,МП_Periods!S358,МП_Periods!S474,МП_Periods!S589,МП_Periods!S704,МП_Periods!S819,МП_Periods!S934,МП_Periods!S1049,МП_Periods!S1164,МП_Periods!S1279) -> 0 | AE13: =IFERROR(AC13/$AC$115,"-") -> - | AG13: =SUM(МП_Periods!V13,МП_Periods!V128,МП_Periods!V243,МП_Periods!V358,МП_Periods!V474,МП_Periods!V589,МП_Periods!V704,МП_Periods!V819,МП_Periods!V934,МП_Periods!V1049,МП_Periods!V1164,МП_Periods!V1279) -> 0 | AJ13: =SUM(МП_Periods!Y13,МП_Periods!Y128,МП_Periods!Y243,МП_Periods!Y358,МП_Periods!Y474,МП_Periods!Y589,МП_Periods!Y704,МП_Periods!Y819,МП_Periods!Y934,МП_Periods!Y1049,МП_Periods!Y1164,МП_Periods!Y1279) -> 0 | AK13: =SUM(МП_Periods!Z13,МП_Periods!Z128,МП_Periods!Z243,МП_Periods!Z358,МП_Periods!Z474,МП_Periods!Z589,МП_Periods!Z704,МП_Periods!Z819,МП_Periods!Z934,МП_Periods!Z1049,МП_Periods!Z1164,МП_Periods!Z1279) -> 0 | AL13: =SUM(МП_Periods!AA13,МП_Periods!AA128,МП_Periods!AA243,МП_Periods!AA358,МП_Periods!AA474,МП_Periods!AA589,МП_Periods!AA704,МП_Periods!AA819,МП_Periods!AA934,МП_Periods!AA1049,МП_Periods!AA1164,МП_Periods!AA1279) -> 0 | AM13: =SUM(МП_Periods!AB13,МП_Periods!AB128,МП_Periods!AB243,МП_Periods!AB358,МП_Periods!AB474,МП_Periods!AB589,МП_Periods!AB704,МП_Periods!AB819,МП_Periods!AB934,МП_Periods!AB1049,МП_Periods!AB1164,МП_Periods!AB1279) -> 0 | AO13: =IFERROR(AC13/AM13,"-") -> - | AP13: =SUM(МП_Periods!AE13,МП_Periods!AE128,МП_Periods!AE243,МП_Periods!AE358,МП_Periods!AE474,МП_Periods!AE589,МП_Periods!AE704,МП_Periods!AE819,МП_Periods!AE934,МП_Periods!AE1049,МП_Periods!AE1164,МП_Periods!AE1279) -> 0 | AQ13: =IFERROR(#REF!/AP13,"-") -> - | AS13: =IFERROR(U13/AG13,"-") -> - | AT13: =SUM(МП_Periods!AI13,МП_Periods!AI128,МП_Periods!AI243,МП_Periods!AI358,МП_Periods!AI474,МП_Periods!AI589,МП_Periods!AI704,МП_Periods!AI819,МП_Periods!AI934,МП_Periods!AI1049,МП_Periods!AI1164,МП_Periods!AI1279) -> 0 | AU13: =IFERROR(AC13/AT13,"-") -> - | AW13: =IFERROR(AX13/AT13,"-") -> - | AX13: =SUM(МП_Periods!AM13,МП_Periods!AM128,МП_Periods!AM243,МП_Periods!AM358,МП_Periods!AM474,МП_Periods!AM589,МП_Periods!AM704,МП_Periods!AM819,МП_Periods!AM934,МП_Periods!AM1049,МП_Periods!AM1164,МП_Periods!AM1279,) -> 0 | AY13: =IFERROR(AC13/AX13,"-") -> - | AZ13: =IFERROR(AX13/$AX$115,"-") -> - | BB13: =IFERROR(BE13/AC13,"-") -> - | BC13: =IFERROR(AC13/BE13,"-") -> - | BD13: =IFERROR(BE13/AX13,"-") -> - | BE13: =SUM(МП_Periods!AT13,МП_Periods!AT128,МП_Periods!AT243,МП_Periods!AT358,МП_Periods!AT474,МП_Periods!AT589,МП_Periods!AT704,МП_Periods!AT819,МП_Periods!AT934,МП_Periods!AT1049,МП_Periods!AT1164,МП_Periods!AT1279) -> 0 | BF13: =IFERROR(BE13/$BE$115,"-") -> - | BH13: =IFERROR(BI13/AX13,"-") -> - | BI13: =SUM(МП_Periods!AX13,МП_Periods!AX128,МП_Periods!AX243,МП_Periods!AX358,МП_Periods!AX474,МП_Periods!AX589,МП_Periods!AX704,МП_Periods!AX819,МП_Periods!AX934,МП_Periods!AX1049,МП_Periods!AX1164,МП_Periods!AX1279) -> 0 | BJ13: =IFERROR(AC13/BI13,"-") -> - | BK13: =IFERROR(BI13/$AX$115,"-") -> - | BM13: =IFERROR(BP13/AC13,"-") -> - | BN13: =IFERROR(AC13/BP13,"-") -> - | BO13: =IFERROR(BP13/BI13,"-") -> - | BP13: =SUM(МП_Periods!BE13,МП_Periods!BE128,МП_Periods!BE243,МП_Periods!BE358,МП_Periods!BE474,МП_Periods!BE589,МП_Periods!BE704,МП_Periods!BE819,МП_Periods!BE934,МП_Periods!BE1049,МП_Periods!BE1164,МП_Periods!BE1279) -> 0 | BQ13: =IFERROR(BP13/$BP$115,"-") -> -
S14: CPC | T14: =IFERROR(W14/U14,"-") -> - | U14: =SUM(МП_Periods!J14,МП_Periods!J129,МП_Periods!J244,МП_Periods!J359,МП_Periods!J475,МП_Periods!J590,МП_Periods!J705,МП_Periods!J820,МП_Periods!J935,МП_Periods!J1050,МП_Periods!J1165,МП_Periods!J1280) -> 0 | W14: =SUM(МП_Periods!L14,МП_Periods!L129,МП_Periods!L244,МП_Periods!L359,МП_Periods!L475,МП_Periods!L590,МП_Periods!L705,МП_Periods!L820,МП_Periods!L935,МП_Periods!L1050,МП_Periods!L1165,МП_Periods!L1280) -> 0 | Y14: =SUM(МП_Periods!N14,МП_Periods!N129,МП_Periods!N244,МП_Periods!N359,МП_Periods!N475,МП_Periods!N590,МП_Periods!N705,МП_Periods!N820,МП_Periods!N935,МП_Periods!N1050,МП_Periods!N1165,МП_Periods!N1280) -> 0 | AA14: =SUM(МП_Periods!P14,МП_Periods!P129,МП_Periods!P244,МП_Periods!P359,МП_Periods!P475,МП_Periods!P590,МП_Periods!P705,МП_Periods!P820,МП_Periods!P935,МП_Periods!P1050,МП_Periods!P1165,МП_Periods!P1280) -> 0 | AB14: =SUM(МП_Periods!Q14,МП_Periods!Q129,МП_Periods!Q244,МП_Periods!Q359,МП_Periods!Q475,МП_Periods!Q590,МП_Periods!Q705,МП_Periods!Q820,МП_Periods!Q935,МП_Periods!Q1050,МП_Periods!Q1165,МП_Periods!Q1280) -> 0 | AC14: =SUM(МП_Periods!R14,МП_Periods!R129,МП_Periods!R244,МП_Periods!R359,МП_Periods!R475,МП_Periods!R590,МП_Periods!R705,МП_Periods!R820,МП_Periods!R935,МП_Periods!R1050,МП_Periods!R1165,МП_Periods!R1280) -> 0 | AD14: =SUM(МП_Periods!S14,МП_Periods!S129,МП_Periods!S244,МП_Periods!S359,МП_Periods!S475,МП_Periods!S590,МП_Periods!S705,МП_Periods!S820,МП_Periods!S935,МП_Periods!S1050,МП_Periods!S1165,МП_Periods!S1280) -> 0 | AE14: =IFERROR(AC14/$AC$115,"-") -> - | AG14: =SUM(МП_Periods!V14,МП_Periods!V129,МП_Periods!V244,МП_Periods!V359,МП_Periods!V475,МП_Periods!V590,МП_Periods!V705,МП_Periods!V820,МП_Periods!V935,МП_Periods!V1050,МП_Periods!V1165,МП_Periods!V1280) -> 0 | AJ14: =SUM(МП_Periods!Y14,МП_Periods!Y129,МП_Periods!Y244,МП_Periods!Y359,МП_Periods!Y475,МП_Periods!Y590,МП_Periods!Y705,МП_Periods!Y820,МП_Periods!Y935,МП_Periods!Y1050,МП_Periods!Y1165,МП_Periods!Y1280) -> 0 | AK14: =SUM(МП_Periods!Z14,МП_Periods!Z129,МП_Periods!Z244,МП_Periods!Z359,МП_Periods!Z475,МП_Periods!Z590,МП_Periods!Z705,МП_Periods!Z820,МП_Periods!Z935,МП_Periods!Z1050,МП_Periods!Z1165,МП_Periods!Z1280) -> 0 | AL14: =SUM(МП_Periods!AA14,МП_Periods!AA129,МП_Periods!AA244,МП_Periods!AA359,МП_Periods!AA475,МП_Periods!AA590,МП_Periods!AA705,МП_Periods!AA820,МП_Periods!AA935,МП_Periods!AA1050,МП_Periods!AA1165,МП_Periods!AA1280) -> 0 | AM14: =SUM(МП_Periods!AB14,МП_Periods!AB129,МП_Periods!AB244,МП_Periods!AB359,МП_Periods!AB475,МП_Periods!AB590,МП_Periods!AB705,МП_Periods!AB820,МП_Periods!AB935,МП_Periods!AB1050,МП_Periods!AB1165,МП_Periods!AB1280) -> 0 | AO14: =IFERROR(AC14/AM14,"-") -> - | AP14: =SUM(МП_Periods!AE14,МП_Periods!AE129,МП_Periods!AE244,МП_Periods!AE359,МП_Periods!AE475,МП_Periods!AE590,МП_Periods!AE705,МП_Periods!AE820,МП_Periods!AE935,МП_Periods!AE1050,МП_Periods!AE1165,МП_Periods!AE1280) -> 0 | AQ14: =IFERROR(#REF!/AP14,"-") -> - | AS14: =IFERROR(U14/AG14,"-") -> - | AT14: =SUM(МП_Periods!AI14,МП_Periods!AI129,МП_Periods!AI244,МП_Periods!AI359,МП_Periods!AI475,МП_Periods!AI590,МП_Periods!AI705,МП_Periods!AI820,МП_Periods!AI935,МП_Periods!AI1050,МП_Periods!AI1165,МП_Periods!AI1280) -> 0 | AU14: =IFERROR(AC14/AT14,"-") -> - | AW14: =IFERROR(AX14/AT14,"-") -> - | AX14: =SUM(МП_Periods!AM14,МП_Periods!AM129,МП_Periods!AM244,МП_Periods!AM359,МП_Periods!AM475,МП_Periods!AM590,МП_Periods!AM705,МП_Periods!AM820,МП_Periods!AM935,МП_Periods!AM1050,МП_Periods!AM1165,МП_Periods!AM1280,) -> 0 | AY14: =IFERROR(AC14/AX14,"-") -> - | AZ14: =IFERROR(AX14/$AX$115,"-") -> - | BB14: =IFERROR(BE14/AC14,"-") -> - | BC14: =IFERROR(AC14/BE14,"-") -> - | BD14: =IFERROR(BE14/AX14,"-") -> - | BE14: =SUM(МП_Periods!AT14,МП_Periods!AT129,МП_Periods!AT244,МП_Periods!AT359,МП_Periods!AT475,МП_Periods!AT590,МП_Periods!AT705,МП_Periods!AT820,МП_Periods!AT935,МП_Periods!AT1050,МП_Periods!AT1165,МП_Periods!AT1280) -> 0 | BF14: =IFERROR(BE14/$BE$115,"-") -> - | BH14: =IFERROR(BI14/AX14,"-") -> - | BI14: =SUM(МП_Periods!AX14,МП_Periods!AX129,МП_Periods!AX244,МП_Periods!AX359,МП_Periods!AX475,МП_Periods!AX590,МП_Periods!AX705,МП_Periods!AX820,МП_Periods!AX935,МП_Periods!AX1050,МП_Periods!AX1165,МП_Periods!AX1280) -> 0 | BJ14: =IFERROR(AC14/BI14,"-") -> - | BK14: =IFERROR(BI14/$AX$115,"-") -> - | BM14: =IFERROR(BP14/AC14,"-") -> - | BN14: =IFERROR(AC14/BP14,"-") -> - | BO14: =IFERROR(BP14/BI14,"-") -> - | BP14: =SUM(МП_Periods!BE14,МП_Periods!BE129,МП_Periods!BE244,МП_Periods!BE359,МП_Periods!BE475,МП_Periods!BE590,МП_Periods!BE705,МП_Periods!BE820,МП_Periods!BE935,МП_Periods!BE1050,МП_Periods!BE1165,МП_Periods!BE1280) -> 0 | BQ14: =IFERROR(BP14/$BP$115,"-") -> -
... S57: CPC | T57: =IFERROR(W57/U57,"-") -> - | U57: =SUM(МП_Periods!J57,МП_Periods!J172,МП_Periods!J287,МП_Periods!J402,МП_Periods!J518,МП_Periods!J633,МП_Periods!J748,МП_Periods!J863,МП_Periods!J978,МП_Periods!J1093,МП_Periods!J1208,МП_Periods!J1323) -> 0 | W57: =SUM(МП_Periods!L57,МП_Periods!L172,МП_Periods!L287,МП_Periods!L402,МП_Periods!L518,МП_Periods!L633,МП_Periods!L748,МП_Periods!L863,МП_Periods!L978,МП_Periods!L1093,МП_Periods!L1208,МП_Periods!L1323) -> 0 | Y57: =SUM(МП_Periods!N57,МП_Periods!N172,МП_Periods!N287,МП_Periods!N402,МП_Periods!N518,МП_Periods!N633,МП_Periods!N748,МП_Periods!N863,МП_Periods!N978,МП_Periods!N1093,МП_Periods!N1208,МП_Periods!N1323) -> 0 | AA57: =SUM(МП_Periods!P57,МП_Periods!P172,МП_Periods!P287,МП_Periods!P402,МП_Periods!P518,МП_Periods!P633,МП_Periods!P748,МП_Periods!P863,МП_Periods!P978,МП_Periods!P1093,МП_Periods!P1208,МП_Periods!P1323) -> 0 | AB57: =SUM(МП_Periods!Q57,МП_Periods!Q172,МП_Periods!Q287,МП_Periods!Q402,МП_Periods!Q518,МП_Periods!Q633,МП_Periods!Q748,МП_Periods!Q863,МП_Periods!Q978,МП_Periods!Q1093,МП_Periods!Q1208,МП_Periods!Q1323) -> 0 | AC57: =SUM(МП_Periods!R57,МП_Periods!R172,МП_Periods!R287,МП_Periods!R402,МП_Periods!R518,МП_Periods!R633,МП_Periods!R748,МП_Periods!R863,МП_Periods!R978,МП_Periods!R1093,МП_Periods!R1208,МП_Periods!R1323) -> 0 | AD57: =SUM(МП_Periods!S57,МП_Periods!S172,МП_Periods!S287,МП_Periods!S402,МП_Periods!S518,МП_Periods!S633,МП_Periods!S748,МП_Periods!S863,МП_Periods!S978,МП_Periods!S1093,МП_Periods!S1208,МП_Periods!S1323) -> 0 | AE57: =IFERROR(AC57/$AC$115,"-") -> - | AG57: =SUM(МП_Periods!V57,МП_Periods!V172,МП_Periods!V287,МП_Periods!V402,МП_Periods!V518,МП_Periods!V633,МП_Periods!V748,МП_Periods!V863,МП_Periods!V978,МП_Periods!V1093,МП_Periods!V1208,МП_Periods!V1323) -> 0 | AJ57: =SUM(МП_Periods!Y57,МП_Periods!Y172,МП_Periods!Y287,МП_Periods!Y402,МП_Periods!Y518,МП_Periods!Y633,МП_Periods!Y748,МП_Periods!Y863,МП_Periods!Y978,МП_Periods!Y1093,МП_Periods!Y1208,МП_Periods!Y1323) -> 0 | AK57: =SUM(МП_Periods!Z57,МП_Periods!Z172,МП_Periods!Z287,МП_Periods!Z402,МП_Periods!Z518,МП_Periods!Z633,МП_Periods!Z748,МП_Periods!Z863,МП_Periods!Z978,МП_Periods!Z1093,МП_Periods!Z1208,МП_Periods!Z1323) -> 0 | AL57: =SUM(МП_Periods!AA57,МП_Periods!AA172,МП_Periods!AA287,МП_Periods!AA402,МП_Periods!AA518,МП_Periods!AA633,МП_Periods!AA748,МП_Periods!AA863,МП_Periods!AA978,МП_Periods!AA1093,МП_Periods!AA1208,МП_Periods!AA1323) -> 0 | AM57: =SUM(МП_Periods!AB57,МП_Periods!AB172,МП_Periods!AB287,МП_Periods!AB402,МП_Periods!AB518,МП_Periods!AB633,МП_Periods!AB748,МП_Periods!AB863,МП_Periods!AB978,МП_Periods!AB1093,МП_Periods!AB1208,МП_Periods!AB1323) -> 0 | AO57: =IFERROR(AC57/AM57,"-") -> - | AP57: =SUM(МП_Periods!AE57,МП_Periods!AE172,МП_Periods!AE287,МП_Periods!AE402,МП_Periods!AE518,МП_Periods!AE633,МП_Periods!AE748,МП_Periods!AE863,МП_Periods!AE978,МП_Periods!AE1093,МП_Periods!AE1208,МП_Periods!AE1323) -> 0 | AQ57: =IFERROR(#REF!/AP57,"-") -> - | AS57: =IFERROR(U57/AG57,"-") -> - | AT57: =SUM(МП_Periods!AI57,МП_Periods!AI172,МП_Periods!AI287,МП_Periods!AI402,МП_Periods!AI518,МП_Periods!AI633,МП_Periods!AI748,МП_Periods!AI863,МП_Periods!AI978,МП_Periods!AI1093,МП_Periods!AI1208,МП_Periods!AI1323) -> 0 | AU57: =IFERROR(AC57/AT57,"-") -> - | AW57: =IFERROR(AX57/AT57,"-") -> - | AX57: =SUM(МП_Periods!AM57,МП_Periods!AM172,МП_Periods!AM287,МП_Periods!AM402,МП_Periods!AM518,МП_Periods!AM633,МП_Periods!AM748,МП_Periods!AM863,МП_Periods!AM978,МП_Periods!AM1093,МП_Periods!AM1208,МП_Periods!AM1323,) -> 0 | AY57: =IFERROR(AC57/AX57,"-") -> - | AZ57: =IFERROR(AX57/$AX$115,"-") -> - | BB57: =IFERROR(BE57/AC57,"-") -> - | BC57: =IFERROR(AC57/BE57,"-") -> - | BD57: =IFERROR(BE57/AX57,"-") -> - | BE57: =SUM(МП_Periods!AT57,МП_Periods!AT172,МП_Periods!AT287,МП_Periods!AT402,МП_Periods!AT518,МП_Periods!AT633,МП_Periods!AT748,МП_Periods!AT863,МП_Periods!AT978,МП_Periods!AT1093,МП_Periods!AT1208,МП_Periods!AT1323) -> 0 | BF57: =IFERROR(BE57/$BE$115,"-") -> - | BH57: =IFERROR(BI57/AX57,"-") -> - | BI57: =SUM(МП_Periods!AX57,МП_Periods!AX172,МП_Periods!AX287,МП_Periods!AX402,МП_Periods!AX518,МП_Periods!AX633,МП_Periods!AX748,МП_Periods!AX863,МП_Periods!AX978,МП_Periods!AX1093,МП_Periods!AX1208,МП_Periods!AX1323) -> 0 | BJ57: =IFERROR(AC57/BI57,"-") -> - | BK57: =IFERROR(BI57/$AX$115,"-") -> - | BM57: =IFERROR(BP57/AC57,"-") -> - | BN57: =IFERROR(AC57/BP57,"-") -> - | BO57: =IFERROR(BP57/BI57,"-") -> - | BP57: =SUM(МП_Periods!BE57,МП_Periods!BE172,МП_Periods!BE287,МП_Periods!BE402,МП_Periods!BE518,МП_Periods!BE633,МП_Periods!BE748,МП_Periods!BE863,МП_Periods!BE978,МП_Periods!BE1093,МП_Periods!BE1208,МП_Periods!BE1323) -> 0 | BQ57: =IFERROR(BP57/$BP$115,"-") -> -
B58: ИТОГО B2C | C58: - | D58: - | F58: - | G58: - | H58: - | I58: - | J58: - | K58: - | L58: - | M58: - | N58: - | O58: - | P58: - | Q58: - | S58: - | T58: =IFERROR(W58/U58,"-") -> - | U58: =SUM(U3:U57) -> 0 | W58: =IFERROR(SUM(W3:W57),"-") -> 0 | X58: - | Y58: =IFERROR(SUM(Y3:Y57),"-") -> 0 | Z58: - | AA58: =IFERROR(AB58-Y58,"-") -> 0 | AB58: =IFERROR(SUM(AB3:AB57),"-") -> 0 | AC58: =IFERROR(SUM(AC3:AC57),"-") -> 0 | AD58: =IFERROR(AC58-AB58,"-") -> 0 | AE58: =SUM(AE3:AE57) -> 0 | AG58: =SUM(AG3:AG57) -> 0 | AH58: - | AI58: - | AJ58: =SUM(AJ3:AJ57) -> 0 | AK58: =SUM(AK3:AK57) -> 0 | AL58: =SUM(AL3:AL57) -> 0 | AM58: =SUM(AM3:AM57) -> 0 | AO58: =IFERROR(AC58/AM58,"-") -> - | AP58: - | AQ58: - | AS58: =IFERROR(AT58/AG58,"-") -> - | AT58: =SUM(AT3:AT57) -> 0 | AU58: =IFERROR(AC58/AT58,"-") -> - | AW58: =IFERROR(AX58/AT58,"-") -> - | AX58: =SUM(AX3:AX57) -> 0 | AY58: =IFERROR(AC58/AX58,"-") -> - | AZ58: =SUM(AZ3:AZ57) -> 0 | BB58: =IFERROR(BE58/AC58,"-") -> - | BC58: =IFERROR(AC58/BE58,"-") -> - | BD58: =IFERROR(BE58/AX58,"-") -> - | BE58: =IFERROR(SUM(BE3:BE57),"-") -> 0 | BF58: =SUM(BF3:BF57) -> 0 | BH58: =IFERROR(BI58/AX58,"-") -> - | BI58: =SUM(BI3:BI57) -> 0 | BJ58: =IFERROR(AC58/BI58,"-") -> - | BK58: =SUM(BK3:BK57) -> 0 | BM58: =IFERROR(BP58/AC58,"-") -> - | BN58: =IFERROR(AC58/BP58,"-") -> - | BO58: =IFERROR(BP58/BI58,"-") -> - | BP58: =SUM(BP3:BP57) -> 0 | BQ58: =SUM(BQ3:BQ57) -> 0
S59: CPC | T59: =IFERROR(W59/U59,"-") -> - | U59: =SUM(МП_Periods!J59,МП_Periods!J174,МП_Periods!J289,МП_Periods!J405,МП_Periods!J520,МП_Periods!J635,МП_Periods!J750,МП_Periods!J865,МП_Periods!J980,МП_Periods!J1095,МП_Periods!J1210,МП_Periods!J1325) -> 0 | W59: =SUM(МП_Periods!L59,МП_Periods!L174,МП_Periods!L289,МП_Periods!L405,МП_Periods!L520,МП_Periods!L635,МП_Periods!L750,МП_Periods!L865,МП_Periods!L980,МП_Periods!L1095,МП_Periods!L1210,МП_Periods!L1325) -> 0 | Y59: =SUM(МП_Periods!N59,МП_Periods!N174,МП_Periods!N289,МП_Periods!N405,МП_Periods!N520,МП_Periods!N635,МП_Periods!N750,МП_Periods!N865,МП_Periods!N980,МП_Periods!N1095,МП_Periods!N1210,МП_Periods!N1325) -> 0 | AA59: =SUM(МП_Periods!P59,МП_Periods!P174,МП_Periods!P289,МП_Periods!P405,МП_Periods!P520,МП_Periods!P635,МП_Periods!P750,МП_Periods!P865,МП_Periods!P980,МП_Periods!P1095,МП_Periods!P1210,МП_Periods!P1325) -> 0 | AB59: =SUM(МП_Periods!Q59,МП_Periods!Q174,МП_Periods!Q289,МП_Periods!Q405,МП_Periods!Q520,МП_Periods!Q635,МП_Periods!Q750,МП_Periods!Q865,МП_Periods!Q980,МП_Periods!Q1095,МП_Periods!Q1210,МП_Periods!Q1325) -> 0 | AC59: =SUM(МП_Periods!R59,МП_Periods!R174,МП_Periods!R289,МП_Periods!R405,МП_Periods!R520,МП_Periods!R635,МП_Periods!R750,МП_Periods!R865,МП_Periods!R980,МП_Periods!R1095,МП_Periods!R1210,МП_Periods!R1325) -> 0 | AD59: =SUM(МП_Periods!S59,МП_Periods!S174,МП_Periods!S289,МП_Periods!S405,МП_Periods!S520,МП_Periods!S635,МП_Periods!S750,МП_Periods!S865,МП_Periods!S980,МП_Periods!S1095,МП_Periods!S1210,МП_Periods!S1325) -> 0 | AE59: =IFERROR(AC59/$AC$115,"-") -> - | AG59: =SUM(МП_Periods!V59,МП_Periods!V174,МП_Periods!V289,МП_Periods!V405,МП_Periods!V520,МП_Periods!V635,МП_Periods!V750,МП_Periods!V865,МП_Periods!V980,МП_Periods!V1095,МП_Periods!V1210,МП_Periods!V1325) -> 0 | AJ59: =SUM(МП_Periods!Y59,МП_Periods!Y174,МП_Periods!Y289,МП_Periods!Y405,МП_Periods!Y520,МП_Periods!Y635,МП_Periods!Y750,МП_Periods!Y865,МП_Periods!Y980,МП_Periods!Y1095,МП_Periods!Y1210,МП_Periods!Y1325) -> 0 | AK59: =SUM(МП_Periods!Z59,МП_Periods!Z174,МП_Periods!Z289,МП_Periods!Z405,МП_Periods!Z520,МП_Periods!Z635,МП_Periods!Z750,МП_Periods!Z865,МП_Periods!Z980,МП_Periods!Z1095,МП_Periods!Z1210,МП_Periods!Z1325) -> 0 | AL59: =SUM(МП_Periods!AA59,МП_Periods!AA174,МП_Periods!AA289,МП_Periods!AA405,МП_Periods!AA520,МП_Periods!AA635,МП_Periods!AA750,МП_Periods!AA865,МП_Periods!AA980,МП_Periods!AA1095,МП_Periods!AA1210,МП_Periods!AA1325) -> 0 | AM59: =SUM(МП_Periods!AB59,МП_Periods!AB174,МП_Periods!AB289,МП_Periods!AB405,МП_Periods!AB520,МП_Periods!AB635,МП_Periods!AB750,МП_Periods!AB865,МП_Periods!AB980,МП_Periods!AB1095,МП_Periods!AB1210,МП_Periods!AB1325) -> 0 | AO59: =IFERROR(AC59/AM59,"-") -> - | AP59: =SUM(МП_Periods!AE59,МП_Periods!AE174,МП_Periods!AE289,МП_Periods!AE405,МП_Periods!AE520,МП_Periods!AE635,МП_Periods!AE750,МП_Periods!AE865,МП_Periods!AE980,МП_Periods!AE1095,МП_Periods!AE1210,МП_Periods!AE1325) -> 0 | AQ59: =IFERROR(#REF!/AP59,"-") -> - | AS59: =IFERROR(U59/AG59,"-") -> - | AT59: =SUM(МП_Periods!AI59,МП_Periods!AI174,МП_Periods!AI289,МП_Periods!AI405,МП_Periods!AI520,МП_Periods!AI635,МП_Periods!AI750,МП_Periods!AI865,МП_Periods!AI980,МП_Periods!AI1095,МП_Periods!AI1210,МП_Periods!AI1325) -> 0 | AU59: =IFERROR(AC59/AT59,"-") -> - | AW59: =IFERROR(AX59/AT59,"-") -> - | AX59: =SUM(МП_Periods!AM59,МП_Periods!AM174,МП_Periods!AM289,МП_Periods!AM405,МП_Periods!AM520,МП_Periods!AM635,МП_Periods!AM750,МП_Periods!AM865,МП_Periods!AM980,МП_Periods!AM1095,МП_Periods!AM1210,МП_Periods!AM1325,) -> 0 | AY59: =IFERROR(AC59/AX59,"-") -> - | AZ59: =IFERROR(AX59/$AX$115,"-") -> - | BB59: =IFERROR(BE59/AC59,"-") -> - | BC59: =IFERROR(AC59/BE59,"-") -> - | BD59: =IFERROR(BE59/AX59,"-") -> - | BE59: =SUM(МП_Periods!AT59,МП_Periods!AT174,МП_Periods!AT289,МП_Periods!AT404,МП_Periods!AT520,МП_Periods!AT635,МП_Periods!AT750,МП_Periods!AT865,МП_Periods!AT980,МП_Periods!AT1095,МП_Periods!AT1210,МП_Periods!AT1325) -> 0 | BF59: =IFERROR(BE59/$BE$115,"-") -> - | BH59: =IFERROR(BI59/AX59,"-") -> - | BI59: =SUM(МП_Periods!AX59,МП_Periods!AX174,МП_Periods!AX289,МП_Periods!AX405,МП_Periods!AX520,МП_Periods!AX635,МП_Periods!AX750,МП_Periods!AX865,МП_Periods!AX980,МП_Periods!AX1095,МП_Periods!AX1210,МП_Periods!AX1325) -> 0 | BJ59: =IFERROR(AC59/BI59,"-") -> - | BK59: =IFERROR(BI59/$AX$115,"-") -> - | BM59: =IFERROR(BP59/AC59,"-") -> - | BN59: =IFERROR(AC59/BP59,"-") -> - | BO59: =IFERROR(BP59/BI59,"-") -> - | BP59: =SUM(МП_Periods!BE59,МП_Periods!BE174,МП_Periods!BE289,МП_Periods!BE405,МП_Periods!BE520,МП_Periods!BE635,МП_Periods!BE750,МП_Periods!BE865,МП_Periods!BE980,МП_Periods!BE1095,МП_Periods!BE1210,МП_Periods!BE1325) -> 0 | BQ59: =IFERROR(BP59/$BP$115,"-") -> -
S60: CPC | T60: =IFERROR(W60/U60,"-") -> - | U60: =SUM(МП_Periods!J60,МП_Periods!J175,МП_Periods!J290,МП_Periods!J406,МП_Periods!J521,МП_Periods!J636,МП_Periods!J751,МП_Periods!J866,МП_Periods!J981,МП_Periods!J1096,МП_Periods!J1211,МП_Periods!J1326) -> 0 | W60: =SUM(МП_Periods!L60,МП_Periods!L175,МП_Periods!L290,МП_Periods!L406,МП_Periods!L521,МП_Periods!L636,МП_Periods!L751,МП_Periods!L866,МП_Periods!L981,МП_Periods!L1096,МП_Periods!L1211,МП_Periods!L1326) -> 0 | Y60: =SUM(МП_Periods!N60,МП_Periods!N175,МП_Periods!N290,МП_Periods!N406,МП_Periods!N521,МП_Periods!N636,МП_Periods!N751,МП_Periods!N866,МП_Periods!N981,МП_Periods!N1096,МП_Periods!N1211,МП_Periods!N1326) -> 0 | AA60: =SUM(МП_Periods!P60,МП_Periods!P175,МП_Periods!P290,МП_Periods!P406,МП_Periods!P521,МП_Periods!P636,МП_Periods!P751,МП_Periods!P866,МП_Periods!P981,МП_Periods!P1096,МП_Periods!P1211,МП_Periods!P1326) -> 0 | AB60: =SUM(МП_Periods!Q60,МП_Periods!Q175,МП_Periods!Q290,МП_Periods!Q406,МП_Periods!Q521,МП_Periods!Q636,МП_Periods!Q751,МП_Periods!Q866,МП_Periods!Q981,МП_Periods!Q1096,МП_Periods!Q1211,МП_Periods!Q1326) -> 0 | AC60: =SUM(МП_Periods!R60,МП_Periods!R175,МП_Periods!R290,МП_Periods!R406,МП_Periods!R521,МП_Periods!R636,МП_Periods!R751,МП_Periods!R866,МП_Periods!R981,МП_Periods!R1096,МП_Periods!R1211,МП_Periods!R1326) -> 0 | AD60: =SUM(МП_Periods!S60,МП_Periods!S175,МП_Periods!S290,МП_Periods!S406,МП_Periods!S521,МП_Periods!S636,МП_Periods!S751,МП_Periods!S866,МП_Periods!S981,МП_Periods!S1096,МП_Periods!S1211,МП_Periods!S1326) -> 0 | AE60: =IFERROR(AC60/$AC$115,"-") -> - | AG60: =SUM(МП_Periods!V60,МП_Periods!V175,МП_Periods!V290,МП_Periods!V406,МП_Periods!V521,МП_Periods!V636,МП_Periods!V751,МП_Periods!V866,МП_Periods!V981,МП_Periods!V1096,МП_Periods!V1211,МП_Periods!V1326) -> 0 | AJ60: =SUM(МП_Periods!Y60,МП_Periods!Y175,МП_Periods!Y290,МП_Periods!Y406,МП_Periods!Y521,МП_Periods!Y636,МП_Periods!Y751,МП_Periods!Y866,МП_Periods!Y981,МП_Periods!Y1096,МП_Periods!Y1211,МП_Periods!Y1326) -> 0 | AK60: =SUM(МП_Periods!Z60,МП_Periods!Z175,МП_Periods!Z290,МП_Periods!Z406,МП_Periods!Z521,МП_Periods!Z636,МП_Periods!Z751,МП_Periods!Z866,МП_Periods!Z981,МП_Periods!Z1096,МП_Periods!Z1211,МП_Periods!Z1326) -> 0 | AL60: =SUM(МП_Periods!AA60,МП_Periods!AA175,МП_Periods!AA290,МП_Periods!AA406,МП_Periods!AA521,МП_Periods!AA636,МП_Periods!AA751,МП_Periods!AA866,МП_Periods!AA981,МП_Periods!AA1096,МП_Periods!AA1211,МП_Periods!AA1326) -> 0 | AM60: =SUM(МП_Periods!AB60,МП_Periods!AB175,МП_Periods!AB290,МП_Periods!AB406,МП_Periods!AB521,МП_Periods!AB636,МП_Periods!AB751,МП_Periods!AB866,МП_Periods!AB981,МП_Periods!AB1096,МП_Periods!AB1211,МП_Periods!AB1326) -> 0 | AO60: =IFERROR(AC60/AM60,"-") -> - | AP60: =SUM(МП_Periods!AE60,МП_Periods!AE175,МП_Periods!AE290,МП_Periods!AE406,МП_Periods!AE521,МП_Periods!AE636,МП_Periods!AE751,МП_Periods!AE866,МП_Periods!AE981,МП_Periods!AE1096,МП_Periods!AE1211,МП_Periods!AE1326) -> 0 | AQ60: =IFERROR(#REF!/AP60,"-") -> - | AS60: =IFERROR(U60/AG60,"-") -> - | AT60: =SUM(МП_Periods!AI60,МП_Periods!AI175,МП_Periods!AI290,МП_Periods!AI406,МП_Periods!AI521,МП_Periods!AI636,МП_Periods!AI751,МП_Periods!AI866,МП_Periods!AI981,МП_Periods!AI1096,МП_Periods!AI1211,МП_Periods!AI1326) -> 0 | AU60: =IFERROR(AC60/AT60,"-") -> - | AW60: =IFERROR(AX60/AT60,"-") -> - | AX60: =SUM(МП_Periods!AM60,МП_Periods!AM175,МП_Periods!AM290,МП_Periods!AM406,МП_Periods!AM521,МП_Periods!AM636,МП_Periods!AM751,МП_Periods!AM866,МП_Periods!AM981,МП_Periods!AM1096,МП_Periods!AM1211,МП_Periods!AM1326,) -> 0 | AY60: =IFERROR(AC60/AX60,"-") -> - | AZ60: =IFERROR(AX60/$AX$115,"-") -> - | BB60: =IFERROR(BE60/AC60,"-") -> - | BC60: =IFERROR(AC60/BE60,"-") -> - | BD60: =IFERROR(BE60/AX60,"-") -> - | BE60: =SUM(МП_Periods!AT60,МП_Periods!AT175,МП_Periods!AT290,МП_Periods!AT405,МП_Periods!AT521,МП_Periods!AT636,МП_Periods!AT751,МП_Periods!AT866,МП_Periods!AT981,МП_Periods!AT1096,МП_Periods!AT1211,МП_Periods!AT1326) -> 0 | BF60: =IFERROR(BE60/$BE$115,"-") -> - | BH60: =IFERROR(BI60/AX60,"-") -> - | BI60: =SUM(МП_Periods!AX60,МП_Periods!AX175,МП_Periods!AX290,МП_Periods!AX406,МП_Periods!AX521,МП_Periods!AX636,МП_Periods!AX751,МП_Periods!AX866,МП_Periods!AX981,МП_Periods!AX1096,МП_Periods!AX1211,МП_Periods!AX1326) -> 0 | BJ60: =IFERROR(AC60/BI60,"-") -> - | BK60: =IFERROR(BI60/$AX$115,"-") -> - | BM60: =IFERROR(BP60/AC60,"-") -> - | BN60: =IFERROR(AC60/BP60,"-") -> - | BO60: =IFERROR(BP60/BI60,"-") -> - | BP60: =SUM(МП_Periods!BE60,МП_Periods!BE175,МП_Periods!BE290,МП_Periods!BE406,МП_Periods!BE521,МП_Periods!BE636,МП_Periods!BE751,МП_Periods!BE866,МП_Periods!BE981,МП_Periods!BE1096,МП_Periods!BE1211,МП_Periods!BE1326) -> 0 | BQ60: =IFERROR(BP60/$BP$115,"-") -> -
S61: CPC | T61: =IFERROR(W61/U61,"-") -> - | U61: =SUM(МП_Periods!J61,МП_Periods!J176,МП_Periods!J291,МП_Periods!J407,МП_Periods!J522,МП_Periods!J637,МП_Periods!J752,МП_Periods!J867,МП_Periods!J982,МП_Periods!J1097,МП_Periods!J1212,МП_Periods!J1327) -> 0 | W61: =SUM(МП_Periods!L61,МП_Periods!L176,МП_Periods!L291,МП_Periods!L407,МП_Periods!L522,МП_Periods!L637,МП_Periods!L752,МП_Periods!L867,МП_Periods!L982,МП_Periods!L1097,МП_Periods!L1212,МП_Periods!L1327) -> 0 | Y61: =SUM(МП_Periods!N61,МП_Periods!N176,МП_Periods!N291,МП_Periods!N407,МП_Periods!N522,МП_Periods!N637,МП_Periods!N752,МП_Periods!N867,МП_Periods!N982,МП_Periods!N1097,МП_Periods!N1212,МП_Periods!N1327) -> 0 | AA61: =SUM(МП_Periods!P61,МП_Periods!P176,МП_Periods!P291,МП_Periods!P407,МП_Periods!P522,МП_Periods!P637,МП_Periods!P752,МП_Periods!P867,МП_Periods!P982,МП_Periods!P1097,МП_Periods!P1212,МП_Periods!P1327) -> 0 | AB61: =SUM(МП_Periods!Q61,МП_Periods!Q176,МП_Periods!Q291,МП_Periods!Q407,МП_Periods!Q522,МП_Periods!Q637,МП_Periods!Q752,МП_Periods!Q867,МП_Periods!Q982,МП_Periods!Q1097,МП_Periods!Q1212,МП_Periods!Q1327) -> 0 | AC61: =SUM(МП_Periods!R61,МП_Periods!R176,МП_Periods!R291,МП_Periods!R407,МП_Periods!R522,МП_Periods!R637,МП_Periods!R752,МП_Periods!R867,МП_Periods!R982,МП_Periods!R1097,МП_Periods!R1212,МП_Periods!R1327) -> 0 | AD61: =SUM(МП_Periods!S61,МП_Periods!S176,МП_Periods!S291,МП_Periods!S407,МП_Periods!S522,МП_Periods!S637,МП_Periods!S752,МП_Periods!S867,МП_Periods!S982,МП_Periods!S1097,МП_Periods!S1212,МП_Periods!S1327) -> 0 | AE61: =IFERROR(AC61/$AC$115,"-") -> - | AG61: =SUM(МП_Periods!V61,МП_Periods!V176,МП_Periods!V291,МП_Periods!V407,МП_Periods!V522,МП_Periods!V637,МП_Periods!V752,МП_Periods!V867,МП_Periods!V982,МП_Periods!V1097,МП_Periods!V1212,МП_Periods!V1327) -> 0 | AJ61: =SUM(МП_Periods!Y61,МП_Periods!Y176,МП_Periods!Y291,МП_Periods!Y407,МП_Periods!Y522,МП_Periods!Y637,МП_Periods!Y752,МП_Periods!Y867,МП_Periods!Y982,МП_Periods!Y1097,МП_Periods!Y1212,МП_Periods!Y1327) -> 0 | AK61: =SUM(МП_Periods!Z61,МП_Periods!Z176,МП_Periods!Z291,МП_Periods!Z407,МП_Periods!Z522,МП_Periods!Z637,МП_Periods!Z752,МП_Periods!Z867,МП_Periods!Z982,МП_Periods!Z1097,МП_Periods!Z1212,МП_Periods!Z1327) -> 0 | AL61: =SUM(МП_Periods!AA61,МП_Periods!AA176,МП_Periods!AA291,МП_Periods!AA407,МП_Periods!AA522,МП_Periods!AA637,МП_Periods!AA752,МП_Periods!AA867,МП_Periods!AA982,МП_Periods!AA1097,МП_Periods!AA1212,МП_Periods!AA1327) -> 0 | AM61: =SUM(МП_Periods!AB61,МП_Periods!AB176,МП_Periods!AB291,МП_Periods!AB407,МП_Periods!AB522,МП_Periods!AB637,МП_Periods!AB752,МП_Periods!AB867,МП_Periods!AB982,МП_Periods!AB1097,МП_Periods!AB1212,МП_Periods!AB1327) -> 0 | AO61: =IFERROR(AC61/AM61,"-") -> - | AP61: =SUM(МП_Periods!AE61,МП_Periods!AE176,МП_Periods!AE291,МП_Periods!AE407,МП_Periods!AE522,МП_Periods!AE637,МП_Periods!AE752,МП_Periods!AE867,МП_Periods!AE982,МП_Periods!AE1097,МП_Periods!AE1212,МП_Periods!AE1327) -> 0 | AQ61: =IFERROR(#REF!/AP61,"-") -> - | AS61: =IFERROR(U61/AG61,"-") -> - | AT61: =SUM(МП_Periods!AI61,МП_Periods!AI176,МП_Periods!AI291,МП_Periods!AI407,МП_Periods!AI522,МП_Periods!AI637,МП_Periods!AI752,МП_Periods!AI867,МП_Periods!AI982,МП_Periods!AI1097,МП_Periods!AI1212,МП_Periods!AI1327) -> 0 | AU61: =IFERROR(AC61/AT61,"-") -> - | AW61: =IFERROR(AX61/AT61,"-") -> - | AX61: =SUM(МП_Periods!AM61,МП_Periods!AM176,МП_Periods!AM291,МП_Periods!AM407,МП_Periods!AM522,МП_Periods!AM637,МП_Periods!AM752,МП_Periods!AM867,МП_Periods!AM982,МП_Periods!AM1097,МП_Periods!AM1212,МП_Periods!AM1327,) -> 0 | AY61: =IFERROR(AC61/AX61,"-") -> - | AZ61: =IFERROR(AX61/$AX$115,"-") -> - | BB61: =IFERROR(BE61/AC61,"-") -> - | BC61: =IFERROR(AC61/BE61,"-") -> - | BD61: =IFERROR(BE61/AX61,"-") -> - | BE61: =SUM(МП_Periods!AT61,МП_Periods!AT176,МП_Periods!AT291,МП_Periods!AT406,МП_Periods!AT522,МП_Periods!AT637,МП_Periods!AT752,МП_Periods!AT867,МП_Periods!AT982,МП_Periods!AT1097,МП_Periods!AT1212,МП_Periods!AT1327) -> 0 | BF61: =IFERROR(BE61/$BE$115,"-") -> - | BH61: =IFERROR(BI61/AX61,"-") -> - | BI61: =SUM(МП_Periods!AX61,МП_Periods!AX176,МП_Periods!AX291,МП_Periods!AX407,МП_Periods!AX522,МП_Periods!AX637,МП_Periods!AX752,МП_Periods!AX867,МП_Periods!AX982,МП_Periods!AX1097,МП_Periods!AX1212,МП_Periods!AX1327) -> 0 | BJ61: =IFERROR(AC61/BI61,"-") -> - | BK61: =IFERROR(BI61/$AX$115,"-") -> - | BM61: =IFERROR(BP61/AC61,"-") -> - | BN61: =IFERROR(AC61/BP61,"-") -> - | BO61: =IFERROR(BP61/BI61,"-") -> - | BP61: =SUM(МП_Periods!BE61,МП_Periods!BE176,МП_Periods!BE291,МП_Periods!BE407,МП_Periods!BE522,МП_Periods!BE637,МП_Periods!BE752,МП_Periods!BE867,МП_Periods!BE982,МП_Periods!BE1097,МП_Periods!BE1212,МП_Periods!BE1327) -> 0 | BQ61: =IFERROR(BP61/$BP$115,"-") -> -
S62: CPC | T62: =IFERROR(W62/U62,"-") -> - | U62: =SUM(МП_Periods!J62,МП_Periods!J177,МП_Periods!J292,МП_Periods!J408,МП_Periods!J523,МП_Periods!J638,МП_Periods!J753,МП_Periods!J868,МП_Periods!J983,МП_Periods!J1098,МП_Periods!J1213,МП_Periods!J1328) -> 0 | W62: =SUM(МП_Periods!L62,МП_Periods!L177,МП_Periods!L292,МП_Periods!L408,МП_Periods!L523,МП_Periods!L638,МП_Periods!L753,МП_Periods!L868,МП_Periods!L983,МП_Periods!L1098,МП_Periods!L1213,МП_Periods!L1328) -> 0 | Y62: =SUM(МП_Periods!N62,МП_Periods!N177,МП_Periods!N292,МП_Periods!N408,МП_Periods!N523,МП_Periods!N638,МП_Periods!N753,МП_Periods!N868,МП_Periods!N983,МП_Periods!N1098,МП_Periods!N1213,МП_Periods!N1328) -> 0 | AA62: =SUM(МП_Periods!P62,МП_Periods!P177,МП_Periods!P292,МП_Periods!P408,МП_Periods!P523,МП_Periods!P638,МП_Periods!P753,МП_Periods!P868,МП_Periods!P983,МП_Periods!P1098,МП_Periods!P1213,МП_Periods!P1328) -> 0 | AB62: =SUM(МП_Periods!Q62,МП_Periods!Q177,МП_Periods!Q292,МП_Periods!Q408,МП_Periods!Q523,МП_Periods!Q638,МП_Periods!Q753,МП_Periods!Q868,МП_Periods!Q983,МП_Periods!Q1098,МП_Periods!Q1213,МП_Periods!Q1328) -> 0 | AC62: =SUM(МП_Periods!R62,МП_Periods!R177,МП_Periods!R292,МП_Periods!R408,МП_Periods!R523,МП_Periods!R638,МП_Periods!R753,МП_Periods!R868,МП_Periods!R983,МП_Periods!R1098,МП_Periods!R1213,МП_Periods!R1328) -> 0 | AD62: =SUM(МП_Periods!S62,МП_Periods!S177,МП_Periods!S292,МП_Periods!S408,МП_Periods!S523,МП_Periods!S638,МП_Periods!S753,МП_Periods!S868,МП_Periods!S983,МП_Periods!S1098,МП_Periods!S1213,МП_Periods!S1328) -> 0 | AE62: =IFERROR(AC62/$AC$115,"-") -> - | AG62: =SUM(МП_Periods!V62,МП_Periods!V177,МП_Periods!V292,МП_Periods!V408,МП_Periods!V523,МП_Periods!V638,МП_Periods!V753,МП_Periods!V868,МП_Periods!V983,МП_Periods!V1098,МП_Periods!V1213,МП_Periods!V1328) -> 0 | AJ62: =SUM(МП_Periods!Y62,МП_Periods!Y177,МП_Periods!Y292,МП_Periods!Y408,МП_Periods!Y523,МП_Periods!Y638,МП_Periods!Y753,МП_Periods!Y868,МП_Periods!Y983,МП_Periods!Y1098,МП_Periods!Y1213,МП_Periods!Y1328) -> 0 | AK62: =SUM(МП_Periods!Z62,МП_Periods!Z177,МП_Periods!Z292,МП_Periods!Z408,МП_Periods!Z523,МП_Periods!Z638,МП_Periods!Z753,МП_Periods!Z868,МП_Periods!Z983,МП_Periods!Z1098,МП_Periods!Z1213,МП_Periods!Z1328) -> 0 | AL62: =SUM(МП_Periods!AA62,МП_Periods!AA177,МП_Periods!AA292,МП_Periods!AA408,МП_Periods!AA523,МП_Periods!AA638,МП_Periods!AA753,МП_Periods!AA868,МП_Periods!AA983,МП_Periods!AA1098,МП_Periods!AA1213,МП_Periods!AA1328) -> 0 | AM62: =SUM(МП_Periods!AB62,МП_Periods!AB177,МП_Periods!AB292,МП_Periods!AB408,МП_Periods!AB523,МП_Periods!AB638,МП_Periods!AB753,МП_Periods!AB868,МП_Periods!AB983,МП_Periods!AB1098,МП_Periods!AB1213,МП_Periods!AB1328) -> 0 | AO62: =IFERROR(AC62/AM62,"-") -> - | AP62: =SUM(МП_Periods!AE62,МП_Periods!AE177,МП_Periods!AE292,МП_Periods!AE408,МП_Periods!AE523,МП_Periods!AE638,МП_Periods!AE753,МП_Periods!AE868,МП_Periods!AE983,МП_Periods!AE1098,МП_Periods!AE1213,МП_Periods!AE1328) -> 0 | AQ62: =IFERROR(#REF!/AP62,"-") -> - | AS62: =IFERROR(U62/AG62,"-") -> - | AT62: =SUM(МП_Periods!AI62,МП_Periods!AI177,МП_Periods!AI292,МП_Periods!AI408,МП_Periods!AI523,МП_Periods!AI638,МП_Periods!AI753,МП_Periods!AI868,МП_Periods!AI983,МП_Periods!AI1098,МП_Periods!AI1213,МП_Periods!AI1328) -> 0 | AU62: =IFERROR(AC62/AT62,"-") -> - | AW62: =IFERROR(AX62/AT62,"-") -> - | AX62: =SUM(МП_Periods!AM62,МП_Periods!AM177,МП_Periods!AM292,МП_Periods!AM408,МП_Periods!AM523,МП_Periods!AM638,МП_Periods!AM753,МП_Periods!AM868,МП_Periods!AM983,МП_Periods!AM1098,МП_Periods!AM1213,МП_Periods!AM1328,) -> 0 | AY62: =IFERROR(AC62/AX62,"-") -> - | AZ62: =IFERROR(AX62/$AX$115,"-") -> - | BB62: =IFERROR(BE62/AC62,"-") -> - | BC62: =IFERROR(AC62/BE62,"-") -> - | BD62: =IFERROR(BE62/AX62,"-") -> - | BE62: =SUM(МП_Periods!AT62,МП_Periods!AT177,МП_Periods!AT292,МП_Periods!AT407,МП_Periods!AT523,МП_Periods!AT638,МП_Periods!AT753,МП_Periods!AT868,МП_Periods!AT983,МП_Periods!AT1098,МП_Periods!AT1213,МП_Periods!AT1328) -> 0 | BF62: =IFERROR(BE62/$BE$115,"-") -> - | BH62: =IFERROR(BI62/AX62,"-") -> - | BI62: =SUM(МП_Periods!AX62,МП_Periods!AX177,МП_Periods!AX292,МП_Periods!AX408,МП_Periods!AX523,МП_Periods!AX638,МП_Periods!AX753,МП_Periods!AX868,МП_Periods!AX983,МП_Periods!AX1098,МП_Periods!AX1213,МП_Periods!AX1328) -> 0 | BJ62: =IFERROR(AC62/BI62,"-") -> - | BK62: =IFERROR(BI62/$AX$115,"-") -> - | BM62: =IFERROR(BP62/AC62,"-") -> - | BN62: =IFERROR(AC62/BP62,"-") -> - | BO62: =IFERROR(BP62/BI62,"-") -> - | BP62: =SUM(МП_Periods!BE62,МП_Periods!BE177,МП_Periods!BE292,МП_Periods!BE408,МП_Periods!BE523,МП_Periods!BE638,МП_Periods!BE753,МП_Periods!BE868,МП_Periods!BE983,МП_Periods!BE1098,МП_Periods!BE1213,МП_Periods!BE1328) -> 0 | BQ62: =IFERROR(BP62/$BP$115,"-") -> -
S63: CPC | T63: =IFERROR(W63/U63,"-") -> - | U63: =SUM(МП_Periods!J63,МП_Periods!J178,МП_Periods!J293,МП_Periods!J409,МП_Periods!J524,МП_Periods!J639,МП_Periods!J754,МП_Periods!J869,МП_Periods!J984,МП_Periods!J1099,МП_Periods!J1214,МП_Periods!J1329) -> 0 | W63: =SUM(МП_Periods!L63,МП_Periods!L178,МП_Periods!L293,МП_Periods!L409,МП_Periods!L524,МП_Periods!L639,МП_Periods!L754,МП_Periods!L869,МП_Periods!L984,МП_Periods!L1099,МП_Periods!L1214,МП_Periods!L1329) -> 0 | Y63: =SUM(МП_Periods!N63,МП_Periods!N178,МП_Periods!N293,МП_Periods!N409,МП_Periods!N524,МП_Periods!N639,МП_Periods!N754,МП_Periods!N869,МП_Periods!N984,МП_Periods!N1099,МП_Periods!N1214,МП_Periods!N1329) -> 0 | AA63: =SUM(МП_Periods!P63,МП_Periods!P178,МП_Periods!P293,МП_Periods!P409,МП_Periods!P524,МП_Periods!P639,МП_Periods!P754,МП_Periods!P869,МП_Periods!P984,МП_Periods!P1099,МП_Periods!P1214,МП_Periods!P1329) -> 0 | AB63: =SUM(МП_Periods!Q63,МП_Periods!Q178,МП_Periods!Q293,МП_Periods!Q409,МП_Periods!Q524,МП_Periods!Q639,МП_Periods!Q754,МП_Periods!Q869,МП_Periods!Q984,МП_Periods!Q1099,МП_Periods!Q1214,МП_Periods!Q1329) -> 0 | AC63: =SUM(МП_Periods!R63,МП_Periods!R178,МП_Periods!R293,МП_Periods!R409,МП_Periods!R524,МП_Periods!R639,МП_Periods!R754,МП_Periods!R869,МП_Periods!R984,МП_Periods!R1099,МП_Periods!R1214,МП_Periods!R1329) -> 0 | AD63: =SUM(МП_Periods!S63,МП_Periods!S178,МП_Periods!S293,МП_Periods!S409,МП_Periods!S524,МП_Periods!S639,МП_Periods!S754,МП_Periods!S869,МП_Periods!S984,МП_Periods!S1099,МП_Periods!S1214,МП_Periods!S1329) -> 0 | AE63: =IFERROR(AC63/$AC$115,"-") -> - | AG63: =SUM(МП_Periods!V63,МП_Periods!V178,МП_Periods!V293,МП_Periods!V409,МП_Periods!V524,МП_Periods!V639,МП_Periods!V754,МП_Periods!V869,МП_Periods!V984,МП_Periods!V1099,МП_Periods!V1214,МП_Periods!V1329) -> 0 | AJ63: =SUM(МП_Periods!Y63,МП_Periods!Y178,МП_Periods!Y293,МП_Periods!Y409,МП_Periods!Y524,МП_Periods!Y639,МП_Periods!Y754,МП_Periods!Y869,МП_Periods!Y984,МП_Periods!Y1099,МП_Periods!Y1214,МП_Periods!Y1329) -> 0 | AK63: =SUM(МП_Periods!Z63,МП_Periods!Z178,МП_Periods!Z293,МП_Periods!Z409,МП_Periods!Z524,МП_Periods!Z639,МП_Periods!Z754,МП_Periods!Z869,МП_Periods!Z984,МП_Periods!Z1099,МП_Periods!Z1214,МП_Periods!Z1329) -> 0 | AL63: =SUM(МП_Periods!AA63,МП_Periods!AA178,МП_Periods!AA293,МП_Periods!AA409,МП_Periods!AA524,МП_Periods!AA639,МП_Periods!AA754,МП_Periods!AA869,МП_Periods!AA984,МП_Periods!AA1099,МП_Periods!AA1214,МП_Periods!AA1329) -> 0 | AM63: =SUM(МП_Periods!AB63,МП_Periods!AB178,МП_Periods!AB293,МП_Periods!AB409,МП_Periods!AB524,МП_Periods!AB639,МП_Periods!AB754,МП_Periods!AB869,МП_Periods!AB984,МП_Periods!AB1099,МП_Periods!AB1214,МП_Periods!AB1329) -> 0 | AO63: =IFERROR(AC63/AM63,"-") -> - | AP63: =SUM(МП_Periods!AE63,МП_Periods!AE178,МП_Periods!AE293,МП_Periods!AE409,МП_Periods!AE524,МП_Periods!AE639,МП_Periods!AE754,МП_Periods!AE869,МП_Periods!AE984,МП_Periods!AE1099,МП_Periods!AE1214,МП_Periods!AE1329) -> 0 | AQ63: =IFERROR(#REF!/AP63,"-") -> - | AS63: =IFERROR(U63/AG63,"-") -> - | AT63: =SUM(МП_Periods!AI63,МП_Periods!AI178,МП_Periods!AI293,МП_Periods!AI409,МП_Periods!AI524,МП_Periods!AI639,МП_Periods!AI754,МП_Periods!AI869,МП_Periods!AI984,МП_Periods!AI1099,МП_Periods!AI1214,МП_Periods!AI1329) -> 0 | AU63: =IFERROR(AC63/AT63,"-") -> - | AW63: =IFERROR(AX63/AT63,"-") -> - | AX63: =SUM(МП_Periods!AM63,МП_Periods!AM178,МП_Periods!AM293,МП_Periods!AM409,МП_Periods!AM524,МП_Periods!AM639,МП_Periods!AM754,МП_Periods!AM869,МП_Periods!AM984,МП_Periods!AM1099,МП_Periods!AM1214,МП_Periods!AM1329,) -> 0 | AY63: =IFERROR(AC63/AX63,"-") -> - | AZ63: =IFERROR(AX63/$AX$115,"-") -> - | BB63: =IFERROR(BE63/AC63,"-") -> - | BC63: =IFERROR(AC63/BE63,"-") -> - | BD63: =IFERROR(BE63/AX63,"-") -> - | BE63: =SUM(МП_Periods!AT63,МП_Periods!AT178,МП_Periods!AT293,МП_Periods!AT408,МП_Periods!AT524,МП_Periods!AT639,МП_Periods!AT754,МП_Periods!AT869,МП_Periods!AT984,МП_Periods!AT1099,МП_Periods!AT1214,МП_Periods!AT1329) -> 0 | BF63: =IFERROR(BE63/$BE$115,"-") -> - | BH63: =IFERROR(BI63/AX63,"-") -> - | BI63: =SUM(МП_Periods!AX63,МП_Periods!AX178,МП_Periods!AX293,МП_Periods!AX409,МП_Periods!AX524,МП_Periods!AX639,МП_Periods!AX754,МП_Periods!AX869,МП_Periods!AX984,МП_Periods!AX1099,МП_Periods!AX1214,МП_Periods!AX1329) -> 0 | BJ63: =IFERROR(AC63/BI63,"-") -> - | BK63: =IFERROR(BI63/$AX$115,"-") -> - | BM63: =IFERROR(BP63/AC63,"-") -> - | BN63: =IFERROR(AC63/BP63,"-") -> - | BO63: =IFERROR(BP63/BI63,"-") -> - | BP63: =SUM(МП_Periods!BE63,МП_Periods!BE178,МП_Periods!BE293,МП_Periods!BE409,МП_Periods!BE524,МП_Periods!BE639,МП_Periods!BE754,МП_Periods!BE869,МП_Periods!BE984,МП_Periods!BE1099,МП_Periods!BE1214,МП_Periods!BE1329) -> 0 | BQ63: =IFERROR(BP63/$BP$115,"-") -> -
S64: CPC | T64: =IFERROR(W64/U64,"-") -> - | U64: =SUM(МП_Periods!J64,МП_Periods!J179,МП_Periods!J294,МП_Periods!J410,МП_Periods!J525,МП_Periods!J640,МП_Periods!J755,МП_Periods!J870,МП_Periods!J985,МП_Periods!J1100,МП_Periods!J1215,МП_Periods!J1330) -> 0 | W64: =SUM(МП_Periods!L64,МП_Periods!L179,МП_Periods!L294,МП_Periods!L410,МП_Periods!L525,МП_Periods!L640,МП_Periods!L755,МП_Periods!L870,МП_Periods!L985,МП_Periods!L1100,МП_Periods!L1215,МП_Periods!L1330) -> 0 | Y64: =SUM(МП_Periods!N64,МП_Periods!N179,МП_Periods!N294,МП_Periods!N410,МП_Periods!N525,МП_Periods!N640,МП_Periods!N755,МП_Periods!N870,МП_Periods!N985,МП_Periods!N1100,МП_Periods!N1215,МП_Periods!N1330) -> 0 | AA64: =SUM(МП_Periods!P64,МП_Periods!P179,МП_Periods!P294,МП_Periods!P410,МП_Periods!P525,МП_Periods!P640,МП_Periods!P755,МП_Periods!P870,МП_Periods!P985,МП_Periods!P1100,МП_Periods!P1215,МП_Periods!P1330) -> 0 | AB64: =SUM(МП_Periods!Q64,МП_Periods!Q179,МП_Periods!Q294,МП_Periods!Q410,МП_Periods!Q525,МП_Periods!Q640,МП_Periods!Q755,МП_Periods!Q870,МП_Periods!Q985,МП_Periods!Q1100,МП_Periods!Q1215,МП_Periods!Q1330) -> 0 | AC64: =SUM(МП_Periods!R64,МП_Periods!R179,МП_Periods!R294,МП_Periods!R410,МП_Periods!R525,МП_Periods!R640,МП_Periods!R755,МП_Periods!R870,МП_Periods!R985,МП_Periods!R1100,МП_Periods!R1215,МП_Periods!R1330) -> 0 | AD64: =SUM(МП_Periods!S64,МП_Periods!S179,МП_Periods!S294,МП_Periods!S410,МП_Periods!S525,МП_Periods!S640,МП_Periods!S755,МП_Periods!S870,МП_Periods!S985,МП_Periods!S1100,МП_Periods!S1215,МП_Periods!S1330) -> 0 | AE64: =IFERROR(AC64/$AC$115,"-") -> - | AG64: =SUM(МП_Periods!V64,МП_Periods!V179,МП_Periods!V294,МП_Periods!V410,МП_Periods!V525,МП_Periods!V640,МП_Periods!V755,МП_Periods!V870,МП_Periods!V985,МП_Periods!V1100,МП_Periods!V1215,МП_Periods!V1330) -> 0 | AJ64: =SUM(МП_Periods!Y64,МП_Periods!Y179,МП_Periods!Y294,МП_Periods!Y410,МП_Periods!Y525,МП_Periods!Y640,МП_Periods!Y755,МП_Periods!Y870,МП_Periods!Y985,МП_Periods!Y1100,МП_Periods!Y1215,МП_Periods!Y1330) -> 0 | AK64: =SUM(МП_Periods!Z64,МП_Periods!Z179,МП_Periods!Z294,МП_Periods!Z410,МП_Periods!Z525,МП_Periods!Z640,МП_Periods!Z755,МП_Periods!Z870,МП_Periods!Z985,МП_Periods!Z1100,МП_Periods!Z1215,МП_Periods!Z1330) -> 0 | AL64: =SUM(МП_Periods!AA64,МП_Periods!AA179,МП_Periods!AA294,МП_Periods!AA410,МП_Periods!AA525,МП_Periods!AA640,МП_Periods!AA755,МП_Periods!AA870,МП_Periods!AA985,МП_Periods!AA1100,МП_Periods!AA1215,МП_Periods!AA1330) -> 0 | AM64: =SUM(МП_Periods!AB64,МП_Periods!AB179,МП_Periods!AB294,МП_Periods!AB410,МП_Periods!AB525,МП_Periods!AB640,МП_Periods!AB755,МП_Periods!AB870,МП_Periods!AB985,МП_Periods!AB1100,МП_Periods!AB1215,МП_Periods!AB1330) -> 0 | AO64: =IFERROR(AC64/AM64,"-") -> - | AP64: =SUM(МП_Periods!AE64,МП_Periods!AE179,МП_Periods!AE294,МП_Periods!AE410,МП_Periods!AE525,МП_Periods!AE640,МП_Periods!AE755,МП_Periods!AE870,МП_Periods!AE985,МП_Periods!AE1100,МП_Periods!AE1215,МП_Periods!AE1330) -> 0 | AQ64: =IFERROR(#REF!/AP64,"-") -> - | AS64: =IFERROR(U64/AG64,"-") -> - | AT64: =SUM(МП_Periods!AI64,МП_Periods!AI179,МП_Periods!AI294,МП_Periods!AI410,МП_Periods!AI525,МП_Periods!AI640,МП_Periods!AI755,МП_Periods!AI870,МП_Periods!AI985,МП_Periods!AI1100,МП_Periods!AI1215,МП_Periods!AI1330) -> 0 | AU64: =IFERROR(AC64/AT64,"-") -> - | AW64: =IFERROR(AX64/AT64,"-") -> - | AX64: =SUM(МП_Periods!AM64,МП_Periods!AM179,МП_Periods!AM294,МП_Periods!AM410,МП_Periods!AM525,МП_Periods!AM640,МП_Periods!AM755,МП_Periods!AM870,МП_Periods!AM985,МП_Periods!AM1100,МП_Periods!AM1215,МП_Periods!AM1330,) -> 0 | AY64: =IFERROR(AC64/AX64,"-") -> - | AZ64: =IFERROR(AX64/$AX$115,"-") -> - | BB64: =IFERROR(BE64/AC64,"-") -> - | BC64: =IFERROR(AC64/BE64,"-") -> - | BD64: =IFERROR(BE64/AX64,"-") -> - | BE64: =SUM(МП_Periods!AT64,МП_Periods!AT179,МП_Periods!AT294,МП_Periods!AT409,МП_Periods!AT525,МП_Periods!AT640,МП_Periods!AT755,МП_Periods!AT870,МП_Periods!AT985,МП_Periods!AT1100,МП_Periods!AT1215,МП_Periods!AT1330) -> 0 | BF64: =IFERROR(BE64/$BE$115,"-") -> - | BH64: =IFERROR(BI64/AX64,"-") -> - | BI64: =SUM(МП_Periods!AX64,МП_Periods!AX179,МП_Periods!AX294,МП_Periods!AX410,МП_Periods!AX525,МП_Periods!AX640,МП_Periods!AX755,МП_Periods!AX870,МП_Periods!AX985,МП_Periods!AX1100,МП_Periods!AX1215,МП_Periods!AX1330) -> 0 | BJ64: =IFERROR(AC64/BI64,"-") -> - | BK64: =IFERROR(BI64/$AX$115,"-") -> - | BM64: =IFERROR(BP64/AC64,"-") -> - | BN64: =IFERROR(AC64/BP64,"-") -> - | BO64: =IFERROR(BP64/BI64,"-") -> - | BP64: =SUM(МП_Periods!BE64,МП_Periods!BE179,МП_Periods!BE294,МП_Periods!BE410,МП_Periods!BE525,МП_Periods!BE640,МП_Periods!BE755,МП_Periods!BE870,МП_Periods!BE985,МП_Periods!BE1100,МП_Periods!BE1215,МП_Periods!BE1330) -> 0 | BQ64: =IFERROR(BP64/$BP$115,"-") -> -
S65: CPC | T65: =IFERROR(W65/U65,"-") -> - | U65: =SUM(МП_Periods!J65,МП_Periods!J180,МП_Periods!J295,МП_Periods!J411,МП_Periods!J526,МП_Periods!J641,МП_Periods!J756,МП_Periods!J871,МП_Periods!J986,МП_Periods!J1101,МП_Periods!J1216,МП_Periods!J1331) -> 0 | W65: =SUM(МП_Periods!L65,МП_Periods!L180,МП_Periods!L295,МП_Periods!L411,МП_Periods!L526,МП_Periods!L641,МП_Periods!L756,МП_Periods!L871,МП_Periods!L986,МП_Periods!L1101,МП_Periods!L1216,МП_Periods!L1331) -> 0 | Y65: =SUM(МП_Periods!N65,МП_Periods!N180,МП_Periods!N295,МП_Periods!N411,МП_Periods!N526,МП_Periods!N641,МП_Periods!N756,МП_Periods!N871,МП_Periods!N986,МП_Periods!N1101,МП_Periods!N1216,МП_Periods!N1331) -> 0 | AA65: =SUM(МП_Periods!P65,МП_Periods!P180,МП_Periods!P295,МП_Periods!P411,МП_Periods!P526,МП_Periods!P641,МП_Periods!P756,МП_Periods!P871,МП_Periods!P986,МП_Periods!P1101,МП_Periods!P1216,МП_Periods!P1331) -> 0 | AB65: =SUM(МП_Periods!Q65,МП_Periods!Q180,МП_Periods!Q295,МП_Periods!Q411,МП_Periods!Q526,МП_Periods!Q641,МП_Periods!Q756,МП_Periods!Q871,МП_Periods!Q986,МП_Periods!Q1101,МП_Periods!Q1216,МП_Periods!Q1331) -> 0 | AC65: =SUM(МП_Periods!R65,МП_Periods!R180,МП_Periods!R295,МП_Periods!R411,МП_Periods!R526,МП_Periods!R641,МП_Periods!R756,МП_Periods!R871,МП_Periods!R986,МП_Periods!R1101,МП_Periods!R1216,МП_Periods!R1331) -> 0 | AD65: =SUM(МП_Periods!S65,МП_Periods!S180,МП_Periods!S295,МП_Periods!S411,МП_Periods!S526,МП_Periods!S641,МП_Periods!S756,МП_Periods!S871,МП_Periods!S986,МП_Periods!S1101,МП_Periods!S1216,МП_Periods!S1331) -> 0 | AE65: =IFERROR(AC65/$AC$115,"-") -> - | AG65: =SUM(МП_Periods!V65,МП_Periods!V180,МП_Periods!V295,МП_Periods!V411,МП_Periods!V526,МП_Periods!V641,МП_Periods!V756,МП_Periods!V871,МП_Periods!V986,МП_Periods!V1101,МП_Periods!V1216,МП_Periods!V1331) -> 0 | AJ65: =SUM(МП_Periods!Y65,МП_Periods!Y180,МП_Periods!Y295,МП_Periods!Y411,МП_Periods!Y526,МП_Periods!Y641,МП_Periods!Y756,МП_Periods!Y871,МП_Periods!Y986,МП_Periods!Y1101,МП_Periods!Y1216,МП_Periods!Y1331) -> 0 | AK65: =SUM(МП_Periods!Z65,МП_Periods!Z180,МП_Periods!Z295,МП_Periods!Z411,МП_Periods!Z526,МП_Periods!Z641,МП_Periods!Z756,МП_Periods!Z871,МП_Periods!Z986,МП_Periods!Z1101,МП_Periods!Z1216,МП_Periods!Z1331) -> 0 | AL65: =SUM(МП_Periods!AA65,МП_Periods!AA180,МП_Periods!AA295,МП_Periods!AA411,МП_Periods!AA526,МП_Periods!AA641,МП_Periods!AA756,МП_Periods!AA871,МП_Periods!AA986,МП_Periods!AA1101,МП_Periods!AA1216,МП_Periods!AA1331) -> 0 | AM65: =SUM(МП_Periods!AB65,МП_Periods!AB180,МП_Periods!AB295,МП_Periods!AB411,МП_Periods!AB526,МП_Periods!AB641,МП_Periods!AB756,МП_Periods!AB871,МП_Periods!AB986,МП_Periods!AB1101,МП_Periods!AB1216,МП_Periods!AB1331) -> 0 | AO65: =IFERROR(AC65/AM65,"-") -> - | AP65: =SUM(МП_Periods!AE65,МП_Periods!AE180,МП_Periods!AE295,МП_Periods!AE411,МП_Periods!AE526,МП_Periods!AE641,МП_Periods!AE756,МП_Periods!AE871,МП_Periods!AE986,МП_Periods!AE1101,МП_Periods!AE1216,МП_Periods!AE1331) -> 0 | AQ65: =IFERROR(#REF!/AP65,"-") -> - | AS65: =IFERROR(U65/AG65,"-") -> - | AT65: =SUM(МП_Periods!AI65,МП_Periods!AI180,МП_Periods!AI295,МП_Periods!AI411,МП_Periods!AI526,МП_Periods!AI641,МП_Periods!AI756,МП_Periods!AI871,МП_Periods!AI986,МП_Periods!AI1101,МП_Periods!AI1216,МП_Periods!AI1331) -> 0 | AU65: =IFERROR(AC65/AT65,"-") -> - | AW65: =IFERROR(AX65/AT65,"-") -> - | AX65: =SUM(МП_Periods!AM65,МП_Periods!AM180,МП_Periods!AM295,МП_Periods!AM411,МП_Periods!AM526,МП_Periods!AM641,МП_Periods!AM756,МП_Periods!AM871,МП_Periods!AM986,МП_Periods!AM1101,МП_Periods!AM1216,МП_Periods!AM1331,) -> 0 | AY65: =IFERROR(AC65/AX65,"-") -> - | AZ65: =IFERROR(AX65/$AX$115,"-") -> - | BB65: =IFERROR(BE65/AC65,"-") -> - | BC65: =IFERROR(AC65/BE65,"-") -> - | BD65: =IFERROR(BE65/AX65,"-") -> - | BE65: =SUM(МП_Periods!AT65,МП_Periods!AT180,МП_Periods!AT295,МП_Periods!AT410,МП_Periods!AT526,МП_Periods!AT641,МП_Periods!AT756,МП_Periods!AT871,МП_Periods!AT986,МП_Periods!AT1101,МП_Periods!AT1216,МП_Periods!AT1331) -> 0 | BF65: =IFERROR(BE65/$BE$115,"-") -> - | BH65: =IFERROR(BI65/AX65,"-") -> - | BI65: =SUM(МП_Periods!AX65,МП_Periods!AX180,МП_Periods!AX295,МП_Periods!AX411,МП_Periods!AX526,МП_Periods!AX641,МП_Periods!AX756,МП_Periods!AX871,МП_Periods!AX986,МП_Periods!AX1101,МП_Periods!AX1216,МП_Periods!AX1331) -> 0 | BJ65: =IFERROR(AC65/BI65,"-") -> - | BK65: =IFERROR(BI65/$AX$115,"-") -> - | BM65: =IFERROR(BP65/AC65,"-") -> - | BN65: =IFERROR(AC65/BP65,"-") -> - | BO65: =IFERROR(BP65/BI65,"-") -> - | BP65: =SUM(МП_Periods!BE65,МП_Periods!BE180,МП_Periods!BE295,МП_Periods!BE411,МП_Periods!BE526,МП_Periods!BE641,МП_Periods!BE756,МП_Periods!BE871,МП_Periods!BE986,МП_Periods!BE1101,МП_Periods!BE1216,МП_Periods!BE1331) -> 0 | BQ65: =IFERROR(BP65/$BP$115,"-") -> -
S66: CPC | T66: =IFERROR(W66/U66,"-") -> - | U66: =SUM(МП_Periods!J66,МП_Periods!J181,МП_Periods!J296,МП_Periods!J412,МП_Periods!J527,МП_Periods!J642,МП_Periods!J757,МП_Periods!J872,МП_Periods!J987,МП_Periods!J1102,МП_Periods!J1217,МП_Periods!J1332) -> 0 | W66: =SUM(МП_Periods!L66,МП_Periods!L181,МП_Periods!L296,МП_Periods!L412,МП_Periods!L527,МП_Periods!L642,МП_Periods!L757,МП_Periods!L872,МП_Periods!L987,МП_Periods!L1102,МП_Periods!L1217,МП_Periods!L1332) -> 0 | Y66: =SUM(МП_Periods!N66,МП_Periods!N181,МП_Periods!N296,МП_Periods!N412,МП_Periods!N527,МП_Periods!N642,МП_Periods!N757,МП_Periods!N872,МП_Periods!N987,МП_Periods!N1102,МП_Periods!N1217,МП_Periods!N1332) -> 0 | AA66: =SUM(МП_Periods!P66,МП_Periods!P181,МП_Periods!P296,МП_Periods!P412,МП_Periods!P527,МП_Periods!P642,МП_Periods!P757,МП_Periods!P872,МП_Periods!P987,МП_Periods!P1102,МП_Periods!P1217,МП_Periods!P1332) -> 0 | AB66: =SUM(МП_Periods!Q66,МП_Periods!Q181,МП_Periods!Q296,МП_Periods!Q412,МП_Periods!Q527,МП_Periods!Q642,МП_Periods!Q757,МП_Periods!Q872,МП_Periods!Q987,МП_Periods!Q1102,МП_Periods!Q1217,МП_Periods!Q1332) -> 0 | AC66: =SUM(МП_Periods!R66,МП_Periods!R181,МП_Periods!R296,МП_Periods!R412,МП_Periods!R527,МП_Periods!R642,МП_Periods!R757,МП_Periods!R872,МП_Periods!R987,МП_Periods!R1102,МП_Periods!R1217,МП_Periods!R1332) -> 0 | AD66: =SUM(МП_Periods!S66,МП_Periods!S181,МП_Periods!S296,МП_Periods!S412,МП_Periods!S527,МП_Periods!S642,МП_Periods!S757,МП_Periods!S872,МП_Periods!S987,МП_Periods!S1102,МП_Periods!S1217,МП_Periods!S1332) -> 0 | AE66: =IFERROR(AC66/$AC$115,"-") -> - | AG66: =SUM(МП_Periods!V66,МП_Periods!V181,МП_Periods!V296,МП_Periods!V412,МП_Periods!V527,МП_Periods!V642,МП_Periods!V757,МП_Periods!V872,МП_Periods!V987,МП_Periods!V1102,МП_Periods!V1217,МП_Periods!V1332) -> 0 | AJ66: =SUM(МП_Periods!Y66,МП_Periods!Y181,МП_Periods!Y296,МП_Periods!Y412,МП_Periods!Y527,МП_Periods!Y642,МП_Periods!Y757,МП_Periods!Y872,МП_Periods!Y987,МП_Periods!Y1102,МП_Periods!Y1217,МП_Periods!Y1332) -> 0 | AK66: =SUM(МП_Periods!Z66,МП_Periods!Z181,МП_Periods!Z296,МП_Periods!Z412,МП_Periods!Z527,МП_Periods!Z642,МП_Periods!Z757,МП_Periods!Z872,МП_Periods!Z987,МП_Periods!Z1102,МП_Periods!Z1217,МП_Periods!Z1332) -> 0 | AL66: =SUM(МП_Periods!AA66,МП_Periods!AA181,МП_Periods!AA296,МП_Periods!AA412,МП_Periods!AA527,МП_Periods!AA642,МП_Periods!AA757,МП_Periods!AA872,МП_Periods!AA987,МП_Periods!AA1102,МП_Periods!AA1217,МП_Periods!AA1332) -> 0 | AM66: =SUM(МП_Periods!AB66,МП_Periods!AB181,МП_Periods!AB296,МП_Periods!AB412,МП_Periods!AB527,МП_Periods!AB642,МП_Periods!AB757,МП_Periods!AB872,МП_Periods!AB987,МП_Periods!AB1102,МП_Periods!AB1217,МП_Periods!AB1332) -> 0 | AO66: =IFERROR(AC66/AM66,"-") -> - | AP66: =SUM(МП_Periods!AE66,МП_Periods!AE181,МП_Periods!AE296,МП_Periods!AE412,МП_Periods!AE527,МП_Periods!AE642,МП_Periods!AE757,МП_Periods!AE872,МП_Periods!AE987,МП_Periods!AE1102,МП_Periods!AE1217,МП_Periods!AE1332) -> 0 | AQ66: =IFERROR(#REF!/AP66,"-") -> - | AS66: =IFERROR(U66/AG66,"-") -> - | AT66: =SUM(МП_Periods!AI66,МП_Periods!AI181,МП_Periods!AI296,МП_Periods!AI412,МП_Periods!AI527,МП_Periods!AI642,МП_Periods!AI757,МП_Periods!AI872,МП_Periods!AI987,МП_Periods!AI1102,МП_Periods!AI1217,МП_Periods!AI1332) -> 0 | AU66: =IFERROR(AC66/AT66,"-") -> - | AW66: =IFERROR(AX66/AT66,"-") -> - | AX66: =SUM(МП_Periods!AM66,МП_Periods!AM181,МП_Periods!AM296,МП_Periods!AM412,МП_Periods!AM527,МП_Periods!AM642,МП_Periods!AM757,МП_Periods!AM872,МП_Periods!AM987,МП_Periods!AM1102,МП_Periods!AM1217,МП_Periods!AM1332,) -> 0 | AY66: =IFERROR(AC66/AX66,"-") -> - | AZ66: =IFERROR(AX66/$AX$115,"-") -> - | BB66: =IFERROR(BE66/AC66,"-") -> - | BC66: =IFERROR(AC66/BE66,"-") -> - | BD66: =IFERROR(BE66/AX66,"-") -> - | BE66: =SUM(МП_Periods!AT66,МП_Periods!AT181,МП_Periods!AT296,МП_Periods!AT411,МП_Periods!AT527,МП_Periods!AT642,МП_Periods!AT757,МП_Periods!AT872,МП_Periods!AT987,МП_Periods!AT1102,МП_Periods!AT1217,МП_Periods!AT1332) -> 0 | BF66: =IFERROR(BE66/$BE$115,"-") -> - | BH66: =IFERROR(BI66/AX66,"-") -> - | BI66: =SUM(МП_Periods!AX66,МП_Periods!AX181,МП_Periods!AX296,МП_Periods!AX412,МП_Periods!AX527,МП_Periods!AX642,МП_Periods!AX757,МП_Periods!AX872,МП_Periods!AX987,МП_Periods!AX1102,МП_Periods!AX1217,МП_Periods!AX1332) -> 0 | BJ66: =IFERROR(AC66/BI66,"-") -> - | BK66: =IFERROR(BI66/$AX$115,"-") -> - | BM66: =IFERROR(BP66/AC66,"-") -> - | BN66: =IFERROR(AC66/BP66,"-") -> - | BO66: =IFERROR(BP66/BI66,"-") -> - | BP66: =SUM(МП_Periods!BE66,МП_Periods!BE181,МП_Periods!BE296,МП_Periods!BE412,МП_Periods!BE527,МП_Periods!BE642,МП_Periods!BE757,МП_Periods!BE872,МП_Periods!BE987,МП_Periods!BE1102,МП_Periods!BE1217,МП_Periods!BE1332) -> 0 | BQ66: =IFERROR(BP66/$BP$115,"-") -> -
S67: CPC | T67: =IFERROR(W67/U67,"-") -> - | U67: =SUM(МП_Periods!J67,МП_Periods!J182,МП_Periods!J297,МП_Periods!J413,МП_Periods!J528,МП_Periods!J643,МП_Periods!J758,МП_Periods!J873,МП_Periods!J988,МП_Periods!J1103,МП_Periods!J1218,МП_Periods!J1333) -> 0 | W67: =SUM(МП_Periods!L67,МП_Periods!L182,МП_Periods!L297,МП_Periods!L413,МП_Periods!L528,МП_Periods!L643,МП_Periods!L758,МП_Periods!L873,МП_Periods!L988,МП_Periods!L1103,МП_Periods!L1218,МП_Periods!L1333) -> 0 | Y67: =SUM(МП_Periods!N67,МП_Periods!N182,МП_Periods!N297,МП_Periods!N413,МП_Periods!N528,МП_Periods!N643,МП_Periods!N758,МП_Periods!N873,МП_Periods!N988,МП_Periods!N1103,МП_Periods!N1218,МП_Periods!N1333) -> 0 | AA67: =SUM(МП_Periods!P67,МП_Periods!P182,МП_Periods!P297,МП_Periods!P413,МП_Periods!P528,МП_Periods!P643,МП_Periods!P758,МП_Periods!P873,МП_Periods!P988,МП_Periods!P1103,МП_Periods!P1218,МП_Periods!P1333) -> 0 | AB67: =SUM(МП_Periods!Q67,МП_Periods!Q182,МП_Periods!Q297,МП_Periods!Q413,МП_Periods!Q528,МП_Periods!Q643,МП_Periods!Q758,МП_Periods!Q873,МП_Periods!Q988,МП_Periods!Q1103,МП_Periods!Q1218,МП_Periods!Q1333) -> 0 | AC67: =SUM(МП_Periods!R67,МП_Periods!R182,МП_Periods!R297,МП_Periods!R413,МП_Periods!R528,МП_Periods!R643,МП_Periods!R758,МП_Periods!R873,МП_Periods!R988,МП_Periods!R1103,МП_Periods!R1218,МП_Periods!R1333) -> 0 | AD67: =SUM(МП_Periods!S67,МП_Periods!S182,МП_Periods!S297,МП_Periods!S413,МП_Periods!S528,МП_Periods!S643,МП_Periods!S758,МП_Periods!S873,МП_Periods!S988,МП_Periods!S1103,МП_Periods!S1218,МП_Periods!S1333) -> 0 | AE67: =IFERROR(AC67/$AC$115,"-") -> - | AG67: =SUM(МП_Periods!V67,МП_Periods!V182,МП_Periods!V297,МП_Periods!V413,МП_Periods!V528,МП_Periods!V643,МП_Periods!V758,МП_Periods!V873,МП_Periods!V988,МП_Periods!V1103,МП_Periods!V1218,МП_Periods!V1333) -> 0 | AJ67: =SUM(МП_Periods!Y67,МП_Periods!Y182,МП_Periods!Y297,МП_Periods!Y413,МП_Periods!Y528,МП_Periods!Y643,МП_Periods!Y758,МП_Periods!Y873,МП_Periods!Y988,МП_Periods!Y1103,МП_Periods!Y1218,МП_Periods!Y1333) -> 0 | AK67: =SUM(МП_Periods!Z67,МП_Periods!Z182,МП_Periods!Z297,МП_Periods!Z413,МП_Periods!Z528,МП_Periods!Z643,МП_Periods!Z758,МП_Periods!Z873,МП_Periods!Z988,МП_Periods!Z1103,МП_Periods!Z1218,МП_Periods!Z1333) -> 0 | AL67: =SUM(МП_Periods!AA67,МП_Periods!AA182,МП_Periods!AA297,МП_Periods!AA413,МП_Periods!AA528,МП_Periods!AA643,МП_Periods!AA758,МП_Periods!AA873,МП_Periods!AA988,МП_Periods!AA1103,МП_Periods!AA1218,МП_Periods!AA1333) -> 0 | AM67: =SUM(МП_Periods!AB67,МП_Periods!AB182,МП_Periods!AB297,МП_Periods!AB413,МП_Periods!AB528,МП_Periods!AB643,МП_Periods!AB758,МП_Periods!AB873,МП_Periods!AB988,МП_Periods!AB1103,МП_Periods!AB1218,МП_Periods!AB1333) -> 0 | AO67: =IFERROR(AC67/AM67,"-") -> - | AP67: =SUM(МП_Periods!AE67,МП_Periods!AE182,МП_Periods!AE297,МП_Periods!AE413,МП_Periods!AE528,МП_Periods!AE643,МП_Periods!AE758,МП_Periods!AE873,МП_Periods!AE988,МП_Periods!AE1103,МП_Periods!AE1218,МП_Periods!AE1333) -> 0 | AQ67: =IFERROR(#REF!/AP67,"-") -> - | AS67: =IFERROR(U67/AG67,"-") -> - | AT67: =SUM(МП_Periods!AI67,МП_Periods!AI182,МП_Periods!AI297,МП_Periods!AI413,МП_Periods!AI528,МП_Periods!AI643,МП_Periods!AI758,МП_Periods!AI873,МП_Periods!AI988,МП_Periods!AI1103,МП_Periods!AI1218,МП_Periods!AI1333) -> 0 | AU67: =IFERROR(AC67/AT67,"-") -> - | AW67: =IFERROR(AX67/AT67,"-") -> - | AX67: =SUM(МП_Periods!AM67,МП_Periods!AM182,МП_Periods!AM297,МП_Periods!AM413,МП_Periods!AM528,МП_Periods!AM643,МП_Periods!AM758,МП_Periods!AM873,МП_Periods!AM988,МП_Periods!AM1103,МП_Periods!AM1218,МП_Periods!AM1333,) -> 0 | AY67: =IFERROR(AC67/AX67,"-") -> - | AZ67: =IFERROR(AX67/$AX$115,"-") -> - | BB67: =IFERROR(BE67/AC67,"-") -> - | BC67: =IFERROR(AC67/BE67,"-") -> - | BD67: =IFERROR(BE67/AX67,"-") -> - | BE67: =SUM(МП_Periods!AT67,МП_Periods!AT182,МП_Periods!AT297,МП_Periods!AT412,МП_Periods!AT528,МП_Periods!AT643,МП_Periods!AT758,МП_Periods!AT873,МП_Periods!AT988,МП_Periods!AT1103,МП_Periods!AT1218,МП_Periods!AT1333) -> 0 | BF67: =IFERROR(BE67/$BE$115,"-") -> - | BH67: =IFERROR(BI67/AX67,"-") -> - | BI67: =SUM(МП_Periods!AX67,МП_Periods!AX182,МП_Periods!AX297,МП_Periods!AX413,МП_Periods!AX528,МП_Periods!AX643,МП_Periods!AX758,МП_Periods!AX873,МП_Periods!AX988,МП_Periods!AX1103,МП_Periods!AX1218,МП_Periods!AX1333) -> 0 | BJ67: =IFERROR(AC67/BI67,"-") -> - | BK67: =IFERROR(BI67/$AX$115,"-") -> - | BM67: =IFERROR(BP67/AC67,"-") -> - | BN67: =IFERROR(AC67/BP67,"-") -> - | BO67: =IFERROR(BP67/BI67,"-") -> - | BP67: =SUM(МП_Periods!BE67,МП_Periods!BE182,МП_Periods!BE297,МП_Periods!BE413,МП_Periods!BE528,МП_Periods!BE643,МП_Periods!BE758,МП_Periods!BE873,МП_Periods!BE988,МП_Periods!BE1103,МП_Periods!BE1218,МП_Periods!BE1333) -> 0 | BQ67: =IFERROR(BP67/$BP$115,"-") -> -
S68: CPC | T68: =IFERROR(W68/U68,"-") -> - | U68: =SUM(МП_Periods!J68,МП_Periods!J183,МП_Periods!J298,МП_Periods!J414,МП_Periods!J529,МП_Periods!J644,МП_Periods!J759,МП_Periods!J874,МП_Periods!J989,МП_Periods!J1104,МП_Periods!J1219,МП_Periods!J1334) -> 0 | W68: =SUM(МП_Periods!L68,МП_Periods!L183,МП_Periods!L298,МП_Periods!L414,МП_Periods!L529,МП_Periods!L644,МП_Periods!L759,МП_Periods!L874,МП_Periods!L989,МП_Periods!L1104,МП_Periods!L1219,МП_Periods!L1334) -> 0 | Y68: =SUM(МП_Periods!N68,МП_Periods!N183,МП_Periods!N298,МП_Periods!N414,МП_Periods!N529,МП_Periods!N644,МП_Periods!N759,МП_Periods!N874,МП_Periods!N989,МП_Periods!N1104,МП_Periods!N1219,МП_Periods!N1334) -> 0 | AA68: =SUM(МП_Periods!P68,МП_Periods!P183,МП_Periods!P298,МП_Periods!P414,МП_Periods!P529,МП_Periods!P644,МП_Periods!P759,МП_Periods!P874,МП_Periods!P989,МП_Periods!P1104,МП_Periods!P1219,МП_Periods!P1334) -> 0 | AB68: =SUM(МП_Periods!Q68,МП_Periods!Q183,МП_Periods!Q298,МП_Periods!Q414,МП_Periods!Q529,МП_Periods!Q644,МП_Periods!Q759,МП_Periods!Q874,МП_Periods!Q989,МП_Periods!Q1104,МП_Periods!Q1219,МП_Periods!Q1334) -> 0 | AC68: =SUM(МП_Periods!R68,МП_Periods!R183,МП_Periods!R298,МП_Periods!R414,МП_Periods!R529,МП_Periods!R644,МП_Periods!R759,МП_Periods!R874,МП_Periods!R989,МП_Periods!R1104,МП_Periods!R1219,МП_Periods!R1334) -> 0 | AD68: =SUM(МП_Periods!S68,МП_Periods!S183,МП_Periods!S298,МП_Periods!S414,МП_Periods!S529,МП_Periods!S644,МП_Periods!S759,МП_Periods!S874,МП_Periods!S989,МП_Periods!S1104,МП_Periods!S1219,МП_Periods!S1334) -> 0 | AE68: =IFERROR(AC68/$AC$115,"-") -> - | AG68: =SUM(МП_Periods!V68,МП_Periods!V183,МП_Periods!V298,МП_Periods!V414,МП_Periods!V529,МП_Periods!V644,МП_Periods!V759,МП_Periods!V874,МП_Periods!V989,МП_Periods!V1104,МП_Periods!V1219,МП_Periods!V1334) -> 0 | AJ68: =SUM(МП_Periods!Y68,МП_Periods!Y183,МП_Periods!Y298,МП_Periods!Y414,МП_Periods!Y529,МП_Periods!Y644,МП_Periods!Y759,МП_Periods!Y874,МП_Periods!Y989,МП_Periods!Y1104,МП_Periods!Y1219,МП_Periods!Y1334) -> 0 | AK68: =SUM(МП_Periods!Z68,МП_Periods!Z183,МП_Periods!Z298,МП_Periods!Z414,МП_Periods!Z529,МП_Periods!Z644,МП_Periods!Z759,МП_Periods!Z874,МП_Periods!Z989,МП_Periods!Z1104,МП_Periods!Z1219,МП_Periods!Z1334) -> 0 | AL68: =SUM(МП_Periods!AA68,МП_Periods!AA183,МП_Periods!AA298,МП_Periods!AA414,МП_Periods!AA529,МП_Periods!AA644,МП_Periods!AA759,МП_Periods!AA874,МП_Periods!AA989,МП_Periods!AA1104,МП_Periods!AA1219,МП_Periods!AA1334) -> 0 | AM68: =SUM(МП_Periods!AB68,МП_Periods!AB183,МП_Periods!AB298,МП_Periods!AB414,МП_Periods!AB529,МП_Periods!AB644,МП_Periods!AB759,МП_Periods!AB874,МП_Periods!AB989,МП_Periods!AB1104,МП_Periods!AB1219,МП_Periods!AB1334) -> 0 | AO68: =IFERROR(AC68/AM68,"-") -> - | AP68: =SUM(МП_Periods!AE68,МП_Periods!AE183,МП_Periods!AE298,МП_Periods!AE414,МП_Periods!AE529,МП_Periods!AE644,МП_Periods!AE759,МП_Periods!AE874,МП_Periods!AE989,МП_Periods!AE1104,МП_Periods!AE1219,МП_Periods!AE1334) -> 0 | AQ68: =IFERROR(#REF!/AP68,"-") -> - | AS68: =IFERROR(U68/AG68,"-") -> - | AT68: =SUM(МП_Periods!AI68,МП_Periods!AI183,МП_Periods!AI298,МП_Periods!AI414,МП_Periods!AI529,МП_Periods!AI644,МП_Periods!AI759,МП_Periods!AI874,МП_Periods!AI989,МП_Periods!AI1104,МП_Periods!AI1219,МП_Periods!AI1334) -> 0 | AU68: =IFERROR(AC68/AT68,"-") -> - | AW68: =IFERROR(AX68/AT68,"-") -> - | AX68: =SUM(МП_Periods!AM68,МП_Periods!AM183,МП_Periods!AM298,МП_Periods!AM414,МП_Periods!AM529,МП_Periods!AM644,МП_Periods!AM759,МП_Periods!AM874,МП_Periods!AM989,МП_Periods!AM1104,МП_Periods!AM1219,МП_Periods!AM1334,) -> 0 | AY68: =IFERROR(AC68/AX68,"-") -> - | AZ68: =IFERROR(AX68/$AX$115,"-") -> - | BB68: =IFERROR(BE68/AC68,"-") -> - | BC68: =IFERROR(AC68/BE68,"-") -> - | BD68: =IFERROR(BE68/AX68,"-") -> - | BE68: =SUM(МП_Periods!AT68,МП_Periods!AT183,МП_Periods!AT298,МП_Periods!AT413,МП_Periods!AT529,МП_Periods!AT644,МП_Periods!AT759,МП_Periods!AT874,МП_Periods!AT989,МП_Periods!AT1104,МП_Periods!AT1219,МП_Periods!AT1334) -> 0 | BF68: =IFERROR(BE68/$BE$115,"-") -> - | BH68: =IFERROR(BI68/AX68,"-") -> - | BI68: =SUM(МП_Periods!AX68,МП_Periods!AX183,МП_Periods!AX298,МП_Periods!AX414,МП_Periods!AX529,МП_Periods!AX644,МП_Periods!AX759,МП_Periods!AX874,МП_Periods!AX989,МП_Periods!AX1104,МП_Periods!AX1219,МП_Periods!AX1334) -> 0 | BJ68: =IFERROR(AC68/BI68,"-") -> - | BK68: =IFERROR(BI68/$AX$115,"-") -> - | BM68: =IFERROR(BP68/AC68,"-") -> - | BN68: =IFERROR(AC68/BP68,"-") -> - | BO68: =IFERROR(BP68/BI68,"-") -> - | BP68: =SUM(МП_Periods!BE68,МП_Periods!BE183,МП_Periods!BE298,МП_Periods!BE414,МП_Periods!BE529,МП_Periods!BE644,МП_Periods!BE759,МП_Periods!BE874,МП_Periods!BE989,МП_Periods!BE1104,МП_Periods!BE1219,МП_Periods!BE1334) -> 0 | BQ68: =IFERROR(BP68/$BP$115,"-") -> -
S69: CPC | T69: =IFERROR(W69/U69,"-") -> - | U69: =SUM(МП_Periods!J69,МП_Periods!J184,МП_Periods!J299,МП_Periods!J415,МП_Periods!J530,МП_Periods!J645,МП_Periods!J760,МП_Periods!J875,МП_Periods!J990,МП_Periods!J1105,МП_Periods!J1220,МП_Periods!J1335) -> 0 | W69: =SUM(МП_Periods!L69,МП_Periods!L184,МП_Periods!L299,МП_Periods!L415,МП_Periods!L530,МП_Periods!L645,МП_Periods!L760,МП_Periods!L875,МП_Periods!L990,МП_Periods!L1105,МП_Periods!L1220,МП_Periods!L1335) -> 0 | Y69: =SUM(МП_Periods!N69,МП_Periods!N184,МП_Periods!N299,МП_Periods!N415,МП_Periods!N530,МП_Periods!N645,МП_Periods!N760,МП_Periods!N875,МП_Periods!N990,МП_Periods!N1105,МП_Periods!N1220,МП_Periods!N1335) -> 0 | AA69: =SUM(МП_Periods!P69,МП_Periods!P184,МП_Periods!P299,МП_Periods!P415,МП_Periods!P530,МП_Periods!P645,МП_Periods!P760,МП_Periods!P875,МП_Periods!P990,МП_Periods!P1105,МП_Periods!P1220,МП_Periods!P1335) -> 0 | AB69: =SUM(МП_Periods!Q69,МП_Periods!Q184,МП_Periods!Q299,МП_Periods!Q415,МП_Periods!Q530,МП_Periods!Q645,МП_Periods!Q760,МП_Periods!Q875,МП_Periods!Q990,МП_Periods!Q1105,МП_Periods!Q1220,МП_Periods!Q1335) -> 0 | AC69: =SUM(МП_Periods!R69,МП_Periods!R184,МП_Periods!R299,МП_Periods!R415,МП_Periods!R530,МП_Periods!R645,МП_Periods!R760,МП_Periods!R875,МП_Periods!R990,МП_Periods!R1105,МП_Periods!R1220,МП_Periods!R1335) -> 0 | AD69: =SUM(МП_Periods!S69,МП_Periods!S184,МП_Periods!S299,МП_Periods!S415,МП_Periods!S530,МП_Periods!S645,МП_Periods!S760,МП_Periods!S875,МП_Periods!S990,МП_Periods!S1105,МП_Periods!S1220,МП_Periods!S1335) -> 0 | AE69: =IFERROR(AC69/$AC$115,"-") -> - | AG69: =SUM(МП_Periods!V69,МП_Periods!V184,МП_Periods!V299,МП_Periods!V415,МП_Periods!V530,МП_Periods!V645,МП_Periods!V760,МП_Periods!V875,МП_Periods!V990,МП_Periods!V1105,МП_Periods!V1220,МП_Periods!V1335) -> 0 | AJ69: =SUM(МП_Periods!Y69,МП_Periods!Y184,МП_Periods!Y299,МП_Periods!Y415,МП_Periods!Y530,МП_Periods!Y645,МП_Periods!Y760,МП_Periods!Y875,МП_Periods!Y990,МП_Periods!Y1105,МП_Periods!Y1220,МП_Periods!Y1335) -> 0 | AK69: =SUM(МП_Periods!Z69,МП_Periods!Z184,МП_Periods!Z299,МП_Periods!Z415,МП_Periods!Z530,МП_Periods!Z645,МП_Periods!Z760,МП_Periods!Z875,МП_Periods!Z990,МП_Periods!Z1105,МП_Periods!Z1220,МП_Periods!Z1335) -> 0 | AL69: =SUM(МП_Periods!AA69,МП_Periods!AA184,МП_Periods!AA299,МП_Periods!AA415,МП_Periods!AA530,МП_Periods!AA645,МП_Periods!AA760,МП_Periods!AA875,МП_Periods!AA990,МП_Periods!AA1105,МП_Periods!AA1220,МП_Periods!AA1335) -> 0 | AM69: =SUM(МП_Periods!AB69,МП_Periods!AB184,МП_Periods!AB299,МП_Periods!AB415,МП_Periods!AB530,МП_Periods!AB645,МП_Periods!AB760,МП_Periods!AB875,МП_Periods!AB990,МП_Periods!AB1105,МП_Periods!AB1220,МП_Periods!AB1335) -> 0 | AO69: =IFERROR(AC69/AM69,"-") -> - | AP69: =SUM(МП_Periods!AE69,МП_Periods!AE184,МП_Periods!AE299,МП_Periods!AE415,МП_Periods!AE530,МП_Periods!AE645,МП_Periods!AE760,МП_Periods!AE875,МП_Periods!AE990,МП_Periods!AE1105,МП_Periods!AE1220,МП_Periods!AE1335) -> 0 | AQ69: =IFERROR(#REF!/AP69,"-") -> - | AS69: =IFERROR(U69/AG69,"-") -> - | AT69: =SUM(МП_Periods!AI69,МП_Periods!AI184,МП_Periods!AI299,МП_Periods!AI415,МП_Periods!AI530,МП_Periods!AI645,МП_Periods!AI760,МП_Periods!AI875,МП_Periods!AI990,МП_Periods!AI1105,МП_Periods!AI1220,МП_Periods!AI1335) -> 0 | AU69: =IFERROR(AC69/AT69,"-") -> - | AW69: =IFERROR(AX69/AT69,"-") -> - | AX69: =SUM(МП_Periods!AM69,МП_Periods!AM184,МП_Periods!AM299,МП_Periods!AM415,МП_Periods!AM530,МП_Periods!AM645,МП_Periods!AM760,МП_Periods!AM875,МП_Periods!AM990,МП_Periods!AM1105,МП_Periods!AM1220,МП_Periods!AM1335,) -> 0 | AY69: =IFERROR(AC69/AX69,"-") -> - | AZ69: =IFERROR(AX69/$AX$115,"-") -> - | BB69: =IFERROR(BE69/AC69,"-") -> - | BC69: =IFERROR(AC69/BE69,"-") -> - | BD69: =IFERROR(BE69/AX69,"-") -> - | BE69: =SUM(МП_Periods!AT69,МП_Periods!AT184,МП_Periods!AT299,МП_Periods!AT414,МП_Periods!AT530,МП_Periods!AT645,МП_Periods!AT760,МП_Periods!AT875,МП_Periods!AT990,МП_Periods!AT1105,МП_Periods!AT1220,МП_Periods!AT1335) -> 0 | BF69: =IFERROR(BE69/$BE$115,"-") -> - | BH69: =IFERROR(BI69/AX69,"-") -> - | BI69: =SUM(МП_Periods!AX69,МП_Periods!AX184,МП_Periods!AX299,МП_Periods!AX415,МП_Periods!AX530,МП_Periods!AX645,МП_Periods!AX760,МП_Periods!AX875,МП_Periods!AX990,МП_Periods!AX1105,МП_Periods!AX1220,МП_Periods!AX1335) -> 0 | BJ69: =IFERROR(AC69/BI69,"-") -> - | BK69: =IFERROR(BI69/$AX$115,"-") -> - | BM69: =IFERROR(BP69/AC69,"-") -> - | BN69: =IFERROR(AC69/BP69,"-") -> - | BO69: =IFERROR(BP69/BI69,"-") -> - | BP69: =SUM(МП_Periods!BE69,МП_Periods!BE184,МП_Periods!BE299,МП_Periods!BE415,МП_Periods!BE530,МП_Periods!BE645,МП_Periods!BE760,МП_Periods!BE875,МП_Periods!BE990,МП_Periods!BE1105,МП_Periods!BE1220,МП_Periods!BE1335) -> 0 | BQ69: =IFERROR(BP69/$BP$115,"-") -> -
S70: CPC | T70: =IFERROR(W70/U70,"-") -> - | U70: =SUM(МП_Periods!J70,МП_Periods!J185,МП_Periods!J300,МП_Periods!J416,МП_Periods!J531,МП_Periods!J646,МП_Periods!J761,МП_Periods!J876,МП_Periods!J991,МП_Periods!J1106,МП_Periods!J1221,МП_Periods!J1336) -> 0 | W70: =SUM(МП_Periods!L70,МП_Periods!L185,МП_Periods!L300,МП_Periods!L416,МП_Periods!L531,МП_Periods!L646,МП_Periods!L761,МП_Periods!L876,МП_Periods!L991,МП_Periods!L1106,МП_Periods!L1221,МП_Periods!L1336) -> 0 | Y70: =SUM(МП_Periods!N70,МП_Periods!N185,МП_Periods!N300,МП_Periods!N416,МП_Periods!N531,МП_Periods!N646,МП_Periods!N761,МП_Periods!N876,МП_Periods!N991,МП_Periods!N1106,МП_Periods!N1221,МП_Periods!N1336) -> 0 | AA70: =SUM(МП_Periods!P70,МП_Periods!P185,МП_Periods!P300,МП_Periods!P416,МП_Periods!P531,МП_Periods!P646,МП_Periods!P761,МП_Periods!P876,МП_Periods!P991,МП_Periods!P1106,МП_Periods!P1221,МП_Periods!P1336) -> 0 | AB70: =SUM(МП_Periods!Q70,МП_Periods!Q185,МП_Periods!Q300,МП_Periods!Q416,МП_Periods!Q531,МП_Periods!Q646,МП_Periods!Q761,МП_Periods!Q876,МП_Periods!Q991,МП_Periods!Q1106,МП_Periods!Q1221,МП_Periods!Q1336) -> 0 | AC70: =SUM(МП_Periods!R70,МП_Periods!R185,МП_Periods!R300,МП_Periods!R416,МП_Periods!R531,МП_Periods!R646,МП_Periods!R761,МП_Periods!R876,МП_Periods!R991,МП_Periods!R1106,МП_Periods!R1221,МП_Periods!R1336) -> 0 | AD70: =SUM(МП_Periods!S70,МП_Periods!S185,МП_Periods!S300,МП_Periods!S416,МП_Periods!S531,МП_Periods!S646,МП_Periods!S761,МП_Periods!S876,МП_Periods!S991,МП_Periods!S1106,МП_Periods!S1221,МП_Periods!S1336) -> 0 | AE70: =IFERROR(AC70/$AC$115,"-") -> - | AG70: =SUM(МП_Periods!V70,МП_Periods!V185,МП_Periods!V300,МП_Periods!V416,МП_Periods!V531,МП_Periods!V646,МП_Periods!V761,МП_Periods!V876,МП_Periods!V991,МП_Periods!V1106,МП_Periods!V1221,МП_Periods!V1336) -> 0 | AJ70: =SUM(МП_Periods!Y70,МП_Periods!Y185,МП_Periods!Y300,МП_Periods!Y416,МП_Periods!Y531,МП_Periods!Y646,МП_Periods!Y761,МП_Periods!Y876,МП_Periods!Y991,МП_Periods!Y1106,МП_Periods!Y1221,МП_Periods!Y1336) -> 0 | AK70: =SUM(МП_Periods!Z70,МП_Periods!Z185,МП_Periods!Z300,МП_Periods!Z416,МП_Periods!Z531,МП_Periods!Z646,МП_Periods!Z761,МП_Periods!Z876,МП_Periods!Z991,МП_Periods!Z1106,МП_Periods!Z1221,МП_Periods!Z1336) -> 0 | AL70: =SUM(МП_Periods!AA70,МП_Periods!AA185,МП_Periods!AA300,МП_Periods!AA416,МП_Periods!AA531,МП_Periods!AA646,МП_Periods!AA761,МП_Periods!AA876,МП_Periods!AA991,МП_Periods!AA1106,МП_Periods!AA1221,МП_Periods!AA1336) -> 0 | AM70: =SUM(МП_Periods!AB70,МП_Periods!AB185,МП_Periods!AB300,МП_Periods!AB416,МП_Periods!AB531,МП_Periods!AB646,МП_Periods!AB761,МП_Periods!AB876,МП_Periods!AB991,МП_Periods!AB1106,МП_Periods!AB1221,МП_Periods!AB1336) -> 0 | AO70: =IFERROR(AC70/AM70,"-") -> - | AP70: =SUM(МП_Periods!AE70,МП_Periods!AE185,МП_Periods!AE300,МП_Periods!AE416,МП_Periods!AE531,МП_Periods!AE646,МП_Periods!AE761,МП_Periods!AE876,МП_Periods!AE991,МП_Periods!AE1106,МП_Periods!AE1221,МП_Periods!AE1336) -> 0 | AQ70: =IFERROR(#REF!/AP70,"-") -> - | AS70: =IFERROR(U70/AG70,"-") -> - | AT70: =SUM(МП_Periods!AI70,МП_Periods!AI185,МП_Periods!AI300,МП_Periods!AI416,МП_Periods!AI531,МП_Periods!AI646,МП_Periods!AI761,МП_Periods!AI876,МП_Periods!AI991,МП_Periods!AI1106,МП_Periods!AI1221,МП_Periods!AI1336) -> 0 | AU70: =IFERROR(AC70/AT70,"-") -> - | AW70: =IFERROR(AX70/AT70,"-") -> - | AX70: =SUM(МП_Periods!AM70,МП_Periods!AM185,МП_Periods!AM300,МП_Periods!AM416,МП_Periods!AM531,МП_Periods!AM646,МП_Periods!AM761,МП_Periods!AM876,МП_Periods!AM991,МП_Periods!AM1106,МП_Periods!AM1221,МП_Periods!AM1336,) -> 0 | AY70: =IFERROR(AC70/AX70,"-") -> - | AZ70: =IFERROR(AX70/$AX$115,"-") -> - | BB70: =IFERROR(BE70/AC70,"-") -> - | BC70: =IFERROR(AC70/BE70,"-") -> - | BD70: =IFERROR(BE70/AX70,"-") -> - | BE70: =SUM(МП_Periods!AT70,МП_Periods!AT185,МП_Periods!AT300,МП_Periods!AT415,МП_Periods!AT531,МП_Periods!AT646,МП_Periods!AT761,МП_Periods!AT876,МП_Periods!AT991,МП_Periods!AT1106,МП_Periods!AT1221,МП_Periods!AT1336) -> 0 | BF70: =IFERROR(BE70/$BE$115,"-") -> - | BH70: =IFERROR(BI70/AX70,"-") -> - | BI70: =SUM(МП_Periods!AX70,МП_Periods!AX185,МП_Periods!AX300,МП_Periods!AX416,МП_Periods!AX531,МП_Periods!AX646,МП_Periods!AX761,МП_Periods!AX876,МП_Periods!AX991,МП_Periods!AX1106,МП_Periods!AX1221,МП_Periods!AX1336) -> 0 | BJ70: =IFERROR(AC70/BI70,"-") -> - | BK70: =IFERROR(BI70/$AX$115,"-") -> - | BM70: =IFERROR(BP70/AC70,"-") -> - | BN70: =IFERROR(AC70/BP70,"-") -> - | BO70: =IFERROR(BP70/BI70,"-") -> - | BP70: =SUM(МП_Periods!BE70,МП_Periods!BE185,МП_Periods!BE300,МП_Periods!BE416,МП_Periods!BE531,МП_Periods!BE646,МП_Periods!BE761,МП_Periods!BE876,МП_Periods!BE991,МП_Periods!BE1106,МП_Periods!BE1221,МП_Periods!BE1336) -> 0 | BQ70: =IFERROR(BP70/$BP$115,"-") -> -
... S113: CPC | T113: =IFERROR(W113/U113,"-") -> - | U113: =SUM(МП_Periods!J113,МП_Periods!J228,МП_Periods!J343,МП_Periods!J459,МП_Periods!J574,МП_Periods!J689,МП_Periods!J804,МП_Periods!J919,МП_Periods!J1034,МП_Periods!J1149,МП_Periods!J1264,МП_Periods!J1379) -> 0 | W113: =SUM(МП_Periods!L113,МП_Periods!L228,МП_Periods!L343,МП_Periods!L459,МП_Periods!L574,МП_Periods!L689,МП_Periods!L804,МП_Periods!L919,МП_Periods!L1034,МП_Periods!L1149,МП_Periods!L1264,МП_Periods!L1379) -> 0 | Y113: =SUM(МП_Periods!N113,МП_Periods!N228,МП_Periods!N343,МП_Periods!N459,МП_Periods!N574,МП_Periods!N689,МП_Periods!N804,МП_Periods!N919,МП_Periods!N1034,МП_Periods!N1149,МП_Periods!N1264,МП_Periods!N1379) -> 0 | AA113: =SUM(МП_Periods!P113,МП_Periods!P228,МП_Periods!P343,МП_Periods!P459,МП_Periods!P574,МП_Periods!P689,МП_Periods!P804,МП_Periods!P919,МП_Periods!P1034,МП_Periods!P1149,МП_Periods!P1264,МП_Periods!P1379) -> 0 | AB113: =SUM(МП_Periods!Q113,МП_Periods!Q228,МП_Periods!Q343,МП_Periods!Q459,МП_Periods!Q574,МП_Periods!Q689,МП_Periods!Q804,МП_Periods!Q919,МП_Periods!Q1034,МП_Periods!Q1149,МП_Periods!Q1264,МП_Periods!Q1379) -> 0 | AC113: =SUM(МП_Periods!R113,МП_Periods!R228,МП_Periods!R343,МП_Periods!R459,МП_Periods!R574,МП_Periods!R689,МП_Periods!R804,МП_Periods!R919,МП_Periods!R1034,МП_Periods!R1149,МП_Periods!R1264,МП_Periods!R1379) -> 0 | AD113: =SUM(МП_Periods!S113,МП_Periods!S228,МП_Periods!S343,МП_Periods!S459,МП_Periods!S574,МП_Periods!S689,МП_Periods!S804,МП_Periods!S919,МП_Periods!S1034,МП_Periods!S1149,МП_Periods!S1264,МП_Periods!S1379) -> 0 | AE113: =IFERROR(AC113/$AC$115,"-") -> - | AG113: =SUM(МП_Periods!V113,МП_Periods!V228,МП_Periods!V343,МП_Periods!V459,МП_Periods!V574,МП_Periods!V689,МП_Periods!V804,МП_Periods!V919,МП_Periods!V1034,МП_Periods!V1149,МП_Periods!V1264,МП_Periods!V1379) -> 0 | AJ113: =SUM(МП_Periods!Y113,МП_Periods!Y228,МП_Periods!Y343,МП_Periods!Y459,МП_Periods!Y574,МП_Periods!Y689,МП_Periods!Y804,МП_Periods!Y919,МП_Periods!Y1034,МП_Periods!Y1149,МП_Periods!Y1264,МП_Periods!Y1379) -> 0 | AK113: =SUM(МП_Periods!Z113,МП_Periods!Z228,МП_Periods!Z343,МП_Periods!Z459,МП_Periods!Z574,МП_Periods!Z689,МП_Periods!Z804,МП_Periods!Z919,МП_Periods!Z1034,МП_Periods!Z1149,МП_Periods!Z1264,МП_Periods!Z1379) -> 0 | AL113: =SUM(МП_Periods!AA113,МП_Periods!AA228,МП_Periods!AA343,МП_Periods!AA459,МП_Periods!AA574,МП_Periods!AA689,МП_Periods!AA804,МП_Periods!AA919,МП_Periods!AA1034,МП_Periods!AA1149,МП_Periods!AA1264,МП_Periods!AA1379) -> 0 | AM113: =SUM(МП_Periods!AB113,МП_Periods!AB228,МП_Periods!AB343,МП_Periods!AB459,МП_Periods!AB574,МП_Periods!AB689,МП_Periods!AB804,МП_Periods!AB919,МП_Periods!AB1034,МП_Periods!AB1149,МП_Periods!AB1264,МП_Periods!AB1379) -> 0 | AO113: =IFERROR(AC113/AM113,"-") -> - | AP113: =SUM(МП_Periods!AE113,МП_Periods!AE228,МП_Periods!AE343,МП_Periods!AE459,МП_Periods!AE574,МП_Periods!AE689,МП_Periods!AE804,МП_Periods!AE919,МП_Periods!AE1034,МП_Periods!AE1149,МП_Periods!AE1264,МП_Periods!AE1379) -> 0 | AQ113: =IFERROR(#REF!/AP113,"-") -> - | AS113: =IFERROR(U113/AG113,"-") -> - | AT113: =SUM(МП_Periods!AI113,МП_Periods!AI228,МП_Periods!AI343,МП_Periods!AI459,МП_Periods!AI574,МП_Periods!AI689,МП_Periods!AI804,МП_Periods!AI919,МП_Periods!AI1034,МП_Periods!AI1149,МП_Periods!AI1264,МП_Periods!AI1379) -> 0 | AU113: =IFERROR(AC113/AT113,"-") -> - | AW113: =IFERROR(AX113/AT113,"-") -> - | AX113: =SUM(МП_Periods!AM113,МП_Periods!AM228,МП_Periods!AM343,МП_Periods!AM459,МП_Periods!AM574,МП_Periods!AM689,МП_Periods!AM804,МП_Periods!AM919,МП_Periods!AM1034,МП_Periods!AM1149,МП_Periods!AM1264,МП_Periods!AM1379,) -> 0 | AY113: =IFERROR(AC113/AX113,"-") -> - | AZ113: =IFERROR(AX113/$AX$115,"-") -> - | BB113: =IFERROR(BE113/AC113,"-") -> - | BC113: =IFERROR(AC113/BE113,"-") -> - | BD113: =IFERROR(BE113/AX113,"-") -> - | BE113: =SUM(МП_Periods!AT113,МП_Periods!AT228,МП_Periods!AT343,МП_Periods!AT458,МП_Periods!AT574,МП_Periods!AT689,МП_Periods!AT804,МП_Periods!AT919,МП_Periods!AT1034,МП_Periods!AT1149,МП_Periods!AT1264,МП_Periods!AT1379) -> 0 | BF113: =IFERROR(BE113/$BE$115,"-") -> - | BH113: =IFERROR(BI113/AX113,"-") -> - | BI113: =SUM(МП_Periods!AX113,МП_Periods!AX228,МП_Periods!AX343,МП_Periods!AX459,МП_Periods!AX574,МП_Periods!AX689,МП_Periods!AX804,МП_Periods!AX919,МП_Periods!AX1034,МП_Periods!AX1149,МП_Periods!AX1264,МП_Periods!AX1379) -> 0 | BJ113: =IFERROR(AC113/BI113,"-") -> - | BK113: =IFERROR(BI113/$AX$115,"-") -> - | BM113: =IFERROR(BP113/AC113,"-") -> - | BN113: =IFERROR(AC113/BP113,"-") -> - | BO113: =IFERROR(BP113/BI113,"-") -> - | BP113: =SUM(МП_Periods!BE113,МП_Periods!BE228,МП_Periods!BE343,МП_Periods!BE459,МП_Periods!BE574,МП_Periods!BE689,МП_Periods!BE804,МП_Periods!BE919,МП_Periods!BE1034,МП_Periods!BE1149,МП_Periods!BE1264,МП_Periods!BE1379) -> 0 | BQ113: =IFERROR(BP113/$BP$115,"-") -> -
B114: ИТОГО B2B | C114: - | D114: - | F114: - | G114: - | H114: - | I114: - | J114: - | K114: - | L114: - | M114: - | N114: - | O114: - | P114: - | Q114: - | S114: - | T114: =IFERROR(W114/U114,"-") -> - | U114: =SUM(U59:U113) -> 0 | W114: =IFERROR(SUM(W59:W113),"-") -> 0 | X114: - | Y114: =IFERROR(SUM(Y59:Y113),"-") -> 0 | Z114: - | AA114: =IFERROR(AB114-Y114,"-") -> 0 | AB114: =IFERROR(SUM(AB59:AB113),"-") -> 0 | AC114: =IFERROR(SUM(AC59:AC113),"-") -> 0 | AD114: =IFERROR(AC114-AB114,"-") -> 0 | AE114: =SUM(AE59:AE113) -> 0 | AG114: =SUM(AG59:AG113) -> 0 | AH114: - | AI114: - | AJ114: =SUM(AJ59:AJ113) -> 0 | AK114: =SUM(AK59:AK113) -> 0 | AL114: =SUM(AL59:AL113) -> 0 | AM114: =SUM(AM59:AM113) -> 0 | AO114: =IFERROR(AC114/AM114,"-") -> - | AP114: - | AQ114: - | AS114: =IFERROR(AT114/AG114,"-") -> - | AT114: =SUM(AT59:AT113) -> 0 | AU114: =IFERROR(AC114/AT114,"-") -> - | AW114: =IFERROR(AX114/AT114,"-") -> - | AX114: =SUM(AX59:AX113) -> 0 | AY114: =IFERROR(AC114/AX114,"-") -> - | AZ114: =SUM(AZ59:AZ113) -> 0 | BB114: =IFERROR(BE114/AC114,"-") -> - | BC114: =IFERROR(AC114/BE114,"-") -> - | BD114: =IFERROR(BE114/AX114,"-") -> - | BE114: =IFERROR(SUM(BE59:BE113),"-") -> 0 | BF114: =SUM(BF59:BF113) -> 0 | BH114: =IFERROR(BI114/AX114,"-") -> - | BI114: =SUM(BI59:BI113) -> 0 | BJ114: =IFERROR(AC114/BI114,"-") -> - | BK114: =SUM(BK59:BK113) -> 0 | BM114: =IFERROR(BP114/AC114,"-") -> - | BN114: =IFERROR(AC114/BP114,"-") -> - | BO114: =IFERROR(BP114/BI114,"-") -> - | BP114: =SUM(BP59:BP113) -> 0 | BQ114: =SUM(BQ59:BQ113) -> 0
B115: Итого | C115: - | D115: - | S115: - | T115: =IFERROR(W115/U115,"-") -> - | U115: =U114+U58 -> 0 | W115: =IFERROR(SUM(W114,W58),"-") -> 0 | X115: - | Y115: =IFERROR(SUM(Y114,Y58),"-") -> 0 | Z115: - | AA115: =IFERROR(AB115-Y115,"-") -> 0 | AB115: =IFERROR(SUM(AB114,AB58),"-") -> 0 | AC115: =IFERROR(SUM(AC114,AC58),"-") -> 0 | AD115: =IFERROR(AC115-AB115,"-") -> 0 | AE115: =SUM(AE58,AE114) -> 0 | AG115: =AG114+AG58 -> 0 | AH115: - | AI115: - | AJ115: =SUM(AJ114,AJ58) -> 0 | AK115: =SUM(AK114,AK58) -> 0 | AL115: =SUM(AL114,AL58) -> 0 | AM115: =SUM(AM114,AM58) -> 0 | AO115: =IFERROR(AC115/AM115,"-") -> - | AP115: - | AQ115: - | AS115: =IFERROR(AT115/AG115,"-") -> - | AT115: =AT114+AT58 -> 0 | AU115: =IFERROR(AC115/AT115,"-") -> - | AW115: =IFERROR(AX115/AT115,"-") -> - | AX115: =AX114+AX58 -> 0 | AY115: =IFERROR(AC115/AX115,"-") -> - | AZ115: =SUM(AZ58,AZ114) -> 0 | BB115: =IFERROR(BE115/AC115,"-") -> - | BC115: =IFERROR(AC115/BE115,"-") -> - | BD115: =IFERROR(BE115/AX115,"-") -> - | BE115: =IFERROR(SUM(BE58,BE114),"-") -> 0 | BF115: =SUM(BF58,BF114) -> 0 | BH115: =IFERROR(BI115/AX115,"-") -> - | BI115: =BI114+BI58 -> 0 | BJ115: =IFERROR(AC115/BI115,"-") -> - | BK115: =SUM(BK58,BK114) -> 0 | BM115: =IFERROR(BP115/AC115,"-") -> - | BN115: =IFERROR(AC115/BP115,"-") -> - | BO115: =IFERROR(BP115/BI115,"-") -> - | BP115: =SUM(BP114,BP58) -> 0 | BQ115: =SUM(BQ58,BQ114) -> 0
B117: Медиабюджет до НДС | C117: =IFERROR(W115,"-") -> 0
B118: Агентская комиссия до НДС | C118: =IFERROR((AB115-Y115),"-") -> 0
B119: Медиабюджет с АК до НДС | C119: =IFERROR(SUM(C117:C118),"-") -> 0
B120: НДС | C120: =AD115 -> 0
B121: Медиабюджет с АК и НДС | C121: =IFERROR(SUM(C119:C120),"-") -> 0
B122: Разработка креативов | C122: 0
B123: Настройка аналитики | C123: 0
B124: Итого с АК и НДС | C124: =IFERROR(SUM(C121:C123),"-") -> 0

Sheet МП_Periods
B2: Рекламная система | C2: Рекламный формат, размер, вид размещения | D2: Таргетинги | E2: ГЕО | G2: Период | H2: Единица измерения стоимости | I2: Цена за единицу (без НДС) | J2: Кол-во единиц | L2: Стоимость (без НДС) | M2: СК, % | N2: Тотал бюджет, руб. без НДС и АК | O2: АК, % | P2: АК, руб. (без НДС) | Q2: Тотал бюджет, руб. без НДС и с учетом АК | R2: Тотал бюджет руб. с учетом НДС и АК | S2: НДС руб. | T2: Доля рекламного бюджета, % | V2: Кол-во показов | W2: Частота (весь срок) | X2: Доля новых клиентов, % | Y2: Кол-во клиентов | Z2: Кол-во абсолютно новых клиентов (ранее не заказывали) | AA2: Кол-во вернувшихся клиентов (не заказывали более 12 мес) | AB2: Кол-во новых клиентов (абсолютно новые + вернувшиеся) | AC2: Частота заказа | AD2: САС, руб. | AE2: Доступная емкость аудитории | AF2: SOV, % | AH2: CTR, % | AI2: Клики | AJ2: CPC (с НДС) | AL2: CR, % | AM2: Кол-во оформленных заказов | AN2: Стоимость оформл. заказа, руб. с НДС | AO2: Доля заказов, % | AQ2: ROAS офомл. (Доход/Бюджет) | AR2: ДРР от оформл. дохода, % | AS2: Средний чек по оформл. доходу, с НДС | AT2: Оформленный доход, руб. с НДС | AU2: Доля заказов, % | AW2: CR2, % | AX2: Кол-во отгруженных заказов | AY2: Стоимость отгр. заказа, руб. с НДС | AZ2: Доля заказов, % | BB2: ROAS отгр. (Выручка/Бюджет) | BC2: ДРР от выручки, % | BD2: Средний чек по выручке, с НДС | BE2: Выручка (отгруженный доход), руб. с НДС | BF2: Доля заказов, %
G3: 01.02.2026 - 28.02.2026 | H3: CPC | J3: =IFERROR(V3*AH3,"-") -> 0 | L3: =IFERROR((I3*J3),"-") -> 0 | N3: =IFERROR(L3*(1-M3),"-") -> 0 | P3: =IFERROR(Q3-N3,"-") -> 0 | Q3: =IFERROR(N3*(1+O3),"-") -> 0 | R3: =IFERROR(Q3*1.22,"-") -> 0 | S3: =IFERROR(R3-Q3,"-") -> 0 | T3: =IFERROR(R3/$R$115,"-") -> - | X3: =IFERROR(AB3/Y3,"-") -> - | AB3: =SUM(Z3:AA3) -> 0 | AD3: =IFERROR(R3/AB3,"-") -> - | AF3: =IFERROR(#REF!/AE3,"-") -> - | AI3: =IFERROR(ROUNDDOWN(V3*AH3,0),"-") -> 0 | AJ3: =IFERROR(R3/AI3,"-") -> - | AM3: =IFERROR(ROUNDDOWN(AI3*AL3,0),"-") -> 0 | AN3: =IFERROR(R3/AM3,"-") -> - | AO3: =IFERROR(AM3/$AM$230,"-") -> - | AQ3: =IFERROR(AT3/R3,"-") -> - | AR3: =IFERROR(R3/AT3,"-") -> - | AT3: =AS3*AM3 -> 0 | AU3: =IFERROR(AT3/$AT$230,"-") -> - | AX3: =IFERROR(ROUNDDOWN(AM3*AW3,0),"-") -> 0 | AY3: =IFERROR(R3/AX3,"-") -> - | AZ3: =IFERROR(AX3/$AM$230,"-") -> - | BB3: =IFERROR(BE3/R3,"-") -> - | BC3: =IFERROR(R3/BE3,"-") -> - | BE3: =BD3*AX3 -> 0 | BF3: =IFERROR(BE3/$AT$230,"-") -> -
G4: 01.02.2026 - 28.02.2026 | H4: CPC | J4: =IFERROR(V4*AH4,"-") -> 0 | L4: =IFERROR((I4*J4),"-") -> 0 | N4: =IFERROR(L4*(1-M4),"-") -> 0 | P4: =IFERROR(Q4-N4,"-") -> 0 | Q4: =IFERROR(N4*(1+O4),"-") -> 0 | R4: =IFERROR(Q4*1.22,"-") -> 0 | S4: =IFERROR(R4-Q4,"-") -> 0 | T4: =IFERROR(R4/$R$115,"-") -> - | X4: =IFERROR(AB4/Y4,"-") -> - | AB4: =SUM(Z4:AA4) -> 0 | AD4: =IFERROR(R4/AB4,"-") -> - | AF4: =IFERROR(#REF!/AE4,"-") -> - | AI4: =IFERROR(ROUNDDOWN(V4*AH4,0),"-") -> 0 | AJ4: =IFERROR(R4/AI4,"-") -> - | AM4: =IFERROR(ROUNDDOWN(AI4*AL4,0),"-") -> 0 | AN4: =IFERROR(R4/AM4,"-") -> - | AO4: =IFERROR(AM4/$AM$230,"-") -> - | AQ4: =IFERROR(AT4/R4,"-") -> - | AR4: =IFERROR(R4/AT4,"-") -> - | AT4: =AS4*AM4 -> 0 | AU4: =IFERROR(AT4/$AT$230,"-") -> - | AX4: =IFERROR(ROUNDDOWN(AM4*AW4,0),"-") -> 0 | AY4: =IFERROR(R4/AX4,"-") -> - | AZ4: =IFERROR(AX4/$AM$230,"-") -> - | BB4: =IFERROR(BE4/R4,"-") -> - | BC4: =IFERROR(R4/BE4,"-") -> - | BE4: =BD4*AX4 -> 0 | BF4: =IFERROR(BE4/$AT$230,"-") -> -
G5: 01.02.2026 - 28.02.2026 | H5: CPC | J5: =IFERROR(V5*AH5,"-") -> 0 | L5: =IFERROR((I5*J5),"-") -> 0 | N5: =IFERROR(L5*(1-M5),"-") -> 0 | P5: =IFERROR(Q5-N5,"-") -> 0 | Q5: =IFERROR(N5*(1+O5),"-") -> 0 | R5: =IFERROR(Q5*1.22,"-") -> 0 | S5: =IFERROR(R5-Q5,"-") -> 0 | T5: =IFERROR(R5/$R$115,"-") -> - | X5: =IFERROR(AB5/Y5,"-") -> - | AB5: =SUM(Z5:AA5) -> 0 | AD5: =IFERROR(R5/AB5,"-") -> - | AF5: =IFERROR(#REF!/AE5,"-") -> - | AI5: =IFERROR(ROUNDDOWN(V5*AH5,0),"-") -> 0 | AJ5: =IFERROR(R5/AI5,"-") -> - | AM5: =IFERROR(ROUNDDOWN(AI5*AL5,0),"-") -> 0 | AN5: =IFERROR(R5/AM5,"-") -> - | AO5: =IFERROR(AM5/$AM$230,"-") -> - | AQ5: =IFERROR(AT5/R5,"-") -> - | AR5: =IFERROR(R5/AT5,"-") -> - | AT5: =AS5*AM5 -> 0 | AU5: =IFERROR(AT5/$AT$230,"-") -> - | AX5: =IFERROR(ROUNDDOWN(AM5*AW5,0),"-") -> 0 | AY5: =IFERROR(R5/AX5,"-") -> - | AZ5: =IFERROR(AX5/$AM$230,"-") -> - | BB5: =IFERROR(BE5/R5,"-") -> - | BC5: =IFERROR(R5/BE5,"-") -> - | BE5: =BD5*AX5 -> 0 | BF5: =IFERROR(BE5/$AT$230,"-") -> -
G6: 01.02.2026 - 28.02.2026 | H6: CPC | J6: =IFERROR(V6*AH6,"-") -> 0 | L6: =IFERROR((I6*J6),"-") -> 0 | N6: =IFERROR(L6*(1-M6),"-") -> 0 | P6: =IFERROR(Q6-N6,"-") -> 0 | Q6: =IFERROR(N6*(1+O6),"-") -> 0 | R6: =IFERROR(Q6*1.22,"-") -> 0 | S6: =IFERROR(R6-Q6,"-") -> 0 | T6: =IFERROR(R6/$R$115,"-") -> - | X6: =IFERROR(AB6/Y6,"-") -> - | AB6: =SUM(Z6:AA6) -> 0 | AD6: =IFERROR(R6/AB6,"-") -> - | AF6: =IFERROR(#REF!/AE6,"-") -> - | AI6: =IFERROR(ROUNDDOWN(V6*AH6,0),"-") -> 0 | AJ6: =IFERROR(R6/AI6,"-") -> - | AM6: =IFERROR(ROUNDDOWN(AI6*AL6,0),"-") -> 0 | AN6: =IFERROR(R6/AM6,"-") -> - | AO6: =IFERROR(AM6/$AM$230,"-") -> - | AQ6: =IFERROR(AT6/R6,"-") -> - | AR6: =IFERROR(R6/AT6,"-") -> - | AT6: =AS6*AM6 -> 0 | AU6: =IFERROR(AT6/$AT$230,"-") -> - | AX6: =IFERROR(ROUNDDOWN(AM6*AW6,0),"-") -> 0 | AY6: =IFERROR(R6/AX6,"-") -> - | AZ6: =IFERROR(AX6/$AM$230,"-") -> - | BB6: =IFERROR(BE6/R6,"-") -> - | BC6: =IFERROR(R6/BE6,"-") -> - | BE6: =BD6*AX6 -> 0 | BF6: =IFERROR(BE6/$AT$230,"-") -> -
G7: 01.02.2026 - 28.02.2026 | H7: CPC | J7: =IFERROR(V7*AH7,"-") -> 0 | L7: =IFERROR((I7*J7),"-") -> 0 | N7: =IFERROR(L7*(1-M7),"-") -> 0 | P7: =IFERROR(Q7-N7,"-") -> 0 | Q7: =IFERROR(N7*(1+O7),"-") -> 0 | R7: =IFERROR(Q7*1.22,"-") -> 0 | S7: =IFERROR(R7-Q7,"-") -> 0 | T7: =IFERROR(R7/$R$115,"-") -> - | X7: =IFERROR(AB7/Y7,"-") -> - | AB7: =SUM(Z7:AA7) -> 0 | AD7: =IFERROR(R7/AB7,"-") -> - | AF7: =IFERROR(#REF!/AE7,"-") -> - | AI7: =IFERROR(ROUNDDOWN(V7*AH7,0),"-") -> 0 | AJ7: =IFERROR(R7/AI7,"-") -> - | AM7: =IFERROR(ROUNDDOWN(AI7*AL7,0),"-") -> 0 | AN7: =IFERROR(R7/AM7,"-") -> - | AO7: =IFERROR(AM7/$AM$230,"-") -> - | AQ7: =IFERROR(AT7/R7,"-") -> - | AR7: =IFERROR(R7/AT7,"-") -> - | AT7: =AS7*AM7 -> 0 | AU7: =IFERROR(AT7/$AT$230,"-") -> - | AX7: =IFERROR(ROUNDDOWN(AM7*AW7,0),"-") -> 0 | AY7: =IFERROR(R7/AX7,"-") -> - | AZ7: =IFERROR(AX7/$AM$230,"-") -> - | BB7: =IFERROR(BE7/R7,"-") -> - | BC7: =IFERROR(R7/BE7,"-") -> - | BE7: =BD7*AX7 -> 0 | BF7: =IFERROR(BE7/$AT$230,"-") -> -
G8: 01.02.2026 - 28.02.2026 | H8: CPC | J8: =IFERROR(V8*AH8,"-") -> 0 | L8: =IFERROR((I8*J8),"-") -> 0 | N8: =IFERROR(L8*(1-M8),"-") -> 0 | P8: =IFERROR(Q8-N8,"-") -> 0 | Q8: =IFERROR(N8*(1+O8),"-") -> 0 | R8: =IFERROR(Q8*1.22,"-") -> 0 | S8: =IFERROR(R8-Q8,"-") -> 0 | T8: =IFERROR(R8/$R$115,"-") -> - | X8: =IFERROR(AB8/Y8,"-") -> - | AB8: =SUM(Z8:AA8) -> 0 | AD8: =IFERROR(R8/AB8,"-") -> - | AF8: =IFERROR(#REF!/AE8,"-") -> - | AI8: =IFERROR(ROUNDDOWN(V8*AH8,0),"-") -> 0 | AJ8: =IFERROR(R8/AI8,"-") -> - | AM8: =IFERROR(ROUNDDOWN(AI8*AL8,0),"-") -> 0 | AN8: =IFERROR(R8/AM8,"-") -> - | AO8: =IFERROR(AM8/$AM$230,"-") -> - | AQ8: =IFERROR(AT8/R8,"-") -> - | AR8: =IFERROR(R8/AT8,"-") -> - | AT8: =AS8*AM8 -> 0 | AU8: =IFERROR(AT8/$AT$230,"-") -> - | AX8: =IFERROR(ROUNDDOWN(AM8*AW8,0),"-") -> 0 | AY8: =IFERROR(R8/AX8,"-") -> - | AZ8: =IFERROR(AX8/$AM$230,"-") -> - | BB8: =IFERROR(BE8/R8,"-") -> - | BC8: =IFERROR(R8/BE8,"-") -> - | BE8: =BD8*AX8 -> 0 | BF8: =IFERROR(BE8/$AT$230,"-") -> -
G9: 01.02.2026 - 28.02.2026 | H9: CPC | J9: =IFERROR(V9*AH9,"-") -> 0 | L9: =IFERROR((I9*J9),"-") -> 0 | N9: =IFERROR(L9*(1-M9),"-") -> 0 | P9: =IFERROR(Q9-N9,"-") -> 0 | Q9: =IFERROR(N9*(1+O9),"-") -> 0 | R9: =IFERROR(Q9*1.22,"-") -> 0 | S9: =IFERROR(R9-Q9,"-") -> 0 | T9: =IFERROR(R9/$R$115,"-") -> - | X9: =IFERROR(AB9/Y9,"-") -> - | AB9: =SUM(Z9:AA9) -> 0 | AD9: =IFERROR(R9/AB9,"-") -> - | AF9: =IFERROR(#REF!/AE9,"-") -> - | AI9: =IFERROR(ROUNDDOWN(V9*AH9,0),"-") -> 0 | AJ9: =IFERROR(R9/AI9,"-") -> - | AM9: =IFERROR(ROUNDDOWN(AI9*AL9,0),"-") -> 0 | AN9: =IFERROR(R9/AM9,"-") -> - | AO9: =IFERROR(AM9/$AM$230,"-") -> - | AQ9: =IFERROR(AT9/R9,"-") -> - | AR9: =IFERROR(R9/AT9,"-") -> - | AT9: =AS9*AM9 -> 0 | AU9: =IFERROR(AT9/$AT$230,"-") -> - | AX9: =IFERROR(ROUNDDOWN(AM9*AW9,0),"-") -> 0 | AY9: =IFERROR(R9/AX9,"-") -> - | AZ9: =IFERROR(AX9/$AM$230,"-") -> - | BB9: =IFERROR(BE9/R9,"-") -> - | BC9: =IFERROR(R9/BE9,"-") -> - | BE9: =BD9*AX9 -> 0 | BF9: =IFERROR(BE9/$AT$230,"-") -> -
G10: 01.02.2026 - 28.02.2026 | H10: CPC | J10: =IFERROR(V10*AH10,"-") -> 0 | L10: =IFERROR((I10*J10),"-") -> 0 | N10: =IFERROR(L10*(1-M10),"-") -> 0 | P10: =IFERROR(Q10-N10,"-") -> 0 | Q10: =IFERROR(N10*(1+O10),"-") -> 0 | R10: =IFERROR(Q10*1.22,"-") -> 0 | S10: =IFERROR(R10-Q10,"-") -> 0 | T10: =IFERROR(R10/$R$115,"-") -> - | X10: =IFERROR(AB10/Y10,"-") -> - | AB10: =SUM(Z10:AA10) -> 0 | AD10: =IFERROR(R10/AB10,"-") -> - | AF10: =IFERROR(#REF!/AE10,"-") -> - | AI10: =IFERROR(ROUNDDOWN(V10*AH10,0),"-") -> 0 | AJ10: =IFERROR(R10/AI10,"-") -> - | AM10: =IFERROR(ROUNDDOWN(AI10*AL10,0),"-") -> 0 | AN10: =IFERROR(R10/AM10,"-") -> - | AO10: =IFERROR(AM10/$AM$230,"-") -> - | AQ10: =IFERROR(AT10/R10,"-") -> - | AR10: =IFERROR(R10/AT10,"-") -> - | AT10: =AS10*AM10 -> 0 | AU10: =IFERROR(AT10/$AT$230,"-") -> - | AX10: =IFERROR(ROUNDDOWN(AM10*AW10,0),"-") -> 0 | AY10: =IFERROR(R10/AX10,"-") -> - | AZ10: =IFERROR(AX10/$AM$230,"-") -> - | BB10: =IFERROR(BE10/R10,"-") -> - | BC10: =IFERROR(R10/BE10,"-") -> - | BE10: =BD10*AX10 -> 0 | BF10: =IFERROR(BE10/$AT$230,"-") -> -
G11: 01.02.2026 - 28.02.2026 | H11: CPC | J11: =IFERROR(V11*AH11,"-") -> 0 | L11: =IFERROR((I11*J11),"-") -> 0 | N11: =IFERROR(L11*(1-M11),"-") -> 0 | P11: =IFERROR(Q11-N11,"-") -> 0 | Q11: =IFERROR(N11*(1+O11),"-") -> 0 | R11: =IFERROR(Q11*1.22,"-") -> 0 | S11: =IFERROR(R11-Q11,"-") -> 0 | T11: =IFERROR(R11/$R$115,"-") -> - | X11: =IFERROR(AB11/Y11,"-") -> - | AB11: =SUM(Z11:AA11) -> 0 | AD11: =IFERROR(R11/AB11,"-") -> - | AF11: =IFERROR(#REF!/AE11,"-") -> - | AI11: =IFERROR(ROUNDDOWN(V11*AH11,0),"-") -> 0 | AJ11: =IFERROR(R11/AI11,"-") -> - | AM11: =IFERROR(ROUNDDOWN(AI11*AL11,0),"-") -> 0 | AN11: =IFERROR(R11/AM11,"-") -> - | AO11: =IFERROR(AM11/$AM$230,"-") -> - | AQ11: =IFERROR(AT11/R11,"-") -> - | AR11: =IFERROR(R11/AT11,"-") -> - | AT11: =AS11*AM11 -> 0 | AU11: =IFERROR(AT11/$AT$230,"-") -> - | AX11: =IFERROR(ROUNDDOWN(AM11*AW11,0),"-") -> 0 | AY11: =IFERROR(R11/AX11,"-") -> - | AZ11: =IFERROR(AX11/$AM$230,"-") -> - | BB11: =IFERROR(BE11/R11,"-") -> - | BC11: =IFERROR(R11/BE11,"-") -> - | BE11: =BD11*AX11 -> 0 | BF11: =IFERROR(BE11/$AT$230,"-") -> -
G12: 01.02.2026 - 28.02.2026 | H12: CPC | J12: =IFERROR(V12*AH12,"-") -> 0 | L12: =IFERROR((I12*J12),"-") -> 0 | N12: =IFERROR(L12*(1-M12),"-") -> 0 | P12: =IFERROR(Q12-N12,"-") -> 0 | Q12: =IFERROR(N12*(1+O12),"-") -> 0 | R12: =IFERROR(Q12*1.22,"-") -> 0 | S12: =IFERROR(R12-Q12,"-") -> 0 | T12: =IFERROR(R12/$R$115,"-") -> - | X12: =IFERROR(AB12/Y12,"-") -> - | AB12: =SUM(Z12:AA12) -> 0 | AD12: =IFERROR(R12/AB12,"-") -> - | AF12: =IFERROR(#REF!/AE12,"-") -> - | AI12: =IFERROR(ROUNDDOWN(V12*AH12,0),"-") -> 0 | AJ12: =IFERROR(R12/AI12,"-") -> - | AM12: =IFERROR(ROUNDDOWN(AI12*AL12,0),"-") -> 0 | AN12: =IFERROR(R12/AM12,"-") -> - | AO12: =IFERROR(AM12/$AM$230,"-") -> - | AQ12: =IFERROR(AT12/R12,"-") -> - | AR12: =IFERROR(R12/AT12,"-") -> - | AT12: =AS12*AM12 -> 0 | AU12: =IFERROR(AT12/$AT$230,"-") -> - | AX12: =IFERROR(ROUNDDOWN(AM12*AW12,0),"-") -> 0 | AY12: =IFERROR(R12/AX12,"-") -> - | AZ12: =IFERROR(AX12/$AM$230,"-") -> - | BB12: =IFERROR(BE12/R12,"-") -> - | BC12: =IFERROR(R12/BE12,"-") -> - | BE12: =BD12*AX12 -> 0 | BF12: =IFERROR(BE12/$AT$230,"-") -> -
G13: 01.02.2026 - 28.02.2026 | H13: CPC | J13: =IFERROR(V13*AH13,"-") -> 0 | L13: =IFERROR((I13*J13),"-") -> 0 | N13: =IFERROR(L13*(1-M13),"-") -> 0 | P13: =IFERROR(Q13-N13,"-") -> 0 | Q13: =IFERROR(N13*(1+O13),"-") -> 0 | R13: =IFERROR(Q13*1.22,"-") -> 0 | S13: =IFERROR(R13-Q13,"-") -> 0 | T13: =IFERROR(R13/$R$115,"-") -> - | X13: =IFERROR(AB13/Y13,"-") -> - | AB13: =SUM(Z13:AA13) -> 0 | AD13: =IFERROR(R13/AB13,"-") -> - | AF13: =IFERROR(#REF!/AE13,"-") -> - | AI13: =IFERROR(ROUNDDOWN(V13*AH13,0),"-") -> 0 | AJ13: =IFERROR(R13/AI13,"-") -> - | AM13: =IFERROR(ROUNDDOWN(AI13*AL13,0),"-") -> 0 | AN13: =IFERROR(R13/AM13,"-") -> - | AO13: =IFERROR(AM13/$AM$230,"-") -> - | AQ13: =IFERROR(AT13/R13,"-") -> - | AR13: =IFERROR(R13/AT13,"-") -> - | AT13: =AS13*AM13 -> 0 | AU13: =IFERROR(AT13/$AT$230,"-") -> - | AX13: =IFERROR(ROUNDDOWN(AM13*AW13,0),"-") -> 0 | AY13: =IFERROR(R13/AX13,"-") -> - | AZ13: =IFERROR(AX13/$AM$230,"-") -> - | BB13: =IFERROR(BE13/R13,"-") -> - | BC13: =IFERROR(R13/BE13,"-") -> - | BE13: =BD13*AX13 -> 0 | BF13: =IFERROR(BE13/$AT$230,"-") -> -
G14: 01.02.2026 - 28.02.2026 | H14: CPC | J14: =IFERROR(V14*AH14,"-") -> 0 | L14: =IFERROR((I14*J14),"-") -> 0 | N14: =IFERROR(L14*(1-M14),"-") -> 0 | P14: =IFERROR(Q14-N14,"-") -> 0 | Q14: =IFERROR(N14*(1+O14),"-") -> 0 | R14: =IFERROR(Q14*1.22,"-") -> 0 | S14: =IFERROR(R14-Q14,"-") -> 0 | T14: =IFERROR(R14/$R$115,"-") -> - | X14: =IFERROR(AB14/Y14,"-") -> - | AB14: =SUM(Z14:AA14) -> 0 | AD14: =IFERROR(R14/AB14,"-") -> - | AF14: =IFERROR(#REF!/AE14,"-") -> - | AI14: =IFERROR(ROUNDDOWN(V14*AH14,0),"-") -> 0 | AJ14: =IFERROR(R14/AI14,"-") -> - | AM14: =IFERROR(ROUNDDOWN(AI14*AL14,0),"-") -> 0 | AN14: =IFERROR(R14/AM14,"-") -> - | AO14: =IFERROR(AM14/$AM$230,"-") -> - | AQ14: =IFERROR(AT14/R14,"-") -> - | AR14: =IFERROR(R14/AT14,"-") -> - | AT14: =AS14*AM14 -> 0 | AU14: =IFERROR(AT14/$AT$230,"-") -> - | AX14: =IFERROR(ROUNDDOWN(AM14*AW14,0),"-") -> 0 | AY14: =IFERROR(R14/AX14,"-") -> - | AZ14: =IFERROR(AX14/$AM$230,"-") -> - | BB14: =IFERROR(BE14/R14,"-") -> - | BC14: =IFERROR(R14/BE14,"-") -> - | BE14: =BD14*AX14 -> 0 | BF14: =IFERROR(BE14/$AT$230,"-") -> -
... G57: 01.02.2026 - 28.02.2026 | H57: CPC | J57: =IFERROR(V57*AH57,"-") -> 0 | L57: =IFERROR((I57*J57),"-") -> 0 | N57: =IFERROR(L57*(1-M57),"-") -> 0 | P57: =IFERROR(Q57-N57,"-") -> 0 | Q57: =IFERROR(N57*(1+O57),"-") -> 0 | R57: =IFERROR(Q57*1.22,"-") -> 0 | S57: =IFERROR(R57-Q57,"-") -> 0 | T57: =IFERROR(R57/$R$115,"-") -> - | X57: =IFERROR(AB57/Y57,"-") -> - | AB57: =SUM(Z57:AA57) -> 0 | AD57: =IFERROR(R57/AB57,"-") -> - | AF57: =IFERROR(#REF!/AE57,"-") -> - | AI57: =IFERROR(ROUNDDOWN(V57*AH57,0),"-") -> 0 | AJ57: =IFERROR(R57/AI57,"-") -> - | AM57: =IFERROR(ROUNDDOWN(AI57*AL57,0),"-") -> 0 | AN57: =IFERROR(R57/AM57,"-") -> - | AO57: =IFERROR(AM57/$AM$230,"-") -> - | AQ57: =IFERROR(AT57/R57,"-") -> - | AR57: =IFERROR(R57/AT57,"-") -> - | AT57: =AS57*AM57 -> 0 | AU57: =IFERROR(AT57/$AT$230,"-") -> - | AX57: =IFERROR(ROUNDDOWN(AM57*AW57,0),"-") -> 0 | AY57: =IFERROR(R57/AX57,"-") -> - | AZ57: =IFERROR(AX57/$AM$230,"-") -> - | BB57: =IFERROR(BE57/R57,"-") -> - | BC57: =IFERROR(R57/BE57,"-") -> - | BE57: =BD57*AX57 -> 0 | BF57: =IFERROR(BE57/$AT$230,"-") -> -
B58: ИТОГО B2C | C58: - | D58: - | G58: - | H58: - | I58: =IFERROR(L58/J58,"-") -> - | J58: =SUM(J3:J57) -> 0 | L58: =IFERROR(SUM(L3:L57),"-") -> 0 | M58: - | N58: =IFERROR(SUM(N3:N57),"-") -> 0 | O58: - | P58: =IFERROR(Q58-N58,"-") -> 0 | Q58: =IFERROR(SUM(Q3:Q57),"-") -> 0 | R58: =IFERROR(SUM(R3:R57),"-") -> 0 | S58: =IFERROR(R58-Q58,"-") -> 0 | T58: =SUM(T3:T57) -> 0 | V58: =SUM(V3:V57) -> 0 | W58: - | X58: - | Y58: =SUM(Y3:Y57) -> 0 | Z58: =SUM(Z3:Z57) -> 0 | AA58: =SUM(AA3:AA57) -> 0 | AB58: =SUM(AB3:AB57) -> 0 | AD58: =IFERROR(R58/AB58,"-") -> - | AE58: - | AF58: - | AH58: =IFERROR(AI58/V58,"-") -> - | AI58: =SUM(AI3:AI57) -> 0 | AJ58: =IFERROR(R58/AI58,"-") -> - | AL58: =IFERROR(AM58/AI58,"-") -> - | AM58: =SUM(AM3:AM57) -> 0 | AN58: =IFERROR(R58/AM58,"-") -> - | AO58: =SUM(AO3:AO57) -> 0 | AQ58: =IFERROR(AT58/R58,"-") -> - | AR58: =IFERROR(R58/AT58,"-") -> - | AS58: =IFERROR(AT58/AM58,"-") -> - | AT58: =IFERROR(SUM(AT3:AT57),"-") -> 0 | AU58: =SUM(AU3:AU57) -> 0 | AW58: =IFERROR(AX58/AM58,"-") -> - | AX58: =SUM(AX3:AX57) -> 0 | AY58: =IFERROR(R58/AX58,"-") -> - | AZ58: =SUM(AZ3:AZ57) -> 0 | BB58: =IFERROR(BE58/R58,"-") -> - | BC58: =IFERROR(R58/BE58,"-") -> - | BD58: =IFERROR(BE58/AX58,"-") -> - | BE58: =SUM(BE3:BE57) -> 0 | BF58: =SUM(BF3:BF57) -> 0
G59: 01.02.2026 - 28.02.2026 | H59: CPC | J59: =IFERROR(V59*AH59,"-") -> 0 | L59: =IFERROR((I59*J59),"-") -> 0 | N59: =IFERROR(L59*(1-M59),"-") -> 0 | P59: =IFERROR(Q59-N59,"-") -> 0 | Q59: =IFERROR(N59*(1+O59),"-") -> 0 | R59: =IFERROR(Q59*1.22,"-") -> 0 | S59: =IFERROR(R59-Q59,"-") -> 0 | T59: =IFERROR(R59/$R$115,"-") -> - | X59: =IFERROR(AB59/Y59,"-") -> - | AB59: =SUM(Z59:AA59) -> 0 | AD59: =IFERROR(R59/AB59,"-") -> - | AF59: =IFERROR(#REF!/AE59,"-") -> - | AI59: =IFERROR(ROUNDDOWN(V59*AH59,0),"-") -> 0 | AJ59: =IFERROR(R59/AI59,"-") -> - | AM59: =IFERROR(ROUNDDOWN(AI59*AL59,0),"-") -> 0 | AN59: =IFERROR(R59/AM59,"-") -> - | AO59: =IFERROR(AM59/$AM$230,"-") -> - | AQ59: =IFERROR(AT59/R59,"-") -> - | AR59: =IFERROR(R59/AT59,"-") -> - | AT59: =AS59*AM59 -> 0 | AU59: =IFERROR(AT59/$AT$230,"-") -> - | AX59: =IFERROR(ROUNDDOWN(AM59*AW59,0),"-") -> 0 | AY59: =IFERROR(R59/AX59,"-") -> - | AZ59: =IFERROR(AX59/$AM$230,"-") -> - | BB59: =IFERROR(BE59/R59,"-") -> - | BC59: =IFERROR(R59/BE59,"-") -> - | BE59: =BD59*AX59 -> 0 | BF59: =IFERROR(BE59/$AT$230,"-") -> -
G60: 01.02.2026 - 28.02.2026 | H60: CPC | J60: =IFERROR(V60*AH60,"-") -> 0 | L60: =IFERROR((I60*J60),"-") -> 0 | N60: =IFERROR(L60*(1-M60),"-") -> 0 | P60: =IFERROR(Q60-N60,"-") -> 0 | Q60: =IFERROR(N60*(1+O60),"-") -> 0 | R60: =IFERROR(Q60*1.22,"-") -> 0 | S60: =IFERROR(R60-Q60,"-") -> 0 | T60: =IFERROR(R60/$R$115,"-") -> - | X60: =IFERROR(AB60/Y60,"-") -> - | AB60: =SUM(Z60:AA60) -> 0 | AD60: =IFERROR(R60/AB60,"-") -> - | AF60: =IFERROR(#REF!/AE60,"-") -> - | AI60: =IFERROR(ROUNDDOWN(V60*AH60,0),"-") -> 0 | AJ60: =IFERROR(R60/AI60,"-") -> - | AM60: =IFERROR(ROUNDDOWN(AI60*AL60,0),"-") -> 0 | AN60: =IFERROR(R60/AM60,"-") -> - | AO60: =IFERROR(AM60/$AM$230,"-") -> - | AQ60: =IFERROR(AT60/R60,"-") -> - | AR60: =IFERROR(R60/AT60,"-") -> - | AT60: =AS60*AM60 -> 0 | AU60: =IFERROR(AT60/$AT$230,"-") -> - | AX60: =IFERROR(ROUNDDOWN(AM60*AW60,0),"-") -> 0 | AY60: =IFERROR(R60/AX60,"-") -> - | AZ60: =IFERROR(AX60/$AM$230,"-") -> - | BB60: =IFERROR(BE60/R60,"-") -> - | BC60: =IFERROR(R60/BE60,"-") -> - | BE60: =BD60*AX60 -> 0 | BF60: =IFERROR(BE60/$AT$230,"-") -> -
G61: 01.02.2026 - 28.02.2026 | H61: CPC | J61: =IFERROR(V61*AH61,"-") -> 0 | L61: =IFERROR((I61*J61),"-") -> 0 | N61: =IFERROR(L61*(1-M61),"-") -> 0 | P61: =IFERROR(Q61-N61,"-") -> 0 | Q61: =IFERROR(N61*(1+O61),"-") -> 0 | R61: =IFERROR(Q61*1.22,"-") -> 0 | S61: =IFERROR(R61-Q61,"-") -> 0 | T61: =IFERROR(R61/$R$115,"-") -> - | X61: =IFERROR(AB61/Y61,"-") -> - | AB61: =SUM(Z61:AA61) -> 0 | AD61: =IFERROR(R61/AB61,"-") -> - | AF61: =IFERROR(#REF!/AE61,"-") -> - | AI61: =IFERROR(ROUNDDOWN(V61*AH61,0),"-") -> 0 | AJ61: =IFERROR(R61/AI61,"-") -> - | AM61: =IFERROR(ROUNDDOWN(AI61*AL61,0),"-") -> 0 | AN61: =IFERROR(R61/AM61,"-") -> - | AO61: =IFERROR(AM61/$AM$230,"-") -> - | AQ61: =IFERROR(AT61/R61,"-") -> - | AR61: =IFERROR(R61/AT61,"-") -> - | AT61: =AS61*AM61 -> 0 | AU61: =IFERROR(AT61/$AT$230,"-") -> - | AX61: =IFERROR(ROUNDDOWN(AM61*AW61,0),"-") -> 0 | AY61: =IFERROR(R61/AX61,"-") -> - | AZ61: =IFERROR(AX61/$AM$230,"-") -> - | BB61: =IFERROR(BE61/R61,"-") -> - | BC61: =IFERROR(R61/BE61,"-") -> - | BE61: =BD61*AX61 -> 0 | BF61: =IFERROR(BE61/$AT$230,"-") -> -
G62: 01.02.2026 - 28.02.2026 | H62: CPC | J62: =IFERROR(V62*AH62,"-") -> 0 | L62: =IFERROR((I62*J62),"-") -> 0 | N62: =IFERROR(L62*(1-M62),"-") -> 0 | P62: =IFERROR(Q62-N62,"-") -> 0 | Q62: =IFERROR(N62*(1+O62),"-") -> 0 | R62: =IFERROR(Q62*1.22,"-") -> 0 | S62: =IFERROR(R62-Q62,"-") -> 0 | T62: =IFERROR(R62/$R$115,"-") -> - | X62: =IFERROR(AB62/Y62,"-") -> - | AB62: =SUM(Z62:AA62) -> 0 | AD62: =IFERROR(R62/AB62,"-") -> - | AF62: =IFERROR(#REF!/AE62,"-") -> - | AI62: =IFERROR(ROUNDDOWN(V62*AH62,0),"-") -> 0 | AJ62: =IFERROR(R62/AI62,"-") -> - | AM62: =IFERROR(ROUNDDOWN(AI62*AL62,0),"-") -> 0 | AN62: =IFERROR(R62/AM62,"-") -> - | AO62: =IFERROR(AM62/$AM$230,"-") -> - | AQ62: =IFERROR(AT62/R62,"-") -> - | AR62: =IFERROR(R62/AT62,"-") -> - | AT62: =AS62*AM62 -> 0 | AU62: =IFERROR(AT62/$AT$230,"-") -> - | AX62: =IFERROR(ROUNDDOWN(AM62*AW62,0),"-") -> 0 | AY62: =IFERROR(R62/AX62,"-") -> - | AZ62: =IFERROR(AX62/$AM$230,"-") -> - | BB62: =IFERROR(BE62/R62,"-") -> - | BC62: =IFERROR(R62/BE62,"-") -> - | BE62: =BD62*AX62 -> 0 | BF62: =IFERROR(BE62/$AT$230,"-") -> -
G63: 01.02.2026 - 28.02.2026 | H63: CPC | J63: =IFERROR(V63*AH63,"-") -> 0 | L63: =IFERROR((I63*J63),"-") -> 0 | N63: =IFERROR(L63*(1-M63),"-") -> 0 | P63: =IFERROR(Q63-N63,"-") -> 0 | Q63: =IFERROR(N63*(1+O63),"-") -> 0 | R63: =IFERROR(Q63*1.22,"-") -> 0 | S63: =IFERROR(R63-Q63,"-") -> 0 | T63: =IFERROR(R63/$R$115,"-") -> - | X63: =IFERROR(AB63/Y63,"-") -> - | AB63: =SUM(Z63:AA63) -> 0 | AD63: =IFERROR(R63/AB63,"-") -> - | AF63: =IFERROR(#REF!/AE63,"-") -> - | AI63: =IFERROR(ROUNDDOWN(V63*AH63,0),"-") -> 0 | AJ63: =IFERROR(R63/AI63,"-") -> - | AM63: =IFERROR(ROUNDDOWN(AI63*AL63,0),"-") -> 0 | AN63: =IFERROR(R63/AM63,"-") -> - | AO63: =IFERROR(AM63/$AM$230,"-") -> - | AQ63: =IFERROR(AT63/R63,"-") -> - | AR63: =IFERROR(R63/AT63,"-") -> - | AT63: =AS63*AM63 -> 0 | AU63: =IFERROR(AT63/$AT$230,"-") -> - | AX63: =IFERROR(ROUNDDOWN(AM63*AW63,0),"-") -> 0 | AY63: =IFERROR(R63/AX63,"-") -> - | AZ63: =IFERROR(AX63/$AM$230,"-") -> - | BB63: =IFERROR(BE63/R63,"-") -> - | BC63: =IFERROR(R63/BE63,"-") -> - | BE63: =BD63*AX63 -> 0 | BF63: =IFERROR(BE63/$AT$230,"-") -> -
G64: 01.02.2026 - 28.02.2026 | H64: CPC | J64: =IFERROR(V64*AH64,"-") -> 0 | L64: =IFERROR((I64*J64),"-") -> 0 | N64: =IFERROR(L64*(1-M64),"-") -> 0 | P64: =IFERROR(Q64-N64,"-") -> 0 | Q64: =IFERROR(N64*(1+O64),"-") -> 0 | R64: =IFERROR(Q64*1.22,"-") -> 0 | S64: =IFERROR(R64-Q64,"-") -> 0 | T64: =IFERROR(R64/$R$115,"-") -> - | X64: =IFERROR(AB64/Y64,"-") -> - | AB64: =SUM(Z64:AA64) -> 0 | AD64: =IFERROR(R64/AB64,"-") -> - | AF64: =IFERROR(#REF!/AE64,"-") -> - | AI64: =IFERROR(ROUNDDOWN(V64*AH64,0),"-") -> 0 | AJ64: =IFERROR(R64/AI64,"-") -> - | AM64: =IFERROR(ROUNDDOWN(AI64*AL64,0),"-") -> 0 | AN64: =IFERROR(R64/AM64,"-") -> - | AO64: =IFERROR(AM64/$AM$230,"-") -> - | AQ64: =IFERROR(AT64/R64,"-") -> - | AR64: =IFERROR(R64/AT64,"-") -> - | AT64: =AS64*AM64 -> 0 | AU64: =IFERROR(AT64/$AT$230,"-") -> - | AX64: =IFERROR(ROUNDDOWN(AM64*AW64,0),"-") -> 0 | AY64: =IFERROR(R64/AX64,"-") -> - | AZ64: =IFERROR(AX64/$AM$230,"-") -> - | BB64: =IFERROR(BE64/R64,"-") -> - | BC64: =IFERROR(R64/BE64,"-") -> - | BE64: =BD64*AX64 -> 0 | BF64: =IFERROR(BE64/$AT$230,"-") -> -
G65: 01.02.2026 - 28.02.2026 | H65: CPC | J65: =IFERROR(V65*AH65,"-") -> 0 | L65: =IFERROR((I65*J65),"-") -> 0 | N65: =IFERROR(L65*(1-M65),"-") -> 0 | P65: =IFERROR(Q65-N65,"-") -> 0 | Q65: =IFERROR(N65*(1+O65),"-") -> 0 | R65: =IFERROR(Q65*1.22,"-") -> 0 | S65: =IFERROR(R65-Q65,"-") -> 0 | T65: =IFERROR(R65/$R$115,"-") -> - | X65: =IFERROR(AB65/Y65,"-") -> - | AB65: =SUM(Z65:AA65) -> 0 | AD65: =IFERROR(R65/AB65,"-") -> - | AF65: =IFERROR(#REF!/AE65,"-") -> - | AI65: =IFERROR(ROUNDDOWN(V65*AH65,0),"-") -> 0 | AJ65: =IFERROR(R65/AI65,"-") -> - | AM65: =IFERROR(ROUNDDOWN(AI65*AL65,0),"-") -> 0 | AN65: =IFERROR(R65/AM65,"-") -> - | AO65: =IFERROR(AM65/$AM$230,"-") -> - | AQ65: =IFERROR(AT65/R65,"-") -> - | AR65: =IFERROR(R65/AT65,"-") -> - | AT65: =AS65*AM65 -> 0 | AU65: =IFERROR(AT65/$AT$230,"-") -> - | AX65: =IFERROR(ROUNDDOWN(AM65*AW65,0),"-") -> 0 | AY65: =IFERROR(R65/AX65,"-") -> - | AZ65: =IFERROR(AX65/$AM$230,"-") -> - | BB65: =IFERROR(BE65/R65,"-") -> - | BC65: =IFERROR(R65/BE65,"-") -> - | BE65: =BD65*AX65 -> 0 | BF65: =IFERROR(BE65/$AT$230,"-") -> -
G66: 01.02.2026 - 28.02.2026 | H66: CPC | J66: =IFERROR(V66*AH66,"-") -> 0 | L66: =IFERROR((I66*J66),"-") -> 0 | N66: =IFERROR(L66*(1-M66),"-") -> 0 | P66: =IFERROR(Q66-N66,"-") -> 0 | Q66: =IFERROR(N66*(1+O66),"-") -> 0 | R66: =IFERROR(Q66*1.22,"-") -> 0 | S66: =IFERROR(R66-Q66,"-") -> 0 | T66: =IFERROR(R66/$R$115,"-") -> - | X66: =IFERROR(AB66/Y66,"-") -> - | AB66: =SUM(Z66:AA66) -> 0 | AD66: =IFERROR(R66/AB66,"-") -> - | AF66: =IFERROR(#REF!/AE66,"-") -> - | AI66: =IFERROR(ROUNDDOWN(V66*AH66,0),"-") -> 0 | AJ66: =IFERROR(R66/AI66,"-") -> - | AM66: =IFERROR(ROUNDDOWN(AI66*AL66,0),"-") -> 0 | AN66: =IFERROR(R66/AM66,"-") -> - | AO66: =IFERROR(AM66/$AM$230,"-") -> - | AQ66: =IFERROR(AT66/R66,"-") -> - | AR66: =IFERROR(R66/AT66,"-") -> - | AT66: =AS66*AM66 -> 0 | AU66: =IFERROR(AT66/$AT$230,"-") -> - | AX66: =IFERROR(ROUNDDOWN(AM66*AW66,0),"-") -> 0 | AY66: =IFERROR(R66/AX66,"-") -> - | AZ66: =IFERROR(AX66/$AM$230,"-") -> - | BB66: =IFERROR(BE66/R66,"-") -> - | BC66: =IFERROR(R66/BE66,"-") -> - | BE66: =BD66*AX66 -> 0 | BF66: =IFERROR(BE66/$AT$230,"-") -> -
G67: 01.02.2026 - 28.02.2026 | H67: CPC | J67: =IFERROR(V67*AH67,"-") -> 0 | L67: =IFERROR((I67*J67),"-") -> 0 | N67: =IFERROR(L67*(1-M67),"-") -> 0 | P67: =IFERROR(Q67-N67,"-") -> 0 | Q67: =IFERROR(N67*(1+O67),"-") -> 0 | R67: =IFERROR(Q67*1.22,"-") -> 0 | S67: =IFERROR(R67-Q67,"-") -> 0 | T67: =IFERROR(R67/$R$115,"-") -> - | X67: =IFERROR(AB67/Y67,"-") -> - | AB67: =SUM(Z67:AA67) -> 0 | AD67: =IFERROR(R67/AB67,"-") -> - | AF67: =IFERROR(#REF!/AE67,"-") -> - | AI67: =IFERROR(ROUNDDOWN(V67*AH67,0),"-") -> 0 | AJ67: =IFERROR(R67/AI67,"-") -> - | AM67: =IFERROR(ROUNDDOWN(AI67*AL67,0),"-") -> 0 | AN67: =IFERROR(R67/AM67,"-") -> - | AO67: =IFERROR(AM67/$AM$230,"-") -> - | AQ67: =IFERROR(AT67/R67,"-") -> - | AR67: =IFERROR(R67/AT67,"-") -> - | AT67: =AS67*AM67 -> 0 | AU67: =IFERROR(AT67/$AT$230,"-") -> - | AX67: =IFERROR(ROUNDDOWN(AM67*AW67,0),"-") -> 0 | AY67: =IFERROR(R67/AX67,"-") -> - | AZ67: =IFERROR(AX67/$AM$230,"-") -> - | BB67: =IFERROR(BE67/R67,"-") -> - | BC67: =IFERROR(R67/BE67,"-") -> - | BE67: =BD67*AX67 -> 0 | BF67: =IFERROR(BE67/$AT$230,"-") -> -
G68: 01.02.2026 - 28.02.2026 | H68: CPC | J68: =IFERROR(V68*AH68,"-") -> 0 | L68: =IFERROR((I68*J68),"-") -> 0 | N68: =IFERROR(L68*(1-M68),"-") -> 0 | P68: =IFERROR(Q68-N68,"-") -> 0 | Q68: =IFERROR(N68*(1+O68),"-") -> 0 | R68: =IFERROR(Q68*1.22,"-") -> 0 | S68: =IFERROR(R68-Q68,"-") -> 0 | T68: =IFERROR(R68/$R$115,"-") -> - | X68: =IFERROR(AB68/Y68,"-") -> - | AB68: =SUM(Z68:AA68) -> 0 | AD68: =IFERROR(R68/AB68,"-") -> - | AF68: =IFERROR(#REF!/AE68,"-") -> - | AI68: =IFERROR(ROUNDDOWN(V68*AH68,0),"-") -> 0 | AJ68: =IFERROR(R68/AI68,"-") -> - | AM68: =IFERROR(ROUNDDOWN(AI68*AL68,0),"-") -> 0 | AN68: =IFERROR(R68/AM68,"-") -> - | AO68: =IFERROR(AM68/$AM$230,"-") -> - | AQ68: =IFERROR(AT68/R68,"-") -> - | AR68: =IFERROR(R68/AT68,"-") -> - | AT68: =AS68*AM68 -> 0 | AU68: =IFERROR(AT68/$AT$230,"-") -> - | AX68: =IFERROR(ROUNDDOWN(AM68*AW68,0),"-") -> 0 | AY68: =IFERROR(R68/AX68,"-") -> - | AZ68: =IFERROR(AX68/$AM$230,"-") -> - | BB68: =IFERROR(BE68/R68,"-") -> - | BC68: =IFERROR(R68/BE68,"-") -> - | BE68: =BD68*AX68 -> 0 | BF68: =IFERROR(BE68/$AT$230,"-") -> -
G69: 01.02.2026 - 28.02.2026 | H69: CPC | J69: =IFERROR(V69*AH69,"-") -> 0 | L69: =IFERROR((I69*J69),"-") -> 0 | N69: =IFERROR(L69*(1-M69),"-") -> 0 | P69: =IFERROR(Q69-N69,"-") -> 0 | Q69: =IFERROR(N69*(1+O69),"-") -> 0 | R69: =IFERROR(Q69*1.22,"-") -> 0 | S69: =IFERROR(R69-Q69,"-") -> 0 | T69: =IFERROR(R69/$R$115,"-") -> - | X69: =IFERROR(AB69/Y69,"-") -> - | AB69: =SUM(Z69:AA69) -> 0 | AD69: =IFERROR(R69/AB69,"-") -> - | AF69: =IFERROR(#REF!/AE69,"-") -> - | AI69: =IFERROR(ROUNDDOWN(V69*AH69,0),"-") -> 0 | AJ69: =IFERROR(R69/AI69,"-") -> - | AM69: =IFERROR(ROUNDDOWN(AI69*AL69,0),"-") -> 0 | AN69: =IFERROR(R69/AM69,"-") -> - | AO69: =IFERROR(AM69/$AM$230,"-") -> - | AQ69: =IFERROR(AT69/R69,"-") -> - | AR69: =IFERROR(R69/AT69,"-") -> - | AT69: =AS69*AM69 -> 0 | AU69: =IFERROR(AT69/$AT$230,"-") -> - | AX69: =IFERROR(ROUNDDOWN(AM69*AW69,0),"-") -> 0 | AY69: =IFERROR(R69/AX69,"-") -> - | AZ69: =IFERROR(AX69/$AM$230,"-") -> - | BB69: =IFERROR(BE69/R69,"-") -> - | BC69: =IFERROR(R69/BE69,"-") -> - | BE69: =BD69*AX69 -> 0 | BF69: =IFERROR(BE69/$AT$230,"-") -> -
G70: 01.02.2026 - 28.02.2026 | H70: CPC | J70: =IFERROR(V70*AH70,"-") -> 0 | L70: =IFERROR((I70*J70),"-") -> 0 | N70: =IFERROR(L70*(1-M70),"-") -> 0 | P70: =IFERROR(Q70-N70,"-") -> 0 | Q70: =IFERROR(N70*(1+O70),"-") -> 0 | R70: =IFERROR(Q70*1.22,"-") -> 0 | S70: =IFERROR(R70-Q70,"-") -> 0 | T70: =IFERROR(R70/$R$115,"-") -> - | X70: =IFERROR(AB70/Y70,"-") -> - | AB70: =SUM(Z70:AA70) -> 0 | AD70: =IFERROR(R70/AB70,"-") -> - | AF70: =IFERROR(#REF!/AE70,"-") -> - | AI70: =IFERROR(ROUNDDOWN(V70*AH70,0),"-") -> 0 | AJ70: =IFERROR(R70/AI70,"-") -> - | AM70: =IFERROR(ROUNDDOWN(AI70*AL70,0),"-") -> 0 | AN70: =IFERROR(R70/AM70,"-") -> - | AO70: =IFERROR(AM70/$AM$230,"-") -> - | AQ70: =IFERROR(AT70/R70,"-") -> - | AR70: =IFERROR(R70/AT70,"-") -> - | AT70: =AS70*AM70 -> 0 | AU70: =IFERROR(AT70/$AT$230,"-") -> - | AX70: =IFERROR(ROUNDDOWN(AM70*AW70,0),"-") -> 0 | AY70: =IFERROR(R70/AX70,"-") -> - | AZ70: =IFERROR(AX70/$AM$230,"-") -> - | BB70: =IFERROR(BE70/R70,"-") -> - | BC70: =IFERROR(R70/BE70,"-") -> - | BE70: =BD70*AX70 -> 0 | BF70: =IFERROR(BE70/$AT$230,"-") -> -
... G113: 01.02.2026 - 28.02.2026 | H113: CPC | J113: =IFERROR(V113*AH113,"-") -> 0 | L113: =IFERROR((I113*J113),"-") -> 0 | N113: =IFERROR(L113*(1-M113),"-") -> 0 | P113: =IFERROR(Q113-N113,"-") -> 0 | Q113: =IFERROR(N113*(1+O113),"-") -> 0 | R113: =IFERROR(Q113*1.22,"-") -> 0 | S113: =IFERROR(R113-Q113,"-") -> 0 | T113: =IFERROR(R113/$R$115,"-") -> - | X113: =IFERROR(AB113/Y113,"-") -> - | AB113: =SUM(Z113:AA113) -> 0 | AD113: =IFERROR(R113/AB113,"-") -> - | AF113: =IFERROR(#REF!/AE113,"-") -> - | AI113: =IFERROR(ROUNDDOWN(V113*AH113,0),"-") -> 0 | AJ113: =IFERROR(R113/AI113,"-") -> - | AM113: =IFERROR(ROUNDDOWN(AI113*AL113,0),"-") -> 0 | AN113: =IFERROR(R113/AM113,"-") -> - | AO113: =IFERROR(AM113/$AM$230,"-") -> - | AQ113: =IFERROR(AT113/R113,"-") -> - | AR113: =IFERROR(R113/AT113,"-") -> - | AT113: =AS113*AM113 -> 0 | AU113: =IFERROR(AT113/$AT$230,"-") -> - | AX113: =IFERROR(ROUNDDOWN(AM113*AW113,0),"-") -> 0 | AY113: =IFERROR(R113/AX113,"-") -> - | AZ113: =IFERROR(AX113/$AM$230,"-") -> - | BB113: =IFERROR(BE113/R113,"-") -> - | BC113: =IFERROR(R113/BE113,"-") -> - | BE113: =BD113*AX113 -> 0 | BF113: =IFERROR(BE113/$AT$230,"-") -> -
B114: ИТОГО B2B | C114: - | D114: - | G114: - | H114: - | I114: =IFERROR(L114/J114,"-") -> - | J114: =SUM(J59:J113) -> 0 | L114: =IFERROR(SUM(L59:L113),"-") -> 0 | M114: - | N114: =IFERROR(SUM(N59:N113),"-") -> 0 | O114: - | P114: =IFERROR(Q114-N114,"-") -> 0 | Q114: =IFERROR(SUM(Q59:Q113),"-") -> 0 | R114: =IFERROR(SUM(R59:R113),"-") -> 0 | S114: =IFERROR(R114-Q114,"-") -> 0 | T114: =SUM(T59:T113) -> 0 | V114: =SUM(V59:V113) -> 0 | W114: - | X114: - | Y114: =SUM(Y59:Y113) -> 0 | Z114: =SUM(Z59:Z113) -> 0 | AA114: =SUM(AA59:AA113) -> 0 | AB114: =SUM(AB59:AB113) -> 0 | AD114: =IFERROR(R114/AB114,"-") -> - | AE114: - | AF114: - | AH114: =IFERROR(AI114/V114,"-") -> - | AI114: =SUM(AI59:AI113) -> 0 | AJ114: =IFERROR(R114/AI114,"-") -> - | AL114: =IFERROR(AM114/AI114,"-") -> - | AM114: =SUM(AM59:AM113) -> 0 | AN114: =IFERROR(R114/AM114,"-") -> - | AO114: =SUM(AO59:AO113) -> 0 | AQ114: =IFERROR(AT114/R114,"-") -> - | AR114: =IFERROR(R114/AT114,"-") -> - | AS114: =IFERROR(AT114/AM114,"-") -> - | AT114: =IFERROR(SUM(AT59:AT113),"-") -> 0 | AU114: =SUM(AU59:AU113) -> 0 | AW114: =IFERROR(AX114/AM114,"-") -> - | AX114: =SUM(AX59:AX113) -> 0 | AY114: =IFERROR(R114/AX114,"-") -> - | AZ114: =SUM(AZ59:AZ113) -> 0 | BB114: =IFERROR(BE114/R114,"-") -> - | BC114: =IFERROR(R114/BE114,"-") -> - | BD114: =IFERROR(BE114/AX114,"-") -> - | BE114: =SUM(BE59:BE113) -> 0 | BF114: =SUM(BF59:BF113) -> 0
B115: Итого | C115: - | D115: - | G115: - | H115: - | I115: =IFERROR(L115/J115,"-") -> - | J115: =J114+J58 -> 0 | L115: =IFERROR(SUM(L114,L58),"-") -> 0 | M115: - | N115: =IFERROR(SUM(N114,N58),"-") -> 0 | O115: - | P115: =IFERROR(Q115-N115,"-") -> 0 | Q115: =IFERROR(SUM(Q114,Q58),"-") -> 0 | R115: =IFERROR(SUM(R114,R58),"-") -> 0 | S115: =IFERROR(R115-Q115,"-") -> 0 | T115: =SUM(T58,T114) -> 0 | V115: =V114+V58 -> 0 | W115: - | X115: - | Y115: =SUM(Y114,Y58) -> 0 | Z115: =SUM(Z114,Z58) -> 0 | AA115: =SUM(AA114,AA58) -> 0 | AB115: =SUM(AB114,AB58) -> 0 | AD115: =IFERROR(R115/AB115,"-") -> - | AE115: - | AF115: - | AH115: =IFERROR(AI115/V115,"-") -> - | AI115: =AI114+AI58 -> 0 | AJ115: =IFERROR(R115/AI115,"-") -> - | AL115: =IFERROR(AM115/AI115,"-") -> - | AM115: =AM114+AM58 -> 0 | AN115: =IFERROR(R115/AM115,"-") -> - | AO115: =SUM(AO58,AO114) -> 0 | AQ115: =IFERROR(AT115/R115,"-") -> - | AR115: =IFERROR(R115/AT115,"-") -> - | AS115: =IFERROR(AT115/AM115,"-") -> - | AT115: =IFERROR(SUM(AT58,AT114),"-") -> 0 | AU115: =SUM(AU58,AU114) -> 0 | AW115: =IFERROR(AX115/AM115,"-") -> - | AX115: =AX114+AX58 -> 0 | AY115: =IFERROR(R115/AX115,"-") -> - | AZ115: =SUM(AZ58,AZ114) -> 0 | BB115: =IFERROR(BE115/R115,"-") -> - | BC115: =IFERROR(R115/BE115,"-") -> - | BD115: =IFERROR(BE115/AX115,"-") -> - | BE115: =SUM(BE114,BE58) -> 0 | BF115: =SUM(BF58,BF114) -> 0
B117: Рекламная система | C117: Рекламный формат, размер, вид размещения | D117: Таргетинги | E117: ГЕО | G117: Период | H117: Единица измерения стоимости | I117: Цена за единицу (без НДС) | J117: Кол-во единиц | L117: Стоимость (без НДС) | M117: СК, % | N117: Тотал бюджет, руб. без НДС и АК | O117: АК, % | P117: АК, руб. (без НДС) | Q117: Тотал бюджет, руб. без НДС и с учетом АК | R117: Тотал бюджет руб. с учетом НДС и АК | S117: НДС руб. | T117: Доля рекламного бюджета, % | V117: Кол-во показов | W117: Частота (весь срок) | X117: Доля новых клиентов, % | Y117: Кол-во клиентов | Z117: Кол-во абсолютно новых клиентов (ранее не заказывали) | AA117: Кол-во вернувшихся клиентов (не заказывали более 12 мес) | AB117: Кол-во новых клиентов (абсолютно новые + вернувшиеся) | AC117: Частота заказа | AD117: САС, руб. | AE117: Доступная емкость аудитории | AF117: SOV, % | AH117: CTR, % | AI117: Клики | AJ117: CPC (с НДС) | AL117: CR, % | AM117: Кол-во оформленных заказов | AN117: Стоимость оформл. заказа, руб. с НДС | AO117: Доля заказов, % | AQ117: ROAS офомл. (Доход/Бюджет) | AR117: ДРР от оформл. дохода, % | AS117: Средний чек по оформл. доходу, с НДС | AT117: Оформленный доход, руб. с НДС | AU117: Доля заказов, % | AW117: CR2, % | AX117: Кол-во отгруженных заказов | AY117: Стоимость отгр. заказа, руб. с НДС | AZ117: Доля заказов, % | BB117: ROAS отгр. (Выручка/Бюджет) | BC117: ДРР от выручки, % | BD117: Средний чек по выручке, с НДС | BE117: Выручка (отгруженный доход), руб. с НДС | BF117: Доля заказов, %
G118: 01.02.2026 - 28.02.2026 | H118: CPC | J118: =IFERROR(V118*AH118,"-") -> 0 | L118: =IFERROR((I118*J118),"-") -> 0 | N118: =IFERROR(L118*(1-M118),"-") -> 0 | P118: =IFERROR(Q118-N118,"-") -> 0 | Q118: =IFERROR(N118*(1+O118),"-") -> 0 | R118: =IFERROR(Q118*1.22,"-") -> 0 | S118: =IFERROR(R118-Q118,"-") -> 0 | T118: =IFERROR(R118/$R$230,"-") -> - | X118: =IFERROR(AB118/Y118,"-") -> - | AB118: =SUM(Z118:AA118) -> 0 | AD118: =IFERROR(R118/AB118,"-") -> - | AF118: =IFERROR(#REF!/AE118,"-") -> - | AI118: =IFERROR(ROUNDDOWN(V118*AH118,0),"-") -> 0 | AJ118: =IFERROR(R118/AI118,"-") -> - | AM118: =IFERROR(ROUNDDOWN(AI118*AL118,0),"-") -> 0 | AN118: =IFERROR(R118/AM118,"-") -> - | AO118: =IFERROR(AM118/$AM$230,"-") -> - | AQ118: =IFERROR(AT118/R118,"-") -> - | AR118: =IFERROR(R118/AT118,"-") -> - | AT118: =AS118*AM118 -> 0 | AU118: =IFERROR(AT118/$AT$230,"-") -> - | AX118: =IFERROR(ROUNDDOWN(AM118*AW118,0),"-") -> 0 | AY118: =IFERROR(R118/AX118,"-") -> - | AZ118: =IFERROR(AX118/$AM$230,"-") -> - | BB118: =IFERROR(BE118/R118,"-") -> - | BC118: =IFERROR(R118/BE118,"-") -> - | BE118: =BD118*AX118 -> 0 | BF118: =IFERROR(BE118/$AT$230,"-") -> -
G119: 01.02.2026 - 28.02.2026 | H119: CPC | J119: =IFERROR(V119*AH119,"-") -> 0 | L119: =IFERROR((I119*J119),"-") -> 0 | N119: =IFERROR(L119*(1-M119),"-") -> 0 | P119: =IFERROR(Q119-N119,"-") -> 0 | Q119: =IFERROR(N119*(1+O119),"-") -> 0 | R119: =IFERROR(Q119*1.22,"-") -> 0 | S119: =IFERROR(R119-Q119,"-") -> 0 | T119: =IFERROR(R119/$R$230,"-") -> - | X119: =IFERROR(AB119/Y119,"-") -> - | AB119: =SUM(Z119:AA119) -> 0 | AD119: =IFERROR(R119/AB119,"-") -> - | AF119: =IFERROR(#REF!/AE119,"-") -> - | AI119: =IFERROR(ROUNDDOWN(V119*AH119,0),"-") -> 0 | AJ119: =IFERROR(R119/AI119,"-") -> - | AM119: =IFERROR(ROUNDDOWN(AI119*AL119,0),"-") -> 0 | AN119: =IFERROR(R119/AM119,"-") -> - | AO119: =IFERROR(AM119/$AM$230,"-") -> - | AQ119: =IFERROR(AT119/R119,"-") -> - | AR119: =IFERROR(R119/AT119,"-") -> - | AT119: =AS119*AM119 -> 0 | AU119: =IFERROR(AT119/$AT$230,"-") -> - | AX119: =IFERROR(ROUNDDOWN(AM119*AW119,0),"-") -> 0 | AY119: =IFERROR(R119/AX119,"-") -> - | AZ119: =IFERROR(AX119/$AM$230,"-") -> - | BB119: =IFERROR(BE119/R119,"-") -> - | BC119: =IFERROR(R119/BE119,"-") -> - | BE119: =BD119*AX119 -> 0 | BF119: =IFERROR(BE119/$AT$230,"-") -> -
G120: 01.02.2026 - 28.02.2026 | H120: CPC | J120: =IFERROR(V120*AH120,"-") -> 0 | L120: =IFERROR((I120*J120),"-") -> 0 | N120: =IFERROR(L120*(1-M120),"-") -> 0 | P120: =IFERROR(Q120-N120,"-") -> 0 | Q120: =IFERROR(N120*(1+O120),"-") -> 0 | R120: =IFERROR(Q120*1.22,"-") -> 0 | S120: =IFERROR(R120-Q120,"-") -> 0 | T120: =IFERROR(R120/$R$230,"-") -> - | X120: =IFERROR(AB120/Y120,"-") -> - | AB120: =SUM(Z120:AA120) -> 0 | AD120: =IFERROR(R120/AB120,"-") -> - | AF120: =IFERROR(#REF!/AE120,"-") -> - | AI120: =IFERROR(ROUNDDOWN(V120*AH120,0),"-") -> 0 | AJ120: =IFERROR(R120/AI120,"-") -> - | AM120: =IFERROR(ROUNDDOWN(AI120*AL120,0),"-") -> 0 | AN120: =IFERROR(R120/AM120,"-") -> - | AO120: =IFERROR(AM120/$AM$230,"-") -> - | AQ120: =IFERROR(AT120/R120,"-") -> - | AR120: =IFERROR(R120/AT120,"-") -> - | AT120: =AS120*AM120 -> 0 | AU120: =IFERROR(AT120/$AT$230,"-") -> - | AX120: =IFERROR(ROUNDDOWN(AM120*AW120,0),"-") -> 0 | AY120: =IFERROR(R120/AX120,"-") -> - | AZ120: =IFERROR(AX120/$AM$230,"-") -> - | BB120: =IFERROR(BE120/R120,"-") -> - | BC120: =IFERROR(R120/BE120,"-") -> - | BE120: =BD120*AX120 -> 0 | BF120: =IFERROR(BE120/$AT$230,"-") -> -
G121: 01.02.2026 - 28.02.2026 | H121: CPC | J121: =IFERROR(V121*AH121,"-") -> 0 | L121: =IFERROR((I121*J121),"-") -> 0 | N121: =IFERROR(L121*(1-M121),"-") -> 0 | P121: =IFERROR(Q121-N121,"-") -> 0 | Q121: =IFERROR(N121*(1+O121),"-") -> 0 | R121: =IFERROR(Q121*1.22,"-") -> 0 | S121: =IFERROR(R121-Q121,"-") -> 0 | T121: =IFERROR(R121/$R$230,"-") -> - | X121: =IFERROR(AB121/Y121,"-") -> - | AB121: =SUM(Z121:AA121) -> 0 | AD121: =IFERROR(R121/AB121,"-") -> - | AF121: =IFERROR(#REF!/AE121,"-") -> - | AI121: =IFERROR(ROUNDDOWN(V121*AH121,0),"-") -> 0 | AJ121: =IFERROR(R121/AI121,"-") -> - | AM121: =IFERROR(ROUNDDOWN(AI121*AL121,0),"-") -> 0 | AN121: =IFERROR(R121/AM121,"-") -> - | AO121: =IFERROR(AM121/$AM$230,"-") -> - | AQ121: =IFERROR(AT121/R121,"-") -> - | AR121: =IFERROR(R121/AT121,"-") -> - | AT121: =AS121*AM121 -> 0 | AU121: =IFERROR(AT121/$AT$230,"-") -> - | AX121: =IFERROR(ROUNDDOWN(AM121*AW121,0),"-") -> 0 | AY121: =IFERROR(R121/AX121,"-") -> - | AZ121: =IFERROR(AX121/$AM$230,"-") -> - | BB121: =IFERROR(BE121/R121,"-") -> - | BC121: =IFERROR(R121/BE121,"-") -> - | BE121: =BD121*AX121 -> 0 | BF121: =IFERROR(BE121/$AT$230,"-") -> -
G122: 01.02.2026 - 28.02.2026 | H122: CPC | J122: =IFERROR(V122*AH122,"-") -> 0 | L122: =IFERROR((I122*J122),"-") -> 0 | N122: =IFERROR(L122*(1-M122),"-") -> 0 | P122: =IFERROR(Q122-N122,"-") -> 0 | Q122: =IFERROR(N122*(1+O122),"-") -> 0 | R122: =IFERROR(Q122*1.22,"-") -> 0 | S122: =IFERROR(R122-Q122,"-") -> 0 | T122: =IFERROR(R122/$R$230,"-") -> - | X122: =IFERROR(AB122/Y122,"-") -> - | AB122: =SUM(Z122:AA122) -> 0 | AD122: =IFERROR(R122/AB122,"-") -> - | AF122: =IFERROR(#REF!/AE122,"-") -> - | AI122: =IFERROR(ROUNDDOWN(V122*AH122,0),"-") -> 0 | AJ122: =IFERROR(R122/AI122,"-") -> - | AM122: =IFERROR(ROUNDDOWN(AI122*AL122,0),"-") -> 0 | AN122: =IFERROR(R122/AM122,"-") -> - | AO122: =IFERROR(AM122/$AM$230,"-") -> - | AQ122: =IFERROR(AT122/R122,"-") -> - | AR122: =IFERROR(R122/AT122,"-") -> - | AT122: =AS122*AM122 -> 0 | AU122: =IFERROR(AT122/$AT$230,"-") -> - | AX122: =IFERROR(ROUNDDOWN(AM122*AW122,0),"-") -> 0 | AY122: =IFERROR(R122/AX122,"-") -> - | AZ122: =IFERROR(AX122/$AM$230,"-") -> - | BB122: =IFERROR(BE122/R122,"-") -> - | BC122: =IFERROR(R122/BE122,"-") -> - | BE122: =BD122*AX122 -> 0 | BF122: =IFERROR(BE122/$AT$230,"-") -> -
G123: 01.02.2026 - 28.02.2026 | H123: CPC | J123: =IFERROR(V123*AH123,"-") -> 0 | L123: =IFERROR((I123*J123),"-") -> 0 | N123: =IFERROR(L123*(1-M123),"-") -> 0 | P123: =IFERROR(Q123-N123,"-") -> 0 | Q123: =IFERROR(N123*(1+O123),"-") -> 0 | R123: =IFERROR(Q123*1.22,"-") -> 0 | S123: =IFERROR(R123-Q123,"-") -> 0 | T123: =IFERROR(R123/$R$230,"-") -> - | X123: =IFERROR(AB123/Y123,"-") -> - | AB123: =SUM(Z123:AA123) -> 0 | AD123: =IFERROR(R123/AB123,"-") -> - | AF123: =IFERROR(#REF!/AE123,"-") -> - | AI123: =IFERROR(ROUNDDOWN(V123*AH123,0),"-") -> 0 | AJ123: =IFERROR(R123/AI123,"-") -> - | AM123: =IFERROR(ROUNDDOWN(AI123*AL123,0),"-") -> 0 | AN123: =IFERROR(R123/AM123,"-") -> - | AO123: =IFERROR(AM123/$AM$230,"-") -> - | AQ123: =IFERROR(AT123/R123,"-") -> - | AR123: =IFERROR(R123/AT123,"-") -> - | AT123: =AS123*AM123 -> 0 | AU123: =IFERROR(AT123/$AT$230,"-") -> - | AX123: =IFERROR(ROUNDDOWN(AM123*AW123,0),"-") -> 0 | AY123: =IFERROR(R123/AX123,"-") -> - | AZ123: =IFERROR(AX123/$AM$230,"-") -> - | BB123: =IFERROR(BE123/R123,"-") -> - | BC123: =IFERROR(R123/BE123,"-") -> - | BE123: =BD123*AX123 -> 0 | BF123: =IFERROR(BE123/$AT$230,"-") -> -
G124: 01.02.2026 - 28.02.2026 | H124: CPC | J124: =IFERROR(V124*AH124,"-") -> 0 | L124: =IFERROR((I124*J124),"-") -> 0 | N124: =IFERROR(L124*(1-M124),"-") -> 0 | P124: =IFERROR(Q124-N124,"-") -> 0 | Q124: =IFERROR(N124*(1+O124),"-") -> 0 | R124: =IFERROR(Q124*1.22,"-") -> 0 | S124: =IFERROR(R124-Q124,"-") -> 0 | T124: =IFERROR(R124/$R$230,"-") -> - | X124: =IFERROR(AB124/Y124,"-") -> - | AB124: =SUM(Z124:AA124) -> 0 | AD124: =IFERROR(R124/AB124,"-") -> - | AF124: =IFERROR(#REF!/AE124,"-") -> - | AI124: =IFERROR(ROUNDDOWN(V124*AH124,0),"-") -> 0 | AJ124: =IFERROR(R124/AI124,"-") -> - | AM124: =IFERROR(ROUNDDOWN(AI124*AL124,0),"-") -> 0 | AN124: =IFERROR(R124/AM124,"-") -> - | AO124: =IFERROR(AM124/$AM$230,"-") -> - | AQ124: =IFERROR(AT124/R124,"-") -> - | AR124: =IFERROR(R124/AT124,"-") -> - | AT124: =AS124*AM124 -> 0 | AU124: =IFERROR(AT124/$AT$230,"-") -> - | AX124: =IFERROR(ROUNDDOWN(AM124*AW124,0),"-") -> 0 | AY124: =IFERROR(R124/AX124,"-") -> - | AZ124: =IFERROR(AX124/$AM$230,"-") -> - | BB124: =IFERROR(BE124/R124,"-") -> - | BC124: =IFERROR(R124/BE124,"-") -> - | BE124: =BD124*AX124 -> 0 | BF124: =IFERROR(BE124/$AT$230,"-") -> -
G125: 01.02.2026 - 28.02.2026 | H125: CPC | J125: =IFERROR(V125*AH125,"-") -> 0 | L125: =IFERROR((I125*J125),"-") -> 0 | N125: =IFERROR(L125*(1-M125),"-") -> 0 | P125: =IFERROR(Q125-N125,"-") -> 0 | Q125: =IFERROR(N125*(1+O125),"-") -> 0 | R125: =IFERROR(Q125*1.22,"-") -> 0 | S125: =IFERROR(R125-Q125,"-") -> 0 | T125: =IFERROR(R125/$R$230,"-") -> - | X125: =IFERROR(AB125/Y125,"-") -> - | AB125: =SUM(Z125:AA125) -> 0 | AD125: =IFERROR(R125/AB125,"-") -> - | AF125: =IFERROR(#REF!/AE125,"-") -> - | AI125: =IFERROR(ROUNDDOWN(V125*AH125,0),"-") -> 0 | AJ125: =IFERROR(R125/AI125,"-") -> - | AM125: =IFERROR(ROUNDDOWN(AI125*AL125,0),"-") -> 0 | AN125: =IFERROR(R125/AM125,"-") -> - | AO125: =IFERROR(AM125/$AM$230,"-") -> - | AQ125: =IFERROR(AT125/R125,"-") -> - | AR125: =IFERROR(R125/AT125,"-") -> - | AT125: =AS125*AM125 -> 0 | AU125: =IFERROR(AT125/$AT$230,"-") -> - | AX125: =IFERROR(ROUNDDOWN(AM125*AW125,0),"-") -> 0 | AY125: =IFERROR(R125/AX125,"-") -> - | AZ125: =IFERROR(AX125/$AM$230,"-") -> - | BB125: =IFERROR(BE125/R125,"-") -> - | BC125: =IFERROR(R125/BE125,"-") -> - | BE125: =BD125*AX125 -> 0 | BF125: =IFERROR(BE125/$AT$230,"-") -> -
G126: 01.02.2026 - 28.02.2026 | H126: CPC | J126: =IFERROR(V126*AH126,"-") -> 0 | L126: =IFERROR((I126*J126),"-") -> 0 | N126: =IFERROR(L126*(1-M126),"-") -> 0 | P126: =IFERROR(Q126-N126,"-") -> 0 | Q126: =IFERROR(N126*(1+O126),"-") -> 0 | R126: =IFERROR(Q126*1.22,"-") -> 0 | S126: =IFERROR(R126-Q126,"-") -> 0 | T126: =IFERROR(R126/$R$230,"-") -> - | X126: =IFERROR(AB126/Y126,"-") -> - | AB126: =SUM(Z126:AA126) -> 0 | AD126: =IFERROR(R126/AB126,"-") -> - | AF126: =IFERROR(#REF!/AE126,"-") -> - | AI126: =IFERROR(ROUNDDOWN(V126*AH126,0),"-") -> 0 | AJ126: =IFERROR(R126/AI126,"-") -> - | AM126: =IFERROR(ROUNDDOWN(AI126*AL126,0),"-") -> 0 | AN126: =IFERROR(R126/AM126,"-") -> - | AO126: =IFERROR(AM126/$AM$230,"-") -> - | AQ126: =IFERROR(AT126/R126,"-") -> - | AR126: =IFERROR(R126/AT126,"-") -> - | AT126: =AS126*AM126 -> 0 | AU126: =IFERROR(AT126/$AT$230,"-") -> - | AX126: =IFERROR(ROUNDDOWN(AM126*AW126,0),"-") -> 0 | AY126: =IFERROR(R126/AX126,"-") -> - | AZ126: =IFERROR(AX126/$AM$230,"-") -> - | BB126: =IFERROR(BE126/R126,"-") -> - | BC126: =IFERROR(R126/BE126,"-") -> - | BE126: =BD126*AX126 -> 0 | BF126: =IFERROR(BE126/$AT$230,"-") -> -
G127: 01.02.2026 - 28.02.2026 | H127: CPC | J127: =IFERROR(V127*AH127,"-") -> 0 | L127: =IFERROR((I127*J127),"-") -> 0 | N127: =IFERROR(L127*(1-M127),"-") -> 0 | P127: =IFERROR(Q127-N127,"-") -> 0 | Q127: =IFERROR(N127*(1+O127),"-") -> 0 | R127: =IFERROR(Q127*1.22,"-") -> 0 | S127: =IFERROR(R127-Q127,"-") -> 0 | T127: =IFERROR(R127/$R$230,"-") -> - | X127: =IFERROR(AB127/Y127,"-") -> - | AB127: =SUM(Z127:AA127) -> 0 | AD127: =IFERROR(R127/AB127,"-") -> - | AF127: =IFERROR(#REF!/AE127,"-") -> - | AI127: =IFERROR(ROUNDDOWN(V127*AH127,0),"-") -> 0 | AJ127: =IFERROR(R127/AI127,"-") -> - | AM127: =IFERROR(ROUNDDOWN(AI127*AL127,0),"-") -> 0 | AN127: =IFERROR(R127/AM127,"-") -> - | AO127: =IFERROR(AM127/$AM$230,"-") -> - | AQ127: =IFERROR(AT127/R127,"-") -> - | AR127: =IFERROR(R127/AT127,"-") -> - | AT127: =AS127*AM127 -> 0 | AU127: =IFERROR(AT127/$AT$230,"-") -> - | AX127: =IFERROR(ROUNDDOWN(AM127*AW127,0),"-") -> 0 | AY127: =IFERROR(R127/AX127,"-") -> - | AZ127: =IFERROR(AX127/$AM$230,"-") -> - | BB127: =IFERROR(BE127/R127,"-") -> - | BC127: =IFERROR(R127/BE127,"-") -> - | BE127: =BD127*AX127 -> 0 | BF127: =IFERROR(BE127/$AT$230,"-") -> -
G128: 01.02.2026 - 28.02.2026 | H128: CPC | J128: =IFERROR(V128*AH128,"-") -> 0 | L128: =IFERROR((I128*J128),"-") -> 0 | N128: =IFERROR(L128*(1-M128),"-") -> 0 | P128: =IFERROR(Q128-N128,"-") -> 0 | Q128: =IFERROR(N128*(1+O128),"-") -> 0 | R128: =IFERROR(Q128*1.22,"-") -> 0 | S128: =IFERROR(R128-Q128,"-") -> 0 | T128: =IFERROR(R128/$R$230,"-") -> - | X128: =IFERROR(AB128/Y128,"-") -> - | AB128: =SUM(Z128:AA128) -> 0 | AD128: =IFERROR(R128/AB128,"-") -> - | AF128: =IFERROR(#REF!/AE128,"-") -> - | AI128: =IFERROR(ROUNDDOWN(V128*AH128,0),"-") -> 0 | AJ128: =IFERROR(R128/AI128,"-") -> - | AM128: =IFERROR(ROUNDDOWN(AI128*AL128,0),"-") -> 0 | AN128: =IFERROR(R128/AM128,"-") -> - | AO128: =IFERROR(AM128/$AM$230,"-") -> - | AQ128: =IFERROR(AT128/R128,"-") -> - | AR128: =IFERROR(R128/AT128,"-") -> - | AT128: =AS128*AM128 -> 0 | AU128: =IFERROR(AT128/$AT$230,"-") -> - | AX128: =IFERROR(ROUNDDOWN(AM128*AW128,0),"-") -> 0 | AY128: =IFERROR(R128/AX128,"-") -> - | AZ128: =IFERROR(AX128/$AM$230,"-") -> - | BB128: =IFERROR(BE128/R128,"-") -> - | BC128: =IFERROR(R128/BE128,"-") -> - | BE128: =BD128*AX128 -> 0 | BF128: =IFERROR(BE128/$AT$230,"-") -> -
G129: 01.02.2026 - 28.02.2026 | H129: CPC | J129: =IFERROR(V129*AH129,"-") -> 0 | L129: =IFERROR((I129*J129),"-") -> 0 | N129: =IFERROR(L129*(1-M129),"-") -> 0 | P129: =IFERROR(Q129-N129,"-") -> 0 | Q129: =IFERROR(N129*(1+O129),"-") -> 0 | R129: =IFERROR(Q129*1.22,"-") -> 0 | S129: =IFERROR(R129-Q129,"-") -> 0 | T129: =IFERROR(R129/$R$230,"-") -> - | X129: =IFERROR(AB129/Y129,"-") -> - | AB129: =SUM(Z129:AA129) -> 0 | AD129: =IFERROR(R129/AB129,"-") -> - | AF129: =IFERROR(#REF!/AE129,"-") -> - | AI129: =IFERROR(ROUNDDOWN(V129*AH129,0),"-") -> 0 | AJ129: =IFERROR(R129/AI129,"-") -> - | AM129: =IFERROR(ROUNDDOWN(AI129*AL129,0),"-") -> 0 | AN129: =IFERROR(R129/AM129,"-") -> - | AO129: =IFERROR(AM129/$AM$230,"-") -> - | AQ129: =IFERROR(AT129/R129,"-") -> - | AR129: =IFERROR(R129/AT129,"-") -> - | AT129: =AS129*AM129 -> 0 | AU129: =IFERROR(AT129/$AT$230,"-") -> - | AX129: =IFERROR(ROUNDDOWN(AM129*AW129,0),"-") -> 0 | AY129: =IFERROR(R129/AX129,"-") -> - | AZ129: =IFERROR(AX129/$AM$230,"-") -> - | BB129: =IFERROR(BE129/R129,"-") -> - | BC129: =IFERROR(R129/BE129,"-") -> - | BE129: =BD129*AX129 -> 0 | BF129: =IFERROR(BE129/$AT$230,"-") -> -
... G172: 01.02.2026 - 28.02.2026 | H172: CPC | J172: =IFERROR(V172*AH172,"-") -> 0 | L172: =IFERROR((I172*J172),"-") -> 0 | N172: =IFERROR(L172*(1-M172),"-") -> 0 | P172: =IFERROR(Q172-N172,"-") -> 0 | Q172: =IFERROR(N172*(1+O172),"-") -> 0 | R172: =IFERROR(Q172*1.22,"-") -> 0 | S172: =IFERROR(R172-Q172,"-") -> 0 | T172: =IFERROR(R172/$R$230,"-") -> - | X172: =IFERROR(AB172/Y172,"-") -> - | AB172: =SUM(Z172:AA172) -> 0 | AD172: =IFERROR(R172/AB172,"-") -> - | AF172: =IFERROR(#REF!/AE172,"-") -> - | AI172: =IFERROR(ROUNDDOWN(V172*AH172,0),"-") -> 0 | AJ172: =IFERROR(R172/AI172,"-") -> - | AM172: =IFERROR(ROUNDDOWN(AI172*AL172,0),"-") -> 0 | AN172: =IFERROR(R172/AM172,"-") -> - | AO172: =IFERROR(AM172/$AM$230,"-") -> - | AQ172: =IFERROR(AT172/R172,"-") -> - | AR172: =IFERROR(R172/AT172,"-") -> - | AT172: =AS172*AM172 -> 0 | AU172: =IFERROR(AT172/$AT$230,"-") -> - | AX172: =IFERROR(ROUNDDOWN(AM172*AW172,0),"-") -> 0 | AY172: =IFERROR(R172/AX172,"-") -> - | AZ172: =IFERROR(AX172/$AM$230,"-") -> - | BB172: =IFERROR(BE172/R172,"-") -> - | BC172: =IFERROR(R172/BE172,"-") -> - | BE172: =BD172*AX172 -> 0 | BF172: =IFERROR(BE172/$AT$230,"-") -> -
B173: ИТОГО B2C | C173: - | D173: - | G173: - | H173: - | I173: =IFERROR(L173/J173,"-") -> - | J173: =SUM(J118:J172) -> 0 | L173: =IFERROR(SUM(L118:L172),"-") -> 0 | M173: - | N173: =IFERROR(SUM(N118:N172),"-") -> 0 | O173: - | P173: =IFERROR(Q173-N173,"-") -> 0 | Q173: =IFERROR(SUM(Q118:Q172),"-") -> 0 | R173: =IFERROR(SUM(R118:R172),"-") -> 0 | S173: =IFERROR(R173-Q173,"-") -> 0 | T173: =SUM(T118:T172) -> 0 | V173: =SUM(V118:V172) -> 0 | W173: - | X173: - | Y173: =SUM(Y118:Y172) -> 0 | Z173: =SUM(Z118:Z172) -> 0 | AA173: =SUM(AA118:AA172) -> 0 | AB173: =SUM(AB118:AB172) -> 0 | AD173: =IFERROR(R173/AB173,"-") -> - | AE173: - | AF173: - | AH173: =IFERROR(AI173/V173,"-") -> - | AI173: =SUM(AI118:AI172) -> 0 | AJ173: =IFERROR(R173/AI173,"-") -> - | AL173: =IFERROR(AM173/AI173,"-") -> - | AM173: =SUM(AM118:AM172) -> 0 | AN173: =IFERROR(R173/AM173,"-") -> - | AO173: =SUM(AO118:AO172) -> 0 | AQ173: =IFERROR(AT173/R173,"-") -> - | AR173: =IFERROR(R173/AT173,"-") -> - | AS173: =IFERROR(AT173/AM173,"-") -> - | AT173: =IFERROR(SUM(AT118:AT172),"-") -> 0 | AU173: =SUM(AU118:AU172) -> 0 | AW173: =IFERROR(AX173/AM173,"-") -> - | AX173: =SUM(AX118:AX172) -> 0 | AY173: =IFERROR(R173/AX173,"-") -> - | AZ173: =SUM(AZ118:AZ172) -> 0 | BB173: =IFERROR(BE173/R173,"-") -> - | BC173: =IFERROR(R173/BE173,"-") -> - | BD173: =IFERROR(BE173/AX173,"-") -> - | BE173: =SUM(BE118:BE172) -> 0 | BF173: =SUM(BF118:BF172) -> 0
G174: 01.02.2026 - 28.02.2026 | H174: CPC | J174: =IFERROR(V174*AH174,"-") -> 0 | L174: =IFERROR((I174*J174),"-") -> 0 | N174: =IFERROR(L174*(1-M174),"-") -> 0 | P174: =IFERROR(Q174-N174,"-") -> 0 | Q174: =IFERROR(N174*(1+O174),"-") -> 0 | R174: =IFERROR(Q174*1.22,"-") -> 0 | S174: =IFERROR(R174-Q174,"-") -> 0 | T174: =IFERROR(R174/$R$230,"-") -> - | X174: =IFERROR(AB174/Y174,"-") -> - | AB174: =SUM(Z174:AA174) -> 0 | AD174: =IFERROR(R174/AB174,"-") -> - | AF174: =IFERROR(#REF!/AE174,"-") -> - | AI174: =IFERROR(ROUNDDOWN(V174*AH174,0),"-") -> 0 | AJ174: =IFERROR(R174/AI174,"-") -> - | AM174: =IFERROR(ROUNDDOWN(AI174*AL174,0),"-") -> 0 | AN174: =IFERROR(R174/AM174,"-") -> - | AO174: =IFERROR(AM174/$AM$230,"-") -> - | AQ174: =IFERROR(AT174/R174,"-") -> - | AR174: =IFERROR(R174/AT174,"-") -> - | AT174: =AS174*AM174 -> 0 | AU174: =IFERROR(AT174/$AT$230,"-") -> - | AX174: =IFERROR(ROUNDDOWN(AM174*AW174,0),"-") -> 0 | AY174: =IFERROR(R174/AX174,"-") -> - | AZ174: =IFERROR(AX174/$AM$230,"-") -> - | BB174: =IFERROR(BE174/R174,"-") -> - | BC174: =IFERROR(R174/BE174,"-") -> - | BE174: =BD174*AX174 -> 0 | BF174: =IFERROR(BE174/$AT$230,"-") -> -
G175: 01.02.2026 - 28.02.2026 | H175: CPC | J175: =IFERROR(V175*AH175,"-") -> 0 | L175: =IFERROR((I175*J175),"-") -> 0 | N175: =IFERROR(L175*(1-M175),"-") -> 0 | P175: =IFERROR(Q175-N175,"-") -> 0 | Q175: =IFERROR(N175*(1+O175),"-") -> 0 | R175: =IFERROR(Q175*1.22,"-") -> 0 | S175: =IFERROR(R175-Q175,"-") -> 0 | T175: =IFERROR(R175/$R$230,"-") -> - | X175: =IFERROR(AB175/Y175,"-") -> - | AB175: =SUM(Z175:AA175) -> 0 | AD175: =IFERROR(R175/AB175,"-") -> - | AF175: =IFERROR(#REF!/AE175,"-") -> - | AI175: =IFERROR(ROUNDDOWN(V175*AH175,0),"-") -> 0 | AJ175: =IFERROR(R175/AI175,"-") -> - | AM175: =IFERROR(ROUNDDOWN(AI175*AL175,0),"-") -> 0 | AN175: =IFERROR(R175/AM175,"-") -> - | AO175: =IFERROR(AM175/$AM$230,"-") -> - | AQ175: =IFERROR(AT175/R175,"-") -> - | AR175: =IFERROR(R175/AT175,"-") -> - | AT175: =AS175*AM175 -> 0 | AU175: =IFERROR(AT175/$AT$230,"-") -> - | AX175: =IFERROR(ROUNDDOWN(AM175*AW175,0),"-") -> 0 | AY175: =IFERROR(R175/AX175,"-") -> - | AZ175: =IFERROR(AX175/$AM$230,"-") -> - | BB175: =IFERROR(BE175/R175,"-") -> - | BC175: =IFERROR(R175/BE175,"-") -> - | BE175: =BD175*AX175 -> 0 | BF175: =IFERROR(BE175/$AT$230,"-") -> -
G176: 01.02.2026 - 28.02.2026 | H176: CPC | J176: =IFERROR(V176*AH176,"-") -> 0 | L176: =IFERROR((I176*J176),"-") -> 0 | N176: =IFERROR(L176*(1-M176),"-") -> 0 | P176: =IFERROR(Q176-N176,"-") -> 0 | Q176: =IFERROR(N176*(1+O176),"-") -> 0 | R176: =IFERROR(Q176*1.22,"-") -> 0 | S176: =IFERROR(R176-Q176,"-") -> 0 | T176: =IFERROR(R176/$R$230,"-") -> - | X176: =IFERROR(AB176/Y176,"-") -> - | AB176: =SUM(Z176:AA176) -> 0 | AD176: =IFERROR(R176/AB176,"-") -> - | AF176: =IFERROR(#REF!/AE176,"-") -> - | AI176: =IFERROR(ROUNDDOWN(V176*AH176,0),"-") -> 0 | AJ176: =IFERROR(R176/AI176,"-") -> - | AM176: =IFERROR(ROUNDDOWN(AI176*AL176,0),"-") -> 0 | AN176: =IFERROR(R176/AM176,"-") -> - | AO176: =IFERROR(AM176/$AM$230,"-") -> - | AQ176: =IFERROR(AT176/R176,"-") -> - | AR176: =IFERROR(R176/AT176,"-") -> - | AT176: =AS176*AM176 -> 0 | AU176: =IFERROR(AT176/$AT$230,"-") -> - | AX176: =IFERROR(ROUNDDOWN(AM176*AW176,0),"-") -> 0 | AY176: =IFERROR(R176/AX176,"-") -> - | AZ176: =IFERROR(AX176/$AM$230,"-") -> - | BB176: =IFERROR(BE176/R176,"-") -> - | BC176: =IFERROR(R176/BE176,"-") -> - | BE176: =BD176*AX176 -> 0 | BF176: =IFERROR(BE176/$AT$230,"-") -> -
G177: 01.02.2026 - 28.02.2026 | H177: CPC | J177: =IFERROR(V177*AH177,"-") -> 0 | L177: =IFERROR((I177*J177),"-") -> 0 | N177: =IFERROR(L177*(1-M177),"-") -> 0 | P177: =IFERROR(Q177-N177,"-") -> 0 | Q177: =IFERROR(N177*(1+O177),"-") -> 0 | R177: =IFERROR(Q177*1.22,"-") -> 0 | S177: =IFERROR(R177-Q177,"-") -> 0 | T177: =IFERROR(R177/$R$230,"-") -> - | X177: =IFERROR(AB177/Y177,"-") -> - | AB177: =SUM(Z177:AA177) -> 0 | AD177: =IFERROR(R177/AB177,"-") -> - | AF177: =IFERROR(#REF!/AE177,"-") -> - | AI177: =IFERROR(ROUNDDOWN(V177*AH177,0),"-") -> 0 | AJ177: =IFERROR(R177/AI177,"-") -> - | AM177: =IFERROR(ROUNDDOWN(AI177*AL177,0),"-") -> 0 | AN177: =IFERROR(R177/AM177,"-") -> - | AO177: =IFERROR(AM177/$AM$230,"-") -> - | AQ177: =IFERROR(AT177/R177,"-") -> - | AR177: =IFERROR(R177/AT177,"-") -> - | AT177: =AS177*AM177 -> 0 | AU177: =IFERROR(AT177/$AT$230,"-") -> - | AX177: =IFERROR(ROUNDDOWN(AM177*AW177,0),"-") -> 0 | AY177: =IFERROR(R177/AX177,"-") -> - | AZ177: =IFERROR(AX177/$AM$230,"-") -> - | BB177: =IFERROR(BE177/R177,"-") -> - | BC177: =IFERROR(R177/BE177,"-") -> - | BE177: =BD177*AX177 -> 0 | BF177: =IFERROR(BE177/$AT$230,"-") -> -
G178: 01.02.2026 - 28.02.2026 | H178: CPC | J178: =IFERROR(V178*AH178,"-") -> 0 | L178: =IFERROR((I178*J178),"-") -> 0 | N178: =IFERROR(L178*(1-M178),"-") -> 0 | P178: =IFERROR(Q178-N178,"-") -> 0 | Q178: =IFERROR(N178*(1+O178),"-") -> 0 | R178: =IFERROR(Q178*1.22,"-") -> 0 | S178: =IFERROR(R178-Q178,"-") -> 0 | T178: =IFERROR(R178/$R$230,"-") -> - | X178: =IFERROR(AB178/Y178,"-") -> - | AB178: =SUM(Z178:AA178) -> 0 | AD178: =IFERROR(R178/AB178,"-") -> - | AF178: =IFERROR(#REF!/AE178,"-") -> - | AI178: =IFERROR(ROUNDDOWN(V178*AH178,0),"-") -> 0 | AJ178: =IFERROR(R178/AI178,"-") -> - | AM178: =IFERROR(ROUNDDOWN(AI178*AL178,0),"-") -> 0 | AN178: =IFERROR(R178/AM178,"-") -> - | AO178: =IFERROR(AM178/$AM$230,"-") -> - | AQ178: =IFERROR(AT178/R178,"-") -> - | AR178: =IFERROR(R178/AT178,"-") -> - | AT178: =AS178*AM178 -> 0 | AU178: =IFERROR(AT178/$AT$230,"-") -> - | AX178: =IFERROR(ROUNDDOWN(AM178*AW178,0),"-") -> 0 | AY178: =IFERROR(R178/AX178,"-") -> - | AZ178: =IFERROR(AX178/$AM$230,"-") -> - | BB178: =IFERROR(BE178/R178,"-") -> - | BC178: =IFERROR(R178/BE178,"-") -> - | BE178: =BD178*AX178 -> 0 | BF178: =IFERROR(BE178/$AT$230,"-") -> -
G179: 01.02.2026 - 28.02.2026 | H179: CPC | J179: =IFERROR(V179*AH179,"-") -> 0 | L179: =IFERROR((I179*J179),"-") -> 0 | N179: =IFERROR(L179*(1-M179),"-") -> 0 | P179: =IFERROR(Q179-N179,"-") -> 0 | Q179: =IFERROR(N179*(1+O179),"-") -> 0 | R179: =IFERROR(Q179*1.22,"-") -> 0 | S179: =IFERROR(R179-Q179,"-") -> 0 | T179: =IFERROR(R179/$R$230,"-") -> - | X179: =IFERROR(AB179/Y179,"-") -> - | AB179: =SUM(Z179:AA179) -> 0 | AD179: =IFERROR(R179/AB179,"-") -> - | AF179: =IFERROR(#REF!/AE179,"-") -> - | AI179: =IFERROR(ROUNDDOWN(V179*AH179,0),"-") -> 0 | AJ179: =IFERROR(R179/AI179,"-") -> - | AM179: =IFERROR(ROUNDDOWN(AI179*AL179,0),"-") -> 0 | AN179: =IFERROR(R179/AM179,"-") -> - | AO179: =IFERROR(AM179/$AM$230,"-") -> - | AQ179: =IFERROR(AT179/R179,"-") -> - | AR179: =IFERROR(R179/AT179,"-") -> - | AT179: =AS179*AM179 -> 0 | AU179: =IFERROR(AT179/$AT$230,"-") -> - | AX179: =IFERROR(ROUNDDOWN(AM179*AW179,0),"-") -> 0 | AY179: =IFERROR(R179/AX179,"-") -> - | AZ179: =IFERROR(AX179/$AM$230,"-") -> - | BB179: =IFERROR(BE179/R179,"-") -> - | BC179: =IFERROR(R179/BE179,"-") -> - | BE179: =BD179*AX179 -> 0 | BF179: =IFERROR(BE179/$AT$230,"-") -> -
G180: 01.02.2026 - 28.02.2026 | H180: CPC | J180: =IFERROR(V180*AH180,"-") -> 0 | L180: =IFERROR((I180*J180),"-") -> 0 | N180: =IFERROR(L180*(1-M180),"-") -> 0 | P180: =IFERROR(Q180-N180,"-") -> 0 | Q180: =IFERROR(N180*(1+O180),"-") -> 0 | R180: =IFERROR(Q180*1.22,"-") -> 0 | S180: =IFERROR(R180-Q180,"-") -> 0 | T180: =IFERROR(R180/$R$230,"-") -> - | X180: =IFERROR(AB180/Y180,"-") -> - | AB180: =SUM(Z180:AA180) -> 0 | AD180: =IFERROR(R180/AB180,"-") -> - | AF180: =IFERROR(#REF!/AE180,"-") -> - | AI180: =IFERROR(ROUNDDOWN(V180*AH180,0),"-") -> 0 | AJ180: =IFERROR(R180/AI180,"-") -> - | AM180: =IFERROR(ROUNDDOWN(AI180*AL180,0),"-") -> 0 | AN180: =IFERROR(R180/AM180,"-") -> - | AO180: =IFERROR(AM180/$AM$230,"-") -> - | AQ180: =IFERROR(AT180/R180,"-") -> - | AR180: =IFERROR(R180/AT180,"-") -> - | AT180: =AS180*AM180 -> 0 | AU180: =IFERROR(AT180/$AT$230,"-") -> - | AX180: =IFERROR(ROUNDDOWN(AM180*AW180,0),"-") -> 0 | AY180: =IFERROR(R180/AX180,"-") -> - | AZ180: =IFERROR(AX180/$AM$230,"-") -> - | BB180: =IFERROR(BE180/R180,"-") -> - | BC180: =IFERROR(R180/BE180,"-") -> - | BE180: =BD180*AX180 -> 0 | BF180: =IFERROR(BE180/$AT$230,"-") -> -
G181: 01.02.2026 - 28.02.2026 | H181: CPC | J181: =IFERROR(V181*AH181,"-") -> 0 | L181: =IFERROR((I181*J181),"-") -> 0 | N181: =IFERROR(L181*(1-M181),"-") -> 0 | P181: =IFERROR(Q181-N181,"-") -> 0 | Q181: =IFERROR(N181*(1+O181),"-") -> 0 | R181: =IFERROR(Q181*1.22,"-") -> 0 | S181: =IFERROR(R181-Q181,"-") -> 0 | T181: =IFERROR(R181/$R$230,"-") -> - | X181: =IFERROR(AB181/Y181,"-") -> - | AB181: =SUM(Z181:AA181) -> 0 | AD181: =IFERROR(R181/AB181,"-") -> - | AF181: =IFERROR(#REF!/AE181,"-") -> - | AI181: =IFERROR(ROUNDDOWN(V181*AH181,0),"-") -> 0 | AJ181: =IFERROR(R181/AI181,"-") -> - | AM181: =IFERROR(ROUNDDOWN(AI181*AL181,0),"-") -> 0 | AN181: =IFERROR(R181/AM181,"-") -> - | AO181: =IFERROR(AM181/$AM$230,"-") -> - | AQ181: =IFERROR(AT181/R181,"-") -> - | AR181: =IFERROR(R181/AT181,"-") -> - | AT181: =AS181*AM181 -> 0 | AU181: =IFERROR(AT181/$AT$230,"-") -> - | AX181: =IFERROR(ROUNDDOWN(AM181*AW181,0),"-") -> 0 | AY181: =IFERROR(R181/AX181,"-") -> - | AZ181: =IFERROR(AX181/$AM$230,"-") -> - | BB181: =IFERROR(BE181/R181,"-") -> - | BC181: =IFERROR(R181/BE181,"-") -> - | BE181: =BD181*AX181 -> 0 | BF181: =IFERROR(BE181/$AT$230,"-") -> -
G182: 01.02.2026 - 28.02.2026 | H182: CPC | J182: =IFERROR(V182*AH182,"-") -> 0 | L182: =IFERROR((I182*J182),"-") -> 0 | N182: =IFERROR(L182*(1-M182),"-") -> 0 | P182: =IFERROR(Q182-N182,"-") -> 0 | Q182: =IFERROR(N182*(1+O182),"-") -> 0 | R182: =IFERROR(Q182*1.22,"-") -> 0 | S182: =IFERROR(R182-Q182,"-") -> 0 | T182: =IFERROR(R182/$R$230,"-") -> - | X182: =IFERROR(AB182/Y182,"-") -> - | AB182: =SUM(Z182:AA182) -> 0 | AD182: =IFERROR(R182/AB182,"-") -> - | AF182: =IFERROR(#REF!/AE182,"-") -> - | AI182: =IFERROR(ROUNDDOWN(V182*AH182,0),"-") -> 0 | AJ182: =IFERROR(R182/AI182,"-") -> - | AM182: =IFERROR(ROUNDDOWN(AI182*AL182,0),"-") -> 0 | AN182: =IFERROR(R182/AM182,"-") -> - | AO182: =IFERROR(AM182/$AM$230,"-") -> - | AQ182: =IFERROR(AT182/R182,"-") -> - | AR182: =IFERROR(R182/AT182,"-") -> - | AT182: =AS182*AM182 -> 0 | AU182: =IFERROR(AT182/$AT$230,"-") -> - | AX182: =IFERROR(ROUNDDOWN(AM182*AW182,0),"-") -> 0 | AY182: =IFERROR(R182/AX182,"-") -> - | AZ182: =IFERROR(AX182/$AM$230,"-") -> - | BB182: =IFERROR(BE182/R182,"-") -> - | BC182: =IFERROR(R182/BE182,"-") -> - | BE182: =BD182*AX182 -> 0 | BF182: =IFERROR(BE182/$AT$230,"-") -> -
G183: 01.02.2026 - 28.02.2026 | H183: CPC | J183: =IFERROR(V183*AH183,"-") -> 0 | L183: =IFERROR((I183*J183),"-") -> 0 | N183: =IFERROR(L183*(1-M183),"-") -> 0 | P183: =IFERROR(Q183-N183,"-") -> 0 | Q183: =IFERROR(N183*(1+O183),"-") -> 0 | R183: =IFERROR(Q183*1.22,"-") -> 0 | S183: =IFERROR(R183-Q183,"-") -> 0 | T183: =IFERROR(R183/$R$230,"-") -> - | X183: =IFERROR(AB183/Y183,"-") -> - | AB183: =SUM(Z183:AA183) -> 0 | AD183: =IFERROR(R183/AB183,"-") -> - | AF183: =IFERROR(#REF!/AE183,"-") -> - | AI183: =IFERROR(ROUNDDOWN(V183*AH183,0),"-") -> 0 | AJ183: =IFERROR(R183/AI183,"-") -> - | AM183: =IFERROR(ROUNDDOWN(AI183*AL183,0),"-") -> 0 | AN183: =IFERROR(R183/AM183,"-") -> - | AO183: =IFERROR(AM183/$AM$230,"-") -> - | AQ183: =IFERROR(AT183/R183,"-") -> - | AR183: =IFERROR(R183/AT183,"-") -> - | AT183: =AS183*AM183 -> 0 | AU183: =IFERROR(AT183/$AT$230,"-") -> - | AX183: =IFERROR(ROUNDDOWN(AM183*AW183,0),"-") -> 0 | AY183: =IFERROR(R183/AX183,"-") -> - | AZ183: =IFERROR(AX183/$AM$230,"-") -> - | BB183: =IFERROR(BE183/R183,"-") -> - | BC183: =IFERROR(R183/BE183,"-") -> - | BE183: =BD183*AX183 -> 0 | BF183: =IFERROR(BE183/$AT$230,"-") -> -
G184: 01.02.2026 - 28.02.2026 | H184: CPC | J184: =IFERROR(V184*AH184,"-") -> 0 | L184: =IFERROR((I184*J184),"-") -> 0 | N184: =IFERROR(L184*(1-M184),"-") -> 0 | P184: =IFERROR(Q184-N184,"-") -> 0 | Q184: =IFERROR(N184*(1+O184),"-") -> 0 | R184: =IFERROR(Q184*1.22,"-") -> 0 | S184: =IFERROR(R184-Q184,"-") -> 0 | T184: =IFERROR(R184/$R$230,"-") -> - | X184: =IFERROR(AB184/Y184,"-") -> - | AB184: =SUM(Z184:AA184) -> 0 | AD184: =IFERROR(R184/AB184,"-") -> - | AF184: =IFERROR(#REF!/AE184,"-") -> - | AI184: =IFERROR(ROUNDDOWN(V184*AH184,0),"-") -> 0 | AJ184: =IFERROR(R184/AI184,"-") -> - | AM184: =IFERROR(ROUNDDOWN(AI184*AL184,0),"-") -> 0 | AN184: =IFERROR(R184/AM184,"-") -> - | AO184: =IFERROR(AM184/$AM$230,"-") -> - | AQ184: =IFERROR(AT184/R184,"-") -> - | AR184: =IFERROR(R184/AT184,"-") -> - | AT184: =AS184*AM184 -> 0 | AU184: =IFERROR(AT184/$AT$230,"-") -> - | AX184: =IFERROR(ROUNDDOWN(AM184*AW184,0),"-") -> 0 | AY184: =IFERROR(R184/AX184,"-") -> - | AZ184: =IFERROR(AX184/$AM$230,"-") -> - | BB184: =IFERROR(BE184/R184,"-") -> - | BC184: =IFERROR(R184/BE184,"-") -> - | BE184: =BD184*AX184 -> 0 | BF184: =IFERROR(BE184/$AT$230,"-") -> -
G185: 01.02.2026 - 28.02.2026 | H185: CPC | J185: =IFERROR(V185*AH185,"-") -> 0 | L185: =IFERROR((I185*J185),"-") -> 0 | N185: =IFERROR(L185*(1-M185),"-") -> 0 | P185: =IFERROR(Q185-N185,"-") -> 0 | Q185: =IFERROR(N185*(1+O185),"-") -> 0 | R185: =IFERROR(Q185*1.22,"-") -> 0 | S185: =IFERROR(R185-Q185,"-") -> 0 | T185: =IFERROR(R185/$R$230,"-") -> - | X185: =IFERROR(AB185/Y185,"-") -> - | AB185: =SUM(Z185:AA185) -> 0 | AD185: =IFERROR(R185/AB185,"-") -> - | AF185: =IFERROR(#REF!/AE185,"-") -> - | AI185: =IFERROR(ROUNDDOWN(V185*AH185,0),"-") -> 0 | AJ185: =IFERROR(R185/AI185,"-") -> - | AM185: =IFERROR(ROUNDDOWN(AI185*AL185,0),"-") -> 0 | AN185: =IFERROR(R185/AM185,"-") -> - | AO185: =IFERROR(AM185/$AM$230,"-") -> - | AQ185: =IFERROR(AT185/R185,"-") -> - | AR185: =IFERROR(R185/AT185,"-") -> - | AT185: =AS185*AM185 -> 0 | AU185: =IFERROR(AT185/$AT$230,"-") -> - | AX185: =IFERROR(ROUNDDOWN(AM185*AW185,0),"-") -> 0 | AY185: =IFERROR(R185/AX185,"-") -> - | AZ185: =IFERROR(AX185/$AM$230,"-") -> - | BB185: =IFERROR(BE185/R185,"-") -> - | BC185: =IFERROR(R185/BE185,"-") -> - | BE185: =BD185*AX185 -> 0 | BF185: =IFERROR(BE185/$AT$230,"-") -> -
... G228: 01.02.2026 - 28.02.2026 | H228: CPC | J228: =IFERROR(V228*AH228,"-") -> 0 | L228: =IFERROR((I228*J228),"-") -> 0 | N228: =IFERROR(L228*(1-M228),"-") -> 0 | P228: =IFERROR(Q228-N228,"-") -> 0 | Q228: =IFERROR(N228*(1+O228),"-") -> 0 | R228: =IFERROR(Q228*1.22,"-") -> 0 | S228: =IFERROR(R228-Q228,"-") -> 0 | T228: =IFERROR(R228/$R$230,"-") -> - | X228: =IFERROR(AB228/Y228,"-") -> - | AB228: =SUM(Z228:AA228) -> 0 | AD228: =IFERROR(R228/AB228,"-") -> - | AF228: =IFERROR(#REF!/AE228,"-") -> - | AI228: =IFERROR(ROUNDDOWN(V228*AH228,0),"-") -> 0 | AJ228: =IFERROR(R228/AI228,"-") -> - | AM228: =IFERROR(ROUNDDOWN(AI228*AL228,0),"-") -> 0 | AN228: =IFERROR(R228/AM228,"-") -> - | AO228: =IFERROR(AM228/$AM$230,"-") -> - | AQ228: =IFERROR(AT228/R228,"-") -> - | AR228: =IFERROR(R228/AT228,"-") -> - | AT228: =AS228*AM228 -> 0 | AU228: =IFERROR(AT228/$AT$230,"-") -> - | AX228: =IFERROR(ROUNDDOWN(AM228*AW228,0),"-") -> 0 | AY228: =IFERROR(R228/AX228,"-") -> - | AZ228: =IFERROR(AX228/$AM$230,"-") -> - | BB228: =IFERROR(BE228/R228,"-") -> - | BC228: =IFERROR(R228/BE228,"-") -> - | BE228: =BD228*AX228 -> 0 | BF228: =IFERROR(BE228/$AT$230,"-") -> -
B229: ИТОГО B2B | C229: - | D229: - | G229: - | H229: - | I229: =IFERROR(L229/J229,"-") -> - | J229: =SUM(J174:J228) -> 0 | L229: =IFERROR(SUM(L174:L228),"-") -> 0 | M229: - | N229: =IFERROR(SUM(N174:N228),"-") -> 0 | O229: - | P229: =IFERROR(Q229-N229,"-") -> 0 | Q229: =IFERROR(SUM(Q174:Q228),"-") -> 0 | R229: =IFERROR(SUM(R174:R228),"-") -> 0 | S229: =IFERROR(R229-Q229,"-") -> 0 | T229: =SUM(T174:T228) -> 0 | V229: =SUM(V174:V228) -> 0 | W229: - | X229: - | Y229: =SUM(Y174:Y228) -> 0 | Z229: =SUM(Z174:Z228) -> 0 | AA229: =SUM(AA174:AA228) -> 0 | AB229: =SUM(AB174:AB228) -> 0 | AD229: =IFERROR(R229/AB229,"-") -> - | AE229: - | AF229: - | AH229: =IFERROR(AI229/V229,"-") -> - | AI229: =SUM(AI174:AI228) -> 0 | AJ229: =IFERROR(R229/AI229,"-") -> - | AL229: =IFERROR(AM229/AI229,"-") -> - | AM229: =SUM(AM174:AM228) -> 0 | AN229: =IFERROR(R229/AM229,"-") -> - | AO229: =SUM(AO174:AO228) -> 0 | AQ229: =IFERROR(AT229/R229,"-") -> - | AR229: =IFERROR(R229/AT229,"-") -> - | AS229: =IFERROR(AT229/AM229,"-") -> - | AT229: =IFERROR(SUM(AT174:AT228),"-") -> 0 | AU229: =SUM(AU174:AU228) -> 0 | AW229: =IFERROR(AX229/AM229,"-") -> - | AX229: =SUM(AX174:AX228) -> 0 | AY229: =IFERROR(R229/AX229,"-") -> - | AZ229: =SUM(AZ174:AZ228) -> 0 | BB229: =IFERROR(BE229/R229,"-") -> - | BC229: =IFERROR(R229/BE229,"-") -> - | BD229: =IFERROR(BE229/AX229,"-") -> - | BE229: =SUM(BE174:BE228) -> 0 | BF229: =SUM(BF174:BF228) -> 0
B230: Итого | C230: - | D230: - | G230: - | H230: - | I230: =IFERROR(L230/J230,"-") -> - | J230: =J229+J173 -> 0 | L230: =IFERROR(SUM(L229,L173),"-") -> 0 | M230: - | N230: =IFERROR(SUM(N229,N173),"-") -> 0 | O230: - | P230: =IFERROR(Q230-N230,"-") -> 0 | Q230: =IFERROR(SUM(Q229,Q173),"-") -> 0 | R230: =IFERROR(SUM(R229,R173),"-") -> 0 | S230: =IFERROR(R230-Q230,"-") -> 0 | T230: =SUM(T173,T229) -> 0 | V230: =V229+V173 -> 0 | W230: - | X230: - | Y230: =SUM(Y229,Y173) -> 0 | Z230: =SUM(Z229,Z173) -> 0 | AA230: =SUM(AA229,AA173) -> 0 | AB230: =SUM(AB229,AB173) -> 0 | AD230: =IFERROR(R230/AB230,"-") -> - | AE230: - | AF230: - | AH230: =IFERROR(AI230/V230,"-") -> - | AI230: =AI229+AI173 -> 0 | AJ230: =IFERROR(R230/AI230,"-") -> - | AL230: =IFERROR(AM230/AI230,"-") -> - | AM230: =AM229+AM173 -> 0 | AN230: =IFERROR(R230/AM230,"-") -> - | AO230: =SUM(AO173,AO229) -> 0 | AQ230: =IFERROR(AT230/R230,"-") -> - | AR230: =IFERROR(R230/AT230,"-") -> - | AS230: =IFERROR(AT230/AM230,"-") -> - | AT230: =IFERROR(SUM(AT173,AT229),"-") -> 0 | AU230: =SUM(AU173,AU229) -> 0 | AW230: =IFERROR(AX230/AM230,"-") -> - | AX230: =AX229+AX173 -> 0 | AY230: =IFERROR(R230/AX230,"-") -> - | AZ230: =SUM(AZ173,AZ229) -> 0 | BB230: =IFERROR(BE230/R230,"-") -> - | BC230: =IFERROR(R230/BE230,"-") -> - | BD230: =IFERROR(BE230/AX230,"-") -> - | BE230: =SUM(BE229,BE173) -> 0 | BF230: =SUM(BF173,BF229) -> 0
B232: Рекламная система | C232: Рекламный формат, размер, вид размещения | D232: Таргетинги | E232: ГЕО | G232: Период | H232: Единица измерения стоимости | I232: Цена за единицу (без НДС) | J232: Кол-во единиц | L232: Стоимость (без НДС) | M232: СК, % | N232: Тотал бюджет, руб. без НДС и АК | O232: АК, % | P232: АК, руб. (без НДС) | Q232: Тотал бюджет, руб. без НДС и с учетом АК | R232: Тотал бюджет руб. с учетом НДС и АК | S232: НДС руб. | T232: Доля рекламного бюджета, % | V232: Кол-во показов | W232: Частота (весь срок) | X232: Доля новых клиентов, % | Y232: Кол-во клиентов | Z232: Кол-во абсолютно новых клиентов (ранее не заказывали) | AA232: Кол-во вернувшихся клиентов (не заказывали более 12 мес) | AB232: Кол-во новых клиентов (абсолютно новые + вернувшиеся) | AC232: Частота заказа | AD232: САС, руб. | AE232: Доступная емкость аудитории | AF232: SOV, % | AH232: CTR, % | AI232: Клики | AJ232: CPC (с НДС) | AL232: CR, % | AM232: Кол-во оформленных заказов | AN232: Стоимость оформл. заказа, руб. с НДС | AO232: Доля заказов, % | AQ232: ROAS офомл. (Доход/Бюджет) | AR232: ДРР от оформл. дохода, % | AS232: Средний чек по оформл. доходу, с НДС | AT232: Оформленный доход, руб. с НДС | AU232: Доля заказов, % | AW232: CR, % | AX232: Кол-во отгруженных заказов | AY232: Стоимость отгр. заказа, руб. с НДС | AZ232: Доля заказов, % | BB232: ROAS отгр. (Выручка/Бюджет) | BC232: ДРР от выручки, % | BD232: Средний чек по выручке, с НДС | BE232: Выручка (отгруженный доход), руб. с НДС | BF232: Доля заказов, %
G233: 01.03.2026 - 31.03.2026 | H233: CPC | J233: =IFERROR(V233*AH233,"-") -> 0 | L233: =IFERROR((I233*J233),"-") -> 0 | N233: =IFERROR(L233*(1-M233),"-") -> 0 | P233: =IFERROR(Q233-N233,"-") -> 0 | Q233: =IFERROR(N233*(1+O233),"-") -> 0 | R233: =IFERROR(Q233*1.22,"-") -> 0 | S233: =IFERROR(R233-Q233,"-") -> 0 | T233: =IFERROR(R233/$R$345,"-") -> - | X233: =IFERROR(AB233/Y233,"-") -> - | AB233: =SUM(Z233:AA233) -> 0 | AD233: =IFERROR(R233/AB233,"-") -> - | AF233: =IFERROR(#REF!/AE233,"-") -> - | AI233: =IFERROR(ROUNDDOWN(V233*AH233,0),"-") -> 0 | AJ233: =IFERROR(R233/AI233,"-") -> - | AM233: =IFERROR(ROUNDDOWN(AI233*AL233,0),"-") -> 0 | AN233: =IFERROR(R233/AM233,"-") -> - | AO233: =IFERROR(AM233/$AM$345,"-") -> - | AQ233: =IFERROR(AT233/R233,"-") -> - | AR233: =IFERROR(R233/AT233,"-") -> - | AT233: =AS233*AM233 -> 0 | AU233: =IFERROR(AT233/$AT$345,"-") -> - | AX233: =IFERROR(ROUNDDOWN(AM233*AW233,0),"-") -> 0 | AY233: =IFERROR(R233/AX233,"-") -> - | AZ233: =IFERROR(AX233/$AM$345,"-") -> - | BB233: =IFERROR(BE233/R233,"-") -> - | BC233: =IFERROR(R233/BE233,"-") -> - | BE233: =BD233*AX233 -> 0 | BF233: =IFERROR(BE233/$AT$345,"-") -> -
